.version 45 3
.class final super c
.super java/lang/Object
.field private static a Z
.field private b Z
.field private c I
.field static d Z
.field static e I
.field static f Z
.field private g I
.field private h I
.field private i [[[I
.field private j [[[B
.field private k [[[B
.field private l [[[B
.field private m [[[B
.field private n [[[B
.field private o [[[B
.field private p [[I
.field private q [I
.field private r [I
.field private s [I
.field private t [I
.field private u [I
.field private v [[[I
.field private static final w [I
.field private static final x [I
.field private static final y [I
.field private static final z [I
.field private static A I
.field private static B I

.method public <init> : (I[[[BI[[[II)V
    .code stack 5 locals 7
L0:     aload_0
L1:     invokespecial Method java/lang/Object <init> ()V
L4:     aload_0
L5:     iconst_1
L6:     putfield Field c b Z
L9:     aload_0
L10:    bipush 8
L12:    putfield Field c c I
        .catch java/lang/RuntimeException from L15 to L229 using L230
L15:    aload_0
L16:    iload_3
L17:    putfield Field c g I
L20:    aload_0
L21:    iload_1
L22:    putfield Field c h I
L25:    aload_0
L26:    aload 4
L28:    putfield Field c i [[[I
L31:    aload_0
L32:    aload_2
L33:    putfield Field c j [[[B
L36:    aload_0
L37:    iconst_4
L38:    aload_0
L39:    getfield Field c g I
L42:    aload_0
L43:    getfield Field c h I
L46:    multianewarray [[[B 3
L50:    putfield Field c k [[[B
L53:    aload_0
L54:    iconst_4
L55:    aload_0
L56:    getfield Field c g I
L59:    aload_0
L60:    getfield Field c h I
L63:    multianewarray [[[B 3
L67:    putfield Field c l [[[B
L70:    aload_0
L71:    iconst_4
L72:    aload_0
L73:    getfield Field c g I
L76:    aload_0
L77:    getfield Field c h I
L80:    multianewarray [[[B 3
L84:    putfield Field c m [[[B
L87:    aload_0
L88:    iconst_4
L89:    aload_0
L90:    getfield Field c g I
L93:    aload_0
L94:    getfield Field c h I
L97:    multianewarray [[[B 3
L101:   putfield Field c n [[[B
L104:   aload_0
L105:   iconst_4
L106:   aload_0
L107:   getfield Field c g I
L110:   iconst_1
L111:   iadd
L112:   aload_0
L113:   getfield Field c h I
L116:   iconst_1
L117:   iadd
L118:   multianewarray [[[I 3
L122:   putfield Field c v [[[I
L125:   aload_0
L126:   iconst_4
L127:   aload_0
L128:   getfield Field c g I
L131:   iconst_1
L132:   iadd
L133:   aload_0
L134:   getfield Field c h I
L137:   iconst_1
L138:   iadd
L139:   multianewarray [[[B 3
L143:   putfield Field c o [[[B
L146:   aload_0
L147:   aload_0
L148:   getfield Field c g I
L151:   iconst_1
L152:   iadd
L153:   aload_0
L154:   getfield Field c h I
L157:   iconst_1
L158:   iadd
L159:   multianewarray [[I 2
L163:   putfield Field c p [[I
L166:   aload_0
L167:   aload_0
L168:   getfield Field c h I
L171:   newarray int
L173:   putfield Field c q [I
L176:   aload_0
L177:   aload_0
L178:   getfield Field c h I
L181:   newarray int
L183:   putfield Field c r [I
L186:   iload 5
L188:   ldc -35388
L190:   if_icmpeq L199
L193:   aload_0
L194:   bipush 28
L196:   putfield Field c c I
L199:   aload_0
L200:   aload_0
L201:   getfield Field c h I
L204:   newarray int
L206:   putfield Field c s [I
L209:   aload_0
L210:   aload_0
L211:   getfield Field c h I
L214:   newarray int
L216:   putfield Field c t [I
L219:   aload_0
L220:   aload_0
L221:   getfield Field c h I
L224:   newarray int
L226:   putfield Field c u [I
L229:   return
L230:   astore 6
L232:   new java/lang/StringBuffer
L235:   dup
L236:   ldc "87235, "
L238:   invokespecial Method java/lang/StringBuffer <init> (Ljava/lang/String;)V
L241:   iload_1
L242:   invokevirtual Method java/lang/StringBuffer append (I)Ljava/lang/StringBuffer;
L245:   ldc ", "
L247:   invokevirtual Method java/lang/StringBuffer append (Ljava/lang/String;)Ljava/lang/StringBuffer;
L250:   aload_2
L251:   invokevirtual Method java/lang/StringBuffer append (Ljava/lang/Object;)Ljava/lang/StringBuffer;
L254:   ldc ", "
L256:   invokevirtual Method java/lang/StringBuffer append (Ljava/lang/String;)Ljava/lang/StringBuffer;
L259:   iload_3
L260:   invokevirtual Method java/lang/StringBuffer append (I)Ljava/lang/StringBuffer;
L263:   ldc ", "
L265:   invokevirtual Method java/lang/StringBuffer append (Ljava/lang/String;)Ljava/lang/StringBuffer;
L268:   aload 4
L270:   invokevirtual Method java/lang/StringBuffer append (Ljava/lang/Object;)Ljava/lang/StringBuffer;
L273:   ldc ", "
L275:   invokevirtual Method java/lang/StringBuffer append (Ljava/lang/String;)Ljava/lang/StringBuffer;
L278:   iload 5
L280:   invokevirtual Method java/lang/StringBuffer append (I)Ljava/lang/StringBuffer;
L283:   ldc ", "
L285:   invokevirtual Method java/lang/StringBuffer append (Ljava/lang/String;)Ljava/lang/StringBuffer;
L288:   aload 6
L290:   invokevirtual Method java/lang/Throwable toString ()Ljava/lang/String;
L293:   invokevirtual Method java/lang/StringBuffer append (Ljava/lang/String;)Ljava/lang/StringBuffer;
L296:   invokevirtual Method java/lang/StringBuffer toString ()Ljava/lang/String;
L299:   invokestatic Method sign/signlink reporterror (Ljava/lang/String;)V
L302:   new java/lang/RuntimeException
L305:   dup
L306:   invokespecial Method java/lang/RuntimeException <init> ()V
L309:   athrow
L310:   
    .end code
.end method

.method public final a : (IIIII)V
    .code stack 4 locals 12
L0:     getstatic Field dc c Z
L3:     istore 11
        .catch java/lang/RuntimeException from L5 to L194 using L195
L5:     iconst_0
L6:     istore 6
L8:     iload_3
L9:     iconst_3
L10:    if_icmpeq L19
L13:    aload_0
L14:    bipush 123
L16:    putfield Field c c I
L19:    iconst_0
L20:    istore 7
L22:    iload 11
L24:    ifeq L59
L27:    getstatic Field fc d [Lfc;
L30:    iload 7
L32:    aaload
L33:    getfield Field fc i Ljava/lang/String;
L36:    ldc "water"
L38:    invokevirtual Method java/lang/String equalsIgnoreCase (Ljava/lang/String;)Z
L41:    ifeq L56
L44:    iload 7
L46:    iconst_1
L47:    iadd
L48:    i2b
L49:    istore 6
L51:    iload 11
L53:    ifeq L67
L56:    iinc 7 1
L59:    iload 7
L61:    getstatic Field fc c I
L64:    if_icmplt L27
L67:    iload_2
L68:    istore 8
L70:    iload 11
L72:    ifeq L185
L75:    iload_1
L76:    istore 9
L78:    iload 11
L80:    ifeq L173
L83:    iload 9
L85:    iflt L170
L88:    iload 9
L90:    aload_0
L91:    getfield Field c g I
L94:    if_icmpge L170
L97:    iload 8
L99:    iflt L170
L102:   iload 8
L104:   aload_0
L105:   getfield Field c h I
L108:   if_icmpge L170
L111:   aload_0
L112:   getfield Field c l [[[B
L115:   iconst_0
L116:   aaload
L117:   iload 9
L119:   aaload
L120:   iload 8
L122:   iload 6
L124:   bastore
L125:   iconst_0
L126:   istore 10
L128:   iload 11
L130:   ifeq L164
L133:   aload_0
L134:   getfield Field c i [[[I
L137:   iload 10
L139:   aaload
L140:   iload 9
L142:   aaload
L143:   iload 8
L145:   iconst_0
L146:   iastore
L147:   aload_0
L148:   getfield Field c j [[[B
L151:   iload 10
L153:   aaload
L154:   iload 9
L156:   aaload
L157:   iload 8
L159:   iconst_0
L160:   bastore
L161:   iinc 10 1
L164:   iload 10
L166:   iconst_4
L167:   if_icmplt L133
L170:   iinc 9 1
L173:   iload 9
L175:   iload_1
L176:   iload 4
L178:   iadd
L179:   if_icmplt L83
L182:   iinc 8 1
L185:   iload 8
L187:   iload_2
L188:   iload 5
L190:   iadd
L191:   if_icmplt L75
L194:   return
L195:   astore 6
L197:   new java/lang/StringBuffer
L200:   dup
L201:   ldc "25754, "
L203:   invokespecial Method java/lang/StringBuffer <init> (Ljava/lang/String;)V
L206:   iload_1
L207:   invokevirtual Method java/lang/StringBuffer append (I)Ljava/lang/StringBuffer;
L210:   ldc ", "
L212:   invokevirtual Method java/lang/StringBuffer append (Ljava/lang/String;)Ljava/lang/StringBuffer;
L215:   iload_2
L216:   invokevirtual Method java/lang/StringBuffer append (I)Ljava/lang/StringBuffer;
L219:   ldc ", "
L221:   invokevirtual Method java/lang/StringBuffer append (Ljava/lang/String;)Ljava/lang/StringBuffer;
L224:   iload_3
L225:   invokevirtual Method java/lang/StringBuffer append (I)Ljava/lang/StringBuffer;
L228:   ldc ", "
L230:   invokevirtual Method java/lang/StringBuffer append (Ljava/lang/String;)Ljava/lang/StringBuffer;
L233:   iload 4
L235:   invokevirtual Method java/lang/StringBuffer append (I)Ljava/lang/StringBuffer;
L238:   ldc ", "
L240:   invokevirtual Method java/lang/StringBuffer append (Ljava/lang/String;)Ljava/lang/StringBuffer;
L243:   iload 5
L245:   invokevirtual Method java/lang/StringBuffer append (I)Ljava/lang/StringBuffer;
L248:   ldc ", "
L250:   invokevirtual Method java/lang/StringBuffer append (Ljava/lang/String;)Ljava/lang/StringBuffer;
L253:   aload 6
L255:   invokevirtual Method java/lang/Throwable toString ()Ljava/lang/String;
L258:   invokevirtual Method java/lang/StringBuffer append (Ljava/lang/String;)Ljava/lang/StringBuffer;
L261:   invokevirtual Method java/lang/StringBuffer toString ()Ljava/lang/String;
L264:   invokestatic Method sign/signlink reporterror (Ljava/lang/String;)V
L267:   new java/lang/RuntimeException
L270:   dup
L271:   invokespecial Method java/lang/RuntimeException <init> ()V
L274:   athrow
L275:   
    .end code
.end method

.method public final a : ([BIIIII)V
    .code stack 6 locals 16
L0:     getstatic Field dc c Z
L3:     istore 15
        .catch java/lang/RuntimeException from L5 to L498 using L499
L5:     new kb
L8:     dup
L9:     sipush 363
L12:    aload_1
L13:    invokespecial Method kb <init> (I[B)V
L16:    astore 7
L18:    iload_3
L19:    iconst_1
L20:    if_icmpeq L39
L23:    aload_0
L24:    aload_0
L25:    getfield Field c b Z
L28:    ifeq L35
L31:    iconst_0
L32:    goto L36
L35:    iconst_1
L36:    putfield Field c b Z
L39:    iconst_0
L40:    istore 8
L42:    iload 15
L44:    ifeq L492
L47:    iconst_0
L48:    istore 9
L50:    iload 15
L52:    ifeq L482
L55:    iconst_0
L56:    istore 10
L58:    iload 15
L60:    ifeq L472
L63:    iload 9
L65:    iload 5
L67:    iadd
L68:    istore 11
L70:    iload 10
L72:    iload 4
L74:    iadd
L75:    istore 12
L77:    iload 11
L79:    iflt L422
L82:    iload 11
L84:    bipush 104
L86:    if_icmpge L422
L89:    iload 12
L91:    iflt L422
L94:    iload 12
L96:    bipush 104
L98:    if_icmpge L422
L101:   aload_0
L102:   getfield Field c j [[[B
L105:   iload 8
L107:   aaload
L108:   iload 11
L110:   aaload
L111:   iload 12
L113:   iconst_0
L114:   bastore
L115:   aload 7
L117:   invokevirtual Method kb c ()I
L120:   istore 13
L122:   iload 13
L124:   ifne L208
L127:   iload 8
L129:   ifne L171
L132:   aload_0
L133:   getfield Field c i [[[I
L136:   iconst_0
L137:   aaload
L138:   iload 11
L140:   aaload
L141:   iload 12
L143:   ldc 932731
L145:   iload 11
L147:   iadd
L148:   iload_2
L149:   iadd
L150:   ldc 556238
L152:   iload 12
L154:   iadd
L155:   iload 6
L157:   iadd
L158:   invokestatic Method c a (II)I
L161:   ineg
L162:   bipush 8
L164:   imul
L165:   iastore
L166:   iload 15
L168:   ifeq L469
L171:   aload_0
L172:   getfield Field c i [[[I
L175:   iload 8
L177:   aaload
L178:   iload 11
L180:   aaload
L181:   iload 12
L183:   aload_0
L184:   getfield Field c i [[[I
L187:   iload 8
L189:   iconst_1
L190:   isub
L191:   aaload
L192:   iload 11
L194:   aaload
L195:   iload 12
L197:   iaload
L198:   sipush 240
L201:   isub
L202:   iastore
L203:   iload 15
L205:   ifeq L469
L208:   iload 13
L210:   iconst_1
L211:   if_icmpne L297
L214:   aload 7
L216:   invokevirtual Method kb c ()I
L219:   istore 14
L221:   iload 14
L223:   iconst_1
L224:   if_icmpne L230
L227:   iconst_0
L228:   istore 14
L230:   iload 8
L232:   ifne L258
L235:   aload_0
L236:   getfield Field c i [[[I
L239:   iconst_0
L240:   aaload
L241:   iload 11
L243:   aaload
L244:   iload 12
L246:   iload 14
L248:   ineg
L249:   bipush 8
L251:   imul
L252:   iastore
L253:   iload 15
L255:   ifeq L469
L258:   aload_0
L259:   getfield Field c i [[[I
L262:   iload 8
L264:   aaload
L265:   iload 11
L267:   aaload
L268:   iload 12
L270:   aload_0
L271:   getfield Field c i [[[I
L274:   iload 8
L276:   iconst_1
L277:   isub
L278:   aaload
L279:   iload 11
L281:   aaload
L282:   iload 12
L284:   iaload
L285:   iload 14
L287:   bipush 8
L289:   imul
L290:   isub
L291:   iastore
L292:   iload 15
L294:   ifeq L469
L297:   iload 13
L299:   bipush 49
L301:   if_icmpgt L367
L304:   aload_0
L305:   getfield Field c l [[[B
L308:   iload 8
L310:   aaload
L311:   iload 11
L313:   aaload
L314:   iload 12
L316:   aload 7
L318:   invokevirtual Method kb d ()B
L321:   bastore
L322:   aload_0
L323:   getfield Field c m [[[B
L326:   iload 8
L328:   aaload
L329:   iload 11
L331:   aaload
L332:   iload 12
L334:   iload 13
L336:   iconst_2
L337:   isub
L338:   iconst_4
L339:   idiv
L340:   i2b
L341:   bastore
L342:   aload_0
L343:   getfield Field c n [[[B
L346:   iload 8
L348:   aaload
L349:   iload 11
L351:   aaload
L352:   iload 12
L354:   iload 13
L356:   iconst_2
L357:   isub
L358:   iconst_3
L359:   iand
L360:   i2b
L361:   bastore
L362:   iload 15
L364:   ifeq L115
L367:   iload 13
L369:   bipush 81
L371:   if_icmpgt L398
L374:   aload_0
L375:   getfield Field c j [[[B
L378:   iload 8
L380:   aaload
L381:   iload 11
L383:   aaload
L384:   iload 12
L386:   iload 13
L388:   bipush 49
L390:   isub
L391:   i2b
L392:   bastore
L393:   iload 15
L395:   ifeq L115
L398:   aload_0
L399:   getfield Field c k [[[B
L402:   iload 8
L404:   aaload
L405:   iload 11
L407:   aaload
L408:   iload 12
L410:   iload 13
L412:   bipush 81
L414:   isub
L415:   i2b
L416:   bastore
L417:   iload 15
L419:   ifeq L115
L422:   aload 7
L424:   invokevirtual Method kb c ()I
L427:   istore 13
L429:   iload 13
L431:   ifeq L469
L434:   iload 13
L436:   iconst_1
L437:   if_icmpne L451
L440:   aload 7
L442:   invokevirtual Method kb c ()I
L445:   pop
L446:   iload 15
L448:   ifeq L469
L451:   iload 13
L453:   bipush 49
L455:   if_icmpgt L422
L458:   aload 7
L460:   invokevirtual Method kb c ()I
L463:   pop
L464:   iload 15
L466:   ifeq L422
L469:   iinc 10 1
L472:   iload 10
L474:   bipush 64
L476:   if_icmplt L63
L479:   iinc 9 1
L482:   iload 9
L484:   bipush 64
L486:   if_icmplt L55
L489:   iinc 8 1
L492:   iload 8
L494:   iconst_4
L495:   if_icmplt L47
L498:   return
L499:   astore 7
L501:   new java/lang/StringBuffer
L504:   dup
L505:   ldc "89670, "
L507:   invokespecial Method java/lang/StringBuffer <init> (Ljava/lang/String;)V
L510:   aload_1
L511:   invokevirtual Method java/lang/StringBuffer append (Ljava/lang/Object;)Ljava/lang/StringBuffer;
L514:   ldc ", "
L516:   invokevirtual Method java/lang/StringBuffer append (Ljava/lang/String;)Ljava/lang/StringBuffer;
L519:   iload_2
L520:   invokevirtual Method java/lang/StringBuffer append (I)Ljava/lang/StringBuffer;
L523:   ldc ", "
L525:   invokevirtual Method java/lang/StringBuffer append (Ljava/lang/String;)Ljava/lang/StringBuffer;
L528:   iload_3
L529:   invokevirtual Method java/lang/StringBuffer append (I)Ljava/lang/StringBuffer;
L532:   ldc ", "
L534:   invokevirtual Method java/lang/StringBuffer append (Ljava/lang/String;)Ljava/lang/StringBuffer;
L537:   iload 4
L539:   invokevirtual Method java/lang/StringBuffer append (I)Ljava/lang/StringBuffer;
L542:   ldc ", "
L544:   invokevirtual Method java/lang/StringBuffer append (Ljava/lang/String;)Ljava/lang/StringBuffer;
L547:   iload 5
L549:   invokevirtual Method java/lang/StringBuffer append (I)Ljava/lang/StringBuffer;
L552:   ldc ", "
L554:   invokevirtual Method java/lang/StringBuffer append (Ljava/lang/String;)Ljava/lang/StringBuffer;
L557:   iload 6
L559:   invokevirtual Method java/lang/StringBuffer append (I)Ljava/lang/StringBuffer;
L562:   ldc ", "
L564:   invokevirtual Method java/lang/StringBuffer append (Ljava/lang/String;)Ljava/lang/StringBuffer;
L567:   aload 7
L569:   invokevirtual Method java/lang/Throwable toString ()Ljava/lang/String;
L572:   invokevirtual Method java/lang/StringBuffer append (Ljava/lang/String;)Ljava/lang/StringBuffer;
L575:   invokevirtual Method java/lang/StringBuffer toString ()Ljava/lang/String;
L578:   invokestatic Method sign/signlink reporterror (Ljava/lang/String;)V
L581:   new java/lang/RuntimeException
L584:   dup
L585:   invokespecial Method java/lang/RuntimeException <init> ()V
L588:   athrow
L589:   
    .end code
.end method

.method public final a : ([BLr;[Lec;Lob;ZII)V
    .code stack 12 locals 24
L0:     getstatic Field dc c Z
L3:     istore 23
        .catch java/lang/RuntimeException from L5 to L237 using L238
L5:     new kb
L8:     dup
L9:     sipush 363
L12:    aload_1
L13:    invokespecial Method kb <init> (I[B)V
L16:    astore 8
L18:    iload 5
L20:    ifne L39
L23:    aload_0
L24:    aload_0
L25:    getfield Field c b Z
L28:    ifeq L35
L31:    iconst_0
L32:    goto L36
L35:    iconst_1
L36:    putfield Field c b Z
L39:    iconst_m1
L40:    istore 9
L42:    aload 8
L44:    invokevirtual Method kb k ()I
L47:    istore 10
L49:    iload 10
L51:    ifeq L237
L54:    iload 9
L56:    iload 10
L58:    iadd
L59:    istore 9
L61:    iconst_0
L62:    istore 11
L64:    aload 8
L66:    invokevirtual Method kb k ()I
L69:    istore 12
L71:    iload 12
L73:    ifeq L232
L76:    iload 11
L78:    iload 12
L80:    iconst_1
L81:    isub
L82:    iadd
L83:    istore 11
L85:    iload 11
L87:    bipush 63
L89:    iand
L90:    istore 13
L92:    iload 11
L94:    bipush 6
L96:    ishr
L97:    bipush 63
L99:    iand
L100:   istore 14
L102:   iload 11
L104:   bipush 12
L106:   ishr
L107:   istore 15
L109:   aload 8
L111:   invokevirtual Method kb c ()I
L114:   istore 16
L116:   iload 16
L118:   iconst_2
L119:   ishr
L120:   istore 17
L122:   iload 16
L124:   iconst_3
L125:   iand
L126:   istore 18
L128:   iload 14
L130:   iload 7
L132:   iadd
L133:   istore 19
L135:   iload 13
L137:   iload 6
L139:   iadd
L140:   istore 20
L142:   iload 19
L144:   ifle L64
L147:   iload 20
L149:   ifle L64
L152:   iload 19
L154:   bipush 103
L156:   if_icmpge L64
L159:   iload 20
L161:   bipush 103
L163:   if_icmpge L64
L166:   iload 15
L168:   istore 21
L170:   aload_0
L171:   getfield Field c j [[[B
L174:   iconst_1
L175:   aaload
L176:   iload 19
L178:   aaload
L179:   iload 20
L181:   baload
L182:   iconst_2
L183:   iand
L184:   iconst_2
L185:   if_icmpne L191
L188:   iinc 21 -1
L191:   aconst_null
L192:   astore 22
L194:   iload 21
L196:   iflt L205
L199:   aload_3
L200:   iload 21
L202:   aaload
L203:   astore 22
L205:   aload_0
L206:   aload 22
L208:   iconst_1
L209:   iload 15
L211:   iload 20
L213:   iload 18
L215:   iload 17
L217:   aload_2
L218:   aload 4
L220:   iload 9
L222:   iload 19
L224:   invokespecial Method c a (Lec;ZIIIILr;Lob;II)V
L227:   iload 23
L229:   ifeq L64
L232:   iload 23
L234:   ifeq L42
L237:   return
L238:   astore 8
L240:   new java/lang/StringBuffer
L243:   dup
L244:   ldc "51686, "
L246:   invokespecial Method java/lang/StringBuffer <init> (Ljava/lang/String;)V
L249:   aload_1
L250:   invokevirtual Method java/lang/StringBuffer append (Ljava/lang/Object;)Ljava/lang/StringBuffer;
L253:   ldc ", "
L255:   invokevirtual Method java/lang/StringBuffer append (Ljava/lang/String;)Ljava/lang/StringBuffer;
L258:   aload_2
L259:   invokevirtual Method java/lang/StringBuffer append (Ljava/lang/Object;)Ljava/lang/StringBuffer;
L262:   ldc ", "
L264:   invokevirtual Method java/lang/StringBuffer append (Ljava/lang/String;)Ljava/lang/StringBuffer;
L267:   aload_3
L268:   invokevirtual Method java/lang/StringBuffer append (Ljava/lang/Object;)Ljava/lang/StringBuffer;
L271:   ldc ", "
L273:   invokevirtual Method java/lang/StringBuffer append (Ljava/lang/String;)Ljava/lang/StringBuffer;
L276:   aload 4
L278:   invokevirtual Method java/lang/StringBuffer append (Ljava/lang/Object;)Ljava/lang/StringBuffer;
L281:   ldc ", "
L283:   invokevirtual Method java/lang/StringBuffer append (Ljava/lang/String;)Ljava/lang/StringBuffer;
L286:   iload 5
L288:   invokevirtual Method java/lang/StringBuffer append (Z)Ljava/lang/StringBuffer;
L291:   ldc ", "
L293:   invokevirtual Method java/lang/StringBuffer append (Ljava/lang/String;)Ljava/lang/StringBuffer;
L296:   iload 6
L298:   invokevirtual Method java/lang/StringBuffer append (I)Ljava/lang/StringBuffer;
L301:   ldc ", "
L303:   invokevirtual Method java/lang/StringBuffer append (Ljava/lang/String;)Ljava/lang/StringBuffer;
L306:   iload 7
L308:   invokevirtual Method java/lang/StringBuffer append (I)Ljava/lang/StringBuffer;
L311:   ldc ", "
L313:   invokevirtual Method java/lang/StringBuffer append (Ljava/lang/String;)Ljava/lang/StringBuffer;
L316:   aload 8
L318:   invokevirtual Method java/lang/Throwable toString ()Ljava/lang/String;
L321:   invokevirtual Method java/lang/StringBuffer append (Ljava/lang/String;)Ljava/lang/StringBuffer;
L324:   invokevirtual Method java/lang/StringBuffer toString ()Ljava/lang/String;
L327:   invokestatic Method sign/signlink reporterror (Ljava/lang/String;)V
L330:   new java/lang/RuntimeException
L333:   dup
L334:   invokespecial Method java/lang/RuntimeException <init> ()V
L337:   athrow
L338:   
    .end code
.end method

.method private final a : (Lec;ZIIIILr;Lob;II)V
    .code stack 14 locals 27
L0:     getstatic Field dc c Z
L3:     istore 26
        .catch java/lang/RuntimeException from L5 to L2797 using L2797
L5:     iload_2
L6:     ifne L10
L9:     return
L10:    getstatic Field c d Z
L13:    ifeq L53
L16:    aload_0
L17:    getfield Field c j [[[B
L20:    iload_3
L21:    aaload
L22:    iload 10
L24:    aaload
L25:    iload 4
L27:    baload
L28:    bipush 16
L30:    iand
L31:    ifeq L35
L34:    return
L35:    aload_0
L36:    iload_3
L37:    bipush 10
L39:    iload 10
L41:    iload 4
L43:    invokevirtual Method c a (IBII)I
L46:    getstatic Field c e I
L49:    if_icmpeq L53
L52:    return
L53:    aload_0
L54:    getfield Field c i [[[I
L57:    iload_3
L58:    aaload
L59:    iload 10
L61:    aaload
L62:    iload 4
L64:    iaload
L65:    istore 11
L67:    aload_0
L68:    getfield Field c i [[[I
L71:    iload_3
L72:    aaload
L73:    iload 10
L75:    iconst_1
L76:    iadd
L77:    aaload
L78:    iload 4
L80:    iaload
L81:    istore 12
L83:    aload_0
L84:    getfield Field c i [[[I
L87:    iload_3
L88:    aaload
L89:    iload 10
L91:    iconst_1
L92:    iadd
L93:    aaload
L94:    iload 4
L96:    iconst_1
L97:    iadd
L98:    iaload
L99:    istore 13
L101:   aload_0
L102:   getfield Field c i [[[I
L105:   iload_3
L106:   aaload
L107:   iload 10
L109:   aaload
L110:   iload 4
L112:   iconst_1
L113:   iadd
L114:   iaload
L115:   istore 14
L117:   iload 11
L119:   iload 12
L121:   iadd
L122:   iload 13
L124:   iadd
L125:   iload 14
L127:   iadd
L128:   iconst_2
L129:   ishr
L130:   istore 15
L132:   iload 9
L134:   invokestatic Method ac a (I)Lac;
L137:   astore 16
L139:   iload 10
L141:   iload 4
L143:   bipush 7
L145:   ishl
L146:   iadd
L147:   iload 9
L149:   bipush 14
L151:   ishl
L152:   iadd
L153:   ldc 1073741824
L155:   iadd
L156:   istore 17
L158:   aload 16
L160:   getfield Field ac t Z
L163:   ifne L173
L166:   iload 17
L168:   ldc -2147483648
L170:   iadd
L171:   istore 17
L173:   iload 5
L175:   bipush 6
L177:   ishl
L178:   iload 6
L180:   iadd
L181:   i2b
L182:   istore 18
L184:   iload 6
L186:   bipush 22
L188:   if_icmpne L325
L191:   getstatic Field c d Z
L194:   ifeq L214
L197:   aload 16
L199:   getfield Field ac t Z
L202:   ifne L214
L205:   aload 16
L207:   getfield Field ac O Z
L210:   ifne L214
L213:   return
L214:   aload 16
L216:   bipush 22
L218:   iload 5
L220:   iload 11
L222:   iload 12
L224:   iload 13
L226:   iload 14
L228:   iconst_m1
L229:   invokevirtual Method ac a (IIIIIII)Leb;
L232:   astore 19
L234:   aload 7
L236:   aload 19
L238:   bipush 6
L240:   iload 10
L242:   iload 17
L244:   iload 4
L246:   iload_3
L247:   iload 18
L249:   iload 15
L251:   invokevirtual Method r a (Leb;BIIIIBI)V
L254:   aload 16
L256:   getfield Field ac r Z
L259:   ifeq L284
L262:   aload 16
L264:   getfield Field ac t Z
L267:   ifeq L284
L270:   aload_1
L271:   ifnull L284
L274:   aload_1
L275:   bipush 12
L277:   iload 4
L279:   iload 10
L281:   invokevirtual Method ec a (BII)V
L284:   aload 16
L286:   getfield Field ac x I
L289:   iconst_m1
L290:   if_icmpeq L324
L293:   aload 8
L295:   new nb
L298:   dup
L299:   iconst_1
L300:   iload 9
L302:   iload_3
L303:   iconst_0
L304:   iconst_3
L305:   getstatic Field jc d [Ljc;
L308:   aload 16
L310:   getfield Field ac x I
L313:   aaload
L314:   iload 4
L316:   iload 10
L318:   invokespecial Method nb <init> (ZIIIILjc;II)V
L321:   invokevirtual Method ob a (Lu;)V
L324:   return
L325:   iload 6
L327:   bipush 10
L329:   if_icmpeq L339
L332:   iload 6
L334:   bipush 11
L336:   if_icmpne L644
L339:   aload 16
L341:   bipush 10
L343:   iload 5
L345:   iload 11
L347:   iload 12
L349:   iload 13
L351:   iload 14
L353:   iconst_m1
L354:   invokevirtual Method ac a (IIIIIII)Leb;
L357:   astore 19
L359:   aload 19
L361:   ifnull L564
L364:   iconst_0
L365:   istore 22
L367:   iload 6
L369:   bipush 11
L371:   if_icmpne L380
L374:   wide iinc 22 256
L380:   iload 5
L382:   iconst_1
L383:   if_icmpeq L392
L386:   iload 5
L388:   iconst_3
L389:   if_icmpne L411
L392:   aload 16
L394:   getfield Field ac q I
L397:   istore 20
L399:   aload 16
L401:   getfield Field ac p I
L404:   istore 21
L406:   iload 26
L408:   ifeq L425
L411:   aload 16
L413:   getfield Field ac p I
L416:   istore 20
L418:   aload 16
L420:   getfield Field ac q I
L423:   istore 21
L425:   aload 7
L427:   iload 15
L429:   sipush 775
L432:   iload_3
L433:   aconst_null
L434:   iload 17
L436:   iload 4
L438:   iload 10
L440:   iload 20
L442:   iload 18
L444:   aload 19
L446:   iload 22
L448:   iload 21
L450:   invokevirtual Method r a (IIILw;IIIIBLeb;II)Z
L453:   ifeq L564
L456:   aload 16
L458:   getfield Field ac G Z
L461:   ifeq L564
L464:   iconst_0
L465:   istore 23
L467:   iload 26
L469:   ifeq L557
L472:   iconst_0
L473:   istore 24
L475:   iload 26
L477:   ifeq L547
L480:   aload 19
L482:   getfield Field eb L I
L485:   iconst_4
L486:   idiv
L487:   istore 25
L489:   iload 25
L491:   bipush 30
L493:   if_icmple L500
L496:   bipush 30
L498:   istore 25
L500:   iload 25
L502:   aload_0
L503:   getfield Field c o [[[B
L506:   iload_3
L507:   aaload
L508:   iload 10
L510:   iload 23
L512:   iadd
L513:   aaload
L514:   iload 4
L516:   iload 24
L518:   iadd
L519:   baload
L520:   if_icmple L544
L523:   aload_0
L524:   getfield Field c o [[[B
L527:   iload_3
L528:   aaload
L529:   iload 10
L531:   iload 23
L533:   iadd
L534:   aaload
L535:   iload 4
L537:   iload 24
L539:   iadd
L540:   iload 25
L542:   i2b
L543:   bastore
L544:   iinc 24 1
L547:   iload 24
L549:   iload 21
L551:   if_icmple L480
L554:   iinc 23 1
L557:   iload 23
L559:   iload 20
L561:   if_icmple L472
L564:   aload 16
L566:   getfield Field ac r Z
L569:   ifeq L603
L572:   aload_1
L573:   ifnull L603
L576:   aload_1
L577:   iload 5
L579:   aload 16
L581:   getfield Field ac q I
L584:   aload 16
L586:   getfield Field ac p I
L589:   iload 10
L591:   bipush 9
L593:   iload 4
L595:   aload 16
L597:   getfield Field ac s Z
L600:   invokevirtual Method ec a (IIIIIIZ)V
L603:   aload 16
L605:   getfield Field ac x I
L608:   iconst_m1
L609:   if_icmpeq L643
L612:   aload 8
L614:   new nb
L617:   dup
L618:   iconst_1
L619:   iload 9
L621:   iload_3
L622:   iconst_0
L623:   iconst_2
L624:   getstatic Field jc d [Ljc;
L627:   aload 16
L629:   getfield Field ac x I
L632:   aaload
L633:   iload 4
L635:   iload 10
L637:   invokespecial Method nb <init> (ZIIIILjc;II)V
L640:   invokevirtual Method ob a (Lu;)V
L643:   return
L644:   iload 6
L646:   bipush 12
L648:   if_icmplt L820
L651:   aload 16
L653:   iload 6
L655:   iload 5
L657:   iload 11
L659:   iload 12
L661:   iload 13
L663:   iload 14
L665:   iconst_m1
L666:   invokevirtual Method ac a (IIIIIII)Leb;
L669:   astore 19
L671:   aload 7
L673:   iload 15
L675:   sipush 775
L678:   iload_3
L679:   aconst_null
L680:   iload 17
L682:   iload 4
L684:   iload 10
L686:   iconst_1
L687:   iload 18
L689:   aload 19
L691:   iconst_0
L692:   iconst_1
L693:   invokevirtual Method r a (IIILw;IIIIBLeb;II)Z
L696:   pop
L697:   iload 6
L699:   bipush 12
L701:   if_icmplt L740
L704:   iload 6
L706:   bipush 17
L708:   if_icmpgt L740
L711:   iload 6
L713:   bipush 13
L715:   if_icmpeq L740
L718:   iload_3
L719:   ifle L740
L722:   aload_0
L723:   getfield Field c v [[[I
L726:   iload_3
L727:   aaload
L728:   iload 10
L730:   aaload
L731:   iload 4
L733:   dup2
L734:   iaload
L735:   sipush 2340
L738:   ior
L739:   iastore
L740:   aload 16
L742:   getfield Field ac r Z
L745:   ifeq L779
L748:   aload_1
L749:   ifnull L779
L752:   aload_1
L753:   iload 5
L755:   aload 16
L757:   getfield Field ac q I
L760:   aload 16
L762:   getfield Field ac p I
L765:   iload 10
L767:   bipush 9
L769:   iload 4
L771:   aload 16
L773:   getfield Field ac s Z
L776:   invokevirtual Method ec a (IIIIIIZ)V
L779:   aload 16
L781:   getfield Field ac x I
L784:   iconst_m1
L785:   if_icmpeq L819
L788:   aload 8
L790:   new nb
L793:   dup
L794:   iconst_1
L795:   iload 9
L797:   iload_3
L798:   iconst_0
L799:   iconst_2
L800:   getstatic Field jc d [Ljc;
L803:   aload 16
L805:   getfield Field ac x I
L808:   aaload
L809:   iload 4
L811:   iload 10
L813:   invokespecial Method nb <init> (ZIIIILjc;II)V
L816:   invokevirtual Method ob a (Lu;)V
L819:   return
L820:   iload 6
L822:   ifne L1276
L825:   aload 16
L827:   iconst_0
L828:   iload 5
L830:   iload 11
L832:   iload 12
L834:   iload 13
L836:   iload 14
L838:   iconst_m1
L839:   invokevirtual Method ac a (IIIIIII)Leb;
L842:   astore 19
L844:   aload 7
L846:   iconst_0
L847:   iload 15
L849:   iload_3
L850:   getstatic Field c w [I
L853:   iload 5
L855:   iaload
L856:   bipush 8
L858:   aload 19
L860:   aconst_null
L861:   iload 10
L863:   iload 17
L865:   iload 4
L867:   iload 18
L869:   invokevirtual Method r a (IIIIILeb;Leb;IIIB)V
L872:   iload 5
L874:   ifne L946
L877:   aload 16
L879:   getfield Field ac G Z
L882:   ifeq L915
L885:   aload_0
L886:   getfield Field c o [[[B
L889:   iload_3
L890:   aaload
L891:   iload 10
L893:   aaload
L894:   iload 4
L896:   bipush 50
L898:   bastore
L899:   aload_0
L900:   getfield Field c o [[[B
L903:   iload_3
L904:   aaload
L905:   iload 10
L907:   aaload
L908:   iload 4
L910:   iconst_1
L911:   iadd
L912:   bipush 50
L914:   bastore
L915:   aload 16
L917:   getfield Field ac w Z
L920:   ifeq L1178
L923:   aload_0
L924:   getfield Field c v [[[I
L927:   iload_3
L928:   aaload
L929:   iload 10
L931:   aaload
L932:   iload 4
L934:   dup2
L935:   iaload
L936:   sipush 585
L939:   ior
L940:   iastore
L941:   iload 26
L943:   ifeq L1178
L946:   iload 5
L948:   iconst_1
L949:   if_icmpne L1027
L952:   aload 16
L954:   getfield Field ac G Z
L957:   ifeq L994
L960:   aload_0
L961:   getfield Field c o [[[B
L964:   iload_3
L965:   aaload
L966:   iload 10
L968:   aaload
L969:   iload 4
L971:   iconst_1
L972:   iadd
L973:   bipush 50
L975:   bastore
L976:   aload_0
L977:   getfield Field c o [[[B
L980:   iload_3
L981:   aaload
L982:   iload 10
L984:   iconst_1
L985:   iadd
L986:   aaload
L987:   iload 4
L989:   iconst_1
L990:   iadd
L991:   bipush 50
L993:   bastore
L994:   aload 16
L996:   getfield Field ac w Z
L999:   ifeq L1178
L1002:  aload_0
L1003:  getfield Field c v [[[I
L1006:  iload_3
L1007:  aaload
L1008:  iload 10
L1010:  aaload
L1011:  iload 4
L1013:  iconst_1
L1014:  iadd
L1015:  dup2
L1016:  iaload
L1017:  sipush 1170
L1020:  ior
L1021:  iastore
L1022:  iload 26
L1024:  ifeq L1178
L1027:  iload 5
L1029:  iconst_2
L1030:  if_icmpne L1108
L1033:  aload 16
L1035:  getfield Field ac G Z
L1038:  ifeq L1075
L1041:  aload_0
L1042:  getfield Field c o [[[B
L1045:  iload_3
L1046:  aaload
L1047:  iload 10
L1049:  iconst_1
L1050:  iadd
L1051:  aaload
L1052:  iload 4
L1054:  bipush 50
L1056:  bastore
L1057:  aload_0
L1058:  getfield Field c o [[[B
L1061:  iload_3
L1062:  aaload
L1063:  iload 10
L1065:  iconst_1
L1066:  iadd
L1067:  aaload
L1068:  iload 4
L1070:  iconst_1
L1071:  iadd
L1072:  bipush 50
L1074:  bastore
L1075:  aload 16
L1077:  getfield Field ac w Z
L1080:  ifeq L1178
L1083:  aload_0
L1084:  getfield Field c v [[[I
L1087:  iload_3
L1088:  aaload
L1089:  iload 10
L1091:  iconst_1
L1092:  iadd
L1093:  aaload
L1094:  iload 4
L1096:  dup2
L1097:  iaload
L1098:  sipush 585
L1101:  ior
L1102:  iastore
L1103:  iload 26
L1105:  ifeq L1178
L1108:  iload 5
L1110:  iconst_3
L1111:  if_icmpne L1178
L1114:  aload 16
L1116:  getfield Field ac G Z
L1119:  ifeq L1152
L1122:  aload_0
L1123:  getfield Field c o [[[B
L1126:  iload_3
L1127:  aaload
L1128:  iload 10
L1130:  aaload
L1131:  iload 4
L1133:  bipush 50
L1135:  bastore
L1136:  aload_0
L1137:  getfield Field c o [[[B
L1140:  iload_3
L1141:  aaload
L1142:  iload 10
L1144:  iconst_1
L1145:  iadd
L1146:  aaload
L1147:  iload 4
L1149:  bipush 50
L1151:  bastore
L1152:  aload 16
L1154:  getfield Field ac w Z
L1157:  ifeq L1178
L1160:  aload_0
L1161:  getfield Field c v [[[I
L1164:  iload_3
L1165:  aaload
L1166:  iload 10
L1168:  aaload
L1169:  iload 4
L1171:  dup2
L1172:  iaload
L1173:  sipush 1170
L1176:  ior
L1177:  iastore
L1178:  aload 16
L1180:  getfield Field ac r Z
L1183:  ifeq L1208
L1186:  aload_1
L1187:  ifnull L1208
L1190:  aload_1
L1191:  iconst_1
L1192:  iload 5
L1194:  iload 4
L1196:  iload 10
L1198:  aload 16
L1200:  getfield Field ac s Z
L1203:  iload 6
L1205:  invokevirtual Method ec a (ZIIIZI)V
L1208:  aload 16
L1210:  getfield Field ac x I
L1213:  iconst_m1
L1214:  if_icmpeq L1248
L1217:  aload 8
L1219:  new nb
L1222:  dup
L1223:  iconst_1
L1224:  iload 9
L1226:  iload_3
L1227:  iconst_0
L1228:  iconst_0
L1229:  getstatic Field jc d [Ljc;
L1232:  aload 16
L1234:  getfield Field ac x I
L1237:  aaload
L1238:  iload 4
L1240:  iload 10
L1242:  invokespecial Method nb <init> (ZIIIILjc;II)V
L1245:  invokevirtual Method ob a (Lu;)V
L1248:  aload 16
L1250:  getfield Field ac y I
L1253:  bipush 16
L1255:  if_icmpeq L1275
L1258:  aload 7
L1260:  iload_3
L1261:  iload 4
L1263:  iload 10
L1265:  aload 16
L1267:  getfield Field ac y I
L1270:  bipush 6
L1272:  invokevirtual Method r a (IIIIB)V
L1275:  return
L1276:  iload 6
L1278:  iconst_1
L1279:  if_icmpne L1510
L1282:  aload 16
L1284:  iconst_1
L1285:  iload 5
L1287:  iload 11
L1289:  iload 12
L1291:  iload 13
L1293:  iload 14
L1295:  iconst_m1
L1296:  invokevirtual Method ac a (IIIIIII)Leb;
L1299:  astore 19
L1301:  aload 7
L1303:  iconst_0
L1304:  iload 15
L1306:  iload_3
L1307:  getstatic Field c x [I
L1310:  iload 5
L1312:  iaload
L1313:  bipush 8
L1315:  aload 19
L1317:  aconst_null
L1318:  iload 10
L1320:  iload 17
L1322:  iload 4
L1324:  iload 18
L1326:  invokevirtual Method r a (IIIIILeb;Leb;IIIB)V
L1329:  aload 16
L1331:  getfield Field ac G Z
L1334:  ifeq L1439
L1337:  iload 5
L1339:  ifne L1363
L1342:  aload_0
L1343:  getfield Field c o [[[B
L1346:  iload_3
L1347:  aaload
L1348:  iload 10
L1350:  aaload
L1351:  iload 4
L1353:  iconst_1
L1354:  iadd
L1355:  bipush 50
L1357:  bastore
L1358:  iload 26
L1360:  ifeq L1439
L1363:  iload 5
L1365:  iconst_1
L1366:  if_icmpne L1392
L1369:  aload_0
L1370:  getfield Field c o [[[B
L1373:  iload_3
L1374:  aaload
L1375:  iload 10
L1377:  iconst_1
L1378:  iadd
L1379:  aaload
L1380:  iload 4
L1382:  iconst_1
L1383:  iadd
L1384:  bipush 50
L1386:  bastore
L1387:  iload 26
L1389:  ifeq L1439
L1392:  iload 5
L1394:  iconst_2
L1395:  if_icmpne L1419
L1398:  aload_0
L1399:  getfield Field c o [[[B
L1402:  iload_3
L1403:  aaload
L1404:  iload 10
L1406:  iconst_1
L1407:  iadd
L1408:  aaload
L1409:  iload 4
L1411:  bipush 50
L1413:  bastore
L1414:  iload 26
L1416:  ifeq L1439
L1419:  iload 5
L1421:  iconst_3
L1422:  if_icmpne L1439
L1425:  aload_0
L1426:  getfield Field c o [[[B
L1429:  iload_3
L1430:  aaload
L1431:  iload 10
L1433:  aaload
L1434:  iload 4
L1436:  bipush 50
L1438:  bastore
L1439:  aload 16
L1441:  getfield Field ac r Z
L1444:  ifeq L1469
L1447:  aload_1
L1448:  ifnull L1469
L1451:  aload_1
L1452:  iconst_1
L1453:  iload 5
L1455:  iload 4
L1457:  iload 10
L1459:  aload 16
L1461:  getfield Field ac s Z
L1464:  iload 6
L1466:  invokevirtual Method ec a (ZIIIZI)V
L1469:  aload 16
L1471:  getfield Field ac x I
L1474:  iconst_m1
L1475:  if_icmpeq L1509
L1478:  aload 8
L1480:  new nb
L1483:  dup
L1484:  iconst_1
L1485:  iload 9
L1487:  iload_3
L1488:  iconst_0
L1489:  iconst_0
L1490:  getstatic Field jc d [Ljc;
L1493:  aload 16
L1495:  getfield Field ac x I
L1498:  aaload
L1499:  iload 4
L1501:  iload 10
L1503:  invokespecial Method nb <init> (ZIIIILjc;II)V
L1506:  invokevirtual Method ob a (Lu;)V
L1509:  return
L1510:  iload 6
L1512:  iconst_2
L1513:  if_icmpne L1894
L1516:  iload 5
L1518:  iconst_1
L1519:  iadd
L1520:  iconst_3
L1521:  iand
L1522:  istore 19
L1524:  aload 16
L1526:  iconst_2
L1527:  iconst_4
L1528:  iload 5
L1530:  iadd
L1531:  iload 11
L1533:  iload 12
L1535:  iload 13
L1537:  iload 14
L1539:  iconst_m1
L1540:  invokevirtual Method ac a (IIIIIII)Leb;
L1543:  astore 20
L1545:  aload 16
L1547:  iconst_2
L1548:  iload 19
L1550:  iload 11
L1552:  iload 12
L1554:  iload 13
L1556:  iload 14
L1558:  iconst_m1
L1559:  invokevirtual Method ac a (IIIIIII)Leb;
L1562:  astore 21
L1564:  aload 7
L1566:  getstatic Field c w [I
L1569:  iload 19
L1571:  iaload
L1572:  iload 15
L1574:  iload_3
L1575:  getstatic Field c w [I
L1578:  iload 5
L1580:  iaload
L1581:  bipush 8
L1583:  aload 20
L1585:  aload 21
L1587:  iload 10
L1589:  iload 17
L1591:  iload 4
L1593:  iload 18
L1595:  invokevirtual Method r a (IIIIILeb;Leb;IIIB)V
L1598:  aload 16
L1600:  getfield Field ac w Z
L1603:  ifeq L1796
L1606:  iload 5
L1608:  ifne L1654
L1611:  aload_0
L1612:  getfield Field c v [[[I
L1615:  iload_3
L1616:  aaload
L1617:  iload 10
L1619:  aaload
L1620:  iload 4
L1622:  dup2
L1623:  iaload
L1624:  sipush 585
L1627:  ior
L1628:  iastore
L1629:  aload_0
L1630:  getfield Field c v [[[I
L1633:  iload_3
L1634:  aaload
L1635:  iload 10
L1637:  aaload
L1638:  iload 4
L1640:  iconst_1
L1641:  iadd
L1642:  dup2
L1643:  iaload
L1644:  sipush 1170
L1647:  ior
L1648:  iastore
L1649:  iload 26
L1651:  ifeq L1796
L1654:  iload 5
L1656:  iconst_1
L1657:  if_icmpne L1705
L1660:  aload_0
L1661:  getfield Field c v [[[I
L1664:  iload_3
L1665:  aaload
L1666:  iload 10
L1668:  aaload
L1669:  iload 4
L1671:  iconst_1
L1672:  iadd
L1673:  dup2
L1674:  iaload
L1675:  sipush 1170
L1678:  ior
L1679:  iastore
L1680:  aload_0
L1681:  getfield Field c v [[[I
L1684:  iload_3
L1685:  aaload
L1686:  iload 10
L1688:  iconst_1
L1689:  iadd
L1690:  aaload
L1691:  iload 4
L1693:  dup2
L1694:  iaload
L1695:  sipush 585
L1698:  ior
L1699:  iastore
L1700:  iload 26
L1702:  ifeq L1796
L1705:  iload 5
L1707:  iconst_2
L1708:  if_icmpne L1754
L1711:  aload_0
L1712:  getfield Field c v [[[I
L1715:  iload_3
L1716:  aaload
L1717:  iload 10
L1719:  iconst_1
L1720:  iadd
L1721:  aaload
L1722:  iload 4
L1724:  dup2
L1725:  iaload
L1726:  sipush 585
L1729:  ior
L1730:  iastore
L1731:  aload_0
L1732:  getfield Field c v [[[I
L1735:  iload_3
L1736:  aaload
L1737:  iload 10
L1739:  aaload
L1740:  iload 4
L1742:  dup2
L1743:  iaload
L1744:  sipush 1170
L1747:  ior
L1748:  iastore
L1749:  iload 26
L1751:  ifeq L1796
L1754:  iload 5
L1756:  iconst_3
L1757:  if_icmpne L1796
L1760:  aload_0
L1761:  getfield Field c v [[[I
L1764:  iload_3
L1765:  aaload
L1766:  iload 10
L1768:  aaload
L1769:  iload 4
L1771:  dup2
L1772:  iaload
L1773:  sipush 1170
L1776:  ior
L1777:  iastore
L1778:  aload_0
L1779:  getfield Field c v [[[I
L1782:  iload_3
L1783:  aaload
L1784:  iload 10
L1786:  aaload
L1787:  iload 4
L1789:  dup2
L1790:  iaload
L1791:  sipush 585
L1794:  ior
L1795:  iastore
L1796:  aload 16
L1798:  getfield Field ac r Z
L1801:  ifeq L1826
L1804:  aload_1
L1805:  ifnull L1826
L1808:  aload_1
L1809:  iconst_1
L1810:  iload 5
L1812:  iload 4
L1814:  iload 10
L1816:  aload 16
L1818:  getfield Field ac s Z
L1821:  iload 6
L1823:  invokevirtual Method ec a (ZIIIZI)V
L1826:  aload 16
L1828:  getfield Field ac x I
L1831:  iconst_m1
L1832:  if_icmpeq L1866
L1835:  aload 8
L1837:  new nb
L1840:  dup
L1841:  iconst_1
L1842:  iload 9
L1844:  iload_3
L1845:  iconst_0
L1846:  iconst_0
L1847:  getstatic Field jc d [Ljc;
L1850:  aload 16
L1852:  getfield Field ac x I
L1855:  aaload
L1856:  iload 4
L1858:  iload 10
L1860:  invokespecial Method nb <init> (ZIIIILjc;II)V
L1863:  invokevirtual Method ob a (Lu;)V
L1866:  aload 16
L1868:  getfield Field ac y I
L1871:  bipush 16
L1873:  if_icmpeq L1893
L1876:  aload 7
L1878:  iload_3
L1879:  iload 4
L1881:  iload 10
L1883:  aload 16
L1885:  getfield Field ac y I
L1888:  bipush 6
L1890:  invokevirtual Method r a (IIIIB)V
L1893:  return
L1894:  iload 6
L1896:  iconst_3
L1897:  if_icmpne L2128
L1900:  aload 16
L1902:  iconst_3
L1903:  iload 5
L1905:  iload 11
L1907:  iload 12
L1909:  iload 13
L1911:  iload 14
L1913:  iconst_m1
L1914:  invokevirtual Method ac a (IIIIIII)Leb;
L1917:  astore 19
L1919:  aload 7
L1921:  iconst_0
L1922:  iload 15
L1924:  iload_3
L1925:  getstatic Field c x [I
L1928:  iload 5
L1930:  iaload
L1931:  bipush 8
L1933:  aload 19
L1935:  aconst_null
L1936:  iload 10
L1938:  iload 17
L1940:  iload 4
L1942:  iload 18
L1944:  invokevirtual Method r a (IIIIILeb;Leb;IIIB)V
L1947:  aload 16
L1949:  getfield Field ac G Z
L1952:  ifeq L2057
L1955:  iload 5
L1957:  ifne L1981
L1960:  aload_0
L1961:  getfield Field c o [[[B
L1964:  iload_3
L1965:  aaload
L1966:  iload 10
L1968:  aaload
L1969:  iload 4
L1971:  iconst_1
L1972:  iadd
L1973:  bipush 50
L1975:  bastore
L1976:  iload 26
L1978:  ifeq L2057
L1981:  iload 5
L1983:  iconst_1
L1984:  if_icmpne L2010
L1987:  aload_0
L1988:  getfield Field c o [[[B
L1991:  iload_3
L1992:  aaload
L1993:  iload 10
L1995:  iconst_1
L1996:  iadd
L1997:  aaload
L1998:  iload 4
L2000:  iconst_1
L2001:  iadd
L2002:  bipush 50
L2004:  bastore
L2005:  iload 26
L2007:  ifeq L2057
L2010:  iload 5
L2012:  iconst_2
L2013:  if_icmpne L2037
L2016:  aload_0
L2017:  getfield Field c o [[[B
L2020:  iload_3
L2021:  aaload
L2022:  iload 10
L2024:  iconst_1
L2025:  iadd
L2026:  aaload
L2027:  iload 4
L2029:  bipush 50
L2031:  bastore
L2032:  iload 26
L2034:  ifeq L2057
L2037:  iload 5
L2039:  iconst_3
L2040:  if_icmpne L2057
L2043:  aload_0
L2044:  getfield Field c o [[[B
L2047:  iload_3
L2048:  aaload
L2049:  iload 10
L2051:  aaload
L2052:  iload 4
L2054:  bipush 50
L2056:  bastore
L2057:  aload 16
L2059:  getfield Field ac r Z
L2062:  ifeq L2087
L2065:  aload_1
L2066:  ifnull L2087
L2069:  aload_1
L2070:  iconst_1
L2071:  iload 5
L2073:  iload 4
L2075:  iload 10
L2077:  aload 16
L2079:  getfield Field ac s Z
L2082:  iload 6
L2084:  invokevirtual Method ec a (ZIIIZI)V
L2087:  aload 16
L2089:  getfield Field ac x I
L2092:  iconst_m1
L2093:  if_icmpeq L2127
L2096:  aload 8
L2098:  new nb
L2101:  dup
L2102:  iconst_1
L2103:  iload 9
L2105:  iload_3
L2106:  iconst_0
L2107:  iconst_0
L2108:  getstatic Field jc d [Ljc;
L2111:  aload 16
L2113:  getfield Field ac x I
L2116:  aaload
L2117:  iload 4
L2119:  iload 10
L2121:  invokespecial Method nb <init> (ZIIIILjc;II)V
L2124:  invokevirtual Method ob a (Lu;)V
L2127:  return
L2128:  iload 6
L2130:  bipush 9
L2132:  if_icmpne L2261
L2135:  aload 16
L2137:  iload 6
L2139:  iload 5
L2141:  iload 11
L2143:  iload 12
L2145:  iload 13
L2147:  iload 14
L2149:  iconst_m1
L2150:  invokevirtual Method ac a (IIIIIII)Leb;
L2153:  astore 19
L2155:  aload 7
L2157:  iload 15
L2159:  sipush 775
L2162:  iload_3
L2163:  aconst_null
L2164:  iload 17
L2166:  iload 4
L2168:  iload 10
L2170:  iconst_1
L2171:  iload 18
L2173:  aload 19
L2175:  iconst_0
L2176:  iconst_1
L2177:  invokevirtual Method r a (IIILw;IIIIBLeb;II)Z
L2180:  pop
L2181:  aload 16
L2183:  getfield Field ac r Z
L2186:  ifeq L2220
L2189:  aload_1
L2190:  ifnull L2220
L2193:  aload_1
L2194:  iload 5
L2196:  aload 16
L2198:  getfield Field ac q I
L2201:  aload 16
L2203:  getfield Field ac p I
L2206:  iload 10
L2208:  bipush 9
L2210:  iload 4
L2212:  aload 16
L2214:  getfield Field ac s Z
L2217:  invokevirtual Method ec a (IIIIIIZ)V
L2220:  aload 16
L2222:  getfield Field ac x I
L2225:  iconst_m1
L2226:  if_icmpeq L2260
L2229:  aload 8
L2231:  new nb
L2234:  dup
L2235:  iconst_1
L2236:  iload 9
L2238:  iload_3
L2239:  iconst_0
L2240:  iconst_2
L2241:  getstatic Field jc d [Ljc;
L2244:  aload 16
L2246:  getfield Field ac x I
L2249:  aaload
L2250:  iload 4
L2252:  iload 10
L2254:  invokespecial Method nb <init> (ZIIIILjc;II)V
L2257:  invokevirtual Method ob a (Lu;)V
L2260:  return
L2261:  iload 6
L2263:  iconst_4
L2264:  if_icmpne L2361
L2267:  aload 16
L2269:  iconst_4
L2270:  iconst_0
L2271:  iload 11
L2273:  iload 12
L2275:  iload 13
L2277:  iload 14
L2279:  iconst_m1
L2280:  invokevirtual Method ac a (IIIIIII)Leb;
L2283:  astore 19
L2285:  aload 7
L2287:  iload 15
L2289:  iload 4
L2291:  iconst_0
L2292:  iload 17
L2294:  iload 5
L2296:  sipush 512
L2299:  imul
L2300:  getstatic Field c w [I
L2303:  iload 5
L2305:  iaload
L2306:  sipush 465
L2309:  iconst_0
L2310:  iload 10
L2312:  aload 19
L2314:  iload 18
L2316:  iload_3
L2317:  invokevirtual Method r a (IIIIIIIIILeb;BI)V
L2320:  aload 16
L2322:  getfield Field ac x I
L2325:  iconst_m1
L2326:  if_icmpeq L2360
L2329:  aload 8
L2331:  new nb
L2334:  dup
L2335:  iconst_1
L2336:  iload 9
L2338:  iload_3
L2339:  iconst_0
L2340:  iconst_1
L2341:  getstatic Field jc d [Ljc;
L2344:  aload 16
L2346:  getfield Field ac x I
L2349:  aaload
L2350:  iload 4
L2352:  iload 10
L2354:  invokespecial Method nb <init> (ZIIIILjc;II)V
L2357:  invokevirtual Method ob a (Lu;)V
L2360:  return
L2361:  iload 6
L2363:  iconst_5
L2364:  if_icmpne L2515
L2367:  bipush 16
L2369:  istore 19
L2371:  aload 7
L2373:  iload_3
L2374:  iload 10
L2376:  iload 4
L2378:  invokevirtual Method r b (III)I
L2381:  istore 20
L2383:  iload 20
L2385:  ifle L2405
L2388:  iload 20
L2390:  bipush 14
L2392:  ishr
L2393:  sipush 32767
L2396:  iand
L2397:  invokestatic Method ac a (I)Lac;
L2400:  getfield Field ac y I
L2403:  istore 19
L2405:  aload 16
L2407:  iconst_4
L2408:  iconst_0
L2409:  iload 11
L2411:  iload 12
L2413:  iload 13
L2415:  iload 14
L2417:  iconst_m1
L2418:  invokevirtual Method ac a (IIIIIII)Leb;
L2421:  astore 21
L2423:  aload 7
L2425:  iload 15
L2427:  iload 4
L2429:  getstatic Field c z [I
L2432:  iload 5
L2434:  iaload
L2435:  iload 19
L2437:  imul
L2438:  iload 17
L2440:  iload 5
L2442:  sipush 512
L2445:  imul
L2446:  getstatic Field c w [I
L2449:  iload 5
L2451:  iaload
L2452:  sipush 465
L2455:  getstatic Field c y [I
L2458:  iload 5
L2460:  iaload
L2461:  iload 19
L2463:  imul
L2464:  iload 10
L2466:  aload 21
L2468:  iload 18
L2470:  iload_3
L2471:  invokevirtual Method r a (IIIIIIIIILeb;BI)V
L2474:  aload 16
L2476:  getfield Field ac x I
L2479:  iconst_m1
L2480:  if_icmpeq L2514
L2483:  aload 8
L2485:  new nb
L2488:  dup
L2489:  iconst_1
L2490:  iload 9
L2492:  iload_3
L2493:  iconst_0
L2494:  iconst_1
L2495:  getstatic Field jc d [Ljc;
L2498:  aload 16
L2500:  getfield Field ac x I
L2503:  aaload
L2504:  iload 4
L2506:  iload 10
L2508:  invokespecial Method nb <init> (ZIIIILjc;II)V
L2511:  invokevirtual Method ob a (Lu;)V
L2514:  return
L2515:  iload 6
L2517:  bipush 6
L2519:  if_icmpne L2609
L2522:  aload 16
L2524:  iconst_4
L2525:  iconst_0
L2526:  iload 11
L2528:  iload 12
L2530:  iload 13
L2532:  iload 14
L2534:  iconst_m1
L2535:  invokevirtual Method ac a (IIIIIII)Leb;
L2538:  astore 19
L2540:  aload 7
L2542:  iload 15
L2544:  iload 4
L2546:  iconst_0
L2547:  iload 17
L2549:  iload 5
L2551:  sipush 256
L2554:  sipush 465
L2557:  iconst_0
L2558:  iload 10
L2560:  aload 19
L2562:  iload 18
L2564:  iload_3
L2565:  invokevirtual Method r a (IIIIIIIIILeb;BI)V
L2568:  aload 16
L2570:  getfield Field ac x I
L2573:  iconst_m1
L2574:  if_icmpeq L2608
L2577:  aload 8
L2579:  new nb
L2582:  dup
L2583:  iconst_1
L2584:  iload 9
L2586:  iload_3
L2587:  iconst_0
L2588:  iconst_1
L2589:  getstatic Field jc d [Ljc;
L2592:  aload 16
L2594:  getfield Field ac x I
L2597:  aaload
L2598:  iload 4
L2600:  iload 10
L2602:  invokespecial Method nb <init> (ZIIIILjc;II)V
L2605:  invokevirtual Method ob a (Lu;)V
L2608:  return
L2609:  iload 6
L2611:  bipush 7
L2613:  if_icmpne L2703
L2616:  aload 16
L2618:  iconst_4
L2619:  iconst_0
L2620:  iload 11
L2622:  iload 12
L2624:  iload 13
L2626:  iload 14
L2628:  iconst_m1
L2629:  invokevirtual Method ac a (IIIIIII)Leb;
L2632:  astore 19
L2634:  aload 7
L2636:  iload 15
L2638:  iload 4
L2640:  iconst_0
L2641:  iload 17
L2643:  iload 5
L2645:  sipush 512
L2648:  sipush 465
L2651:  iconst_0
L2652:  iload 10
L2654:  aload 19
L2656:  iload 18
L2658:  iload_3
L2659:  invokevirtual Method r a (IIIIIIIIILeb;BI)V
L2662:  aload 16
L2664:  getfield Field ac x I
L2667:  iconst_m1
L2668:  if_icmpeq L2702
L2671:  aload 8
L2673:  new nb
L2676:  dup
L2677:  iconst_1
L2678:  iload 9
L2680:  iload_3
L2681:  iconst_0
L2682:  iconst_1
L2683:  getstatic Field jc d [Ljc;
L2686:  aload 16
L2688:  getfield Field ac x I
L2691:  aaload
L2692:  iload 4
L2694:  iload 10
L2696:  invokespecial Method nb <init> (ZIIIILjc;II)V
L2699:  invokevirtual Method ob a (Lu;)V
L2702:  return
L2703:  iload 6
L2705:  bipush 8
L2707:  if_icmpne L2927
L2710:  aload 16
L2712:  iconst_4
L2713:  iconst_0
L2714:  iload 11
L2716:  iload 12
L2718:  iload 13
L2720:  iload 14
L2722:  iconst_m1
L2723:  invokevirtual Method ac a (IIIIIII)Leb;
L2726:  astore 19
L2728:  aload 7
L2730:  iload 15
L2732:  iload 4
L2734:  iconst_0
L2735:  iload 17
L2737:  iload 5
L2739:  sipush 768
L2742:  sipush 465
L2745:  iconst_0
L2746:  iload 10
L2748:  aload 19
L2750:  iload 18
L2752:  iload_3
L2753:  invokevirtual Method r a (IIIIIIIIILeb;BI)V
L2756:  aload 16
L2758:  getfield Field ac x I
L2761:  iconst_m1
L2762:  if_icmpeq L2796
L2765:  aload 8
L2767:  new nb
L2770:  dup
L2771:  iconst_1
L2772:  iload 9
L2774:  iload_3
L2775:  iconst_0
L2776:  iconst_1
L2777:  getstatic Field jc d [Ljc;
L2780:  aload 16
L2782:  getfield Field ac x I
L2785:  aaload
L2786:  iload 4
L2788:  iload 10
L2790:  invokespecial Method nb <init> (ZIIIILjc;II)V
L2793:  invokevirtual Method ob a (Lu;)V
L2796:  return
L2797:  astore 11
L2799:  new java/lang/StringBuffer
L2802:  dup
L2803:  ldc "46393, "
L2805:  invokespecial Method java/lang/StringBuffer <init> (Ljava/lang/String;)V
L2808:  aload_1
L2809:  invokevirtual Method java/lang/StringBuffer append (Ljava/lang/Object;)Ljava/lang/StringBuffer;
L2812:  ldc ", "
L2814:  invokevirtual Method java/lang/StringBuffer append (Ljava/lang/String;)Ljava/lang/StringBuffer;
L2817:  iload_2
L2818:  invokevirtual Method java/lang/StringBuffer append (Z)Ljava/lang/StringBuffer;
L2821:  ldc ", "
L2823:  invokevirtual Method java/lang/StringBuffer append (Ljava/lang/String;)Ljava/lang/StringBuffer;
L2826:  iload_3
L2827:  invokevirtual Method java/lang/StringBuffer append (I)Ljava/lang/StringBuffer;
L2830:  ldc ", "
L2832:  invokevirtual Method java/lang/StringBuffer append (Ljava/lang/String;)Ljava/lang/StringBuffer;
L2835:  iload 4
L2837:  invokevirtual Method java/lang/StringBuffer append (I)Ljava/lang/StringBuffer;
L2840:  ldc ", "
L2842:  invokevirtual Method java/lang/StringBuffer append (Ljava/lang/String;)Ljava/lang/StringBuffer;
L2845:  iload 5
L2847:  invokevirtual Method java/lang/StringBuffer append (I)Ljava/lang/StringBuffer;
L2850:  ldc ", "
L2852:  invokevirtual Method java/lang/StringBuffer append (Ljava/lang/String;)Ljava/lang/StringBuffer;
L2855:  iload 6
L2857:  invokevirtual Method java/lang/StringBuffer append (I)Ljava/lang/StringBuffer;
L2860:  ldc ", "
L2862:  invokevirtual Method java/lang/StringBuffer append (Ljava/lang/String;)Ljava/lang/StringBuffer;
L2865:  aload 7
L2867:  invokevirtual Method java/lang/StringBuffer append (Ljava/lang/Object;)Ljava/lang/StringBuffer;
L2870:  ldc ", "
L2872:  invokevirtual Method java/lang/StringBuffer append (Ljava/lang/String;)Ljava/lang/StringBuffer;
L2875:  aload 8
L2877:  invokevirtual Method java/lang/StringBuffer append (Ljava/lang/Object;)Ljava/lang/StringBuffer;
L2880:  ldc ", "
L2882:  invokevirtual Method java/lang/StringBuffer append (Ljava/lang/String;)Ljava/lang/StringBuffer;
L2885:  iload 9
L2887:  invokevirtual Method java/lang/StringBuffer append (I)Ljava/lang/StringBuffer;
L2890:  ldc ", "
L2892:  invokevirtual Method java/lang/StringBuffer append (Ljava/lang/String;)Ljava/lang/StringBuffer;
L2895:  iload 10
L2897:  invokevirtual Method java/lang/StringBuffer append (I)Ljava/lang/StringBuffer;
L2900:  ldc ", "
L2902:  invokevirtual Method java/lang/StringBuffer append (Ljava/lang/String;)Ljava/lang/StringBuffer;
L2905:  aload 11
L2907:  invokevirtual Method java/lang/Throwable toString ()Ljava/lang/String;
L2910:  invokevirtual Method java/lang/StringBuffer append (Ljava/lang/String;)Ljava/lang/StringBuffer;
L2913:  invokevirtual Method java/lang/StringBuffer toString ()Ljava/lang/String;
L2916:  invokestatic Method sign/signlink reporterror (Ljava/lang/String;)V
L2919:  new java/lang/RuntimeException
L2922:  dup
L2923:  invokespecial Method java/lang/RuntimeException <init> ()V
L2926:  athrow
L2927:  return
L2928:  
    .end code
.end method

.method public final a : (Lr;I[Lec;)V
    .code stack 22 locals 46
L0:     getstatic Field dc c Z
L3:     istore 45
        .catch java/lang/RuntimeException from L5 to L3287 using L3288
L5:     iconst_0
L6:     istore 4
L8:     iload 45
L10:    ifeq L114
L13:    iconst_0
L14:    istore 5
L16:    iload 45
L18:    ifeq L104
L21:    iconst_0
L22:    istore 6
L24:    iload 45
L26:    ifeq L94
L29:    aload_0
L30:    getfield Field c j [[[B
L33:    iload 4
L35:    aaload
L36:    iload 5
L38:    aaload
L39:    iload 6
L41:    baload
L42:    iconst_1
L43:    iand
L44:    iconst_1
L45:    if_icmpne L91
L48:    iload 4
L50:    istore 7
L52:    aload_0
L53:    getfield Field c j [[[B
L56:    iconst_1
L57:    aaload
L58:    iload 5
L60:    aaload
L61:    iload 6
L63:    baload
L64:    iconst_2
L65:    iand
L66:    iconst_2
L67:    if_icmpne L73
L70:    iinc 7 -1
L73:    iload 7
L75:    iflt L91
L78:    aload_3
L79:    iload 7
L81:    aaload
L82:    bipush 12
L84:    iload 6
L86:    iload 5
L88:    invokevirtual Method ec a (BII)V
L91:    iinc 6 1
L94:    iload 6
L96:    bipush 104
L98:    if_icmplt L29
L101:   iinc 5 1
L104:   iload 5
L106:   bipush 104
L108:   if_icmplt L21
L111:   iinc 4 1
L114:   iload 4
L116:   iconst_4
L117:   if_icmplt L13
L120:   getstatic Field c A I
L123:   invokestatic Method java/lang/Math random ()D
L126:   ldc2_w 5e0
L129:   dmul
L130:   d2i
L131:   iconst_2
L132:   isub
L133:   iadd
L134:   putstatic Field c A I
L137:   getstatic Field c A I
L140:   bipush -8
L142:   if_icmpge L150
L145:   bipush -8
L147:   putstatic Field c A I
L150:   getstatic Field c A I
L153:   bipush 8
L155:   if_icmple L163
L158:   bipush 8
L160:   putstatic Field c A I
L163:   getstatic Field c B I
L166:   invokestatic Method java/lang/Math random ()D
L169:   ldc2_w 5e0
L172:   dmul
L173:   d2i
L174:   iconst_2
L175:   isub
L176:   iadd
L177:   putstatic Field c B I
L180:   getstatic Field c B I
L183:   bipush -16
L185:   if_icmpge L193
L188:   bipush -16
L190:   putstatic Field c B I
L193:   getstatic Field c B I
L196:   bipush 16
L198:   if_icmple L206
L201:   bipush 16
L203:   putstatic Field c B I
L206:   iconst_0
L207:   istore 5
L209:   iload 45
L211:   ifeq L1928
L214:   aload_0
L215:   getfield Field c o [[[B
L218:   iload 5
L220:   aaload
L221:   astore 6
L223:   bipush 96
L225:   istore 7
L227:   sipush 768
L230:   istore 8
L232:   bipush -50
L234:   istore 9
L236:   bipush -10
L238:   istore 10
L240:   bipush -50
L242:   istore 11
L244:   iload 9
L246:   iload 9
L248:   imul
L249:   iload 10
L251:   iload 10
L253:   imul
L254:   iadd
L255:   iload 11
L257:   iload 11
L259:   imul
L260:   iadd
L261:   i2d
L262:   invokestatic Method java/lang/Math sqrt (D)D
L265:   d2i
L266:   istore 12
L268:   iload 8
L270:   iload 12
L272:   imul
L273:   bipush 8
L275:   ishr
L276:   istore 13
L278:   iconst_1
L279:   istore 14
L281:   iload 45
L283:   ifeq L529
L286:   iconst_1
L287:   istore 15
L289:   iload 45
L291:   ifeq L515
L294:   aload_0
L295:   getfield Field c i [[[I
L298:   iload 5
L300:   aaload
L301:   iload 15
L303:   iconst_1
L304:   iadd
L305:   aaload
L306:   iload 14
L308:   iaload
L309:   aload_0
L310:   getfield Field c i [[[I
L313:   iload 5
L315:   aaload
L316:   iload 15
L318:   iconst_1
L319:   isub
L320:   aaload
L321:   iload 14
L323:   iaload
L324:   isub
L325:   istore 16
L327:   aload_0
L328:   getfield Field c i [[[I
L331:   iload 5
L333:   aaload
L334:   iload 15
L336:   aaload
L337:   iload 14
L339:   iconst_1
L340:   iadd
L341:   iaload
L342:   aload_0
L343:   getfield Field c i [[[I
L346:   iload 5
L348:   aaload
L349:   iload 15
L351:   aaload
L352:   iload 14
L354:   iconst_1
L355:   isub
L356:   iaload
L357:   isub
L358:   istore 17
L360:   iload 16
L362:   iload 16
L364:   imul
L365:   ldc 65536
L367:   iadd
L368:   iload 17
L370:   iload 17
L372:   imul
L373:   iadd
L374:   i2d
L375:   invokestatic Method java/lang/Math sqrt (D)D
L378:   d2i
L379:   istore 18
L381:   iload 16
L383:   bipush 8
L385:   ishl
L386:   iload 18
L388:   idiv
L389:   istore 19
L391:   ldc 65536
L393:   iload 18
L395:   idiv
L396:   istore 20
L398:   iload 17
L400:   bipush 8
L402:   ishl
L403:   iload 18
L405:   idiv
L406:   istore 21
L408:   iload 7
L410:   iload 9
L412:   iload 19
L414:   imul
L415:   iload 10
L417:   iload 20
L419:   imul
L420:   iadd
L421:   iload 11
L423:   iload 21
L425:   imul
L426:   iadd
L427:   iload 13
L429:   idiv
L430:   iadd
L431:   istore 22
L433:   aload 6
L435:   iload 15
L437:   iconst_1
L438:   isub
L439:   aaload
L440:   iload 14
L442:   baload
L443:   iconst_2
L444:   ishr
L445:   aload 6
L447:   iload 15
L449:   iconst_1
L450:   iadd
L451:   aaload
L452:   iload 14
L454:   baload
L455:   iconst_3
L456:   ishr
L457:   iadd
L458:   aload 6
L460:   iload 15
L462:   aaload
L463:   iload 14
L465:   iconst_1
L466:   isub
L467:   baload
L468:   iconst_2
L469:   ishr
L470:   iadd
L471:   aload 6
L473:   iload 15
L475:   aaload
L476:   iload 14
L478:   iconst_1
L479:   iadd
L480:   baload
L481:   iconst_3
L482:   ishr
L483:   iadd
L484:   aload 6
L486:   iload 15
L488:   aaload
L489:   iload 14
L491:   baload
L492:   iconst_1
L493:   ishr
L494:   iadd
L495:   istore 23
L497:   aload_0
L498:   getfield Field c p [[I
L501:   iload 15
L503:   aaload
L504:   iload 14
L506:   iload 22
L508:   iload 23
L510:   isub
L511:   iastore
L512:   iinc 15 1
L515:   iload 15
L517:   aload_0
L518:   getfield Field c g I
L521:   iconst_1
L522:   isub
L523:   if_icmplt L294
L526:   iinc 14 1
L529:   iload 14
L531:   aload_0
L532:   getfield Field c h I
L535:   iconst_1
L536:   isub
L537:   if_icmplt L286
L540:   iconst_0
L541:   istore 15
L543:   iload 45
L545:   ifeq L591
L548:   aload_0
L549:   getfield Field c q [I
L552:   iload 15
L554:   iconst_0
L555:   iastore
L556:   aload_0
L557:   getfield Field c r [I
L560:   iload 15
L562:   iconst_0
L563:   iastore
L564:   aload_0
L565:   getfield Field c s [I
L568:   iload 15
L570:   iconst_0
L571:   iastore
L572:   aload_0
L573:   getfield Field c t [I
L576:   iload 15
L578:   iconst_0
L579:   iastore
L580:   aload_0
L581:   getfield Field c u [I
L584:   iload 15
L586:   iconst_0
L587:   iastore
L588:   iinc 15 1
L591:   iload 15
L593:   aload_0
L594:   getfield Field c h I
L597:   if_icmplt L548
L600:   bipush -5
L602:   istore 16
L604:   iload 45
L606:   ifeq L1848
L609:   iconst_0
L610:   istore 17
L612:   iload 45
L614:   ifeq L870
L617:   iload 16
L619:   iconst_5
L620:   iadd
L621:   istore 18
L623:   iload 18
L625:   iflt L742
L628:   iload 18
L630:   aload_0
L631:   getfield Field c g I
L634:   if_icmpge L742
L637:   aload_0
L638:   getfield Field c k [[[B
L641:   iload 5
L643:   aaload
L644:   iload 18
L646:   aaload
L647:   iload 17
L649:   baload
L650:   sipush 255
L653:   iand
L654:   istore 19
L656:   iload 19
L658:   ifle L742
L661:   getstatic Field fc d [Lfc;
L664:   iload 19
L666:   iconst_1
L667:   isub
L668:   aaload
L669:   astore 20
L671:   aload_0
L672:   getfield Field c q [I
L675:   iload 17
L677:   dup2
L678:   iaload
L679:   aload 20
L681:   getfield Field fc m I
L684:   iadd
L685:   iastore
L686:   aload_0
L687:   getfield Field c r [I
L690:   iload 17
L692:   dup2
L693:   iaload
L694:   aload 20
L696:   getfield Field fc k I
L699:   iadd
L700:   iastore
L701:   aload_0
L702:   getfield Field c s [I
L705:   iload 17
L707:   dup2
L708:   iaload
L709:   aload 20
L711:   getfield Field fc l I
L714:   iadd
L715:   iastore
L716:   aload_0
L717:   getfield Field c t [I
L720:   iload 17
L722:   dup2
L723:   iaload
L724:   aload 20
L726:   getfield Field fc n I
L729:   iadd
L730:   iastore
L731:   aload_0
L732:   getfield Field c u [I
L735:   iload 17
L737:   dup2
L738:   iaload
L739:   iconst_1
L740:   iadd
L741:   iastore
L742:   iload 16
L744:   iconst_5
L745:   isub
L746:   istore 19
L748:   iload 19
L750:   iflt L867
L753:   iload 19
L755:   aload_0
L756:   getfield Field c g I
L759:   if_icmpge L867
L762:   aload_0
L763:   getfield Field c k [[[B
L766:   iload 5
L768:   aaload
L769:   iload 19
L771:   aaload
L772:   iload 17
L774:   baload
L775:   sipush 255
L778:   iand
L779:   istore 20
L781:   iload 20
L783:   ifle L867
L786:   getstatic Field fc d [Lfc;
L789:   iload 20
L791:   iconst_1
L792:   isub
L793:   aaload
L794:   astore 21
L796:   aload_0
L797:   getfield Field c q [I
L800:   iload 17
L802:   dup2
L803:   iaload
L804:   aload 21
L806:   getfield Field fc m I
L809:   isub
L810:   iastore
L811:   aload_0
L812:   getfield Field c r [I
L815:   iload 17
L817:   dup2
L818:   iaload
L819:   aload 21
L821:   getfield Field fc k I
L824:   isub
L825:   iastore
L826:   aload_0
L827:   getfield Field c s [I
L830:   iload 17
L832:   dup2
L833:   iaload
L834:   aload 21
L836:   getfield Field fc l I
L839:   isub
L840:   iastore
L841:   aload_0
L842:   getfield Field c t [I
L845:   iload 17
L847:   dup2
L848:   iaload
L849:   aload 21
L851:   getfield Field fc n I
L854:   isub
L855:   iastore
L856:   aload_0
L857:   getfield Field c u [I
L860:   iload 17
L862:   dup2
L863:   iaload
L864:   iconst_1
L865:   isub
L866:   iastore
L867:   iinc 17 1
L870:   iload 17
L872:   aload_0
L873:   getfield Field c h I
L876:   if_icmplt L617
L879:   iload 16
L881:   iconst_1
L882:   if_icmplt L1845
L885:   iload 16
L887:   aload_0
L888:   getfield Field c g I
L891:   iconst_1
L892:   isub
L893:   if_icmpge L1845
L896:   iconst_0
L897:   istore 18
L899:   iconst_0
L900:   istore 19
L902:   iconst_0
L903:   istore 20
L905:   iconst_0
L906:   istore 21
L908:   iconst_0
L909:   istore 22
L911:   bipush -5
L913:   istore 23
L915:   iload 45
L917:   ifeq L1834
L920:   iload 23
L922:   iconst_5
L923:   iadd
L924:   istore 24
L926:   iload 24
L928:   iflt L1000
L931:   iload 24
L933:   aload_0
L934:   getfield Field c h I
L937:   if_icmpge L1000
L940:   iload 18
L942:   aload_0
L943:   getfield Field c q [I
L946:   iload 24
L948:   iaload
L949:   iadd
L950:   istore 18
L952:   iload 19
L954:   aload_0
L955:   getfield Field c r [I
L958:   iload 24
L960:   iaload
L961:   iadd
L962:   istore 19
L964:   iload 20
L966:   aload_0
L967:   getfield Field c s [I
L970:   iload 24
L972:   iaload
L973:   iadd
L974:   istore 20
L976:   iload 21
L978:   aload_0
L979:   getfield Field c t [I
L982:   iload 24
L984:   iaload
L985:   iadd
L986:   istore 21
L988:   iload 22
L990:   aload_0
L991:   getfield Field c u [I
L994:   iload 24
L996:   iaload
L997:   iadd
L998:   istore 22
L1000:  iload 23
L1002:  iconst_5
L1003:  isub
L1004:  istore 25
L1006:  iload 25
L1008:  iflt L1080
L1011:  iload 25
L1013:  aload_0
L1014:  getfield Field c h I
L1017:  if_icmpge L1080
L1020:  iload 18
L1022:  aload_0
L1023:  getfield Field c q [I
L1026:  iload 25
L1028:  iaload
L1029:  isub
L1030:  istore 18
L1032:  iload 19
L1034:  aload_0
L1035:  getfield Field c r [I
L1038:  iload 25
L1040:  iaload
L1041:  isub
L1042:  istore 19
L1044:  iload 20
L1046:  aload_0
L1047:  getfield Field c s [I
L1050:  iload 25
L1052:  iaload
L1053:  isub
L1054:  istore 20
L1056:  iload 21
L1058:  aload_0
L1059:  getfield Field c t [I
L1062:  iload 25
L1064:  iaload
L1065:  isub
L1066:  istore 21
L1068:  iload 22
L1070:  aload_0
L1071:  getfield Field c u [I
L1074:  iload 25
L1076:  iaload
L1077:  isub
L1078:  istore 22
L1080:  iload 23
L1082:  iconst_1
L1083:  if_icmplt L1831
L1086:  iload 23
L1088:  aload_0
L1089:  getfield Field c h I
L1092:  iconst_1
L1093:  isub
L1094:  if_icmpge L1831
L1097:  getstatic Field c d Z
L1100:  ifeq L1143
L1103:  aload_0
L1104:  getfield Field c j [[[B
L1107:  iload 5
L1109:  aaload
L1110:  iload 16
L1112:  aaload
L1113:  iload 23
L1115:  baload
L1116:  bipush 16
L1118:  iand
L1119:  ifne L1831
L1122:  aload_0
L1123:  iload 5
L1125:  bipush 10
L1127:  iload 16
L1129:  iload 23
L1131:  invokevirtual Method c a (IBII)I
L1134:  getstatic Field c e I
L1137:  if_icmpeq L1143
L1140:  goto L1831
L1143:  aload_0
L1144:  getfield Field c k [[[B
L1147:  iload 5
L1149:  aaload
L1150:  iload 16
L1152:  aaload
L1153:  iload 23
L1155:  baload
L1156:  sipush 255
L1159:  iand
L1160:  istore 26
L1162:  aload_0
L1163:  getfield Field c l [[[B
L1166:  iload 5
L1168:  aaload
L1169:  iload 16
L1171:  aaload
L1172:  iload 23
L1174:  baload
L1175:  sipush 255
L1178:  iand
L1179:  istore 27
L1181:  iload 26
L1183:  ifgt L1191
L1186:  iload 27
L1188:  ifle L1831
L1191:  aload_0
L1192:  getfield Field c i [[[I
L1195:  iload 5
L1197:  aaload
L1198:  iload 16
L1200:  aaload
L1201:  iload 23
L1203:  iaload
L1204:  istore 28
L1206:  aload_0
L1207:  getfield Field c i [[[I
L1210:  iload 5
L1212:  aaload
L1213:  iload 16
L1215:  iconst_1
L1216:  iadd
L1217:  aaload
L1218:  iload 23
L1220:  iaload
L1221:  istore 29
L1223:  aload_0
L1224:  getfield Field c i [[[I
L1227:  iload 5
L1229:  aaload
L1230:  iload 16
L1232:  iconst_1
L1233:  iadd
L1234:  aaload
L1235:  iload 23
L1237:  iconst_1
L1238:  iadd
L1239:  iaload
L1240:  istore 30
L1242:  aload_0
L1243:  getfield Field c i [[[I
L1246:  iload 5
L1248:  aaload
L1249:  iload 16
L1251:  aaload
L1252:  iload 23
L1254:  iconst_1
L1255:  iadd
L1256:  iaload
L1257:  istore 31
L1259:  aload_0
L1260:  getfield Field c p [[I
L1263:  iload 16
L1265:  aaload
L1266:  iload 23
L1268:  iaload
L1269:  istore 32
L1271:  aload_0
L1272:  getfield Field c p [[I
L1275:  iload 16
L1277:  iconst_1
L1278:  iadd
L1279:  aaload
L1280:  iload 23
L1282:  iaload
L1283:  istore 33
L1285:  aload_0
L1286:  getfield Field c p [[I
L1289:  iload 16
L1291:  iconst_1
L1292:  iadd
L1293:  aaload
L1294:  iload 23
L1296:  iconst_1
L1297:  iadd
L1298:  iaload
L1299:  istore 34
L1301:  aload_0
L1302:  getfield Field c p [[I
L1305:  iload 16
L1307:  aaload
L1308:  iload 23
L1310:  iconst_1
L1311:  iadd
L1312:  iaload
L1313:  istore 35
L1315:  iconst_m1
L1316:  istore 36
L1318:  iconst_m1
L1319:  istore 37
L1321:  iload 26
L1323:  ifle L1421
L1326:  iload 18
L1328:  sipush 256
L1331:  imul
L1332:  iload 21
L1334:  idiv
L1335:  istore 38
L1337:  iload 19
L1339:  iload 22
L1341:  idiv
L1342:  istore 39
L1344:  iload 20
L1346:  iload 22
L1348:  idiv
L1349:  istore 40
L1351:  aload_0
L1352:  iload 38
L1354:  iload 39
L1356:  iload 40
L1358:  invokespecial Method c b (III)I
L1361:  istore 36
L1363:  iload 38
L1365:  getstatic Field c A I
L1368:  iadd
L1369:  sipush 255
L1372:  iand
L1373:  istore 38
L1375:  iload 40
L1377:  getstatic Field c B I
L1380:  iadd
L1381:  istore 40
L1383:  iload 40
L1385:  ifge L1396
L1388:  iconst_0
L1389:  istore 40
L1391:  iload 45
L1393:  ifeq L1409
L1396:  iload 40
L1398:  sipush 255
L1401:  if_icmple L1409
L1404:  sipush 255
L1407:  istore 40
L1409:  aload_0
L1410:  iload 38
L1412:  iload 39
L1414:  iload 40
L1416:  invokespecial Method c b (III)I
L1419:  istore 37
L1421:  iload 5
L1423:  ifle L1520
L1426:  iconst_1
L1427:  istore 38
L1429:  iload 26
L1431:  ifne L1453
L1434:  aload_0
L1435:  getfield Field c m [[[B
L1438:  iload 5
L1440:  aaload
L1441:  iload 16
L1443:  aaload
L1444:  iload 23
L1446:  baload
L1447:  ifeq L1453
L1450:  iconst_0
L1451:  istore 38
L1453:  iload 27
L1455:  ifle L1475
L1458:  getstatic Field fc d [Lfc;
L1461:  iload 27
L1463:  iconst_1
L1464:  isub
L1465:  aaload
L1466:  getfield Field fc h Z
L1469:  ifne L1475
L1472:  iconst_0
L1473:  istore 38
L1475:  iload 38
L1477:  ifeq L1520
L1480:  iload 28
L1482:  iload 29
L1484:  if_icmpne L1520
L1487:  iload 28
L1489:  iload 30
L1491:  if_icmpne L1520
L1494:  iload 28
L1496:  iload 31
L1498:  if_icmpne L1520
L1501:  aload_0
L1502:  getfield Field c v [[[I
L1505:  iload 5
L1507:  aaload
L1508:  iload 16
L1510:  aaload
L1511:  iload 23
L1513:  dup2
L1514:  iaload
L1515:  sipush 2340
L1518:  ior
L1519:  iastore
L1520:  iconst_0
L1521:  istore 38
L1523:  iload 36
L1525:  iconst_m1
L1526:  if_icmpeq L1542
L1529:  getstatic Field gb V [I
L1532:  iload 37
L1534:  bipush 96
L1536:  invokestatic Method c d (II)I
L1539:  iaload
L1540:  istore 38
L1542:  iload 27
L1544:  ifne L1608
L1547:  aload_1
L1548:  iload 5
L1550:  iload 16
L1552:  iload 23
L1554:  iconst_0
L1555:  iconst_0
L1556:  iconst_m1
L1557:  iload 28
L1559:  iload 29
L1561:  iload 30
L1563:  iload 31
L1565:  iload 36
L1567:  iload 32
L1569:  invokestatic Method c d (II)I
L1572:  iload 36
L1574:  iload 33
L1576:  invokestatic Method c d (II)I
L1579:  iload 36
L1581:  iload 34
L1583:  invokestatic Method c d (II)I
L1586:  iload 36
L1588:  iload 35
L1590:  invokestatic Method c d (II)I
L1593:  iconst_0
L1594:  iconst_0
L1595:  iconst_0
L1596:  iconst_0
L1597:  iload 38
L1599:  iconst_0
L1600:  invokevirtual Method r a (IIIIIIIIIIIIIIIIIIII)V
L1603:  iload 45
L1605:  ifeq L1831
L1608:  aload_0
L1609:  getfield Field c m [[[B
L1612:  iload 5
L1614:  aaload
L1615:  iload 16
L1617:  aaload
L1618:  iload 23
L1620:  baload
L1621:  iconst_1
L1622:  iadd
L1623:  istore 39
L1625:  aload_0
L1626:  getfield Field c n [[[B
L1629:  iload 5
L1631:  aaload
L1632:  iload 16
L1634:  aaload
L1635:  iload 23
L1637:  baload
L1638:  istore 40
L1640:  getstatic Field fc d [Lfc;
L1643:  iload 27
L1645:  iconst_1
L1646:  isub
L1647:  aaload
L1648:  astore 41
L1650:  aload 41
L1652:  getfield Field fc f I
L1655:  istore 42
L1657:  iload 42
L1659:  iflt L1680
L1662:  sipush 787
L1665:  iload 42
L1667:  invokestatic Method gb b (II)I
L1670:  istore 44
L1672:  iconst_m1
L1673:  istore 43
L1675:  iload 45
L1677:  ifeq L1743
L1680:  aload 41
L1682:  getfield Field fc e I
L1685:  ldc 16711935
L1687:  if_icmpne L1705
L1690:  iconst_0
L1691:  istore 44
L1693:  bipush -2
L1695:  istore 43
L1697:  iconst_m1
L1698:  istore 42
L1700:  iload 45
L1702:  ifeq L1743
L1705:  aload_0
L1706:  aload 41
L1708:  getfield Field fc j I
L1711:  aload 41
L1713:  getfield Field fc k I
L1716:  aload 41
L1718:  getfield Field fc l I
L1721:  invokespecial Method c b (III)I
L1724:  istore 43
L1726:  getstatic Field gb V [I
L1729:  aload_0
L1730:  aload 41
L1732:  getfield Field fc o I
L1735:  bipush 96
L1737:  invokespecial Method c e (II)I
L1740:  iaload
L1741:  istore 44
L1743:  aload_1
L1744:  iload 5
L1746:  iload 16
L1748:  iload 23
L1750:  iload 39
L1752:  iload 40
L1754:  iload 42
L1756:  iload 28
L1758:  iload 29
L1760:  iload 30
L1762:  iload 31
L1764:  iload 36
L1766:  iload 32
L1768:  invokestatic Method c d (II)I
L1771:  iload 36
L1773:  iload 33
L1775:  invokestatic Method c d (II)I
L1778:  iload 36
L1780:  iload 34
L1782:  invokestatic Method c d (II)I
L1785:  iload 36
L1787:  iload 35
L1789:  invokestatic Method c d (II)I
L1792:  aload_0
L1793:  iload 43
L1795:  iload 32
L1797:  invokespecial Method c e (II)I
L1800:  aload_0
L1801:  iload 43
L1803:  iload 33
L1805:  invokespecial Method c e (II)I
L1808:  aload_0
L1809:  iload 43
L1811:  iload 34
L1813:  invokespecial Method c e (II)I
L1816:  aload_0
L1817:  iload 43
L1819:  iload 35
L1821:  invokespecial Method c e (II)I
L1824:  iload 38
L1826:  iload 44
L1828:  invokevirtual Method r a (IIIIIIIIIIIIIIIIIIII)V
L1831:  iinc 23 1
L1834:  iload 23
L1836:  aload_0
L1837:  getfield Field c h I
L1840:  iconst_5
L1841:  iadd
L1842:  if_icmplt L920
L1845:  iinc 16 1
L1848:  iload 16
L1850:  aload_0
L1851:  getfield Field c g I
L1854:  iconst_5
L1855:  iadd
L1856:  if_icmplt L609
L1859:  iconst_1
L1860:  istore 17
L1862:  iload 45
L1864:  ifeq L1914
L1867:  iconst_1
L1868:  istore 18
L1870:  iload 45
L1872:  ifeq L1900
L1875:  aload_1
L1876:  iload 5
L1878:  iload 18
L1880:  iload 17
L1882:  aload_0
L1883:  iload 5
L1885:  bipush 10
L1887:  iload 18
L1889:  iload 17
L1891:  invokevirtual Method c a (IBII)I
L1894:  invokevirtual Method r a (IIII)V
L1897:  iinc 18 1
L1900:  iload 18
L1902:  aload_0
L1903:  getfield Field c g I
L1906:  iconst_1
L1907:  isub
L1908:  if_icmplt L1875
L1911:  iinc 17 1
L1914:  iload 17
L1916:  aload_0
L1917:  getfield Field c h I
L1920:  iconst_1
L1921:  isub
L1922:  if_icmplt L1867
L1925:  iinc 5 1
L1928:  iload 5
L1930:  iconst_4
L1931:  if_icmplt L214
L1934:  iload 45
L1936:  ifeq L1955
L1939:  iconst_1
L1940:  istore 6
L1942:  iload 45
L1944:  ifeq L1950
L1947:  iinc 6 1
L1950:  iload 6
L1952:  ifgt L1947
L1955:  iload_2
L1956:  ifge L1939
L1959:  getstatic Field c f Z
L1962:  ifne L1981
L1965:  aload_1
L1966:  bipush -10
L1968:  bipush 64
L1970:  bipush -50
L1972:  sipush 768
L1975:  bipush -50
L1977:  iconst_0
L1978:  invokevirtual Method r a (IIIIIZ)V
L1981:  iconst_0
L1982:  istore 6
L1984:  iload 45
L1986:  ifeq L2040
L1989:  iconst_0
L1990:  istore 7
L1992:  iload 45
L1994:  ifeq L2028
L1997:  aload_0
L1998:  getfield Field c j [[[B
L2001:  iconst_1
L2002:  aaload
L2003:  iload 6
L2005:  aaload
L2006:  iload 7
L2008:  baload
L2009:  iconst_2
L2010:  iand
L2011:  iconst_2
L2012:  if_icmpne L2025
L2015:  aload_1
L2016:  iload 7
L2018:  iload 6
L2020:  bipush -41
L2022:  invokevirtual Method r a (IIB)V
L2025:  iinc 7 1
L2028:  iload 7
L2030:  aload_0
L2031:  getfield Field c h I
L2034:  if_icmplt L1997
L2037:  iinc 6 1
L2040:  iload 6
L2042:  aload_0
L2043:  getfield Field c g I
L2046:  if_icmplt L1989
L2049:  getstatic Field c f Z
L2052:  ifeq L2056
L2055:  return
L2056:  iconst_1
L2057:  istore 7
L2059:  iconst_2
L2060:  istore 8
L2062:  iconst_4
L2063:  istore 9
L2065:  iconst_0
L2066:  istore 10
L2068:  iload 45
L2070:  ifeq L3281
L2073:  iload 10
L2075:  ifle L2096
L2078:  iload 7
L2080:  iconst_3
L2081:  ishl
L2082:  istore 7
L2084:  iload 8
L2086:  iconst_3
L2087:  ishl
L2088:  istore 8
L2090:  iload 9
L2092:  iconst_3
L2093:  ishl
L2094:  istore 9
L2096:  iconst_0
L2097:  istore 11
L2099:  iload 45
L2101:  ifeq L3271
L2104:  iconst_0
L2105:  istore 12
L2107:  iload 45
L2109:  ifeq L3259
L2112:  iconst_0
L2113:  istore 13
L2115:  iload 45
L2117:  ifeq L3247
L2120:  aload_0
L2121:  getfield Field c v [[[I
L2124:  iload 11
L2126:  aaload
L2127:  iload 13
L2129:  aaload
L2130:  iload 12
L2132:  iaload
L2133:  iload 7
L2135:  iand
L2136:  ifeq L2502
L2139:  iload 12
L2141:  istore 14
L2143:  iload 12
L2145:  istore 15
L2147:  iload 11
L2149:  istore 16
L2151:  iload 11
L2153:  istore 17
L2155:  iload 45
L2157:  ifeq L2163
L2160:  iinc 14 -1
L2163:  iload 14
L2165:  ifle L2197
L2168:  aload_0
L2169:  getfield Field c v [[[I
L2172:  iload 11
L2174:  aaload
L2175:  iload 13
L2177:  aaload
L2178:  iload 14
L2180:  iconst_1
L2181:  isub
L2182:  iaload
L2183:  iload 7
L2185:  iand
L2186:  ifne L2160
L2189:  iload 45
L2191:  ifeq L2197
L2194:  iinc 15 1
L2197:  iload 15
L2199:  aload_0
L2200:  getfield Field c h I
L2203:  if_icmpge L2278
L2206:  aload_0
L2207:  getfield Field c v [[[I
L2210:  iload 11
L2212:  aaload
L2213:  iload 13
L2215:  aaload
L2216:  iload 15
L2218:  iconst_1
L2219:  iadd
L2220:  iaload
L2221:  iload 7
L2223:  iand
L2224:  ifne L2194
L2227:  iload 45
L2229:  ifeq L2278
L2232:  iload 14
L2234:  istore 18
L2236:  iload 45
L2238:  ifeq L2268
L2241:  aload_0
L2242:  getfield Field c v [[[I
L2245:  iload 16
L2247:  iconst_1
L2248:  isub
L2249:  aaload
L2250:  iload 13
L2252:  aaload
L2253:  iload 18
L2255:  iaload
L2256:  iload 7
L2258:  iand
L2259:  ifne L2265
L2262:  goto L2334
L2265:  iinc 18 1
L2268:  iload 18
L2270:  iload 15
L2272:  if_icmple L2241
L2275:  iinc 16 -1
L2278:  iload 16
L2280:  ifgt L2232
L2283:  iload 45
L2285:  ifeq L2334
L2288:  iload 14
L2290:  istore 18
L2292:  iload 45
L2294:  ifeq L2324
L2297:  aload_0
L2298:  getfield Field c v [[[I
L2301:  iload 17
L2303:  iconst_1
L2304:  iadd
L2305:  aaload
L2306:  iload 13
L2308:  aaload
L2309:  iload 18
L2311:  iaload
L2312:  iload 7
L2314:  iand
L2315:  ifne L2321
L2318:  goto L2341
L2321:  iinc 18 1
L2324:  iload 18
L2326:  iload 15
L2328:  if_icmple L2297
L2331:  iinc 17 1
L2334:  iload 17
L2336:  iload 10
L2338:  if_icmplt L2288
L2341:  iload 17
L2343:  iconst_1
L2344:  iadd
L2345:  iload 16
L2347:  isub
L2348:  iload 15
L2350:  iload 14
L2352:  isub
L2353:  iconst_1
L2354:  iadd
L2355:  imul
L2356:  istore 18
L2358:  iload 18
L2360:  bipush 8
L2362:  if_icmplt L2502
L2365:  sipush 240
L2368:  istore 19
L2370:  aload_0
L2371:  getfield Field c i [[[I
L2374:  iload 17
L2376:  aaload
L2377:  iload 13
L2379:  aaload
L2380:  iload 14
L2382:  iaload
L2383:  iload 19
L2385:  isub
L2386:  istore 20
L2388:  aload_0
L2389:  getfield Field c i [[[I
L2392:  iload 16
L2394:  aaload
L2395:  iload 13
L2397:  aaload
L2398:  iload 14
L2400:  iaload
L2401:  istore 21
L2403:  iload 15
L2405:  sipush 128
L2408:  imul
L2409:  sipush 128
L2412:  iadd
L2413:  iload 13
L2415:  sipush 128
L2418:  imul
L2419:  sipush -802
L2422:  iload 21
L2424:  iconst_1
L2425:  iload 13
L2427:  sipush 128
L2430:  imul
L2431:  iload 10
L2433:  iload 20
L2435:  iload 14
L2437:  sipush 128
L2440:  imul
L2441:  invokestatic Method r a (IIIIIIIII)V
L2444:  iload 16
L2446:  istore 22
L2448:  iload 45
L2450:  ifeq L2495
L2453:  iload 14
L2455:  istore 23
L2457:  iload 45
L2459:  ifeq L2485
L2462:  aload_0
L2463:  getfield Field c v [[[I
L2466:  iload 22
L2468:  aaload
L2469:  iload 13
L2471:  aaload
L2472:  iload 23
L2474:  dup2
L2475:  iaload
L2476:  iload 7
L2478:  iconst_m1
L2479:  ixor
L2480:  iand
L2481:  iastore
L2482:  iinc 23 1
L2485:  iload 23
L2487:  iload 15
L2489:  if_icmple L2462
L2492:  iinc 22 1
L2495:  iload 22
L2497:  iload 17
L2499:  if_icmple L2453
L2502:  aload_0
L2503:  getfield Field c v [[[I
L2506:  iload 11
L2508:  aaload
L2509:  iload 13
L2511:  aaload
L2512:  iload 12
L2514:  iaload
L2515:  iload 8
L2517:  iand
L2518:  ifeq L2884
L2521:  iload 13
L2523:  istore 14
L2525:  iload 13
L2527:  istore 15
L2529:  iload 11
L2531:  istore 16
L2533:  iload 11
L2535:  istore 17
L2537:  iload 45
L2539:  ifeq L2545
L2542:  iinc 14 -1
L2545:  iload 14
L2547:  ifle L2579
L2550:  aload_0
L2551:  getfield Field c v [[[I
L2554:  iload 11
L2556:  aaload
L2557:  iload 14
L2559:  iconst_1
L2560:  isub
L2561:  aaload
L2562:  iload 12
L2564:  iaload
L2565:  iload 8
L2567:  iand
L2568:  ifne L2542
L2571:  iload 45
L2573:  ifeq L2579
L2576:  iinc 15 1
L2579:  iload 15
L2581:  aload_0
L2582:  getfield Field c g I
L2585:  if_icmpge L2660
L2588:  aload_0
L2589:  getfield Field c v [[[I
L2592:  iload 11
L2594:  aaload
L2595:  iload 15
L2597:  iconst_1
L2598:  iadd
L2599:  aaload
L2600:  iload 12
L2602:  iaload
L2603:  iload 8
L2605:  iand
L2606:  ifne L2576
L2609:  iload 45
L2611:  ifeq L2660
L2614:  iload 14
L2616:  istore 18
L2618:  iload 45
L2620:  ifeq L2650
L2623:  aload_0
L2624:  getfield Field c v [[[I
L2627:  iload 16
L2629:  iconst_1
L2630:  isub
L2631:  aaload
L2632:  iload 18
L2634:  aaload
L2635:  iload 12
L2637:  iaload
L2638:  iload 8
L2640:  iand
L2641:  ifne L2647
L2644:  goto L2716
L2647:  iinc 18 1
L2650:  iload 18
L2652:  iload 15
L2654:  if_icmple L2623
L2657:  iinc 16 -1
L2660:  iload 16
L2662:  ifgt L2614
L2665:  iload 45
L2667:  ifeq L2716
L2670:  iload 14
L2672:  istore 18
L2674:  iload 45
L2676:  ifeq L2706
L2679:  aload_0
L2680:  getfield Field c v [[[I
L2683:  iload 17
L2685:  iconst_1
L2686:  iadd
L2687:  aaload
L2688:  iload 18
L2690:  aaload
L2691:  iload 12
L2693:  iaload
L2694:  iload 8
L2696:  iand
L2697:  ifne L2703
L2700:  goto L2723
L2703:  iinc 18 1
L2706:  iload 18
L2708:  iload 15
L2710:  if_icmple L2679
L2713:  iinc 17 1
L2716:  iload 17
L2718:  iload 10
L2720:  if_icmplt L2670
L2723:  iload 17
L2725:  iconst_1
L2726:  iadd
L2727:  iload 16
L2729:  isub
L2730:  iload 15
L2732:  iload 14
L2734:  isub
L2735:  iconst_1
L2736:  iadd
L2737:  imul
L2738:  istore 18
L2740:  iload 18
L2742:  bipush 8
L2744:  if_icmplt L2884
L2747:  sipush 240
L2750:  istore 19
L2752:  aload_0
L2753:  getfield Field c i [[[I
L2756:  iload 17
L2758:  aaload
L2759:  iload 14
L2761:  aaload
L2762:  iload 12
L2764:  iaload
L2765:  iload 19
L2767:  isub
L2768:  istore 20
L2770:  aload_0
L2771:  getfield Field c i [[[I
L2774:  iload 16
L2776:  aaload
L2777:  iload 14
L2779:  aaload
L2780:  iload 12
L2782:  iaload
L2783:  istore 21
L2785:  iload 12
L2787:  sipush 128
L2790:  imul
L2791:  iload 14
L2793:  sipush 128
L2796:  imul
L2797:  sipush -802
L2800:  iload 21
L2802:  iconst_2
L2803:  iload 15
L2805:  sipush 128
L2808:  imul
L2809:  sipush 128
L2812:  iadd
L2813:  iload 10
L2815:  iload 20
L2817:  iload 12
L2819:  sipush 128
L2822:  imul
L2823:  invokestatic Method r a (IIIIIIIII)V
L2826:  iload 16
L2828:  istore 22
L2830:  iload 45
L2832:  ifeq L2877
L2835:  iload 14
L2837:  istore 23
L2839:  iload 45
L2841:  ifeq L2867
L2844:  aload_0
L2845:  getfield Field c v [[[I
L2848:  iload 22
L2850:  aaload
L2851:  iload 23
L2853:  aaload
L2854:  iload 12
L2856:  dup2
L2857:  iaload
L2858:  iload 8
L2860:  iconst_m1
L2861:  ixor
L2862:  iand
L2863:  iastore
L2864:  iinc 23 1
L2867:  iload 23
L2869:  iload 15
L2871:  if_icmple L2844
L2874:  iinc 22 1
L2877:  iload 22
L2879:  iload 17
L2881:  if_icmple L2835
L2884:  aload_0
L2885:  getfield Field c v [[[I
L2888:  iload 11
L2890:  aaload
L2891:  iload 13
L2893:  aaload
L2894:  iload 12
L2896:  iaload
L2897:  iload 9
L2899:  iand
L2900:  ifeq L3244
L2903:  iload 13
L2905:  istore 14
L2907:  iload 13
L2909:  istore 15
L2911:  iload 12
L2913:  istore 16
L2915:  iload 12
L2917:  istore 17
L2919:  iload 45
L2921:  ifeq L2927
L2924:  iinc 16 -1
L2927:  iload 16
L2929:  ifle L2961
L2932:  aload_0
L2933:  getfield Field c v [[[I
L2936:  iload 11
L2938:  aaload
L2939:  iload 13
L2941:  aaload
L2942:  iload 16
L2944:  iconst_1
L2945:  isub
L2946:  iaload
L2947:  iload 9
L2949:  iand
L2950:  ifne L2924
L2953:  iload 45
L2955:  ifeq L2961
L2958:  iinc 17 1
L2961:  iload 17
L2963:  aload_0
L2964:  getfield Field c h I
L2967:  if_icmpge L3042
L2970:  aload_0
L2971:  getfield Field c v [[[I
L2974:  iload 11
L2976:  aaload
L2977:  iload 13
L2979:  aaload
L2980:  iload 17
L2982:  iconst_1
L2983:  iadd
L2984:  iaload
L2985:  iload 9
L2987:  iand
L2988:  ifne L2958
L2991:  iload 45
L2993:  ifeq L3042
L2996:  iload 16
L2998:  istore 18
L3000:  iload 45
L3002:  ifeq L3032
L3005:  aload_0
L3006:  getfield Field c v [[[I
L3009:  iload 11
L3011:  aaload
L3012:  iload 14
L3014:  iconst_1
L3015:  isub
L3016:  aaload
L3017:  iload 18
L3019:  iaload
L3020:  iload 9
L3022:  iand
L3023:  ifne L3029
L3026:  goto L3098
L3029:  iinc 18 1
L3032:  iload 18
L3034:  iload 17
L3036:  if_icmple L3005
L3039:  iinc 14 -1
L3042:  iload 14
L3044:  ifgt L2996
L3047:  iload 45
L3049:  ifeq L3098
L3052:  iload 16
L3054:  istore 18
L3056:  iload 45
L3058:  ifeq L3088
L3061:  aload_0
L3062:  getfield Field c v [[[I
L3065:  iload 11
L3067:  aaload
L3068:  iload 15
L3070:  iconst_1
L3071:  iadd
L3072:  aaload
L3073:  iload 18
L3075:  iaload
L3076:  iload 9
L3078:  iand
L3079:  ifne L3085
L3082:  goto L3107
L3085:  iinc 18 1
L3088:  iload 18
L3090:  iload 17
L3092:  if_icmple L3061
L3095:  iinc 15 1
L3098:  iload 15
L3100:  aload_0
L3101:  getfield Field c g I
L3104:  if_icmplt L3052
L3107:  iload 15
L3109:  iload 14
L3111:  isub
L3112:  iconst_1
L3113:  iadd
L3114:  iload 17
L3116:  iload 16
L3118:  isub
L3119:  iconst_1
L3120:  iadd
L3121:  imul
L3122:  iconst_4
L3123:  if_icmplt L3244
L3126:  aload_0
L3127:  getfield Field c i [[[I
L3130:  iload 11
L3132:  aaload
L3133:  iload 14
L3135:  aaload
L3136:  iload 16
L3138:  iaload
L3139:  istore 18
L3141:  iload 17
L3143:  sipush 128
L3146:  imul
L3147:  sipush 128
L3150:  iadd
L3151:  iload 14
L3153:  sipush 128
L3156:  imul
L3157:  sipush -802
L3160:  iload 18
L3162:  iconst_4
L3163:  iload 15
L3165:  sipush 128
L3168:  imul
L3169:  sipush 128
L3172:  iadd
L3173:  iload 10
L3175:  iload 18
L3177:  iload 16
L3179:  sipush 128
L3182:  imul
L3183:  invokestatic Method r a (IIIIIIIII)V
L3186:  iload 14
L3188:  istore 19
L3190:  iload 45
L3192:  ifeq L3237
L3195:  iload 16
L3197:  istore 20
L3199:  iload 45
L3201:  ifeq L3227
L3204:  aload_0
L3205:  getfield Field c v [[[I
L3208:  iload 11
L3210:  aaload
L3211:  iload 19
L3213:  aaload
L3214:  iload 20
L3216:  dup2
L3217:  iaload
L3218:  iload 9
L3220:  iconst_m1
L3221:  ixor
L3222:  iand
L3223:  iastore
L3224:  iinc 20 1
L3227:  iload 20
L3229:  iload 17
L3231:  if_icmple L3204
L3234:  iinc 19 1
L3237:  iload 19
L3239:  iload 15
L3241:  if_icmple L3195
L3244:  iinc 13 1
L3247:  iload 13
L3249:  aload_0
L3250:  getfield Field c g I
L3253:  if_icmple L2120
L3256:  iinc 12 1
L3259:  iload 12
L3261:  aload_0
L3262:  getfield Field c h I
L3265:  if_icmple L2112
L3268:  iinc 11 1
L3271:  iload 11
L3273:  iload 10
L3275:  if_icmple L2104
L3278:  iinc 10 1
L3281:  iload 10
L3283:  iconst_4
L3284:  if_icmplt L2073
L3287:  return
L3288:  astore 4
L3290:  new java/lang/StringBuffer
L3293:  dup
L3294:  ldc "31873, "
L3296:  invokespecial Method java/lang/StringBuffer <init> (Ljava/lang/String;)V
L3299:  aload_1
L3300:  invokevirtual Method java/lang/StringBuffer append (Ljava/lang/Object;)Ljava/lang/StringBuffer;
L3303:  ldc ", "
L3305:  invokevirtual Method java/lang/StringBuffer append (Ljava/lang/String;)Ljava/lang/StringBuffer;
L3308:  iload_2
L3309:  invokevirtual Method java/lang/StringBuffer append (I)Ljava/lang/StringBuffer;
L3312:  ldc ", "
L3314:  invokevirtual Method java/lang/StringBuffer append (Ljava/lang/String;)Ljava/lang/StringBuffer;
L3317:  aload_3
L3318:  invokevirtual Method java/lang/StringBuffer append (Ljava/lang/Object;)Ljava/lang/StringBuffer;
L3321:  ldc ", "
L3323:  invokevirtual Method java/lang/StringBuffer append (Ljava/lang/String;)Ljava/lang/StringBuffer;
L3326:  aload 4
L3328:  invokevirtual Method java/lang/Throwable toString ()Ljava/lang/String;
L3331:  invokevirtual Method java/lang/StringBuffer append (Ljava/lang/String;)Ljava/lang/StringBuffer;
L3334:  invokevirtual Method java/lang/StringBuffer toString ()Ljava/lang/String;
L3337:  invokestatic Method sign/signlink reporterror (Ljava/lang/String;)V
L3340:  new java/lang/RuntimeException
L3343:  dup
L3344:  invokespecial Method java/lang/RuntimeException <init> ()V
L3347:  athrow
L3348:  
    .end code
.end method

.method public a : (IBII)I
    .code stack 3 locals 6
        .catch java/lang/RuntimeException from L0 to L57 using L57
L0:     iload_2
L1:     bipush 10
L3:     if_icmpeq L12
L6:     aload_0
L7:     bipush 29
L9:     putfield Field c c I
L12:    aload_0
L13:    getfield Field c j [[[B
L16:    iload_1
L17:    aaload
L18:    iload_3
L19:    aaload
L20:    iload 4
L22:    baload
L23:    bipush 8
L25:    iand
L26:    ifeq L31
L29:    iconst_0
L30:    ireturn
L31:    iload_1
L32:    ifle L55
L35:    aload_0
L36:    getfield Field c j [[[B
L39:    iconst_1
L40:    aaload
L41:    iload_3
L42:    aaload
L43:    iload 4
L45:    baload
L46:    iconst_2
L47:    iand
L48:    ifeq L55
L51:    iload_1
L52:    iconst_1
L53:    isub
L54:    ireturn
L55:    iload_1
L56:    ireturn
L57:    astore 5
L59:    new java/lang/StringBuffer
L62:    dup
L63:    ldc "77679, "
L65:    invokespecial Method java/lang/StringBuffer <init> (Ljava/lang/String;)V
L68:    iload_1
L69:    invokevirtual Method java/lang/StringBuffer append (I)Ljava/lang/StringBuffer;
L72:    ldc ", "
L74:    invokevirtual Method java/lang/StringBuffer append (Ljava/lang/String;)Ljava/lang/StringBuffer;
L77:    iload_2
L78:    invokevirtual Method java/lang/StringBuffer append (I)Ljava/lang/StringBuffer;
L81:    ldc ", "
L83:    invokevirtual Method java/lang/StringBuffer append (Ljava/lang/String;)Ljava/lang/StringBuffer;
L86:    iload_3
L87:    invokevirtual Method java/lang/StringBuffer append (I)Ljava/lang/StringBuffer;
L90:    ldc ", "
L92:    invokevirtual Method java/lang/StringBuffer append (Ljava/lang/String;)Ljava/lang/StringBuffer;
L95:    iload 4
L97:    invokevirtual Method java/lang/StringBuffer append (I)Ljava/lang/StringBuffer;
L100:   ldc ", "
L102:   invokevirtual Method java/lang/StringBuffer append (Ljava/lang/String;)Ljava/lang/StringBuffer;
L105:   aload 5
L107:   invokevirtual Method java/lang/Throwable toString ()Ljava/lang/String;
L110:   invokevirtual Method java/lang/StringBuffer append (Ljava/lang/String;)Ljava/lang/StringBuffer;
L113:   invokevirtual Method java/lang/StringBuffer toString ()Ljava/lang/String;
L116:   invokestatic Method sign/signlink reporterror (Ljava/lang/String;)V
L119:   new java/lang/RuntimeException
L122:   dup
L123:   invokespecial Method java/lang/RuntimeException <init> ()V
L126:   athrow
L127:   
    .end code
.end method

.method private static final a : (II)I
    .code stack 5 locals 3
L0:     iload_0
L1:     ldc 45365
L3:     iadd
L4:     iload_1
L5:     ldc 91923
L7:     iadd
L8:     iconst_4
L9:     invokestatic Method c a (III)I
L12:    sipush 128
L15:    isub
L16:    iload_0
L17:    sipush 10294
L20:    iadd
L21:    iload_1
L22:    ldc 37821
L24:    iadd
L25:    iconst_2
L26:    invokestatic Method c a (III)I
L29:    sipush 128
L32:    isub
L33:    iconst_1
L34:    ishr
L35:    iadd
L36:    iload_0
L37:    iload_1
L38:    iconst_1
L39:    invokestatic Method c a (III)I
L42:    sipush 128
L45:    isub
L46:    iconst_2
L47:    ishr
L48:    iadd
L49:    istore_2
L50:    iload_2
L51:    i2d
L52:    ldc2_w 3e-1
L55:    dmul
L56:    d2i
L57:    bipush 35
L59:    iadd
L60:    istore_2
L61:    iload_2
L62:    bipush 10
L64:    if_icmpge L76
L67:    bipush 10
L69:    istore_2
L70:    getstatic Field dc c Z
L73:    ifeq L85
L76:    iload_2
L77:    bipush 60
L79:    if_icmple L85
L82:    bipush 60
L84:    istore_2
L85:    iload_2
L86:    ireturn
L87:    
    .end code
.end method

.method private static final a : (III)I
    .code stack 4 locals 13
L0:     iload_0
L1:     iload_2
L2:     idiv
L3:     istore_3
L4:     iload_0
L5:     iload_2
L6:     iconst_1
L7:     isub
L8:     iand
L9:     istore 4
L11:    iload_1
L12:    iload_2
L13:    idiv
L14:    istore 5
L16:    iload_1
L17:    iload_2
L18:    iconst_1
L19:    isub
L20:    iand
L21:    istore 6
L23:    iload_3
L24:    iload 5
L26:    invokestatic Method c b (II)I
L29:    istore 7
L31:    iload_3
L32:    iconst_1
L33:    iadd
L34:    iload 5
L36:    invokestatic Method c b (II)I
L39:    istore 8
L41:    iload_3
L42:    iload 5
L44:    iconst_1
L45:    iadd
L46:    invokestatic Method c b (II)I
L49:    istore 9
L51:    iload_3
L52:    iconst_1
L53:    iadd
L54:    iload 5
L56:    iconst_1
L57:    iadd
L58:    invokestatic Method c b (II)I
L61:    istore 10
L63:    iload 7
L65:    iload 8
L67:    iload 4
L69:    iload_2
L70:    invokestatic Method c a (IIII)I
L73:    istore 11
L75:    iload 9
L77:    iload 10
L79:    iload 4
L81:    iload_2
L82:    invokestatic Method c a (IIII)I
L85:    istore 12
L87:    iload 11
L89:    iload 12
L91:    iload 6
L93:    iload_2
L94:    invokestatic Method c a (IIII)I
L97:    ireturn
L98:    
    .end code
.end method

.method private static final a : (IIII)I
    .code stack 4 locals 5
L0:     ldc 65536
L2:     getstatic Field gb K [I
L5:     iload_2
L6:     sipush 1024
L9:     imul
L10:    iload_3
L11:    idiv
L12:    iaload
L13:    isub
L14:    iconst_1
L15:    ishr
L16:    istore 4
L18:    iload_0
L19:    ldc 65536
L21:    iload 4
L23:    isub
L24:    imul
L25:    bipush 16
L27:    ishr
L28:    iload_1
L29:    iload 4
L31:    imul
L32:    bipush 16
L34:    ishr
L35:    iadd
L36:    ireturn
L37:    
    .end code
.end method

.method private static final b : (II)I
    .code stack 4 locals 5
L0:     iload_0
L1:     iconst_1
L2:     isub
L3:     iload_1
L4:     iconst_1
L5:     isub
L6:     invokestatic Method c c (II)I
L9:     iload_0
L10:    iconst_1
L11:    iadd
L12:    iload_1
L13:    iconst_1
L14:    isub
L15:    invokestatic Method c c (II)I
L18:    iadd
L19:    iload_0
L20:    iconst_1
L21:    isub
L22:    iload_1
L23:    iconst_1
L24:    iadd
L25:    invokestatic Method c c (II)I
L28:    iadd
L29:    iload_0
L30:    iconst_1
L31:    iadd
L32:    iload_1
L33:    iconst_1
L34:    iadd
L35:    invokestatic Method c c (II)I
L38:    iadd
L39:    istore_2
L40:    iload_0
L41:    iconst_1
L42:    isub
L43:    iload_1
L44:    invokestatic Method c c (II)I
L47:    iload_0
L48:    iconst_1
L49:    iadd
L50:    iload_1
L51:    invokestatic Method c c (II)I
L54:    iadd
L55:    iload_0
L56:    iload_1
L57:    iconst_1
L58:    isub
L59:    invokestatic Method c c (II)I
L62:    iadd
L63:    iload_0
L64:    iload_1
L65:    iconst_1
L66:    iadd
L67:    invokestatic Method c c (II)I
L70:    iadd
L71:    istore_3
L72:    iload_0
L73:    iload_1
L74:    invokestatic Method c c (II)I
L77:    istore 4
L79:    iload_2
L80:    bipush 16
L82:    idiv
L83:    iload_3
L84:    bipush 8
L86:    idiv
L87:    iadd
L88:    iload 4
L90:    iconst_4
L91:    idiv
L92:    iadd
L93:    ireturn
L94:    
    .end code
.end method

.method private static final c : (II)I
    .code stack 3 locals 4
L0:     iload_0
L1:     iload_1
L2:     bipush 57
L4:     imul
L5:     iadd
L6:     istore_2
L7:     iload_2
L8:     bipush 13
L10:    ishl
L11:    iload_2
L12:    ixor
L13:    istore_2
L14:    iload_2
L15:    iload_2
L16:    iload_2
L17:    imul
L18:    sipush 15731
L21:    imul
L22:    ldc 789221
L24:    iadd
L25:    imul
L26:    ldc 1376312589
L28:    iadd
L29:    ldc 2147483647
L31:    iand
L32:    istore_3
L33:    iload_3
L34:    bipush 19
L36:    ishr
L37:    sipush 255
L40:    iand
L41:    ireturn
L42:    
    .end code
.end method

.method private static final d : (II)I
    .code stack 4 locals 2
L0:     iload_0
L1:     iconst_m1
L2:     if_icmpne L8
L5:     ldc 12345678
L7:     ireturn
L8:     iload_1
L9:     iload_0
L10:    bipush 127
L12:    iand
L13:    imul
L14:    sipush 128
L17:    idiv
L18:    istore_1
L19:    iload_1
L20:    iconst_2
L21:    if_icmpge L32
L24:    iconst_2
L25:    istore_1
L26:    getstatic Field dc c Z
L29:    ifeq L41
L32:    iload_1
L33:    bipush 126
L35:    if_icmple L41
L38:    bipush 126
L40:    istore_1
L41:    iload_0
L42:    ldc 65408
L44:    iand
L45:    iload_1
L46:    iadd
L47:    ireturn
L48:    
    .end code
.end method

.method private final e : (II)I
    .code stack 4 locals 4
L0:     getstatic Field dc c Z
L3:     istore_3
L4:     iload_1
L5:     bipush -2
L7:     if_icmpne L13
L10:    ldc 12345678
L12:    ireturn
L13:    iload_1
L14:    iconst_m1
L15:    if_icmpne L44
L18:    iload_2
L19:    ifge L28
L22:    iconst_0
L23:    istore_2
L24:    iload_3
L25:    ifeq L37
L28:    iload_2
L29:    bipush 127
L31:    if_icmple L37
L34:    bipush 127
L36:    istore_2
L37:    bipush 127
L39:    iload_2
L40:    isub
L41:    istore_2
L42:    iload_2
L43:    ireturn
L44:    iload_2
L45:    iload_1
L46:    bipush 127
L48:    iand
L49:    imul
L50:    sipush 128
L53:    idiv
L54:    istore_2
L55:    iload_2
L56:    iconst_2
L57:    if_icmpge L66
L60:    iconst_2
L61:    istore_2
L62:    iload_3
L63:    ifeq L75
L66:    iload_2
L67:    bipush 126
L69:    if_icmple L75
L72:    bipush 126
L74:    istore_2
L75:    iload_1
L76:    ldc 65408
L78:    iand
L79:    iload_2
L80:    iadd
L81:    ireturn
L82:    
    .end code
.end method

.method private final b : (III)I
    .code stack 3 locals 5
L0:     iload_3
L1:     sipush 179
L4:     if_icmple L11
L7:     iload_2
L8:     iconst_2
L9:     idiv
L10:    istore_2
L11:    iload_3
L12:    sipush 192
L15:    if_icmple L22
L18:    iload_2
L19:    iconst_2
L20:    idiv
L21:    istore_2
L22:    iload_3
L23:    sipush 217
L26:    if_icmple L33
L29:    iload_2
L30:    iconst_2
L31:    idiv
L32:    istore_2
L33:    iload_3
L34:    sipush 243
L37:    if_icmple L44
L40:    iload_2
L41:    iconst_2
L42:    idiv
L43:    istore_2
L44:    iload_1
L45:    iconst_4
L46:    idiv
L47:    bipush 10
L49:    ishl
L50:    iload_2
L51:    bipush 32
L53:    idiv
L54:    bipush 7
L56:    ishl
L57:    iadd
L58:    iload_3
L59:    iconst_2
L60:    idiv
L61:    iadd
L62:    istore 4
L64:    iload 4
L66:    ireturn
L67:    
    .end code
.end method

.method public static final a : (ILob;Lec;II[[[IIIIILr;I)V
    .code stack 14 locals 24
        .catch java/lang/RuntimeException from L0 to L1708 using L1708
L0:     iload 6
L2:     ifeq L19
L5:     getstatic Field c a Z
L8:     ifeq L15
L11:    iconst_0
L12:    goto L16
L15:    iconst_1
L16:    putstatic Field c a Z
L19:    aload 5
L21:    iload 11
L23:    aaload
L24:    iload_0
L25:    aaload
L26:    iload_3
L27:    iaload
L28:    istore 12
L30:    aload 5
L32:    iload 11
L34:    aaload
L35:    iload_0
L36:    iconst_1
L37:    iadd
L38:    aaload
L39:    iload_3
L40:    iaload
L41:    istore 13
L43:    aload 5
L45:    iload 11
L47:    aaload
L48:    iload_0
L49:    iconst_1
L50:    iadd
L51:    aaload
L52:    iload_3
L53:    iconst_1
L54:    iadd
L55:    iaload
L56:    istore 14
L58:    aload 5
L60:    iload 11
L62:    aaload
L63:    iload_0
L64:    aaload
L65:    iload_3
L66:    iconst_1
L67:    iadd
L68:    iaload
L69:    istore 15
L71:    iload 12
L73:    iload 13
L75:    iadd
L76:    iload 14
L78:    iadd
L79:    iload 15
L81:    iadd
L82:    iconst_2
L83:    ishr
L84:    istore 16
L86:    iload 8
L88:    invokestatic Method ac a (I)Lac;
L91:    astore 17
L93:    iload_0
L94:    iload_3
L95:    bipush 7
L97:    ishl
L98:    iadd
L99:    iload 8
L101:   bipush 14
L103:   ishl
L104:   iadd
L105:   ldc 1073741824
L107:   iadd
L108:   istore 18
L110:   aload 17
L112:   getfield Field ac t Z
L115:   ifne L125
L118:   iload 18
L120:   ldc -2147483648
L122:   iadd
L123:   istore 18
L125:   iload 4
L127:   bipush 6
L129:   ishl
L130:   iload 9
L132:   iadd
L133:   i2b
L134:   istore 19
L136:   iload 9
L138:   bipush 22
L140:   if_icmpne L245
L143:   aload 17
L145:   bipush 22
L147:   iload 4
L149:   iload 12
L151:   iload 13
L153:   iload 14
L155:   iload 15
L157:   iconst_m1
L158:   invokevirtual Method ac a (IIIIIII)Leb;
L161:   astore 20
L163:   aload 10
L165:   aload 20
L167:   bipush 6
L169:   iload_0
L170:   iload 18
L172:   iload_3
L173:   iload 7
L175:   iload 19
L177:   iload 16
L179:   invokevirtual Method r a (Leb;BIIIIBI)V
L182:   aload 17
L184:   getfield Field ac r Z
L187:   ifeq L206
L190:   aload 17
L192:   getfield Field ac t Z
L195:   ifeq L206
L198:   aload_2
L199:   bipush 12
L201:   iload_3
L202:   iload_0
L203:   invokevirtual Method ec a (BII)V
L206:   aload 17
L208:   getfield Field ac x I
L211:   iconst_m1
L212:   if_icmpeq L244
L215:   aload_1
L216:   new nb
L219:   dup
L220:   iconst_1
L221:   iload 8
L223:   iload 7
L225:   iconst_0
L226:   iconst_3
L227:   getstatic Field jc d [Ljc;
L230:   aload 17
L232:   getfield Field ac x I
L235:   aaload
L236:   iload_3
L237:   iload_0
L238:   invokespecial Method nb <init> (ZIIIILjc;II)V
L241:   invokevirtual Method ob a (Lu;)V
L244:   return
L245:   iload 9
L247:   bipush 10
L249:   if_icmpeq L259
L252:   iload 9
L254:   bipush 11
L256:   if_icmpne L446
L259:   aload 17
L261:   bipush 10
L263:   iload 4
L265:   iload 12
L267:   iload 13
L269:   iload 14
L271:   iload 15
L273:   iconst_m1
L274:   invokevirtual Method ac a (IIIIIII)Leb;
L277:   astore 20
L279:   aload 20
L281:   ifnull L374
L284:   iconst_0
L285:   istore 23
L287:   iload 9
L289:   bipush 11
L291:   if_icmpne L300
L294:   wide iinc 23 256
L300:   iload 4
L302:   iconst_1
L303:   if_icmpeq L312
L306:   iload 4
L308:   iconst_3
L309:   if_icmpne L332
L312:   aload 17
L314:   getfield Field ac q I
L317:   istore 21
L319:   aload 17
L321:   getfield Field ac p I
L324:   istore 22
L326:   getstatic Field dc c Z
L329:   ifeq L346
L332:   aload 17
L334:   getfield Field ac p I
L337:   istore 21
L339:   aload 17
L341:   getfield Field ac q I
L344:   istore 22
L346:   aload 10
L348:   iload 16
L350:   sipush 775
L353:   iload 7
L355:   aconst_null
L356:   iload 18
L358:   iload_3
L359:   iload_0
L360:   iload 21
L362:   iload 19
L364:   aload 20
L366:   iload 23
L368:   iload 22
L370:   invokevirtual Method r a (IIILw;IIIIBLeb;II)Z
L373:   pop
L374:   aload 17
L376:   getfield Field ac r Z
L379:   ifeq L407
L382:   aload_2
L383:   iload 4
L385:   aload 17
L387:   getfield Field ac q I
L390:   aload 17
L392:   getfield Field ac p I
L395:   iload_0
L396:   bipush 9
L398:   iload_3
L399:   aload 17
L401:   getfield Field ac s Z
L404:   invokevirtual Method ec a (IIIIIIZ)V
L407:   aload 17
L409:   getfield Field ac x I
L412:   iconst_m1
L413:   if_icmpeq L445
L416:   aload_1
L417:   new nb
L420:   dup
L421:   iconst_1
L422:   iload 8
L424:   iload 7
L426:   iconst_0
L427:   iconst_2
L428:   getstatic Field jc d [Ljc;
L431:   aload 17
L433:   getfield Field ac x I
L436:   aaload
L437:   iload_3
L438:   iload_0
L439:   invokespecial Method nb <init> (ZIIIILjc;II)V
L442:   invokevirtual Method ob a (Lu;)V
L445:   return
L446:   iload 9
L448:   bipush 12
L450:   if_icmplt L570
L453:   aload 17
L455:   iload 9
L457:   iload 4
L459:   iload 12
L461:   iload 13
L463:   iload 14
L465:   iload 15
L467:   iconst_m1
L468:   invokevirtual Method ac a (IIIIIII)Leb;
L471:   astore 20
L473:   aload 10
L475:   iload 16
L477:   sipush 775
L480:   iload 7
L482:   aconst_null
L483:   iload 18
L485:   iload_3
L486:   iload_0
L487:   iconst_1
L488:   iload 19
L490:   aload 20
L492:   iconst_0
L493:   iconst_1
L494:   invokevirtual Method r a (IIILw;IIIIBLeb;II)Z
L497:   pop
L498:   aload 17
L500:   getfield Field ac r Z
L503:   ifeq L531
L506:   aload_2
L507:   iload 4
L509:   aload 17
L511:   getfield Field ac q I
L514:   aload 17
L516:   getfield Field ac p I
L519:   iload_0
L520:   bipush 9
L522:   iload_3
L523:   aload 17
L525:   getfield Field ac s Z
L528:   invokevirtual Method ec a (IIIIIIZ)V
L531:   aload 17
L533:   getfield Field ac x I
L536:   iconst_m1
L537:   if_icmpeq L569
L540:   aload_1
L541:   new nb
L544:   dup
L545:   iconst_1
L546:   iload 8
L548:   iload 7
L550:   iconst_0
L551:   iconst_2
L552:   getstatic Field jc d [Ljc;
L555:   aload 17
L557:   getfield Field ac x I
L560:   aaload
L561:   iload_3
L562:   iload_0
L563:   invokespecial Method nb <init> (ZIIIILjc;II)V
L566:   invokevirtual Method ob a (Lu;)V
L569:   return
L570:   iload 9
L572:   ifne L684
L575:   aload 17
L577:   iconst_0
L578:   iload 4
L580:   iload 12
L582:   iload 13
L584:   iload 14
L586:   iload 15
L588:   iconst_m1
L589:   invokevirtual Method ac a (IIIIIII)Leb;
L592:   astore 20
L594:   aload 10
L596:   iconst_0
L597:   iload 16
L599:   iload 7
L601:   getstatic Field c w [I
L604:   iload 4
L606:   iaload
L607:   bipush 8
L609:   aload 20
L611:   aconst_null
L612:   iload_0
L613:   iload 18
L615:   iload_3
L616:   iload 19
L618:   invokevirtual Method r a (IIIIILeb;Leb;IIIB)V
L621:   aload 17
L623:   getfield Field ac r Z
L626:   ifeq L645
L629:   aload_2
L630:   iconst_1
L631:   iload 4
L633:   iload_3
L634:   iload_0
L635:   aload 17
L637:   getfield Field ac s Z
L640:   iload 9
L642:   invokevirtual Method ec a (ZIIIZI)V
L645:   aload 17
L647:   getfield Field ac x I
L650:   iconst_m1
L651:   if_icmpeq L683
L654:   aload_1
L655:   new nb
L658:   dup
L659:   iconst_1
L660:   iload 8
L662:   iload 7
L664:   iconst_0
L665:   iconst_0
L666:   getstatic Field jc d [Ljc;
L669:   aload 17
L671:   getfield Field ac x I
L674:   aaload
L675:   iload_3
L676:   iload_0
L677:   invokespecial Method nb <init> (ZIIIILjc;II)V
L680:   invokevirtual Method ob a (Lu;)V
L683:   return
L684:   iload 9
L686:   iconst_1
L687:   if_icmpne L799
L690:   aload 17
L692:   iconst_1
L693:   iload 4
L695:   iload 12
L697:   iload 13
L699:   iload 14
L701:   iload 15
L703:   iconst_m1
L704:   invokevirtual Method ac a (IIIIIII)Leb;
L707:   astore 20
L709:   aload 10
L711:   iconst_0
L712:   iload 16
L714:   iload 7
L716:   getstatic Field c x [I
L719:   iload 4
L721:   iaload
L722:   bipush 8
L724:   aload 20
L726:   aconst_null
L727:   iload_0
L728:   iload 18
L730:   iload_3
L731:   iload 19
L733:   invokevirtual Method r a (IIIIILeb;Leb;IIIB)V
L736:   aload 17
L738:   getfield Field ac r Z
L741:   ifeq L760
L744:   aload_2
L745:   iconst_1
L746:   iload 4
L748:   iload_3
L749:   iload_0
L750:   aload 17
L752:   getfield Field ac s Z
L755:   iload 9
L757:   invokevirtual Method ec a (ZIIIZI)V
L760:   aload 17
L762:   getfield Field ac x I
L765:   iconst_m1
L766:   if_icmpeq L798
L769:   aload_1
L770:   new nb
L773:   dup
L774:   iconst_1
L775:   iload 8
L777:   iload 7
L779:   iconst_0
L780:   iconst_0
L781:   getstatic Field jc d [Ljc;
L784:   aload 17
L786:   getfield Field ac x I
L789:   aaload
L790:   iload_3
L791:   iload_0
L792:   invokespecial Method nb <init> (ZIIIILjc;II)V
L795:   invokevirtual Method ob a (Lu;)V
L798:   return
L799:   iload 9
L801:   iconst_2
L802:   if_icmpne L949
L805:   iload 4
L807:   iconst_1
L808:   iadd
L809:   iconst_3
L810:   iand
L811:   istore 20
L813:   aload 17
L815:   iconst_2
L816:   iconst_4
L817:   iload 4
L819:   iadd
L820:   iload 12
L822:   iload 13
L824:   iload 14
L826:   iload 15
L828:   iconst_m1
L829:   invokevirtual Method ac a (IIIIIII)Leb;
L832:   astore 21
L834:   aload 17
L836:   iconst_2
L837:   iload 20
L839:   iload 12
L841:   iload 13
L843:   iload 14
L845:   iload 15
L847:   iconst_m1
L848:   invokevirtual Method ac a (IIIIIII)Leb;
L851:   astore 22
L853:   aload 10
L855:   getstatic Field c w [I
L858:   iload 20
L860:   iaload
L861:   iload 16
L863:   iload 7
L865:   getstatic Field c w [I
L868:   iload 4
L870:   iaload
L871:   bipush 8
L873:   aload 21
L875:   aload 22
L877:   iload_0
L878:   iload 18
L880:   iload_3
L881:   iload 19
L883:   invokevirtual Method r a (IIIIILeb;Leb;IIIB)V
L886:   aload 17
L888:   getfield Field ac r Z
L891:   ifeq L910
L894:   aload_2
L895:   iconst_1
L896:   iload 4
L898:   iload_3
L899:   iload_0
L900:   aload 17
L902:   getfield Field ac s Z
L905:   iload 9
L907:   invokevirtual Method ec a (ZIIIZI)V
L910:   aload 17
L912:   getfield Field ac x I
L915:   iconst_m1
L916:   if_icmpeq L948
L919:   aload_1
L920:   new nb
L923:   dup
L924:   iconst_1
L925:   iload 8
L927:   iload 7
L929:   iconst_0
L930:   iconst_0
L931:   getstatic Field jc d [Ljc;
L934:   aload 17
L936:   getfield Field ac x I
L939:   aaload
L940:   iload_3
L941:   iload_0
L942:   invokespecial Method nb <init> (ZIIIILjc;II)V
L945:   invokevirtual Method ob a (Lu;)V
L948:   return
L949:   iload 9
L951:   iconst_3
L952:   if_icmpne L1064
L955:   aload 17
L957:   iconst_3
L958:   iload 4
L960:   iload 12
L962:   iload 13
L964:   iload 14
L966:   iload 15
L968:   iconst_m1
L969:   invokevirtual Method ac a (IIIIIII)Leb;
L972:   astore 20
L974:   aload 10
L976:   iconst_0
L977:   iload 16
L979:   iload 7
L981:   getstatic Field c x [I
L984:   iload 4
L986:   iaload
L987:   bipush 8
L989:   aload 20
L991:   aconst_null
L992:   iload_0
L993:   iload 18
L995:   iload_3
L996:   iload 19
L998:   invokevirtual Method r a (IIIIILeb;Leb;IIIB)V
L1001:  aload 17
L1003:  getfield Field ac r Z
L1006:  ifeq L1025
L1009:  aload_2
L1010:  iconst_1
L1011:  iload 4
L1013:  iload_3
L1014:  iload_0
L1015:  aload 17
L1017:  getfield Field ac s Z
L1020:  iload 9
L1022:  invokevirtual Method ec a (ZIIIZI)V
L1025:  aload 17
L1027:  getfield Field ac x I
L1030:  iconst_m1
L1031:  if_icmpeq L1063
L1034:  aload_1
L1035:  new nb
L1038:  dup
L1039:  iconst_1
L1040:  iload 8
L1042:  iload 7
L1044:  iconst_0
L1045:  iconst_0
L1046:  getstatic Field jc d [Ljc;
L1049:  aload 17
L1051:  getfield Field ac x I
L1054:  aaload
L1055:  iload_3
L1056:  iload_0
L1057:  invokespecial Method nb <init> (ZIIIILjc;II)V
L1060:  invokevirtual Method ob a (Lu;)V
L1063:  return
L1064:  iload 9
L1066:  bipush 9
L1068:  if_icmpne L1188
L1071:  aload 17
L1073:  iload 9
L1075:  iload 4
L1077:  iload 12
L1079:  iload 13
L1081:  iload 14
L1083:  iload 15
L1085:  iconst_m1
L1086:  invokevirtual Method ac a (IIIIIII)Leb;
L1089:  astore 20
L1091:  aload 10
L1093:  iload 16
L1095:  sipush 775
L1098:  iload 7
L1100:  aconst_null
L1101:  iload 18
L1103:  iload_3
L1104:  iload_0
L1105:  iconst_1
L1106:  iload 19
L1108:  aload 20
L1110:  iconst_0
L1111:  iconst_1
L1112:  invokevirtual Method r a (IIILw;IIIIBLeb;II)Z
L1115:  pop
L1116:  aload 17
L1118:  getfield Field ac r Z
L1121:  ifeq L1149
L1124:  aload_2
L1125:  iload 4
L1127:  aload 17
L1129:  getfield Field ac q I
L1132:  aload 17
L1134:  getfield Field ac p I
L1137:  iload_0
L1138:  bipush 9
L1140:  iload_3
L1141:  aload 17
L1143:  getfield Field ac s Z
L1146:  invokevirtual Method ec a (IIIIIIZ)V
L1149:  aload 17
L1151:  getfield Field ac x I
L1154:  iconst_m1
L1155:  if_icmpeq L1187
L1158:  aload_1
L1159:  new nb
L1162:  dup
L1163:  iconst_1
L1164:  iload 8
L1166:  iload 7
L1168:  iconst_0
L1169:  iconst_2
L1170:  getstatic Field jc d [Ljc;
L1173:  aload 17
L1175:  getfield Field ac x I
L1178:  aaload
L1179:  iload_3
L1180:  iload_0
L1181:  invokespecial Method nb <init> (ZIIIILjc;II)V
L1184:  invokevirtual Method ob a (Lu;)V
L1187:  return
L1188:  iload 9
L1190:  iconst_4
L1191:  if_icmpne L1285
L1194:  aload 17
L1196:  iconst_4
L1197:  iconst_0
L1198:  iload 12
L1200:  iload 13
L1202:  iload 14
L1204:  iload 15
L1206:  iconst_m1
L1207:  invokevirtual Method ac a (IIIIIII)Leb;
L1210:  astore 20
L1212:  aload 10
L1214:  iload 16
L1216:  iload_3
L1217:  iconst_0
L1218:  iload 18
L1220:  iload 4
L1222:  sipush 512
L1225:  imul
L1226:  getstatic Field c w [I
L1229:  iload 4
L1231:  iaload
L1232:  sipush 465
L1235:  iconst_0
L1236:  iload_0
L1237:  aload 20
L1239:  iload 19
L1241:  iload 7
L1243:  invokevirtual Method r a (IIIIIIIIILeb;BI)V
L1246:  aload 17
L1248:  getfield Field ac x I
L1251:  iconst_m1
L1252:  if_icmpeq L1284
L1255:  aload_1
L1256:  new nb
L1259:  dup
L1260:  iconst_1
L1261:  iload 8
L1263:  iload 7
L1265:  iconst_0
L1266:  iconst_1
L1267:  getstatic Field jc d [Ljc;
L1270:  aload 17
L1272:  getfield Field ac x I
L1275:  aaload
L1276:  iload_3
L1277:  iload_0
L1278:  invokespecial Method nb <init> (ZIIIILjc;II)V
L1281:  invokevirtual Method ob a (Lu;)V
L1284:  return
L1285:  iload 9
L1287:  iconst_5
L1288:  if_icmpne L1435
L1291:  bipush 16
L1293:  istore 20
L1295:  aload 10
L1297:  iload 7
L1299:  iload_0
L1300:  iload_3
L1301:  invokevirtual Method r b (III)I
L1304:  istore 21
L1306:  iload 21
L1308:  ifle L1328
L1311:  iload 21
L1313:  bipush 14
L1315:  ishr
L1316:  sipush 32767
L1319:  iand
L1320:  invokestatic Method ac a (I)Lac;
L1323:  getfield Field ac y I
L1326:  istore 20
L1328:  aload 17
L1330:  iconst_4
L1331:  iconst_0
L1332:  iload 12
L1334:  iload 13
L1336:  iload 14
L1338:  iload 15
L1340:  iconst_m1
L1341:  invokevirtual Method ac a (IIIIIII)Leb;
L1344:  astore 22
L1346:  aload 10
L1348:  iload 16
L1350:  iload_3
L1351:  getstatic Field c z [I
L1354:  iload 4
L1356:  iaload
L1357:  iload 20
L1359:  imul
L1360:  iload 18
L1362:  iload 4
L1364:  sipush 512
L1367:  imul
L1368:  getstatic Field c w [I
L1371:  iload 4
L1373:  iaload
L1374:  sipush 465
L1377:  getstatic Field c y [I
L1380:  iload 4
L1382:  iaload
L1383:  iload 20
L1385:  imul
L1386:  iload_0
L1387:  aload 22
L1389:  iload 19
L1391:  iload 7
L1393:  invokevirtual Method r a (IIIIIIIIILeb;BI)V
L1396:  aload 17
L1398:  getfield Field ac x I
L1401:  iconst_m1
L1402:  if_icmpeq L1434
L1405:  aload_1
L1406:  new nb
L1409:  dup
L1410:  iconst_1
L1411:  iload 8
L1413:  iload 7
L1415:  iconst_0
L1416:  iconst_1
L1417:  getstatic Field jc d [Ljc;
L1420:  aload 17
L1422:  getfield Field ac x I
L1425:  aaload
L1426:  iload_3
L1427:  iload_0
L1428:  invokespecial Method nb <init> (ZIIIILjc;II)V
L1431:  invokevirtual Method ob a (Lu;)V
L1434:  return
L1435:  iload 9
L1437:  bipush 6
L1439:  if_icmpne L1526
L1442:  aload 17
L1444:  iconst_4
L1445:  iconst_0
L1446:  iload 12
L1448:  iload 13
L1450:  iload 14
L1452:  iload 15
L1454:  iconst_m1
L1455:  invokevirtual Method ac a (IIIIIII)Leb;
L1458:  astore 20
L1460:  aload 10
L1462:  iload 16
L1464:  iload_3
L1465:  iconst_0
L1466:  iload 18
L1468:  iload 4
L1470:  sipush 256
L1473:  sipush 465
L1476:  iconst_0
L1477:  iload_0
L1478:  aload 20
L1480:  iload 19
L1482:  iload 7
L1484:  invokevirtual Method r a (IIIIIIIIILeb;BI)V
L1487:  aload 17
L1489:  getfield Field ac x I
L1492:  iconst_m1
L1493:  if_icmpeq L1525
L1496:  aload_1
L1497:  new nb
L1500:  dup
L1501:  iconst_1
L1502:  iload 8
L1504:  iload 7
L1506:  iconst_0
L1507:  iconst_1
L1508:  getstatic Field jc d [Ljc;
L1511:  aload 17
L1513:  getfield Field ac x I
L1516:  aaload
L1517:  iload_3
L1518:  iload_0
L1519:  invokespecial Method nb <init> (ZIIIILjc;II)V
L1522:  invokevirtual Method ob a (Lu;)V
L1525:  return
L1526:  iload 9
L1528:  bipush 7
L1530:  if_icmpne L1617
L1533:  aload 17
L1535:  iconst_4
L1536:  iconst_0
L1537:  iload 12
L1539:  iload 13
L1541:  iload 14
L1543:  iload 15
L1545:  iconst_m1
L1546:  invokevirtual Method ac a (IIIIIII)Leb;
L1549:  astore 20
L1551:  aload 10
L1553:  iload 16
L1555:  iload_3
L1556:  iconst_0
L1557:  iload 18
L1559:  iload 4
L1561:  sipush 512
L1564:  sipush 465
L1567:  iconst_0
L1568:  iload_0
L1569:  aload 20
L1571:  iload 19
L1573:  iload 7
L1575:  invokevirtual Method r a (IIIIIIIIILeb;BI)V
L1578:  aload 17
L1580:  getfield Field ac x I
L1583:  iconst_m1
L1584:  if_icmpeq L1616
L1587:  aload_1
L1588:  new nb
L1591:  dup
L1592:  iconst_1
L1593:  iload 8
L1595:  iload 7
L1597:  iconst_0
L1598:  iconst_1
L1599:  getstatic Field jc d [Ljc;
L1602:  aload 17
L1604:  getfield Field ac x I
L1607:  aaload
L1608:  iload_3
L1609:  iload_0
L1610:  invokespecial Method nb <init> (ZIIIILjc;II)V
L1613:  invokevirtual Method ob a (Lu;)V
L1616:  return
L1617:  iload 9
L1619:  bipush 8
L1621:  if_icmpne L1857
L1624:  aload 17
L1626:  iconst_4
L1627:  iconst_0
L1628:  iload 12
L1630:  iload 13
L1632:  iload 14
L1634:  iload 15
L1636:  iconst_m1
L1637:  invokevirtual Method ac a (IIIIIII)Leb;
L1640:  astore 20
L1642:  aload 10
L1644:  iload 16
L1646:  iload_3
L1647:  iconst_0
L1648:  iload 18
L1650:  iload 4
L1652:  sipush 768
L1655:  sipush 465
L1658:  iconst_0
L1659:  iload_0
L1660:  aload 20
L1662:  iload 19
L1664:  iload 7
L1666:  invokevirtual Method r a (IIIIIIIIILeb;BI)V
L1669:  aload 17
L1671:  getfield Field ac x I
L1674:  iconst_m1
L1675:  if_icmpeq L1707
L1678:  aload_1
L1679:  new nb
L1682:  dup
L1683:  iconst_1
L1684:  iload 8
L1686:  iload 7
L1688:  iconst_0
L1689:  iconst_1
L1690:  getstatic Field jc d [Ljc;
L1693:  aload 17
L1695:  getfield Field ac x I
L1698:  aaload
L1699:  iload_3
L1700:  iload_0
L1701:  invokespecial Method nb <init> (ZIIIILjc;II)V
L1704:  invokevirtual Method ob a (Lu;)V
L1707:  return
L1708:  astore 12
L1710:  new java/lang/StringBuffer
L1713:  dup
L1714:  ldc "74512, "
L1716:  invokespecial Method java/lang/StringBuffer <init> (Ljava/lang/String;)V
L1719:  iload_0
L1720:  invokevirtual Method java/lang/StringBuffer append (I)Ljava/lang/StringBuffer;
L1723:  ldc ", "
L1725:  invokevirtual Method java/lang/StringBuffer append (Ljava/lang/String;)Ljava/lang/StringBuffer;
L1728:  aload_1
L1729:  invokevirtual Method java/lang/StringBuffer append (Ljava/lang/Object;)Ljava/lang/StringBuffer;
L1732:  ldc ", "
L1734:  invokevirtual Method java/lang/StringBuffer append (Ljava/lang/String;)Ljava/lang/StringBuffer;
L1737:  aload_2
L1738:  invokevirtual Method java/lang/StringBuffer append (Ljava/lang/Object;)Ljava/lang/StringBuffer;
L1741:  ldc ", "
L1743:  invokevirtual Method java/lang/StringBuffer append (Ljava/lang/String;)Ljava/lang/StringBuffer;
L1746:  iload_3
L1747:  invokevirtual Method java/lang/StringBuffer append (I)Ljava/lang/StringBuffer;
L1750:  ldc ", "
L1752:  invokevirtual Method java/lang/StringBuffer append (Ljava/lang/String;)Ljava/lang/StringBuffer;
L1755:  iload 4
L1757:  invokevirtual Method java/lang/StringBuffer append (I)Ljava/lang/StringBuffer;
L1760:  ldc ", "
L1762:  invokevirtual Method java/lang/StringBuffer append (Ljava/lang/String;)Ljava/lang/StringBuffer;
L1765:  aload 5
L1767:  invokevirtual Method java/lang/StringBuffer append (Ljava/lang/Object;)Ljava/lang/StringBuffer;
L1770:  ldc ", "
L1772:  invokevirtual Method java/lang/StringBuffer append (Ljava/lang/String;)Ljava/lang/StringBuffer;
L1775:  iload 6
L1777:  invokevirtual Method java/lang/StringBuffer append (I)Ljava/lang/StringBuffer;
L1780:  ldc ", "
L1782:  invokevirtual Method java/lang/StringBuffer append (Ljava/lang/String;)Ljava/lang/StringBuffer;
L1785:  iload 7
L1787:  invokevirtual Method java/lang/StringBuffer append (I)Ljava/lang/StringBuffer;
L1790:  ldc ", "
L1792:  invokevirtual Method java/lang/StringBuffer append (Ljava/lang/String;)Ljava/lang/StringBuffer;
L1795:  iload 8
L1797:  invokevirtual Method java/lang/StringBuffer append (I)Ljava/lang/StringBuffer;
L1800:  ldc ", "
L1802:  invokevirtual Method java/lang/StringBuffer append (Ljava/lang/String;)Ljava/lang/StringBuffer;
L1805:  iload 9
L1807:  invokevirtual Method java/lang/StringBuffer append (I)Ljava/lang/StringBuffer;
L1810:  ldc ", "
L1812:  invokevirtual Method java/lang/StringBuffer append (Ljava/lang/String;)Ljava/lang/StringBuffer;
L1815:  aload 10
L1817:  invokevirtual Method java/lang/StringBuffer append (Ljava/lang/Object;)Ljava/lang/StringBuffer;
L1820:  ldc ", "
L1822:  invokevirtual Method java/lang/StringBuffer append (Ljava/lang/String;)Ljava/lang/StringBuffer;
L1825:  iload 11
L1827:  invokevirtual Method java/lang/StringBuffer append (I)Ljava/lang/StringBuffer;
L1830:  ldc ", "
L1832:  invokevirtual Method java/lang/StringBuffer append (Ljava/lang/String;)Ljava/lang/StringBuffer;
L1835:  aload 12
L1837:  invokevirtual Method java/lang/Throwable toString ()Ljava/lang/String;
L1840:  invokevirtual Method java/lang/StringBuffer append (Ljava/lang/String;)Ljava/lang/StringBuffer;
L1843:  invokevirtual Method java/lang/StringBuffer toString ()Ljava/lang/String;
L1846:  invokestatic Method sign/signlink reporterror (Ljava/lang/String;)V
L1849:  new java/lang/RuntimeException
L1852:  dup
L1853:  invokespecial Method java/lang/RuntimeException <init> ()V
L1856:  athrow
L1857:  return
L1858:  
    .end code
.end method

.method static <clinit> : ()V
    .code stack 4 locals 0
L0:     iconst_1
L1:     putstatic Field c a Z
L4:     iconst_1
L5:     putstatic Field c d Z
L8:     iconst_4
L9:     newarray int
L11:    dup
L12:    iconst_0
L13:    iconst_1
L14:    iastore
L15:    dup
L16:    iconst_1
L17:    iconst_2
L18:    iastore
L19:    dup
L20:    iconst_2
L21:    iconst_4
L22:    iastore
L23:    dup
L24:    iconst_3
L25:    bipush 8
L27:    iastore
L28:    putstatic Field c w [I
L31:    iconst_4
L32:    newarray int
L34:    dup
L35:    iconst_0
L36:    bipush 16
L38:    iastore
L39:    dup
L40:    iconst_1
L41:    bipush 32
L43:    iastore
L44:    dup
L45:    iconst_2
L46:    bipush 64
L48:    iastore
L49:    dup
L50:    iconst_3
L51:    sipush 128
L54:    iastore
L55:    putstatic Field c x [I
L58:    iconst_4
L59:    newarray int
L61:    dup
L62:    iconst_0
L63:    iconst_1
L64:    iastore
L65:    dup
L66:    iconst_2
L67:    iconst_m1
L68:    iastore
L69:    putstatic Field c y [I
L72:    iconst_4
L73:    newarray int
L75:    dup
L76:    iconst_1
L77:    iconst_m1
L78:    iastore
L79:    dup
L80:    iconst_3
L81:    iconst_1
L82:    iastore
L83:    putstatic Field c z [I
L86:    invokestatic Method java/lang/Math random ()D
L89:    ldc2_w 1.7e1
L92:    dmul
L93:    d2i
L94:    bipush 8
L96:    isub
L97:    putstatic Field c A I
L100:   invokestatic Method java/lang/Math random ()D
L103:   ldc2_w 3.3e1
L106:   dmul
L107:   d2i
L108:   bipush 16
L110:   isub
L111:   putstatic Field c B I
L114:   return
L115:   
    .end code
.end method
.end class
