.version 45 3
.class final super CRRWDRTI
.super java/lang/Object
.field private static a I
.field private b [I
.field private c [I
.field private d [I
.field private e [I
.field private f [I
.field private g [[[I
.field private h [[[B
.field static i I
.field private j Z
.field private static k I
.field private l [[[B
.field private m [[[I
.field private n [[[B
.field private static final o [I
.field private static p I
.field private q [[I
.field private static final r [I
.field private static s Z
.field private t [[[B
.field private u Z
.field private static final v [I
.field static w I
.field private x I
.field private y I
.field private z [[[B
.field private A [[[B
.field private B I
.field static C Z
.field private static final D [I
.field private static E I

.method public <init> : ([[[BIII[[[I)V
    .code stack 6 locals 7
L0:     aload_0
L1:     invokespecial Method java/lang/Object <init> ()V
L4:     aload_0
L5:     iconst_1
L6:     putfield Field CRRWDRTI j Z
L9:     aload_0
L10:    iconst_0
L11:    putfield Field CRRWDRTI u Z
L14:    aload_0
L15:    bipush -53
L17:    putfield Field CRRWDRTI B I
        .catch java/lang/RuntimeException from L20 to L243 using L244
L20:    bipush 99
L22:    putstatic Field CRRWDRTI w I
L25:    aload_0
L26:    iload 4
L28:    putfield Field CRRWDRTI x I
L31:    aload_0
L32:    iload_3
L33:    putfield Field CRRWDRTI y I
L36:    getstatic Field client Jj I
L39:    ifeq L48
L42:    sipush -320
L45:    putstatic Field CRRWDRTI E I
L48:    iload_2
L49:    ifge L42
L52:    aload_0
L53:    aload 5
L55:    putfield Field CRRWDRTI g [[[I
L58:    aload_0
L59:    aload_1
L60:    putfield Field CRRWDRTI A [[[B
L63:    aload_0
L64:    iconst_4
L65:    aload_0
L66:    getfield Field CRRWDRTI x I
L69:    aload_0
L70:    getfield Field CRRWDRTI y I
L73:    multianewarray [[[B 3
L77:    putfield Field CRRWDRTI t [[[B
L80:    aload_0
L81:    iconst_4
L82:    aload_0
L83:    getfield Field CRRWDRTI x I
L86:    aload_0
L87:    getfield Field CRRWDRTI y I
L90:    multianewarray [[[B 3
L94:    putfield Field CRRWDRTI h [[[B
L97:    aload_0
L98:    iconst_4
L99:    aload_0
L100:   getfield Field CRRWDRTI x I
L103:   aload_0
L104:   getfield Field CRRWDRTI y I
L107:   multianewarray [[[B 3
L111:   putfield Field CRRWDRTI n [[[B
L114:   aload_0
L115:   iconst_4
L116:   aload_0
L117:   getfield Field CRRWDRTI x I
L120:   aload_0
L121:   getfield Field CRRWDRTI y I
L124:   multianewarray [[[B 3
L128:   putfield Field CRRWDRTI z [[[B
L131:   aload_0
L132:   iconst_4
L133:   aload_0
L134:   getfield Field CRRWDRTI x I
L137:   iconst_1
L138:   iadd
L139:   aload_0
L140:   getfield Field CRRWDRTI y I
L143:   iconst_1
L144:   iadd
L145:   multianewarray [[[I 3
L149:   putfield Field CRRWDRTI m [[[I
L152:   aload_0
L153:   iconst_4
L154:   aload_0
L155:   getfield Field CRRWDRTI x I
L158:   iconst_1
L159:   iadd
L160:   aload_0
L161:   getfield Field CRRWDRTI y I
L164:   iconst_1
L165:   iadd
L166:   multianewarray [[[B 3
L170:   putfield Field CRRWDRTI l [[[B
L173:   aload_0
L174:   aload_0
L175:   getfield Field CRRWDRTI x I
L178:   iconst_1
L179:   iadd
L180:   aload_0
L181:   getfield Field CRRWDRTI y I
L184:   iconst_1
L185:   iadd
L186:   multianewarray [[I 2
L190:   putfield Field CRRWDRTI q [[I
L193:   aload_0
L194:   aload_0
L195:   getfield Field CRRWDRTI y I
L198:   newarray int
L200:   putfield Field CRRWDRTI b [I
L203:   aload_0
L204:   aload_0
L205:   getfield Field CRRWDRTI y I
L208:   newarray int
L210:   putfield Field CRRWDRTI c [I
L213:   aload_0
L214:   aload_0
L215:   getfield Field CRRWDRTI y I
L218:   newarray int
L220:   putfield Field CRRWDRTI d [I
L223:   aload_0
L224:   aload_0
L225:   getfield Field CRRWDRTI y I
L228:   newarray int
L230:   putfield Field CRRWDRTI e [I
L233:   aload_0
L234:   aload_0
L235:   getfield Field CRRWDRTI y I
L238:   newarray int
L240:   putfield Field CRRWDRTI f [I
L243:   return
L244:   astore 6
L246:   new java/lang/StringBuffer
L249:   dup
L250:   ldc "40803, "
L252:   invokespecial Method java/lang/StringBuffer <init> (Ljava/lang/String;)V
L255:   aload_1
L256:   invokevirtual Method java/lang/StringBuffer append (Ljava/lang/Object;)Ljava/lang/StringBuffer;
L259:   ldc ", "
L261:   invokevirtual Method java/lang/StringBuffer append (Ljava/lang/String;)Ljava/lang/StringBuffer;
L264:   iload_2
L265:   invokevirtual Method java/lang/StringBuffer append (I)Ljava/lang/StringBuffer;
L268:   ldc ", "
L270:   invokevirtual Method java/lang/StringBuffer append (Ljava/lang/String;)Ljava/lang/StringBuffer;
L273:   iload_3
L274:   invokevirtual Method java/lang/StringBuffer append (I)Ljava/lang/StringBuffer;
L277:   ldc ", "
L279:   invokevirtual Method java/lang/StringBuffer append (Ljava/lang/String;)Ljava/lang/StringBuffer;
L282:   iload 4
L284:   invokevirtual Method java/lang/StringBuffer append (I)Ljava/lang/StringBuffer;
L287:   ldc ", "
L289:   invokevirtual Method java/lang/StringBuffer append (Ljava/lang/String;)Ljava/lang/StringBuffer;
L292:   aload 5
L294:   invokevirtual Method java/lang/StringBuffer append (Ljava/lang/Object;)Ljava/lang/StringBuffer;
L297:   ldc ", "
L299:   invokevirtual Method java/lang/StringBuffer append (Ljava/lang/String;)Ljava/lang/StringBuffer;
L302:   aload 6
L304:   invokevirtual Method java/lang/Throwable toString ()Ljava/lang/String;
L307:   invokevirtual Method java/lang/StringBuffer append (Ljava/lang/String;)Ljava/lang/StringBuffer;
L310:   invokevirtual Method java/lang/StringBuffer toString ()Ljava/lang/String;
L313:   invokestatic Method sign/signlink reporterror (Ljava/lang/String;)V
L316:   new java/lang/RuntimeException
L319:   dup
L320:   invokespecial Method java/lang/RuntimeException <init> ()V
L323:   athrow
L324:   
    .end code
.end method

.method private static final a : (II)I
    .code stack 3 locals 4
L0:     iload_0
L1:     iload_1
L2:     bipush 57
L4:     imul
L5:     iadd
L6:     istore_2
L7:     iload_2
L8:     bipush 13
L10:    ishl
L11:    iload_2
L12:    ixor
L13:    istore_2
L14:    iload_2
L15:    iload_2
L16:    iload_2
L17:    imul
L18:    sipush 15731
L21:    imul
L22:    ldc 789221
L24:    iadd
L25:    imul
L26:    ldc 1376312589
L28:    iadd
L29:    ldc 2147483647
L31:    iand
L32:    istore_3
L33:    iload_3
L34:    bipush 19
L36:    ishr
L37:    sipush 255
L40:    iand
L41:    ireturn
L42:    
    .end code
.end method

.method public final a : ([LFTPNODIB;LNYFUGYQS;I)V
    .code stack 22 locals 46
L0:     getstatic Field client Jj I
L3:     istore 45
        .catch java/lang/RuntimeException from L5 to L3296 using L3297
L5:     iconst_0
L6:     istore 4
L8:     iload 45
L10:    ifeq L113
L13:    iconst_0
L14:    istore 5
L16:    iload 45
L18:    ifeq L103
L21:    iconst_0
L22:    istore 6
L24:    iload 45
L26:    ifeq L93
L29:    aload_0
L30:    getfield Field CRRWDRTI A [[[B
L33:    iload 4
L35:    aaload
L36:    iload 5
L38:    aaload
L39:    iload 6
L41:    baload
L42:    iconst_1
L43:    iand
L44:    iconst_1
L45:    if_icmpne L90
L48:    iload 4
L50:    istore 7
L52:    aload_0
L53:    getfield Field CRRWDRTI A [[[B
L56:    iconst_1
L57:    aaload
L58:    iload 5
L60:    aaload
L61:    iload 6
L63:    baload
L64:    iconst_2
L65:    iand
L66:    iconst_2
L67:    if_icmpne L73
L70:    iinc 7 -1
L73:    iload 7
L75:    iflt L90
L78:    aload_1
L79:    iload 7
L81:    aaload
L82:    iload 6
L84:    iconst_0
L85:    iload 5
L87:    invokevirtual Method FTPNODIB a (III)V
L90:    iinc 6 1
L93:    iload 6
L95:    bipush 104
L97:    if_icmplt L29
L100:   iinc 5 1
L103:   iload 5
L105:   bipush 104
L107:   if_icmplt L21
L110:   iinc 4 1
L113:   iload 4
L115:   iconst_4
L116:   if_icmplt L13
L119:   iload_3
L120:   iconst_2
L121:   if_icmplt L129
L124:   iload_3
L125:   iconst_2
L126:   if_icmple L135
L129:   sipush 329
L132:   putstatic Field CRRWDRTI p I
L135:   getstatic Field CRRWDRTI a I
L138:   invokestatic Method java/lang/Math random ()D
L141:   ldc2_w 5e0
L144:   dmul
L145:   d2i
L146:   iconst_2
L147:   isub
L148:   iadd
L149:   putstatic Field CRRWDRTI a I
L152:   getstatic Field CRRWDRTI a I
L155:   bipush -8
L157:   if_icmpge L165
L160:   bipush -8
L162:   putstatic Field CRRWDRTI a I
L165:   getstatic Field CRRWDRTI a I
L168:   bipush 8
L170:   if_icmple L178
L173:   bipush 8
L175:   putstatic Field CRRWDRTI a I
L178:   getstatic Field CRRWDRTI k I
L181:   invokestatic Method java/lang/Math random ()D
L184:   ldc2_w 5e0
L187:   dmul
L188:   d2i
L189:   iconst_2
L190:   isub
L191:   iadd
L192:   putstatic Field CRRWDRTI k I
L195:   getstatic Field CRRWDRTI k I
L198:   bipush -16
L200:   if_icmpge L208
L203:   bipush -16
L205:   putstatic Field CRRWDRTI k I
L208:   getstatic Field CRRWDRTI k I
L211:   bipush 16
L213:   if_icmple L221
L216:   bipush 16
L218:   putstatic Field CRRWDRTI k I
L221:   iconst_0
L222:   istore 5
L224:   iload 45
L226:   ifeq L1971
L229:   aload_0
L230:   getfield Field CRRWDRTI l [[[B
L233:   iload 5
L235:   aaload
L236:   astore 6
L238:   bipush 96
L240:   istore 7
L242:   sipush 768
L245:   istore 8
L247:   bipush -50
L249:   istore 9
L251:   bipush -10
L253:   istore 10
L255:   bipush -50
L257:   istore 11
L259:   iload 9
L261:   iload 9
L263:   imul
L264:   iload 10
L266:   iload 10
L268:   imul
L269:   iadd
L270:   iload 11
L272:   iload 11
L274:   imul
L275:   iadd
L276:   i2d
L277:   invokestatic Method java/lang/Math sqrt (D)D
L280:   d2i
L281:   istore 12
L283:   iload 8
L285:   iload 12
L287:   imul
L288:   bipush 8
L290:   ishr
L291:   istore 13
L293:   iconst_1
L294:   istore 14
L296:   iload 45
L298:   ifeq L544
L301:   iconst_1
L302:   istore 15
L304:   iload 45
L306:   ifeq L530
L309:   aload_0
L310:   getfield Field CRRWDRTI g [[[I
L313:   iload 5
L315:   aaload
L316:   iload 15
L318:   iconst_1
L319:   iadd
L320:   aaload
L321:   iload 14
L323:   iaload
L324:   aload_0
L325:   getfield Field CRRWDRTI g [[[I
L328:   iload 5
L330:   aaload
L331:   iload 15
L333:   iconst_1
L334:   isub
L335:   aaload
L336:   iload 14
L338:   iaload
L339:   isub
L340:   istore 16
L342:   aload_0
L343:   getfield Field CRRWDRTI g [[[I
L346:   iload 5
L348:   aaload
L349:   iload 15
L351:   aaload
L352:   iload 14
L354:   iconst_1
L355:   iadd
L356:   iaload
L357:   aload_0
L358:   getfield Field CRRWDRTI g [[[I
L361:   iload 5
L363:   aaload
L364:   iload 15
L366:   aaload
L367:   iload 14
L369:   iconst_1
L370:   isub
L371:   iaload
L372:   isub
L373:   istore 17
L375:   iload 16
L377:   iload 16
L379:   imul
L380:   ldc 65536
L382:   iadd
L383:   iload 17
L385:   iload 17
L387:   imul
L388:   iadd
L389:   i2d
L390:   invokestatic Method java/lang/Math sqrt (D)D
L393:   d2i
L394:   istore 18
L396:   iload 16
L398:   bipush 8
L400:   ishl
L401:   iload 18
L403:   idiv
L404:   istore 19
L406:   ldc 65536
L408:   iload 18
L410:   idiv
L411:   istore 20
L413:   iload 17
L415:   bipush 8
L417:   ishl
L418:   iload 18
L420:   idiv
L421:   istore 21
L423:   iload 7
L425:   iload 9
L427:   iload 19
L429:   imul
L430:   iload 10
L432:   iload 20
L434:   imul
L435:   iadd
L436:   iload 11
L438:   iload 21
L440:   imul
L441:   iadd
L442:   iload 13
L444:   idiv
L445:   iadd
L446:   istore 22
L448:   aload 6
L450:   iload 15
L452:   iconst_1
L453:   isub
L454:   aaload
L455:   iload 14
L457:   baload
L458:   iconst_2
L459:   ishr
L460:   aload 6
L462:   iload 15
L464:   iconst_1
L465:   iadd
L466:   aaload
L467:   iload 14
L469:   baload
L470:   iconst_3
L471:   ishr
L472:   iadd
L473:   aload 6
L475:   iload 15
L477:   aaload
L478:   iload 14
L480:   iconst_1
L481:   isub
L482:   baload
L483:   iconst_2
L484:   ishr
L485:   iadd
L486:   aload 6
L488:   iload 15
L490:   aaload
L491:   iload 14
L493:   iconst_1
L494:   iadd
L495:   baload
L496:   iconst_3
L497:   ishr
L498:   iadd
L499:   aload 6
L501:   iload 15
L503:   aaload
L504:   iload 14
L506:   baload
L507:   iconst_1
L508:   ishr
L509:   iadd
L510:   istore 23
L512:   aload_0
L513:   getfield Field CRRWDRTI q [[I
L516:   iload 15
L518:   aaload
L519:   iload 14
L521:   iload 22
L523:   iload 23
L525:   isub
L526:   iastore
L527:   iinc 15 1
L530:   iload 15
L532:   aload_0
L533:   getfield Field CRRWDRTI x I
L536:   iconst_1
L537:   isub
L538:   if_icmplt L309
L541:   iinc 14 1
L544:   iload 14
L546:   aload_0
L547:   getfield Field CRRWDRTI y I
L550:   iconst_1
L551:   isub
L552:   if_icmplt L301
L555:   iconst_0
L556:   istore 15
L558:   iload 45
L560:   ifeq L606
L563:   aload_0
L564:   getfield Field CRRWDRTI b [I
L567:   iload 15
L569:   iconst_0
L570:   iastore
L571:   aload_0
L572:   getfield Field CRRWDRTI c [I
L575:   iload 15
L577:   iconst_0
L578:   iastore
L579:   aload_0
L580:   getfield Field CRRWDRTI d [I
L583:   iload 15
L585:   iconst_0
L586:   iastore
L587:   aload_0
L588:   getfield Field CRRWDRTI e [I
L591:   iload 15
L593:   iconst_0
L594:   iastore
L595:   aload_0
L596:   getfield Field CRRWDRTI f [I
L599:   iload 15
L601:   iconst_0
L602:   iastore
L603:   iinc 15 1
L606:   iload 15
L608:   aload_0
L609:   getfield Field CRRWDRTI y I
L612:   if_icmplt L563
L615:   bipush -5
L617:   istore 16
L619:   iload 45
L621:   ifeq L1892
L624:   iconst_0
L625:   istore 17
L627:   iload 45
L629:   ifeq L885
L632:   iload 16
L634:   iconst_5
L635:   iadd
L636:   istore 18
L638:   iload 18
L640:   iflt L757
L643:   iload 18
L645:   aload_0
L646:   getfield Field CRRWDRTI x I
L649:   if_icmpge L757
L652:   aload_0
L653:   getfield Field CRRWDRTI t [[[B
L656:   iload 5
L658:   aaload
L659:   iload 18
L661:   aaload
L662:   iload 17
L664:   baload
L665:   sipush 255
L668:   iand
L669:   istore 19
L671:   iload 19
L673:   ifle L757
L676:   getstatic Field MNHKFPQO d [LMNHKFPQO;
L679:   iload 19
L681:   iconst_1
L682:   isub
L683:   aaload
L684:   astore 20
L686:   aload_0
L687:   getfield Field CRRWDRTI b [I
L690:   iload 17
L692:   dup2
L693:   iaload
L694:   aload 20
L696:   getfield Field MNHKFPQO m I
L699:   iadd
L700:   iastore
L701:   aload_0
L702:   getfield Field CRRWDRTI c [I
L705:   iload 17
L707:   dup2
L708:   iaload
L709:   aload 20
L711:   getfield Field MNHKFPQO k I
L714:   iadd
L715:   iastore
L716:   aload_0
L717:   getfield Field CRRWDRTI d [I
L720:   iload 17
L722:   dup2
L723:   iaload
L724:   aload 20
L726:   getfield Field MNHKFPQO l I
L729:   iadd
L730:   iastore
L731:   aload_0
L732:   getfield Field CRRWDRTI e [I
L735:   iload 17
L737:   dup2
L738:   iaload
L739:   aload 20
L741:   getfield Field MNHKFPQO n I
L744:   iadd
L745:   iastore
L746:   aload_0
L747:   getfield Field CRRWDRTI f [I
L750:   iload 17
L752:   dup2
L753:   iaload
L754:   iconst_1
L755:   iadd
L756:   iastore
L757:   iload 16
L759:   iconst_5
L760:   isub
L761:   istore 19
L763:   iload 19
L765:   iflt L882
L768:   iload 19
L770:   aload_0
L771:   getfield Field CRRWDRTI x I
L774:   if_icmpge L882
L777:   aload_0
L778:   getfield Field CRRWDRTI t [[[B
L781:   iload 5
L783:   aaload
L784:   iload 19
L786:   aaload
L787:   iload 17
L789:   baload
L790:   sipush 255
L793:   iand
L794:   istore 20
L796:   iload 20
L798:   ifle L882
L801:   getstatic Field MNHKFPQO d [LMNHKFPQO;
L804:   iload 20
L806:   iconst_1
L807:   isub
L808:   aaload
L809:   astore 21
L811:   aload_0
L812:   getfield Field CRRWDRTI b [I
L815:   iload 17
L817:   dup2
L818:   iaload
L819:   aload 21
L821:   getfield Field MNHKFPQO m I
L824:   isub
L825:   iastore
L826:   aload_0
L827:   getfield Field CRRWDRTI c [I
L830:   iload 17
L832:   dup2
L833:   iaload
L834:   aload 21
L836:   getfield Field MNHKFPQO k I
L839:   isub
L840:   iastore
L841:   aload_0
L842:   getfield Field CRRWDRTI d [I
L845:   iload 17
L847:   dup2
L848:   iaload
L849:   aload 21
L851:   getfield Field MNHKFPQO l I
L854:   isub
L855:   iastore
L856:   aload_0
L857:   getfield Field CRRWDRTI e [I
L860:   iload 17
L862:   dup2
L863:   iaload
L864:   aload 21
L866:   getfield Field MNHKFPQO n I
L869:   isub
L870:   iastore
L871:   aload_0
L872:   getfield Field CRRWDRTI f [I
L875:   iload 17
L877:   dup2
L878:   iaload
L879:   iconst_1
L880:   isub
L881:   iastore
L882:   iinc 17 1
L885:   iload 17
L887:   aload_0
L888:   getfield Field CRRWDRTI y I
L891:   if_icmplt L632
L894:   iload 16
L896:   iconst_1
L897:   if_icmplt L1889
L900:   iload 16
L902:   aload_0
L903:   getfield Field CRRWDRTI x I
L906:   iconst_1
L907:   isub
L908:   if_icmpge L1889
L911:   iconst_0
L912:   istore 18
L914:   iconst_0
L915:   istore 19
L917:   iconst_0
L918:   istore 20
L920:   iconst_0
L921:   istore 21
L923:   iconst_0
L924:   istore 22
L926:   bipush -5
L928:   istore 23
L930:   iload 45
L932:   ifeq L1878
L935:   iload 23
L937:   iconst_5
L938:   iadd
L939:   istore 24
L941:   iload 24
L943:   iflt L1015
L946:   iload 24
L948:   aload_0
L949:   getfield Field CRRWDRTI y I
L952:   if_icmpge L1015
L955:   iload 18
L957:   aload_0
L958:   getfield Field CRRWDRTI b [I
L961:   iload 24
L963:   iaload
L964:   iadd
L965:   istore 18
L967:   iload 19
L969:   aload_0
L970:   getfield Field CRRWDRTI c [I
L973:   iload 24
L975:   iaload
L976:   iadd
L977:   istore 19
L979:   iload 20
L981:   aload_0
L982:   getfield Field CRRWDRTI d [I
L985:   iload 24
L987:   iaload
L988:   iadd
L989:   istore 20
L991:   iload 21
L993:   aload_0
L994:   getfield Field CRRWDRTI e [I
L997:   iload 24
L999:   iaload
L1000:  iadd
L1001:  istore 21
L1003:  iload 22
L1005:  aload_0
L1006:  getfield Field CRRWDRTI f [I
L1009:  iload 24
L1011:  iaload
L1012:  iadd
L1013:  istore 22
L1015:  iload 23
L1017:  iconst_5
L1018:  isub
L1019:  istore 25
L1021:  iload 25
L1023:  iflt L1095
L1026:  iload 25
L1028:  aload_0
L1029:  getfield Field CRRWDRTI y I
L1032:  if_icmpge L1095
L1035:  iload 18
L1037:  aload_0
L1038:  getfield Field CRRWDRTI b [I
L1041:  iload 25
L1043:  iaload
L1044:  isub
L1045:  istore 18
L1047:  iload 19
L1049:  aload_0
L1050:  getfield Field CRRWDRTI c [I
L1053:  iload 25
L1055:  iaload
L1056:  isub
L1057:  istore 19
L1059:  iload 20
L1061:  aload_0
L1062:  getfield Field CRRWDRTI d [I
L1065:  iload 25
L1067:  iaload
L1068:  isub
L1069:  istore 20
L1071:  iload 21
L1073:  aload_0
L1074:  getfield Field CRRWDRTI e [I
L1077:  iload 25
L1079:  iaload
L1080:  isub
L1081:  istore 21
L1083:  iload 22
L1085:  aload_0
L1086:  getfield Field CRRWDRTI f [I
L1089:  iload 25
L1091:  iaload
L1092:  isub
L1093:  istore 22
L1095:  iload 23
L1097:  iconst_1
L1098:  if_icmplt L1875
L1101:  iload 23
L1103:  aload_0
L1104:  getfield Field CRRWDRTI y I
L1107:  iconst_1
L1108:  isub
L1109:  if_icmpge L1875
L1112:  getstatic Field CRRWDRTI C Z
L1115:  ifeq L1174
L1118:  aload_0
L1119:  getfield Field CRRWDRTI A [[[B
L1122:  iconst_0
L1123:  aaload
L1124:  iload 16
L1126:  aaload
L1127:  iload 23
L1129:  baload
L1130:  iconst_2
L1131:  iand
L1132:  ifne L1174
L1135:  aload_0
L1136:  getfield Field CRRWDRTI A [[[B
L1139:  iload 5
L1141:  aaload
L1142:  iload 16
L1144:  aaload
L1145:  iload 23
L1147:  baload
L1148:  bipush 16
L1150:  iand
L1151:  ifne L1875
L1154:  aload_0
L1155:  iload 23
L1157:  iload 5
L1159:  iload 16
L1161:  iconst_0
L1162:  invokevirtual Method CRRWDRTI a (IIII)I
L1165:  getstatic Field CRRWDRTI i I
L1168:  if_icmpeq L1174
L1171:  goto L1875
L1174:  iload 5
L1176:  getstatic Field CRRWDRTI w I
L1179:  if_icmpge L1187
L1182:  iload 5
L1184:  putstatic Field CRRWDRTI w I
L1187:  aload_0
L1188:  getfield Field CRRWDRTI t [[[B
L1191:  iload 5
L1193:  aaload
L1194:  iload 16
L1196:  aaload
L1197:  iload 23
L1199:  baload
L1200:  sipush 255
L1203:  iand
L1204:  istore 26
L1206:  aload_0
L1207:  getfield Field CRRWDRTI h [[[B
L1210:  iload 5
L1212:  aaload
L1213:  iload 16
L1215:  aaload
L1216:  iload 23
L1218:  baload
L1219:  sipush 255
L1222:  iand
L1223:  istore 27
L1225:  iload 26
L1227:  ifgt L1235
L1230:  iload 27
L1232:  ifle L1875
L1235:  aload_0
L1236:  getfield Field CRRWDRTI g [[[I
L1239:  iload 5
L1241:  aaload
L1242:  iload 16
L1244:  aaload
L1245:  iload 23
L1247:  iaload
L1248:  istore 28
L1250:  aload_0
L1251:  getfield Field CRRWDRTI g [[[I
L1254:  iload 5
L1256:  aaload
L1257:  iload 16
L1259:  iconst_1
L1260:  iadd
L1261:  aaload
L1262:  iload 23
L1264:  iaload
L1265:  istore 29
L1267:  aload_0
L1268:  getfield Field CRRWDRTI g [[[I
L1271:  iload 5
L1273:  aaload
L1274:  iload 16
L1276:  iconst_1
L1277:  iadd
L1278:  aaload
L1279:  iload 23
L1281:  iconst_1
L1282:  iadd
L1283:  iaload
L1284:  istore 30
L1286:  aload_0
L1287:  getfield Field CRRWDRTI g [[[I
L1290:  iload 5
L1292:  aaload
L1293:  iload 16
L1295:  aaload
L1296:  iload 23
L1298:  iconst_1
L1299:  iadd
L1300:  iaload
L1301:  istore 31
L1303:  aload_0
L1304:  getfield Field CRRWDRTI q [[I
L1307:  iload 16
L1309:  aaload
L1310:  iload 23
L1312:  iaload
L1313:  istore 32
L1315:  aload_0
L1316:  getfield Field CRRWDRTI q [[I
L1319:  iload 16
L1321:  iconst_1
L1322:  iadd
L1323:  aaload
L1324:  iload 23
L1326:  iaload
L1327:  istore 33
L1329:  aload_0
L1330:  getfield Field CRRWDRTI q [[I
L1333:  iload 16
L1335:  iconst_1
L1336:  iadd
L1337:  aaload
L1338:  iload 23
L1340:  iconst_1
L1341:  iadd
L1342:  iaload
L1343:  istore 34
L1345:  aload_0
L1346:  getfield Field CRRWDRTI q [[I
L1349:  iload 16
L1351:  aaload
L1352:  iload 23
L1354:  iconst_1
L1355:  iadd
L1356:  iaload
L1357:  istore 35
L1359:  iconst_m1
L1360:  istore 36
L1362:  iconst_m1
L1363:  istore 37
L1365:  iload 26
L1367:  ifle L1465
L1370:  iload 18
L1372:  sipush 256
L1375:  imul
L1376:  iload 21
L1378:  idiv
L1379:  istore 38
L1381:  iload 19
L1383:  iload 22
L1385:  idiv
L1386:  istore 39
L1388:  iload 20
L1390:  iload 22
L1392:  idiv
L1393:  istore 40
L1395:  aload_0
L1396:  iload 38
L1398:  iload 39
L1400:  iload 40
L1402:  invokespecial Method CRRWDRTI b (III)I
L1405:  istore 36
L1407:  iload 38
L1409:  getstatic Field CRRWDRTI a I
L1412:  iadd
L1413:  sipush 255
L1416:  iand
L1417:  istore 38
L1419:  iload 40
L1421:  getstatic Field CRRWDRTI k I
L1424:  iadd
L1425:  istore 40
L1427:  iload 40
L1429:  ifge L1440
L1432:  iconst_0
L1433:  istore 40
L1435:  iload 45
L1437:  ifeq L1453
L1440:  iload 40
L1442:  sipush 255
L1445:  if_icmple L1453
L1448:  sipush 255
L1451:  istore 40
L1453:  aload_0
L1454:  iload 38
L1456:  iload 39
L1458:  iload 40
L1460:  invokespecial Method CRRWDRTI b (III)I
L1463:  istore 37
L1465:  iload 5
L1467:  ifle L1564
L1470:  iconst_1
L1471:  istore 38
L1473:  iload 26
L1475:  ifne L1497
L1478:  aload_0
L1479:  getfield Field CRRWDRTI n [[[B
L1482:  iload 5
L1484:  aaload
L1485:  iload 16
L1487:  aaload
L1488:  iload 23
L1490:  baload
L1491:  ifeq L1497
L1494:  iconst_0
L1495:  istore 38
L1497:  iload 27
L1499:  ifle L1519
L1502:  getstatic Field MNHKFPQO d [LMNHKFPQO;
L1505:  iload 27
L1507:  iconst_1
L1508:  isub
L1509:  aaload
L1510:  getfield Field MNHKFPQO i Z
L1513:  ifne L1519
L1516:  iconst_0
L1517:  istore 38
L1519:  iload 38
L1521:  ifeq L1564
L1524:  iload 28
L1526:  iload 29
L1528:  if_icmpne L1564
L1531:  iload 28
L1533:  iload 30
L1535:  if_icmpne L1564
L1538:  iload 28
L1540:  iload 31
L1542:  if_icmpne L1564
L1545:  aload_0
L1546:  getfield Field CRRWDRTI m [[[I
L1549:  iload 5
L1551:  aaload
L1552:  iload 16
L1554:  aaload
L1555:  iload 23
L1557:  dup2
L1558:  iaload
L1559:  sipush 2340
L1562:  ior
L1563:  iastore
L1564:  iconst_0
L1565:  istore 38
L1567:  iload 36
L1569:  iconst_m1
L1570:  if_icmpeq L1586
L1573:  getstatic Field OPPOFIOL V [I
L1576:  iload 37
L1578:  bipush 96
L1580:  invokestatic Method CRRWDRTI e (II)I
L1583:  iaload
L1584:  istore 38
L1586:  iload 27
L1588:  ifne L1652
L1591:  aload_2
L1592:  iload 5
L1594:  iload 16
L1596:  iload 23
L1598:  iconst_0
L1599:  iconst_0
L1600:  iconst_m1
L1601:  iload 28
L1603:  iload 29
L1605:  iload 30
L1607:  iload 31
L1609:  iload 36
L1611:  iload 32
L1613:  invokestatic Method CRRWDRTI e (II)I
L1616:  iload 36
L1618:  iload 33
L1620:  invokestatic Method CRRWDRTI e (II)I
L1623:  iload 36
L1625:  iload 34
L1627:  invokestatic Method CRRWDRTI e (II)I
L1630:  iload 36
L1632:  iload 35
L1634:  invokestatic Method CRRWDRTI e (II)I
L1637:  iconst_0
L1638:  iconst_0
L1639:  iconst_0
L1640:  iconst_0
L1641:  iload 38
L1643:  iconst_0
L1644:  invokevirtual Method NYFUGYQS a (IIIIIIIIIIIIIIIIIIII)V
L1647:  iload 45
L1649:  ifeq L1875
L1652:  aload_0
L1653:  getfield Field CRRWDRTI n [[[B
L1656:  iload 5
L1658:  aaload
L1659:  iload 16
L1661:  aaload
L1662:  iload 23
L1664:  baload
L1665:  iconst_1
L1666:  iadd
L1667:  istore 39
L1669:  aload_0
L1670:  getfield Field CRRWDRTI z [[[B
L1673:  iload 5
L1675:  aaload
L1676:  iload 16
L1678:  aaload
L1679:  iload 23
L1681:  baload
L1682:  istore 40
L1684:  getstatic Field MNHKFPQO d [LMNHKFPQO;
L1687:  iload 27
L1689:  iconst_1
L1690:  isub
L1691:  aaload
L1692:  astore 41
L1694:  aload 41
L1696:  getfield Field MNHKFPQO g I
L1699:  istore 42
L1701:  iload 42
L1703:  iflt L1724
L1706:  iload 42
L1708:  sipush 12660
L1711:  invokestatic Method OPPOFIOL a (II)I
L1714:  istore 44
L1716:  iconst_m1
L1717:  istore 43
L1719:  iload 45
L1721:  ifeq L1787
L1724:  aload 41
L1726:  getfield Field MNHKFPQO f I
L1729:  ldc 16711935
L1731:  if_icmpne L1749
L1734:  iconst_0
L1735:  istore 44
L1737:  bipush -2
L1739:  istore 43
L1741:  iconst_m1
L1742:  istore 42
L1744:  iload 45
L1746:  ifeq L1787
L1749:  aload_0
L1750:  aload 41
L1752:  getfield Field MNHKFPQO j I
L1755:  aload 41
L1757:  getfield Field MNHKFPQO k I
L1760:  aload 41
L1762:  getfield Field MNHKFPQO l I
L1765:  invokespecial Method CRRWDRTI b (III)I
L1768:  istore 43
L1770:  getstatic Field OPPOFIOL V [I
L1773:  aload_0
L1774:  aload 41
L1776:  getfield Field MNHKFPQO o I
L1779:  bipush 96
L1781:  invokespecial Method CRRWDRTI c (II)I
L1784:  iaload
L1785:  istore 44
L1787:  aload_2
L1788:  iload 5
L1790:  iload 16
L1792:  iload 23
L1794:  iload 39
L1796:  iload 40
L1798:  iload 42
L1800:  iload 28
L1802:  iload 29
L1804:  iload 30
L1806:  iload 31
L1808:  iload 36
L1810:  iload 32
L1812:  invokestatic Method CRRWDRTI e (II)I
L1815:  iload 36
L1817:  iload 33
L1819:  invokestatic Method CRRWDRTI e (II)I
L1822:  iload 36
L1824:  iload 34
L1826:  invokestatic Method CRRWDRTI e (II)I
L1829:  iload 36
L1831:  iload 35
L1833:  invokestatic Method CRRWDRTI e (II)I
L1836:  aload_0
L1837:  iload 43
L1839:  iload 32
L1841:  invokespecial Method CRRWDRTI c (II)I
L1844:  aload_0
L1845:  iload 43
L1847:  iload 33
L1849:  invokespecial Method CRRWDRTI c (II)I
L1852:  aload_0
L1853:  iload 43
L1855:  iload 34
L1857:  invokespecial Method CRRWDRTI c (II)I
L1860:  aload_0
L1861:  iload 43
L1863:  iload 35
L1865:  invokespecial Method CRRWDRTI c (II)I
L1868:  iload 38
L1870:  iload 44
L1872:  invokevirtual Method NYFUGYQS a (IIIIIIIIIIIIIIIIIIII)V
L1875:  iinc 23 1
L1878:  iload 23
L1880:  aload_0
L1881:  getfield Field CRRWDRTI y I
L1884:  iconst_5
L1885:  iadd
L1886:  if_icmplt L935
L1889:  iinc 16 1
L1892:  iload 16
L1894:  aload_0
L1895:  getfield Field CRRWDRTI x I
L1898:  iconst_5
L1899:  iadd
L1900:  if_icmplt L624
L1903:  iconst_1
L1904:  istore 17
L1906:  iload 45
L1908:  ifeq L1957
L1911:  iconst_1
L1912:  istore 18
L1914:  iload 45
L1916:  ifeq L1943
L1919:  aload_2
L1920:  iload 5
L1922:  iload 18
L1924:  iload 17
L1926:  aload_0
L1927:  iload 17
L1929:  iload 5
L1931:  iload 18
L1933:  iconst_0
L1934:  invokevirtual Method CRRWDRTI a (IIII)I
L1937:  invokevirtual Method NYFUGYQS a (IIII)V
L1940:  iinc 18 1
L1943:  iload 18
L1945:  aload_0
L1946:  getfield Field CRRWDRTI x I
L1949:  iconst_1
L1950:  isub
L1951:  if_icmplt L1919
L1954:  iinc 17 1
L1957:  iload 17
L1959:  aload_0
L1960:  getfield Field CRRWDRTI y I
L1963:  iconst_1
L1964:  isub
L1965:  if_icmplt L1911
L1968:  iinc 5 1
L1971:  iload 5
L1973:  iconst_4
L1974:  if_icmplt L229
L1977:  aload_2
L1978:  bipush -10
L1980:  iconst_3
L1981:  bipush 64
L1983:  bipush -50
L1985:  sipush 768
L1988:  bipush -50
L1990:  invokevirtual Method NYFUGYQS a (IBIIII)V
L1993:  iconst_0
L1994:  istore 6
L1996:  iload 45
L1998:  ifeq L2053
L2001:  iconst_0
L2002:  istore 7
L2004:  iload 45
L2006:  ifeq L2041
L2009:  aload_0
L2010:  getfield Field CRRWDRTI A [[[B
L2013:  iconst_1
L2014:  aaload
L2015:  iload 6
L2017:  aaload
L2018:  iload 7
L2020:  baload
L2021:  iconst_2
L2022:  iand
L2023:  iconst_2
L2024:  if_icmpne L2038
L2027:  aload_2
L2028:  iload 7
L2030:  iload 6
L2032:  sipush -438
L2035:  invokevirtual Method NYFUGYQS a (III)V
L2038:  iinc 7 1
L2041:  iload 7
L2043:  aload_0
L2044:  getfield Field CRRWDRTI y I
L2047:  if_icmplt L2009
L2050:  iinc 6 1
L2053:  iload 6
L2055:  aload_0
L2056:  getfield Field CRRWDRTI x I
L2059:  if_icmplt L2001
L2062:  iconst_1
L2063:  istore 7
L2065:  iconst_2
L2066:  istore 8
L2068:  iconst_4
L2069:  istore 9
L2071:  iconst_0
L2072:  istore 10
L2074:  iload 45
L2076:  ifeq L3290
L2079:  iload 10
L2081:  ifle L2102
L2084:  iload 7
L2086:  iconst_3
L2087:  ishl
L2088:  istore 7
L2090:  iload 8
L2092:  iconst_3
L2093:  ishl
L2094:  istore 8
L2096:  iload 9
L2098:  iconst_3
L2099:  ishl
L2100:  istore 9
L2102:  iconst_0
L2103:  istore 11
L2105:  iload 45
L2107:  ifeq L3280
L2110:  iconst_0
L2111:  istore 12
L2113:  iload 45
L2115:  ifeq L3268
L2118:  iconst_0
L2119:  istore 13
L2121:  iload 45
L2123:  ifeq L3256
L2126:  aload_0
L2127:  getfield Field CRRWDRTI m [[[I
L2130:  iload 11
L2132:  aaload
L2133:  iload 13
L2135:  aaload
L2136:  iload 12
L2138:  iaload
L2139:  iload 7
L2141:  iand
L2142:  ifeq L2509
L2145:  iload 12
L2147:  istore 14
L2149:  iload 12
L2151:  istore 15
L2153:  iload 11
L2155:  istore 16
L2157:  iload 11
L2159:  istore 17
L2161:  iload 45
L2163:  ifeq L2169
L2166:  iinc 14 -1
L2169:  iload 14
L2171:  ifle L2203
L2174:  aload_0
L2175:  getfield Field CRRWDRTI m [[[I
L2178:  iload 11
L2180:  aaload
L2181:  iload 13
L2183:  aaload
L2184:  iload 14
L2186:  iconst_1
L2187:  isub
L2188:  iaload
L2189:  iload 7
L2191:  iand
L2192:  ifne L2166
L2195:  iload 45
L2197:  ifeq L2203
L2200:  iinc 15 1
L2203:  iload 15
L2205:  aload_0
L2206:  getfield Field CRRWDRTI y I
L2209:  if_icmpge L2284
L2212:  aload_0
L2213:  getfield Field CRRWDRTI m [[[I
L2216:  iload 11
L2218:  aaload
L2219:  iload 13
L2221:  aaload
L2222:  iload 15
L2224:  iconst_1
L2225:  iadd
L2226:  iaload
L2227:  iload 7
L2229:  iand
L2230:  ifne L2200
L2233:  iload 45
L2235:  ifeq L2284
L2238:  iload 14
L2240:  istore 18
L2242:  iload 45
L2244:  ifeq L2274
L2247:  aload_0
L2248:  getfield Field CRRWDRTI m [[[I
L2251:  iload 16
L2253:  iconst_1
L2254:  isub
L2255:  aaload
L2256:  iload 13
L2258:  aaload
L2259:  iload 18
L2261:  iaload
L2262:  iload 7
L2264:  iand
L2265:  ifne L2271
L2268:  goto L2340
L2271:  iinc 18 1
L2274:  iload 18
L2276:  iload 15
L2278:  if_icmple L2247
L2281:  iinc 16 -1
L2284:  iload 16
L2286:  ifgt L2238
L2289:  iload 45
L2291:  ifeq L2340
L2294:  iload 14
L2296:  istore 18
L2298:  iload 45
L2300:  ifeq L2330
L2303:  aload_0
L2304:  getfield Field CRRWDRTI m [[[I
L2307:  iload 17
L2309:  iconst_1
L2310:  iadd
L2311:  aaload
L2312:  iload 13
L2314:  aaload
L2315:  iload 18
L2317:  iaload
L2318:  iload 7
L2320:  iand
L2321:  ifne L2327
L2324:  goto L2347
L2327:  iinc 18 1
L2330:  iload 18
L2332:  iload 15
L2334:  if_icmple L2303
L2337:  iinc 17 1
L2340:  iload 17
L2342:  iload 10
L2344:  if_icmplt L2294
L2347:  iload 17
L2349:  iconst_1
L2350:  iadd
L2351:  iload 16
L2353:  isub
L2354:  iload 15
L2356:  iload 14
L2358:  isub
L2359:  iconst_1
L2360:  iadd
L2361:  imul
L2362:  istore 18
L2364:  iload 18
L2366:  bipush 8
L2368:  if_icmplt L2509
L2371:  sipush 240
L2374:  istore 19
L2376:  aload_0
L2377:  getfield Field CRRWDRTI g [[[I
L2380:  iload 17
L2382:  aaload
L2383:  iload 13
L2385:  aaload
L2386:  iload 14
L2388:  iaload
L2389:  iload 19
L2391:  isub
L2392:  istore 20
L2394:  aload_0
L2395:  getfield Field CRRWDRTI g [[[I
L2398:  iload 16
L2400:  aaload
L2401:  iload 13
L2403:  aaload
L2404:  iload 14
L2406:  iaload
L2407:  istore 21
L2409:  iload 10
L2411:  iload 13
L2413:  sipush 128
L2416:  imul
L2417:  iload 21
L2419:  iload 13
L2421:  sipush 128
L2424:  imul
L2425:  iload 15
L2427:  sipush 128
L2430:  imul
L2431:  sipush 128
L2434:  iadd
L2435:  iload 20
L2437:  aload_0
L2438:  getfield Field CRRWDRTI B I
L2441:  iload 14
L2443:  sipush 128
L2446:  imul
L2447:  iconst_1
L2448:  invokestatic Method NYFUGYQS a (IIIIIIIII)V
L2451:  iload 16
L2453:  istore 22
L2455:  iload 45
L2457:  ifeq L2502
L2460:  iload 14
L2462:  istore 23
L2464:  iload 45
L2466:  ifeq L2492
L2469:  aload_0
L2470:  getfield Field CRRWDRTI m [[[I
L2473:  iload 22
L2475:  aaload
L2476:  iload 13
L2478:  aaload
L2479:  iload 23
L2481:  dup2
L2482:  iaload
L2483:  iload 7
L2485:  iconst_m1
L2486:  ixor
L2487:  iand
L2488:  iastore
L2489:  iinc 23 1
L2492:  iload 23
L2494:  iload 15
L2496:  if_icmple L2469
L2499:  iinc 22 1
L2502:  iload 22
L2504:  iload 17
L2506:  if_icmple L2460
L2509:  aload_0
L2510:  getfield Field CRRWDRTI m [[[I
L2513:  iload 11
L2515:  aaload
L2516:  iload 13
L2518:  aaload
L2519:  iload 12
L2521:  iaload
L2522:  iload 8
L2524:  iand
L2525:  ifeq L2892
L2528:  iload 13
L2530:  istore 14
L2532:  iload 13
L2534:  istore 15
L2536:  iload 11
L2538:  istore 16
L2540:  iload 11
L2542:  istore 17
L2544:  iload 45
L2546:  ifeq L2552
L2549:  iinc 14 -1
L2552:  iload 14
L2554:  ifle L2586
L2557:  aload_0
L2558:  getfield Field CRRWDRTI m [[[I
L2561:  iload 11
L2563:  aaload
L2564:  iload 14
L2566:  iconst_1
L2567:  isub
L2568:  aaload
L2569:  iload 12
L2571:  iaload
L2572:  iload 8
L2574:  iand
L2575:  ifne L2549
L2578:  iload 45
L2580:  ifeq L2586
L2583:  iinc 15 1
L2586:  iload 15
L2588:  aload_0
L2589:  getfield Field CRRWDRTI x I
L2592:  if_icmpge L2667
L2595:  aload_0
L2596:  getfield Field CRRWDRTI m [[[I
L2599:  iload 11
L2601:  aaload
L2602:  iload 15
L2604:  iconst_1
L2605:  iadd
L2606:  aaload
L2607:  iload 12
L2609:  iaload
L2610:  iload 8
L2612:  iand
L2613:  ifne L2583
L2616:  iload 45
L2618:  ifeq L2667
L2621:  iload 14
L2623:  istore 18
L2625:  iload 45
L2627:  ifeq L2657
L2630:  aload_0
L2631:  getfield Field CRRWDRTI m [[[I
L2634:  iload 16
L2636:  iconst_1
L2637:  isub
L2638:  aaload
L2639:  iload 18
L2641:  aaload
L2642:  iload 12
L2644:  iaload
L2645:  iload 8
L2647:  iand
L2648:  ifne L2654
L2651:  goto L2723
L2654:  iinc 18 1
L2657:  iload 18
L2659:  iload 15
L2661:  if_icmple L2630
L2664:  iinc 16 -1
L2667:  iload 16
L2669:  ifgt L2621
L2672:  iload 45
L2674:  ifeq L2723
L2677:  iload 14
L2679:  istore 18
L2681:  iload 45
L2683:  ifeq L2713
L2686:  aload_0
L2687:  getfield Field CRRWDRTI m [[[I
L2690:  iload 17
L2692:  iconst_1
L2693:  iadd
L2694:  aaload
L2695:  iload 18
L2697:  aaload
L2698:  iload 12
L2700:  iaload
L2701:  iload 8
L2703:  iand
L2704:  ifne L2710
L2707:  goto L2730
L2710:  iinc 18 1
L2713:  iload 18
L2715:  iload 15
L2717:  if_icmple L2686
L2720:  iinc 17 1
L2723:  iload 17
L2725:  iload 10
L2727:  if_icmplt L2677
L2730:  iload 17
L2732:  iconst_1
L2733:  iadd
L2734:  iload 16
L2736:  isub
L2737:  iload 15
L2739:  iload 14
L2741:  isub
L2742:  iconst_1
L2743:  iadd
L2744:  imul
L2745:  istore 18
L2747:  iload 18
L2749:  bipush 8
L2751:  if_icmplt L2892
L2754:  sipush 240
L2757:  istore 19
L2759:  aload_0
L2760:  getfield Field CRRWDRTI g [[[I
L2763:  iload 17
L2765:  aaload
L2766:  iload 14
L2768:  aaload
L2769:  iload 12
L2771:  iaload
L2772:  iload 19
L2774:  isub
L2775:  istore 20
L2777:  aload_0
L2778:  getfield Field CRRWDRTI g [[[I
L2781:  iload 16
L2783:  aaload
L2784:  iload 14
L2786:  aaload
L2787:  iload 12
L2789:  iaload
L2790:  istore 21
L2792:  iload 10
L2794:  iload 14
L2796:  sipush 128
L2799:  imul
L2800:  iload 21
L2802:  iload 15
L2804:  sipush 128
L2807:  imul
L2808:  sipush 128
L2811:  iadd
L2812:  iload 12
L2814:  sipush 128
L2817:  imul
L2818:  iload 20
L2820:  aload_0
L2821:  getfield Field CRRWDRTI B I
L2824:  iload 12
L2826:  sipush 128
L2829:  imul
L2830:  iconst_2
L2831:  invokestatic Method NYFUGYQS a (IIIIIIIII)V
L2834:  iload 16
L2836:  istore 22
L2838:  iload 45
L2840:  ifeq L2885
L2843:  iload 14
L2845:  istore 23
L2847:  iload 45
L2849:  ifeq L2875
L2852:  aload_0
L2853:  getfield Field CRRWDRTI m [[[I
L2856:  iload 22
L2858:  aaload
L2859:  iload 23
L2861:  aaload
L2862:  iload 12
L2864:  dup2
L2865:  iaload
L2866:  iload 8
L2868:  iconst_m1
L2869:  ixor
L2870:  iand
L2871:  iastore
L2872:  iinc 23 1
L2875:  iload 23
L2877:  iload 15
L2879:  if_icmple L2852
L2882:  iinc 22 1
L2885:  iload 22
L2887:  iload 17
L2889:  if_icmple L2843
L2892:  aload_0
L2893:  getfield Field CRRWDRTI m [[[I
L2896:  iload 11
L2898:  aaload
L2899:  iload 13
L2901:  aaload
L2902:  iload 12
L2904:  iaload
L2905:  iload 9
L2907:  iand
L2908:  ifeq L3253
L2911:  iload 13
L2913:  istore 14
L2915:  iload 13
L2917:  istore 15
L2919:  iload 12
L2921:  istore 16
L2923:  iload 12
L2925:  istore 17
L2927:  iload 45
L2929:  ifeq L2935
L2932:  iinc 16 -1
L2935:  iload 16
L2937:  ifle L2969
L2940:  aload_0
L2941:  getfield Field CRRWDRTI m [[[I
L2944:  iload 11
L2946:  aaload
L2947:  iload 13
L2949:  aaload
L2950:  iload 16
L2952:  iconst_1
L2953:  isub
L2954:  iaload
L2955:  iload 9
L2957:  iand
L2958:  ifne L2932
L2961:  iload 45
L2963:  ifeq L2969
L2966:  iinc 17 1
L2969:  iload 17
L2971:  aload_0
L2972:  getfield Field CRRWDRTI y I
L2975:  if_icmpge L3050
L2978:  aload_0
L2979:  getfield Field CRRWDRTI m [[[I
L2982:  iload 11
L2984:  aaload
L2985:  iload 13
L2987:  aaload
L2988:  iload 17
L2990:  iconst_1
L2991:  iadd
L2992:  iaload
L2993:  iload 9
L2995:  iand
L2996:  ifne L2966
L2999:  iload 45
L3001:  ifeq L3050
L3004:  iload 16
L3006:  istore 18
L3008:  iload 45
L3010:  ifeq L3040
L3013:  aload_0
L3014:  getfield Field CRRWDRTI m [[[I
L3017:  iload 11
L3019:  aaload
L3020:  iload 14
L3022:  iconst_1
L3023:  isub
L3024:  aaload
L3025:  iload 18
L3027:  iaload
L3028:  iload 9
L3030:  iand
L3031:  ifne L3037
L3034:  goto L3106
L3037:  iinc 18 1
L3040:  iload 18
L3042:  iload 17
L3044:  if_icmple L3013
L3047:  iinc 14 -1
L3050:  iload 14
L3052:  ifgt L3004
L3055:  iload 45
L3057:  ifeq L3106
L3060:  iload 16
L3062:  istore 18
L3064:  iload 45
L3066:  ifeq L3096
L3069:  aload_0
L3070:  getfield Field CRRWDRTI m [[[I
L3073:  iload 11
L3075:  aaload
L3076:  iload 15
L3078:  iconst_1
L3079:  iadd
L3080:  aaload
L3081:  iload 18
L3083:  iaload
L3084:  iload 9
L3086:  iand
L3087:  ifne L3093
L3090:  goto L3115
L3093:  iinc 18 1
L3096:  iload 18
L3098:  iload 17
L3100:  if_icmple L3069
L3103:  iinc 15 1
L3106:  iload 15
L3108:  aload_0
L3109:  getfield Field CRRWDRTI x I
L3112:  if_icmplt L3060
L3115:  iload 15
L3117:  iload 14
L3119:  isub
L3120:  iconst_1
L3121:  iadd
L3122:  iload 17
L3124:  iload 16
L3126:  isub
L3127:  iconst_1
L3128:  iadd
L3129:  imul
L3130:  iconst_4
L3131:  if_icmplt L3253
L3134:  aload_0
L3135:  getfield Field CRRWDRTI g [[[I
L3138:  iload 11
L3140:  aaload
L3141:  iload 14
L3143:  aaload
L3144:  iload 16
L3146:  iaload
L3147:  istore 18
L3149:  iload 10
L3151:  iload 14
L3153:  sipush 128
L3156:  imul
L3157:  iload 18
L3159:  iload 15
L3161:  sipush 128
L3164:  imul
L3165:  sipush 128
L3168:  iadd
L3169:  iload 17
L3171:  sipush 128
L3174:  imul
L3175:  sipush 128
L3178:  iadd
L3179:  iload 18
L3181:  aload_0
L3182:  getfield Field CRRWDRTI B I
L3185:  iload 16
L3187:  sipush 128
L3190:  imul
L3191:  iconst_4
L3192:  invokestatic Method NYFUGYQS a (IIIIIIIII)V
L3195:  iload 14
L3197:  istore 19
L3199:  iload 45
L3201:  ifeq L3246
L3204:  iload 16
L3206:  istore 20
L3208:  iload 45
L3210:  ifeq L3236
L3213:  aload_0
L3214:  getfield Field CRRWDRTI m [[[I
L3217:  iload 11
L3219:  aaload
L3220:  iload 19
L3222:  aaload
L3223:  iload 20
L3225:  dup2
L3226:  iaload
L3227:  iload 9
L3229:  iconst_m1
L3230:  ixor
L3231:  iand
L3232:  iastore
L3233:  iinc 20 1
L3236:  iload 20
L3238:  iload 17
L3240:  if_icmple L3213
L3243:  iinc 19 1
L3246:  iload 19
L3248:  iload 15
L3250:  if_icmple L3204
L3253:  iinc 13 1
L3256:  iload 13
L3258:  aload_0
L3259:  getfield Field CRRWDRTI x I
L3262:  if_icmple L2126
L3265:  iinc 12 1
L3268:  iload 12
L3270:  aload_0
L3271:  getfield Field CRRWDRTI y I
L3274:  if_icmple L2118
L3277:  iinc 11 1
L3280:  iload 11
L3282:  iload 10
L3284:  if_icmple L2110
L3287:  iinc 10 1
L3290:  iload 10
L3292:  iconst_4
L3293:  if_icmplt L2079
L3296:  return
L3297:  astore 4
L3299:  new java/lang/StringBuffer
L3302:  dup
L3303:  ldc "90532, "
L3305:  invokespecial Method java/lang/StringBuffer <init> (Ljava/lang/String;)V
L3308:  aload_1
L3309:  invokevirtual Method java/lang/StringBuffer append (Ljava/lang/Object;)Ljava/lang/StringBuffer;
L3312:  ldc ", "
L3314:  invokevirtual Method java/lang/StringBuffer append (Ljava/lang/String;)Ljava/lang/StringBuffer;
L3317:  aload_2
L3318:  invokevirtual Method java/lang/StringBuffer append (Ljava/lang/Object;)Ljava/lang/StringBuffer;
L3321:  ldc ", "
L3323:  invokevirtual Method java/lang/StringBuffer append (Ljava/lang/String;)Ljava/lang/StringBuffer;
L3326:  iload_3
L3327:  invokevirtual Method java/lang/StringBuffer append (I)Ljava/lang/StringBuffer;
L3330:  ldc ", "
L3332:  invokevirtual Method java/lang/StringBuffer append (Ljava/lang/String;)Ljava/lang/StringBuffer;
L3335:  aload 4
L3337:  invokevirtual Method java/lang/Throwable toString ()Ljava/lang/String;
L3340:  invokevirtual Method java/lang/StringBuffer append (Ljava/lang/String;)Ljava/lang/StringBuffer;
L3343:  invokevirtual Method java/lang/StringBuffer toString ()Ljava/lang/String;
L3346:  invokestatic Method sign/signlink reporterror (Ljava/lang/String;)V
L3349:  new java/lang/RuntimeException
L3352:  dup
L3353:  invokespecial Method java/lang/RuntimeException <init> ()V
L3356:  athrow
L3357:  
    .end code
.end method

.method private static final b : (II)I
    .code stack 5 locals 3
L0:     iload_0
L1:     ldc 45365
L3:     iadd
L4:     iload_1
L5:     ldc 91923
L7:     iadd
L8:     iconst_4
L9:     invokestatic Method CRRWDRTI a (III)I
L12:    sipush 128
L15:    isub
L16:    iload_0
L17:    sipush 10294
L20:    iadd
L21:    iload_1
L22:    ldc 37821
L24:    iadd
L25:    iconst_2
L26:    invokestatic Method CRRWDRTI a (III)I
L29:    sipush 128
L32:    isub
L33:    iconst_1
L34:    ishr
L35:    iadd
L36:    iload_0
L37:    iload_1
L38:    iconst_1
L39:    invokestatic Method CRRWDRTI a (III)I
L42:    sipush 128
L45:    isub
L46:    iconst_2
L47:    ishr
L48:    iadd
L49:    istore_2
L50:    iload_2
L51:    i2d
L52:    ldc2_w 3e-1
L55:    dmul
L56:    d2i
L57:    bipush 35
L59:    iadd
L60:    istore_2
L61:    iload_2
L62:    bipush 10
L64:    if_icmpge L76
L67:    bipush 10
L69:    istore_2
L70:    getstatic Field client Jj I
L73:    ifeq L85
L76:    iload_2
L77:    bipush 60
L79:    if_icmple L85
L82:    bipush 60
L84:    istore_2
L85:    iload_2
L86:    ireturn
L87:    
    .end code
.end method

.method public static final a : (BLMBMGIXGO;LGHOWLKWN;)V
    .code stack 4 locals 8
L0:     getstatic Field client Jj I
L3:     istore 7
        .catch java/lang/RuntimeException from L5 to L84 using L85
L5:     iconst_m1
L6:     istore_3
L7:     iload_0
L8:     bipush -107
L10:    if_icmpeq L27
L13:    getstatic Field CRRWDRTI s Z
L16:    ifeq L23
L19:    iconst_0
L20:    goto L24
L23:    iconst_1
L24:    putstatic Field CRRWDRTI s Z
L27:    aload_1
L28:    invokevirtual Method MBMGIXGO k ()I
L31:    istore 4
L33:    iload 4
L35:    ifeq L84
L38:    iload_3
L39:    iload 4
L41:    iadd
L42:    istore_3
L43:    iload_3
L44:    invokestatic Method YZDBYLRM a (I)LYZDBYLRM;
L47:    astore 5
L49:    aload 5
L51:    aload_2
L52:    sipush -235
L55:    invokevirtual Method YZDBYLRM a (LGHOWLKWN;I)V
L58:    aload_1
L59:    invokevirtual Method MBMGIXGO k ()I
L62:    istore 6
L64:    iload 6
L66:    ifeq L79
L69:    aload_1
L70:    invokevirtual Method MBMGIXGO c ()I
L73:    pop
L74:    iload 7
L76:    ifeq L58
L79:    iload 7
L81:    ifeq L27
L84:    return
L85:    astore_3
L86:    new java/lang/StringBuffer
L89:    dup
L90:    ldc "73405, "
L92:    invokespecial Method java/lang/StringBuffer <init> (Ljava/lang/String;)V
L95:    iload_0
L96:    invokevirtual Method java/lang/StringBuffer append (I)Ljava/lang/StringBuffer;
L99:    ldc ", "
L101:   invokevirtual Method java/lang/StringBuffer append (Ljava/lang/String;)Ljava/lang/StringBuffer;
L104:   aload_1
L105:   invokevirtual Method java/lang/StringBuffer append (Ljava/lang/Object;)Ljava/lang/StringBuffer;
L108:   ldc ", "
L110:   invokevirtual Method java/lang/StringBuffer append (Ljava/lang/String;)Ljava/lang/StringBuffer;
L113:   aload_2
L114:   invokevirtual Method java/lang/StringBuffer append (Ljava/lang/Object;)Ljava/lang/StringBuffer;
L117:   ldc ", "
L119:   invokevirtual Method java/lang/StringBuffer append (Ljava/lang/String;)Ljava/lang/StringBuffer;
L122:   aload_3
L123:   invokevirtual Method java/lang/Throwable toString ()Ljava/lang/String;
L126:   invokevirtual Method java/lang/StringBuffer append (Ljava/lang/String;)Ljava/lang/StringBuffer;
L129:   invokevirtual Method java/lang/StringBuffer toString ()Ljava/lang/String;
L132:   invokestatic Method sign/signlink reporterror (Ljava/lang/String;)V
L135:   new java/lang/RuntimeException
L138:   dup
L139:   invokespecial Method java/lang/RuntimeException <init> ()V
L142:   athrow
L143:   
    .end code
.end method

.method public final a : (IIIII)V
    .code stack 6 locals 9
L0:     getstatic Field client Jj I
L3:     istore 8
        .catch java/lang/RuntimeException from L5 to L265 using L266
L5:     iload_1
L6:     istore 6
L8:     iload 8
L10:    ifeq L247
L13:    iload 5
L15:    istore 7
L17:    iload 8
L19:    ifeq L234
L22:    iload 7
L24:    iflt L231
L27:    iload 7
L29:    aload_0
L30:    getfield Field CRRWDRTI x I
L33:    if_icmpge L231
L36:    iload 6
L38:    iflt L231
L41:    iload 6
L43:    aload_0
L44:    getfield Field CRRWDRTI y I
L47:    if_icmpge L231
L50:    aload_0
L51:    getfield Field CRRWDRTI l [[[B
L54:    iconst_0
L55:    aaload
L56:    iload 7
L58:    aaload
L59:    iload 6
L61:    bipush 127
L63:    bastore
L64:    iload 7
L66:    iload 5
L68:    if_icmpne L102
L71:    iload 7
L73:    ifle L102
L76:    aload_0
L77:    getfield Field CRRWDRTI g [[[I
L80:    iconst_0
L81:    aaload
L82:    iload 7
L84:    aaload
L85:    iload 6
L87:    aload_0
L88:    getfield Field CRRWDRTI g [[[I
L91:    iconst_0
L92:    aaload
L93:    iload 7
L95:    iconst_1
L96:    isub
L97:    aaload
L98:    iload 6
L100:   iaload
L101:   iastore
L102:   iload 7
L104:   iload 5
L106:   iload 4
L108:   iadd
L109:   if_icmpne L149
L112:   iload 7
L114:   aload_0
L115:   getfield Field CRRWDRTI x I
L118:   iconst_1
L119:   isub
L120:   if_icmpge L149
L123:   aload_0
L124:   getfield Field CRRWDRTI g [[[I
L127:   iconst_0
L128:   aaload
L129:   iload 7
L131:   aaload
L132:   iload 6
L134:   aload_0
L135:   getfield Field CRRWDRTI g [[[I
L138:   iconst_0
L139:   aaload
L140:   iload 7
L142:   iconst_1
L143:   iadd
L144:   aaload
L145:   iload 6
L147:   iaload
L148:   iastore
L149:   iload 6
L151:   iload_1
L152:   if_icmpne L186
L155:   iload 6
L157:   ifle L186
L160:   aload_0
L161:   getfield Field CRRWDRTI g [[[I
L164:   iconst_0
L165:   aaload
L166:   iload 7
L168:   aaload
L169:   iload 6
L171:   aload_0
L172:   getfield Field CRRWDRTI g [[[I
L175:   iconst_0
L176:   aaload
L177:   iload 7
L179:   aaload
L180:   iload 6
L182:   iconst_1
L183:   isub
L184:   iaload
L185:   iastore
L186:   iload 6
L188:   iload_1
L189:   iload_2
L190:   iadd
L191:   if_icmpne L231
L194:   iload 6
L196:   aload_0
L197:   getfield Field CRRWDRTI y I
L200:   iconst_1
L201:   isub
L202:   if_icmpge L231
L205:   aload_0
L206:   getfield Field CRRWDRTI g [[[I
L209:   iconst_0
L210:   aaload
L211:   iload 7
L213:   aaload
L214:   iload 6
L216:   aload_0
L217:   getfield Field CRRWDRTI g [[[I
L220:   iconst_0
L221:   aaload
L222:   iload 7
L224:   aaload
L225:   iload 6
L227:   iconst_1
L228:   iadd
L229:   iaload
L230:   iastore
L231:   iinc 7 1
L234:   iload 7
L236:   iload 5
L238:   iload 4
L240:   iadd
L241:   if_icmple L22
L244:   iinc 6 1
L247:   iload 6
L249:   iload_1
L250:   iload_2
L251:   iadd
L252:   if_icmple L13
L255:   iload_3
L256:   ifeq L346
L259:   sipush 284
L262:   putstatic Field CRRWDRTI E I
L265:   return
L266:   astore 6
L268:   new java/lang/StringBuffer
L271:   dup
L272:   ldc "73091, "
L274:   invokespecial Method java/lang/StringBuffer <init> (Ljava/lang/String;)V
L277:   iload_1
L278:   invokevirtual Method java/lang/StringBuffer append (I)Ljava/lang/StringBuffer;
L281:   ldc ", "
L283:   invokevirtual Method java/lang/StringBuffer append (Ljava/lang/String;)Ljava/lang/StringBuffer;
L286:   iload_2
L287:   invokevirtual Method java/lang/StringBuffer append (I)Ljava/lang/StringBuffer;
L290:   ldc ", "
L292:   invokevirtual Method java/lang/StringBuffer append (Ljava/lang/String;)Ljava/lang/StringBuffer;
L295:   iload_3
L296:   invokevirtual Method java/lang/StringBuffer append (I)Ljava/lang/StringBuffer;
L299:   ldc ", "
L301:   invokevirtual Method java/lang/StringBuffer append (Ljava/lang/String;)Ljava/lang/StringBuffer;
L304:   iload 4
L306:   invokevirtual Method java/lang/StringBuffer append (I)Ljava/lang/StringBuffer;
L309:   ldc ", "
L311:   invokevirtual Method java/lang/StringBuffer append (Ljava/lang/String;)Ljava/lang/StringBuffer;
L314:   iload 5
L316:   invokevirtual Method java/lang/StringBuffer append (I)Ljava/lang/StringBuffer;
L319:   ldc ", "
L321:   invokevirtual Method java/lang/StringBuffer append (Ljava/lang/String;)Ljava/lang/StringBuffer;
L324:   aload 6
L326:   invokevirtual Method java/lang/Throwable toString ()Ljava/lang/String;
L329:   invokevirtual Method java/lang/StringBuffer append (Ljava/lang/String;)Ljava/lang/StringBuffer;
L332:   invokevirtual Method java/lang/StringBuffer toString ()Ljava/lang/String;
L335:   invokestatic Method sign/signlink reporterror (Ljava/lang/String;)V
L338:   new java/lang/RuntimeException
L341:   dup
L342:   invokespecial Method java/lang/RuntimeException <init> ()V
L345:   athrow
L346:   return
L347:   
    .end code
.end method

.method private final a : (ILNYFUGYQS;LFTPNODIB;IIIIZI)V
    .code stack 15 locals 27
L0:     getstatic Field client Jj I
L3:     istore 26
        .catch java/lang/RuntimeException from L5 to L3128 using L3128
L5:     getstatic Field CRRWDRTI C Z
L8:     ifeq L63
L11:    aload_0
L12:    getfield Field CRRWDRTI A [[[B
L15:    iconst_0
L16:    aaload
L17:    iload 6
L19:    aaload
L20:    iload_1
L21:    baload
L22:    iconst_2
L23:    iand
L24:    ifne L63
L27:    aload_0
L28:    getfield Field CRRWDRTI A [[[B
L31:    iload 5
L33:    aaload
L34:    iload 6
L36:    aaload
L37:    iload_1
L38:    baload
L39:    bipush 16
L41:    iand
L42:    ifeq L46
L45:    return
L46:    aload_0
L47:    iload_1
L48:    iload 5
L50:    iload 6
L52:    iconst_0
L53:    invokevirtual Method CRRWDRTI a (IIII)I
L56:    getstatic Field CRRWDRTI i I
L59:    if_icmpeq L63
L62:    return
L63:    iload 5
L65:    getstatic Field CRRWDRTI w I
L68:    if_icmpge L76
L71:    iload 5
L73:    putstatic Field CRRWDRTI w I
L76:    aload_0
L77:    getfield Field CRRWDRTI g [[[I
L80:    iload 5
L82:    aaload
L83:    iload 6
L85:    aaload
L86:    iload_1
L87:    iaload
L88:    istore 10
L90:    aload_0
L91:    getfield Field CRRWDRTI g [[[I
L94:    iload 5
L96:    aaload
L97:    iload 6
L99:    iconst_1
L100:   iadd
L101:   aaload
L102:   iload_1
L103:   iaload
L104:   istore 11
L106:   aload_0
L107:   getfield Field CRRWDRTI g [[[I
L110:   iload 5
L112:   aaload
L113:   iload 6
L115:   iconst_1
L116:   iadd
L117:   aaload
L118:   iload_1
L119:   iconst_1
L120:   iadd
L121:   iaload
L122:   istore 12
L124:   aload_0
L125:   getfield Field CRRWDRTI g [[[I
L128:   iload 5
L130:   aaload
L131:   iload 6
L133:   aaload
L134:   iload_1
L135:   iconst_1
L136:   iadd
L137:   iaload
L138:   istore 13
L140:   iload 10
L142:   iload 11
L144:   iadd
L145:   iload 12
L147:   iadd
L148:   iload 13
L150:   iadd
L151:   iconst_2
L152:   ishr
L153:   istore 14
L155:   iload 7
L157:   invokestatic Method YZDBYLRM a (I)LYZDBYLRM;
L160:   astore 15
L162:   iload 6
L164:   iload_1
L165:   bipush 7
L167:   ishl
L168:   iadd
L169:   iload 7
L171:   bipush 14
L173:   ishl
L174:   iadd
L175:   ldc 1073741824
L177:   iadd
L178:   istore 16
L180:   aload 15
L182:   getfield Field YZDBYLRM Q Z
L185:   ifne L195
L188:   iload 16
L190:   ldc -2147483648
L192:   iadd
L193:   istore 16
L195:   iload 9
L197:   bipush 6
L199:   ishl
L200:   iload 4
L202:   iadd
L203:   i2b
L204:   istore 17
L206:   iload 8
L208:   ifeq L212
L211:   return
L212:   iload 4
L214:   bipush 22
L216:   if_icmpne L363
L219:   getstatic Field CRRWDRTI C Z
L222:   ifeq L242
L225:   aload 15
L227:   getfield Field YZDBYLRM Q Z
L230:   ifne L242
L233:   aload 15
L235:   getfield Field YZDBYLRM a Z
L238:   ifne L242
L241:   return
L242:   aload 15
L244:   getfield Field YZDBYLRM T I
L247:   iconst_m1
L248:   if_icmpne L284
L251:   aload 15
L253:   getfield Field YZDBYLRM x [I
L256:   ifnonnull L284
L259:   aload 15
L261:   bipush 22
L263:   iload 9
L265:   iload 10
L267:   iload 11
L269:   iload 12
L271:   iload 13
L273:   iconst_m1
L274:   invokevirtual Method YZDBYLRM a (IIIIIII)LZKARKDQW;
L277:   astore 18
L279:   iload 26
L281:   ifeq L315
L284:   new WBWOBAFW
L287:   dup
L288:   iload 7
L290:   iload 9
L292:   bipush 22
L294:   iload 11
L296:   bipush 7
L298:   iload 12
L300:   iload 10
L302:   iload 13
L304:   aload 15
L306:   getfield Field YZDBYLRM T I
L309:   iconst_1
L310:   invokespecial Method WBWOBAFW <init> (IIIIBIIIIZ)V
L313:   astore 18
L315:   aload_2
L316:   iload 5
L318:   iload 14
L320:   iload_1
L321:   bipush 68
L323:   aload 18
L325:   iload 17
L327:   iload 16
L329:   iload 6
L331:   invokevirtual Method NYFUGYQS a (IIIILXHHRODPC;BII)V
L334:   aload 15
L336:   getfield Field YZDBYLRM F Z
L339:   ifeq L362
L342:   aload 15
L344:   getfield Field YZDBYLRM Q Z
L347:   ifeq L362
L350:   aload_3
L351:   ifnull L362
L354:   aload_3
L355:   iload_1
L356:   iconst_0
L357:   iload 6
L359:   invokevirtual Method FTPNODIB a (III)V
L362:   return
L363:   iload 4
L365:   bipush 10
L367:   if_icmpeq L377
L370:   iload 4
L372:   bipush 11
L374:   if_icmpne L737
L377:   aload 15
L379:   getfield Field YZDBYLRM T I
L382:   iconst_m1
L383:   if_icmpne L419
L386:   aload 15
L388:   getfield Field YZDBYLRM x [I
L391:   ifnonnull L419
L394:   aload 15
L396:   bipush 10
L398:   iload 9
L400:   iload 10
L402:   iload 11
L404:   iload 12
L406:   iload 13
L408:   iconst_m1
L409:   invokevirtual Method YZDBYLRM a (IIIIIII)LZKARKDQW;
L412:   astore 18
L414:   iload 26
L416:   ifeq L450
L419:   new WBWOBAFW
L422:   dup
L423:   iload 7
L425:   iload 9
L427:   bipush 10
L429:   iload 11
L431:   bipush 7
L433:   iload 12
L435:   iload 10
L437:   iload 13
L439:   aload 15
L441:   getfield Field YZDBYLRM T I
L444:   iconst_1
L445:   invokespecial Method WBWOBAFW <init> (IIIIBIIIIZ)V
L448:   astore 18
L450:   aload 18
L452:   ifnull L697
L455:   iconst_0
L456:   istore 21
L458:   iload 4
L460:   bipush 11
L462:   if_icmpne L471
L465:   wide iinc 21 256
L471:   iload 9
L473:   iconst_1
L474:   if_icmpeq L483
L477:   iload 9
L479:   iconst_3
L480:   if_icmpne L502
L483:   aload 15
L485:   getfield Field YZDBYLRM z I
L488:   istore 19
L490:   aload 15
L492:   getfield Field YZDBYLRM i I
L495:   istore 20
L497:   iload 26
L499:   ifeq L516
L502:   aload 15
L504:   getfield Field YZDBYLRM i I
L507:   istore 19
L509:   aload 15
L511:   getfield Field YZDBYLRM z I
L514:   istore 20
L516:   aload_2
L517:   iload 16
L519:   iload 17
L521:   iload 14
L523:   iload 20
L525:   aload 18
L527:   iload 19
L529:   iload 5
L531:   iload 21
L533:   bipush 110
L535:   iload_1
L536:   iload 6
L538:   invokevirtual Method NYFUGYQS a (IBIILXHHRODPC;IIIBII)Z
L541:   ifeq L697
L544:   aload 15
L546:   getfield Field YZDBYLRM R Z
L549:   ifeq L697
L552:   aload 18
L554:   instanceof ZKARKDQW
L557:   ifeq L572
L560:   aload 18
L562:   checkcast ZKARKDQW
L565:   astore 22
L567:   iload 26
L569:   ifeq L592
L572:   aload 15
L574:   bipush 10
L576:   iload 9
L578:   iload 10
L580:   iload 11
L582:   iload 12
L584:   iload 13
L586:   iconst_m1
L587:   invokevirtual Method YZDBYLRM a (IIIIIII)LZKARKDQW;
L590:   astore 22
L592:   aload 22
L594:   ifnull L697
L597:   iconst_0
L598:   istore 23
L600:   iload 26
L602:   ifeq L690
L605:   iconst_0
L606:   istore 24
L608:   iload 26
L610:   ifeq L680
L613:   aload 22
L615:   getfield Field ZKARKDQW W I
L618:   iconst_4
L619:   idiv
L620:   istore 25
L622:   iload 25
L624:   bipush 30
L626:   if_icmple L633
L629:   bipush 30
L631:   istore 25
L633:   iload 25
L635:   aload_0
L636:   getfield Field CRRWDRTI l [[[B
L639:   iload 5
L641:   aaload
L642:   iload 6
L644:   iload 23
L646:   iadd
L647:   aaload
L648:   iload_1
L649:   iload 24
L651:   iadd
L652:   baload
L653:   if_icmple L677
L656:   aload_0
L657:   getfield Field CRRWDRTI l [[[B
L660:   iload 5
L662:   aaload
L663:   iload 6
L665:   iload 23
L667:   iadd
L668:   aaload
L669:   iload_1
L670:   iload 24
L672:   iadd
L673:   iload 25
L675:   i2b
L676:   bastore
L677:   iinc 24 1
L680:   iload 24
L682:   iload 20
L684:   if_icmple L613
L687:   iinc 23 1
L690:   iload 23
L692:   iload 19
L694:   if_icmple L605
L697:   aload 15
L699:   getfield Field YZDBYLRM F Z
L702:   ifeq L736
L705:   aload_3
L706:   ifnull L736
L709:   aload_3
L710:   aload 15
L712:   getfield Field YZDBYLRM v Z
L715:   getstatic Field CRRWDRTI p I
L718:   aload 15
L720:   getfield Field YZDBYLRM i I
L723:   aload 15
L725:   getfield Field YZDBYLRM z I
L728:   iload 6
L730:   iload_1
L731:   iload 9
L733:   invokevirtual Method FTPNODIB a (ZIIIIII)V
L736:   return
L737:   iload 4
L739:   bipush 12
L741:   if_icmplt L924
L744:   aload 15
L746:   getfield Field YZDBYLRM T I
L749:   iconst_m1
L750:   if_icmpne L786
L753:   aload 15
L755:   getfield Field YZDBYLRM x [I
L758:   ifnonnull L786
L761:   aload 15
L763:   iload 4
L765:   iload 9
L767:   iload 10
L769:   iload 11
L771:   iload 12
L773:   iload 13
L775:   iconst_m1
L776:   invokevirtual Method YZDBYLRM a (IIIIIII)LZKARKDQW;
L779:   astore 18
L781:   iload 26
L783:   ifeq L817
L786:   new WBWOBAFW
L789:   dup
L790:   iload 7
L792:   iload 9
L794:   iload 4
L796:   iload 11
L798:   bipush 7
L800:   iload 12
L802:   iload 10
L804:   iload 13
L806:   aload 15
L808:   getfield Field YZDBYLRM T I
L811:   iconst_1
L812:   invokespecial Method WBWOBAFW <init> (IIIIBIIIIZ)V
L815:   astore 18
L817:   aload_2
L818:   iload 16
L820:   iload 17
L822:   iload 14
L824:   iconst_1
L825:   aload 18
L827:   iconst_1
L828:   iload 5
L830:   iconst_0
L831:   bipush 110
L833:   iload_1
L834:   iload 6
L836:   invokevirtual Method NYFUGYQS a (IBIILXHHRODPC;IIIBII)Z
L839:   pop
L840:   iload 4
L842:   bipush 12
L844:   if_icmplt L884
L847:   iload 4
L849:   bipush 17
L851:   if_icmpgt L884
L854:   iload 4
L856:   bipush 13
L858:   if_icmpeq L884
L861:   iload 5
L863:   ifle L884
L866:   aload_0
L867:   getfield Field CRRWDRTI m [[[I
L870:   iload 5
L872:   aaload
L873:   iload 6
L875:   aaload
L876:   iload_1
L877:   dup2
L878:   iaload
L879:   sipush 2340
L882:   ior
L883:   iastore
L884:   aload 15
L886:   getfield Field YZDBYLRM F Z
L889:   ifeq L923
L892:   aload_3
L893:   ifnull L923
L896:   aload_3
L897:   aload 15
L899:   getfield Field YZDBYLRM v Z
L902:   getstatic Field CRRWDRTI p I
L905:   aload 15
L907:   getfield Field YZDBYLRM i I
L910:   aload 15
L912:   getfield Field YZDBYLRM z I
L915:   iload 6
L917:   iload_1
L918:   iload 9
L920:   invokevirtual Method FTPNODIB a (ZIIIIII)V
L923:   return
L924:   iload 4
L926:   ifne L1389
L929:   aload 15
L931:   getfield Field YZDBYLRM T I
L934:   iconst_m1
L935:   if_icmpne L970
L938:   aload 15
L940:   getfield Field YZDBYLRM x [I
L943:   ifnonnull L970
L946:   aload 15
L948:   iconst_0
L949:   iload 9
L951:   iload 10
L953:   iload 11
L955:   iload 12
L957:   iload 13
L959:   iconst_m1
L960:   invokevirtual Method YZDBYLRM a (IIIIIII)LZKARKDQW;
L963:   astore 18
L965:   iload 26
L967:   ifeq L1000
L970:   new WBWOBAFW
L973:   dup
L974:   iload 7
L976:   iload 9
L978:   iconst_0
L979:   iload 11
L981:   bipush 7
L983:   iload 12
L985:   iload 10
L987:   iload 13
L989:   aload 15
L991:   getfield Field YZDBYLRM T I
L994:   iconst_1
L995:   invokespecial Method WBWOBAFW <init> (IIIIBIIIIZ)V
L998:   astore 18
L1000:  aload_2
L1001:  getstatic Field CRRWDRTI D [I
L1004:  iload 9
L1006:  iaload
L1007:  aload 18
L1009:  iconst_1
L1010:  iload 16
L1012:  iload_1
L1013:  iload 17
L1015:  iload 6
L1017:  aconst_null
L1018:  iload 14
L1020:  iconst_0
L1021:  iload 5
L1023:  invokevirtual Method NYFUGYQS a (ILXHHRODPC;ZIIBILXHHRODPC;III)V
L1026:  iload 9
L1028:  ifne L1100
L1031:  aload 15
L1033:  getfield Field YZDBYLRM R Z
L1036:  ifeq L1069
L1039:  aload_0
L1040:  getfield Field CRRWDRTI l [[[B
L1043:  iload 5
L1045:  aaload
L1046:  iload 6
L1048:  aaload
L1049:  iload_1
L1050:  bipush 50
L1052:  bastore
L1053:  aload_0
L1054:  getfield Field CRRWDRTI l [[[B
L1057:  iload 5
L1059:  aaload
L1060:  iload 6
L1062:  aaload
L1063:  iload_1
L1064:  iconst_1
L1065:  iadd
L1066:  bipush 50
L1068:  bastore
L1069:  aload 15
L1071:  getfield Field YZDBYLRM C Z
L1074:  ifeq L1332
L1077:  aload_0
L1078:  getfield Field CRRWDRTI m [[[I
L1081:  iload 5
L1083:  aaload
L1084:  iload 6
L1086:  aaload
L1087:  iload_1
L1088:  dup2
L1089:  iaload
L1090:  sipush 585
L1093:  ior
L1094:  iastore
L1095:  iload 26
L1097:  ifeq L1332
L1100:  iload 9
L1102:  iconst_1
L1103:  if_icmpne L1181
L1106:  aload 15
L1108:  getfield Field YZDBYLRM R Z
L1111:  ifeq L1148
L1114:  aload_0
L1115:  getfield Field CRRWDRTI l [[[B
L1118:  iload 5
L1120:  aaload
L1121:  iload 6
L1123:  aaload
L1124:  iload_1
L1125:  iconst_1
L1126:  iadd
L1127:  bipush 50
L1129:  bastore
L1130:  aload_0
L1131:  getfield Field CRRWDRTI l [[[B
L1134:  iload 5
L1136:  aaload
L1137:  iload 6
L1139:  iconst_1
L1140:  iadd
L1141:  aaload
L1142:  iload_1
L1143:  iconst_1
L1144:  iadd
L1145:  bipush 50
L1147:  bastore
L1148:  aload 15
L1150:  getfield Field YZDBYLRM C Z
L1153:  ifeq L1332
L1156:  aload_0
L1157:  getfield Field CRRWDRTI m [[[I
L1160:  iload 5
L1162:  aaload
L1163:  iload 6
L1165:  aaload
L1166:  iload_1
L1167:  iconst_1
L1168:  iadd
L1169:  dup2
L1170:  iaload
L1171:  sipush 1170
L1174:  ior
L1175:  iastore
L1176:  iload 26
L1178:  ifeq L1332
L1181:  iload 9
L1183:  iconst_2
L1184:  if_icmpne L1262
L1187:  aload 15
L1189:  getfield Field YZDBYLRM R Z
L1192:  ifeq L1229
L1195:  aload_0
L1196:  getfield Field CRRWDRTI l [[[B
L1199:  iload 5
L1201:  aaload
L1202:  iload 6
L1204:  iconst_1
L1205:  iadd
L1206:  aaload
L1207:  iload_1
L1208:  bipush 50
L1210:  bastore
L1211:  aload_0
L1212:  getfield Field CRRWDRTI l [[[B
L1215:  iload 5
L1217:  aaload
L1218:  iload 6
L1220:  iconst_1
L1221:  iadd
L1222:  aaload
L1223:  iload_1
L1224:  iconst_1
L1225:  iadd
L1226:  bipush 50
L1228:  bastore
L1229:  aload 15
L1231:  getfield Field YZDBYLRM C Z
L1234:  ifeq L1332
L1237:  aload_0
L1238:  getfield Field CRRWDRTI m [[[I
L1241:  iload 5
L1243:  aaload
L1244:  iload 6
L1246:  iconst_1
L1247:  iadd
L1248:  aaload
L1249:  iload_1
L1250:  dup2
L1251:  iaload
L1252:  sipush 585
L1255:  ior
L1256:  iastore
L1257:  iload 26
L1259:  ifeq L1332
L1262:  iload 9
L1264:  iconst_3
L1265:  if_icmpne L1332
L1268:  aload 15
L1270:  getfield Field YZDBYLRM R Z
L1273:  ifeq L1306
L1276:  aload_0
L1277:  getfield Field CRRWDRTI l [[[B
L1280:  iload 5
L1282:  aaload
L1283:  iload 6
L1285:  aaload
L1286:  iload_1
L1287:  bipush 50
L1289:  bastore
L1290:  aload_0
L1291:  getfield Field CRRWDRTI l [[[B
L1294:  iload 5
L1296:  aaload
L1297:  iload 6
L1299:  iconst_1
L1300:  iadd
L1301:  aaload
L1302:  iload_1
L1303:  bipush 50
L1305:  bastore
L1306:  aload 15
L1308:  getfield Field YZDBYLRM C Z
L1311:  ifeq L1332
L1314:  aload_0
L1315:  getfield Field CRRWDRTI m [[[I
L1318:  iload 5
L1320:  aaload
L1321:  iload 6
L1323:  aaload
L1324:  iload_1
L1325:  dup2
L1326:  iaload
L1327:  sipush 1170
L1330:  ior
L1331:  iastore
L1332:  aload 15
L1334:  getfield Field YZDBYLRM F Z
L1337:  ifeq L1361
L1340:  aload_3
L1341:  ifnull L1361
L1344:  aload_3
L1345:  iload_1
L1346:  iload 9
L1348:  iload 6
L1350:  iload 4
L1352:  iconst_1
L1353:  aload 15
L1355:  getfield Field YZDBYLRM v Z
L1358:  invokevirtual Method FTPNODIB a (IIIIBZ)V
L1361:  aload 15
L1363:  getfield Field YZDBYLRM N I
L1366:  bipush 16
L1368:  if_icmpeq L1388
L1371:  aload_2
L1372:  iload_1
L1373:  sipush 441
L1376:  aload 15
L1378:  getfield Field YZDBYLRM N I
L1381:  iload 6
L1383:  iload 5
L1385:  invokevirtual Method NYFUGYQS a (IIIII)V
L1388:  return
L1389:  iload 4
L1391:  iconst_1
L1392:  if_icmpne L1632
L1395:  aload 15
L1397:  getfield Field YZDBYLRM T I
L1400:  iconst_m1
L1401:  if_icmpne L1436
L1404:  aload 15
L1406:  getfield Field YZDBYLRM x [I
L1409:  ifnonnull L1436
L1412:  aload 15
L1414:  iconst_1
L1415:  iload 9
L1417:  iload 10
L1419:  iload 11
L1421:  iload 12
L1423:  iload 13
L1425:  iconst_m1
L1426:  invokevirtual Method YZDBYLRM a (IIIIIII)LZKARKDQW;
L1429:  astore 18
L1431:  iload 26
L1433:  ifeq L1466
L1436:  new WBWOBAFW
L1439:  dup
L1440:  iload 7
L1442:  iload 9
L1444:  iconst_1
L1445:  iload 11
L1447:  bipush 7
L1449:  iload 12
L1451:  iload 10
L1453:  iload 13
L1455:  aload 15
L1457:  getfield Field YZDBYLRM T I
L1460:  iconst_1
L1461:  invokespecial Method WBWOBAFW <init> (IIIIBIIIIZ)V
L1464:  astore 18
L1466:  aload_2
L1467:  getstatic Field CRRWDRTI r [I
L1470:  iload 9
L1472:  iaload
L1473:  aload 18
L1475:  iconst_1
L1476:  iload 16
L1478:  iload_1
L1479:  iload 17
L1481:  iload 6
L1483:  aconst_null
L1484:  iload 14
L1486:  iconst_0
L1487:  iload 5
L1489:  invokevirtual Method NYFUGYQS a (ILXHHRODPC;ZIIBILXHHRODPC;III)V
L1492:  aload 15
L1494:  getfield Field YZDBYLRM R Z
L1497:  ifeq L1602
L1500:  iload 9
L1502:  ifne L1526
L1505:  aload_0
L1506:  getfield Field CRRWDRTI l [[[B
L1509:  iload 5
L1511:  aaload
L1512:  iload 6
L1514:  aaload
L1515:  iload_1
L1516:  iconst_1
L1517:  iadd
L1518:  bipush 50
L1520:  bastore
L1521:  iload 26
L1523:  ifeq L1602
L1526:  iload 9
L1528:  iconst_1
L1529:  if_icmpne L1555
L1532:  aload_0
L1533:  getfield Field CRRWDRTI l [[[B
L1536:  iload 5
L1538:  aaload
L1539:  iload 6
L1541:  iconst_1
L1542:  iadd
L1543:  aaload
L1544:  iload_1
L1545:  iconst_1
L1546:  iadd
L1547:  bipush 50
L1549:  bastore
L1550:  iload 26
L1552:  ifeq L1602
L1555:  iload 9
L1557:  iconst_2
L1558:  if_icmpne L1582
L1561:  aload_0
L1562:  getfield Field CRRWDRTI l [[[B
L1565:  iload 5
L1567:  aaload
L1568:  iload 6
L1570:  iconst_1
L1571:  iadd
L1572:  aaload
L1573:  iload_1
L1574:  bipush 50
L1576:  bastore
L1577:  iload 26
L1579:  ifeq L1602
L1582:  iload 9
L1584:  iconst_3
L1585:  if_icmpne L1602
L1588:  aload_0
L1589:  getfield Field CRRWDRTI l [[[B
L1592:  iload 5
L1594:  aaload
L1595:  iload 6
L1597:  aaload
L1598:  iload_1
L1599:  bipush 50
L1601:  bastore
L1602:  aload 15
L1604:  getfield Field YZDBYLRM F Z
L1607:  ifeq L1631
L1610:  aload_3
L1611:  ifnull L1631
L1614:  aload_3
L1615:  iload_1
L1616:  iload 9
L1618:  iload 6
L1620:  iload 4
L1622:  iconst_1
L1623:  aload 15
L1625:  getfield Field YZDBYLRM v Z
L1628:  invokevirtual Method FTPNODIB a (IIIIBZ)V
L1631:  return
L1632:  iload 4
L1634:  iconst_2
L1635:  if_icmpne L2057
L1638:  iload 9
L1640:  iconst_1
L1641:  iadd
L1642:  iconst_3
L1643:  iand
L1644:  istore 18
L1646:  aload 15
L1648:  getfield Field YZDBYLRM T I
L1651:  iconst_m1
L1652:  if_icmpne L1708
L1655:  aload 15
L1657:  getfield Field YZDBYLRM x [I
L1660:  ifnonnull L1708
L1663:  aload 15
L1665:  iconst_2
L1666:  iconst_4
L1667:  iload 9
L1669:  iadd
L1670:  iload 10
L1672:  iload 11
L1674:  iload 12
L1676:  iload 13
L1678:  iconst_m1
L1679:  invokevirtual Method YZDBYLRM a (IIIIIII)LZKARKDQW;
L1682:  astore 19
L1684:  aload 15
L1686:  iconst_2
L1687:  iload 18
L1689:  iload 10
L1691:  iload 11
L1693:  iload 12
L1695:  iload 13
L1697:  iconst_m1
L1698:  invokevirtual Method YZDBYLRM a (IIIIIII)LZKARKDQW;
L1701:  astore 20
L1703:  iload 26
L1705:  ifeq L1770
L1708:  new WBWOBAFW
L1711:  dup
L1712:  iload 7
L1714:  iconst_4
L1715:  iload 9
L1717:  iadd
L1718:  iconst_2
L1719:  iload 11
L1721:  bipush 7
L1723:  iload 12
L1725:  iload 10
L1727:  iload 13
L1729:  aload 15
L1731:  getfield Field YZDBYLRM T I
L1734:  iconst_1
L1735:  invokespecial Method WBWOBAFW <init> (IIIIBIIIIZ)V
L1738:  astore 19
L1740:  new WBWOBAFW
L1743:  dup
L1744:  iload 7
L1746:  iload 18
L1748:  iconst_2
L1749:  iload 11
L1751:  bipush 7
L1753:  iload 12
L1755:  iload 10
L1757:  iload 13
L1759:  aload 15
L1761:  getfield Field YZDBYLRM T I
L1764:  iconst_1
L1765:  invokespecial Method WBWOBAFW <init> (IIIIBIIIIZ)V
L1768:  astore 20
L1770:  aload_2
L1771:  getstatic Field CRRWDRTI D [I
L1774:  iload 9
L1776:  iaload
L1777:  aload 19
L1779:  iconst_1
L1780:  iload 16
L1782:  iload_1
L1783:  iload 17
L1785:  iload 6
L1787:  aload 20
L1789:  iload 14
L1791:  getstatic Field CRRWDRTI D [I
L1794:  iload 18
L1796:  iaload
L1797:  iload 5
L1799:  invokevirtual Method NYFUGYQS a (ILXHHRODPC;ZIIBILXHHRODPC;III)V
L1802:  aload 15
L1804:  getfield Field YZDBYLRM C Z
L1807:  ifeq L2000
L1810:  iload 9
L1812:  ifne L1858
L1815:  aload_0
L1816:  getfield Field CRRWDRTI m [[[I
L1819:  iload 5
L1821:  aaload
L1822:  iload 6
L1824:  aaload
L1825:  iload_1
L1826:  dup2
L1827:  iaload
L1828:  sipush 585
L1831:  ior
L1832:  iastore
L1833:  aload_0
L1834:  getfield Field CRRWDRTI m [[[I
L1837:  iload 5
L1839:  aaload
L1840:  iload 6
L1842:  aaload
L1843:  iload_1
L1844:  iconst_1
L1845:  iadd
L1846:  dup2
L1847:  iaload
L1848:  sipush 1170
L1851:  ior
L1852:  iastore
L1853:  iload 26
L1855:  ifeq L2000
L1858:  iload 9
L1860:  iconst_1
L1861:  if_icmpne L1909
L1864:  aload_0
L1865:  getfield Field CRRWDRTI m [[[I
L1868:  iload 5
L1870:  aaload
L1871:  iload 6
L1873:  aaload
L1874:  iload_1
L1875:  iconst_1
L1876:  iadd
L1877:  dup2
L1878:  iaload
L1879:  sipush 1170
L1882:  ior
L1883:  iastore
L1884:  aload_0
L1885:  getfield Field CRRWDRTI m [[[I
L1888:  iload 5
L1890:  aaload
L1891:  iload 6
L1893:  iconst_1
L1894:  iadd
L1895:  aaload
L1896:  iload_1
L1897:  dup2
L1898:  iaload
L1899:  sipush 585
L1902:  ior
L1903:  iastore
L1904:  iload 26
L1906:  ifeq L2000
L1909:  iload 9
L1911:  iconst_2
L1912:  if_icmpne L1958
L1915:  aload_0
L1916:  getfield Field CRRWDRTI m [[[I
L1919:  iload 5
L1921:  aaload
L1922:  iload 6
L1924:  iconst_1
L1925:  iadd
L1926:  aaload
L1927:  iload_1
L1928:  dup2
L1929:  iaload
L1930:  sipush 585
L1933:  ior
L1934:  iastore
L1935:  aload_0
L1936:  getfield Field CRRWDRTI m [[[I
L1939:  iload 5
L1941:  aaload
L1942:  iload 6
L1944:  aaload
L1945:  iload_1
L1946:  dup2
L1947:  iaload
L1948:  sipush 1170
L1951:  ior
L1952:  iastore
L1953:  iload 26
L1955:  ifeq L2000
L1958:  iload 9
L1960:  iconst_3
L1961:  if_icmpne L2000
L1964:  aload_0
L1965:  getfield Field CRRWDRTI m [[[I
L1968:  iload 5
L1970:  aaload
L1971:  iload 6
L1973:  aaload
L1974:  iload_1
L1975:  dup2
L1976:  iaload
L1977:  sipush 1170
L1980:  ior
L1981:  iastore
L1982:  aload_0
L1983:  getfield Field CRRWDRTI m [[[I
L1986:  iload 5
L1988:  aaload
L1989:  iload 6
L1991:  aaload
L1992:  iload_1
L1993:  dup2
L1994:  iaload
L1995:  sipush 585
L1998:  ior
L1999:  iastore
L2000:  aload 15
L2002:  getfield Field YZDBYLRM F Z
L2005:  ifeq L2029
L2008:  aload_3
L2009:  ifnull L2029
L2012:  aload_3
L2013:  iload_1
L2014:  iload 9
L2016:  iload 6
L2018:  iload 4
L2020:  iconst_1
L2021:  aload 15
L2023:  getfield Field YZDBYLRM v Z
L2026:  invokevirtual Method FTPNODIB a (IIIIBZ)V
L2029:  aload 15
L2031:  getfield Field YZDBYLRM N I
L2034:  bipush 16
L2036:  if_icmpeq L2056
L2039:  aload_2
L2040:  iload_1
L2041:  sipush 441
L2044:  aload 15
L2046:  getfield Field YZDBYLRM N I
L2049:  iload 6
L2051:  iload 5
L2053:  invokevirtual Method NYFUGYQS a (IIIII)V
L2056:  return
L2057:  iload 4
L2059:  iconst_3
L2060:  if_icmpne L2300
L2063:  aload 15
L2065:  getfield Field YZDBYLRM T I
L2068:  iconst_m1
L2069:  if_icmpne L2104
L2072:  aload 15
L2074:  getfield Field YZDBYLRM x [I
L2077:  ifnonnull L2104
L2080:  aload 15
L2082:  iconst_3
L2083:  iload 9
L2085:  iload 10
L2087:  iload 11
L2089:  iload 12
L2091:  iload 13
L2093:  iconst_m1
L2094:  invokevirtual Method YZDBYLRM a (IIIIIII)LZKARKDQW;
L2097:  astore 18
L2099:  iload 26
L2101:  ifeq L2134
L2104:  new WBWOBAFW
L2107:  dup
L2108:  iload 7
L2110:  iload 9
L2112:  iconst_3
L2113:  iload 11
L2115:  bipush 7
L2117:  iload 12
L2119:  iload 10
L2121:  iload 13
L2123:  aload 15
L2125:  getfield Field YZDBYLRM T I
L2128:  iconst_1
L2129:  invokespecial Method WBWOBAFW <init> (IIIIBIIIIZ)V
L2132:  astore 18
L2134:  aload_2
L2135:  getstatic Field CRRWDRTI r [I
L2138:  iload 9
L2140:  iaload
L2141:  aload 18
L2143:  iconst_1
L2144:  iload 16
L2146:  iload_1
L2147:  iload 17
L2149:  iload 6
L2151:  aconst_null
L2152:  iload 14
L2154:  iconst_0
L2155:  iload 5
L2157:  invokevirtual Method NYFUGYQS a (ILXHHRODPC;ZIIBILXHHRODPC;III)V
L2160:  aload 15
L2162:  getfield Field YZDBYLRM R Z
L2165:  ifeq L2270
L2168:  iload 9
L2170:  ifne L2194
L2173:  aload_0
L2174:  getfield Field CRRWDRTI l [[[B
L2177:  iload 5
L2179:  aaload
L2180:  iload 6
L2182:  aaload
L2183:  iload_1
L2184:  iconst_1
L2185:  iadd
L2186:  bipush 50
L2188:  bastore
L2189:  iload 26
L2191:  ifeq L2270
L2194:  iload 9
L2196:  iconst_1
L2197:  if_icmpne L2223
L2200:  aload_0
L2201:  getfield Field CRRWDRTI l [[[B
L2204:  iload 5
L2206:  aaload
L2207:  iload 6
L2209:  iconst_1
L2210:  iadd
L2211:  aaload
L2212:  iload_1
L2213:  iconst_1
L2214:  iadd
L2215:  bipush 50
L2217:  bastore
L2218:  iload 26
L2220:  ifeq L2270
L2223:  iload 9
L2225:  iconst_2
L2226:  if_icmpne L2250
L2229:  aload_0
L2230:  getfield Field CRRWDRTI l [[[B
L2233:  iload 5
L2235:  aaload
L2236:  iload 6
L2238:  iconst_1
L2239:  iadd
L2240:  aaload
L2241:  iload_1
L2242:  bipush 50
L2244:  bastore
L2245:  iload 26
L2247:  ifeq L2270
L2250:  iload 9
L2252:  iconst_3
L2253:  if_icmpne L2270
L2256:  aload_0
L2257:  getfield Field CRRWDRTI l [[[B
L2260:  iload 5
L2262:  aaload
L2263:  iload 6
L2265:  aaload
L2266:  iload_1
L2267:  bipush 50
L2269:  bastore
L2270:  aload 15
L2272:  getfield Field YZDBYLRM F Z
L2275:  ifeq L2299
L2278:  aload_3
L2279:  ifnull L2299
L2282:  aload_3
L2283:  iload_1
L2284:  iload 9
L2286:  iload 6
L2288:  iload 4
L2290:  iconst_1
L2291:  aload 15
L2293:  getfield Field YZDBYLRM v Z
L2296:  invokevirtual Method FTPNODIB a (IIIIBZ)V
L2299:  return
L2300:  iload 4
L2302:  bipush 9
L2304:  if_icmpne L2443
L2307:  aload 15
L2309:  getfield Field YZDBYLRM T I
L2312:  iconst_m1
L2313:  if_icmpne L2349
L2316:  aload 15
L2318:  getfield Field YZDBYLRM x [I
L2321:  ifnonnull L2349
L2324:  aload 15
L2326:  iload 4
L2328:  iload 9
L2330:  iload 10
L2332:  iload 11
L2334:  iload 12
L2336:  iload 13
L2338:  iconst_m1
L2339:  invokevirtual Method YZDBYLRM a (IIIIIII)LZKARKDQW;
L2342:  astore 18
L2344:  iload 26
L2346:  ifeq L2380
L2349:  new WBWOBAFW
L2352:  dup
L2353:  iload 7
L2355:  iload 9
L2357:  iload 4
L2359:  iload 11
L2361:  bipush 7
L2363:  iload 12
L2365:  iload 10
L2367:  iload 13
L2369:  aload 15
L2371:  getfield Field YZDBYLRM T I
L2374:  iconst_1
L2375:  invokespecial Method WBWOBAFW <init> (IIIIBIIIIZ)V
L2378:  astore 18
L2380:  aload_2
L2381:  iload 16
L2383:  iload 17
L2385:  iload 14
L2387:  iconst_1
L2388:  aload 18
L2390:  iconst_1
L2391:  iload 5
L2393:  iconst_0
L2394:  bipush 110
L2396:  iload_1
L2397:  iload 6
L2399:  invokevirtual Method NYFUGYQS a (IBIILXHHRODPC;IIIBII)Z
L2402:  pop
L2403:  aload 15
L2405:  getfield Field YZDBYLRM F Z
L2408:  ifeq L2442
L2411:  aload_3
L2412:  ifnull L2442
L2415:  aload_3
L2416:  aload 15
L2418:  getfield Field YZDBYLRM v Z
L2421:  getstatic Field CRRWDRTI p I
L2424:  aload 15
L2426:  getfield Field YZDBYLRM i I
L2429:  aload 15
L2431:  getfield Field YZDBYLRM z I
L2434:  iload 6
L2436:  iload_1
L2437:  iload 9
L2439:  invokevirtual Method FTPNODIB a (ZIIIIII)V
L2442:  return
L2443:  aload 15
L2445:  getfield Field YZDBYLRM A Z
L2448:  ifeq L2543
L2451:  iload 9
L2453:  iconst_1
L2454:  if_icmpne L2482
L2457:  iload 13
L2459:  istore 18
L2461:  iload 12
L2463:  istore 13
L2465:  iload 11
L2467:  istore 12
L2469:  iload 10
L2471:  istore 11
L2473:  iload 18
L2475:  istore 10
L2477:  iload 26
L2479:  ifeq L2543
L2482:  iload 9
L2484:  iconst_2
L2485:  if_icmpne L2517
L2488:  iload 13
L2490:  istore 18
L2492:  iload 11
L2494:  istore 13
L2496:  iload 18
L2498:  istore 11
L2500:  iload 12
L2502:  istore 18
L2504:  iload 10
L2506:  istore 12
L2508:  iload 18
L2510:  istore 10
L2512:  iload 26
L2514:  ifeq L2543
L2517:  iload 9
L2519:  iconst_3
L2520:  if_icmpne L2543
L2523:  iload 13
L2525:  istore 18
L2527:  iload 10
L2529:  istore 13
L2531:  iload 11
L2533:  istore 10
L2535:  iload 12
L2537:  istore 11
L2539:  iload 18
L2541:  istore 12
L2543:  iload 4
L2545:  iconst_4
L2546:  if_icmpne L2653
L2549:  aload 15
L2551:  getfield Field YZDBYLRM T I
L2554:  iconst_m1
L2555:  if_icmpne L2589
L2558:  aload 15
L2560:  getfield Field YZDBYLRM x [I
L2563:  ifnonnull L2589
L2566:  aload 15
L2568:  iconst_4
L2569:  iconst_0
L2570:  iload 10
L2572:  iload 11
L2574:  iload 12
L2576:  iload 13
L2578:  iconst_m1
L2579:  invokevirtual Method YZDBYLRM a (IIIIIII)LZKARKDQW;
L2582:  astore 18
L2584:  iload 26
L2586:  ifeq L2618
L2589:  new WBWOBAFW
L2592:  dup
L2593:  iload 7
L2595:  iconst_0
L2596:  iconst_4
L2597:  iload 11
L2599:  bipush 7
L2601:  iload 12
L2603:  iload 10
L2605:  iload 13
L2607:  aload 15
L2609:  getfield Field YZDBYLRM T I
L2612:  iconst_1
L2613:  invokespecial Method WBWOBAFW <init> (IIIIBIIIIZ)V
L2616:  astore 18
L2618:  aload_2
L2619:  iload 16
L2621:  iload_1
L2622:  iload 9
L2624:  sipush 512
L2627:  imul
L2628:  sipush -460
L2631:  iload 5
L2633:  iconst_0
L2634:  iload 14
L2636:  aload 18
L2638:  iload 6
L2640:  iload 17
L2642:  iconst_0
L2643:  getstatic Field CRRWDRTI D [I
L2646:  iload 9
L2648:  iaload
L2649:  invokevirtual Method NYFUGYQS a (IIIIIIILXHHRODPC;IBII)V
L2652:  return
L2653:  iload 4
L2655:  iconst_5
L2656:  if_icmpne L2816
L2659:  bipush 16
L2661:  istore 18
L2663:  aload_2
L2664:  iload 5
L2666:  iload 6
L2668:  iload_1
L2669:  invokevirtual Method NYFUGYQS c (III)I
L2672:  istore 19
L2674:  iload 19
L2676:  ifle L2696
L2679:  iload 19
L2681:  bipush 14
L2683:  ishr
L2684:  sipush 32767
L2687:  iand
L2688:  invokestatic Method YZDBYLRM a (I)LYZDBYLRM;
L2691:  getfield Field YZDBYLRM N I
L2694:  istore 18
L2696:  aload 15
L2698:  getfield Field YZDBYLRM T I
L2701:  iconst_m1
L2702:  if_icmpne L2736
L2705:  aload 15
L2707:  getfield Field YZDBYLRM x [I
L2710:  ifnonnull L2736
L2713:  aload 15
L2715:  iconst_4
L2716:  iconst_0
L2717:  iload 10
L2719:  iload 11
L2721:  iload 12
L2723:  iload 13
L2725:  iconst_m1
L2726:  invokevirtual Method YZDBYLRM a (IIIIIII)LZKARKDQW;
L2729:  astore 20
L2731:  iload 26
L2733:  ifeq L2765
L2736:  new WBWOBAFW
L2739:  dup
L2740:  iload 7
L2742:  iconst_0
L2743:  iconst_4
L2744:  iload 11
L2746:  bipush 7
L2748:  iload 12
L2750:  iload 10
L2752:  iload 13
L2754:  aload 15
L2756:  getfield Field YZDBYLRM T I
L2759:  iconst_1
L2760:  invokespecial Method WBWOBAFW <init> (IIIIBIIIIZ)V
L2763:  astore 20
L2765:  aload_2
L2766:  iload 16
L2768:  iload_1
L2769:  iload 9
L2771:  sipush 512
L2774:  imul
L2775:  sipush -460
L2778:  iload 5
L2780:  getstatic Field CRRWDRTI o [I
L2783:  iload 9
L2785:  iaload
L2786:  iload 18
L2788:  imul
L2789:  iload 14
L2791:  aload 20
L2793:  iload 6
L2795:  iload 17
L2797:  getstatic Field CRRWDRTI v [I
L2800:  iload 9
L2802:  iaload
L2803:  iload 18
L2805:  imul
L2806:  getstatic Field CRRWDRTI D [I
L2809:  iload 9
L2811:  iaload
L2812:  invokevirtual Method NYFUGYQS a (IIIIIIILXHHRODPC;IBII)V
L2815:  return
L2816:  iload 4
L2818:  bipush 6
L2820:  if_icmpne L2920
L2823:  aload 15
L2825:  getfield Field YZDBYLRM T I
L2828:  iconst_m1
L2829:  if_icmpne L2863
L2832:  aload 15
L2834:  getfield Field YZDBYLRM x [I
L2837:  ifnonnull L2863
L2840:  aload 15
L2842:  iconst_4
L2843:  iconst_0
L2844:  iload 10
L2846:  iload 11
L2848:  iload 12
L2850:  iload 13
L2852:  iconst_m1
L2853:  invokevirtual Method YZDBYLRM a (IIIIIII)LZKARKDQW;
L2856:  astore 18
L2858:  iload 26
L2860:  ifeq L2892
L2863:  new WBWOBAFW
L2866:  dup
L2867:  iload 7
L2869:  iconst_0
L2870:  iconst_4
L2871:  iload 11
L2873:  bipush 7
L2875:  iload 12
L2877:  iload 10
L2879:  iload 13
L2881:  aload 15
L2883:  getfield Field YZDBYLRM T I
L2886:  iconst_1
L2887:  invokespecial Method WBWOBAFW <init> (IIIIBIIIIZ)V
L2890:  astore 18
L2892:  aload_2
L2893:  iload 16
L2895:  iload_1
L2896:  iload 9
L2898:  sipush -460
L2901:  iload 5
L2903:  iconst_0
L2904:  iload 14
L2906:  aload 18
L2908:  iload 6
L2910:  iload 17
L2912:  iconst_0
L2913:  sipush 256
L2916:  invokevirtual Method NYFUGYQS a (IIIIIIILXHHRODPC;IBII)V
L2919:  return
L2920:  iload 4
L2922:  bipush 7
L2924:  if_icmpne L3024
L2927:  aload 15
L2929:  getfield Field YZDBYLRM T I
L2932:  iconst_m1
L2933:  if_icmpne L2967
L2936:  aload 15
L2938:  getfield Field YZDBYLRM x [I
L2941:  ifnonnull L2967
L2944:  aload 15
L2946:  iconst_4
L2947:  iconst_0
L2948:  iload 10
L2950:  iload 11
L2952:  iload 12
L2954:  iload 13
L2956:  iconst_m1
L2957:  invokevirtual Method YZDBYLRM a (IIIIIII)LZKARKDQW;
L2960:  astore 18
L2962:  iload 26
L2964:  ifeq L2996
L2967:  new WBWOBAFW
L2970:  dup
L2971:  iload 7
L2973:  iconst_0
L2974:  iconst_4
L2975:  iload 11
L2977:  bipush 7
L2979:  iload 12
L2981:  iload 10
L2983:  iload 13
L2985:  aload 15
L2987:  getfield Field YZDBYLRM T I
L2990:  iconst_1
L2991:  invokespecial Method WBWOBAFW <init> (IIIIBIIIIZ)V
L2994:  astore 18
L2996:  aload_2
L2997:  iload 16
L2999:  iload_1
L3000:  iload 9
L3002:  sipush -460
L3005:  iload 5
L3007:  iconst_0
L3008:  iload 14
L3010:  aload 18
L3012:  iload 6
L3014:  iload 17
L3016:  iconst_0
L3017:  sipush 512
L3020:  invokevirtual Method NYFUGYQS a (IIIIIIILXHHRODPC;IBII)V
L3023:  return
L3024:  iload 4
L3026:  bipush 8
L3028:  if_icmpne L3248
L3031:  aload 15
L3033:  getfield Field YZDBYLRM T I
L3036:  iconst_m1
L3037:  if_icmpne L3071
L3040:  aload 15
L3042:  getfield Field YZDBYLRM x [I
L3045:  ifnonnull L3071
L3048:  aload 15
L3050:  iconst_4
L3051:  iconst_0
L3052:  iload 10
L3054:  iload 11
L3056:  iload 12
L3058:  iload 13
L3060:  iconst_m1
L3061:  invokevirtual Method YZDBYLRM a (IIIIIII)LZKARKDQW;
L3064:  astore 18
L3066:  iload 26
L3068:  ifeq L3100
L3071:  new WBWOBAFW
L3074:  dup
L3075:  iload 7
L3077:  iconst_0
L3078:  iconst_4
L3079:  iload 11
L3081:  bipush 7
L3083:  iload 12
L3085:  iload 10
L3087:  iload 13
L3089:  aload 15
L3091:  getfield Field YZDBYLRM T I
L3094:  iconst_1
L3095:  invokespecial Method WBWOBAFW <init> (IIIIBIIIIZ)V
L3098:  astore 18
L3100:  aload_2
L3101:  iload 16
L3103:  iload_1
L3104:  iload 9
L3106:  sipush -460
L3109:  iload 5
L3111:  iconst_0
L3112:  iload 14
L3114:  aload 18
L3116:  iload 6
L3118:  iload 17
L3120:  iconst_0
L3121:  sipush 768
L3124:  invokevirtual Method NYFUGYQS a (IIIIIIILXHHRODPC;IBII)V
L3127:  return
L3128:  astore 10
L3130:  new java/lang/StringBuffer
L3133:  dup
L3134:  ldc "16863, "
L3136:  invokespecial Method java/lang/StringBuffer <init> (Ljava/lang/String;)V
L3139:  iload_1
L3140:  invokevirtual Method java/lang/StringBuffer append (I)Ljava/lang/StringBuffer;
L3143:  ldc ", "
L3145:  invokevirtual Method java/lang/StringBuffer append (Ljava/lang/String;)Ljava/lang/StringBuffer;
L3148:  aload_2
L3149:  invokevirtual Method java/lang/StringBuffer append (Ljava/lang/Object;)Ljava/lang/StringBuffer;
L3152:  ldc ", "
L3154:  invokevirtual Method java/lang/StringBuffer append (Ljava/lang/String;)Ljava/lang/StringBuffer;
L3157:  aload_3
L3158:  invokevirtual Method java/lang/StringBuffer append (Ljava/lang/Object;)Ljava/lang/StringBuffer;
L3161:  ldc ", "
L3163:  invokevirtual Method java/lang/StringBuffer append (Ljava/lang/String;)Ljava/lang/StringBuffer;
L3166:  iload 4
L3168:  invokevirtual Method java/lang/StringBuffer append (I)Ljava/lang/StringBuffer;
L3171:  ldc ", "
L3173:  invokevirtual Method java/lang/StringBuffer append (Ljava/lang/String;)Ljava/lang/StringBuffer;
L3176:  iload 5
L3178:  invokevirtual Method java/lang/StringBuffer append (I)Ljava/lang/StringBuffer;
L3181:  ldc ", "
L3183:  invokevirtual Method java/lang/StringBuffer append (Ljava/lang/String;)Ljava/lang/StringBuffer;
L3186:  iload 6
L3188:  invokevirtual Method java/lang/StringBuffer append (I)Ljava/lang/StringBuffer;
L3191:  ldc ", "
L3193:  invokevirtual Method java/lang/StringBuffer append (Ljava/lang/String;)Ljava/lang/StringBuffer;
L3196:  iload 7
L3198:  invokevirtual Method java/lang/StringBuffer append (I)Ljava/lang/StringBuffer;
L3201:  ldc ", "
L3203:  invokevirtual Method java/lang/StringBuffer append (Ljava/lang/String;)Ljava/lang/StringBuffer;
L3206:  iload 8
L3208:  invokevirtual Method java/lang/StringBuffer append (Z)Ljava/lang/StringBuffer;
L3211:  ldc ", "
L3213:  invokevirtual Method java/lang/StringBuffer append (Ljava/lang/String;)Ljava/lang/StringBuffer;
L3216:  iload 9
L3218:  invokevirtual Method java/lang/StringBuffer append (I)Ljava/lang/StringBuffer;
L3221:  ldc ", "
L3223:  invokevirtual Method java/lang/StringBuffer append (Ljava/lang/String;)Ljava/lang/StringBuffer;
L3226:  aload 10
L3228:  invokevirtual Method java/lang/Throwable toString ()Ljava/lang/String;
L3231:  invokevirtual Method java/lang/StringBuffer append (Ljava/lang/String;)Ljava/lang/StringBuffer;
L3234:  invokevirtual Method java/lang/StringBuffer toString ()Ljava/lang/String;
L3237:  invokestatic Method sign/signlink reporterror (Ljava/lang/String;)V
L3240:  new java/lang/RuntimeException
L3243:  dup
L3244:  invokespecial Method java/lang/RuntimeException <init> ()V
L3247:  athrow
L3248:  return
L3249:  
    .end code
.end method

.method private static final a : (III)I
    .code stack 4 locals 13
L0:     iload_0
L1:     iload_2
L2:     idiv
L3:     istore_3
L4:     iload_0
L5:     iload_2
L6:     iconst_1
L7:     isub
L8:     iand
L9:     istore 4
L11:    iload_1
L12:    iload_2
L13:    idiv
L14:    istore 5
L16:    iload_1
L17:    iload_2
L18:    iconst_1
L19:    isub
L20:    iand
L21:    istore 6
L23:    iload_3
L24:    iload 5
L26:    invokestatic Method CRRWDRTI d (II)I
L29:    istore 7
L31:    iload_3
L32:    iconst_1
L33:    iadd
L34:    iload 5
L36:    invokestatic Method CRRWDRTI d (II)I
L39:    istore 8
L41:    iload_3
L42:    iload 5
L44:    iconst_1
L45:    iadd
L46:    invokestatic Method CRRWDRTI d (II)I
L49:    istore 9
L51:    iload_3
L52:    iconst_1
L53:    iadd
L54:    iload 5
L56:    iconst_1
L57:    iadd
L58:    invokestatic Method CRRWDRTI d (II)I
L61:    istore 10
L63:    iload 7
L65:    iload 8
L67:    iload 4
L69:    iload_2
L70:    invokestatic Method CRRWDRTI b (IIII)I
L73:    istore 11
L75:    iload 9
L77:    iload 10
L79:    iload 4
L81:    iload_2
L82:    invokestatic Method CRRWDRTI b (IIII)I
L85:    istore 12
L87:    iload 11
L89:    iload 12
L91:    iload 6
L93:    iload_2
L94:    invokestatic Method CRRWDRTI b (IIII)I
L97:    ireturn
L98:    
    .end code
.end method

.method private final b : (III)I
    .code stack 3 locals 5
L0:     iload_3
L1:     sipush 179
L4:     if_icmple L11
L7:     iload_2
L8:     iconst_2
L9:     idiv
L10:    istore_2
L11:    iload_3
L12:    sipush 192
L15:    if_icmple L22
L18:    iload_2
L19:    iconst_2
L20:    idiv
L21:    istore_2
L22:    iload_3
L23:    sipush 217
L26:    if_icmple L33
L29:    iload_2
L30:    iconst_2
L31:    idiv
L32:    istore_2
L33:    iload_3
L34:    sipush 243
L37:    if_icmple L44
L40:    iload_2
L41:    iconst_2
L42:    idiv
L43:    istore_2
L44:    iload_1
L45:    iconst_4
L46:    idiv
L47:    bipush 10
L49:    ishl
L50:    iload_2
L51:    bipush 32
L53:    idiv
L54:    bipush 7
L56:    ishl
L57:    iadd
L58:    iload_3
L59:    iconst_2
L60:    idiv
L61:    iadd
L62:    istore 4
L64:    iload 4
L66:    ireturn
L67:    
    .end code
.end method

.method public static final c : (III)Z
    .code stack 4 locals 5
        .catch java/lang/RuntimeException from L0 to L57 using L57
L0:     iload_0
L1:     invokestatic Method YZDBYLRM a (I)LYZDBYLRM;
L4:     astore_3
L5:     iload_2
L6:     bipush 8
L8:     if_icmpeq L28
L11:    iconst_1
L12:    istore 4
L14:    getstatic Field client Jj I
L17:    ifeq L23
L20:    iinc 4 1
L23:    iload 4
L25:    ifgt L20
L28:    iload_1
L29:    bipush 11
L31:    if_icmpne L37
L34:    bipush 10
L36:    istore_1
L37:    iload_1
L38:    iconst_5
L39:    if_icmplt L50
L42:    iload_1
L43:    bipush 8
L45:    if_icmpgt L50
L48:    iconst_4
L49:    istore_1
L50:    aload_3
L51:    iload_1
L52:    iconst_1
L53:    invokevirtual Method YZDBYLRM a (IZ)Z
L56:    ireturn
L57:    astore_3
L58:    new java/lang/StringBuffer
L61:    dup
L62:    ldc "51637, "
L64:    invokespecial Method java/lang/StringBuffer <init> (Ljava/lang/String;)V
L67:    iload_0
L68:    invokevirtual Method java/lang/StringBuffer append (I)Ljava/lang/StringBuffer;
L71:    ldc ", "
L73:    invokevirtual Method java/lang/StringBuffer append (Ljava/lang/String;)Ljava/lang/StringBuffer;
L76:    iload_1
L77:    invokevirtual Method java/lang/StringBuffer append (I)Ljava/lang/StringBuffer;
L80:    ldc ", "
L82:    invokevirtual Method java/lang/StringBuffer append (Ljava/lang/String;)Ljava/lang/StringBuffer;
L85:    iload_2
L86:    invokevirtual Method java/lang/StringBuffer append (I)Ljava/lang/StringBuffer;
L89:    ldc ", "
L91:    invokevirtual Method java/lang/StringBuffer append (Ljava/lang/String;)Ljava/lang/StringBuffer;
L94:    aload_3
L95:    invokevirtual Method java/lang/Throwable toString ()Ljava/lang/String;
L98:    invokevirtual Method java/lang/StringBuffer append (Ljava/lang/String;)Ljava/lang/StringBuffer;
L101:   invokevirtual Method java/lang/StringBuffer toString ()Ljava/lang/String;
L104:   invokestatic Method sign/signlink reporterror (Ljava/lang/String;)V
L107:   new java/lang/RuntimeException
L110:   dup
L111:   invokespecial Method java/lang/RuntimeException <init> ()V
L114:   athrow
L115:   
    .end code
.end method

.method public final a : (II[LFTPNODIB;III[BIII)V
    .code stack 10 locals 17
L0:     getstatic Field client Jj I
L3:     istore 16
        .catch java/lang/RuntimeException from L5 to L310 using L311
L5:     iconst_0
L6:     istore 11
L8:     iload 16
L10:    ifeq L94
L13:    iconst_0
L14:    istore 12
L16:    iload 16
L18:    ifeq L84
L21:    iload 5
L23:    iload 11
L25:    iadd
L26:    ifle L81
L29:    iload 5
L31:    iload 11
L33:    iadd
L34:    bipush 103
L36:    if_icmpge L81
L39:    iload 10
L41:    iload 12
L43:    iadd
L44:    ifle L81
L47:    iload 10
L49:    iload 12
L51:    iadd
L52:    bipush 103
L54:    if_icmpge L81
L57:    aload_3
L58:    iload 9
L60:    aaload
L61:    getfield Field FTPNODIB m [[I
L64:    iload 5
L66:    iload 11
L68:    iadd
L69:    aaload
L70:    iload 10
L72:    iload 12
L74:    iadd
L75:    dup2
L76:    iaload
L77:    ldc -16777217
L79:    iand
L80:    iastore
L81:    iinc 12 1
L84:    iload 12
L86:    bipush 8
L88:    if_icmplt L21
L91:    iinc 11 1
L94:    iload 11
L96:    bipush 8
L98:    if_icmplt L13
L101:   iload 4
L103:   bipush 9
L105:   if_icmplt L115
L108:   iload 4
L110:   bipush 9
L112:   if_icmple L131
L115:   iconst_1
L116:   istore 12
L118:   iload 16
L120:   ifeq L126
L123:   iinc 12 1
L126:   iload 12
L128:   ifgt L123
L131:   new MBMGIXGO
L134:   dup
L135:   aload 7
L137:   sipush 891
L140:   invokespecial Method MBMGIXGO <init> ([BI)V
L143:   astore 12
L145:   iconst_0
L146:   istore 13
L148:   iload 16
L150:   ifeq L304
L153:   iconst_0
L154:   istore 14
L156:   iload 16
L158:   ifeq L294
L161:   iconst_0
L162:   istore 15
L164:   iload 16
L166:   ifeq L284
L169:   iload 13
L171:   iload_1
L172:   if_icmpne L266
L175:   iload 14
L177:   iload 6
L179:   if_icmplt L266
L182:   iload 14
L184:   iload 6
L186:   bipush 8
L188:   iadd
L189:   if_icmpge L266
L192:   iload 15
L194:   iload 8
L196:   if_icmplt L266
L199:   iload 15
L201:   iload 8
L203:   bipush 8
L205:   iadd
L206:   if_icmpge L266
L209:   aload_0
L210:   iload 10
L212:   iload 15
L214:   bipush 7
L216:   iand
L217:   iload_2
L218:   sipush -383
L221:   iload 14
L223:   bipush 7
L225:   iand
L226:   invokestatic Method CDEJWOSB a (IIII)I
L229:   iadd
L230:   iconst_0
L231:   aload 12
L233:   iload 5
L235:   iload_2
L236:   iload 15
L238:   bipush 7
L240:   iand
L241:   iload 14
L243:   bipush 7
L245:   iand
L246:   iconst_0
L247:   invokestatic Method CDEJWOSB a (IIIZ)I
L250:   iadd
L251:   iload 9
L253:   iload_2
L254:   sipush 942
L257:   iconst_0
L258:   invokespecial Method CRRWDRTI a (IILMBMGIXGO;IIIII)V
L261:   iload 16
L263:   ifeq L281
L266:   aload_0
L267:   iconst_m1
L268:   iconst_0
L269:   aload 12
L271:   iconst_m1
L272:   iconst_0
L273:   iconst_0
L274:   sipush 942
L277:   iconst_0
L278:   invokespecial Method CRRWDRTI a (IILMBMGIXGO;IIIII)V
L281:   iinc 15 1
L284:   iload 15
L286:   bipush 64
L288:   if_icmplt L169
L291:   iinc 14 1
L294:   iload 14
L296:   bipush 64
L298:   if_icmplt L161
L301:   iinc 13 1
L304:   iload 13
L306:   iconst_4
L307:   if_icmplt L153
L310:   return
L311:   astore 11
L313:   new java/lang/StringBuffer
L316:   dup
L317:   ldc "28153, "
L319:   invokespecial Method java/lang/StringBuffer <init> (Ljava/lang/String;)V
L322:   iload_1
L323:   invokevirtual Method java/lang/StringBuffer append (I)Ljava/lang/StringBuffer;
L326:   ldc ", "
L328:   invokevirtual Method java/lang/StringBuffer append (Ljava/lang/String;)Ljava/lang/StringBuffer;
L331:   iload_2
L332:   invokevirtual Method java/lang/StringBuffer append (I)Ljava/lang/StringBuffer;
L335:   ldc ", "
L337:   invokevirtual Method java/lang/StringBuffer append (Ljava/lang/String;)Ljava/lang/StringBuffer;
L340:   aload_3
L341:   invokevirtual Method java/lang/StringBuffer append (Ljava/lang/Object;)Ljava/lang/StringBuffer;
L344:   ldc ", "
L346:   invokevirtual Method java/lang/StringBuffer append (Ljava/lang/String;)Ljava/lang/StringBuffer;
L349:   iload 4
L351:   invokevirtual Method java/lang/StringBuffer append (I)Ljava/lang/StringBuffer;
L354:   ldc ", "
L356:   invokevirtual Method java/lang/StringBuffer append (Ljava/lang/String;)Ljava/lang/StringBuffer;
L359:   iload 5
L361:   invokevirtual Method java/lang/StringBuffer append (I)Ljava/lang/StringBuffer;
L364:   ldc ", "
L366:   invokevirtual Method java/lang/StringBuffer append (Ljava/lang/String;)Ljava/lang/StringBuffer;
L369:   iload 6
L371:   invokevirtual Method java/lang/StringBuffer append (I)Ljava/lang/StringBuffer;
L374:   ldc ", "
L376:   invokevirtual Method java/lang/StringBuffer append (Ljava/lang/String;)Ljava/lang/StringBuffer;
L379:   aload 7
L381:   invokevirtual Method java/lang/StringBuffer append (Ljava/lang/Object;)Ljava/lang/StringBuffer;
L384:   ldc ", "
L386:   invokevirtual Method java/lang/StringBuffer append (Ljava/lang/String;)Ljava/lang/StringBuffer;
L389:   iload 8
L391:   invokevirtual Method java/lang/StringBuffer append (I)Ljava/lang/StringBuffer;
L394:   ldc ", "
L396:   invokevirtual Method java/lang/StringBuffer append (Ljava/lang/String;)Ljava/lang/StringBuffer;
L399:   iload 9
L401:   invokevirtual Method java/lang/StringBuffer append (I)Ljava/lang/StringBuffer;
L404:   ldc ", "
L406:   invokevirtual Method java/lang/StringBuffer append (Ljava/lang/String;)Ljava/lang/StringBuffer;
L409:   iload 10
L411:   invokevirtual Method java/lang/StringBuffer append (I)Ljava/lang/StringBuffer;
L414:   ldc ", "
L416:   invokevirtual Method java/lang/StringBuffer append (Ljava/lang/String;)Ljava/lang/StringBuffer;
L419:   aload 11
L421:   invokevirtual Method java/lang/Throwable toString ()Ljava/lang/String;
L424:   invokevirtual Method java/lang/StringBuffer append (Ljava/lang/String;)Ljava/lang/StringBuffer;
L427:   invokevirtual Method java/lang/StringBuffer toString ()Ljava/lang/String;
L430:   invokestatic Method sign/signlink reporterror (Ljava/lang/String;)V
L433:   new java/lang/RuntimeException
L436:   dup
L437:   invokespecial Method java/lang/RuntimeException <init> ()V
L440:   athrow
L441:   
    .end code
.end method

.method public final a : ([BIIIIB[LFTPNODIB;)V
    .code stack 10 locals 14
L0:     getstatic Field client Jj I
L3:     istore 13
        .catch java/lang/RuntimeException from L5 to L225 using L226
L5:     iconst_0
L6:     istore 8
L8:     iload 13
L10:    ifeq L107
L13:    iconst_0
L14:    istore 9
L16:    iload 13
L18:    ifeq L97
L21:    iconst_0
L22:    istore 10
L24:    iload 13
L26:    ifeq L87
L29:    iload_3
L30:    iload 9
L32:    iadd
L33:    ifle L84
L36:    iload_3
L37:    iload 9
L39:    iadd
L40:    bipush 103
L42:    if_icmpge L84
L45:    iload_2
L46:    iload 10
L48:    iadd
L49:    ifle L84
L52:    iload_2
L53:    iload 10
L55:    iadd
L56:    bipush 103
L58:    if_icmpge L84
L61:    aload 7
L63:    iload 8
L65:    aaload
L66:    getfield Field FTPNODIB m [[I
L69:    iload_3
L70:    iload 9
L72:    iadd
L73:    aaload
L74:    iload_2
L75:    iload 10
L77:    iadd
L78:    dup2
L79:    iaload
L80:    ldc -16777217
L82:    iand
L83:    iastore
L84:    iinc 10 1
L87:    iload 10
L89:    bipush 64
L91:    if_icmplt L29
L94:    iinc 9 1
L97:    iload 9
L99:    bipush 64
L101:   if_icmplt L21
L104:   iinc 8 1
L107:   iload 8
L109:   iconst_4
L110:   if_icmplt L13
L113:   new MBMGIXGO
L116:   dup
L117:   aload_1
L118:   sipush 891
L121:   invokespecial Method MBMGIXGO <init> ([BI)V
L124:   astore 9
L126:   iconst_0
L127:   istore 10
L129:   iload 13
L131:   ifeq L197
L134:   iconst_0
L135:   istore 11
L137:   iload 13
L139:   ifeq L187
L142:   iconst_0
L143:   istore 12
L145:   iload 13
L147:   ifeq L177
L150:   aload_0
L151:   iload 12
L153:   iload_2
L154:   iadd
L155:   iload 5
L157:   aload 9
L159:   iload 11
L161:   iload_3
L162:   iadd
L163:   iload 10
L165:   iconst_0
L166:   sipush 942
L169:   iload 4
L171:   invokespecial Method CRRWDRTI a (IILMBMGIXGO;IIIII)V
L174:   iinc 12 1
L177:   iload 12
L179:   bipush 64
L181:   if_icmplt L150
L184:   iinc 11 1
L187:   iload 11
L189:   bipush 64
L191:   if_icmplt L142
L194:   iinc 10 1
L197:   iload 10
L199:   iconst_4
L200:   if_icmplt L134
L203:   iload 6
L205:   iconst_4
L206:   if_icmpeq L326
L209:   aload_0
L210:   aload_0
L211:   getfield Field CRRWDRTI u Z
L214:   ifeq L221
L217:   iconst_0
L218:   goto L222
L221:   iconst_1
L222:   putfield Field CRRWDRTI u Z
L225:   return
L226:   astore 8
L228:   new java/lang/StringBuffer
L231:   dup
L232:   ldc "41691, "
L234:   invokespecial Method java/lang/StringBuffer <init> (Ljava/lang/String;)V
L237:   aload_1
L238:   invokevirtual Method java/lang/StringBuffer append (Ljava/lang/Object;)Ljava/lang/StringBuffer;
L241:   ldc ", "
L243:   invokevirtual Method java/lang/StringBuffer append (Ljava/lang/String;)Ljava/lang/StringBuffer;
L246:   iload_2
L247:   invokevirtual Method java/lang/StringBuffer append (I)Ljava/lang/StringBuffer;
L250:   ldc ", "
L252:   invokevirtual Method java/lang/StringBuffer append (Ljava/lang/String;)Ljava/lang/StringBuffer;
L255:   iload_3
L256:   invokevirtual Method java/lang/StringBuffer append (I)Ljava/lang/StringBuffer;
L259:   ldc ", "
L261:   invokevirtual Method java/lang/StringBuffer append (Ljava/lang/String;)Ljava/lang/StringBuffer;
L264:   iload 4
L266:   invokevirtual Method java/lang/StringBuffer append (I)Ljava/lang/StringBuffer;
L269:   ldc ", "
L271:   invokevirtual Method java/lang/StringBuffer append (Ljava/lang/String;)Ljava/lang/StringBuffer;
L274:   iload 5
L276:   invokevirtual Method java/lang/StringBuffer append (I)Ljava/lang/StringBuffer;
L279:   ldc ", "
L281:   invokevirtual Method java/lang/StringBuffer append (Ljava/lang/String;)Ljava/lang/StringBuffer;
L284:   iload 6
L286:   invokevirtual Method java/lang/StringBuffer append (I)Ljava/lang/StringBuffer;
L289:   ldc ", "
L291:   invokevirtual Method java/lang/StringBuffer append (Ljava/lang/String;)Ljava/lang/StringBuffer;
L294:   aload 7
L296:   invokevirtual Method java/lang/StringBuffer append (Ljava/lang/Object;)Ljava/lang/StringBuffer;
L299:   ldc ", "
L301:   invokevirtual Method java/lang/StringBuffer append (Ljava/lang/String;)Ljava/lang/StringBuffer;
L304:   aload 8
L306:   invokevirtual Method java/lang/Throwable toString ()Ljava/lang/String;
L309:   invokevirtual Method java/lang/StringBuffer append (Ljava/lang/String;)Ljava/lang/StringBuffer;
L312:   invokevirtual Method java/lang/StringBuffer toString ()Ljava/lang/String;
L315:   invokestatic Method sign/signlink reporterror (Ljava/lang/String;)V
L318:   new java/lang/RuntimeException
L321:   dup
L322:   invokespecial Method java/lang/RuntimeException <init> ()V
L325:   athrow
L326:   return
L327:   
    .end code
.end method

.method private final a : (IILMBMGIXGO;IIIII)V
    .code stack 6 locals 12
L0:     getstatic Field client Jj I
L3:     istore 11
        .catch java/lang/RuntimeException from L5 to L366 using L367
L5:     bipush 36
L7:     iload 7
L9:     idiv
L10:    istore 7
L12:    iload 4
L14:    iflt L326
L17:    iload 4
L19:    bipush 104
L21:    if_icmpge L326
L24:    iload_1
L25:    iflt L326
L28:    iload_1
L29:    bipush 104
L31:    if_icmpge L326
L34:    aload_0
L35:    getfield Field CRRWDRTI A [[[B
L38:    iload 5
L40:    aaload
L41:    iload 4
L43:    aaload
L44:    iload_1
L45:    iconst_0
L46:    bastore
L47:    aload_3
L48:    invokevirtual Method MBMGIXGO c ()I
L51:    istore 9
L53:    iload 9
L55:    ifne L127
L58:    iload 5
L60:    ifne L96
L63:    aload_0
L64:    getfield Field CRRWDRTI g [[[I
L67:    iconst_0
L68:    aaload
L69:    iload 4
L71:    aaload
L72:    iload_1
L73:    ldc 932731
L75:    iload 4
L77:    iadd
L78:    iload 8
L80:    iadd
L81:    ldc 556238
L83:    iload_1
L84:    iadd
L85:    iload_2
L86:    iadd
L87:    invokestatic Method CRRWDRTI b (II)I
L90:    ineg
L91:    bipush 8
L93:    imul
L94:    iastore
L95:    return
L96:    aload_0
L97:    getfield Field CRRWDRTI g [[[I
L100:   iload 5
L102:   aaload
L103:   iload 4
L105:   aaload
L106:   iload_1
L107:   aload_0
L108:   getfield Field CRRWDRTI g [[[I
L111:   iload 5
L113:   iconst_1
L114:   isub
L115:   aaload
L116:   iload 4
L118:   aaload
L119:   iload_1
L120:   iaload
L121:   sipush 240
L124:   isub
L125:   iastore
L126:   return
L127:   iload 9
L129:   iconst_1
L130:   if_icmpne L204
L133:   aload_3
L134:   invokevirtual Method MBMGIXGO c ()I
L137:   istore 10
L139:   iload 10
L141:   iconst_1
L142:   if_icmpne L148
L145:   iconst_0
L146:   istore 10
L148:   iload 5
L150:   ifne L171
L153:   aload_0
L154:   getfield Field CRRWDRTI g [[[I
L157:   iconst_0
L158:   aaload
L159:   iload 4
L161:   aaload
L162:   iload_1
L163:   iload 10
L165:   ineg
L166:   bipush 8
L168:   imul
L169:   iastore
L170:   return
L171:   aload_0
L172:   getfield Field CRRWDRTI g [[[I
L175:   iload 5
L177:   aaload
L178:   iload 4
L180:   aaload
L181:   iload_1
L182:   aload_0
L183:   getfield Field CRRWDRTI g [[[I
L186:   iload 5
L188:   iconst_1
L189:   isub
L190:   aaload
L191:   iload 4
L193:   aaload
L194:   iload_1
L195:   iaload
L196:   iload 10
L198:   bipush 8
L200:   imul
L201:   isub
L202:   iastore
L203:   return
L204:   iload 9
L206:   bipush 49
L208:   if_icmpgt L273
L211:   aload_0
L212:   getfield Field CRRWDRTI h [[[B
L215:   iload 5
L217:   aaload
L218:   iload 4
L220:   aaload
L221:   iload_1
L222:   aload_3
L223:   invokevirtual Method MBMGIXGO d ()B
L226:   bastore
L227:   aload_0
L228:   getfield Field CRRWDRTI n [[[B
L231:   iload 5
L233:   aaload
L234:   iload 4
L236:   aaload
L237:   iload_1
L238:   iload 9
L240:   iconst_2
L241:   isub
L242:   iconst_4
L243:   idiv
L244:   i2b
L245:   bastore
L246:   aload_0
L247:   getfield Field CRRWDRTI z [[[B
L250:   iload 5
L252:   aaload
L253:   iload 4
L255:   aaload
L256:   iload_1
L257:   iload 9
L259:   iconst_2
L260:   isub
L261:   iload 6
L263:   iadd
L264:   iconst_3
L265:   iand
L266:   i2b
L267:   bastore
L268:   iload 11
L270:   ifeq L47
L273:   iload 9
L275:   bipush 81
L277:   if_icmpgt L303
L280:   aload_0
L281:   getfield Field CRRWDRTI A [[[B
L284:   iload 5
L286:   aaload
L287:   iload 4
L289:   aaload
L290:   iload_1
L291:   iload 9
L293:   bipush 49
L295:   isub
L296:   i2b
L297:   bastore
L298:   iload 11
L300:   ifeq L47
L303:   aload_0
L304:   getfield Field CRRWDRTI t [[[B
L307:   iload 5
L309:   aaload
L310:   iload 4
L312:   aaload
L313:   iload_1
L314:   iload 9
L316:   bipush 81
L318:   isub
L319:   i2b
L320:   bastore
L321:   iload 11
L323:   ifeq L47
L326:   aload_3
L327:   invokevirtual Method MBMGIXGO c ()I
L330:   istore 9
L332:   iload 9
L334:   ifeq L366
L337:   iload 9
L339:   iconst_1
L340:   if_icmpne L349
L343:   aload_3
L344:   invokevirtual Method MBMGIXGO c ()I
L347:   pop
L348:   return
L349:   iload 9
L351:   bipush 49
L353:   if_icmpgt L326
L356:   aload_3
L357:   invokevirtual Method MBMGIXGO c ()I
L360:   pop
L361:   iload 11
L363:   ifeq L326
L366:   return
L367:   astore 9
L369:   new java/lang/StringBuffer
L372:   dup
L373:   ldc "30203, "
L375:   invokespecial Method java/lang/StringBuffer <init> (Ljava/lang/String;)V
L378:   iload_1
L379:   invokevirtual Method java/lang/StringBuffer append (I)Ljava/lang/StringBuffer;
L382:   ldc ", "
L384:   invokevirtual Method java/lang/StringBuffer append (Ljava/lang/String;)Ljava/lang/StringBuffer;
L387:   iload_2
L388:   invokevirtual Method java/lang/StringBuffer append (I)Ljava/lang/StringBuffer;
L391:   ldc ", "
L393:   invokevirtual Method java/lang/StringBuffer append (Ljava/lang/String;)Ljava/lang/StringBuffer;
L396:   aload_3
L397:   invokevirtual Method java/lang/StringBuffer append (Ljava/lang/Object;)Ljava/lang/StringBuffer;
L400:   ldc ", "
L402:   invokevirtual Method java/lang/StringBuffer append (Ljava/lang/String;)Ljava/lang/StringBuffer;
L405:   iload 4
L407:   invokevirtual Method java/lang/StringBuffer append (I)Ljava/lang/StringBuffer;
L410:   ldc ", "
L412:   invokevirtual Method java/lang/StringBuffer append (Ljava/lang/String;)Ljava/lang/StringBuffer;
L415:   iload 5
L417:   invokevirtual Method java/lang/StringBuffer append (I)Ljava/lang/StringBuffer;
L420:   ldc ", "
L422:   invokevirtual Method java/lang/StringBuffer append (Ljava/lang/String;)Ljava/lang/StringBuffer;
L425:   iload 6
L427:   invokevirtual Method java/lang/StringBuffer append (I)Ljava/lang/StringBuffer;
L430:   ldc ", "
L432:   invokevirtual Method java/lang/StringBuffer append (Ljava/lang/String;)Ljava/lang/StringBuffer;
L435:   iload 7
L437:   invokevirtual Method java/lang/StringBuffer append (I)Ljava/lang/StringBuffer;
L440:   ldc ", "
L442:   invokevirtual Method java/lang/StringBuffer append (Ljava/lang/String;)Ljava/lang/StringBuffer;
L445:   iload 8
L447:   invokevirtual Method java/lang/StringBuffer append (I)Ljava/lang/StringBuffer;
L450:   ldc ", "
L452:   invokevirtual Method java/lang/StringBuffer append (Ljava/lang/String;)Ljava/lang/StringBuffer;
L455:   aload 9
L457:   invokevirtual Method java/lang/Throwable toString ()Ljava/lang/String;
L460:   invokevirtual Method java/lang/StringBuffer append (Ljava/lang/String;)Ljava/lang/StringBuffer;
L463:   invokevirtual Method java/lang/StringBuffer toString ()Ljava/lang/String;
L466:   invokestatic Method sign/signlink reporterror (Ljava/lang/String;)V
L469:   new java/lang/RuntimeException
L472:   dup
L473:   invokespecial Method java/lang/RuntimeException <init> ()V
L476:   athrow
L477:   
    .end code
.end method

.method public a : (IIII)I
    .code stack 3 locals 6
        .catch java/lang/RuntimeException from L0 to L50 using L50
L0:     iload 4
L2:     ifeq L7
L5:     iconst_2
L6:     ireturn
L7:     aload_0
L8:     getfield Field CRRWDRTI A [[[B
L11:    iload_2
L12:    aaload
L13:    iload_3
L14:    aaload
L15:    iload_1
L16:    baload
L17:    bipush 8
L19:    iand
L20:    ifeq L25
L23:    iconst_0
L24:    ireturn
L25:    iload_2
L26:    ifle L48
L29:    aload_0
L30:    getfield Field CRRWDRTI A [[[B
L33:    iconst_1
L34:    aaload
L35:    iload_3
L36:    aaload
L37:    iload_1
L38:    baload
L39:    iconst_2
L40:    iand
L41:    ifeq L48
L44:    iload_2
L45:    iconst_1
L46:    isub
L47:    ireturn
L48:    iload_2
L49:    ireturn
L50:    astore 5
L52:    new java/lang/StringBuffer
L55:    dup
L56:    ldc "5828, "
L58:    invokespecial Method java/lang/StringBuffer <init> (Ljava/lang/String;)V
L61:    iload_1
L62:    invokevirtual Method java/lang/StringBuffer append (I)Ljava/lang/StringBuffer;
L65:    ldc ", "
L67:    invokevirtual Method java/lang/StringBuffer append (Ljava/lang/String;)Ljava/lang/StringBuffer;
L70:    iload_2
L71:    invokevirtual Method java/lang/StringBuffer append (I)Ljava/lang/StringBuffer;
L74:    ldc ", "
L76:    invokevirtual Method java/lang/StringBuffer append (Ljava/lang/String;)Ljava/lang/StringBuffer;
L79:    iload_3
L80:    invokevirtual Method java/lang/StringBuffer append (I)Ljava/lang/StringBuffer;
L83:    ldc ", "
L85:    invokevirtual Method java/lang/StringBuffer append (Ljava/lang/String;)Ljava/lang/StringBuffer;
L88:    iload 4
L90:    invokevirtual Method java/lang/StringBuffer append (I)Ljava/lang/StringBuffer;
L93:    ldc ", "
L95:    invokevirtual Method java/lang/StringBuffer append (Ljava/lang/String;)Ljava/lang/StringBuffer;
L98:    aload 5
L100:   invokevirtual Method java/lang/Throwable toString ()Ljava/lang/String;
L103:   invokevirtual Method java/lang/StringBuffer append (Ljava/lang/String;)Ljava/lang/StringBuffer;
L106:   invokevirtual Method java/lang/StringBuffer toString ()Ljava/lang/String;
L109:   invokestatic Method sign/signlink reporterror (Ljava/lang/String;)V
L112:   new java/lang/RuntimeException
L115:   dup
L116:   invokespecial Method java/lang/RuntimeException <init> ()V
L119:   athrow
L120:   
    .end code
.end method

.method public final a : ([LFTPNODIB;LNYFUGYQS;IIIZI[BIII)V
    .code stack 12 locals 29
L0:     getstatic Field client Jj I
L3:     istore 28
        .catch java/lang/RuntimeException from L5 to L339 using L340
L5:     new MBMGIXGO
L8:     dup
L9:     aload 8
L11:    sipush 891
L14:    invokespecial Method MBMGIXGO <init> ([BI)V
L17:    astore 12
L19:    iconst_m1
L20:    istore 13
L22:    iload 6
L24:    ifne L43
L27:    aload_0
L28:    aload_0
L29:    getfield Field CRRWDRTI u Z
L32:    ifeq L39
L35:    iconst_0
L36:    goto L40
L39:    iconst_1
L40:    putfield Field CRRWDRTI u Z
L43:    aload 12
L45:    invokevirtual Method MBMGIXGO k ()I
L48:    istore 14
L50:    iload 14
L52:    ifeq L339
L55:    iload 13
L57:    iload 14
L59:    iadd
L60:    istore 13
L62:    iconst_0
L63:    istore 15
L65:    aload 12
L67:    invokevirtual Method MBMGIXGO k ()I
L70:    istore 16
L72:    iload 16
L74:    ifeq L334
L77:    iload 15
L79:    iload 16
L81:    iconst_1
L82:    isub
L83:    iadd
L84:    istore 15
L86:    iload 15
L88:    bipush 63
L90:    iand
L91:    istore 17
L93:    iload 15
L95:    bipush 6
L97:    ishr
L98:    bipush 63
L100:   iand
L101:   istore 18
L103:   iload 15
L105:   bipush 12
L107:   ishr
L108:   istore 19
L110:   aload 12
L112:   invokevirtual Method MBMGIXGO c ()I
L115:   istore 20
L117:   iload 20
L119:   iconst_2
L120:   ishr
L121:   istore 21
L123:   iload 20
L125:   iconst_3
L126:   iand
L127:   istore 22
L129:   iload 19
L131:   iload_3
L132:   if_icmpne L65
L135:   iload 18
L137:   iload 9
L139:   if_icmplt L65
L142:   iload 18
L144:   iload 9
L146:   bipush 8
L148:   iadd
L149:   if_icmpge L65
L152:   iload 17
L154:   iload 5
L156:   if_icmplt L65
L159:   iload 17
L161:   iload 5
L163:   bipush 8
L165:   iadd
L166:   if_icmpge L65
L169:   iload 13
L171:   invokestatic Method YZDBYLRM a (I)LYZDBYLRM;
L174:   astore 23
L176:   iload 4
L178:   iload 10
L180:   aload 23
L182:   getfield Field YZDBYLRM z I
L185:   iload 18
L187:   bipush 7
L189:   iand
L190:   bipush 113
L192:   iload 17
L194:   bipush 7
L196:   iand
L197:   aload 23
L199:   getfield Field YZDBYLRM i I
L202:   invokestatic Method CDEJWOSB a (IIIBII)I
L205:   iadd
L206:   istore 24
L208:   iload 11
L210:   sipush -433
L213:   iload 17
L215:   bipush 7
L217:   iand
L218:   aload 23
L220:   getfield Field YZDBYLRM z I
L223:   iload 10
L225:   aload 23
L227:   getfield Field YZDBYLRM i I
L230:   iload 18
L232:   bipush 7
L234:   iand
L235:   invokestatic Method CDEJWOSB a (IIIIII)I
L238:   iadd
L239:   istore 25
L241:   iload 24
L243:   ifle L65
L246:   iload 25
L248:   ifle L65
L251:   iload 24
L253:   bipush 103
L255:   if_icmpge L65
L258:   iload 25
L260:   bipush 103
L262:   if_icmpge L65
L265:   iload 19
L267:   istore 26
L269:   aload_0
L270:   getfield Field CRRWDRTI A [[[B
L273:   iconst_1
L274:   aaload
L275:   iload 24
L277:   aaload
L278:   iload 25
L280:   baload
L281:   iconst_2
L282:   iand
L283:   iconst_2
L284:   if_icmpne L290
L287:   iinc 26 -1
L290:   aconst_null
L291:   astore 27
L293:   iload 26
L295:   iflt L304
L298:   aload_1
L299:   iload 26
L301:   aaload
L302:   astore 27
L304:   aload_0
L305:   iload 25
L307:   aload_2
L308:   aload 27
L310:   iload 21
L312:   iload 7
L314:   iload 24
L316:   iload 13
L318:   iconst_0
L319:   iload 22
L321:   iload 10
L323:   iadd
L324:   iconst_3
L325:   iand
L326:   invokespecial Method CRRWDRTI a (ILNYFUGYQS;LFTPNODIB;IIIIZI)V
L329:   iload 28
L331:   ifeq L65
L334:   iload 28
L336:   ifeq L43
L339:   return
L340:   astore 12
L342:   new java/lang/StringBuffer
L345:   dup
L346:   ldc "1483, "
L348:   invokespecial Method java/lang/StringBuffer <init> (Ljava/lang/String;)V
L351:   aload_1
L352:   invokevirtual Method java/lang/StringBuffer append (Ljava/lang/Object;)Ljava/lang/StringBuffer;
L355:   ldc ", "
L357:   invokevirtual Method java/lang/StringBuffer append (Ljava/lang/String;)Ljava/lang/StringBuffer;
L360:   aload_2
L361:   invokevirtual Method java/lang/StringBuffer append (Ljava/lang/Object;)Ljava/lang/StringBuffer;
L364:   ldc ", "
L366:   invokevirtual Method java/lang/StringBuffer append (Ljava/lang/String;)Ljava/lang/StringBuffer;
L369:   iload_3
L370:   invokevirtual Method java/lang/StringBuffer append (I)Ljava/lang/StringBuffer;
L373:   ldc ", "
L375:   invokevirtual Method java/lang/StringBuffer append (Ljava/lang/String;)Ljava/lang/StringBuffer;
L378:   iload 4
L380:   invokevirtual Method java/lang/StringBuffer append (I)Ljava/lang/StringBuffer;
L383:   ldc ", "
L385:   invokevirtual Method java/lang/StringBuffer append (Ljava/lang/String;)Ljava/lang/StringBuffer;
L388:   iload 5
L390:   invokevirtual Method java/lang/StringBuffer append (I)Ljava/lang/StringBuffer;
L393:   ldc ", "
L395:   invokevirtual Method java/lang/StringBuffer append (Ljava/lang/String;)Ljava/lang/StringBuffer;
L398:   iload 6
L400:   invokevirtual Method java/lang/StringBuffer append (Z)Ljava/lang/StringBuffer;
L403:   ldc ", "
L405:   invokevirtual Method java/lang/StringBuffer append (Ljava/lang/String;)Ljava/lang/StringBuffer;
L408:   iload 7
L410:   invokevirtual Method java/lang/StringBuffer append (I)Ljava/lang/StringBuffer;
L413:   ldc ", "
L415:   invokevirtual Method java/lang/StringBuffer append (Ljava/lang/String;)Ljava/lang/StringBuffer;
L418:   aload 8
L420:   invokevirtual Method java/lang/StringBuffer append (Ljava/lang/Object;)Ljava/lang/StringBuffer;
L423:   ldc ", "
L425:   invokevirtual Method java/lang/StringBuffer append (Ljava/lang/String;)Ljava/lang/StringBuffer;
L428:   iload 9
L430:   invokevirtual Method java/lang/StringBuffer append (I)Ljava/lang/StringBuffer;
L433:   ldc ", "
L435:   invokevirtual Method java/lang/StringBuffer append (Ljava/lang/String;)Ljava/lang/StringBuffer;
L438:   iload 10
L440:   invokevirtual Method java/lang/StringBuffer append (I)Ljava/lang/StringBuffer;
L443:   ldc ", "
L445:   invokevirtual Method java/lang/StringBuffer append (Ljava/lang/String;)Ljava/lang/StringBuffer;
L448:   iload 11
L450:   invokevirtual Method java/lang/StringBuffer append (I)Ljava/lang/StringBuffer;
L453:   ldc ", "
L455:   invokevirtual Method java/lang/StringBuffer append (Ljava/lang/String;)Ljava/lang/StringBuffer;
L458:   aload 12
L460:   invokevirtual Method java/lang/Throwable toString ()Ljava/lang/String;
L463:   invokevirtual Method java/lang/StringBuffer append (Ljava/lang/String;)Ljava/lang/StringBuffer;
L466:   invokevirtual Method java/lang/StringBuffer toString ()Ljava/lang/String;
L469:   invokestatic Method sign/signlink reporterror (Ljava/lang/String;)V
L472:   new java/lang/RuntimeException
L475:   dup
L476:   invokespecial Method java/lang/RuntimeException <init> ()V
L479:   athrow
L480:   
    .end code
.end method

.method private static final b : (IIII)I
    .code stack 4 locals 5
L0:     ldc 65536
L2:     getstatic Field OPPOFIOL K [I
L5:     iload_2
L6:     sipush 1024
L9:     imul
L10:    iload_3
L11:    idiv
L12:    iaload
L13:    isub
L14:    iconst_1
L15:    ishr
L16:    istore 4
L18:    iload_0
L19:    ldc 65536
L21:    iload 4
L23:    isub
L24:    imul
L25:    bipush 16
L27:    ishr
L28:    iload_1
L29:    iload 4
L31:    imul
L32:    bipush 16
L34:    ishr
L35:    iadd
L36:    ireturn
L37:    
    .end code
.end method

.method private final c : (II)I
    .code stack 4 locals 4
L0:     getstatic Field client Jj I
L3:     istore_3
L4:     iload_1
L5:     bipush -2
L7:     if_icmpne L13
L10:    ldc 12345678
L12:    ireturn
L13:    iload_1
L14:    iconst_m1
L15:    if_icmpne L44
L18:    iload_2
L19:    ifge L28
L22:    iconst_0
L23:    istore_2
L24:    iload_3
L25:    ifeq L37
L28:    iload_2
L29:    bipush 127
L31:    if_icmple L37
L34:    bipush 127
L36:    istore_2
L37:    bipush 127
L39:    iload_2
L40:    isub
L41:    istore_2
L42:    iload_2
L43:    ireturn
L44:    iload_2
L45:    iload_1
L46:    bipush 127
L48:    iand
L49:    imul
L50:    sipush 128
L53:    idiv
L54:    istore_2
L55:    iload_2
L56:    iconst_2
L57:    if_icmpge L66
L60:    iconst_2
L61:    istore_2
L62:    iload_3
L63:    ifeq L75
L66:    iload_2
L67:    bipush 126
L69:    if_icmple L75
L72:    bipush 126
L74:    istore_2
L75:    iload_1
L76:    ldc 65408
L78:    iand
L79:    iload_2
L80:    iadd
L81:    ireturn
L82:    
    .end code
.end method

.method private static final d : (II)I
    .code stack 4 locals 5
L0:     iload_0
L1:     iconst_1
L2:     isub
L3:     iload_1
L4:     iconst_1
L5:     isub
L6:     invokestatic Method CRRWDRTI a (II)I
L9:     iload_0
L10:    iconst_1
L11:    iadd
L12:    iload_1
L13:    iconst_1
L14:    isub
L15:    invokestatic Method CRRWDRTI a (II)I
L18:    iadd
L19:    iload_0
L20:    iconst_1
L21:    isub
L22:    iload_1
L23:    iconst_1
L24:    iadd
L25:    invokestatic Method CRRWDRTI a (II)I
L28:    iadd
L29:    iload_0
L30:    iconst_1
L31:    iadd
L32:    iload_1
L33:    iconst_1
L34:    iadd
L35:    invokestatic Method CRRWDRTI a (II)I
L38:    iadd
L39:    istore_2
L40:    iload_0
L41:    iconst_1
L42:    isub
L43:    iload_1
L44:    invokestatic Method CRRWDRTI a (II)I
L47:    iload_0
L48:    iconst_1
L49:    iadd
L50:    iload_1
L51:    invokestatic Method CRRWDRTI a (II)I
L54:    iadd
L55:    iload_0
L56:    iload_1
L57:    iconst_1
L58:    isub
L59:    invokestatic Method CRRWDRTI a (II)I
L62:    iadd
L63:    iload_0
L64:    iload_1
L65:    iconst_1
L66:    iadd
L67:    invokestatic Method CRRWDRTI a (II)I
L70:    iadd
L71:    istore_3
L72:    iload_0
L73:    iload_1
L74:    invokestatic Method CRRWDRTI a (II)I
L77:    istore 4
L79:    iload_2
L80:    bipush 16
L82:    idiv
L83:    iload_3
L84:    bipush 8
L86:    idiv
L87:    iadd
L88:    iload 4
L90:    iconst_4
L91:    idiv
L92:    iadd
L93:    ireturn
L94:    
    .end code
.end method

.method private static final e : (II)I
    .code stack 4 locals 2
L0:     iload_0
L1:     iconst_m1
L2:     if_icmpne L8
L5:     ldc 12345678
L7:     ireturn
L8:     iload_1
L9:     iload_0
L10:    bipush 127
L12:    iand
L13:    imul
L14:    sipush 128
L17:    idiv
L18:    istore_1
L19:    iload_1
L20:    iconst_2
L21:    if_icmpge L32
L24:    iconst_2
L25:    istore_1
L26:    getstatic Field client Jj I
L29:    ifeq L41
L32:    iload_1
L33:    bipush 126
L35:    if_icmple L41
L38:    bipush 126
L40:    istore_1
L41:    iload_0
L42:    ldc 65408
L44:    iand
L45:    iload_1
L46:    iadd
L47:    ireturn
L48:    
    .end code
.end method

.method public static final a : (LNYFUGYQS;IIIILFTPNODIB;[[[IIIIB)V
    .code stack 15 locals 24
L0:     getstatic Field client Jj I
L3:     istore 23
        .catch java/lang/RuntimeException from L5 to L1965 using L1965
L5:     aload 6
L7:     iload 4
L9:     aaload
L10:    iload 7
L12:    aaload
L13:    iload_2
L14:    iaload
L15:    istore 11
L17:    aload 6
L19:    iload 4
L21:    aaload
L22:    iload 7
L24:    iconst_1
L25:    iadd
L26:    aaload
L27:    iload_2
L28:    iaload
L29:    istore 12
L31:    aload 6
L33:    iload 4
L35:    aaload
L36:    iload 7
L38:    iconst_1
L39:    iadd
L40:    aaload
L41:    iload_2
L42:    iconst_1
L43:    iadd
L44:    iaload
L45:    istore 13
L47:    aload 6
L49:    iload 4
L51:    aaload
L52:    iload 7
L54:    aaload
L55:    iload_2
L56:    iconst_1
L57:    iadd
L58:    iaload
L59:    istore 14
L61:    iload 10
L63:    bipush 93
L65:    if_icmpeq L74
L68:    sipush -145
L71:    putstatic Field CRRWDRTI E I
L74:    iload 11
L76:    iload 12
L78:    iadd
L79:    iload 13
L81:    iadd
L82:    iload 14
L84:    iadd
L85:    iconst_2
L86:    ishr
L87:    istore 15
L89:    iload 8
L91:    invokestatic Method YZDBYLRM a (I)LYZDBYLRM;
L94:    astore 16
L96:    iload 7
L98:    iload_2
L99:    bipush 7
L101:   ishl
L102:   iadd
L103:   iload 8
L105:   bipush 14
L107:   ishl
L108:   iadd
L109:   ldc 1073741824
L111:   iadd
L112:   istore 17
L114:   aload 16
L116:   getfield Field YZDBYLRM Q Z
L119:   ifne L129
L122:   iload 17
L124:   ldc -2147483648
L126:   iadd
L127:   istore 17
L129:   iload_1
L130:   bipush 6
L132:   ishl
L133:   iload_3
L134:   iadd
L135:   i2b
L136:   istore 18
L138:   iload_3
L139:   bipush 22
L141:   if_icmpne L260
L144:   aload 16
L146:   getfield Field YZDBYLRM T I
L149:   iconst_m1
L150:   if_icmpne L185
L153:   aload 16
L155:   getfield Field YZDBYLRM x [I
L158:   ifnonnull L185
L161:   aload 16
L163:   bipush 22
L165:   iload_1
L166:   iload 11
L168:   iload 12
L170:   iload 13
L172:   iload 14
L174:   iconst_m1
L175:   invokevirtual Method YZDBYLRM a (IIIIIII)LZKARKDQW;
L178:   astore 19
L180:   iload 23
L182:   ifeq L215
L185:   new WBWOBAFW
L188:   dup
L189:   iload 8
L191:   iload_1
L192:   bipush 22
L194:   iload 12
L196:   bipush 7
L198:   iload 13
L200:   iload 11
L202:   iload 14
L204:   aload 16
L206:   getfield Field YZDBYLRM T I
L209:   iconst_1
L210:   invokespecial Method WBWOBAFW <init> (IIIIBIIIIZ)V
L213:   astore 19
L215:   aload_0
L216:   iload 9
L218:   iload 15
L220:   iload_2
L221:   bipush 68
L223:   aload 19
L225:   iload 18
L227:   iload 17
L229:   iload 7
L231:   invokevirtual Method NYFUGYQS a (IIIILXHHRODPC;BII)V
L234:   aload 16
L236:   getfield Field YZDBYLRM F Z
L239:   ifeq L259
L242:   aload 16
L244:   getfield Field YZDBYLRM Q Z
L247:   ifeq L259
L250:   aload 5
L252:   iload_2
L253:   iconst_0
L254:   iload 7
L256:   invokevirtual Method FTPNODIB a (III)V
L259:   return
L260:   iload_3
L261:   bipush 10
L263:   if_icmpeq L272
L266:   iload_3
L267:   bipush 11
L269:   if_icmpne L468
L272:   aload 16
L274:   getfield Field YZDBYLRM T I
L277:   iconst_m1
L278:   if_icmpne L313
L281:   aload 16
L283:   getfield Field YZDBYLRM x [I
L286:   ifnonnull L313
L289:   aload 16
L291:   bipush 10
L293:   iload_1
L294:   iload 11
L296:   iload 12
L298:   iload 13
L300:   iload 14
L302:   iconst_m1
L303:   invokevirtual Method YZDBYLRM a (IIIIIII)LZKARKDQW;
L306:   astore 19
L308:   iload 23
L310:   ifeq L343
L313:   new WBWOBAFW
L316:   dup
L317:   iload 8
L319:   iload_1
L320:   bipush 10
L322:   iload 12
L324:   bipush 7
L326:   iload 13
L328:   iload 11
L330:   iload 14
L332:   aload 16
L334:   getfield Field YZDBYLRM T I
L337:   iconst_1
L338:   invokespecial Method WBWOBAFW <init> (IIIIBIIIIZ)V
L341:   astore 19
L343:   aload 19
L345:   ifnull L432
L348:   iconst_0
L349:   istore 22
L351:   iload_3
L352:   bipush 11
L354:   if_icmpne L363
L357:   wide iinc 22 256
L363:   iload_1
L364:   iconst_1
L365:   if_icmpeq L373
L368:   iload_1
L369:   iconst_3
L370:   if_icmpne L392
L373:   aload 16
L375:   getfield Field YZDBYLRM z I
L378:   istore 20
L380:   aload 16
L382:   getfield Field YZDBYLRM i I
L385:   istore 21
L387:   iload 23
L389:   ifeq L406
L392:   aload 16
L394:   getfield Field YZDBYLRM i I
L397:   istore 20
L399:   aload 16
L401:   getfield Field YZDBYLRM z I
L404:   istore 21
L406:   aload_0
L407:   iload 17
L409:   iload 18
L411:   iload 15
L413:   iload 21
L415:   aload 19
L417:   iload 20
L419:   iload 9
L421:   iload 22
L423:   bipush 110
L425:   iload_2
L426:   iload 7
L428:   invokevirtual Method NYFUGYQS a (IBIILXHHRODPC;IIIBII)Z
L431:   pop
L432:   aload 16
L434:   getfield Field YZDBYLRM F Z
L437:   ifeq L467
L440:   aload 5
L442:   aload 16
L444:   getfield Field YZDBYLRM v Z
L447:   getstatic Field CRRWDRTI p I
L450:   aload 16
L452:   getfield Field YZDBYLRM i I
L455:   aload 16
L457:   getfield Field YZDBYLRM z I
L460:   iload 7
L462:   iload_2
L463:   iload_1
L464:   invokevirtual Method FTPNODIB a (ZIIIIII)V
L467:   return
L468:   iload_3
L469:   bipush 12
L471:   if_icmplt L602
L474:   aload 16
L476:   getfield Field YZDBYLRM T I
L479:   iconst_m1
L480:   if_icmpne L514
L483:   aload 16
L485:   getfield Field YZDBYLRM x [I
L488:   ifnonnull L514
L491:   aload 16
L493:   iload_3
L494:   iload_1
L495:   iload 11
L497:   iload 12
L499:   iload 13
L501:   iload 14
L503:   iconst_m1
L504:   invokevirtual Method YZDBYLRM a (IIIIIII)LZKARKDQW;
L507:   astore 19
L509:   iload 23
L511:   ifeq L543
L514:   new WBWOBAFW
L517:   dup
L518:   iload 8
L520:   iload_1
L521:   iload_3
L522:   iload 12
L524:   bipush 7
L526:   iload 13
L528:   iload 11
L530:   iload 14
L532:   aload 16
L534:   getfield Field YZDBYLRM T I
L537:   iconst_1
L538:   invokespecial Method WBWOBAFW <init> (IIIIBIIIIZ)V
L541:   astore 19
L543:   aload_0
L544:   iload 17
L546:   iload 18
L548:   iload 15
L550:   iconst_1
L551:   aload 19
L553:   iconst_1
L554:   iload 9
L556:   iconst_0
L557:   bipush 110
L559:   iload_2
L560:   iload 7
L562:   invokevirtual Method NYFUGYQS a (IBIILXHHRODPC;IIIBII)Z
L565:   pop
L566:   aload 16
L568:   getfield Field YZDBYLRM F Z
L571:   ifeq L601
L574:   aload 5
L576:   aload 16
L578:   getfield Field YZDBYLRM v Z
L581:   getstatic Field CRRWDRTI p I
L584:   aload 16
L586:   getfield Field YZDBYLRM i I
L589:   aload 16
L591:   getfield Field YZDBYLRM z I
L594:   iload 7
L596:   iload_2
L597:   iload_1
L598:   invokevirtual Method FTPNODIB a (ZIIIIII)V
L601:   return
L602:   iload_3
L603:   ifne L725
L606:   aload 16
L608:   getfield Field YZDBYLRM T I
L611:   iconst_m1
L612:   if_icmpne L646
L615:   aload 16
L617:   getfield Field YZDBYLRM x [I
L620:   ifnonnull L646
L623:   aload 16
L625:   iconst_0
L626:   iload_1
L627:   iload 11
L629:   iload 12
L631:   iload 13
L633:   iload 14
L635:   iconst_m1
L636:   invokevirtual Method YZDBYLRM a (IIIIIII)LZKARKDQW;
L639:   astore 19
L641:   iload 23
L643:   ifeq L675
L646:   new WBWOBAFW
L649:   dup
L650:   iload 8
L652:   iload_1
L653:   iconst_0
L654:   iload 12
L656:   bipush 7
L658:   iload 13
L660:   iload 11
L662:   iload 14
L664:   aload 16
L666:   getfield Field YZDBYLRM T I
L669:   iconst_1
L670:   invokespecial Method WBWOBAFW <init> (IIIIBIIIIZ)V
L673:   astore 19
L675:   aload_0
L676:   getstatic Field CRRWDRTI D [I
L679:   iload_1
L680:   iaload
L681:   aload 19
L683:   iconst_1
L684:   iload 17
L686:   iload_2
L687:   iload 18
L689:   iload 7
L691:   aconst_null
L692:   iload 15
L694:   iconst_0
L695:   iload 9
L697:   invokevirtual Method NYFUGYQS a (ILXHHRODPC;ZIIBILXHHRODPC;III)V
L700:   aload 16
L702:   getfield Field YZDBYLRM F Z
L705:   ifeq L724
L708:   aload 5
L710:   iload_2
L711:   iload_1
L712:   iload 7
L714:   iload_3
L715:   iconst_1
L716:   aload 16
L718:   getfield Field YZDBYLRM v Z
L721:   invokevirtual Method FTPNODIB a (IIIIBZ)V
L724:   return
L725:   iload_3
L726:   iconst_1
L727:   if_icmpne L849
L730:   aload 16
L732:   getfield Field YZDBYLRM T I
L735:   iconst_m1
L736:   if_icmpne L770
L739:   aload 16
L741:   getfield Field YZDBYLRM x [I
L744:   ifnonnull L770
L747:   aload 16
L749:   iconst_1
L750:   iload_1
L751:   iload 11
L753:   iload 12
L755:   iload 13
L757:   iload 14
L759:   iconst_m1
L760:   invokevirtual Method YZDBYLRM a (IIIIIII)LZKARKDQW;
L763:   astore 19
L765:   iload 23
L767:   ifeq L799
L770:   new WBWOBAFW
L773:   dup
L774:   iload 8
L776:   iload_1
L777:   iconst_1
L778:   iload 12
L780:   bipush 7
L782:   iload 13
L784:   iload 11
L786:   iload 14
L788:   aload 16
L790:   getfield Field YZDBYLRM T I
L793:   iconst_1
L794:   invokespecial Method WBWOBAFW <init> (IIIIBIIIIZ)V
L797:   astore 19
L799:   aload_0
L800:   getstatic Field CRRWDRTI r [I
L803:   iload_1
L804:   iaload
L805:   aload 19
L807:   iconst_1
L808:   iload 17
L810:   iload_2
L811:   iload 18
L813:   iload 7
L815:   aconst_null
L816:   iload 15
L818:   iconst_0
L819:   iload 9
L821:   invokevirtual Method NYFUGYQS a (ILXHHRODPC;ZIIBILXHHRODPC;III)V
L824:   aload 16
L826:   getfield Field YZDBYLRM F Z
L829:   ifeq L848
L832:   aload 5
L834:   iload_2
L835:   iload_1
L836:   iload 7
L838:   iload_3
L839:   iconst_1
L840:   aload 16
L842:   getfield Field YZDBYLRM v Z
L845:   invokevirtual Method FTPNODIB a (IIIIBZ)V
L848:   return
L849:   iload_3
L850:   iconst_2
L851:   if_icmpne L1039
L854:   iload_1
L855:   iconst_1
L856:   iadd
L857:   iconst_3
L858:   iand
L859:   istore 19
L861:   aload 16
L863:   getfield Field YZDBYLRM T I
L866:   iconst_m1
L867:   if_icmpne L922
L870:   aload 16
L872:   getfield Field YZDBYLRM x [I
L875:   ifnonnull L922
L878:   aload 16
L880:   iconst_2
L881:   iconst_4
L882:   iload_1
L883:   iadd
L884:   iload 11
L886:   iload 12
L888:   iload 13
L890:   iload 14
L892:   iconst_m1
L893:   invokevirtual Method YZDBYLRM a (IIIIIII)LZKARKDQW;
L896:   astore 20
L898:   aload 16
L900:   iconst_2
L901:   iload 19
L903:   iload 11
L905:   iload 12
L907:   iload 13
L909:   iload 14
L911:   iconst_m1
L912:   invokevirtual Method YZDBYLRM a (IIIIIII)LZKARKDQW;
L915:   astore 21
L917:   iload 23
L919:   ifeq L983
L922:   new WBWOBAFW
L925:   dup
L926:   iload 8
L928:   iconst_4
L929:   iload_1
L930:   iadd
L931:   iconst_2
L932:   iload 12
L934:   bipush 7
L936:   iload 13
L938:   iload 11
L940:   iload 14
L942:   aload 16
L944:   getfield Field YZDBYLRM T I
L947:   iconst_1
L948:   invokespecial Method WBWOBAFW <init> (IIIIBIIIIZ)V
L951:   astore 20
L953:   new WBWOBAFW
L956:   dup
L957:   iload 8
L959:   iload 19
L961:   iconst_2
L962:   iload 12
L964:   bipush 7
L966:   iload 13
L968:   iload 11
L970:   iload 14
L972:   aload 16
L974:   getfield Field YZDBYLRM T I
L977:   iconst_1
L978:   invokespecial Method WBWOBAFW <init> (IIIIBIIIIZ)V
L981:   astore 21
L983:   aload_0
L984:   getstatic Field CRRWDRTI D [I
L987:   iload_1
L988:   iaload
L989:   aload 20
L991:   iconst_1
L992:   iload 17
L994:   iload_2
L995:   iload 18
L997:   iload 7
L999:   aload 21
L1001:  iload 15
L1003:  getstatic Field CRRWDRTI D [I
L1006:  iload 19
L1008:  iaload
L1009:  iload 9
L1011:  invokevirtual Method NYFUGYQS a (ILXHHRODPC;ZIIBILXHHRODPC;III)V
L1014:  aload 16
L1016:  getfield Field YZDBYLRM F Z
L1019:  ifeq L1038
L1022:  aload 5
L1024:  iload_2
L1025:  iload_1
L1026:  iload 7
L1028:  iload_3
L1029:  iconst_1
L1030:  aload 16
L1032:  getfield Field YZDBYLRM v Z
L1035:  invokevirtual Method FTPNODIB a (IIIIBZ)V
L1038:  return
L1039:  iload_3
L1040:  iconst_3
L1041:  if_icmpne L1163
L1044:  aload 16
L1046:  getfield Field YZDBYLRM T I
L1049:  iconst_m1
L1050:  if_icmpne L1084
L1053:  aload 16
L1055:  getfield Field YZDBYLRM x [I
L1058:  ifnonnull L1084
L1061:  aload 16
L1063:  iconst_3
L1064:  iload_1
L1065:  iload 11
L1067:  iload 12
L1069:  iload 13
L1071:  iload 14
L1073:  iconst_m1
L1074:  invokevirtual Method YZDBYLRM a (IIIIIII)LZKARKDQW;
L1077:  astore 19
L1079:  iload 23
L1081:  ifeq L1113
L1084:  new WBWOBAFW
L1087:  dup
L1088:  iload 8
L1090:  iload_1
L1091:  iconst_3
L1092:  iload 12
L1094:  bipush 7
L1096:  iload 13
L1098:  iload 11
L1100:  iload 14
L1102:  aload 16
L1104:  getfield Field YZDBYLRM T I
L1107:  iconst_1
L1108:  invokespecial Method WBWOBAFW <init> (IIIIBIIIIZ)V
L1111:  astore 19
L1113:  aload_0
L1114:  getstatic Field CRRWDRTI r [I
L1117:  iload_1
L1118:  iaload
L1119:  aload 19
L1121:  iconst_1
L1122:  iload 17
L1124:  iload_2
L1125:  iload 18
L1127:  iload 7
L1129:  aconst_null
L1130:  iload 15
L1132:  iconst_0
L1133:  iload 9
L1135:  invokevirtual Method NYFUGYQS a (ILXHHRODPC;ZIIBILXHHRODPC;III)V
L1138:  aload 16
L1140:  getfield Field YZDBYLRM F Z
L1143:  ifeq L1162
L1146:  aload 5
L1148:  iload_2
L1149:  iload_1
L1150:  iload 7
L1152:  iload_3
L1153:  iconst_1
L1154:  aload 16
L1156:  getfield Field YZDBYLRM v Z
L1159:  invokevirtual Method FTPNODIB a (IIIIBZ)V
L1162:  return
L1163:  iload_3
L1164:  bipush 9
L1166:  if_icmpne L1297
L1169:  aload 16
L1171:  getfield Field YZDBYLRM T I
L1174:  iconst_m1
L1175:  if_icmpne L1209
L1178:  aload 16
L1180:  getfield Field YZDBYLRM x [I
L1183:  ifnonnull L1209
L1186:  aload 16
L1188:  iload_3
L1189:  iload_1
L1190:  iload 11
L1192:  iload 12
L1194:  iload 13
L1196:  iload 14
L1198:  iconst_m1
L1199:  invokevirtual Method YZDBYLRM a (IIIIIII)LZKARKDQW;
L1202:  astore 19
L1204:  iload 23
L1206:  ifeq L1238
L1209:  new WBWOBAFW
L1212:  dup
L1213:  iload 8
L1215:  iload_1
L1216:  iload_3
L1217:  iload 12
L1219:  bipush 7
L1221:  iload 13
L1223:  iload 11
L1225:  iload 14
L1227:  aload 16
L1229:  getfield Field YZDBYLRM T I
L1232:  iconst_1
L1233:  invokespecial Method WBWOBAFW <init> (IIIIBIIIIZ)V
L1236:  astore 19
L1238:  aload_0
L1239:  iload 17
L1241:  iload 18
L1243:  iload 15
L1245:  iconst_1
L1246:  aload 19
L1248:  iconst_1
L1249:  iload 9
L1251:  iconst_0
L1252:  bipush 110
L1254:  iload_2
L1255:  iload 7
L1257:  invokevirtual Method NYFUGYQS a (IBIILXHHRODPC;IIIBII)Z
L1260:  pop
L1261:  aload 16
L1263:  getfield Field YZDBYLRM F Z
L1266:  ifeq L1296
L1269:  aload 5
L1271:  aload 16
L1273:  getfield Field YZDBYLRM v Z
L1276:  getstatic Field CRRWDRTI p I
L1279:  aload 16
L1281:  getfield Field YZDBYLRM i I
L1284:  aload 16
L1286:  getfield Field YZDBYLRM z I
L1289:  iload 7
L1291:  iload_2
L1292:  iload_1
L1293:  invokevirtual Method FTPNODIB a (ZIIIIII)V
L1296:  return
L1297:  aload 16
L1299:  getfield Field YZDBYLRM A Z
L1302:  ifeq L1394
L1305:  iload_1
L1306:  iconst_1
L1307:  if_icmpne L1335
L1310:  iload 14
L1312:  istore 19
L1314:  iload 13
L1316:  istore 14
L1318:  iload 12
L1320:  istore 13
L1322:  iload 11
L1324:  istore 12
L1326:  iload 19
L1328:  istore 11
L1330:  iload 23
L1332:  ifeq L1394
L1335:  iload_1
L1336:  iconst_2
L1337:  if_icmpne L1369
L1340:  iload 14
L1342:  istore 19
L1344:  iload 12
L1346:  istore 14
L1348:  iload 19
L1350:  istore 12
L1352:  iload 13
L1354:  istore 19
L1356:  iload 11
L1358:  istore 13
L1360:  iload 19
L1362:  istore 11
L1364:  iload 23
L1366:  ifeq L1394
L1369:  iload_1
L1370:  iconst_3
L1371:  if_icmpne L1394
L1374:  iload 14
L1376:  istore 19
L1378:  iload 11
L1380:  istore 14
L1382:  iload 12
L1384:  istore 11
L1386:  iload 13
L1388:  istore 12
L1390:  iload 19
L1392:  istore 13
L1394:  iload_3
L1395:  iconst_4
L1396:  if_icmpne L1501
L1399:  aload 16
L1401:  getfield Field YZDBYLRM T I
L1404:  iconst_m1
L1405:  if_icmpne L1439
L1408:  aload 16
L1410:  getfield Field YZDBYLRM x [I
L1413:  ifnonnull L1439
L1416:  aload 16
L1418:  iconst_4
L1419:  iconst_0
L1420:  iload 11
L1422:  iload 12
L1424:  iload 13
L1426:  iload 14
L1428:  iconst_m1
L1429:  invokevirtual Method YZDBYLRM a (IIIIIII)LZKARKDQW;
L1432:  astore 19
L1434:  iload 23
L1436:  ifeq L1468
L1439:  new WBWOBAFW
L1442:  dup
L1443:  iload 8
L1445:  iconst_0
L1446:  iconst_4
L1447:  iload 12
L1449:  bipush 7
L1451:  iload 13
L1453:  iload 11
L1455:  iload 14
L1457:  aload 16
L1459:  getfield Field YZDBYLRM T I
L1462:  iconst_1
L1463:  invokespecial Method WBWOBAFW <init> (IIIIBIIIIZ)V
L1466:  astore 19
L1468:  aload_0
L1469:  iload 17
L1471:  iload_2
L1472:  iload_1
L1473:  sipush 512
L1476:  imul
L1477:  sipush -460
L1480:  iload 9
L1482:  iconst_0
L1483:  iload 15
L1485:  aload 19
L1487:  iload 7
L1489:  iload 18
L1491:  iconst_0
L1492:  getstatic Field CRRWDRTI D [I
L1495:  iload_1
L1496:  iaload
L1497:  invokevirtual Method NYFUGYQS a (IIIIIIILXHHRODPC;IBII)V
L1500:  return
L1501:  iload_3
L1502:  iconst_5
L1503:  if_icmpne L1659
L1506:  bipush 16
L1508:  istore 19
L1510:  aload_0
L1511:  iload 9
L1513:  iload 7
L1515:  iload_2
L1516:  invokevirtual Method NYFUGYQS c (III)I
L1519:  istore 20
L1521:  iload 20
L1523:  ifle L1543
L1526:  iload 20
L1528:  bipush 14
L1530:  ishr
L1531:  sipush 32767
L1534:  iand
L1535:  invokestatic Method YZDBYLRM a (I)LYZDBYLRM;
L1538:  getfield Field YZDBYLRM N I
L1541:  istore 19
L1543:  aload 16
L1545:  getfield Field YZDBYLRM T I
L1548:  iconst_m1
L1549:  if_icmpne L1583
L1552:  aload 16
L1554:  getfield Field YZDBYLRM x [I
L1557:  ifnonnull L1583
L1560:  aload 16
L1562:  iconst_4
L1563:  iconst_0
L1564:  iload 11
L1566:  iload 12
L1568:  iload 13
L1570:  iload 14
L1572:  iconst_m1
L1573:  invokevirtual Method YZDBYLRM a (IIIIIII)LZKARKDQW;
L1576:  astore 21
L1578:  iload 23
L1580:  ifeq L1612
L1583:  new WBWOBAFW
L1586:  dup
L1587:  iload 8
L1589:  iconst_0
L1590:  iconst_4
L1591:  iload 12
L1593:  bipush 7
L1595:  iload 13
L1597:  iload 11
L1599:  iload 14
L1601:  aload 16
L1603:  getfield Field YZDBYLRM T I
L1606:  iconst_1
L1607:  invokespecial Method WBWOBAFW <init> (IIIIBIIIIZ)V
L1610:  astore 21
L1612:  aload_0
L1613:  iload 17
L1615:  iload_2
L1616:  iload_1
L1617:  sipush 512
L1620:  imul
L1621:  sipush -460
L1624:  iload 9
L1626:  getstatic Field CRRWDRTI o [I
L1629:  iload_1
L1630:  iaload
L1631:  iload 19
L1633:  imul
L1634:  iload 15
L1636:  aload 21
L1638:  iload 7
L1640:  iload 18
L1642:  getstatic Field CRRWDRTI v [I
L1645:  iload_1
L1646:  iaload
L1647:  iload 19
L1649:  imul
L1650:  getstatic Field CRRWDRTI D [I
L1653:  iload_1
L1654:  iaload
L1655:  invokevirtual Method NYFUGYQS a (IIIIIIILXHHRODPC;IBII)V
L1658:  return
L1659:  iload_3
L1660:  bipush 6
L1662:  if_icmpne L1761
L1665:  aload 16
L1667:  getfield Field YZDBYLRM T I
L1670:  iconst_m1
L1671:  if_icmpne L1705
L1674:  aload 16
L1676:  getfield Field YZDBYLRM x [I
L1679:  ifnonnull L1705
L1682:  aload 16
L1684:  iconst_4
L1685:  iconst_0
L1686:  iload 11
L1688:  iload 12
L1690:  iload 13
L1692:  iload 14
L1694:  iconst_m1
L1695:  invokevirtual Method YZDBYLRM a (IIIIIII)LZKARKDQW;
L1698:  astore 19
L1700:  iload 23
L1702:  ifeq L1734
L1705:  new WBWOBAFW
L1708:  dup
L1709:  iload 8
L1711:  iconst_0
L1712:  iconst_4
L1713:  iload 12
L1715:  bipush 7
L1717:  iload 13
L1719:  iload 11
L1721:  iload 14
L1723:  aload 16
L1725:  getfield Field YZDBYLRM T I
L1728:  iconst_1
L1729:  invokespecial Method WBWOBAFW <init> (IIIIBIIIIZ)V
L1732:  astore 19
L1734:  aload_0
L1735:  iload 17
L1737:  iload_2
L1738:  iload_1
L1739:  sipush -460
L1742:  iload 9
L1744:  iconst_0
L1745:  iload 15
L1747:  aload 19
L1749:  iload 7
L1751:  iload 18
L1753:  iconst_0
L1754:  sipush 256
L1757:  invokevirtual Method NYFUGYQS a (IIIIIIILXHHRODPC;IBII)V
L1760:  return
L1761:  iload_3
L1762:  bipush 7
L1764:  if_icmpne L1863
L1767:  aload 16
L1769:  getfield Field YZDBYLRM T I
L1772:  iconst_m1
L1773:  if_icmpne L1807
L1776:  aload 16
L1778:  getfield Field YZDBYLRM x [I
L1781:  ifnonnull L1807
L1784:  aload 16
L1786:  iconst_4
L1787:  iconst_0
L1788:  iload 11
L1790:  iload 12
L1792:  iload 13
L1794:  iload 14
L1796:  iconst_m1
L1797:  invokevirtual Method YZDBYLRM a (IIIIIII)LZKARKDQW;
L1800:  astore 19
L1802:  iload 23
L1804:  ifeq L1836
L1807:  new WBWOBAFW
L1810:  dup
L1811:  iload 8
L1813:  iconst_0
L1814:  iconst_4
L1815:  iload 12
L1817:  bipush 7
L1819:  iload 13
L1821:  iload 11
L1823:  iload 14
L1825:  aload 16
L1827:  getfield Field YZDBYLRM T I
L1830:  iconst_1
L1831:  invokespecial Method WBWOBAFW <init> (IIIIBIIIIZ)V
L1834:  astore 19
L1836:  aload_0
L1837:  iload 17
L1839:  iload_2
L1840:  iload_1
L1841:  sipush -460
L1844:  iload 9
L1846:  iconst_0
L1847:  iload 15
L1849:  aload 19
L1851:  iload 7
L1853:  iload 18
L1855:  iconst_0
L1856:  sipush 512
L1859:  invokevirtual Method NYFUGYQS a (IIIIIIILXHHRODPC;IBII)V
L1862:  return
L1863:  iload_3
L1864:  bipush 8
L1866:  if_icmpne L2104
L1869:  aload 16
L1871:  getfield Field YZDBYLRM T I
L1874:  iconst_m1
L1875:  if_icmpne L1909
L1878:  aload 16
L1880:  getfield Field YZDBYLRM x [I
L1883:  ifnonnull L1909
L1886:  aload 16
L1888:  iconst_4
L1889:  iconst_0
L1890:  iload 11
L1892:  iload 12
L1894:  iload 13
L1896:  iload 14
L1898:  iconst_m1
L1899:  invokevirtual Method YZDBYLRM a (IIIIIII)LZKARKDQW;
L1902:  astore 19
L1904:  iload 23
L1906:  ifeq L1938
L1909:  new WBWOBAFW
L1912:  dup
L1913:  iload 8
L1915:  iconst_0
L1916:  iconst_4
L1917:  iload 12
L1919:  bipush 7
L1921:  iload 13
L1923:  iload 11
L1925:  iload 14
L1927:  aload 16
L1929:  getfield Field YZDBYLRM T I
L1932:  iconst_1
L1933:  invokespecial Method WBWOBAFW <init> (IIIIBIIIIZ)V
L1936:  astore 19
L1938:  aload_0
L1939:  iload 17
L1941:  iload_2
L1942:  iload_1
L1943:  sipush -460
L1946:  iload 9
L1948:  iconst_0
L1949:  iload 15
L1951:  aload 19
L1953:  iload 7
L1955:  iload 18
L1957:  iconst_0
L1958:  sipush 768
L1961:  invokevirtual Method NYFUGYQS a (IIIIIIILXHHRODPC;IBII)V
L1964:  return
L1965:  astore 11
L1967:  new java/lang/StringBuffer
L1970:  dup
L1971:  ldc "89985, "
L1973:  invokespecial Method java/lang/StringBuffer <init> (Ljava/lang/String;)V
L1976:  aload_0
L1977:  invokevirtual Method java/lang/StringBuffer append (Ljava/lang/Object;)Ljava/lang/StringBuffer;
L1980:  ldc ", "
L1982:  invokevirtual Method java/lang/StringBuffer append (Ljava/lang/String;)Ljava/lang/StringBuffer;
L1985:  iload_1
L1986:  invokevirtual Method java/lang/StringBuffer append (I)Ljava/lang/StringBuffer;
L1989:  ldc ", "
L1991:  invokevirtual Method java/lang/StringBuffer append (Ljava/lang/String;)Ljava/lang/StringBuffer;
L1994:  iload_2
L1995:  invokevirtual Method java/lang/StringBuffer append (I)Ljava/lang/StringBuffer;
L1998:  ldc ", "
L2000:  invokevirtual Method java/lang/StringBuffer append (Ljava/lang/String;)Ljava/lang/StringBuffer;
L2003:  iload_3
L2004:  invokevirtual Method java/lang/StringBuffer append (I)Ljava/lang/StringBuffer;
L2007:  ldc ", "
L2009:  invokevirtual Method java/lang/StringBuffer append (Ljava/lang/String;)Ljava/lang/StringBuffer;
L2012:  iload 4
L2014:  invokevirtual Method java/lang/StringBuffer append (I)Ljava/lang/StringBuffer;
L2017:  ldc ", "
L2019:  invokevirtual Method java/lang/StringBuffer append (Ljava/lang/String;)Ljava/lang/StringBuffer;
L2022:  aload 5
L2024:  invokevirtual Method java/lang/StringBuffer append (Ljava/lang/Object;)Ljava/lang/StringBuffer;
L2027:  ldc ", "
L2029:  invokevirtual Method java/lang/StringBuffer append (Ljava/lang/String;)Ljava/lang/StringBuffer;
L2032:  aload 6
L2034:  invokevirtual Method java/lang/StringBuffer append (Ljava/lang/Object;)Ljava/lang/StringBuffer;
L2037:  ldc ", "
L2039:  invokevirtual Method java/lang/StringBuffer append (Ljava/lang/String;)Ljava/lang/StringBuffer;
L2042:  iload 7
L2044:  invokevirtual Method java/lang/StringBuffer append (I)Ljava/lang/StringBuffer;
L2047:  ldc ", "
L2049:  invokevirtual Method java/lang/StringBuffer append (Ljava/lang/String;)Ljava/lang/StringBuffer;
L2052:  iload 8
L2054:  invokevirtual Method java/lang/StringBuffer append (I)Ljava/lang/StringBuffer;
L2057:  ldc ", "
L2059:  invokevirtual Method java/lang/StringBuffer append (Ljava/lang/String;)Ljava/lang/StringBuffer;
L2062:  iload 9
L2064:  invokevirtual Method java/lang/StringBuffer append (I)Ljava/lang/StringBuffer;
L2067:  ldc ", "
L2069:  invokevirtual Method java/lang/StringBuffer append (Ljava/lang/String;)Ljava/lang/StringBuffer;
L2072:  iload 10
L2074:  invokevirtual Method java/lang/StringBuffer append (I)Ljava/lang/StringBuffer;
L2077:  ldc ", "
L2079:  invokevirtual Method java/lang/StringBuffer append (Ljava/lang/String;)Ljava/lang/StringBuffer;
L2082:  aload 11
L2084:  invokevirtual Method java/lang/Throwable toString ()Ljava/lang/String;
L2087:  invokevirtual Method java/lang/StringBuffer append (Ljava/lang/String;)Ljava/lang/StringBuffer;
L2090:  invokevirtual Method java/lang/StringBuffer toString ()Ljava/lang/String;
L2093:  invokestatic Method sign/signlink reporterror (Ljava/lang/String;)V
L2096:  new java/lang/RuntimeException
L2099:  dup
L2100:  invokespecial Method java/lang/RuntimeException <init> ()V
L2103:  athrow
L2104:  return
L2105:  
    .end code
.end method

.method public static final a : (I[BII)Z
    .code stack 5 locals 18
L0:     getstatic Field client Jj I
L3:     istore 17
        .catch java/lang/RuntimeException from L5 to L243 using L243
L5:     iload_3
L6:     bipush 6
L8:     if_icmplt L17
L11:    iload_3
L12:    bipush 6
L14:    if_icmple L25
L17:    new java/lang/NullPointerException
L20:    dup
L21:    invokespecial Method java/lang/NullPointerException <init> ()V
L24:    athrow
L25:    iconst_1
L26:    istore 4
L28:    new MBMGIXGO
L31:    dup
L32:    aload_1
L33:    sipush 891
L36:    invokespecial Method MBMGIXGO <init> ([BI)V
L39:    astore 5
L41:    iconst_m1
L42:    istore 6
L44:    aload 5
L46:    invokevirtual Method MBMGIXGO k ()I
L49:    istore 7
L51:    iload 7
L53:    ifeq L240
L56:    iload 6
L58:    iload 7
L60:    iadd
L61:    istore 6
L63:    iconst_0
L64:    istore 8
L66:    iconst_0
L67:    istore 9
L69:    iload 9
L71:    ifeq L97
L74:    aload 5
L76:    invokevirtual Method MBMGIXGO k ()I
L79:    istore 10
L81:    iload 10
L83:    ifeq L235
L86:    aload 5
L88:    invokevirtual Method MBMGIXGO c ()I
L91:    pop
L92:    iload 17
L94:    ifeq L69
L97:    aload 5
L99:    invokevirtual Method MBMGIXGO k ()I
L102:   istore 10
L104:   iload 10
L106:   ifeq L235
L109:   iload 8
L111:   iload 10
L113:   iconst_1
L114:   isub
L115:   iadd
L116:   istore 8
L118:   iload 8
L120:   bipush 63
L122:   iand
L123:   istore 11
L125:   iload 8
L127:   bipush 6
L129:   ishr
L130:   bipush 63
L132:   iand
L133:   istore 12
L135:   aload 5
L137:   invokevirtual Method MBMGIXGO c ()I
L140:   iconst_2
L141:   ishr
L142:   istore 13
L144:   iload 12
L146:   iload_0
L147:   iadd
L148:   istore 14
L150:   iload 11
L152:   iload_2
L153:   iadd
L154:   istore 15
L156:   iload 14
L158:   ifle L69
L161:   iload 15
L163:   ifle L69
L166:   iload 14
L168:   bipush 103
L170:   if_icmpge L69
L173:   iload 15
L175:   bipush 103
L177:   if_icmpge L69
L180:   iload 6
L182:   invokestatic Method YZDBYLRM a (I)LYZDBYLRM;
L185:   astore 16
L187:   iload 13
L189:   bipush 22
L191:   if_icmpne L216
L194:   getstatic Field CRRWDRTI C Z
L197:   ifeq L216
L200:   aload 16
L202:   getfield Field YZDBYLRM Q Z
L205:   ifne L216
L208:   aload 16
L210:   getfield Field YZDBYLRM a Z
L213:   ifeq L230
L216:   iload 4
L218:   aload 16
L220:   iconst_1
L221:   invokevirtual Method YZDBYLRM a (Z)Z
L224:   iand
L225:   istore 4
L227:   iconst_1
L228:   istore 9
L230:   iload 17
L232:   ifeq L69
L235:   iload 17
L237:   ifeq L44
L240:   iload 4
L242:   ireturn
L243:   astore 4
L245:   new java/lang/StringBuffer
L248:   dup
L249:   ldc "14134, "
L251:   invokespecial Method java/lang/StringBuffer <init> (Ljava/lang/String;)V
L254:   iload_0
L255:   invokevirtual Method java/lang/StringBuffer append (I)Ljava/lang/StringBuffer;
L258:   ldc ", "
L260:   invokevirtual Method java/lang/StringBuffer append (Ljava/lang/String;)Ljava/lang/StringBuffer;
L263:   aload_1
L264:   invokevirtual Method java/lang/StringBuffer append (Ljava/lang/Object;)Ljava/lang/StringBuffer;
L267:   ldc ", "
L269:   invokevirtual Method java/lang/StringBuffer append (Ljava/lang/String;)Ljava/lang/StringBuffer;
L272:   iload_2
L273:   invokevirtual Method java/lang/StringBuffer append (I)Ljava/lang/StringBuffer;
L276:   ldc ", "
L278:   invokevirtual Method java/lang/StringBuffer append (Ljava/lang/String;)Ljava/lang/StringBuffer;
L281:   iload_3
L282:   invokevirtual Method java/lang/StringBuffer append (I)Ljava/lang/StringBuffer;
L285:   ldc ", "
L287:   invokevirtual Method java/lang/StringBuffer append (Ljava/lang/String;)Ljava/lang/StringBuffer;
L290:   aload 4
L292:   invokevirtual Method java/lang/Throwable toString ()Ljava/lang/String;
L295:   invokevirtual Method java/lang/StringBuffer append (Ljava/lang/String;)Ljava/lang/StringBuffer;
L298:   invokevirtual Method java/lang/StringBuffer toString ()Ljava/lang/String;
L301:   invokestatic Method sign/signlink reporterror (Ljava/lang/String;)V
L304:   new java/lang/RuntimeException
L307:   dup
L308:   invokespecial Method java/lang/RuntimeException <init> ()V
L311:   athrow
L312:   
    .end code
.end method

.method public final a : (I[LFTPNODIB;IILNYFUGYQS;[B)V
    .code stack 11 locals 23
L0:     getstatic Field client Jj I
L3:     istore 22
        .catch java/lang/RuntimeException from L5 to L229 using L230
L5:     iload 4
L7:     bipush 7
L9:     if_icmplt L19
L12:    iload 4
L14:    bipush 7
L16:    if_icmple L20
L19:    return
L20:    new MBMGIXGO
L23:    dup
L24:    aload 6
L26:    sipush 891
L29:    invokespecial Method MBMGIXGO <init> ([BI)V
L32:    astore 7
L34:    iconst_m1
L35:    istore 8
L37:    aload 7
L39:    invokevirtual Method MBMGIXGO k ()I
L42:    istore 9
L44:    iload 9
L46:    ifeq L229
L49:    iload 8
L51:    iload 9
L53:    iadd
L54:    istore 8
L56:    iconst_0
L57:    istore 10
L59:    aload 7
L61:    invokevirtual Method MBMGIXGO k ()I
L64:    istore 11
L66:    iload 11
L68:    ifeq L224
L71:    iload 10
L73:    iload 11
L75:    iconst_1
L76:    isub
L77:    iadd
L78:    istore 10
L80:    iload 10
L82:    bipush 63
L84:    iand
L85:    istore 12
L87:    iload 10
L89:    bipush 6
L91:    ishr
L92:    bipush 63
L94:    iand
L95:    istore 13
L97:    iload 10
L99:    bipush 12
L101:   ishr
L102:   istore 14
L104:   aload 7
L106:   invokevirtual Method MBMGIXGO c ()I
L109:   istore 15
L111:   iload 15
L113:   iconst_2
L114:   ishr
L115:   istore 16
L117:   iload 15
L119:   iconst_3
L120:   iand
L121:   istore 17
L123:   iload 13
L125:   iload_1
L126:   iadd
L127:   istore 18
L129:   iload 12
L131:   iload_3
L132:   iadd
L133:   istore 19
L135:   iload 18
L137:   ifle L59
L140:   iload 19
L142:   ifle L59
L145:   iload 18
L147:   bipush 103
L149:   if_icmpge L59
L152:   iload 19
L154:   bipush 103
L156:   if_icmpge L59
L159:   iload 14
L161:   istore 20
L163:   aload_0
L164:   getfield Field CRRWDRTI A [[[B
L167:   iconst_1
L168:   aaload
L169:   iload 18
L171:   aaload
L172:   iload 19
L174:   baload
L175:   iconst_2
L176:   iand
L177:   iconst_2
L178:   if_icmpne L184
L181:   iinc 20 -1
L184:   aconst_null
L185:   astore 21
L187:   iload 20
L189:   iflt L198
L192:   aload_2
L193:   iload 20
L195:   aaload
L196:   astore 21
L198:   aload_0
L199:   iload 19
L201:   aload 5
L203:   aload 21
L205:   iload 16
L207:   iload 14
L209:   iload 18
L211:   iload 8
L213:   iconst_0
L214:   iload 17
L216:   invokespecial Method CRRWDRTI a (ILNYFUGYQS;LFTPNODIB;IIIIZI)V
L219:   iload 22
L221:   ifeq L59
L224:   iload 22
L226:   ifeq L37
L229:   return
L230:   astore 7
L232:   new java/lang/StringBuffer
L235:   dup
L236:   ldc "18363, "
L238:   invokespecial Method java/lang/StringBuffer <init> (Ljava/lang/String;)V
L241:   iload_1
L242:   invokevirtual Method java/lang/StringBuffer append (I)Ljava/lang/StringBuffer;
L245:   ldc ", "
L247:   invokevirtual Method java/lang/StringBuffer append (Ljava/lang/String;)Ljava/lang/StringBuffer;
L250:   aload_2
L251:   invokevirtual Method java/lang/StringBuffer append (Ljava/lang/Object;)Ljava/lang/StringBuffer;
L254:   ldc ", "
L256:   invokevirtual Method java/lang/StringBuffer append (Ljava/lang/String;)Ljava/lang/StringBuffer;
L259:   iload_3
L260:   invokevirtual Method java/lang/StringBuffer append (I)Ljava/lang/StringBuffer;
L263:   ldc ", "
L265:   invokevirtual Method java/lang/StringBuffer append (Ljava/lang/String;)Ljava/lang/StringBuffer;
L268:   iload 4
L270:   invokevirtual Method java/lang/StringBuffer append (I)Ljava/lang/StringBuffer;
L273:   ldc ", "
L275:   invokevirtual Method java/lang/StringBuffer append (Ljava/lang/String;)Ljava/lang/StringBuffer;
L278:   aload 5
L280:   invokevirtual Method java/lang/StringBuffer append (Ljava/lang/Object;)Ljava/lang/StringBuffer;
L283:   ldc ", "
L285:   invokevirtual Method java/lang/StringBuffer append (Ljava/lang/String;)Ljava/lang/StringBuffer;
L288:   aload 6
L290:   invokevirtual Method java/lang/StringBuffer append (Ljava/lang/Object;)Ljava/lang/StringBuffer;
L293:   ldc ", "
L295:   invokevirtual Method java/lang/StringBuffer append (Ljava/lang/String;)Ljava/lang/StringBuffer;
L298:   aload 7
L300:   invokevirtual Method java/lang/Throwable toString ()Ljava/lang/String;
L303:   invokevirtual Method java/lang/StringBuffer append (Ljava/lang/String;)Ljava/lang/StringBuffer;
L306:   invokevirtual Method java/lang/StringBuffer toString ()Ljava/lang/String;
L309:   invokestatic Method sign/signlink reporterror (Ljava/lang/String;)V
L312:   new java/lang/RuntimeException
L315:   dup
L316:   invokespecial Method java/lang/RuntimeException <init> ()V
L319:   athrow
L320:   
    .end code
.end method

.method static <clinit> : ()V
    .code stack 4 locals 0
L0:     invokestatic Method java/lang/Math random ()D
L3:     ldc2_w 1.7e1
L6:     dmul
L7:     d2i
L8:     bipush 8
L10:    isub
L11:    putstatic Field CRRWDRTI a I
L14:    invokestatic Method java/lang/Math random ()D
L17:    ldc2_w 3.3e1
L20:    dmul
L21:    d2i
L22:    bipush 16
L24:    isub
L25:    putstatic Field CRRWDRTI k I
L28:    iconst_4
L29:    newarray int
L31:    dup
L32:    iconst_0
L33:    iconst_1
L34:    iastore
L35:    dup
L36:    iconst_2
L37:    iconst_m1
L38:    iastore
L39:    putstatic Field CRRWDRTI o [I
L42:    sipush 323
L45:    putstatic Field CRRWDRTI p I
L48:    iconst_4
L49:    newarray int
L51:    dup
L52:    iconst_0
L53:    bipush 16
L55:    iastore
L56:    dup
L57:    iconst_1
L58:    bipush 32
L60:    iastore
L61:    dup
L62:    iconst_2
L63:    bipush 64
L65:    iastore
L66:    dup
L67:    iconst_3
L68:    sipush 128
L71:    iastore
L72:    putstatic Field CRRWDRTI r [I
L75:    iconst_4
L76:    newarray int
L78:    dup
L79:    iconst_1
L80:    iconst_m1
L81:    iastore
L82:    dup
L83:    iconst_3
L84:    iconst_1
L85:    iastore
L86:    putstatic Field CRRWDRTI v [I
L89:    bipush 99
L91:    putstatic Field CRRWDRTI w I
L94:    iconst_1
L95:    putstatic Field CRRWDRTI C Z
L98:    iconst_4
L99:    newarray int
L101:   dup
L102:   iconst_0
L103:   iconst_1
L104:   iastore
L105:   dup
L106:   iconst_1
L107:   iconst_2
L108:   iastore
L109:   dup
L110:   iconst_2
L111:   iconst_4
L112:   iastore
L113:   dup
L114:   iconst_3
L115:   bipush 8
L117:   iastore
L118:   putstatic Field CRRWDRTI D [I
L121:   sipush -388
L124:   putstatic Field CRRWDRTI E I
L127:   return
L128:   
    .end code
.end method
.end class
