.version 45 3
.class public super eb
.super db
.field private static h Z
.field private i I
.field private j B
.field private k B
.field private l I
.field private m Z
.field public n I
.field public o [I
.field public p [I
.field public q [I
.field public r I
.field public s [I
.field public t [I
.field public u [I
.field public v [I
.field public w [I
.field public x [I
.field public y [I
.field public z [I
.field public A [I
.field public B [I
.field public C I
.field public D I
.field public E [I
.field public F [I
.field public G [I
.field public H I
.field public I I
.field public J I
.field public K I
.field public L I
.field public M I
.field public N I
.field public O I
.field public P I
.field public Q I
.field public R [I
.field public S [I
.field public T [[I
.field public U [[I
.field public V Z
.field W [Ln;
.field X [Ln;
.field static Y [Ll;
.field static Z Lkb;
.field static ab Lkb;
.field static bb Lkb;
.field static cb Lkb;
.field static db Lkb;
.field static eb Lkb;
.field static fb Lkb;
.field static gb Lkb;
.field static hb Lkb;
.field static ib Lkb;
.field static jb Lkb;
.field static kb Lkb;
.field static lb Lkb;
.field static mb Lkb;
.field static nb [Z
.field static ob [Z
.field static pb [I
.field static qb [I
.field static rb [I
.field static sb [I
.field static tb [I
.field static ub [I
.field static vb [I
.field static wb [[I
.field static xb [I
.field static yb [[I
.field static zb [I
.field static Ab [I
.field static Bb [I
.field static Cb [I
.field static Db [I
.field static Eb [I
.field static Fb I
.field static Gb I
.field static Hb I
.field public static Ib Z
.field public static Jb I
.field public static Kb I
.field public static Lb I
.field public static Mb [I
.field public static Nb [I
.field public static Ob [I
.field static Pb [I
.field static Qb [I
.field public static Rb Z

.method public static a : (Z)V
    .code stack 3 locals 2
        .catch java/lang/RuntimeException from L0 to L154 using L155
L0:     aconst_null
L1:     putstatic Field eb Y [Ll;
L4:     aconst_null
L5:     putstatic Field eb Z Lkb;
L8:     aconst_null
L9:     putstatic Field eb ab Lkb;
L12:    aconst_null
L13:    putstatic Field eb bb Lkb;
L16:    aconst_null
L17:    putstatic Field eb cb Lkb;
L20:    aconst_null
L21:    putstatic Field eb db Lkb;
L24:    aconst_null
L25:    putstatic Field eb eb Lkb;
L28:    aconst_null
L29:    putstatic Field eb fb Lkb;
L32:    aconst_null
L33:    putstatic Field eb gb Lkb;
L36:    aconst_null
L37:    putstatic Field eb hb Lkb;
L40:    aconst_null
L41:    putstatic Field eb ib Lkb;
L44:    aconst_null
L45:    putstatic Field eb jb Lkb;
L48:    aconst_null
L49:    putstatic Field eb kb Lkb;
L52:    aconst_null
L53:    putstatic Field eb lb Lkb;
L56:    aconst_null
L57:    putstatic Field eb mb Lkb;
L60:    aconst_null
L61:    putstatic Field eb nb [Z
L64:    iload_0
L65:    ifne L82
L68:    getstatic Field eb h Z
L71:    ifeq L78
L74:    iconst_0
L75:    goto L79
L78:    iconst_1
L79:    putstatic Field eb h Z
L82:    aconst_null
L83:    putstatic Field eb ob [Z
L86:    aconst_null
L87:    putstatic Field eb pb [I
L90:    aconst_null
L91:    putstatic Field eb qb [I
L94:    aconst_null
L95:    putstatic Field eb rb [I
L98:    aconst_null
L99:    putstatic Field eb sb [I
L102:   aconst_null
L103:   putstatic Field eb tb [I
L106:   aconst_null
L107:   putstatic Field eb ub [I
L110:   aconst_null
L111:   putstatic Field eb vb [I
L114:   aconst_null
L115:   putstatic Field eb wb [[I
L118:   aconst_null
L119:   putstatic Field eb xb [I
L122:   aconst_null
L123:   putstatic Field eb yb [[I
L126:   aconst_null
L127:   putstatic Field eb zb [I
L130:   aconst_null
L131:   putstatic Field eb Ab [I
L134:   aconst_null
L135:   putstatic Field eb Bb [I
L138:   aconst_null
L139:   putstatic Field eb Nb [I
L142:   aconst_null
L143:   putstatic Field eb Ob [I
L146:   aconst_null
L147:   putstatic Field eb Pb [I
L150:   aconst_null
L151:   putstatic Field eb Qb [I
L154:   return
L155:   astore_1
L156:   new java/lang/StringBuffer
L159:   dup
L160:   ldc "40423, "
L162:   invokespecial Method java/lang/StringBuffer <init> (Ljava/lang/String;)V
L165:   iload_0
L166:   invokevirtual Method java/lang/StringBuffer append (Z)Ljava/lang/StringBuffer;
L169:   ldc ", "
L171:   invokevirtual Method java/lang/StringBuffer append (Ljava/lang/String;)Ljava/lang/StringBuffer;
L174:   aload_1
L175:   invokevirtual Method java/lang/Throwable toString ()Ljava/lang/String;
L178:   invokevirtual Method java/lang/StringBuffer append (Ljava/lang/String;)Ljava/lang/StringBuffer;
L181:   invokevirtual Method java/lang/StringBuffer toString ()Ljava/lang/String;
L184:   invokestatic Method sign/signlink reporterror (Ljava/lang/String;)V
L187:   new java/lang/RuntimeException
L190:   dup
L191:   invokespecial Method java/lang/RuntimeException <init> ()V
L194:   athrow
L195:   
    .end code
.end method

.method public static a : (ILub;)V
    .code stack 8 locals 22
L0:     getstatic Field eb Rb Z
L3:     istore 21
L5:     iload_0
L6:     iconst_3
L7:     if_icmplt L15
L10:    iload_0
L11:    iconst_3
L12:    if_icmple L16
L15:    return
        .catch java/lang/Exception from L16 to L912 using L913
        .catch java/lang/RuntimeException from L5 to L927 using L927
L16:    new kb
L19:    dup
L20:    sipush 363
L23:    aload_1
L24:    ldc "ob_head.dat"
L26:    aconst_null
L27:    iconst_2
L28:    invokevirtual Method ub a (Ljava/lang/String;[BB)[B
L31:    invokespecial Method kb <init> (I[B)V
L34:    putstatic Field eb Z Lkb;
L37:    new kb
L40:    dup
L41:    sipush 363
L44:    aload_1
L45:    ldc "ob_face1.dat"
L47:    aconst_null
L48:    iconst_2
L49:    invokevirtual Method ub a (Ljava/lang/String;[BB)[B
L52:    invokespecial Method kb <init> (I[B)V
L55:    putstatic Field eb ab Lkb;
L58:    new kb
L61:    dup
L62:    sipush 363
L65:    aload_1
L66:    ldc "ob_face2.dat"
L68:    aconst_null
L69:    iconst_2
L70:    invokevirtual Method ub a (Ljava/lang/String;[BB)[B
L73:    invokespecial Method kb <init> (I[B)V
L76:    putstatic Field eb bb Lkb;
L79:    new kb
L82:    dup
L83:    sipush 363
L86:    aload_1
L87:    ldc "ob_face3.dat"
L89:    aconst_null
L90:    iconst_2
L91:    invokevirtual Method ub a (Ljava/lang/String;[BB)[B
L94:    invokespecial Method kb <init> (I[B)V
L97:    putstatic Field eb cb Lkb;
L100:   new kb
L103:   dup
L104:   sipush 363
L107:   aload_1
L108:   ldc "ob_face4.dat"
L110:   aconst_null
L111:   iconst_2
L112:   invokevirtual Method ub a (Ljava/lang/String;[BB)[B
L115:   invokespecial Method kb <init> (I[B)V
L118:   putstatic Field eb db Lkb;
L121:   new kb
L124:   dup
L125:   sipush 363
L128:   aload_1
L129:   ldc "ob_face5.dat"
L131:   aconst_null
L132:   iconst_2
L133:   invokevirtual Method ub a (Ljava/lang/String;[BB)[B
L136:   invokespecial Method kb <init> (I[B)V
L139:   putstatic Field eb eb Lkb;
L142:   new kb
L145:   dup
L146:   sipush 363
L149:   aload_1
L150:   ldc "ob_point1.dat"
L152:   aconst_null
L153:   iconst_2
L154:   invokevirtual Method ub a (Ljava/lang/String;[BB)[B
L157:   invokespecial Method kb <init> (I[B)V
L160:   putstatic Field eb fb Lkb;
L163:   new kb
L166:   dup
L167:   sipush 363
L170:   aload_1
L171:   ldc "ob_point2.dat"
L173:   aconst_null
L174:   iconst_2
L175:   invokevirtual Method ub a (Ljava/lang/String;[BB)[B
L178:   invokespecial Method kb <init> (I[B)V
L181:   putstatic Field eb gb Lkb;
L184:   new kb
L187:   dup
L188:   sipush 363
L191:   aload_1
L192:   ldc "ob_point3.dat"
L194:   aconst_null
L195:   iconst_2
L196:   invokevirtual Method ub a (Ljava/lang/String;[BB)[B
L199:   invokespecial Method kb <init> (I[B)V
L202:   putstatic Field eb hb Lkb;
L205:   new kb
L208:   dup
L209:   sipush 363
L212:   aload_1
L213:   ldc "ob_point4.dat"
L215:   aconst_null
L216:   iconst_2
L217:   invokevirtual Method ub a (Ljava/lang/String;[BB)[B
L220:   invokespecial Method kb <init> (I[B)V
L223:   putstatic Field eb ib Lkb;
L226:   new kb
L229:   dup
L230:   sipush 363
L233:   aload_1
L234:   ldc "ob_point5.dat"
L236:   aconst_null
L237:   iconst_2
L238:   invokevirtual Method ub a (Ljava/lang/String;[BB)[B
L241:   invokespecial Method kb <init> (I[B)V
L244:   putstatic Field eb jb Lkb;
L247:   new kb
L250:   dup
L251:   sipush 363
L254:   aload_1
L255:   ldc "ob_vertex1.dat"
L257:   aconst_null
L258:   iconst_2
L259:   invokevirtual Method ub a (Ljava/lang/String;[BB)[B
L262:   invokespecial Method kb <init> (I[B)V
L265:   putstatic Field eb kb Lkb;
L268:   new kb
L271:   dup
L272:   sipush 363
L275:   aload_1
L276:   ldc "ob_vertex2.dat"
L278:   aconst_null
L279:   iconst_2
L280:   invokevirtual Method ub a (Ljava/lang/String;[BB)[B
L283:   invokespecial Method kb <init> (I[B)V
L286:   putstatic Field eb lb Lkb;
L289:   new kb
L292:   dup
L293:   sipush 363
L296:   aload_1
L297:   ldc "ob_axis.dat"
L299:   aconst_null
L300:   iconst_2
L301:   invokevirtual Method ub a (Ljava/lang/String;[BB)[B
L304:   invokespecial Method kb <init> (I[B)V
L307:   putstatic Field eb mb Lkb;
L310:   getstatic Field eb Z Lkb;
L313:   iconst_0
L314:   putfield Field kb r I
L317:   getstatic Field eb fb Lkb;
L320:   iconst_0
L321:   putfield Field kb r I
L324:   getstatic Field eb gb Lkb;
L327:   iconst_0
L328:   putfield Field kb r I
L331:   getstatic Field eb hb Lkb;
L334:   iconst_0
L335:   putfield Field kb r I
L338:   getstatic Field eb ib Lkb;
L341:   iconst_0
L342:   putfield Field kb r I
L345:   getstatic Field eb kb Lkb;
L348:   iconst_0
L349:   putfield Field kb r I
L352:   getstatic Field eb lb Lkb;
L355:   iconst_0
L356:   putfield Field kb r I
L359:   getstatic Field eb Z Lkb;
L362:   invokevirtual Method kb e ()I
L365:   istore_2
L366:   iload_2
L367:   bipush 100
L369:   iadd
L370:   anewarray l
L373:   putstatic Field eb Y [Ll;
L376:   iconst_0
L377:   istore_3
L378:   iconst_0
L379:   istore 4
L381:   iconst_0
L382:   istore 5
L384:   iconst_0
L385:   istore 6
L387:   iconst_0
L388:   istore 7
L390:   iconst_0
L391:   istore 8
L393:   iconst_0
L394:   istore 9
L396:   iconst_0
L397:   istore 10
L399:   iload 21
L401:   ifeq L906
L404:   getstatic Field eb Z Lkb;
L407:   invokevirtual Method kb e ()I
L410:   istore 11
L412:   getstatic Field eb Y [Ll;
L415:   iload 11
L417:   new l
L420:   dup
L421:   invokespecial Method l <init> ()V
L424:   dup_x2
L425:   aastore
L426:   astore 12
L428:   aload 12
L430:   getstatic Field eb Z Lkb;
L433:   invokevirtual Method kb e ()I
L436:   putfield Field l a I
L439:   aload 12
L441:   getstatic Field eb Z Lkb;
L444:   invokevirtual Method kb e ()I
L447:   putfield Field l b I
L450:   aload 12
L452:   getstatic Field eb Z Lkb;
L455:   invokevirtual Method kb c ()I
L458:   putfield Field l c I
L461:   aload 12
L463:   getstatic Field eb fb Lkb;
L466:   getfield Field kb r I
L469:   putfield Field l d I
L472:   aload 12
L474:   getstatic Field eb gb Lkb;
L477:   getfield Field kb r I
L480:   putfield Field l e I
L483:   aload 12
L485:   getstatic Field eb hb Lkb;
L488:   getfield Field kb r I
L491:   putfield Field l f I
L494:   aload 12
L496:   getstatic Field eb ib Lkb;
L499:   getfield Field kb r I
L502:   putfield Field l g I
L505:   aload 12
L507:   getstatic Field eb kb Lkb;
L510:   getfield Field kb r I
L513:   putfield Field l i I
L516:   aload 12
L518:   getstatic Field eb lb Lkb;
L521:   getfield Field kb r I
L524:   putfield Field l j I
L527:   getstatic Field eb Z Lkb;
L530:   invokevirtual Method kb c ()I
L533:   istore 13
L535:   getstatic Field eb Z Lkb;
L538:   invokevirtual Method kb c ()I
L541:   istore 14
L543:   getstatic Field eb Z Lkb;
L546:   invokevirtual Method kb c ()I
L549:   istore 15
L551:   getstatic Field eb Z Lkb;
L554:   invokevirtual Method kb c ()I
L557:   istore 16
L559:   getstatic Field eb Z Lkb;
L562:   invokevirtual Method kb c ()I
L565:   istore 17
L567:   iconst_0
L568:   istore 18
L570:   iload 21
L572:   ifeq L628
L575:   getstatic Field eb fb Lkb;
L578:   invokevirtual Method kb c ()I
L581:   istore 19
L583:   iload 19
L585:   iconst_1
L586:   iand
L587:   ifeq L597
L590:   getstatic Field eb gb Lkb;
L593:   invokevirtual Method kb j ()I
L596:   pop
L597:   iload 19
L599:   iconst_2
L600:   iand
L601:   ifeq L611
L604:   getstatic Field eb hb Lkb;
L607:   invokevirtual Method kb j ()I
L610:   pop
L611:   iload 19
L613:   iconst_4
L614:   iand
L615:   ifeq L625
L618:   getstatic Field eb ib Lkb;
L621:   invokevirtual Method kb j ()I
L624:   pop
L625:   iinc 18 1
L628:   iload 18
L630:   aload 12
L632:   getfield Field l a I
L635:   if_icmplt L575
L638:   iconst_0
L639:   istore 19
L641:   iload 21
L643:   ifeq L684
L646:   getstatic Field eb lb Lkb;
L649:   invokevirtual Method kb c ()I
L652:   istore 20
L654:   iload 20
L656:   iconst_1
L657:   if_icmpne L674
L660:   getstatic Field eb kb Lkb;
L663:   invokevirtual Method kb j ()I
L666:   pop
L667:   getstatic Field eb kb Lkb;
L670:   invokevirtual Method kb j ()I
L673:   pop
L674:   getstatic Field eb kb Lkb;
L677:   invokevirtual Method kb j ()I
L680:   pop
L681:   iinc 19 1
L684:   iload 19
L686:   aload 12
L688:   getfield Field l b I
L691:   if_icmplt L646
L694:   aload 12
L696:   iload 5
L698:   putfield Field l k I
L701:   iload 5
L703:   aload 12
L705:   getfield Field l b I
L708:   iconst_2
L709:   imul
L710:   iadd
L711:   istore 5
L713:   iload 13
L715:   iconst_1
L716:   if_icmpne L741
L719:   aload 12
L721:   iload 6
L723:   putfield Field l l I
L726:   iload 6
L728:   aload 12
L730:   getfield Field l b I
L733:   iadd
L734:   istore 6
L736:   iload 21
L738:   ifeq L747
L741:   aload 12
L743:   iconst_m1
L744:   putfield Field l l I
L747:   iload 14
L749:   sipush 255
L752:   if_icmpne L777
L755:   aload 12
L757:   iload 7
L759:   putfield Field l m I
L762:   iload 7
L764:   aload 12
L766:   getfield Field l b I
L769:   iadd
L770:   istore 7
L772:   iload 21
L774:   ifeq L787
L777:   aload 12
L779:   iload 14
L781:   ineg
L782:   iconst_1
L783:   isub
L784:   putfield Field l m I
L787:   iload 15
L789:   iconst_1
L790:   if_icmpne L815
L793:   aload 12
L795:   iload 8
L797:   putfield Field l n I
L800:   iload 8
L802:   aload 12
L804:   getfield Field l b I
L807:   iadd
L808:   istore 8
L810:   iload 21
L812:   ifeq L821
L815:   aload 12
L817:   iconst_m1
L818:   putfield Field l n I
L821:   iload 16
L823:   iconst_1
L824:   if_icmpne L849
L827:   aload 12
L829:   iload 9
L831:   putfield Field l o I
L834:   iload 9
L836:   aload 12
L838:   getfield Field l b I
L841:   iadd
L842:   istore 9
L844:   iload 21
L846:   ifeq L855
L849:   aload 12
L851:   iconst_m1
L852:   putfield Field l o I
L855:   iload 17
L857:   iconst_1
L858:   if_icmpne L883
L861:   aload 12
L863:   iload 4
L865:   putfield Field l h I
L868:   iload 4
L870:   aload 12
L872:   getfield Field l a I
L875:   iadd
L876:   istore 4
L878:   iload 21
L880:   ifeq L889
L883:   aload 12
L885:   iconst_m1
L886:   putfield Field l h I
L889:   aload 12
L891:   iload_3
L892:   putfield Field l p I
L895:   iload_3
L896:   aload 12
L898:   getfield Field l c I
L901:   iadd
L902:   istore_3
L903:   iinc 10 1
L906:   iload 10
L908:   iload_2
L909:   if_icmplt L404
L912:   return
L913:   astore_2
L914:   getstatic Field java/lang/System out Ljava/io/PrintStream;
L917:   ldc "Error loading model index"
L919:   invokevirtual Method java/io/PrintStream println (Ljava/lang/String;)V
L922:   aload_2
L923:   invokevirtual Method java/lang/Throwable printStackTrace ()V
L926:   return
L927:   astore_2
L928:   new java/lang/StringBuffer
L931:   dup
L932:   ldc "33624, "
L934:   invokespecial Method java/lang/StringBuffer <init> (Ljava/lang/String;)V
L937:   iload_0
L938:   invokevirtual Method java/lang/StringBuffer append (I)Ljava/lang/StringBuffer;
L941:   ldc ", "
L943:   invokevirtual Method java/lang/StringBuffer append (Ljava/lang/String;)Ljava/lang/StringBuffer;
L946:   aload_1
L947:   invokevirtual Method java/lang/StringBuffer append (Ljava/lang/Object;)Ljava/lang/StringBuffer;
L950:   ldc ", "
L952:   invokevirtual Method java/lang/StringBuffer append (Ljava/lang/String;)Ljava/lang/StringBuffer;
L955:   aload_2
L956:   invokevirtual Method java/lang/Throwable toString ()Ljava/lang/String;
L959:   invokevirtual Method java/lang/StringBuffer append (Ljava/lang/String;)Ljava/lang/StringBuffer;
L962:   invokevirtual Method java/lang/StringBuffer toString ()Ljava/lang/String;
L965:   invokestatic Method sign/signlink reporterror (Ljava/lang/String;)V
L968:   new java/lang/RuntimeException
L971:   dup
L972:   invokespecial Method java/lang/RuntimeException <init> ()V
L975:   athrow
L976:   
    .end code
.end method

.method public <init> : (ZI)V
    .code stack 5 locals 17
L0:     getstatic Field eb Rb Z
L3:     istore 16
L5:     aload_0
L6:     invokespecial Method db <init> ()V
L9:     aload_0
L10:    ldc 45861
L12:    putfield Field eb i I
L15:    aload_0
L16:    bipush 47
L18:    putfield Field eb j B
L21:    aload_0
L22:    bipush 47
L24:    putfield Field eb k B
L27:    aload_0
L28:    iconst_5
L29:    putfield Field eb l I
L32:    aload_0
L33:    iconst_0
L34:    putfield Field eb m Z
L37:    aload_0
L38:    iconst_0
L39:    putfield Field eb V Z
        .catch java/lang/RuntimeException from L42 to L1093 using L1094
L42:    getstatic Field eb Y [Ll;
L45:    ifnonnull L49
L48:    return
L49:    getstatic Field eb Y [Ll;
L52:    iload_2
L53:    aaload
L54:    astore_3
L55:    aload_3
L56:    ifnonnull L87
L59:    getstatic Field java/lang/System out Ljava/io/PrintStream;
L62:    new java/lang/StringBuffer
L65:    dup
L66:    ldc "Error model:"
L68:    invokespecial Method java/lang/StringBuffer <init> (Ljava/lang/String;)V
L71:    iload_2
L72:    invokevirtual Method java/lang/StringBuffer append (I)Ljava/lang/StringBuffer;
L75:    ldc " not found!"
L77:    invokevirtual Method java/lang/StringBuffer append (Ljava/lang/String;)Ljava/lang/StringBuffer;
L80:    invokevirtual Method java/lang/StringBuffer toString ()Ljava/lang/String;
L83:    invokevirtual Method java/io/PrintStream println (Ljava/lang/String;)V
L86:    return
L87:    aload_0
L88:    aload_3
L89:    getfield Field l a I
L92:    putfield Field eb n I
L95:    aload_0
L96:    aload_3
L97:    getfield Field l b I
L100:   putfield Field eb r I
L103:   aload_0
L104:   aload_3
L105:   getfield Field l c I
L108:   putfield Field eb D I
L111:   aload_0
L112:   aload_0
L113:   getfield Field eb n I
L116:   newarray int
L118:   putfield Field eb o [I
L121:   aload_0
L122:   aload_0
L123:   getfield Field eb n I
L126:   newarray int
L128:   putfield Field eb p [I
L131:   aload_0
L132:   aload_0
L133:   getfield Field eb n I
L136:   newarray int
L138:   putfield Field eb q [I
L141:   aload_0
L142:   aload_0
L143:   getfield Field eb r I
L146:   newarray int
L148:   putfield Field eb s [I
L151:   aload_0
L152:   aload_0
L153:   getfield Field eb r I
L156:   newarray int
L158:   putfield Field eb t [I
L161:   aload_0
L162:   aload_0
L163:   getfield Field eb r I
L166:   newarray int
L168:   putfield Field eb u [I
L171:   aload_0
L172:   aload_0
L173:   getfield Field eb D I
L176:   newarray int
L178:   putfield Field eb E [I
L181:   aload_0
L182:   aload_0
L183:   getfield Field eb D I
L186:   newarray int
L188:   putfield Field eb F [I
L191:   aload_0
L192:   aload_0
L193:   getfield Field eb D I
L196:   newarray int
L198:   putfield Field eb G [I
L201:   aload_3
L202:   getfield Field l h I
L205:   iflt L218
L208:   aload_0
L209:   aload_0
L210:   getfield Field eb n I
L213:   newarray int
L215:   putfield Field eb R [I
L218:   aload_3
L219:   getfield Field l l I
L222:   iflt L235
L225:   aload_0
L226:   aload_0
L227:   getfield Field eb r I
L230:   newarray int
L232:   putfield Field eb y [I
L235:   aload_3
L236:   getfield Field l m I
L239:   iflt L257
L242:   aload_0
L243:   aload_0
L244:   getfield Field eb r I
L247:   newarray int
L249:   putfield Field eb z [I
L252:   iload 16
L254:   ifeq L268
L257:   aload_0
L258:   aload_3
L259:   getfield Field l m I
L262:   ineg
L263:   iconst_1
L264:   isub
L265:   putfield Field eb C I
L268:   aload_3
L269:   getfield Field l n I
L272:   iflt L285
L275:   aload_0
L276:   aload_0
L277:   getfield Field eb r I
L280:   newarray int
L282:   putfield Field eb A [I
L285:   aload_3
L286:   getfield Field l o I
L289:   iflt L302
L292:   aload_0
L293:   aload_0
L294:   getfield Field eb r I
L297:   newarray int
L299:   putfield Field eb S [I
L302:   aload_0
L303:   aload_0
L304:   getfield Field eb r I
L307:   newarray int
L309:   putfield Field eb B [I
L312:   getstatic Field eb fb Lkb;
L315:   aload_3
L316:   getfield Field l d I
L319:   putfield Field kb r I
L322:   getstatic Field eb gb Lkb;
L325:   aload_3
L326:   getfield Field l e I
L329:   putfield Field kb r I
L332:   getstatic Field eb hb Lkb;
L335:   aload_3
L336:   getfield Field l f I
L339:   putfield Field kb r I
L342:   getstatic Field eb ib Lkb;
L345:   aload_3
L346:   getfield Field l g I
L349:   putfield Field kb r I
L352:   getstatic Field eb jb Lkb;
L355:   aload_3
L356:   getfield Field l h I
L359:   putfield Field kb r I
L362:   iconst_0
L363:   istore 4
L365:   iconst_0
L366:   istore 5
L368:   iconst_0
L369:   istore 6
L371:   iconst_0
L372:   istore 7
L374:   iload 16
L376:   ifeq L527
L379:   getstatic Field eb fb Lkb;
L382:   invokevirtual Method kb c ()I
L385:   istore 8
L387:   iconst_0
L388:   istore 9
L390:   iload 8
L392:   iconst_1
L393:   iand
L394:   ifeq L405
L397:   getstatic Field eb gb Lkb;
L400:   invokevirtual Method kb j ()I
L403:   istore 9
L405:   iconst_0
L406:   istore 10
L408:   iload 8
L410:   iconst_2
L411:   iand
L412:   ifeq L423
L415:   getstatic Field eb hb Lkb;
L418:   invokevirtual Method kb j ()I
L421:   istore 10
L423:   iconst_0
L424:   istore 11
L426:   iload 8
L428:   iconst_4
L429:   iand
L430:   ifeq L441
L433:   getstatic Field eb ib Lkb;
L436:   invokevirtual Method kb j ()I
L439:   istore 11
L441:   aload_0
L442:   getfield Field eb o [I
L445:   iload 7
L447:   iload 4
L449:   iload 9
L451:   iadd
L452:   iastore
L453:   aload_0
L454:   getfield Field eb p [I
L457:   iload 7
L459:   iload 5
L461:   iload 10
L463:   iadd
L464:   iastore
L465:   aload_0
L466:   getfield Field eb q [I
L469:   iload 7
L471:   iload 6
L473:   iload 11
L475:   iadd
L476:   iastore
L477:   aload_0
L478:   getfield Field eb o [I
L481:   iload 7
L483:   iaload
L484:   istore 4
L486:   aload_0
L487:   getfield Field eb p [I
L490:   iload 7
L492:   iaload
L493:   istore 5
L495:   aload_0
L496:   getfield Field eb q [I
L499:   iload 7
L501:   iaload
L502:   istore 6
L504:   aload_0
L505:   getfield Field eb R [I
L508:   ifnull L524
L511:   aload_0
L512:   getfield Field eb R [I
L515:   iload 7
L517:   getstatic Field eb jb Lkb;
L520:   invokevirtual Method kb c ()I
L523:   iastore
L524:   iinc 7 1
L527:   iload 7
L529:   aload_0
L530:   getfield Field eb n I
L533:   if_icmplt L379
L536:   getstatic Field eb ab Lkb;
L539:   aload_3
L540:   getfield Field l k I
L543:   putfield Field kb r I
L546:   getstatic Field eb bb Lkb;
L549:   aload_3
L550:   getfield Field l l I
L553:   putfield Field kb r I
L556:   getstatic Field eb cb Lkb;
L559:   aload_3
L560:   getfield Field l m I
L563:   putfield Field kb r I
L566:   getstatic Field eb db Lkb;
L569:   aload_3
L570:   getfield Field l n I
L573:   putfield Field kb r I
L576:   getstatic Field eb eb Lkb;
L579:   aload_3
L580:   getfield Field l o I
L583:   putfield Field kb r I
L586:   iconst_0
L587:   istore 8
L589:   iload 16
L591:   ifeq L690
L594:   aload_0
L595:   getfield Field eb B [I
L598:   iload 8
L600:   getstatic Field eb ab Lkb;
L603:   invokevirtual Method kb e ()I
L606:   iastore
L607:   aload_0
L608:   getfield Field eb y [I
L611:   ifnull L627
L614:   aload_0
L615:   getfield Field eb y [I
L618:   iload 8
L620:   getstatic Field eb bb Lkb;
L623:   invokevirtual Method kb c ()I
L626:   iastore
L627:   aload_0
L628:   getfield Field eb z [I
L631:   ifnull L647
L634:   aload_0
L635:   getfield Field eb z [I
L638:   iload 8
L640:   getstatic Field eb cb Lkb;
L643:   invokevirtual Method kb c ()I
L646:   iastore
L647:   aload_0
L648:   getfield Field eb A [I
L651:   ifnull L667
L654:   aload_0
L655:   getfield Field eb A [I
L658:   iload 8
L660:   getstatic Field eb db Lkb;
L663:   invokevirtual Method kb c ()I
L666:   iastore
L667:   aload_0
L668:   getfield Field eb S [I
L671:   ifnull L687
L674:   aload_0
L675:   getfield Field eb S [I
L678:   iload 8
L680:   getstatic Field eb eb Lkb;
L683:   invokevirtual Method kb c ()I
L686:   iastore
L687:   iinc 8 1
L690:   iload 8
L692:   aload_0
L693:   getfield Field eb r I
L696:   if_icmplt L594
L699:   getstatic Field eb kb Lkb;
L702:   aload_3
L703:   getfield Field l i I
L706:   putfield Field kb r I
L709:   getstatic Field eb lb Lkb;
L712:   aload_3
L713:   getfield Field l j I
L716:   putfield Field kb r I
L719:   iconst_0
L720:   istore 9
L722:   iconst_0
L723:   istore 10
L725:   iconst_0
L726:   istore 11
L728:   iconst_0
L729:   istore 12
L731:   iconst_0
L732:   istore 13
L734:   iload 16
L736:   ifeq L1000
L739:   getstatic Field eb lb Lkb;
L742:   invokevirtual Method kb c ()I
L745:   istore 14
L747:   iload 14
L749:   iconst_1
L750:   if_icmpne L825
L753:   getstatic Field eb kb Lkb;
L756:   invokevirtual Method kb j ()I
L759:   iload 12
L761:   iadd
L762:   istore 9
L764:   iload 9
L766:   istore 12
L768:   getstatic Field eb kb Lkb;
L771:   invokevirtual Method kb j ()I
L774:   iload 12
L776:   iadd
L777:   istore 10
L779:   iload 10
L781:   istore 12
L783:   getstatic Field eb kb Lkb;
L786:   invokevirtual Method kb j ()I
L789:   iload 12
L791:   iadd
L792:   istore 11
L794:   iload 11
L796:   istore 12
L798:   aload_0
L799:   getfield Field eb s [I
L802:   iload 13
L804:   iload 9
L806:   iastore
L807:   aload_0
L808:   getfield Field eb t [I
L811:   iload 13
L813:   iload 10
L815:   iastore
L816:   aload_0
L817:   getfield Field eb u [I
L820:   iload 13
L822:   iload 11
L824:   iastore
L825:   iload 14
L827:   iconst_2
L828:   if_icmpne L881
L831:   iload 9
L833:   istore 9
L835:   iload 11
L837:   istore 10
L839:   getstatic Field eb kb Lkb;
L842:   invokevirtual Method kb j ()I
L845:   iload 12
L847:   iadd
L848:   istore 11
L850:   iload 11
L852:   istore 12
L854:   aload_0
L855:   getfield Field eb s [I
L858:   iload 13
L860:   iload 9
L862:   iastore
L863:   aload_0
L864:   getfield Field eb t [I
L867:   iload 13
L869:   iload 10
L871:   iastore
L872:   aload_0
L873:   getfield Field eb u [I
L876:   iload 13
L878:   iload 11
L880:   iastore
L881:   iload 14
L883:   iconst_3
L884:   if_icmpne L937
L887:   iload 11
L889:   istore 9
L891:   iload 10
L893:   istore 10
L895:   getstatic Field eb kb Lkb;
L898:   invokevirtual Method kb j ()I
L901:   iload 12
L903:   iadd
L904:   istore 11
L906:   iload 11
L908:   istore 12
L910:   aload_0
L911:   getfield Field eb s [I
L914:   iload 13
L916:   iload 9
L918:   iastore
L919:   aload_0
L920:   getfield Field eb t [I
L923:   iload 13
L925:   iload 10
L927:   iastore
L928:   aload_0
L929:   getfield Field eb u [I
L932:   iload 13
L934:   iload 11
L936:   iastore
L937:   iload 14
L939:   iconst_4
L940:   if_icmpne L997
L943:   iload 9
L945:   istore 15
L947:   iload 10
L949:   istore 9
L951:   iload 15
L953:   istore 10
L955:   getstatic Field eb kb Lkb;
L958:   invokevirtual Method kb j ()I
L961:   iload 12
L963:   iadd
L964:   istore 11
L966:   iload 11
L968:   istore 12
L970:   aload_0
L971:   getfield Field eb s [I
L974:   iload 13
L976:   iload 9
L978:   iastore
L979:   aload_0
L980:   getfield Field eb t [I
L983:   iload 13
L985:   iload 10
L987:   iastore
L988:   aload_0
L989:   getfield Field eb u [I
L992:   iload 13
L994:   iload 11
L996:   iastore
L997:   iinc 13 1
L1000:  iload 13
L1002:  aload_0
L1003:  getfield Field eb r I
L1006:  if_icmplt L739
L1009:  iload_1
L1010:  ifeq L1021
L1013:  new java/lang/NullPointerException
L1016:  dup
L1017:  invokespecial Method java/lang/NullPointerException <init> ()V
L1020:  athrow
L1021:  getstatic Field eb mb Lkb;
L1024:  aload_3
L1025:  getfield Field l p I
L1028:  bipush 6
L1030:  imul
L1031:  putfield Field kb r I
L1034:  iconst_0
L1035:  istore 14
L1037:  iload 16
L1039:  ifeq L1084
L1042:  aload_0
L1043:  getfield Field eb E [I
L1046:  iload 14
L1048:  getstatic Field eb mb Lkb;
L1051:  invokevirtual Method kb e ()I
L1054:  iastore
L1055:  aload_0
L1056:  getfield Field eb F [I
L1059:  iload 14
L1061:  getstatic Field eb mb Lkb;
L1064:  invokevirtual Method kb e ()I
L1067:  iastore
L1068:  aload_0
L1069:  getfield Field eb G [I
L1072:  iload 14
L1074:  getstatic Field eb mb Lkb;
L1077:  invokevirtual Method kb e ()I
L1080:  iastore
L1081:  iinc 14 1
L1084:  iload 14
L1086:  aload_0
L1087:  getfield Field eb D I
L1090:  if_icmplt L1042
L1093:  return
L1094:  astore_3
L1095:  new java/lang/StringBuffer
L1098:  dup
L1099:  ldc "23365, "
L1101:  invokespecial Method java/lang/StringBuffer <init> (Ljava/lang/String;)V
L1104:  iload_1
L1105:  invokevirtual Method java/lang/StringBuffer append (Z)Ljava/lang/StringBuffer;
L1108:  ldc ", "
L1110:  invokevirtual Method java/lang/StringBuffer append (Ljava/lang/String;)Ljava/lang/StringBuffer;
L1113:  iload_2
L1114:  invokevirtual Method java/lang/StringBuffer append (I)Ljava/lang/StringBuffer;
L1117:  ldc ", "
L1119:  invokevirtual Method java/lang/StringBuffer append (Ljava/lang/String;)Ljava/lang/StringBuffer;
L1122:  aload_3
L1123:  invokevirtual Method java/lang/Throwable toString ()Ljava/lang/String;
L1126:  invokevirtual Method java/lang/StringBuffer append (Ljava/lang/String;)Ljava/lang/StringBuffer;
L1129:  invokevirtual Method java/lang/StringBuffer toString ()Ljava/lang/String;
L1132:  invokestatic Method sign/signlink reporterror (Ljava/lang/String;)V
L1135:  new java/lang/RuntimeException
L1138:  dup
L1139:  invokespecial Method java/lang/RuntimeException <init> ()V
L1142:  athrow
L1143:  
    .end code
.end method

.method public <init> : (I[Leb;I)V
    .code stack 7 locals 14
L0:     getstatic Field eb Rb Z
L3:     istore 13
L5:     aload_0
L6:     invokespecial Method db <init> ()V
L9:     aload_0
L10:    ldc 45861
L12:    putfield Field eb i I
L15:    aload_0
L16:    bipush 47
L18:    putfield Field eb j B
L21:    aload_0
L22:    bipush 47
L24:    putfield Field eb k B
L27:    aload_0
L28:    iconst_5
L29:    putfield Field eb l I
L32:    aload_0
L33:    iconst_0
L34:    putfield Field eb m Z
L37:    aload_0
L38:    iconst_0
L39:    putfield Field eb V Z
        .catch java/lang/RuntimeException from L42 to L857 using L858
L42:    iconst_0
L43:    istore 4
L45:    iconst_0
L46:    istore 5
L48:    iconst_0
L49:    istore 6
L51:    iconst_0
L52:    istore 7
L54:    aload_0
L55:    iconst_0
L56:    putfield Field eb n I
L59:    aload_0
L60:    iconst_0
L61:    putfield Field eb r I
L64:    aload_0
L65:    iconst_0
L66:    putfield Field eb D I
L69:    aload_0
L70:    iconst_m1
L71:    putfield Field eb C I
L74:    iconst_0
L75:    istore 8
L77:    iload 13
L79:    ifeq L240
L82:    aload_2
L83:    iload 8
L85:    aaload
L86:    astore 9
L88:    aload 9
L90:    ifnull L237
L93:    aload_0
L94:    dup
L95:    getfield Field eb n I
L98:    aload 9
L100:   getfield Field eb n I
L103:   iadd
L104:   putfield Field eb n I
L107:   aload_0
L108:   dup
L109:   getfield Field eb r I
L112:   aload 9
L114:   getfield Field eb r I
L117:   iadd
L118:   putfield Field eb r I
L121:   aload_0
L122:   dup
L123:   getfield Field eb D I
L126:   aload 9
L128:   getfield Field eb D I
L131:   iadd
L132:   putfield Field eb D I
L135:   iload 4
L137:   aload 9
L139:   getfield Field eb y [I
L142:   ifnonnull L149
L145:   iconst_0
L146:   goto L150
L149:   iconst_1
L150:   ior
L151:   istore 4
L153:   aload 9
L155:   getfield Field eb z [I
L158:   ifnull L169
L161:   iconst_1
L162:   istore 5
L164:   iload 13
L166:   ifeq L201
L169:   aload_0
L170:   getfield Field eb C I
L173:   iconst_m1
L174:   if_icmpne L186
L177:   aload_0
L178:   aload 9
L180:   getfield Field eb C I
L183:   putfield Field eb C I
L186:   aload_0
L187:   getfield Field eb C I
L190:   aload 9
L192:   getfield Field eb C I
L195:   if_icmpeq L201
L198:   iconst_1
L199:   istore 5
L201:   iload 6
L203:   aload 9
L205:   getfield Field eb A [I
L208:   ifnonnull L215
L211:   iconst_0
L212:   goto L216
L215:   iconst_1
L216:   ior
L217:   istore 6
L219:   iload 7
L221:   aload 9
L223:   getfield Field eb S [I
L226:   ifnonnull L233
L229:   iconst_0
L230:   goto L234
L233:   iconst_1
L234:   ior
L235:   istore 7
L237:   iinc 8 1
L240:   iload 8
L242:   iload_3
L243:   if_icmplt L82
L246:   iload_1
L247:   ifeq L258
L250:   new java/lang/NullPointerException
L253:   dup
L254:   invokespecial Method java/lang/NullPointerException <init> ()V
L257:   athrow
L258:   aload_0
L259:   aload_0
L260:   getfield Field eb n I
L263:   newarray int
L265:   putfield Field eb o [I
L268:   aload_0
L269:   aload_0
L270:   getfield Field eb n I
L273:   newarray int
L275:   putfield Field eb p [I
L278:   aload_0
L279:   aload_0
L280:   getfield Field eb n I
L283:   newarray int
L285:   putfield Field eb q [I
L288:   aload_0
L289:   aload_0
L290:   getfield Field eb n I
L293:   newarray int
L295:   putfield Field eb R [I
L298:   aload_0
L299:   aload_0
L300:   getfield Field eb r I
L303:   newarray int
L305:   putfield Field eb s [I
L308:   aload_0
L309:   aload_0
L310:   getfield Field eb r I
L313:   newarray int
L315:   putfield Field eb t [I
L318:   aload_0
L319:   aload_0
L320:   getfield Field eb r I
L323:   newarray int
L325:   putfield Field eb u [I
L328:   aload_0
L329:   aload_0
L330:   getfield Field eb D I
L333:   newarray int
L335:   putfield Field eb E [I
L338:   aload_0
L339:   aload_0
L340:   getfield Field eb D I
L343:   newarray int
L345:   putfield Field eb F [I
L348:   aload_0
L349:   aload_0
L350:   getfield Field eb D I
L353:   newarray int
L355:   putfield Field eb G [I
L358:   iload 4
L360:   ifeq L373
L363:   aload_0
L364:   aload_0
L365:   getfield Field eb r I
L368:   newarray int
L370:   putfield Field eb y [I
L373:   iload 5
L375:   ifeq L388
L378:   aload_0
L379:   aload_0
L380:   getfield Field eb r I
L383:   newarray int
L385:   putfield Field eb z [I
L388:   iload 6
L390:   ifeq L403
L393:   aload_0
L394:   aload_0
L395:   getfield Field eb r I
L398:   newarray int
L400:   putfield Field eb A [I
L403:   iload 7
L405:   ifeq L418
L408:   aload_0
L409:   aload_0
L410:   getfield Field eb r I
L413:   newarray int
L415:   putfield Field eb S [I
L418:   aload_0
L419:   aload_0
L420:   getfield Field eb r I
L423:   newarray int
L425:   putfield Field eb B [I
L428:   aload_0
L429:   iconst_0
L430:   putfield Field eb n I
L433:   aload_0
L434:   iconst_0
L435:   putfield Field eb r I
L438:   aload_0
L439:   iconst_0
L440:   putfield Field eb D I
L443:   iconst_0
L444:   istore 9
L446:   iload 13
L448:   ifeq L851
L451:   aload_2
L452:   iload 9
L454:   aaload
L455:   astore 10
L457:   aload 10
L459:   ifnull L848
L462:   iconst_0
L463:   istore 11
L465:   iload 13
L467:   ifeq L738
L470:   iload 4
L472:   ifeq L515
L475:   aload 10
L477:   getfield Field eb y [I
L480:   ifnonnull L498
L483:   aload_0
L484:   getfield Field eb y [I
L487:   aload_0
L488:   getfield Field eb r I
L491:   iconst_0
L492:   iastore
L493:   iload 13
L495:   ifeq L515
L498:   aload_0
L499:   getfield Field eb y [I
L502:   aload_0
L503:   getfield Field eb r I
L506:   aload 10
L508:   getfield Field eb y [I
L511:   iload 11
L513:   iaload
L514:   iastore
L515:   iload 5
L517:   ifeq L564
L520:   aload 10
L522:   getfield Field eb z [I
L525:   ifnonnull L547
L528:   aload_0
L529:   getfield Field eb z [I
L532:   aload_0
L533:   getfield Field eb r I
L536:   aload 10
L538:   getfield Field eb C I
L541:   iastore
L542:   iload 13
L544:   ifeq L564
L547:   aload_0
L548:   getfield Field eb z [I
L551:   aload_0
L552:   getfield Field eb r I
L555:   aload 10
L557:   getfield Field eb z [I
L560:   iload 11
L562:   iaload
L563:   iastore
L564:   iload 6
L566:   ifeq L609
L569:   aload 10
L571:   getfield Field eb A [I
L574:   ifnonnull L592
L577:   aload_0
L578:   getfield Field eb A [I
L581:   aload_0
L582:   getfield Field eb r I
L585:   iconst_0
L586:   iastore
L587:   iload 13
L589:   ifeq L609
L592:   aload_0
L593:   getfield Field eb A [I
L596:   aload_0
L597:   getfield Field eb r I
L600:   aload 10
L602:   getfield Field eb A [I
L605:   iload 11
L607:   iaload
L608:   iastore
L609:   iload 7
L611:   ifeq L639
L614:   aload 10
L616:   getfield Field eb S [I
L619:   ifnull L639
L622:   aload_0
L623:   getfield Field eb S [I
L626:   aload_0
L627:   getfield Field eb r I
L630:   aload 10
L632:   getfield Field eb S [I
L635:   iload 11
L637:   iaload
L638:   iastore
L639:   aload_0
L640:   getfield Field eb B [I
L643:   aload_0
L644:   getfield Field eb r I
L647:   aload 10
L649:   getfield Field eb B [I
L652:   iload 11
L654:   iaload
L655:   iastore
L656:   aload_0
L657:   getfield Field eb s [I
L660:   aload_0
L661:   getfield Field eb r I
L664:   aload_0
L665:   aload 10
L667:   aload 10
L669:   getfield Field eb s [I
L672:   iload 11
L674:   iaload
L675:   invokespecial Method eb a (Leb;I)I
L678:   iastore
L679:   aload_0
L680:   getfield Field eb t [I
L683:   aload_0
L684:   getfield Field eb r I
L687:   aload_0
L688:   aload 10
L690:   aload 10
L692:   getfield Field eb t [I
L695:   iload 11
L697:   iaload
L698:   invokespecial Method eb a (Leb;I)I
L701:   iastore
L702:   aload_0
L703:   getfield Field eb u [I
L706:   aload_0
L707:   getfield Field eb r I
L710:   aload_0
L711:   aload 10
L713:   aload 10
L715:   getfield Field eb u [I
L718:   iload 11
L720:   iaload
L721:   invokespecial Method eb a (Leb;I)I
L724:   iastore
L725:   aload_0
L726:   dup
L727:   getfield Field eb r I
L730:   iconst_1
L731:   iadd
L732:   putfield Field eb r I
L735:   iinc 11 1
L738:   iload 11
L740:   aload 10
L742:   getfield Field eb r I
L745:   if_icmplt L470
L748:   iconst_0
L749:   istore 12
L751:   iload 13
L753:   ifeq L838
L756:   aload_0
L757:   getfield Field eb E [I
L760:   aload_0
L761:   getfield Field eb D I
L764:   aload_0
L765:   aload 10
L767:   aload 10
L769:   getfield Field eb E [I
L772:   iload 12
L774:   iaload
L775:   invokespecial Method eb a (Leb;I)I
L778:   iastore
L779:   aload_0
L780:   getfield Field eb F [I
L783:   aload_0
L784:   getfield Field eb D I
L787:   aload_0
L788:   aload 10
L790:   aload 10
L792:   getfield Field eb F [I
L795:   iload 12
L797:   iaload
L798:   invokespecial Method eb a (Leb;I)I
L801:   iastore
L802:   aload_0
L803:   getfield Field eb G [I
L806:   aload_0
L807:   getfield Field eb D I
L810:   aload_0
L811:   aload 10
L813:   aload 10
L815:   getfield Field eb G [I
L818:   iload 12
L820:   iaload
L821:   invokespecial Method eb a (Leb;I)I
L824:   iastore
L825:   aload_0
L826:   dup
L827:   getfield Field eb D I
L830:   iconst_1
L831:   iadd
L832:   putfield Field eb D I
L835:   iinc 12 1
L838:   iload 12
L840:   aload 10
L842:   getfield Field eb D I
L845:   if_icmplt L756
L848:   iinc 9 1
L851:   iload 9
L853:   iload_3
L854:   if_icmplt L451
L857:   return
L858:   astore 4
L860:   new java/lang/StringBuffer
L863:   dup
L864:   ldc "76712, "
L866:   invokespecial Method java/lang/StringBuffer <init> (Ljava/lang/String;)V
L869:   iload_1
L870:   invokevirtual Method java/lang/StringBuffer append (I)Ljava/lang/StringBuffer;
L873:   ldc ", "
L875:   invokevirtual Method java/lang/StringBuffer append (Ljava/lang/String;)Ljava/lang/StringBuffer;
L878:   aload_2
L879:   invokevirtual Method java/lang/StringBuffer append (Ljava/lang/Object;)Ljava/lang/StringBuffer;
L882:   ldc ", "
L884:   invokevirtual Method java/lang/StringBuffer append (Ljava/lang/String;)Ljava/lang/StringBuffer;
L887:   iload_3
L888:   invokevirtual Method java/lang/StringBuffer append (I)Ljava/lang/StringBuffer;
L891:   ldc ", "
L893:   invokevirtual Method java/lang/StringBuffer append (Ljava/lang/String;)Ljava/lang/StringBuffer;
L896:   aload 4
L898:   invokevirtual Method java/lang/Throwable toString ()Ljava/lang/String;
L901:   invokevirtual Method java/lang/StringBuffer append (Ljava/lang/String;)Ljava/lang/StringBuffer;
L904:   invokevirtual Method java/lang/StringBuffer toString ()Ljava/lang/String;
L907:   invokestatic Method sign/signlink reporterror (Ljava/lang/String;)V
L910:   new java/lang/RuntimeException
L913:   dup
L914:   invokespecial Method java/lang/RuntimeException <init> ()V
L917:   athrow
L918:   
    .end code
.end method

.method public <init> : ([Leb;BIZ)V
    .code stack 5 locals 17
L0:     getstatic Field eb Rb Z
L3:     istore 16
L5:     aload_0
L6:     invokespecial Method db <init> ()V
L9:     aload_0
L10:    ldc 45861
L12:    putfield Field eb i I
L15:    aload_0
L16:    bipush 47
L18:    putfield Field eb j B
L21:    aload_0
L22:    bipush 47
L24:    putfield Field eb k B
L27:    aload_0
L28:    iconst_5
L29:    putfield Field eb l I
L32:    aload_0
L33:    iconst_0
L34:    putfield Field eb m Z
L37:    aload_0
L38:    iconst_0
L39:    putfield Field eb V Z
        .catch java/lang/RuntimeException from L42 to L988 using L989
L42:    iconst_0
L43:    istore 5
L45:    iconst_0
L46:    istore 6
L48:    iconst_0
L49:    istore 7
L51:    iconst_0
L52:    istore 8
L54:    aload_0
L55:    iconst_0
L56:    putfield Field eb n I
L59:    aload_0
L60:    iconst_0
L61:    putfield Field eb r I
L64:    aload_0
L65:    iconst_0
L66:    putfield Field eb D I
L69:    aload_0
L70:    iconst_m1
L71:    putfield Field eb C I
L74:    iconst_0
L75:    istore 9
L77:    iload 16
L79:    ifeq L240
L82:    aload_1
L83:    iload 9
L85:    aaload
L86:    astore 10
L88:    aload 10
L90:    ifnull L237
L93:    aload_0
L94:    dup
L95:    getfield Field eb n I
L98:    aload 10
L100:   getfield Field eb n I
L103:   iadd
L104:   putfield Field eb n I
L107:   aload_0
L108:   dup
L109:   getfield Field eb r I
L112:   aload 10
L114:   getfield Field eb r I
L117:   iadd
L118:   putfield Field eb r I
L121:   aload_0
L122:   dup
L123:   getfield Field eb D I
L126:   aload 10
L128:   getfield Field eb D I
L131:   iadd
L132:   putfield Field eb D I
L135:   iload 5
L137:   aload 10
L139:   getfield Field eb y [I
L142:   ifnonnull L149
L145:   iconst_0
L146:   goto L150
L149:   iconst_1
L150:   ior
L151:   istore 5
L153:   aload 10
L155:   getfield Field eb z [I
L158:   ifnull L169
L161:   iconst_1
L162:   istore 6
L164:   iload 16
L166:   ifeq L201
L169:   aload_0
L170:   getfield Field eb C I
L173:   iconst_m1
L174:   if_icmpne L186
L177:   aload_0
L178:   aload 10
L180:   getfield Field eb C I
L183:   putfield Field eb C I
L186:   aload_0
L187:   getfield Field eb C I
L190:   aload 10
L192:   getfield Field eb C I
L195:   if_icmpeq L201
L198:   iconst_1
L199:   istore 6
L201:   iload 7
L203:   aload 10
L205:   getfield Field eb A [I
L208:   ifnonnull L215
L211:   iconst_0
L212:   goto L216
L215:   iconst_1
L216:   ior
L217:   istore 7
L219:   iload 8
L221:   aload 10
L223:   getfield Field eb B [I
L226:   ifnonnull L233
L229:   iconst_0
L230:   goto L234
L233:   iconst_1
L234:   ior
L235:   istore 8
L237:   iinc 9 1
L240:   iload 9
L242:   iload_3
L243:   if_icmplt L82
L246:   aload_0
L247:   aload_0
L248:   getfield Field eb n I
L251:   newarray int
L253:   putfield Field eb o [I
L256:   aload_0
L257:   aload_0
L258:   getfield Field eb n I
L261:   newarray int
L263:   putfield Field eb p [I
L266:   aload_0
L267:   aload_0
L268:   getfield Field eb n I
L271:   newarray int
L273:   putfield Field eb q [I
L276:   aload_0
L277:   aload_0
L278:   getfield Field eb r I
L281:   newarray int
L283:   putfield Field eb s [I
L286:   aload_0
L287:   aload_0
L288:   getfield Field eb r I
L291:   newarray int
L293:   putfield Field eb t [I
L296:   aload_0
L297:   aload_0
L298:   getfield Field eb r I
L301:   newarray int
L303:   putfield Field eb u [I
L306:   aload_0
L307:   aload_0
L308:   getfield Field eb r I
L311:   newarray int
L313:   putfield Field eb v [I
L316:   aload_0
L317:   aload_0
L318:   getfield Field eb r I
L321:   newarray int
L323:   putfield Field eb w [I
L326:   aload_0
L327:   aload_0
L328:   getfield Field eb r I
L331:   newarray int
L333:   putfield Field eb x [I
L336:   aload_0
L337:   aload_0
L338:   getfield Field eb D I
L341:   newarray int
L343:   putfield Field eb E [I
L346:   aload_0
L347:   aload_0
L348:   getfield Field eb D I
L351:   newarray int
L353:   putfield Field eb F [I
L356:   aload_0
L357:   aload_0
L358:   getfield Field eb D I
L361:   newarray int
L363:   putfield Field eb G [I
L366:   iload 5
L368:   ifeq L381
L371:   aload_0
L372:   aload_0
L373:   getfield Field eb r I
L376:   newarray int
L378:   putfield Field eb y [I
L381:   iload 6
L383:   ifeq L396
L386:   aload_0
L387:   aload_0
L388:   getfield Field eb r I
L391:   newarray int
L393:   putfield Field eb z [I
L396:   iload 7
L398:   ifeq L411
L401:   aload_0
L402:   aload_0
L403:   getfield Field eb r I
L406:   newarray int
L408:   putfield Field eb A [I
L411:   iload 8
L413:   ifeq L426
L416:   aload_0
L417:   aload_0
L418:   getfield Field eb r I
L421:   newarray int
L423:   putfield Field eb B [I
L426:   aload_0
L427:   iconst_0
L428:   putfield Field eb n I
L431:   aload_0
L432:   iconst_0
L433:   putfield Field eb r I
L436:   aload_0
L437:   iconst_0
L438:   putfield Field eb D I
L441:   iload_2
L442:   bipush -31
L444:   if_icmpeq L463
L447:   iconst_1
L448:   istore 10
L450:   iload 16
L452:   ifeq L458
L455:   iinc 10 1
L458:   iload 10
L460:   ifgt L455
L463:   iconst_0
L464:   istore 10
L466:   iload 16
L468:   ifeq L975
L471:   aload_1
L472:   iload 10
L474:   aaload
L475:   astore 11
L477:   aload 11
L479:   ifnull L972
L482:   aload_0
L483:   getfield Field eb n I
L486:   istore 12
L488:   iconst_0
L489:   istore 13
L491:   iload 16
L493:   ifeq L560
L496:   aload_0
L497:   getfield Field eb o [I
L500:   aload_0
L501:   getfield Field eb n I
L504:   aload 11
L506:   getfield Field eb o [I
L509:   iload 13
L511:   iaload
L512:   iastore
L513:   aload_0
L514:   getfield Field eb p [I
L517:   aload_0
L518:   getfield Field eb n I
L521:   aload 11
L523:   getfield Field eb p [I
L526:   iload 13
L528:   iaload
L529:   iastore
L530:   aload_0
L531:   getfield Field eb q [I
L534:   aload_0
L535:   getfield Field eb n I
L538:   aload 11
L540:   getfield Field eb q [I
L543:   iload 13
L545:   iaload
L546:   iastore
L547:   aload_0
L548:   dup
L549:   getfield Field eb n I
L552:   iconst_1
L553:   iadd
L554:   putfield Field eb n I
L557:   iinc 13 1
L560:   iload 13
L562:   aload 11
L564:   getfield Field eb n I
L567:   if_icmplt L496
L570:   iconst_0
L571:   istore 14
L573:   iload 16
L575:   ifeq L871
L578:   aload_0
L579:   getfield Field eb s [I
L582:   aload_0
L583:   getfield Field eb r I
L586:   aload 11
L588:   getfield Field eb s [I
L591:   iload 14
L593:   iaload
L594:   iload 12
L596:   iadd
L597:   iastore
L598:   aload_0
L599:   getfield Field eb t [I
L602:   aload_0
L603:   getfield Field eb r I
L606:   aload 11
L608:   getfield Field eb t [I
L611:   iload 14
L613:   iaload
L614:   iload 12
L616:   iadd
L617:   iastore
L618:   aload_0
L619:   getfield Field eb u [I
L622:   aload_0
L623:   getfield Field eb r I
L626:   aload 11
L628:   getfield Field eb u [I
L631:   iload 14
L633:   iaload
L634:   iload 12
L636:   iadd
L637:   iastore
L638:   aload_0
L639:   getfield Field eb v [I
L642:   aload_0
L643:   getfield Field eb r I
L646:   aload 11
L648:   getfield Field eb v [I
L651:   iload 14
L653:   iaload
L654:   iastore
L655:   aload_0
L656:   getfield Field eb w [I
L659:   aload_0
L660:   getfield Field eb r I
L663:   aload 11
L665:   getfield Field eb w [I
L668:   iload 14
L670:   iaload
L671:   iastore
L672:   aload_0
L673:   getfield Field eb x [I
L676:   aload_0
L677:   getfield Field eb r I
L680:   aload 11
L682:   getfield Field eb x [I
L685:   iload 14
L687:   iaload
L688:   iastore
L689:   iload 5
L691:   ifeq L734
L694:   aload 11
L696:   getfield Field eb y [I
L699:   ifnonnull L717
L702:   aload_0
L703:   getfield Field eb y [I
L706:   aload_0
L707:   getfield Field eb r I
L710:   iconst_0
L711:   iastore
L712:   iload 16
L714:   ifeq L734
L717:   aload_0
L718:   getfield Field eb y [I
L721:   aload_0
L722:   getfield Field eb r I
L725:   aload 11
L727:   getfield Field eb y [I
L730:   iload 14
L732:   iaload
L733:   iastore
L734:   iload 6
L736:   ifeq L783
L739:   aload 11
L741:   getfield Field eb z [I
L744:   ifnonnull L766
L747:   aload_0
L748:   getfield Field eb z [I
L751:   aload_0
L752:   getfield Field eb r I
L755:   aload 11
L757:   getfield Field eb C I
L760:   iastore
L761:   iload 16
L763:   ifeq L783
L766:   aload_0
L767:   getfield Field eb z [I
L770:   aload_0
L771:   getfield Field eb r I
L774:   aload 11
L776:   getfield Field eb z [I
L779:   iload 14
L781:   iaload
L782:   iastore
L783:   iload 7
L785:   ifeq L828
L788:   aload 11
L790:   getfield Field eb A [I
L793:   ifnonnull L811
L796:   aload_0
L797:   getfield Field eb A [I
L800:   aload_0
L801:   getfield Field eb r I
L804:   iconst_0
L805:   iastore
L806:   iload 16
L808:   ifeq L828
L811:   aload_0
L812:   getfield Field eb A [I
L815:   aload_0
L816:   getfield Field eb r I
L819:   aload 11
L821:   getfield Field eb A [I
L824:   iload 14
L826:   iaload
L827:   iastore
L828:   iload 8
L830:   ifeq L858
L833:   aload 11
L835:   getfield Field eb B [I
L838:   ifnull L858
L841:   aload_0
L842:   getfield Field eb B [I
L845:   aload_0
L846:   getfield Field eb r I
L849:   aload 11
L851:   getfield Field eb B [I
L854:   iload 14
L856:   iaload
L857:   iastore
L858:   aload_0
L859:   dup
L860:   getfield Field eb r I
L863:   iconst_1
L864:   iadd
L865:   putfield Field eb r I
L868:   iinc 14 1
L871:   iload 14
L873:   aload 11
L875:   getfield Field eb r I
L878:   if_icmplt L578
L881:   iconst_0
L882:   istore 15
L884:   iload 16
L886:   ifeq L962
L889:   aload_0
L890:   getfield Field eb E [I
L893:   aload_0
L894:   getfield Field eb D I
L897:   aload 11
L899:   getfield Field eb E [I
L902:   iload 15
L904:   iaload
L905:   iload 12
L907:   iadd
L908:   iastore
L909:   aload_0
L910:   getfield Field eb F [I
L913:   aload_0
L914:   getfield Field eb D I
L917:   aload 11
L919:   getfield Field eb F [I
L922:   iload 15
L924:   iaload
L925:   iload 12
L927:   iadd
L928:   iastore
L929:   aload_0
L930:   getfield Field eb G [I
L933:   aload_0
L934:   getfield Field eb D I
L937:   aload 11
L939:   getfield Field eb G [I
L942:   iload 15
L944:   iaload
L945:   iload 12
L947:   iadd
L948:   iastore
L949:   aload_0
L950:   dup
L951:   getfield Field eb D I
L954:   iconst_1
L955:   iadd
L956:   putfield Field eb D I
L959:   iinc 15 1
L962:   iload 15
L964:   aload 11
L966:   getfield Field eb D I
L969:   if_icmplt L889
L972:   iinc 10 1
L975:   iload 10
L977:   iload_3
L978:   if_icmplt L471
L981:   aload_0
L982:   sipush 2992
L985:   invokevirtual Method eb a (I)V
L988:   return
L989:   astore 5
L991:   new java/lang/StringBuffer
L994:   dup
L995:   ldc "4659, "
L997:   invokespecial Method java/lang/StringBuffer <init> (Ljava/lang/String;)V
L1000:  aload_1
L1001:  invokevirtual Method java/lang/StringBuffer append (Ljava/lang/Object;)Ljava/lang/StringBuffer;
L1004:  ldc ", "
L1006:  invokevirtual Method java/lang/StringBuffer append (Ljava/lang/String;)Ljava/lang/StringBuffer;
L1009:  iload_2
L1010:  invokevirtual Method java/lang/StringBuffer append (I)Ljava/lang/StringBuffer;
L1013:  ldc ", "
L1015:  invokevirtual Method java/lang/StringBuffer append (Ljava/lang/String;)Ljava/lang/StringBuffer;
L1018:  iload_3
L1019:  invokevirtual Method java/lang/StringBuffer append (I)Ljava/lang/StringBuffer;
L1022:  ldc ", "
L1024:  invokevirtual Method java/lang/StringBuffer append (Ljava/lang/String;)Ljava/lang/StringBuffer;
L1027:  iload 4
L1029:  invokevirtual Method java/lang/StringBuffer append (Z)Ljava/lang/StringBuffer;
L1032:  ldc ", "
L1034:  invokevirtual Method java/lang/StringBuffer append (Ljava/lang/String;)Ljava/lang/StringBuffer;
L1037:  aload 5
L1039:  invokevirtual Method java/lang/Throwable toString ()Ljava/lang/String;
L1042:  invokevirtual Method java/lang/StringBuffer append (Ljava/lang/String;)Ljava/lang/StringBuffer;
L1045:  invokevirtual Method java/lang/StringBuffer toString ()Ljava/lang/String;
L1048:  invokestatic Method sign/signlink reporterror (Ljava/lang/String;)V
L1051:  new java/lang/RuntimeException
L1054:  dup
L1055:  invokespecial Method java/lang/RuntimeException <init> ()V
L1058:  athrow
L1059:  
    .end code
.end method

.method public <init> : (Leb;ZZIZ)V
    .code stack 5 locals 8
L0:     getstatic Field eb Rb Z
L3:     istore 7
L5:     aload_0
L6:     invokespecial Method db <init> ()V
L9:     aload_0
L10:    ldc 45861
L12:    putfield Field eb i I
L15:    aload_0
L16:    bipush 47
L18:    putfield Field eb j B
L21:    aload_0
L22:    bipush 47
L24:    putfield Field eb k B
L27:    aload_0
L28:    iconst_5
L29:    putfield Field eb l I
L32:    aload_0
L33:    iconst_0
L34:    putfield Field eb m Z
L37:    aload_0
L38:    iconst_0
L39:    putfield Field eb V Z
        .catch java/lang/RuntimeException from L42 to L459 using L460
L42:    aload_0
L43:    aload_1
L44:    getfield Field eb n I
L47:    putfield Field eb n I
L50:    aload_0
L51:    aload_1
L52:    getfield Field eb r I
L55:    putfield Field eb r I
L58:    aload_0
L59:    aload_1
L60:    getfield Field eb D I
L63:    putfield Field eb D I
L66:    iload 5
L68:    ifeq L100
L71:    aload_0
L72:    aload_1
L73:    getfield Field eb o [I
L76:    putfield Field eb o [I
L79:    aload_0
L80:    aload_1
L81:    getfield Field eb p [I
L84:    putfield Field eb p [I
L87:    aload_0
L88:    aload_1
L89:    getfield Field eb q [I
L92:    putfield Field eb q [I
L95:    iload 7
L97:    ifeq L192
L100:   aload_0
L101:   aload_0
L102:   getfield Field eb n I
L105:   newarray int
L107:   putfield Field eb o [I
L110:   aload_0
L111:   aload_0
L112:   getfield Field eb n I
L115:   newarray int
L117:   putfield Field eb p [I
L120:   aload_0
L121:   aload_0
L122:   getfield Field eb n I
L125:   newarray int
L127:   putfield Field eb q [I
L130:   iconst_0
L131:   istore 6
L133:   iload 7
L135:   ifeq L183
L138:   aload_0
L139:   getfield Field eb o [I
L142:   iload 6
L144:   aload_1
L145:   getfield Field eb o [I
L148:   iload 6
L150:   iaload
L151:   iastore
L152:   aload_0
L153:   getfield Field eb p [I
L156:   iload 6
L158:   aload_1
L159:   getfield Field eb p [I
L162:   iload 6
L164:   iaload
L165:   iastore
L166:   aload_0
L167:   getfield Field eb q [I
L170:   iload 6
L172:   aload_1
L173:   getfield Field eb q [I
L176:   iload 6
L178:   iaload
L179:   iastore
L180:   iinc 6 1
L183:   iload 6
L185:   aload_0
L186:   getfield Field eb n I
L189:   if_icmplt L138
L192:   iload_2
L193:   ifeq L209
L196:   aload_0
L197:   aload_1
L198:   getfield Field eb B [I
L201:   putfield Field eb B [I
L204:   iload 7
L206:   ifeq L253
L209:   aload_0
L210:   aload_0
L211:   getfield Field eb r I
L214:   newarray int
L216:   putfield Field eb B [I
L219:   iconst_0
L220:   istore 6
L222:   iload 7
L224:   ifeq L244
L227:   aload_0
L228:   getfield Field eb B [I
L231:   iload 6
L233:   aload_1
L234:   getfield Field eb B [I
L237:   iload 6
L239:   iaload
L240:   iastore
L241:   iinc 6 1
L244:   iload 6
L246:   aload_0
L247:   getfield Field eb r I
L250:   if_icmplt L227
L253:   iload_3
L254:   ifeq L270
L257:   aload_0
L258:   aload_1
L259:   getfield Field eb A [I
L262:   putfield Field eb A [I
L265:   iload 7
L267:   ifeq L352
L270:   aload_0
L271:   aload_0
L272:   getfield Field eb r I
L275:   newarray int
L277:   putfield Field eb A [I
L280:   aload_1
L281:   getfield Field eb A [I
L284:   ifnonnull L318
L287:   iconst_0
L288:   istore 6
L290:   iload 7
L292:   ifeq L306
L295:   aload_0
L296:   getfield Field eb A [I
L299:   iload 6
L301:   iconst_0
L302:   iastore
L303:   iinc 6 1
L306:   iload 6
L308:   aload_0
L309:   getfield Field eb r I
L312:   if_icmplt L295
L315:   goto L352
L318:   iconst_0
L319:   istore 6
L321:   iload 7
L323:   ifeq L343
L326:   aload_0
L327:   getfield Field eb A [I
L330:   iload 6
L332:   aload_1
L333:   getfield Field eb A [I
L336:   iload 6
L338:   iaload
L339:   iastore
L340:   iinc 6 1
L343:   iload 6
L345:   aload_0
L346:   getfield Field eb r I
L349:   if_icmplt L326
L352:   aload_0
L353:   aload_1
L354:   getfield Field eb R [I
L357:   putfield Field eb R [I
L360:   aload_0
L361:   aload_1
L362:   getfield Field eb S [I
L365:   putfield Field eb S [I
L368:   aload_0
L369:   aload_1
L370:   getfield Field eb y [I
L373:   putfield Field eb y [I
L376:   iload 4
L378:   ifeq L395
L381:   getstatic Field eb h Z
L384:   ifeq L391
L387:   iconst_0
L388:   goto L392
L391:   iconst_1
L392:   putstatic Field eb h Z
L395:   aload_0
L396:   aload_1
L397:   getfield Field eb s [I
L400:   putfield Field eb s [I
L403:   aload_0
L404:   aload_1
L405:   getfield Field eb t [I
L408:   putfield Field eb t [I
L411:   aload_0
L412:   aload_1
L413:   getfield Field eb u [I
L416:   putfield Field eb u [I
L419:   aload_0
L420:   aload_1
L421:   getfield Field eb z [I
L424:   putfield Field eb z [I
L427:   aload_0
L428:   aload_1
L429:   getfield Field eb C I
L432:   putfield Field eb C I
L435:   aload_0
L436:   aload_1
L437:   getfield Field eb E [I
L440:   putfield Field eb E [I
L443:   aload_0
L444:   aload_1
L445:   getfield Field eb F [I
L448:   putfield Field eb F [I
L451:   aload_0
L452:   aload_1
L453:   getfield Field eb G [I
L456:   putfield Field eb G [I
L459:   return
L460:   astore 6
L462:   new java/lang/StringBuffer
L465:   dup
L466:   ldc "52705, "
L468:   invokespecial Method java/lang/StringBuffer <init> (Ljava/lang/String;)V
L471:   aload_1
L472:   invokevirtual Method java/lang/StringBuffer append (Ljava/lang/Object;)Ljava/lang/StringBuffer;
L475:   ldc ", "
L477:   invokevirtual Method java/lang/StringBuffer append (Ljava/lang/String;)Ljava/lang/StringBuffer;
L480:   iload_2
L481:   invokevirtual Method java/lang/StringBuffer append (Z)Ljava/lang/StringBuffer;
L484:   ldc ", "
L486:   invokevirtual Method java/lang/StringBuffer append (Ljava/lang/String;)Ljava/lang/StringBuffer;
L489:   iload_3
L490:   invokevirtual Method java/lang/StringBuffer append (Z)Ljava/lang/StringBuffer;
L493:   ldc ", "
L495:   invokevirtual Method java/lang/StringBuffer append (Ljava/lang/String;)Ljava/lang/StringBuffer;
L498:   iload 4
L500:   invokevirtual Method java/lang/StringBuffer append (I)Ljava/lang/StringBuffer;
L503:   ldc ", "
L505:   invokevirtual Method java/lang/StringBuffer append (Ljava/lang/String;)Ljava/lang/StringBuffer;
L508:   iload 5
L510:   invokevirtual Method java/lang/StringBuffer append (Z)Ljava/lang/StringBuffer;
L513:   ldc ", "
L515:   invokevirtual Method java/lang/StringBuffer append (Ljava/lang/String;)Ljava/lang/StringBuffer;
L518:   aload 6
L520:   invokevirtual Method java/lang/Throwable toString ()Ljava/lang/String;
L523:   invokevirtual Method java/lang/StringBuffer append (Ljava/lang/String;)Ljava/lang/StringBuffer;
L526:   invokevirtual Method java/lang/StringBuffer toString ()Ljava/lang/String;
L529:   invokestatic Method sign/signlink reporterror (Ljava/lang/String;)V
L532:   new java/lang/RuntimeException
L535:   dup
L536:   invokespecial Method java/lang/RuntimeException <init> ()V
L539:   athrow
L540:   
    .end code
.end method

.method public <init> : (Leb;BZZ)V
    .code stack 5 locals 10
L0:     getstatic Field eb Rb Z
L3:     istore 9
L5:     aload_0
L6:     invokespecial Method db <init> ()V
L9:     aload_0
L10:    ldc 45861
L12:    putfield Field eb i I
L15:    aload_0
L16:    bipush 47
L18:    putfield Field eb j B
L21:    aload_0
L22:    bipush 47
L24:    putfield Field eb k B
L27:    aload_0
L28:    iconst_5
L29:    putfield Field eb l I
L32:    aload_0
L33:    iconst_0
L34:    putfield Field eb m Z
L37:    aload_0
L38:    iconst_0
L39:    putfield Field eb V Z
        .catch java/lang/RuntimeException from L42 to L628 using L629
L42:    aload_0
L43:    aload_1
L44:    getfield Field eb n I
L47:    putfield Field eb n I
L50:    aload_0
L51:    aload_1
L52:    getfield Field eb r I
L55:    putfield Field eb r I
L58:    aload_0
L59:    aload_1
L60:    getfield Field eb D I
L63:    putfield Field eb D I
L66:    iload_3
L67:    ifeq L117
L70:    aload_0
L71:    aload_0
L72:    getfield Field eb n I
L75:    newarray int
L77:    putfield Field eb p [I
L80:    iconst_0
L81:    istore 5
L83:    iload 9
L85:    ifeq L105
L88:    aload_0
L89:    getfield Field eb p [I
L92:    iload 5
L94:    aload_1
L95:    getfield Field eb p [I
L98:    iload 5
L100:   iaload
L101:   iastore
L102:   iinc 5 1
L105:   iload 5
L107:   aload_0
L108:   getfield Field eb n I
L111:   if_icmplt L88
L114:   goto L125
L117:   aload_0
L118:   aload_1
L119:   getfield Field eb p [I
L122:   putfield Field eb p [I
L125:   iload 4
L127:   ifeq L414
L130:   aload_0
L131:   aload_0
L132:   getfield Field eb r I
L135:   newarray int
L137:   putfield Field eb v [I
L140:   aload_0
L141:   aload_0
L142:   getfield Field eb r I
L145:   newarray int
L147:   putfield Field eb w [I
L150:   aload_0
L151:   aload_0
L152:   getfield Field eb r I
L155:   newarray int
L157:   putfield Field eb x [I
L160:   iconst_0
L161:   istore 5
L163:   iload 9
L165:   ifeq L213
L168:   aload_0
L169:   getfield Field eb v [I
L172:   iload 5
L174:   aload_1
L175:   getfield Field eb v [I
L178:   iload 5
L180:   iaload
L181:   iastore
L182:   aload_0
L183:   getfield Field eb w [I
L186:   iload 5
L188:   aload_1
L189:   getfield Field eb w [I
L192:   iload 5
L194:   iaload
L195:   iastore
L196:   aload_0
L197:   getfield Field eb x [I
L200:   iload 5
L202:   aload_1
L203:   getfield Field eb x [I
L206:   iload 5
L208:   iaload
L209:   iastore
L210:   iinc 5 1
L213:   iload 5
L215:   aload_0
L216:   getfield Field eb r I
L219:   if_icmplt L168
L222:   aload_0
L223:   aload_0
L224:   getfield Field eb r I
L227:   newarray int
L229:   putfield Field eb y [I
L232:   aload_1
L233:   getfield Field eb y [I
L236:   ifnonnull L270
L239:   iconst_0
L240:   istore 6
L242:   iload 9
L244:   ifeq L258
L247:   aload_0
L248:   getfield Field eb y [I
L251:   iload 6
L253:   iconst_0
L254:   iastore
L255:   iinc 6 1
L258:   iload 6
L260:   aload_0
L261:   getfield Field eb r I
L264:   if_icmplt L247
L267:   goto L304
L270:   iconst_0
L271:   istore 6
L273:   iload 9
L275:   ifeq L295
L278:   aload_0
L279:   getfield Field eb y [I
L282:   iload 6
L284:   aload_1
L285:   getfield Field eb y [I
L288:   iload 6
L290:   iaload
L291:   iastore
L292:   iinc 6 1
L295:   iload 6
L297:   aload_0
L298:   getfield Field eb r I
L301:   if_icmplt L278
L304:   aload_0
L305:   aload_0
L306:   getfield Field eb n I
L309:   anewarray n
L312:   putfield Field eb W [Ln;
L315:   iconst_0
L316:   istore 6
L318:   iload 9
L320:   ifeq L392
L323:   aload_0
L324:   getfield Field eb W [Ln;
L327:   iload 6
L329:   new n
L332:   dup
L333:   invokespecial Method n <init> ()V
L336:   dup_x2
L337:   aastore
L338:   astore 7
L340:   aload_1
L341:   getfield Field eb W [Ln;
L344:   iload 6
L346:   aaload
L347:   astore 8
L349:   aload 7
L351:   aload 8
L353:   getfield Field n a I
L356:   putfield Field n a I
L359:   aload 7
L361:   aload 8
L363:   getfield Field n b I
L366:   putfield Field n b I
L369:   aload 7
L371:   aload 8
L373:   getfield Field n c I
L376:   putfield Field n c I
L379:   aload 7
L381:   aload 8
L383:   getfield Field n d I
L386:   putfield Field n d I
L389:   iinc 6 1
L392:   iload 6
L394:   aload_0
L395:   getfield Field eb n I
L398:   if_icmplt L323
L401:   aload_0
L402:   aload_1
L403:   getfield Field eb X [Ln;
L406:   putfield Field eb X [Ln;
L409:   iload 9
L411:   ifeq L446
L414:   aload_0
L415:   aload_1
L416:   getfield Field eb v [I
L419:   putfield Field eb v [I
L422:   aload_0
L423:   aload_1
L424:   getfield Field eb w [I
L427:   putfield Field eb w [I
L430:   aload_0
L431:   aload_1
L432:   getfield Field eb x [I
L435:   putfield Field eb x [I
L438:   aload_0
L439:   aload_1
L440:   getfield Field eb y [I
L443:   putfield Field eb y [I
L446:   aload_0
L447:   aload_1
L448:   getfield Field eb o [I
L451:   putfield Field eb o [I
L454:   aload_0
L455:   aload_1
L456:   getfield Field eb q [I
L459:   putfield Field eb q [I
L462:   aload_0
L463:   aload_1
L464:   getfield Field eb B [I
L467:   putfield Field eb B [I
L470:   aload_0
L471:   aload_1
L472:   getfield Field eb A [I
L475:   putfield Field eb A [I
L478:   aload_0
L479:   aload_1
L480:   getfield Field eb z [I
L483:   putfield Field eb z [I
L486:   aload_0
L487:   aload_1
L488:   getfield Field eb C I
L491:   putfield Field eb C I
L494:   aload_0
L495:   aload_1
L496:   getfield Field eb s [I
L499:   putfield Field eb s [I
L502:   aload_0
L503:   aload_1
L504:   getfield Field eb t [I
L507:   putfield Field eb t [I
L510:   aload_0
L511:   aload_1
L512:   getfield Field eb u [I
L515:   putfield Field eb u [I
L518:   aload_0
L519:   aload_1
L520:   getfield Field eb E [I
L523:   putfield Field eb E [I
L526:   aload_0
L527:   aload_1
L528:   getfield Field eb F [I
L531:   putfield Field eb F [I
L534:   aload_0
L535:   aload_1
L536:   getfield Field eb G [I
L539:   putfield Field eb G [I
L542:   iload_2
L543:   bipush -31
L545:   if_icmpeq L556
L548:   new java/lang/NullPointerException
L551:   dup
L552:   invokespecial Method java/lang/NullPointerException <init> ()V
L555:   athrow
L556:   aload_0
L557:   aload_1
L558:   getfield Field eb M I
L561:   putfield Field eb M I
L564:   aload_0
L565:   aload_1
L566:   getfield Field eb N I
L569:   putfield Field eb N I
L572:   aload_0
L573:   aload_1
L574:   getfield Field eb L I
L577:   putfield Field eb L I
L580:   aload_0
L581:   aload_1
L582:   getfield Field eb P I
L585:   putfield Field eb P I
L588:   aload_0
L589:   aload_1
L590:   getfield Field eb O I
L593:   putfield Field eb O I
L596:   aload_0
L597:   aload_1
L598:   getfield Field eb H I
L601:   putfield Field eb H I
L604:   aload_0
L605:   aload_1
L606:   getfield Field eb J I
L609:   putfield Field eb J I
L612:   aload_0
L613:   aload_1
L614:   getfield Field eb K I
L617:   putfield Field eb K I
L620:   aload_0
L621:   aload_1
L622:   getfield Field eb I I
L625:   putfield Field eb I I
L628:   return
L629:   astore 5
L631:   new java/lang/StringBuffer
L634:   dup
L635:   ldc "38920, "
L637:   invokespecial Method java/lang/StringBuffer <init> (Ljava/lang/String;)V
L640:   aload_1
L641:   invokevirtual Method java/lang/StringBuffer append (Ljava/lang/Object;)Ljava/lang/StringBuffer;
L644:   ldc ", "
L646:   invokevirtual Method java/lang/StringBuffer append (Ljava/lang/String;)Ljava/lang/StringBuffer;
L649:   iload_2
L650:   invokevirtual Method java/lang/StringBuffer append (I)Ljava/lang/StringBuffer;
L653:   ldc ", "
L655:   invokevirtual Method java/lang/StringBuffer append (Ljava/lang/String;)Ljava/lang/StringBuffer;
L658:   iload_3
L659:   invokevirtual Method java/lang/StringBuffer append (Z)Ljava/lang/StringBuffer;
L662:   ldc ", "
L664:   invokevirtual Method java/lang/StringBuffer append (Ljava/lang/String;)Ljava/lang/StringBuffer;
L667:   iload 4
L669:   invokevirtual Method java/lang/StringBuffer append (Z)Ljava/lang/StringBuffer;
L672:   ldc ", "
L674:   invokevirtual Method java/lang/StringBuffer append (Ljava/lang/String;)Ljava/lang/StringBuffer;
L677:   aload 5
L679:   invokevirtual Method java/lang/Throwable toString ()Ljava/lang/String;
L682:   invokevirtual Method java/lang/StringBuffer append (Ljava/lang/String;)Ljava/lang/StringBuffer;
L685:   invokevirtual Method java/lang/StringBuffer toString ()Ljava/lang/String;
L688:   invokestatic Method sign/signlink reporterror (Ljava/lang/String;)V
L691:   new java/lang/RuntimeException
L694:   dup
L695:   invokespecial Method java/lang/RuntimeException <init> ()V
L698:   athrow
L699:   
    .end code
.end method

.method public <init> : (ILeb;Z)V
    .code stack 5 locals 7
L0:     getstatic Field eb Rb Z
L3:     istore 6
L5:     aload_0
L6:     invokespecial Method db <init> ()V
L9:     aload_0
L10:    ldc 45861
L12:    putfield Field eb i I
L15:    aload_0
L16:    bipush 47
L18:    putfield Field eb j B
L21:    aload_0
L22:    bipush 47
L24:    putfield Field eb k B
L27:    aload_0
L28:    iconst_5
L29:    putfield Field eb l I
L32:    aload_0
L33:    iconst_0
L34:    putfield Field eb m Z
L37:    aload_0
L38:    iconst_0
L39:    putfield Field eb V Z
        .catch java/lang/RuntimeException from L42 to L388 using L389
L42:    aload_0
L43:    aload_2
L44:    getfield Field eb n I
L47:    putfield Field eb n I
L50:    aload_0
L51:    aload_2
L52:    getfield Field eb r I
L55:    putfield Field eb r I
L58:    aload_0
L59:    aload_2
L60:    getfield Field eb D I
L63:    putfield Field eb D I
L66:    aload_0
L67:    aload_0
L68:    getfield Field eb n I
L71:    newarray int
L73:    putfield Field eb o [I
L76:    aload_0
L77:    aload_0
L78:    getfield Field eb n I
L81:    newarray int
L83:    putfield Field eb p [I
L86:    aload_0
L87:    aload_0
L88:    getfield Field eb n I
L91:    newarray int
L93:    putfield Field eb q [I
L96:    iconst_0
L97:    istore 4
L99:    iload 6
L101:   ifeq L149
L104:   aload_0
L105:   getfield Field eb o [I
L108:   iload 4
L110:   aload_2
L111:   getfield Field eb o [I
L114:   iload 4
L116:   iaload
L117:   iastore
L118:   aload_0
L119:   getfield Field eb p [I
L122:   iload 4
L124:   aload_2
L125:   getfield Field eb p [I
L128:   iload 4
L130:   iaload
L131:   iastore
L132:   aload_0
L133:   getfield Field eb q [I
L136:   iload 4
L138:   aload_2
L139:   getfield Field eb q [I
L142:   iload 4
L144:   iaload
L145:   iastore
L146:   iinc 4 1
L149:   iload 4
L151:   aload_0
L152:   getfield Field eb n I
L155:   if_icmplt L104
L158:   iload_3
L159:   ifeq L175
L162:   aload_0
L163:   aload_2
L164:   getfield Field eb A [I
L167:   putfield Field eb A [I
L170:   iload 6
L172:   ifeq L257
L175:   aload_0
L176:   aload_0
L177:   getfield Field eb r I
L180:   newarray int
L182:   putfield Field eb A [I
L185:   aload_2
L186:   getfield Field eb A [I
L189:   ifnonnull L223
L192:   iconst_0
L193:   istore 5
L195:   iload 6
L197:   ifeq L211
L200:   aload_0
L201:   getfield Field eb A [I
L204:   iload 5
L206:   iconst_0
L207:   iastore
L208:   iinc 5 1
L211:   iload 5
L213:   aload_0
L214:   getfield Field eb r I
L217:   if_icmplt L200
L220:   goto L257
L223:   iconst_0
L224:   istore 5
L226:   iload 6
L228:   ifeq L248
L231:   aload_0
L232:   getfield Field eb A [I
L235:   iload 5
L237:   aload_2
L238:   getfield Field eb A [I
L241:   iload 5
L243:   iaload
L244:   iastore
L245:   iinc 5 1
L248:   iload 5
L250:   aload_0
L251:   getfield Field eb r I
L254:   if_icmplt L231
L257:   aload_0
L258:   aload_2
L259:   getfield Field eb y [I
L262:   putfield Field eb y [I
L265:   aload_0
L266:   aload_2
L267:   getfield Field eb B [I
L270:   putfield Field eb B [I
L273:   aload_0
L274:   aload_2
L275:   getfield Field eb z [I
L278:   putfield Field eb z [I
L281:   iload_1
L282:   ifeq L292
L285:   aload_0
L286:   sipush 213
L289:   putfield Field eb l I
L292:   aload_0
L293:   aload_2
L294:   getfield Field eb C I
L297:   putfield Field eb C I
L300:   aload_0
L301:   aload_2
L302:   getfield Field eb U [[I
L305:   putfield Field eb U [[I
L308:   aload_0
L309:   aload_2
L310:   getfield Field eb T [[I
L313:   putfield Field eb T [[I
L316:   aload_0
L317:   aload_2
L318:   getfield Field eb s [I
L321:   putfield Field eb s [I
L324:   aload_0
L325:   aload_2
L326:   getfield Field eb t [I
L329:   putfield Field eb t [I
L332:   aload_0
L333:   aload_2
L334:   getfield Field eb u [I
L337:   putfield Field eb u [I
L340:   aload_0
L341:   aload_2
L342:   getfield Field eb v [I
L345:   putfield Field eb v [I
L348:   aload_0
L349:   aload_2
L350:   getfield Field eb w [I
L353:   putfield Field eb w [I
L356:   aload_0
L357:   aload_2
L358:   getfield Field eb x [I
L361:   putfield Field eb x [I
L364:   aload_0
L365:   aload_2
L366:   getfield Field eb E [I
L369:   putfield Field eb E [I
L372:   aload_0
L373:   aload_2
L374:   getfield Field eb F [I
L377:   putfield Field eb F [I
L380:   aload_0
L381:   aload_2
L382:   getfield Field eb G [I
L385:   putfield Field eb G [I
L388:   return
L389:   astore 4
L391:   new java/lang/StringBuffer
L394:   dup
L395:   ldc "94709, "
L397:   invokespecial Method java/lang/StringBuffer <init> (Ljava/lang/String;)V
L400:   iload_1
L401:   invokevirtual Method java/lang/StringBuffer append (I)Ljava/lang/StringBuffer;
L404:   ldc ", "
L406:   invokevirtual Method java/lang/StringBuffer append (Ljava/lang/String;)Ljava/lang/StringBuffer;
L409:   aload_2
L410:   invokevirtual Method java/lang/StringBuffer append (Ljava/lang/Object;)Ljava/lang/StringBuffer;
L413:   ldc ", "
L415:   invokevirtual Method java/lang/StringBuffer append (Ljava/lang/String;)Ljava/lang/StringBuffer;
L418:   iload_3
L419:   invokevirtual Method java/lang/StringBuffer append (Z)Ljava/lang/StringBuffer;
L422:   ldc ", "
L424:   invokevirtual Method java/lang/StringBuffer append (Ljava/lang/String;)Ljava/lang/StringBuffer;
L427:   aload 4
L429:   invokevirtual Method java/lang/Throwable toString ()Ljava/lang/String;
L432:   invokevirtual Method java/lang/StringBuffer append (Ljava/lang/String;)Ljava/lang/StringBuffer;
L435:   invokevirtual Method java/lang/StringBuffer toString ()Ljava/lang/String;
L438:   invokestatic Method sign/signlink reporterror (Ljava/lang/String;)V
L441:   new java/lang/RuntimeException
L444:   dup
L445:   invokespecial Method java/lang/RuntimeException <init> ()V
L448:   athrow
L449:   
    .end code
.end method

.method private final a : (Leb;I)I
    .code stack 5 locals 9
L0:     getstatic Field eb Rb Z
L3:     istore 8
L5:     iconst_m1
L6:     istore_3
L7:     aload_1
L8:     getfield Field eb o [I
L11:    iload_2
L12:    iaload
L13:    istore 4
L15:    aload_1
L16:    getfield Field eb p [I
L19:    iload_2
L20:    iaload
L21:    istore 5
L23:    aload_1
L24:    getfield Field eb q [I
L27:    iload_2
L28:    iaload
L29:    istore 6
L31:    iconst_0
L32:    istore 7
L34:    iload 8
L36:    ifeq L86
L39:    iload 4
L41:    aload_0
L42:    getfield Field eb o [I
L45:    iload 7
L47:    iaload
L48:    if_icmpne L83
L51:    iload 5
L53:    aload_0
L54:    getfield Field eb p [I
L57:    iload 7
L59:    iaload
L60:    if_icmpne L83
L63:    iload 6
L65:    aload_0
L66:    getfield Field eb q [I
L69:    iload 7
L71:    iaload
L72:    if_icmpne L83
L75:    iload 7
L77:    istore_3
L78:    iload 8
L80:    ifeq L95
L83:    iinc 7 1
L86:    iload 7
L88:    aload_0
L89:    getfield Field eb n I
L92:    if_icmplt L39
L95:    iload_3
L96:    iconst_m1
L97:    if_icmpne L167
L100:   aload_0
L101:   getfield Field eb o [I
L104:   aload_0
L105:   getfield Field eb n I
L108:   iload 4
L110:   iastore
L111:   aload_0
L112:   getfield Field eb p [I
L115:   aload_0
L116:   getfield Field eb n I
L119:   iload 5
L121:   iastore
L122:   aload_0
L123:   getfield Field eb q [I
L126:   aload_0
L127:   getfield Field eb n I
L130:   iload 6
L132:   iastore
L133:   aload_1
L134:   getfield Field eb R [I
L137:   ifnull L155
L140:   aload_0
L141:   getfield Field eb R [I
L144:   aload_0
L145:   getfield Field eb n I
L148:   aload_1
L149:   getfield Field eb R [I
L152:   iload_2
L153:   iaload
L154:   iastore
L155:   aload_0
L156:   dup
L157:   getfield Field eb n I
L160:   dup_x1
L161:   iconst_1
L162:   iadd
L163:   putfield Field eb n I
L166:   istore_3
L167:   iload_3
L168:   ireturn
L169:   
    .end code
.end method

.method public a : (I)V
    .code stack 7 locals 7
        .catch java/lang/RuntimeException from L0 to L209 using L210
L0:     aload_0
L1:     iconst_0
L2:     putfield Field eb M I
L5:     iload_1
L6:     sipush 2992
L9:     if_icmpeq L13
L12:    return
L13:    aload_0
L14:    iconst_0
L15:    putfield Field eb L I
L18:    aload_0
L19:    iconst_0
L20:    putfield Field eb N I
L23:    iconst_0
L24:    istore_2
L25:    getstatic Field eb Rb Z
L28:    ifeq L115
L31:    aload_0
L32:    getfield Field eb o [I
L35:    iload_2
L36:    iaload
L37:    istore_3
L38:    aload_0
L39:    getfield Field eb p [I
L42:    iload_2
L43:    iaload
L44:    istore 4
L46:    aload_0
L47:    getfield Field eb q [I
L50:    iload_2
L51:    iaload
L52:    istore 5
L54:    iload 4
L56:    ineg
L57:    aload_0
L58:    getfield Field eb M I
L61:    if_icmple L71
L64:    aload_0
L65:    iload 4
L67:    ineg
L68:    putfield Field eb M I
L71:    iload 4
L73:    aload_0
L74:    getfield Field eb N I
L77:    if_icmple L86
L80:    aload_0
L81:    iload 4
L83:    putfield Field eb N I
L86:    iload_3
L87:    iload_3
L88:    imul
L89:    iload 5
L91:    iload 5
L93:    imul
L94:    iadd
L95:    istore 6
L97:    iload 6
L99:    aload_0
L100:   getfield Field eb L I
L103:   if_icmple L112
L106:   aload_0
L107:   iload 6
L109:   putfield Field eb L I
L112:   iinc 2 1
L115:   iload_2
L116:   aload_0
L117:   getfield Field eb n I
L120:   if_icmplt L31
L123:   aload_0
L124:   aload_0
L125:   getfield Field eb L I
L128:   i2d
L129:   invokestatic Method java/lang/Math sqrt (D)D
L132:   ldc2_w 9.9e-1
L135:   dadd
L136:   d2i
L137:   putfield Field eb L I
L140:   aload_0
L141:   aload_0
L142:   getfield Field eb L I
L145:   aload_0
L146:   getfield Field eb L I
L149:   imul
L150:   aload_0
L151:   getfield Field eb M I
L154:   aload_0
L155:   getfield Field eb M I
L158:   imul
L159:   iadd
L160:   i2d
L161:   invokestatic Method java/lang/Math sqrt (D)D
L164:   ldc2_w 9.9e-1
L167:   dadd
L168:   d2i
L169:   putfield Field eb P I
L172:   aload_0
L173:   aload_0
L174:   getfield Field eb P I
L177:   aload_0
L178:   getfield Field eb L I
L181:   aload_0
L182:   getfield Field eb L I
L185:   imul
L186:   aload_0
L187:   getfield Field eb N I
L190:   aload_0
L191:   getfield Field eb N I
L194:   imul
L195:   iadd
L196:   i2d
L197:   invokestatic Method java/lang/Math sqrt (D)D
L200:   ldc2_w 9.9e-1
L203:   dadd
L204:   d2i
L205:   iadd
L206:   putfield Field eb O I
L209:   return
L210:   astore_2
L211:   new java/lang/StringBuffer
L214:   dup
L215:   ldc "64225, "
L217:   invokespecial Method java/lang/StringBuffer <init> (Ljava/lang/String;)V
L220:   iload_1
L221:   invokevirtual Method java/lang/StringBuffer append (I)Ljava/lang/StringBuffer;
L224:   ldc ", "
L226:   invokevirtual Method java/lang/StringBuffer append (Ljava/lang/String;)Ljava/lang/StringBuffer;
L229:   aload_2
L230:   invokevirtual Method java/lang/Throwable toString ()Ljava/lang/String;
L233:   invokevirtual Method java/lang/StringBuffer append (Ljava/lang/String;)Ljava/lang/StringBuffer;
L236:   invokevirtual Method java/lang/StringBuffer toString ()Ljava/lang/String;
L239:   invokestatic Method sign/signlink reporterror (Ljava/lang/String;)V
L242:   new java/lang/RuntimeException
L245:   dup
L246:   invokespecial Method java/lang/RuntimeException <init> ()V
L249:   athrow
L250:   
    .end code
.end method

.method public b : (I)V
    .code stack 7 locals 5
L0:     getstatic Field eb Rb Z
L3:     istore 4
        .catch java/lang/RuntimeException from L5 to L155 using L156
L5:     aload_0
L6:     iconst_0
L7:     putfield Field eb M I
L10:    iload_1
L11:    ifeq L28
L14:    iconst_1
L15:    istore_2
L16:    iload 4
L18:    ifeq L24
L21:    iinc 2 1
L24:    iload_2
L25:    ifgt L21
L28:    aload_0
L29:    iconst_0
L30:    putfield Field eb N I
L33:    iconst_0
L34:    istore_2
L35:    iload 4
L37:    ifeq L78
L40:    aload_0
L41:    getfield Field eb p [I
L44:    iload_2
L45:    iaload
L46:    istore_3
L47:    iload_3
L48:    ineg
L49:    aload_0
L50:    getfield Field eb M I
L53:    if_icmple L62
L56:    aload_0
L57:    iload_3
L58:    ineg
L59:    putfield Field eb M I
L62:    iload_3
L63:    aload_0
L64:    getfield Field eb N I
L67:    if_icmple L75
L70:    aload_0
L71:    iload_3
L72:    putfield Field eb N I
L75:    iinc 2 1
L78:    iload_2
L79:    aload_0
L80:    getfield Field eb n I
L83:    if_icmplt L40
L86:    aload_0
L87:    aload_0
L88:    getfield Field eb L I
L91:    aload_0
L92:    getfield Field eb L I
L95:    imul
L96:    aload_0
L97:    getfield Field eb M I
L100:   aload_0
L101:   getfield Field eb M I
L104:   imul
L105:   iadd
L106:   i2d
L107:   invokestatic Method java/lang/Math sqrt (D)D
L110:   ldc2_w 9.9e-1
L113:   dadd
L114:   d2i
L115:   putfield Field eb P I
L118:   aload_0
L119:   aload_0
L120:   getfield Field eb P I
L123:   aload_0
L124:   getfield Field eb L I
L127:   aload_0
L128:   getfield Field eb L I
L131:   imul
L132:   aload_0
L133:   getfield Field eb N I
L136:   aload_0
L137:   getfield Field eb N I
L140:   imul
L141:   iadd
L142:   i2d
L143:   invokestatic Method java/lang/Math sqrt (D)D
L146:   ldc2_w 9.9e-1
L149:   dadd
L150:   d2i
L151:   iadd
L152:   putfield Field eb O I
L155:   return
L156:   astore_2
L157:   new java/lang/StringBuffer
L160:   dup
L161:   ldc "27954, "
L163:   invokespecial Method java/lang/StringBuffer <init> (Ljava/lang/String;)V
L166:   iload_1
L167:   invokevirtual Method java/lang/StringBuffer append (I)Ljava/lang/StringBuffer;
L170:   ldc ", "
L172:   invokevirtual Method java/lang/StringBuffer append (Ljava/lang/String;)Ljava/lang/StringBuffer;
L175:   aload_2
L176:   invokevirtual Method java/lang/Throwable toString ()Ljava/lang/String;
L179:   invokevirtual Method java/lang/StringBuffer append (Ljava/lang/String;)Ljava/lang/StringBuffer;
L182:   invokevirtual Method java/lang/StringBuffer toString ()Ljava/lang/String;
L185:   invokestatic Method sign/signlink reporterror (Ljava/lang/String;)V
L188:   new java/lang/RuntimeException
L191:   dup
L192:   invokespecial Method java/lang/RuntimeException <init> ()V
L195:   athrow
L196:   
    .end code
.end method

.method public a : (B)V
    .code stack 6 locals 7
        .catch java/lang/RuntimeException from L0 to L278 using L279
L0:     aload_0
L1:     iconst_0
L2:     putfield Field eb M I
L5:     iload_1
L6:     aload_0
L7:     getfield Field eb k B
L10:    if_icmpeq L14
L13:    return
L14:    aload_0
L15:    iconst_0
L16:    putfield Field eb L I
L19:    aload_0
L20:    iconst_0
L21:    putfield Field eb N I
L24:    aload_0
L25:    ldc 999999
L27:    putfield Field eb H I
L30:    aload_0
L31:    ldc -999999
L33:    putfield Field eb I I
L36:    aload_0
L37:    ldc -99999
L39:    putfield Field eb J I
L42:    aload_0
L43:    ldc 99999
L45:    putfield Field eb K I
L48:    iconst_0
L49:    istore_2
L50:    getstatic Field eb Rb Z
L53:    ifeq L196
L56:    aload_0
L57:    getfield Field eb o [I
L60:    iload_2
L61:    iaload
L62:    istore_3
L63:    aload_0
L64:    getfield Field eb p [I
L67:    iload_2
L68:    iaload
L69:    istore 4
L71:    aload_0
L72:    getfield Field eb q [I
L75:    iload_2
L76:    iaload
L77:    istore 5
L79:    iload_3
L80:    aload_0
L81:    getfield Field eb H I
L84:    if_icmpge L92
L87:    aload_0
L88:    iload_3
L89:    putfield Field eb H I
L92:    iload_3
L93:    aload_0
L94:    getfield Field eb I I
L97:    if_icmple L105
L100:   aload_0
L101:   iload_3
L102:   putfield Field eb I I
L105:   iload 5
L107:   aload_0
L108:   getfield Field eb K I
L111:   if_icmpge L120
L114:   aload_0
L115:   iload 5
L117:   putfield Field eb K I
L120:   iload 5
L122:   aload_0
L123:   getfield Field eb J I
L126:   if_icmple L135
L129:   aload_0
L130:   iload 5
L132:   putfield Field eb J I
L135:   iload 4
L137:   ineg
L138:   aload_0
L139:   getfield Field eb M I
L142:   if_icmple L152
L145:   aload_0
L146:   iload 4
L148:   ineg
L149:   putfield Field eb M I
L152:   iload 4
L154:   aload_0
L155:   getfield Field eb N I
L158:   if_icmple L167
L161:   aload_0
L162:   iload 4
L164:   putfield Field eb N I
L167:   iload_3
L168:   iload_3
L169:   imul
L170:   iload 5
L172:   iload 5
L174:   imul
L175:   iadd
L176:   istore 6
L178:   iload 6
L180:   aload_0
L181:   getfield Field eb L I
L184:   if_icmple L193
L187:   aload_0
L188:   iload 6
L190:   putfield Field eb L I
L193:   iinc 2 1
L196:   iload_2
L197:   aload_0
L198:   getfield Field eb n I
L201:   if_icmplt L56
L204:   aload_0
L205:   aload_0
L206:   getfield Field eb L I
L209:   i2d
L210:   invokestatic Method java/lang/Math sqrt (D)D
L213:   d2i
L214:   putfield Field eb L I
L217:   aload_0
L218:   aload_0
L219:   getfield Field eb L I
L222:   aload_0
L223:   getfield Field eb L I
L226:   imul
L227:   aload_0
L228:   getfield Field eb M I
L231:   aload_0
L232:   getfield Field eb M I
L235:   imul
L236:   iadd
L237:   i2d
L238:   invokestatic Method java/lang/Math sqrt (D)D
L241:   d2i
L242:   putfield Field eb P I
L245:   aload_0
L246:   aload_0
L247:   getfield Field eb P I
L250:   aload_0
L251:   getfield Field eb L I
L254:   aload_0
L255:   getfield Field eb L I
L258:   imul
L259:   aload_0
L260:   getfield Field eb N I
L263:   aload_0
L264:   getfield Field eb N I
L267:   imul
L268:   iadd
L269:   i2d
L270:   invokestatic Method java/lang/Math sqrt (D)D
L273:   d2i
L274:   iadd
L275:   putfield Field eb O I
L278:   return
L279:   astore_2
L280:   new java/lang/StringBuffer
L283:   dup
L284:   ldc "62953, "
L286:   invokespecial Method java/lang/StringBuffer <init> (Ljava/lang/String;)V
L289:   iload_1
L290:   invokevirtual Method java/lang/StringBuffer append (I)Ljava/lang/StringBuffer;
L293:   ldc ", "
L295:   invokevirtual Method java/lang/StringBuffer append (Ljava/lang/String;)Ljava/lang/StringBuffer;
L298:   aload_2
L299:   invokevirtual Method java/lang/Throwable toString ()Ljava/lang/String;
L302:   invokevirtual Method java/lang/StringBuffer append (Ljava/lang/String;)Ljava/lang/StringBuffer;
L305:   invokevirtual Method java/lang/StringBuffer toString ()Ljava/lang/String;
L308:   invokestatic Method sign/signlink reporterror (Ljava/lang/String;)V
L311:   new java/lang/RuntimeException
L314:   dup
L315:   invokespecial Method java/lang/RuntimeException <init> ()V
L318:   athrow
L319:   
    .end code
.end method

.method public c : (I)V
    .code stack 7 locals 9
L0:     getstatic Field eb Rb Z
L3:     istore 8
        .catch java/lang/RuntimeException from L5 to L331 using L332
L5:     iload_1
L6:     iconst_4
L7:     if_icmpeq L11
L10:    return
L11:    aload_0
L12:    getfield Field eb R [I
L15:    ifnull L171
L18:    sipush 256
L21:    newarray int
L23:    astore_2
L24:    iconst_0
L25:    istore_3
L26:    iconst_0
L27:    istore 4
L29:    iload 8
L31:    ifeq L63
L34:    aload_0
L35:    getfield Field eb R [I
L38:    iload 4
L40:    iaload
L41:    istore 5
L43:    aload_2
L44:    iload 5
L46:    dup2
L47:    iaload
L48:    iconst_1
L49:    iadd
L50:    iastore
L51:    iload 5
L53:    iload_3
L54:    if_icmple L60
L57:    iload 5
L59:    istore_3
L60:    iinc 4 1
L63:    iload 4
L65:    aload_0
L66:    getfield Field eb n I
L69:    if_icmplt L34
L72:    aload_0
L73:    iload_3
L74:    iconst_1
L75:    iadd
L76:    multianewarray [[I 1
L80:    putfield Field eb T [[I
L83:    iconst_0
L84:    istore 5
L86:    iload 8
L88:    ifeq L112
L91:    aload_0
L92:    getfield Field eb T [[I
L95:    iload 5
L97:    aload_2
L98:    iload 5
L100:   iaload
L101:   newarray int
L103:   aastore
L104:   aload_2
L105:   iload 5
L107:   iconst_0
L108:   iastore
L109:   iinc 5 1
L112:   iload 5
L114:   iload_3
L115:   if_icmple L91
L118:   iconst_0
L119:   istore 6
L121:   iload 8
L123:   ifeq L157
L126:   aload_0
L127:   getfield Field eb R [I
L130:   iload 6
L132:   iaload
L133:   istore 7
L135:   aload_0
L136:   getfield Field eb T [[I
L139:   iload 7
L141:   aaload
L142:   aload_2
L143:   iload 7
L145:   dup2
L146:   iaload
L147:   dup_x2
L148:   iconst_1
L149:   iadd
L150:   iastore
L151:   iload 6
L153:   iastore
L154:   iinc 6 1
L157:   iload 6
L159:   aload_0
L160:   getfield Field eb n I
L163:   if_icmplt L126
L166:   aload_0
L167:   aconst_null
L168:   putfield Field eb R [I
L171:   aload_0
L172:   getfield Field eb S [I
L175:   ifnull L372
L178:   sipush 256
L181:   newarray int
L183:   astore_2
L184:   iconst_0
L185:   istore_3
L186:   iconst_0
L187:   istore 4
L189:   iload 8
L191:   ifeq L223
L194:   aload_0
L195:   getfield Field eb S [I
L198:   iload 4
L200:   iaload
L201:   istore 5
L203:   aload_2
L204:   iload 5
L206:   dup2
L207:   iaload
L208:   iconst_1
L209:   iadd
L210:   iastore
L211:   iload 5
L213:   iload_3
L214:   if_icmple L220
L217:   iload 5
L219:   istore_3
L220:   iinc 4 1
L223:   iload 4
L225:   aload_0
L226:   getfield Field eb r I
L229:   if_icmplt L194
L232:   aload_0
L233:   iload_3
L234:   iconst_1
L235:   iadd
L236:   multianewarray [[I 1
L240:   putfield Field eb U [[I
L243:   iconst_0
L244:   istore 5
L246:   iload 8
L248:   ifeq L272
L251:   aload_0
L252:   getfield Field eb U [[I
L255:   iload 5
L257:   aload_2
L258:   iload 5
L260:   iaload
L261:   newarray int
L263:   aastore
L264:   aload_2
L265:   iload 5
L267:   iconst_0
L268:   iastore
L269:   iinc 5 1
L272:   iload 5
L274:   iload_3
L275:   if_icmple L251
L278:   iconst_0
L279:   istore 6
L281:   iload 8
L283:   ifeq L317
L286:   aload_0
L287:   getfield Field eb S [I
L290:   iload 6
L292:   iaload
L293:   istore 7
L295:   aload_0
L296:   getfield Field eb U [[I
L299:   iload 7
L301:   aaload
L302:   aload_2
L303:   iload 7
L305:   dup2
L306:   iaload
L307:   dup_x2
L308:   iconst_1
L309:   iadd
L310:   iastore
L311:   iload 6
L313:   iastore
L314:   iinc 6 1
L317:   iload 6
L319:   aload_0
L320:   getfield Field eb r I
L323:   if_icmplt L286
L326:   aload_0
L327:   aconst_null
L328:   putfield Field eb S [I
L331:   return
L332:   astore_2
L333:   new java/lang/StringBuffer
L336:   dup
L337:   ldc "9753, "
L339:   invokespecial Method java/lang/StringBuffer <init> (Ljava/lang/String;)V
L342:   iload_1
L343:   invokevirtual Method java/lang/StringBuffer append (I)Ljava/lang/StringBuffer;
L346:   ldc ", "
L348:   invokevirtual Method java/lang/StringBuffer append (Ljava/lang/String;)Ljava/lang/StringBuffer;
L351:   aload_2
L352:   invokevirtual Method java/lang/Throwable toString ()Ljava/lang/String;
L355:   invokevirtual Method java/lang/StringBuffer append (Ljava/lang/String;)Ljava/lang/StringBuffer;
L358:   invokevirtual Method java/lang/StringBuffer toString ()Ljava/lang/String;
L361:   invokestatic Method sign/signlink reporterror (Ljava/lang/String;)V
L364:   new java/lang/RuntimeException
L367:   dup
L368:   invokespecial Method java/lang/RuntimeException <init> ()V
L371:   athrow
L372:   return
L373:   
    .end code
.end method

.method public a : (II)V
    .code stack 8 locals 7
        .catch java/lang/RuntimeException from L0 to L117 using L117
L0:     aload_0
L1:     getfield Field eb T [[I
L4:     ifnonnull L8
L7:     return
L8:     iload_2
L9:     iconst_m1
L10:    if_icmpne L14
L13:    return
L14:    getstatic Field g a [Lg;
L17:    iload_2
L18:    aaload
L19:    astore_3
L20:    aload_3
L21:    getfield Field g c Lf;
L24:    astore 4
L26:    iconst_0
L27:    putstatic Field eb Fb I
L30:    iconst_0
L31:    putstatic Field eb Gb I
L34:    iconst_0
L35:    putstatic Field eb Hb I
L38:    iconst_0
L39:    istore 5
L41:    getstatic Field eb Rb Z
L44:    ifeq L100
L47:    aload_3
L48:    getfield Field g e [I
L51:    iload 5
L53:    iaload
L54:    istore 6
L56:    aload_0
L57:    aload 4
L59:    getfield Field f c [I
L62:    iload 6
L64:    iaload
L65:    aload 4
L67:    getfield Field f d [[I
L70:    iload 6
L72:    aaload
L73:    aload_3
L74:    getfield Field g f [I
L77:    iload 5
L79:    iaload
L80:    aload_3
L81:    getfield Field g g [I
L84:    iload 5
L86:    iaload
L87:    aload_3
L88:    getfield Field g h [I
L91:    iload 5
L93:    iaload
L94:    invokespecial Method eb a (I[IIII)V
L97:    iinc 5 1
L100:   iload 5
L102:   aload_3
L103:   getfield Field g d I
L106:   if_icmplt L47
L109:   iload_1
L110:   sipush -16599
L113:   if_icmpeq L166
L116:   return
L117:   astore_3
L118:   new java/lang/StringBuffer
L121:   dup
L122:   ldc "30537, "
L124:   invokespecial Method java/lang/StringBuffer <init> (Ljava/lang/String;)V
L127:   iload_1
L128:   invokevirtual Method java/lang/StringBuffer append (I)Ljava/lang/StringBuffer;
L131:   ldc ", "
L133:   invokevirtual Method java/lang/StringBuffer append (Ljava/lang/String;)Ljava/lang/StringBuffer;
L136:   iload_2
L137:   invokevirtual Method java/lang/StringBuffer append (I)Ljava/lang/StringBuffer;
L140:   ldc ", "
L142:   invokevirtual Method java/lang/StringBuffer append (Ljava/lang/String;)Ljava/lang/StringBuffer;
L145:   aload_3
L146:   invokevirtual Method java/lang/Throwable toString ()Ljava/lang/String;
L149:   invokevirtual Method java/lang/StringBuffer append (Ljava/lang/String;)Ljava/lang/StringBuffer;
L152:   invokevirtual Method java/lang/StringBuffer toString ()Ljava/lang/String;
L155:   invokestatic Method sign/signlink reporterror (Ljava/lang/String;)V
L158:   new java/lang/RuntimeException
L161:   dup
L162:   invokespecial Method java/lang/RuntimeException <init> ()V
L165:   athrow
L166:   return
L167:   
    .end code
.end method

.method public a : (III[I)V
    .code stack 8 locals 14
L0:     getstatic Field eb Rb Z
L3:     istore 13
        .catch java/lang/RuntimeException from L5 to L348 using L349
L5:     iload_3
L6:     iconst_m1
L7:     if_icmpne L11
L10:    return
L11:    aload 4
L13:    ifnull L21
L16:    iload_1
L17:    iconst_m1
L18:    if_icmpne L30
L21:    aload_0
L22:    sipush -16599
L25:    iload_3
L26:    invokevirtual Method eb a (II)V
L29:    return
L30:    getstatic Field g a [Lg;
L33:    iload_3
L34:    aaload
L35:    astore 5
L37:    iload_2
L38:    iconst_3
L39:    if_icmplt L47
L42:    iload_2
L43:    iconst_3
L44:    if_icmple L54
L47:    aload_0
L48:    sipush -162
L51:    putfield Field eb l I
L54:    getstatic Field g a [Lg;
L57:    iload_1
L58:    aaload
L59:    astore 6
L61:    aload 5
L63:    getfield Field g c Lf;
L66:    astore 7
L68:    iconst_0
L69:    putstatic Field eb Fb I
L72:    iconst_0
L73:    putstatic Field eb Gb I
L76:    iconst_0
L77:    putstatic Field eb Hb I
L80:    iconst_0
L81:    istore 8
L83:    aload 4
L85:    iload 8
L87:    iinc 8 1
L90:    iaload
L91:    istore 9
L93:    iconst_0
L94:    istore 10
L96:    iload 13
L98:    ifeq L198
L101:   aload 5
L103:   getfield Field g e [I
L106:   iload 10
L108:   iaload
L109:   istore 11
L111:   iload 13
L113:   ifeq L126
L116:   aload 4
L118:   iload 8
L120:   iinc 8 1
L123:   iaload
L124:   istore 9
L126:   iload 11
L128:   iload 9
L130:   if_icmpgt L116
L133:   iload 11
L135:   iload 9
L137:   if_icmpne L151
L140:   aload 7
L142:   getfield Field f c [I
L145:   iload 11
L147:   iaload
L148:   ifne L195
L151:   aload_0
L152:   aload 7
L154:   getfield Field f c [I
L157:   iload 11
L159:   iaload
L160:   aload 7
L162:   getfield Field f d [[I
L165:   iload 11
L167:   aaload
L168:   aload 5
L170:   getfield Field g f [I
L173:   iload 10
L175:   iaload
L176:   aload 5
L178:   getfield Field g g [I
L181:   iload 10
L183:   iaload
L184:   aload 5
L186:   getfield Field g h [I
L189:   iload 10
L191:   iaload
L192:   invokespecial Method eb a (I[IIII)V
L195:   iinc 10 1
L198:   iload 10
L200:   aload 5
L202:   getfield Field g d I
L205:   if_icmplt L101
L208:   iconst_0
L209:   putstatic Field eb Fb I
L212:   iconst_0
L213:   putstatic Field eb Gb I
L216:   iconst_0
L217:   putstatic Field eb Hb I
L220:   iconst_0
L221:   istore 8
L223:   aload 4
L225:   iload 8
L227:   iinc 8 1
L230:   iaload
L231:   istore 9
L233:   iconst_0
L234:   istore 11
L236:   iload 13
L238:   ifeq L338
L241:   aload 6
L243:   getfield Field g e [I
L246:   iload 11
L248:   iaload
L249:   istore 12
L251:   iload 13
L253:   ifeq L266
L256:   aload 4
L258:   iload 8
L260:   iinc 8 1
L263:   iaload
L264:   istore 9
L266:   iload 12
L268:   iload 9
L270:   if_icmpgt L256
L273:   iload 12
L275:   iload 9
L277:   if_icmpeq L291
L280:   aload 7
L282:   getfield Field f c [I
L285:   iload 12
L287:   iaload
L288:   ifne L335
L291:   aload_0
L292:   aload 7
L294:   getfield Field f c [I
L297:   iload 12
L299:   iaload
L300:   aload 7
L302:   getfield Field f d [[I
L305:   iload 12
L307:   aaload
L308:   aload 6
L310:   getfield Field g f [I
L313:   iload 11
L315:   iaload
L316:   aload 6
L318:   getfield Field g g [I
L321:   iload 11
L323:   iaload
L324:   aload 6
L326:   getfield Field g h [I
L329:   iload 11
L331:   iaload
L332:   invokespecial Method eb a (I[IIII)V
L335:   iinc 11 1
L338:   iload 11
L340:   aload 6
L342:   getfield Field g d I
L345:   if_icmplt L241
L348:   return
L349:   astore 5
L351:   new java/lang/StringBuffer
L354:   dup
L355:   ldc "37286, "
L357:   invokespecial Method java/lang/StringBuffer <init> (Ljava/lang/String;)V
L360:   iload_1
L361:   invokevirtual Method java/lang/StringBuffer append (I)Ljava/lang/StringBuffer;
L364:   ldc ", "
L366:   invokevirtual Method java/lang/StringBuffer append (Ljava/lang/String;)Ljava/lang/StringBuffer;
L369:   iload_2
L370:   invokevirtual Method java/lang/StringBuffer append (I)Ljava/lang/StringBuffer;
L373:   ldc ", "
L375:   invokevirtual Method java/lang/StringBuffer append (Ljava/lang/String;)Ljava/lang/StringBuffer;
L378:   iload_3
L379:   invokevirtual Method java/lang/StringBuffer append (I)Ljava/lang/StringBuffer;
L382:   ldc ", "
L384:   invokevirtual Method java/lang/StringBuffer append (Ljava/lang/String;)Ljava/lang/StringBuffer;
L387:   aload 4
L389:   invokevirtual Method java/lang/StringBuffer append (Ljava/lang/Object;)Ljava/lang/StringBuffer;
L392:   ldc ", "
L394:   invokevirtual Method java/lang/StringBuffer append (Ljava/lang/String;)Ljava/lang/StringBuffer;
L397:   aload 5
L399:   invokevirtual Method java/lang/Throwable toString ()Ljava/lang/String;
L402:   invokevirtual Method java/lang/StringBuffer append (Ljava/lang/String;)Ljava/lang/StringBuffer;
L405:   invokevirtual Method java/lang/StringBuffer toString ()Ljava/lang/String;
L408:   invokestatic Method sign/signlink reporterror (Ljava/lang/String;)V
L411:   new java/lang/RuntimeException
L414:   dup
L415:   invokespecial Method java/lang/RuntimeException <init> ()V
L418:   athrow
L419:   
    .end code
.end method

.method private a : (I[IIII)V
    .code stack 6 locals 19
L0:     getstatic Field eb Rb Z
L3:     istore 18
L5:     aload_2
L6:     arraylength
L7:     istore 6
L9:     iload_1
L10:    ifne L198
L13:    iconst_0
L14:    istore 7
L16:    iconst_0
L17:    putstatic Field eb Fb I
L20:    iconst_0
L21:    putstatic Field eb Gb I
L24:    iconst_0
L25:    putstatic Field eb Hb I
L28:    iconst_0
L29:    istore 8
L31:    iload 18
L33:    ifeq L135
L36:    aload_2
L37:    iload 8
L39:    iaload
L40:    istore 9
L42:    iload 9
L44:    aload_0
L45:    getfield Field eb T [[I
L48:    arraylength
L49:    if_icmpge L132
L52:    aload_0
L53:    getfield Field eb T [[I
L56:    iload 9
L58:    aaload
L59:    astore 10
L61:    iconst_0
L62:    istore 11
L64:    iload 18
L66:    ifeq L124
L69:    aload 10
L71:    iload 11
L73:    iaload
L74:    istore 12
L76:    getstatic Field eb Fb I
L79:    aload_0
L80:    getfield Field eb o [I
L83:    iload 12
L85:    iaload
L86:    iadd
L87:    putstatic Field eb Fb I
L90:    getstatic Field eb Gb I
L93:    aload_0
L94:    getfield Field eb p [I
L97:    iload 12
L99:    iaload
L100:   iadd
L101:   putstatic Field eb Gb I
L104:   getstatic Field eb Hb I
L107:   aload_0
L108:   getfield Field eb q [I
L111:   iload 12
L113:   iaload
L114:   iadd
L115:   putstatic Field eb Hb I
L118:   iinc 7 1
L121:   iinc 11 1
L124:   iload 11
L126:   aload 10
L128:   arraylength
L129:   if_icmplt L69
L132:   iinc 8 1
L135:   iload 8
L137:   iload 6
L139:   if_icmplt L36
L142:   iload 7
L144:   ifle L183
L147:   getstatic Field eb Fb I
L150:   iload 7
L152:   idiv
L153:   iload_3
L154:   iadd
L155:   putstatic Field eb Fb I
L158:   getstatic Field eb Gb I
L161:   iload 7
L163:   idiv
L164:   iload 4
L166:   iadd
L167:   putstatic Field eb Gb I
L170:   getstatic Field eb Hb I
L173:   iload 7
L175:   idiv
L176:   iload 5
L178:   iadd
L179:   putstatic Field eb Hb I
L182:   return
L183:   iload_3
L184:   putstatic Field eb Fb I
L187:   iload 4
L189:   putstatic Field eb Gb I
L192:   iload 5
L194:   putstatic Field eb Hb I
L197:   return
L198:   iload_1
L199:   iconst_1
L200:   if_icmpne L308
L203:   iconst_0
L204:   istore 7
L206:   iload 18
L208:   ifeq L300
L211:   aload_2
L212:   iload 7
L214:   iaload
L215:   istore 8
L217:   iload 8
L219:   aload_0
L220:   getfield Field eb T [[I
L223:   arraylength
L224:   if_icmpge L297
L227:   aload_0
L228:   getfield Field eb T [[I
L231:   iload 8
L233:   aaload
L234:   astore 9
L236:   iconst_0
L237:   istore 10
L239:   iload 18
L241:   ifeq L289
L244:   aload 9
L246:   iload 10
L248:   iaload
L249:   istore 11
L251:   aload_0
L252:   getfield Field eb o [I
L255:   iload 11
L257:   dup2
L258:   iaload
L259:   iload_3
L260:   iadd
L261:   iastore
L262:   aload_0
L263:   getfield Field eb p [I
L266:   iload 11
L268:   dup2
L269:   iaload
L270:   iload 4
L272:   iadd
L273:   iastore
L274:   aload_0
L275:   getfield Field eb q [I
L278:   iload 11
L280:   dup2
L281:   iaload
L282:   iload 5
L284:   iadd
L285:   iastore
L286:   iinc 10 1
L289:   iload 10
L291:   aload 9
L293:   arraylength
L294:   if_icmplt L244
L297:   iinc 7 1
L300:   iload 7
L302:   iload 6
L304:   if_icmplt L211
L307:   return
L308:   iload_1
L309:   iconst_2
L310:   if_icmpne L754
L313:   iconst_0
L314:   istore 7
L316:   iload 18
L318:   ifeq L746
L321:   aload_2
L322:   iload 7
L324:   iaload
L325:   istore 8
L327:   iload 8
L329:   aload_0
L330:   getfield Field eb T [[I
L333:   arraylength
L334:   if_icmpge L743
L337:   aload_0
L338:   getfield Field eb T [[I
L341:   iload 8
L343:   aaload
L344:   astore 9
L346:   iconst_0
L347:   istore 10
L349:   iload 18
L351:   ifeq L735
L354:   aload 9
L356:   iload 10
L358:   iaload
L359:   istore 11
L361:   aload_0
L362:   getfield Field eb o [I
L365:   iload 11
L367:   dup2
L368:   iaload
L369:   getstatic Field eb Fb I
L372:   isub
L373:   iastore
L374:   aload_0
L375:   getfield Field eb p [I
L378:   iload 11
L380:   dup2
L381:   iaload
L382:   getstatic Field eb Gb I
L385:   isub
L386:   iastore
L387:   aload_0
L388:   getfield Field eb q [I
L391:   iload 11
L393:   dup2
L394:   iaload
L395:   getstatic Field eb Hb I
L398:   isub
L399:   iastore
L400:   iload_3
L401:   sipush 255
L404:   iand
L405:   bipush 8
L407:   imul
L408:   istore 12
L410:   iload 4
L412:   sipush 255
L415:   iand
L416:   bipush 8
L418:   imul
L419:   istore 13
L421:   iload 5
L423:   sipush 255
L426:   iand
L427:   bipush 8
L429:   imul
L430:   istore 14
L432:   iload 14
L434:   ifeq L519
L437:   getstatic Field eb Nb [I
L440:   iload 14
L442:   iaload
L443:   istore 15
L445:   getstatic Field eb Ob [I
L448:   iload 14
L450:   iaload
L451:   istore 16
L453:   aload_0
L454:   getfield Field eb p [I
L457:   iload 11
L459:   iaload
L460:   iload 15
L462:   imul
L463:   aload_0
L464:   getfield Field eb o [I
L467:   iload 11
L469:   iaload
L470:   iload 16
L472:   imul
L473:   iadd
L474:   bipush 16
L476:   ishr
L477:   istore 17
L479:   aload_0
L480:   getfield Field eb p [I
L483:   iload 11
L485:   aload_0
L486:   getfield Field eb p [I
L489:   iload 11
L491:   iaload
L492:   iload 16
L494:   imul
L495:   aload_0
L496:   getfield Field eb o [I
L499:   iload 11
L501:   iaload
L502:   iload 15
L504:   imul
L505:   isub
L506:   bipush 16
L508:   ishr
L509:   iastore
L510:   aload_0
L511:   getfield Field eb o [I
L514:   iload 11
L516:   iload 17
L518:   iastore
L519:   iload 12
L521:   ifeq L606
L524:   getstatic Field eb Nb [I
L527:   iload 12
L529:   iaload
L530:   istore 15
L532:   getstatic Field eb Ob [I
L535:   iload 12
L537:   iaload
L538:   istore 16
L540:   aload_0
L541:   getfield Field eb p [I
L544:   iload 11
L546:   iaload
L547:   iload 16
L549:   imul
L550:   aload_0
L551:   getfield Field eb q [I
L554:   iload 11
L556:   iaload
L557:   iload 15
L559:   imul
L560:   isub
L561:   bipush 16
L563:   ishr
L564:   istore 17
L566:   aload_0
L567:   getfield Field eb q [I
L570:   iload 11
L572:   aload_0
L573:   getfield Field eb p [I
L576:   iload 11
L578:   iaload
L579:   iload 15
L581:   imul
L582:   aload_0
L583:   getfield Field eb q [I
L586:   iload 11
L588:   iaload
L589:   iload 16
L591:   imul
L592:   iadd
L593:   bipush 16
L595:   ishr
L596:   iastore
L597:   aload_0
L598:   getfield Field eb p [I
L601:   iload 11
L603:   iload 17
L605:   iastore
L606:   iload 13
L608:   ifeq L693
L611:   getstatic Field eb Nb [I
L614:   iload 13
L616:   iaload
L617:   istore 15
L619:   getstatic Field eb Ob [I
L622:   iload 13
L624:   iaload
L625:   istore 16
L627:   aload_0
L628:   getfield Field eb q [I
L631:   iload 11
L633:   iaload
L634:   iload 15
L636:   imul
L637:   aload_0
L638:   getfield Field eb o [I
L641:   iload 11
L643:   iaload
L644:   iload 16
L646:   imul
L647:   iadd
L648:   bipush 16
L650:   ishr
L651:   istore 17
L653:   aload_0
L654:   getfield Field eb q [I
L657:   iload 11
L659:   aload_0
L660:   getfield Field eb q [I
L663:   iload 11
L665:   iaload
L666:   iload 16
L668:   imul
L669:   aload_0
L670:   getfield Field eb o [I
L673:   iload 11
L675:   iaload
L676:   iload 15
L678:   imul
L679:   isub
L680:   bipush 16
L682:   ishr
L683:   iastore
L684:   aload_0
L685:   getfield Field eb o [I
L688:   iload 11
L690:   iload 17
L692:   iastore
L693:   aload_0
L694:   getfield Field eb o [I
L697:   iload 11
L699:   dup2
L700:   iaload
L701:   getstatic Field eb Fb I
L704:   iadd
L705:   iastore
L706:   aload_0
L707:   getfield Field eb p [I
L710:   iload 11
L712:   dup2
L713:   iaload
L714:   getstatic Field eb Gb I
L717:   iadd
L718:   iastore
L719:   aload_0
L720:   getfield Field eb q [I
L723:   iload 11
L725:   dup2
L726:   iaload
L727:   getstatic Field eb Hb I
L730:   iadd
L731:   iastore
L732:   iinc 10 1
L735:   iload 10
L737:   aload 9
L739:   arraylength
L740:   if_icmplt L354
L743:   iinc 7 1
L746:   iload 7
L748:   iload 6
L750:   if_icmplt L321
L753:   return
L754:   iload_1
L755:   iconst_3
L756:   if_icmpne L969
L759:   iconst_0
L760:   istore 7
L762:   iload 18
L764:   ifeq L961
L767:   aload_2
L768:   iload 7
L770:   iaload
L771:   istore 8
L773:   iload 8
L775:   aload_0
L776:   getfield Field eb T [[I
L779:   arraylength
L780:   if_icmpge L958
L783:   aload_0
L784:   getfield Field eb T [[I
L787:   iload 8
L789:   aaload
L790:   astore 9
L792:   iconst_0
L793:   istore 10
L795:   iload 18
L797:   ifeq L950
L800:   aload 9
L802:   iload 10
L804:   iaload
L805:   istore 11
L807:   aload_0
L808:   getfield Field eb o [I
L811:   iload 11
L813:   dup2
L814:   iaload
L815:   getstatic Field eb Fb I
L818:   isub
L819:   iastore
L820:   aload_0
L821:   getfield Field eb p [I
L824:   iload 11
L826:   dup2
L827:   iaload
L828:   getstatic Field eb Gb I
L831:   isub
L832:   iastore
L833:   aload_0
L834:   getfield Field eb q [I
L837:   iload 11
L839:   dup2
L840:   iaload
L841:   getstatic Field eb Hb I
L844:   isub
L845:   iastore
L846:   aload_0
L847:   getfield Field eb o [I
L850:   iload 11
L852:   aload_0
L853:   getfield Field eb o [I
L856:   iload 11
L858:   iaload
L859:   iload_3
L860:   imul
L861:   sipush 128
L864:   idiv
L865:   iastore
L866:   aload_0
L867:   getfield Field eb p [I
L870:   iload 11
L872:   aload_0
L873:   getfield Field eb p [I
L876:   iload 11
L878:   iaload
L879:   iload 4
L881:   imul
L882:   sipush 128
L885:   idiv
L886:   iastore
L887:   aload_0
L888:   getfield Field eb q [I
L891:   iload 11
L893:   aload_0
L894:   getfield Field eb q [I
L897:   iload 11
L899:   iaload
L900:   iload 5
L902:   imul
L903:   sipush 128
L906:   idiv
L907:   iastore
L908:   aload_0
L909:   getfield Field eb o [I
L912:   iload 11
L914:   dup2
L915:   iaload
L916:   getstatic Field eb Fb I
L919:   iadd
L920:   iastore
L921:   aload_0
L922:   getfield Field eb p [I
L925:   iload 11
L927:   dup2
L928:   iaload
L929:   getstatic Field eb Gb I
L932:   iadd
L933:   iastore
L934:   aload_0
L935:   getfield Field eb q [I
L938:   iload 11
L940:   dup2
L941:   iaload
L942:   getstatic Field eb Hb I
L945:   iadd
L946:   iastore
L947:   iinc 10 1
L950:   iload 10
L952:   aload 9
L954:   arraylength
L955:   if_icmplt L800
L958:   iinc 7 1
L961:   iload 7
L963:   iload 6
L965:   if_icmplt L767
L968:   return
L969:   iload_1
L970:   iconst_5
L971:   if_icmpne L1113
L974:   aload_0
L975:   getfield Field eb U [[I
L978:   ifnull L1112
L981:   aload_0
L982:   getfield Field eb A [I
L985:   ifnull L1112
L988:   iconst_0
L989:   istore 7
L991:   iload 18
L993:   ifeq L1105
L996:   aload_2
L997:   iload 7
L999:   iaload
L1000:  istore 8
L1002:  iload 8
L1004:  aload_0
L1005:  getfield Field eb U [[I
L1008:  arraylength
L1009:  if_icmpge L1102
L1012:  aload_0
L1013:  getfield Field eb U [[I
L1016:  iload 8
L1018:  aaload
L1019:  astore 9
L1021:  iconst_0
L1022:  istore 10
L1024:  iload 18
L1026:  ifeq L1094
L1029:  aload 9
L1031:  iload 10
L1033:  iaload
L1034:  istore 11
L1036:  aload_0
L1037:  getfield Field eb A [I
L1040:  iload 11
L1042:  dup2
L1043:  iaload
L1044:  iload_3
L1045:  bipush 8
L1047:  imul
L1048:  iadd
L1049:  iastore
L1050:  aload_0
L1051:  getfield Field eb A [I
L1054:  iload 11
L1056:  iaload
L1057:  ifge L1068
L1060:  aload_0
L1061:  getfield Field eb A [I
L1064:  iload 11
L1066:  iconst_0
L1067:  iastore
L1068:  aload_0
L1069:  getfield Field eb A [I
L1072:  iload 11
L1074:  iaload
L1075:  sipush 255
L1078:  if_icmple L1091
L1081:  aload_0
L1082:  getfield Field eb A [I
L1085:  iload 11
L1087:  sipush 255
L1090:  iastore
L1091:  iinc 10 1
L1094:  iload 10
L1096:  aload 9
L1098:  arraylength
L1099:  if_icmplt L1029
L1102:  iinc 7 1
L1105:  iload 7
L1107:  iload 6
L1109:  if_icmplt L996
L1112:  return
L1113:  return
L1114:  
    .end code
.end method

.method public d : (I)V
    .code stack 5 locals 4
        .catch java/lang/RuntimeException from L0 to L57 using L58
L0:     iload_1
L1:     ifeq L11
L4:     aload_0
L5:     sipush 472
L8:     putfield Field eb i I
L11:    iconst_0
L12:    istore_2
L13:    getstatic Field eb Rb Z
L16:    ifeq L49
L19:    aload_0
L20:    getfield Field eb o [I
L23:    iload_2
L24:    iaload
L25:    istore_3
L26:    aload_0
L27:    getfield Field eb o [I
L30:    iload_2
L31:    aload_0
L32:    getfield Field eb q [I
L35:    iload_2
L36:    iaload
L37:    iastore
L38:    aload_0
L39:    getfield Field eb q [I
L42:    iload_2
L43:    iload_3
L44:    ineg
L45:    iastore
L46:    iinc 2 1
L49:    iload_2
L50:    aload_0
L51:    getfield Field eb n I
L54:    if_icmplt L19
L57:    return
L58:    astore_2
L59:    new java/lang/StringBuffer
L62:    dup
L63:    ldc "87214, "
L65:    invokespecial Method java/lang/StringBuffer <init> (Ljava/lang/String;)V
L68:    iload_1
L69:    invokevirtual Method java/lang/StringBuffer append (I)Ljava/lang/StringBuffer;
L72:    ldc ", "
L74:    invokevirtual Method java/lang/StringBuffer append (Ljava/lang/String;)Ljava/lang/StringBuffer;
L77:    aload_2
L78:    invokevirtual Method java/lang/Throwable toString ()Ljava/lang/String;
L81:    invokevirtual Method java/lang/StringBuffer append (Ljava/lang/String;)Ljava/lang/StringBuffer;
L84:    invokevirtual Method java/lang/StringBuffer toString ()Ljava/lang/String;
L87:    invokestatic Method sign/signlink reporterror (Ljava/lang/String;)V
L90:    new java/lang/RuntimeException
L93:    dup
L94:    invokespecial Method java/lang/RuntimeException <init> ()V
L97:    athrow
L98:    
    .end code
.end method

.method public a : (BI)V
    .code stack 6 locals 7
        .catch java/lang/RuntimeException from L0 to L108 using L108
L0:     getstatic Field eb Nb [I
L3:     iload_2
L4:     iaload
L5:     istore_3
L6:     getstatic Field eb Ob [I
L9:     iload_2
L10:    iaload
L11:    istore 4
L13:    iconst_0
L14:    istore 5
L16:    getstatic Field eb Rb Z
L19:    ifeq L89
L22:    aload_0
L23:    getfield Field eb p [I
L26:    iload 5
L28:    iaload
L29:    iload 4
L31:    imul
L32:    aload_0
L33:    getfield Field eb q [I
L36:    iload 5
L38:    iaload
L39:    iload_3
L40:    imul
L41:    isub
L42:    bipush 16
L44:    ishr
L45:    istore 6
L47:    aload_0
L48:    getfield Field eb q [I
L51:    iload 5
L53:    aload_0
L54:    getfield Field eb p [I
L57:    iload 5
L59:    iaload
L60:    iload_3
L61:    imul
L62:    aload_0
L63:    getfield Field eb q [I
L66:    iload 5
L68:    iaload
L69:    iload 4
L71:    imul
L72:    iadd
L73:    bipush 16
L75:    ishr
L76:    iastore
L77:    aload_0
L78:    getfield Field eb p [I
L81:    iload 5
L83:    iload 6
L85:    iastore
L86:    iinc 5 1
L89:    iload 5
L91:    aload_0
L92:    getfield Field eb n I
L95:    if_icmplt L22
L98:    iload_1
L99:    bipush 7
L101:   if_icmpne L107
L104:   iconst_0
L105:   istore_1
L106:   return
L107:   return
L108:   astore_3
L109:   new java/lang/StringBuffer
L112:   dup
L113:   ldc "42556, "
L115:   invokespecial Method java/lang/StringBuffer <init> (Ljava/lang/String;)V
L118:   iload_1
L119:   invokevirtual Method java/lang/StringBuffer append (I)Ljava/lang/StringBuffer;
L122:   ldc ", "
L124:   invokevirtual Method java/lang/StringBuffer append (Ljava/lang/String;)Ljava/lang/StringBuffer;
L127:   iload_2
L128:   invokevirtual Method java/lang/StringBuffer append (I)Ljava/lang/StringBuffer;
L131:   ldc ", "
L133:   invokevirtual Method java/lang/StringBuffer append (Ljava/lang/String;)Ljava/lang/StringBuffer;
L136:   aload_3
L137:   invokevirtual Method java/lang/Throwable toString ()Ljava/lang/String;
L140:   invokevirtual Method java/lang/StringBuffer append (Ljava/lang/String;)Ljava/lang/StringBuffer;
L143:   invokevirtual Method java/lang/StringBuffer toString ()Ljava/lang/String;
L146:   invokestatic Method sign/signlink reporterror (Ljava/lang/String;)V
L149:   new java/lang/RuntimeException
L152:   dup
L153:   invokespecial Method java/lang/RuntimeException <init> ()V
L156:   athrow
L157:   
    .end code
.end method

.method public a : (IIII)V
    .code stack 5 locals 6
        .catch java/lang/RuntimeException from L0 to L75 using L76
L0:     iload_3
L1:     iflt L20
L4:     aload_0
L5:     aload_0
L6:     getfield Field eb m Z
L9:     ifeq L16
L12:    iconst_0
L13:    goto L17
L16:    iconst_1
L17:    putfield Field eb m Z
L20:    iconst_0
L21:    istore 5
L23:    getstatic Field eb Rb Z
L26:    ifeq L66
L29:    aload_0
L30:    getfield Field eb o [I
L33:    iload 5
L35:    dup2
L36:    iaload
L37:    iload_2
L38:    iadd
L39:    iastore
L40:    aload_0
L41:    getfield Field eb p [I
L44:    iload 5
L46:    dup2
L47:    iaload
L48:    iload_1
L49:    iadd
L50:    iastore
L51:    aload_0
L52:    getfield Field eb q [I
L55:    iload 5
L57:    dup2
L58:    iaload
L59:    iload 4
L61:    iadd
L62:    iastore
L63:    iinc 5 1
L66:    iload 5
L68:    aload_0
L69:    getfield Field eb n I
L72:    if_icmplt L29
L75:    return
L76:    astore 5
L78:    new java/lang/StringBuffer
L81:    dup
L82:    ldc "79785, "
L84:    invokespecial Method java/lang/StringBuffer <init> (Ljava/lang/String;)V
L87:    iload_1
L88:    invokevirtual Method java/lang/StringBuffer append (I)Ljava/lang/StringBuffer;
L91:    ldc ", "
L93:    invokevirtual Method java/lang/StringBuffer append (Ljava/lang/String;)Ljava/lang/StringBuffer;
L96:    iload_2
L97:    invokevirtual Method java/lang/StringBuffer append (I)Ljava/lang/StringBuffer;
L100:   ldc ", "
L102:   invokevirtual Method java/lang/StringBuffer append (Ljava/lang/String;)Ljava/lang/StringBuffer;
L105:   iload_3
L106:   invokevirtual Method java/lang/StringBuffer append (I)Ljava/lang/StringBuffer;
L109:   ldc ", "
L111:   invokevirtual Method java/lang/StringBuffer append (Ljava/lang/String;)Ljava/lang/StringBuffer;
L114:   iload 4
L116:   invokevirtual Method java/lang/StringBuffer append (I)Ljava/lang/StringBuffer;
L119:   ldc ", "
L121:   invokevirtual Method java/lang/StringBuffer append (Ljava/lang/String;)Ljava/lang/StringBuffer;
L124:   aload 5
L126:   invokevirtual Method java/lang/Throwable toString ()Ljava/lang/String;
L129:   invokevirtual Method java/lang/StringBuffer append (Ljava/lang/String;)Ljava/lang/StringBuffer;
L132:   invokevirtual Method java/lang/StringBuffer toString ()Ljava/lang/String;
L135:   invokestatic Method sign/signlink reporterror (Ljava/lang/String;)V
L138:   new java/lang/RuntimeException
L141:   dup
L142:   invokespecial Method java/lang/RuntimeException <init> ()V
L145:   athrow
L146:   
    .end code
.end method

.method public b : (II)V
    .code stack 4 locals 4
L0:     iconst_0
L1:     istore_3
L2:     getstatic Field eb Rb Z
L5:     ifeq L28
L8:     aload_0
L9:     getfield Field eb B [I
L12:    iload_3
L13:    iaload
L14:    iload_1
L15:    if_icmpne L25
L18:    aload_0
L19:    getfield Field eb B [I
L22:    iload_3
L23:    iload_2
L24:    iastore
L25:    iinc 3 1
L28:    iload_3
L29:    aload_0
L30:    getfield Field eb r I
L33:    if_icmplt L8
L36:    return
L37:    
    .end code
.end method

.method public e : (I)V
    .code stack 5 locals 6
L0:     getstatic Field eb Rb Z
L3:     istore 5
        .catch java/lang/RuntimeException from L5 to L102 using L103
L5:     iconst_0
L6:     istore_2
L7:     iload 5
L9:     ifeq L28
L12:    aload_0
L13:    getfield Field eb q [I
L16:    iload_2
L17:    aload_0
L18:    getfield Field eb q [I
L21:    iload_2
L22:    iaload
L23:    ineg
L24:    iastore
L25:    iinc 2 1
L28:    iload_2
L29:    aload_0
L30:    getfield Field eb n I
L33:    if_icmplt L12
L36:    iconst_0
L37:    istore_3
L38:    iload 5
L40:    ifeq L74
L43:    aload_0
L44:    getfield Field eb s [I
L47:    iload_3
L48:    iaload
L49:    istore 4
L51:    aload_0
L52:    getfield Field eb s [I
L55:    iload_3
L56:    aload_0
L57:    getfield Field eb u [I
L60:    iload_3
L61:    iaload
L62:    iastore
L63:    aload_0
L64:    getfield Field eb u [I
L67:    iload_3
L68:    iload 4
L70:    iastore
L71:    iinc 3 1
L74:    iload_3
L75:    aload_0
L76:    getfield Field eb r I
L79:    if_icmplt L43
L82:    iload_1
L83:    iflt L143
L86:    iconst_1
L87:    istore 4
L89:    iload 5
L91:    ifeq L97
L94:    iinc 4 1
L97:    iload 4
L99:    ifgt L94
L102:   return
L103:   astore_2
L104:   new java/lang/StringBuffer
L107:   dup
L108:   ldc "99608, "
L110:   invokespecial Method java/lang/StringBuffer <init> (Ljava/lang/String;)V
L113:   iload_1
L114:   invokevirtual Method java/lang/StringBuffer append (I)Ljava/lang/StringBuffer;
L117:   ldc ", "
L119:   invokevirtual Method java/lang/StringBuffer append (Ljava/lang/String;)Ljava/lang/StringBuffer;
L122:   aload_2
L123:   invokevirtual Method java/lang/Throwable toString ()Ljava/lang/String;
L126:   invokevirtual Method java/lang/StringBuffer append (Ljava/lang/String;)Ljava/lang/StringBuffer;
L129:   invokevirtual Method java/lang/StringBuffer toString ()Ljava/lang/String;
L132:   invokestatic Method sign/signlink reporterror (Ljava/lang/String;)V
L135:   new java/lang/RuntimeException
L138:   dup
L139:   invokespecial Method java/lang/RuntimeException <init> ()V
L142:   athrow
L143:   return
L144:   
    .end code
.end method

.method public b : (IIII)V
    .code stack 5 locals 6
        .catch java/lang/RuntimeException from L0 to L93 using L93
L0:     iconst_0
L1:     istore 5
L3:     getstatic Field eb Rb Z
L6:     ifeq L73
L9:     aload_0
L10:    getfield Field eb o [I
L13:    iload 5
L15:    aload_0
L16:    getfield Field eb o [I
L19:    iload 5
L21:    iaload
L22:    iload 4
L24:    imul
L25:    sipush 128
L28:    idiv
L29:    iastore
L30:    aload_0
L31:    getfield Field eb p [I
L34:    iload 5
L36:    aload_0
L37:    getfield Field eb p [I
L40:    iload 5
L42:    iaload
L43:    iload_3
L44:    imul
L45:    sipush 128
L48:    idiv
L49:    iastore
L50:    aload_0
L51:    getfield Field eb q [I
L54:    iload 5
L56:    aload_0
L57:    getfield Field eb q [I
L60:    iload 5
L62:    iaload
L63:    iload_1
L64:    imul
L65:    sipush 128
L68:    idiv
L69:    iastore
L70:    iinc 5 1
L73:    iload 5
L75:    aload_0
L76:    getfield Field eb n I
L79:    if_icmplt L9
L82:    iload_2
L83:    iconst_2
L84:    if_icmplt L92
L87:    iload_2
L88:    iconst_2
L89:    if_icmple L163
L92:    return
L93:    astore 5
L95:    new java/lang/StringBuffer
L98:    dup
L99:    ldc "99322, "
L101:   invokespecial Method java/lang/StringBuffer <init> (Ljava/lang/String;)V
L104:   iload_1
L105:   invokevirtual Method java/lang/StringBuffer append (I)Ljava/lang/StringBuffer;
L108:   ldc ", "
L110:   invokevirtual Method java/lang/StringBuffer append (Ljava/lang/String;)Ljava/lang/StringBuffer;
L113:   iload_2
L114:   invokevirtual Method java/lang/StringBuffer append (I)Ljava/lang/StringBuffer;
L117:   ldc ", "
L119:   invokevirtual Method java/lang/StringBuffer append (Ljava/lang/String;)Ljava/lang/StringBuffer;
L122:   iload_3
L123:   invokevirtual Method java/lang/StringBuffer append (I)Ljava/lang/StringBuffer;
L126:   ldc ", "
L128:   invokevirtual Method java/lang/StringBuffer append (Ljava/lang/String;)Ljava/lang/StringBuffer;
L131:   iload 4
L133:   invokevirtual Method java/lang/StringBuffer append (I)Ljava/lang/StringBuffer;
L136:   ldc ", "
L138:   invokevirtual Method java/lang/StringBuffer append (Ljava/lang/String;)Ljava/lang/StringBuffer;
L141:   aload 5
L143:   invokevirtual Method java/lang/Throwable toString ()Ljava/lang/String;
L146:   invokevirtual Method java/lang/StringBuffer append (Ljava/lang/String;)Ljava/lang/StringBuffer;
L149:   invokevirtual Method java/lang/StringBuffer toString ()Ljava/lang/String;
L152:   invokestatic Method sign/signlink reporterror (Ljava/lang/String;)V
L155:   new java/lang/RuntimeException
L158:   dup
L159:   invokespecial Method java/lang/RuntimeException <init> ()V
L162:   athrow
L163:   return
L164:   
    .end code
.end method

.method public final a : (IIIIIZ)V
    .code stack 7 locals 25
L0:     getstatic Field eb Rb Z
L3:     istore 24
L5:     iload_3
L6:     iload_3
L7:     imul
L8:     iload 4
L10:    iload 4
L12:    imul
L13:    iadd
L14:    iload 5
L16:    iload 5
L18:    imul
L19:    iadd
L20:    i2d
L21:    invokestatic Method java/lang/Math sqrt (D)D
L24:    d2i
L25:    istore 7
L27:    iload_2
L28:    iload 7
L30:    imul
L31:    bipush 8
L33:    ishr
L34:    istore 8
L36:    aload_0
L37:    getfield Field eb v [I
L40:    ifnonnull L73
L43:    aload_0
L44:    aload_0
L45:    getfield Field eb r I
L48:    newarray int
L50:    putfield Field eb v [I
L53:    aload_0
L54:    aload_0
L55:    getfield Field eb r I
L58:    newarray int
L60:    putfield Field eb w [I
L63:    aload_0
L64:    aload_0
L65:    getfield Field eb r I
L68:    newarray int
L70:    putfield Field eb x [I
L73:    aload_0
L74:    getfield Field eb W [Ln;
L77:    ifnonnull L125
L80:    aload_0
L81:    aload_0
L82:    getfield Field eb n I
L85:    anewarray n
L88:    putfield Field eb W [Ln;
L91:    iconst_0
L92:    istore 9
L94:    iload 24
L96:    ifeq L116
L99:    aload_0
L100:   getfield Field eb W [Ln;
L103:   iload 9
L105:   new n
L108:   dup
L109:   invokespecial Method n <init> ()V
L112:   aastore
L113:   iinc 9 1
L116:   iload 9
L118:   aload_0
L119:   getfield Field eb n I
L122:   if_icmplt L99
L125:   iconst_0
L126:   istore 9
L128:   iload 24
L130:   ifeq L686
L133:   aload_0
L134:   getfield Field eb s [I
L137:   iload 9
L139:   iaload
L140:   istore 10
L142:   aload_0
L143:   getfield Field eb t [I
L146:   iload 9
L148:   iaload
L149:   istore 11
L151:   aload_0
L152:   getfield Field eb u [I
L155:   iload 9
L157:   iaload
L158:   istore 12
L160:   aload_0
L161:   getfield Field eb o [I
L164:   iload 11
L166:   iaload
L167:   aload_0
L168:   getfield Field eb o [I
L171:   iload 10
L173:   iaload
L174:   isub
L175:   istore 13
L177:   aload_0
L178:   getfield Field eb p [I
L181:   iload 11
L183:   iaload
L184:   aload_0
L185:   getfield Field eb p [I
L188:   iload 10
L190:   iaload
L191:   isub
L192:   istore 14
L194:   aload_0
L195:   getfield Field eb q [I
L198:   iload 11
L200:   iaload
L201:   aload_0
L202:   getfield Field eb q [I
L205:   iload 10
L207:   iaload
L208:   isub
L209:   istore 15
L211:   aload_0
L212:   getfield Field eb o [I
L215:   iload 12
L217:   iaload
L218:   aload_0
L219:   getfield Field eb o [I
L222:   iload 10
L224:   iaload
L225:   isub
L226:   istore 16
L228:   aload_0
L229:   getfield Field eb p [I
L232:   iload 12
L234:   iaload
L235:   aload_0
L236:   getfield Field eb p [I
L239:   iload 10
L241:   iaload
L242:   isub
L243:   istore 17
L245:   aload_0
L246:   getfield Field eb q [I
L249:   iload 12
L251:   iaload
L252:   aload_0
L253:   getfield Field eb q [I
L256:   iload 10
L258:   iaload
L259:   isub
L260:   istore 18
L262:   iload 14
L264:   iload 18
L266:   imul
L267:   iload 17
L269:   iload 15
L271:   imul
L272:   isub
L273:   istore 19
L275:   iload 15
L277:   iload 16
L279:   imul
L280:   iload 18
L282:   iload 13
L284:   imul
L285:   isub
L286:   istore 20
L288:   iload 13
L290:   iload 17
L292:   imul
L293:   iload 16
L295:   iload 14
L297:   imul
L298:   isub
L299:   istore 21
L301:   iload 24
L303:   ifeq L324
L306:   iload 19
L308:   iconst_1
L309:   ishr
L310:   istore 19
L312:   iload 20
L314:   iconst_1
L315:   ishr
L316:   istore 20
L318:   iload 21
L320:   iconst_1
L321:   ishr
L322:   istore 21
L324:   iload 19
L326:   sipush 8192
L329:   if_icmpgt L306
L332:   iload 20
L334:   sipush 8192
L337:   if_icmpgt L306
L340:   iload 21
L342:   sipush 8192
L345:   if_icmpgt L306
L348:   iload 19
L350:   sipush -8192
L353:   if_icmplt L306
L356:   iload 20
L358:   sipush -8192
L361:   if_icmplt L306
L364:   iload 21
L366:   sipush -8192
L369:   if_icmplt L306
L372:   iload 19
L374:   iload 19
L376:   imul
L377:   iload 20
L379:   iload 20
L381:   imul
L382:   iadd
L383:   iload 21
L385:   iload 21
L387:   imul
L388:   iadd
L389:   i2d
L390:   invokestatic Method java/lang/Math sqrt (D)D
L393:   d2i
L394:   istore 22
L396:   iload 22
L398:   ifgt L404
L401:   iconst_1
L402:   istore 22
L404:   iload 19
L406:   sipush 256
L409:   imul
L410:   iload 22
L412:   idiv
L413:   istore 19
L415:   iload 20
L417:   sipush 256
L420:   imul
L421:   iload 22
L423:   idiv
L424:   istore 20
L426:   iload 21
L428:   sipush 256
L431:   imul
L432:   iload 22
L434:   idiv
L435:   istore 21
L437:   aload_0
L438:   getfield Field eb y [I
L441:   ifnull L456
L444:   aload_0
L445:   getfield Field eb y [I
L448:   iload 9
L450:   iaload
L451:   iconst_1
L452:   iand
L453:   ifne L629
L456:   aload_0
L457:   getfield Field eb W [Ln;
L460:   iload 10
L462:   aaload
L463:   astore 23
L465:   aload 23
L467:   dup
L468:   getfield Field n a I
L471:   iload 19
L473:   iadd
L474:   putfield Field n a I
L477:   aload 23
L479:   dup
L480:   getfield Field n b I
L483:   iload 20
L485:   iadd
L486:   putfield Field n b I
L489:   aload 23
L491:   dup
L492:   getfield Field n c I
L495:   iload 21
L497:   iadd
L498:   putfield Field n c I
L501:   aload 23
L503:   dup
L504:   getfield Field n d I
L507:   iconst_1
L508:   iadd
L509:   putfield Field n d I
L512:   aload_0
L513:   getfield Field eb W [Ln;
L516:   iload 11
L518:   aaload
L519:   astore 23
L521:   aload 23
L523:   dup
L524:   getfield Field n a I
L527:   iload 19
L529:   iadd
L530:   putfield Field n a I
L533:   aload 23
L535:   dup
L536:   getfield Field n b I
L539:   iload 20
L541:   iadd
L542:   putfield Field n b I
L545:   aload 23
L547:   dup
L548:   getfield Field n c I
L551:   iload 21
L553:   iadd
L554:   putfield Field n c I
L557:   aload 23
L559:   dup
L560:   getfield Field n d I
L563:   iconst_1
L564:   iadd
L565:   putfield Field n d I
L568:   aload_0
L569:   getfield Field eb W [Ln;
L572:   iload 12
L574:   aaload
L575:   astore 23
L577:   aload 23
L579:   dup
L580:   getfield Field n a I
L583:   iload 19
L585:   iadd
L586:   putfield Field n a I
L589:   aload 23
L591:   dup
L592:   getfield Field n b I
L595:   iload 20
L597:   iadd
L598:   putfield Field n b I
L601:   aload 23
L603:   dup
L604:   getfield Field n c I
L607:   iload 21
L609:   iadd
L610:   putfield Field n c I
L613:   aload 23
L615:   dup
L616:   getfield Field n d I
L619:   iconst_1
L620:   iadd
L621:   putfield Field n d I
L624:   iload 24
L626:   ifeq L683
L629:   iload_1
L630:   iload_3
L631:   iload 19
L633:   imul
L634:   iload 4
L636:   iload 20
L638:   imul
L639:   iadd
L640:   iload 5
L642:   iload 21
L644:   imul
L645:   iadd
L646:   iload 8
L648:   iload 8
L650:   iconst_2
L651:   idiv
L652:   iadd
L653:   idiv
L654:   iadd
L655:   istore 23
L657:   aload_0
L658:   getfield Field eb v [I
L661:   iload 9
L663:   aload_0
L664:   getfield Field eb B [I
L667:   iload 9
L669:   iaload
L670:   iload 23
L672:   aload_0
L673:   getfield Field eb y [I
L676:   iload 9
L678:   iaload
L679:   invokestatic Method eb a (III)I
L682:   iastore
L683:   iinc 9 1
L686:   iload 9
L688:   aload_0
L689:   getfield Field eb r I
L692:   if_icmplt L133
L695:   iload 6
L697:   ifeq L717
L700:   aload_0
L701:   iload_1
L702:   iload 8
L704:   iload_3
L705:   iload 4
L707:   iload 5
L709:   invokevirtual Method eb a (IIIII)V
L712:   iload 24
L714:   ifeq L814
L717:   aload_0
L718:   aload_0
L719:   getfield Field eb n I
L722:   anewarray n
L725:   putfield Field eb X [Ln;
L728:   iconst_0
L729:   istore 10
L731:   iload 24
L733:   ifeq L805
L736:   aload_0
L737:   getfield Field eb W [Ln;
L740:   iload 10
L742:   aaload
L743:   astore 11
L745:   aload_0
L746:   getfield Field eb X [Ln;
L749:   iload 10
L751:   new n
L754:   dup
L755:   invokespecial Method n <init> ()V
L758:   dup_x2
L759:   aastore
L760:   astore 12
L762:   aload 12
L764:   aload 11
L766:   getfield Field n a I
L769:   putfield Field n a I
L772:   aload 12
L774:   aload 11
L776:   getfield Field n b I
L779:   putfield Field n b I
L782:   aload 12
L784:   aload 11
L786:   getfield Field n c I
L789:   putfield Field n c I
L792:   aload 12
L794:   aload 11
L796:   getfield Field n d I
L799:   putfield Field n d I
L802:   iinc 10 1
L805:   iload 10
L807:   aload_0
L808:   getfield Field eb n I
L811:   if_icmplt L736
L814:   iload 6
L816:   ifeq L827
L819:   aload_0
L820:   sipush 2992
L823:   invokevirtual Method eb a (I)V
L826:   return
L827:   aload_0
L828:   aload_0
L829:   getfield Field eb j B
L832:   invokevirtual Method eb a (B)V
L835:   return
L836:   
    .end code
.end method

.method public final a : (IIIII)V
    .code stack 6 locals 15
L0:     getstatic Field eb Rb Z
L3:     istore 14
L5:     iconst_0
L6:     istore 6
L8:     iload 14
L10:    ifeq L463
L13:    aload_0
L14:    getfield Field eb s [I
L17:    iload 6
L19:    iaload
L20:    istore 7
L22:    aload_0
L23:    getfield Field eb t [I
L26:    iload 6
L28:    iaload
L29:    istore 8
L31:    aload_0
L32:    getfield Field eb u [I
L35:    iload 6
L37:    iaload
L38:    istore 9
L40:    aload_0
L41:    getfield Field eb y [I
L44:    ifnonnull L244
L47:    aload_0
L48:    getfield Field eb B [I
L51:    iload 6
L53:    iaload
L54:    istore 12
L56:    aload_0
L57:    getfield Field eb W [Ln;
L60:    iload 7
L62:    aaload
L63:    astore 10
L65:    iload_1
L66:    iload_3
L67:    aload 10
L69:    getfield Field n a I
L72:    imul
L73:    iload 4
L75:    aload 10
L77:    getfield Field n b I
L80:    imul
L81:    iadd
L82:    iload 5
L84:    aload 10
L86:    getfield Field n c I
L89:    imul
L90:    iadd
L91:    iload_2
L92:    aload 10
L94:    getfield Field n d I
L97:    imul
L98:    idiv
L99:    iadd
L100:   istore 11
L102:   aload_0
L103:   getfield Field eb v [I
L106:   iload 6
L108:   iload 12
L110:   iload 11
L112:   iconst_0
L113:   invokestatic Method eb a (III)I
L116:   iastore
L117:   aload_0
L118:   getfield Field eb W [Ln;
L121:   iload 8
L123:   aaload
L124:   astore 10
L126:   iload_1
L127:   iload_3
L128:   aload 10
L130:   getfield Field n a I
L133:   imul
L134:   iload 4
L136:   aload 10
L138:   getfield Field n b I
L141:   imul
L142:   iadd
L143:   iload 5
L145:   aload 10
L147:   getfield Field n c I
L150:   imul
L151:   iadd
L152:   iload_2
L153:   aload 10
L155:   getfield Field n d I
L158:   imul
L159:   idiv
L160:   iadd
L161:   istore 11
L163:   aload_0
L164:   getfield Field eb w [I
L167:   iload 6
L169:   iload 12
L171:   iload 11
L173:   iconst_0
L174:   invokestatic Method eb a (III)I
L177:   iastore
L178:   aload_0
L179:   getfield Field eb W [Ln;
L182:   iload 9
L184:   aaload
L185:   astore 10
L187:   iload_1
L188:   iload_3
L189:   aload 10
L191:   getfield Field n a I
L194:   imul
L195:   iload 4
L197:   aload 10
L199:   getfield Field n b I
L202:   imul
L203:   iadd
L204:   iload 5
L206:   aload 10
L208:   getfield Field n c I
L211:   imul
L212:   iadd
L213:   iload_2
L214:   aload 10
L216:   getfield Field n d I
L219:   imul
L220:   idiv
L221:   iadd
L222:   istore 11
L224:   aload_0
L225:   getfield Field eb x [I
L228:   iload 6
L230:   iload 12
L232:   iload 11
L234:   iconst_0
L235:   invokestatic Method eb a (III)I
L238:   iastore
L239:   iload 14
L241:   ifeq L460
L244:   aload_0
L245:   getfield Field eb y [I
L248:   iload 6
L250:   iaload
L251:   iconst_1
L252:   iand
L253:   ifne L460
L256:   aload_0
L257:   getfield Field eb B [I
L260:   iload 6
L262:   iaload
L263:   istore 12
L265:   aload_0
L266:   getfield Field eb y [I
L269:   iload 6
L271:   iaload
L272:   istore 13
L274:   aload_0
L275:   getfield Field eb W [Ln;
L278:   iload 7
L280:   aaload
L281:   astore 10
L283:   iload_1
L284:   iload_3
L285:   aload 10
L287:   getfield Field n a I
L290:   imul
L291:   iload 4
L293:   aload 10
L295:   getfield Field n b I
L298:   imul
L299:   iadd
L300:   iload 5
L302:   aload 10
L304:   getfield Field n c I
L307:   imul
L308:   iadd
L309:   iload_2
L310:   aload 10
L312:   getfield Field n d I
L315:   imul
L316:   idiv
L317:   iadd
L318:   istore 11
L320:   aload_0
L321:   getfield Field eb v [I
L324:   iload 6
L326:   iload 12
L328:   iload 11
L330:   iload 13
L332:   invokestatic Method eb a (III)I
L335:   iastore
L336:   aload_0
L337:   getfield Field eb W [Ln;
L340:   iload 8
L342:   aaload
L343:   astore 10
L345:   iload_1
L346:   iload_3
L347:   aload 10
L349:   getfield Field n a I
L352:   imul
L353:   iload 4
L355:   aload 10
L357:   getfield Field n b I
L360:   imul
L361:   iadd
L362:   iload 5
L364:   aload 10
L366:   getfield Field n c I
L369:   imul
L370:   iadd
L371:   iload_2
L372:   aload 10
L374:   getfield Field n d I
L377:   imul
L378:   idiv
L379:   iadd
L380:   istore 11
L382:   aload_0
L383:   getfield Field eb w [I
L386:   iload 6
L388:   iload 12
L390:   iload 11
L392:   iload 13
L394:   invokestatic Method eb a (III)I
L397:   iastore
L398:   aload_0
L399:   getfield Field eb W [Ln;
L402:   iload 9
L404:   aaload
L405:   astore 10
L407:   iload_1
L408:   iload_3
L409:   aload 10
L411:   getfield Field n a I
L414:   imul
L415:   iload 4
L417:   aload 10
L419:   getfield Field n b I
L422:   imul
L423:   iadd
L424:   iload 5
L426:   aload 10
L428:   getfield Field n c I
L431:   imul
L432:   iadd
L433:   iload_2
L434:   aload 10
L436:   getfield Field n d I
L439:   imul
L440:   idiv
L441:   iadd
L442:   istore 11
L444:   aload_0
L445:   getfield Field eb x [I
L448:   iload 6
L450:   iload 12
L452:   iload 11
L454:   iload 13
L456:   invokestatic Method eb a (III)I
L459:   iastore
L460:   iinc 6 1
L463:   iload 6
L465:   aload_0
L466:   getfield Field eb r I
L469:   if_icmplt L13
L472:   aload_0
L473:   aconst_null
L474:   putfield Field eb W [Ln;
L477:   aload_0
L478:   aconst_null
L479:   putfield Field eb X [Ln;
L482:   aload_0
L483:   aconst_null
L484:   putfield Field eb R [I
L487:   aload_0
L488:   aconst_null
L489:   putfield Field eb S [I
L492:   aload_0
L493:   getfield Field eb y [I
L496:   ifnull L533
L499:   iconst_0
L500:   istore 7
L502:   iload 14
L504:   ifeq L524
L507:   aload_0
L508:   getfield Field eb y [I
L511:   iload 7
L513:   iaload
L514:   iconst_2
L515:   iand
L516:   iconst_2
L517:   if_icmpne L521
L520:   return
L521:   iinc 7 1
L524:   iload 7
L526:   aload_0
L527:   getfield Field eb r I
L530:   if_icmplt L507
L533:   aload_0
L534:   aconst_null
L535:   putfield Field eb B [I
L538:   return
L539:   
    .end code
.end method

.method public static final a : (III)I
    .code stack 4 locals 4
L0:     getstatic Field eb Rb Z
L3:     istore_3
L4:     iload_2
L5:     iconst_2
L6:     iand
L7:     iconst_2
L8:     if_icmpne L37
L11:    iload_1
L12:    ifge L21
L15:    iconst_0
L16:    istore_1
L17:    iload_3
L18:    ifeq L30
L21:    iload_1
L22:    bipush 127
L24:    if_icmple L30
L27:    bipush 127
L29:    istore_1
L30:    bipush 127
L32:    iload_1
L33:    isub
L34:    istore_1
L35:    iload_1
L36:    ireturn
L37:    iload_1
L38:    iload_0
L39:    bipush 127
L41:    iand
L42:    imul
L43:    bipush 7
L45:    ishr
L46:    istore_1
L47:    iload_1
L48:    iconst_2
L49:    if_icmpge L58
L52:    iconst_2
L53:    istore_1
L54:    iload_3
L55:    ifeq L67
L58:    iload_1
L59:    bipush 126
L61:    if_icmple L67
L64:    bipush 126
L66:    istore_1
L67:    iload_0
L68:    ldc 65408
L70:    iand
L71:    iload_1
L72:    iadd
L73:    ireturn
L74:    
    .end code
.end method

.method public final a : (IIIIIII)V
    .code stack 6 locals 24
L0:     getstatic Field gb F I
L3:     istore 8
L5:     getstatic Field gb G I
L8:     istore 9
L10:    getstatic Field eb Nb [I
L13:    iload_1
L14:    iaload
L15:    istore 10
L17:    getstatic Field eb Ob [I
L20:    iload_1
L21:    iaload
L22:    istore 11
L24:    getstatic Field eb Nb [I
L27:    iload_2
L28:    iaload
L29:    istore 12
L31:    getstatic Field eb Ob [I
L34:    iload_2
L35:    iaload
L36:    istore 13
L38:    getstatic Field eb Nb [I
L41:    iload_3
L42:    iaload
L43:    istore 14
L45:    getstatic Field eb Ob [I
L48:    iload_3
L49:    iaload
L50:    istore 15
L52:    getstatic Field eb Nb [I
L55:    iload 4
L57:    iaload
L58:    istore 16
L60:    getstatic Field eb Ob [I
L63:    iload 4
L65:    iaload
L66:    istore 17
L68:    iload 6
L70:    iload 16
L72:    imul
L73:    iload 7
L75:    iload 17
L77:    imul
L78:    iadd
L79:    bipush 16
L81:    ishr
L82:    istore 18
L84:    iconst_0
L85:    istore 19
L87:    getstatic Field eb Rb Z
L90:    ifeq L376
L93:    aload_0
L94:    getfield Field eb o [I
L97:    iload 19
L99:    iaload
L100:   istore 20
L102:   aload_0
L103:   getfield Field eb p [I
L106:   iload 19
L108:   iaload
L109:   istore 21
L111:   aload_0
L112:   getfield Field eb q [I
L115:   iload 19
L117:   iaload
L118:   istore 22
L120:   iload_3
L121:   ifeq L160
L124:   iload 21
L126:   iload 14
L128:   imul
L129:   iload 20
L131:   iload 15
L133:   imul
L134:   iadd
L135:   bipush 16
L137:   ishr
L138:   istore 23
L140:   iload 21
L142:   iload 15
L144:   imul
L145:   iload 20
L147:   iload 14
L149:   imul
L150:   isub
L151:   bipush 16
L153:   ishr
L154:   istore 21
L156:   iload 23
L158:   istore 20
L160:   iload_1
L161:   ifeq L200
L164:   iload 21
L166:   iload 11
L168:   imul
L169:   iload 22
L171:   iload 10
L173:   imul
L174:   isub
L175:   bipush 16
L177:   ishr
L178:   istore 23
L180:   iload 21
L182:   iload 10
L184:   imul
L185:   iload 22
L187:   iload 11
L189:   imul
L190:   iadd
L191:   bipush 16
L193:   ishr
L194:   istore 22
L196:   iload 23
L198:   istore 21
L200:   iload_2
L201:   ifeq L240
L204:   iload 22
L206:   iload 12
L208:   imul
L209:   iload 20
L211:   iload 13
L213:   imul
L214:   iadd
L215:   bipush 16
L217:   ishr
L218:   istore 23
L220:   iload 22
L222:   iload 13
L224:   imul
L225:   iload 20
L227:   iload 12
L229:   imul
L230:   isub
L231:   bipush 16
L233:   ishr
L234:   istore 22
L236:   iload 23
L238:   istore 20
L240:   iload 20
L242:   iload 5
L244:   iadd
L245:   istore 20
L247:   iload 21
L249:   iload 6
L251:   iadd
L252:   istore 21
L254:   iload 22
L256:   iload 7
L258:   iadd
L259:   istore 22
L261:   iload 21
L263:   iload 17
L265:   imul
L266:   iload 22
L268:   iload 16
L270:   imul
L271:   isub
L272:   bipush 16
L274:   ishr
L275:   istore 23
L277:   iload 21
L279:   iload 16
L281:   imul
L282:   iload 22
L284:   iload 17
L286:   imul
L287:   iadd
L288:   bipush 16
L290:   ishr
L291:   istore 22
L293:   iload 23
L295:   istore 21
L297:   getstatic Field eb rb [I
L300:   iload 19
L302:   iload 22
L304:   iload 18
L306:   isub
L307:   iastore
L308:   getstatic Field eb pb [I
L311:   iload 19
L313:   iload 8
L315:   iload 20
L317:   bipush 9
L319:   ishl
L320:   iload 22
L322:   idiv
L323:   iadd
L324:   iastore
L325:   getstatic Field eb qb [I
L328:   iload 19
L330:   iload 9
L332:   iload 21
L334:   bipush 9
L336:   ishl
L337:   iload 22
L339:   idiv
L340:   iadd
L341:   iastore
L342:   aload_0
L343:   getfield Field eb D I
L346:   ifle L373
L349:   getstatic Field eb sb [I
L352:   iload 19
L354:   iload 20
L356:   iastore
L357:   getstatic Field eb tb [I
L360:   iload 19
L362:   iload 21
L364:   iastore
L365:   getstatic Field eb ub [I
L368:   iload 19
L370:   iload 22
L372:   iastore
L373:   iinc 19 1
L376:   iload 19
L378:   aload_0
L379:   getfield Field eb n I
L382:   if_icmplt L93
        .catch java/lang/Exception from L385 to L392 using L393
L385:   aload_0
L386:   iconst_0
L387:   iconst_0
L388:   iconst_0
L389:   invokespecial Method eb a (ZZI)V
L392:   return
L393:   pop
L394:   return
L395:   
    .end code
.end method

.method public final a : (IIIIIIIII)V
    .code stack 6 locals 35
L0:     getstatic Field eb Rb Z
L3:     istore 34
L5:     iload 8
L7:     iload 5
L9:     imul
L10:    iload 6
L12:    iload 4
L14:    imul
L15:    isub
L16:    bipush 16
L18:    ishr
L19:    istore 10
L21:    iload 7
L23:    iload_2
L24:    imul
L25:    iload 10
L27:    iload_3
L28:    imul
L29:    iadd
L30:    bipush 16
L32:    ishr
L33:    istore 11
L35:    aload_0
L36:    getfield Field eb L I
L39:    iload_3
L40:    imul
L41:    bipush 16
L43:    ishr
L44:    istore 12
L46:    iload 11
L48:    iload 12
L50:    iadd
L51:    istore 13
L53:    iload 13
L55:    bipush 50
L57:    if_icmple L68
L60:    iload 11
L62:    sipush 3500
L65:    if_icmplt L69
L68:    return
L69:    iload 8
L71:    iload 4
L73:    imul
L74:    iload 6
L76:    iload 5
L78:    imul
L79:    iadd
L80:    bipush 16
L82:    ishr
L83:    istore 14
L85:    iload 14
L87:    aload_0
L88:    getfield Field eb L I
L91:    isub
L92:    bipush 9
L94:    ishl
L95:    istore 15
L97:    iload 15
L99:    iload 13
L101:   idiv
L102:   getstatic Field fb s I
L105:   if_icmplt L109
L108:   return
L109:   iload 14
L111:   aload_0
L112:   getfield Field eb L I
L115:   iadd
L116:   bipush 9
L118:   ishl
L119:   istore 16
L121:   iload 16
L123:   iload 13
L125:   idiv
L126:   getstatic Field fb s I
L129:   ineg
L130:   if_icmpgt L134
L133:   return
L134:   iload 7
L136:   iload_3
L137:   imul
L138:   iload 10
L140:   iload_2
L141:   imul
L142:   isub
L143:   bipush 16
L145:   ishr
L146:   istore 17
L148:   aload_0
L149:   getfield Field eb L I
L152:   iload_2
L153:   imul
L154:   bipush 16
L156:   ishr
L157:   istore 18
L159:   iload 17
L161:   iload 18
L163:   iadd
L164:   bipush 9
L166:   ishl
L167:   istore 19
L169:   iload 19
L171:   iload 13
L173:   idiv
L174:   getstatic Field fb t I
L177:   ineg
L178:   if_icmpgt L182
L181:   return
L182:   iload 18
L184:   aload_0
L185:   getfield Field eb M I
L188:   iload_3
L189:   imul
L190:   bipush 16
L192:   ishr
L193:   iadd
L194:   istore 20
L196:   iload 17
L198:   iload 20
L200:   isub
L201:   bipush 9
L203:   ishl
L204:   istore 21
L206:   iload 21
L208:   iload 13
L210:   idiv
L211:   getstatic Field fb t I
L214:   if_icmplt L218
L217:   return
L218:   iload 12
L220:   aload_0
L221:   getfield Field eb M I
L224:   iload_2
L225:   imul
L226:   bipush 16
L228:   ishr
L229:   iadd
L230:   istore 22
L232:   iconst_0
L233:   istore 23
L235:   iload 11
L237:   iload 22
L239:   isub
L240:   bipush 50
L242:   if_icmpgt L248
L245:   iconst_1
L246:   istore 23
L248:   iconst_0
L249:   istore 24
L251:   iload 9
L253:   ifle L432
L256:   getstatic Field eb Ib Z
L259:   ifeq L432
L262:   iload 11
L264:   iload 12
L266:   isub
L267:   istore 25
L269:   iload 25
L271:   bipush 50
L273:   if_icmpgt L280
L276:   bipush 50
L278:   istore 25
L280:   iload 14
L282:   ifle L304
L285:   iload 15
L287:   iload 13
L289:   idiv
L290:   istore 15
L292:   iload 16
L294:   iload 25
L296:   idiv
L297:   istore 16
L299:   iload 34
L301:   ifeq L318
L304:   iload 16
L306:   iload 13
L308:   idiv
L309:   istore 16
L311:   iload 15
L313:   iload 25
L315:   idiv
L316:   istore 15
L318:   iload 17
L320:   ifle L342
L323:   iload 21
L325:   iload 13
L327:   idiv
L328:   istore 21
L330:   iload 19
L332:   iload 25
L334:   idiv
L335:   istore 19
L337:   iload 34
L339:   ifeq L356
L342:   iload 19
L344:   iload 13
L346:   idiv
L347:   istore 19
L349:   iload 21
L351:   iload 25
L353:   idiv
L354:   istore 21
L356:   getstatic Field eb Jb I
L359:   getstatic Field gb F I
L362:   isub
L363:   istore 26
L365:   getstatic Field eb Kb I
L368:   getstatic Field gb G I
L371:   isub
L372:   istore 27
L374:   iload 26
L376:   iload 15
L378:   if_icmple L432
L381:   iload 26
L383:   iload 16
L385:   if_icmpge L432
L388:   iload 27
L390:   iload 21
L392:   if_icmple L432
L395:   iload 27
L397:   iload 19
L399:   if_icmpge L432
L402:   aload_0
L403:   getfield Field eb V Z
L406:   ifeq L429
L409:   getstatic Field eb Mb [I
L412:   getstatic Field eb Lb I
L415:   dup
L416:   iconst_1
L417:   iadd
L418:   putstatic Field eb Lb I
L421:   iload 9
L423:   iastore
L424:   iload 34
L426:   ifeq L432
L429:   iconst_1
L430:   istore 24
L432:   getstatic Field gb F I
L435:   istore 25
L437:   getstatic Field gb G I
L440:   istore 26
L442:   iconst_0
L443:   istore 27
L445:   iconst_0
L446:   istore 28
L448:   iload_1
L449:   ifeq L466
L452:   getstatic Field eb Nb [I
L455:   iload_1
L456:   iaload
L457:   istore 27
L459:   getstatic Field eb Ob [I
L462:   iload_1
L463:   iaload
L464:   istore 28
L466:   iconst_0
L467:   istore 29
L469:   iload 34
L471:   ifeq L738
L474:   aload_0
L475:   getfield Field eb o [I
L478:   iload 29
L480:   iaload
L481:   istore 30
L483:   aload_0
L484:   getfield Field eb p [I
L487:   iload 29
L489:   iaload
L490:   istore 31
L492:   aload_0
L493:   getfield Field eb q [I
L496:   iload 29
L498:   iaload
L499:   istore 32
L501:   iload_1
L502:   ifeq L541
L505:   iload 32
L507:   iload 27
L509:   imul
L510:   iload 30
L512:   iload 28
L514:   imul
L515:   iadd
L516:   bipush 16
L518:   ishr
L519:   istore 33
L521:   iload 32
L523:   iload 28
L525:   imul
L526:   iload 30
L528:   iload 27
L530:   imul
L531:   isub
L532:   bipush 16
L534:   ishr
L535:   istore 32
L537:   iload 33
L539:   istore 30
L541:   iload 30
L543:   iload 6
L545:   iadd
L546:   istore 30
L548:   iload 31
L550:   iload 7
L552:   iadd
L553:   istore 31
L555:   iload 32
L557:   iload 8
L559:   iadd
L560:   istore 32
L562:   iload 32
L564:   iload 4
L566:   imul
L567:   iload 30
L569:   iload 5
L571:   imul
L572:   iadd
L573:   bipush 16
L575:   ishr
L576:   istore 33
L578:   iload 32
L580:   iload 5
L582:   imul
L583:   iload 30
L585:   iload 4
L587:   imul
L588:   isub
L589:   bipush 16
L591:   ishr
L592:   istore 32
L594:   iload 33
L596:   istore 30
L598:   iload 31
L600:   iload_3
L601:   imul
L602:   iload 32
L604:   iload_2
L605:   imul
L606:   isub
L607:   bipush 16
L609:   ishr
L610:   istore 33
L612:   iload 31
L614:   iload_2
L615:   imul
L616:   iload 32
L618:   iload_3
L619:   imul
L620:   iadd
L621:   bipush 16
L623:   ishr
L624:   istore 32
L626:   iload 33
L628:   istore 31
L630:   getstatic Field eb rb [I
L633:   iload 29
L635:   iload 32
L637:   iload 11
L639:   isub
L640:   iastore
L641:   iload 32
L643:   bipush 50
L645:   if_icmplt L687
L648:   getstatic Field eb pb [I
L651:   iload 29
L653:   iload 25
L655:   iload 30
L657:   bipush 9
L659:   ishl
L660:   iload 32
L662:   idiv
L663:   iadd
L664:   iastore
L665:   getstatic Field eb qb [I
L668:   iload 29
L670:   iload 26
L672:   iload 31
L674:   bipush 9
L676:   ishl
L677:   iload 32
L679:   idiv
L680:   iadd
L681:   iastore
L682:   iload 34
L684:   ifeq L699
L687:   getstatic Field eb pb [I
L690:   iload 29
L692:   sipush -5000
L695:   iastore
L696:   iconst_1
L697:   istore 23
L699:   iload 23
L701:   ifne L711
L704:   aload_0
L705:   getfield Field eb D I
L708:   ifle L735
L711:   getstatic Field eb sb [I
L714:   iload 29
L716:   iload 30
L718:   iastore
L719:   getstatic Field eb tb [I
L722:   iload 29
L724:   iload 31
L726:   iastore
L727:   getstatic Field eb ub [I
L730:   iload 29
L732:   iload 32
L734:   iastore
L735:   iinc 29 1
L738:   iload 29
L740:   aload_0
L741:   getfield Field eb n I
L744:   if_icmplt L474
        .catch java/lang/Exception from L747 to L757 using L758
L747:   aload_0
L748:   iload 23
L750:   iload 24
L752:   iload 9
L754:   invokespecial Method eb a (ZZI)V
L757:   return
L758:   pop
L759:   return
L760:   
    .end code
.end method

.method private final a : (ZZI)V
    .code stack 10 locals 21
L0:     getstatic Field eb Rb Z
L3:     istore 20
L5:     iconst_0
L6:     istore 4
L8:     iload 20
L10:    ifeq L23
L13:    getstatic Field eb vb [I
L16:    iload 4
L18:    iconst_0
L19:    iastore
L20:    iinc 4 1
L23:    iload 4
L25:    aload_0
L26:    getfield Field eb O I
L29:    if_icmplt L13
L32:    iconst_0
L33:    istore 5
L35:    iload 20
L37:    ifeq L414
L40:    aload_0
L41:    getfield Field eb y [I
L44:    ifnull L58
L47:    aload_0
L48:    getfield Field eb y [I
L51:    iload 5
L53:    iaload
L54:    iconst_m1
L55:    if_icmpeq L411
L58:    aload_0
L59:    getfield Field eb s [I
L62:    iload 5
L64:    iaload
L65:    istore 6
L67:    aload_0
L68:    getfield Field eb t [I
L71:    iload 5
L73:    iaload
L74:    istore 7
L76:    aload_0
L77:    getfield Field eb u [I
L80:    iload 5
L82:    iaload
L83:    istore 8
L85:    getstatic Field eb pb [I
L88:    iload 6
L90:    iaload
L91:    istore 9
L93:    getstatic Field eb pb [I
L96:    iload 7
L98:    iaload
L99:    istore 10
L101:   getstatic Field eb pb [I
L104:   iload 8
L106:   iaload
L107:   istore 11
L109:   iload_1
L110:   ifeq L198
L113:   iload 9
L115:   sipush -5000
L118:   if_icmpeq L137
L121:   iload 10
L123:   sipush -5000
L126:   if_icmpeq L137
L129:   iload 11
L131:   sipush -5000
L134:   if_icmpne L198
L137:   getstatic Field eb ob [Z
L140:   iload 5
L142:   iconst_1
L143:   bastore
L144:   getstatic Field eb rb [I
L147:   iload 6
L149:   iaload
L150:   getstatic Field eb rb [I
L153:   iload 7
L155:   iaload
L156:   iadd
L157:   getstatic Field eb rb [I
L160:   iload 8
L162:   iaload
L163:   iadd
L164:   iconst_3
L165:   idiv
L166:   aload_0
L167:   getfield Field eb P I
L170:   iadd
L171:   istore 12
L173:   getstatic Field eb wb [[I
L176:   iload 12
L178:   aaload
L179:   getstatic Field eb vb [I
L182:   iload 12
L184:   dup2
L185:   iaload
L186:   dup_x2
L187:   iconst_1
L188:   iadd
L189:   iastore
L190:   iload 5
L192:   iastore
L193:   iload 20
L195:   ifeq L411
L198:   iload_2
L199:   ifeq L255
L202:   aload_0
L203:   getstatic Field eb Jb I
L206:   getstatic Field eb Kb I
L209:   getstatic Field eb qb [I
L212:   iload 6
L214:   iaload
L215:   getstatic Field eb qb [I
L218:   iload 7
L220:   iaload
L221:   getstatic Field eb qb [I
L224:   iload 8
L226:   iaload
L227:   iload 9
L229:   iload 10
L231:   iload 11
L233:   invokespecial Method eb a (IIIIIIII)Z
L236:   ifeq L255
L239:   getstatic Field eb Mb [I
L242:   getstatic Field eb Lb I
L245:   dup
L246:   iconst_1
L247:   iadd
L248:   putstatic Field eb Lb I
L251:   iload_3
L252:   iastore
L253:   iconst_0
L254:   istore_2
L255:   iload 9
L257:   iload 10
L259:   isub
L260:   getstatic Field eb qb [I
L263:   iload 8
L265:   iaload
L266:   getstatic Field eb qb [I
L269:   iload 7
L271:   iaload
L272:   isub
L273:   imul
L274:   getstatic Field eb qb [I
L277:   iload 6
L279:   iaload
L280:   getstatic Field eb qb [I
L283:   iload 7
L285:   iaload
L286:   isub
L287:   iload 11
L289:   iload 10
L291:   isub
L292:   imul
L293:   isub
L294:   ifle L411
L297:   getstatic Field eb ob [Z
L300:   iload 5
L302:   iconst_0
L303:   bastore
L304:   iload 9
L306:   iflt L343
L309:   iload 10
L311:   iflt L343
L314:   iload 11
L316:   iflt L343
L319:   iload 9
L321:   getstatic Field fb r I
L324:   if_icmpgt L343
L327:   iload 10
L329:   getstatic Field fb r I
L332:   if_icmpgt L343
L335:   iload 11
L337:   getstatic Field fb r I
L340:   if_icmple L355
L343:   getstatic Field eb nb [Z
L346:   iload 5
L348:   iconst_1
L349:   bastore
L350:   iload 20
L352:   ifeq L362
L355:   getstatic Field eb nb [Z
L358:   iload 5
L360:   iconst_0
L361:   bastore
L362:   getstatic Field eb rb [I
L365:   iload 6
L367:   iaload
L368:   getstatic Field eb rb [I
L371:   iload 7
L373:   iaload
L374:   iadd
L375:   getstatic Field eb rb [I
L378:   iload 8
L380:   iaload
L381:   iadd
L382:   iconst_3
L383:   idiv
L384:   aload_0
L385:   getfield Field eb P I
L388:   iadd
L389:   istore 12
L391:   getstatic Field eb wb [[I
L394:   iload 12
L396:   aaload
L397:   getstatic Field eb vb [I
L400:   iload 12
L402:   dup2
L403:   iaload
L404:   dup_x2
L405:   iconst_1
L406:   iadd
L407:   iastore
L408:   iload 5
L410:   iastore
L411:   iinc 5 1
L414:   iload 5
L416:   aload_0
L417:   getfield Field eb r I
L420:   if_icmplt L40
L423:   aload_0
L424:   getfield Field eb z [I
L427:   ifnonnull L500
L430:   aload_0
L431:   getfield Field eb O I
L434:   iconst_1
L435:   isub
L436:   istore 6
L438:   iload 20
L440:   ifeq L494
L443:   getstatic Field eb vb [I
L446:   iload 6
L448:   iaload
L449:   istore 7
L451:   iload 7
L453:   ifle L491
L456:   getstatic Field eb wb [[I
L459:   iload 6
L461:   aaload
L462:   astore 8
L464:   iconst_0
L465:   istore 9
L467:   iload 20
L469:   ifeq L484
L472:   aload_0
L473:   aload 8
L475:   iload 9
L477:   iaload
L478:   invokespecial Method eb f (I)V
L481:   iinc 9 1
L484:   iload 9
L486:   iload 7
L488:   if_icmplt L472
L491:   iinc 6 -1
L494:   iload 6
L496:   ifge L443
L499:   return
L500:   iconst_0
L501:   istore 6
L503:   iload 20
L505:   ifeq L525
L508:   getstatic Field eb xb [I
L511:   iload 6
L513:   iconst_0
L514:   iastore
L515:   getstatic Field eb Bb [I
L518:   iload 6
L520:   iconst_0
L521:   iastore
L522:   iinc 6 1
L525:   iload 6
L527:   bipush 12
L529:   if_icmplt L508
L532:   aload_0
L533:   getfield Field eb O I
L536:   iconst_1
L537:   isub
L538:   istore 7
L540:   iload 20
L542:   ifeq L678
L545:   getstatic Field eb vb [I
L548:   iload 7
L550:   iaload
L551:   istore 8
L553:   iload 8
L555:   ifle L675
L558:   getstatic Field eb wb [[I
L561:   iload 7
L563:   aaload
L564:   astore 9
L566:   iconst_0
L567:   istore 10
L569:   iload 20
L571:   ifeq L668
L574:   aload 9
L576:   iload 10
L578:   iaload
L579:   istore 11
L581:   aload_0
L582:   getfield Field eb z [I
L585:   iload 11
L587:   iaload
L588:   istore 12
L590:   getstatic Field eb xb [I
L593:   iload 12
L595:   dup2
L596:   iaload
L597:   dup_x2
L598:   iconst_1
L599:   iadd
L600:   iastore
L601:   istore 13
L603:   getstatic Field eb yb [[I
L606:   iload 12
L608:   aaload
L609:   iload 13
L611:   iload 11
L613:   iastore
L614:   iload 12
L616:   bipush 10
L618:   if_icmpge L637
L621:   getstatic Field eb Bb [I
L624:   iload 12
L626:   dup2
L627:   iaload
L628:   iload 7
L630:   iadd
L631:   iastore
L632:   iload 20
L634:   ifeq L665
L637:   iload 12
L639:   bipush 10
L641:   if_icmpne L657
L644:   getstatic Field eb zb [I
L647:   iload 13
L649:   iload 7
L651:   iastore
L652:   iload 20
L654:   ifeq L665
L657:   getstatic Field eb Ab [I
L660:   iload 13
L662:   iload 7
L664:   iastore
L665:   iinc 10 1
L668:   iload 10
L670:   iload 8
L672:   if_icmplt L574
L675:   iinc 7 -1
L678:   iload 7
L680:   ifge L545
L683:   iconst_0
L684:   istore 8
L686:   getstatic Field eb xb [I
L689:   iconst_1
L690:   iaload
L691:   ifgt L702
L694:   getstatic Field eb xb [I
L697:   iconst_2
L698:   iaload
L699:   ifle L727
L702:   getstatic Field eb Bb [I
L705:   iconst_1
L706:   iaload
L707:   getstatic Field eb Bb [I
L710:   iconst_2
L711:   iaload
L712:   iadd
L713:   getstatic Field eb xb [I
L716:   iconst_1
L717:   iaload
L718:   getstatic Field eb xb [I
L721:   iconst_2
L722:   iaload
L723:   iadd
L724:   idiv
L725:   istore 8
L727:   iconst_0
L728:   istore 9
L730:   getstatic Field eb xb [I
L733:   iconst_3
L734:   iaload
L735:   ifgt L746
L738:   getstatic Field eb xb [I
L741:   iconst_4
L742:   iaload
L743:   ifle L771
L746:   getstatic Field eb Bb [I
L749:   iconst_3
L750:   iaload
L751:   getstatic Field eb Bb [I
L754:   iconst_4
L755:   iaload
L756:   iadd
L757:   getstatic Field eb xb [I
L760:   iconst_3
L761:   iaload
L762:   getstatic Field eb xb [I
L765:   iconst_4
L766:   iaload
L767:   iadd
L768:   idiv
L769:   istore 9
L771:   iconst_0
L772:   istore 10
L774:   getstatic Field eb xb [I
L777:   bipush 6
L779:   iaload
L780:   ifgt L792
L783:   getstatic Field eb xb [I
L786:   bipush 8
L788:   iaload
L789:   ifle L821
L792:   getstatic Field eb Bb [I
L795:   bipush 6
L797:   iaload
L798:   getstatic Field eb Bb [I
L801:   bipush 8
L803:   iaload
L804:   iadd
L805:   getstatic Field eb xb [I
L808:   bipush 6
L810:   iaload
L811:   getstatic Field eb xb [I
L814:   bipush 8
L816:   iaload
L817:   iadd
L818:   idiv
L819:   istore 10
L821:   iconst_0
L822:   istore 12
L824:   getstatic Field eb xb [I
L827:   bipush 10
L829:   iaload
L830:   istore 13
L832:   getstatic Field eb yb [[I
L835:   bipush 10
L837:   aaload
L838:   astore 14
L840:   getstatic Field eb zb [I
L843:   astore 15
L845:   iload 12
L847:   iload 13
L849:   if_icmpne L876
L852:   iconst_0
L853:   istore 12
L855:   getstatic Field eb xb [I
L858:   bipush 11
L860:   iaload
L861:   istore 13
L863:   getstatic Field eb yb [[I
L866:   bipush 11
L868:   aaload
L869:   astore 14
L871:   getstatic Field eb Ab [I
L874:   astore 15
L876:   iload 12
L878:   iload 13
L880:   if_icmpge L895
L883:   aload 15
L885:   iload 12
L887:   iaload
L888:   istore 11
L890:   iload 20
L892:   ifeq L900
L895:   sipush -1000
L898:   istore 11
L900:   iconst_0
L901:   istore 16
L903:   iload 20
L905:   ifeq L1236
L908:   aload_0
L909:   aload 14
L911:   iload 12
L913:   iinc 12 1
L916:   iaload
L917:   invokespecial Method eb f (I)V
L920:   iload 12
L922:   iload 13
L924:   if_icmpne L962
L927:   aload 14
L929:   getstatic Field eb yb [[I
L932:   bipush 11
L934:   aaload
L935:   if_acmpeq L962
L938:   iconst_0
L939:   istore 12
L941:   getstatic Field eb xb [I
L944:   bipush 11
L946:   iaload
L947:   istore 13
L949:   getstatic Field eb yb [[I
L952:   bipush 11
L954:   aaload
L955:   astore 14
L957:   getstatic Field eb Ab [I
L960:   astore 15
L962:   iload 12
L964:   iload 13
L966:   if_icmpge L981
L969:   aload 15
L971:   iload 12
L973:   iaload
L974:   istore 11
L976:   iload 20
L978:   ifeq L986
L981:   sipush -1000
L984:   istore 11
L986:   iload 16
L988:   ifne L1081
L991:   iload 11
L993:   iload 8
L995:   if_icmpgt L908
L998:   iload 20
L1000:  ifeq L1081
L1003:  aload_0
L1004:  aload 14
L1006:  iload 12
L1008:  iinc 12 1
L1011:  iaload
L1012:  invokespecial Method eb f (I)V
L1015:  iload 12
L1017:  iload 13
L1019:  if_icmpne L1057
L1022:  aload 14
L1024:  getstatic Field eb yb [[I
L1027:  bipush 11
L1029:  aaload
L1030:  if_acmpeq L1057
L1033:  iconst_0
L1034:  istore 12
L1036:  getstatic Field eb xb [I
L1039:  bipush 11
L1041:  iaload
L1042:  istore 13
L1044:  getstatic Field eb yb [[I
L1047:  bipush 11
L1049:  aaload
L1050:  astore 14
L1052:  getstatic Field eb Ab [I
L1055:  astore 15
L1057:  iload 12
L1059:  iload 13
L1061:  if_icmpge L1076
L1064:  aload 15
L1066:  iload 12
L1068:  iaload
L1069:  istore 11
L1071:  iload 20
L1073:  ifeq L1081
L1076:  sipush -1000
L1079:  istore 11
L1081:  iload 16
L1083:  iconst_3
L1084:  if_icmpne L1177
L1087:  iload 11
L1089:  iload 9
L1091:  if_icmpgt L1003
L1094:  iload 20
L1096:  ifeq L1177
L1099:  aload_0
L1100:  aload 14
L1102:  iload 12
L1104:  iinc 12 1
L1107:  iaload
L1108:  invokespecial Method eb f (I)V
L1111:  iload 12
L1113:  iload 13
L1115:  if_icmpne L1153
L1118:  aload 14
L1120:  getstatic Field eb yb [[I
L1123:  bipush 11
L1125:  aaload
L1126:  if_acmpeq L1153
L1129:  iconst_0
L1130:  istore 12
L1132:  getstatic Field eb xb [I
L1135:  bipush 11
L1137:  iaload
L1138:  istore 13
L1140:  getstatic Field eb yb [[I
L1143:  bipush 11
L1145:  aaload
L1146:  astore 14
L1148:  getstatic Field eb Ab [I
L1151:  astore 15
L1153:  iload 12
L1155:  iload 13
L1157:  if_icmpge L1172
L1160:  aload 15
L1162:  iload 12
L1164:  iaload
L1165:  istore 11
L1167:  iload 20
L1169:  ifeq L1177
L1172:  sipush -1000
L1175:  istore 11
L1177:  iload 16
L1179:  iconst_5
L1180:  if_icmpne L1190
L1183:  iload 11
L1185:  iload 10
L1187:  if_icmpgt L1099
L1190:  getstatic Field eb xb [I
L1193:  iload 16
L1195:  iaload
L1196:  istore 17
L1198:  getstatic Field eb yb [[I
L1201:  iload 16
L1203:  aaload
L1204:  astore 18
L1206:  iconst_0
L1207:  istore 19
L1209:  iload 20
L1211:  ifeq L1226
L1214:  aload_0
L1215:  aload 18
L1217:  iload 19
L1219:  iaload
L1220:  invokespecial Method eb f (I)V
L1223:  iinc 19 1
L1226:  iload 19
L1228:  iload 17
L1230:  if_icmplt L1214
L1233:  iinc 16 1
L1236:  iload 16
L1238:  bipush 10
L1240:  if_icmplt L986
L1243:  iload 20
L1245:  ifeq L1326
L1248:  aload_0
L1249:  aload 14
L1251:  iload 12
L1253:  iinc 12 1
L1256:  iaload
L1257:  invokespecial Method eb f (I)V
L1260:  iload 12
L1262:  iload 13
L1264:  if_icmpne L1302
L1267:  aload 14
L1269:  getstatic Field eb yb [[I
L1272:  bipush 11
L1274:  aaload
L1275:  if_acmpeq L1302
L1278:  iconst_0
L1279:  istore 12
L1281:  getstatic Field eb yb [[I
L1284:  bipush 11
L1286:  aaload
L1287:  astore 14
L1289:  getstatic Field eb xb [I
L1292:  bipush 11
L1294:  iaload
L1295:  istore 13
L1297:  getstatic Field eb Ab [I
L1300:  astore 15
L1302:  iload 12
L1304:  iload 13
L1306:  if_icmpge L1321
L1309:  aload 15
L1311:  iload 12
L1313:  iaload
L1314:  istore 11
L1316:  iload 20
L1318:  ifeq L1326
L1321:  sipush -1000
L1324:  istore 11
L1326:  iload 11
L1328:  sipush -1000
L1331:  if_icmpne L1248
L1334:  return
L1335:  
    .end code
.end method

.method private final f : (I)V
    .code stack 21 locals 11
L0:     getstatic Field eb Rb Z
L3:     istore 10
L5:     getstatic Field eb ob [Z
L8:     iload_1
L9:     baload
L10:    ifeq L19
L13:    aload_0
L14:    iload_1
L15:    invokespecial Method eb g (I)V
L18:    return
L19:    aload_0
L20:    getfield Field eb s [I
L23:    iload_1
L24:    iaload
L25:    istore_2
L26:    aload_0
L27:    getfield Field eb t [I
L30:    iload_1
L31:    iaload
L32:    istore_3
L33:    aload_0
L34:    getfield Field eb u [I
L37:    iload_1
L38:    iaload
L39:    istore 4
L41:    getstatic Field eb nb [Z
L44:    iload_1
L45:    baload
L46:    putstatic Field gb B Z
L49:    aload_0
L50:    getfield Field eb A [I
L53:    ifnonnull L65
L56:    iconst_0
L57:    putstatic Field gb E I
L60:    iload 10
L62:    ifeq L74
L65:    aload_0
L66:    getfield Field eb A [I
L69:    iload_1
L70:    iaload
L71:    putstatic Field gb E I
L74:    aload_0
L75:    getfield Field eb y [I
L78:    ifnonnull L89
L81:    iconst_0
L82:    istore 5
L84:    iload 10
L86:    ifeq L99
L89:    aload_0
L90:    getfield Field eb y [I
L93:    iload_1
L94:    iaload
L95:    iconst_3
L96:    iand
L97:    istore 5
L99:    iload 5
L101:   ifne L158
L104:   getstatic Field eb qb [I
L107:   iload_2
L108:   iaload
L109:   getstatic Field eb qb [I
L112:   iload_3
L113:   iaload
L114:   getstatic Field eb qb [I
L117:   iload 4
L119:   iaload
L120:   getstatic Field eb pb [I
L123:   iload_2
L124:   iaload
L125:   getstatic Field eb pb [I
L128:   iload_3
L129:   iaload
L130:   getstatic Field eb pb [I
L133:   iload 4
L135:   iaload
L136:   aload_0
L137:   getfield Field eb v [I
L140:   iload_1
L141:   iaload
L142:   aload_0
L143:   getfield Field eb w [I
L146:   iload_1
L147:   iaload
L148:   aload_0
L149:   getfield Field eb x [I
L152:   iload_1
L153:   iaload
L154:   invokestatic Method gb a (IIIIIIIII)V
L157:   return
L158:   iload 5
L160:   iconst_1
L161:   if_icmpne L210
L164:   getstatic Field eb qb [I
L167:   iload_2
L168:   iaload
L169:   getstatic Field eb qb [I
L172:   iload_3
L173:   iaload
L174:   getstatic Field eb qb [I
L177:   iload 4
L179:   iaload
L180:   getstatic Field eb pb [I
L183:   iload_2
L184:   iaload
L185:   getstatic Field eb pb [I
L188:   iload_3
L189:   iaload
L190:   getstatic Field eb pb [I
L193:   iload 4
L195:   iaload
L196:   getstatic Field eb Pb [I
L199:   aload_0
L200:   getfield Field eb v [I
L203:   iload_1
L204:   iaload
L205:   iaload
L206:   invokestatic Method gb a (IIIIIII)V
L209:   return
L210:   iload 5
L212:   iconst_2
L213:   if_icmpne L367
L216:   aload_0
L217:   getfield Field eb y [I
L220:   iload_1
L221:   iaload
L222:   iconst_2
L223:   ishr
L224:   istore 6
L226:   aload_0
L227:   getfield Field eb E [I
L230:   iload 6
L232:   iaload
L233:   istore 7
L235:   aload_0
L236:   getfield Field eb F [I
L239:   iload 6
L241:   iaload
L242:   istore 8
L244:   aload_0
L245:   getfield Field eb G [I
L248:   iload 6
L250:   iaload
L251:   istore 9
L253:   getstatic Field eb qb [I
L256:   iload_2
L257:   iaload
L258:   getstatic Field eb qb [I
L261:   iload_3
L262:   iaload
L263:   getstatic Field eb qb [I
L266:   iload 4
L268:   iaload
L269:   getstatic Field eb pb [I
L272:   iload_2
L273:   iaload
L274:   getstatic Field eb pb [I
L277:   iload_3
L278:   iaload
L279:   getstatic Field eb pb [I
L282:   iload 4
L284:   iaload
L285:   aload_0
L286:   getfield Field eb v [I
L289:   iload_1
L290:   iaload
L291:   aload_0
L292:   getfield Field eb w [I
L295:   iload_1
L296:   iaload
L297:   aload_0
L298:   getfield Field eb x [I
L301:   iload_1
L302:   iaload
L303:   getstatic Field eb sb [I
L306:   iload 7
L308:   iaload
L309:   getstatic Field eb sb [I
L312:   iload 8
L314:   iaload
L315:   getstatic Field eb sb [I
L318:   iload 9
L320:   iaload
L321:   getstatic Field eb tb [I
L324:   iload 7
L326:   iaload
L327:   getstatic Field eb tb [I
L330:   iload 8
L332:   iaload
L333:   getstatic Field eb tb [I
L336:   iload 9
L338:   iaload
L339:   getstatic Field eb ub [I
L342:   iload 7
L344:   iaload
L345:   getstatic Field eb ub [I
L348:   iload 8
L350:   iaload
L351:   getstatic Field eb ub [I
L354:   iload 9
L356:   iaload
L357:   aload_0
L358:   getfield Field eb B [I
L361:   iload_1
L362:   iaload
L363:   invokestatic Method gb a (IIIIIIIIIIIIIIIIIII)V
L366:   return
L367:   iload 5
L369:   iconst_3
L370:   if_icmpne L523
L373:   aload_0
L374:   getfield Field eb y [I
L377:   iload_1
L378:   iaload
L379:   iconst_2
L380:   ishr
L381:   istore 6
L383:   aload_0
L384:   getfield Field eb E [I
L387:   iload 6
L389:   iaload
L390:   istore 7
L392:   aload_0
L393:   getfield Field eb F [I
L396:   iload 6
L398:   iaload
L399:   istore 8
L401:   aload_0
L402:   getfield Field eb G [I
L405:   iload 6
L407:   iaload
L408:   istore 9
L410:   getstatic Field eb qb [I
L413:   iload_2
L414:   iaload
L415:   getstatic Field eb qb [I
L418:   iload_3
L419:   iaload
L420:   getstatic Field eb qb [I
L423:   iload 4
L425:   iaload
L426:   getstatic Field eb pb [I
L429:   iload_2
L430:   iaload
L431:   getstatic Field eb pb [I
L434:   iload_3
L435:   iaload
L436:   getstatic Field eb pb [I
L439:   iload 4
L441:   iaload
L442:   aload_0
L443:   getfield Field eb v [I
L446:   iload_1
L447:   iaload
L448:   aload_0
L449:   getfield Field eb v [I
L452:   iload_1
L453:   iaload
L454:   aload_0
L455:   getfield Field eb v [I
L458:   iload_1
L459:   iaload
L460:   getstatic Field eb sb [I
L463:   iload 7
L465:   iaload
L466:   getstatic Field eb sb [I
L469:   iload 8
L471:   iaload
L472:   getstatic Field eb sb [I
L475:   iload 9
L477:   iaload
L478:   getstatic Field eb tb [I
L481:   iload 7
L483:   iaload
L484:   getstatic Field eb tb [I
L487:   iload 8
L489:   iaload
L490:   getstatic Field eb tb [I
L493:   iload 9
L495:   iaload
L496:   getstatic Field eb ub [I
L499:   iload 7
L501:   iaload
L502:   getstatic Field eb ub [I
L505:   iload 8
L507:   iaload
L508:   getstatic Field eb ub [I
L511:   iload 9
L513:   iaload
L514:   aload_0
L515:   getfield Field eb B [I
L518:   iload_1
L519:   iaload
L520:   invokestatic Method gb a (IIIIIIIIIIIIIIIIIII)V
L523:   return
L524:   
    .end code
.end method

.method private final g : (I)V
    .code stack 21 locals 23
L0:     getstatic Field eb Rb Z
L3:     istore 22
L5:     getstatic Field gb F I
L8:     istore_2
L9:     getstatic Field gb G I
L12:    istore_3
L13:    iconst_0
L14:    istore 4
L16:    aload_0
L17:    getfield Field eb s [I
L20:    iload_1
L21:    iaload
L22:    istore 5
L24:    aload_0
L25:    getfield Field eb t [I
L28:    iload_1
L29:    iaload
L30:    istore 6
L32:    aload_0
L33:    getfield Field eb u [I
L36:    iload_1
L37:    iaload
L38:    istore 7
L40:    getstatic Field eb ub [I
L43:    iload 5
L45:    iaload
L46:    istore 8
L48:    getstatic Field eb ub [I
L51:    iload 6
L53:    iaload
L54:    istore 9
L56:    getstatic Field eb ub [I
L59:    iload 7
L61:    iaload
L62:    istore 10
L64:    iload 8
L66:    bipush 50
L68:    if_icmplt L115
L71:    getstatic Field eb Cb [I
L74:    iload 4
L76:    getstatic Field eb pb [I
L79:    iload 5
L81:    iaload
L82:    iastore
L83:    getstatic Field eb Db [I
L86:    iload 4
L88:    getstatic Field eb qb [I
L91:    iload 5
L93:    iaload
L94:    iastore
L95:    getstatic Field eb Eb [I
L98:    iload 4
L100:   iinc 4 1
L103:   aload_0
L104:   getfield Field eb v [I
L107:   iload_1
L108:   iaload
L109:   iastore
L110:   iload 22
L112:   ifeq L369
L115:   getstatic Field eb sb [I
L118:   iload 5
L120:   iaload
L121:   istore 11
L123:   getstatic Field eb tb [I
L126:   iload 5
L128:   iaload
L129:   istore 12
L131:   aload_0
L132:   getfield Field eb v [I
L135:   iload_1
L136:   iaload
L137:   istore 13
L139:   iload 10
L141:   bipush 50
L143:   if_icmplt L254
L146:   bipush 50
L148:   iload 8
L150:   isub
L151:   getstatic Field eb Qb [I
L154:   iload 10
L156:   iload 8
L158:   isub
L159:   iaload
L160:   imul
L161:   istore 14
L163:   getstatic Field eb Cb [I
L166:   iload 4
L168:   iload_2
L169:   iload 11
L171:   getstatic Field eb sb [I
L174:   iload 7
L176:   iaload
L177:   iload 11
L179:   isub
L180:   iload 14
L182:   imul
L183:   bipush 16
L185:   ishr
L186:   iadd
L187:   bipush 9
L189:   ishl
L190:   bipush 50
L192:   idiv
L193:   iadd
L194:   iastore
L195:   getstatic Field eb Db [I
L198:   iload 4
L200:   iload_3
L201:   iload 12
L203:   getstatic Field eb tb [I
L206:   iload 7
L208:   iaload
L209:   iload 12
L211:   isub
L212:   iload 14
L214:   imul
L215:   bipush 16
L217:   ishr
L218:   iadd
L219:   bipush 9
L221:   ishl
L222:   bipush 50
L224:   idiv
L225:   iadd
L226:   iastore
L227:   getstatic Field eb Eb [I
L230:   iload 4
L232:   iinc 4 1
L235:   iload 13
L237:   aload_0
L238:   getfield Field eb x [I
L241:   iload_1
L242:   iaload
L243:   iload 13
L245:   isub
L246:   iload 14
L248:   imul
L249:   bipush 16
L251:   ishr
L252:   iadd
L253:   iastore
L254:   iload 9
L256:   bipush 50
L258:   if_icmplt L369
L261:   bipush 50
L263:   iload 8
L265:   isub
L266:   getstatic Field eb Qb [I
L269:   iload 9
L271:   iload 8
L273:   isub
L274:   iaload
L275:   imul
L276:   istore 14
L278:   getstatic Field eb Cb [I
L281:   iload 4
L283:   iload_2
L284:   iload 11
L286:   getstatic Field eb sb [I
L289:   iload 6
L291:   iaload
L292:   iload 11
L294:   isub
L295:   iload 14
L297:   imul
L298:   bipush 16
L300:   ishr
L301:   iadd
L302:   bipush 9
L304:   ishl
L305:   bipush 50
L307:   idiv
L308:   iadd
L309:   iastore
L310:   getstatic Field eb Db [I
L313:   iload 4
L315:   iload_3
L316:   iload 12
L318:   getstatic Field eb tb [I
L321:   iload 6
L323:   iaload
L324:   iload 12
L326:   isub
L327:   iload 14
L329:   imul
L330:   bipush 16
L332:   ishr
L333:   iadd
L334:   bipush 9
L336:   ishl
L337:   bipush 50
L339:   idiv
L340:   iadd
L341:   iastore
L342:   getstatic Field eb Eb [I
L345:   iload 4
L347:   iinc 4 1
L350:   iload 13
L352:   aload_0
L353:   getfield Field eb w [I
L356:   iload_1
L357:   iaload
L358:   iload 13
L360:   isub
L361:   iload 14
L363:   imul
L364:   bipush 16
L366:   ishr
L367:   iadd
L368:   iastore
L369:   iload 9
L371:   bipush 50
L373:   if_icmplt L420
L376:   getstatic Field eb Cb [I
L379:   iload 4
L381:   getstatic Field eb pb [I
L384:   iload 6
L386:   iaload
L387:   iastore
L388:   getstatic Field eb Db [I
L391:   iload 4
L393:   getstatic Field eb qb [I
L396:   iload 6
L398:   iaload
L399:   iastore
L400:   getstatic Field eb Eb [I
L403:   iload 4
L405:   iinc 4 1
L408:   aload_0
L409:   getfield Field eb w [I
L412:   iload_1
L413:   iaload
L414:   iastore
L415:   iload 22
L417:   ifeq L674
L420:   getstatic Field eb sb [I
L423:   iload 6
L425:   iaload
L426:   istore 11
L428:   getstatic Field eb tb [I
L431:   iload 6
L433:   iaload
L434:   istore 12
L436:   aload_0
L437:   getfield Field eb w [I
L440:   iload_1
L441:   iaload
L442:   istore 13
L444:   iload 8
L446:   bipush 50
L448:   if_icmplt L559
L451:   bipush 50
L453:   iload 9
L455:   isub
L456:   getstatic Field eb Qb [I
L459:   iload 8
L461:   iload 9
L463:   isub
L464:   iaload
L465:   imul
L466:   istore 14
L468:   getstatic Field eb Cb [I
L471:   iload 4
L473:   iload_2
L474:   iload 11
L476:   getstatic Field eb sb [I
L479:   iload 5
L481:   iaload
L482:   iload 11
L484:   isub
L485:   iload 14
L487:   imul
L488:   bipush 16
L490:   ishr
L491:   iadd
L492:   bipush 9
L494:   ishl
L495:   bipush 50
L497:   idiv
L498:   iadd
L499:   iastore
L500:   getstatic Field eb Db [I
L503:   iload 4
L505:   iload_3
L506:   iload 12
L508:   getstatic Field eb tb [I
L511:   iload 5
L513:   iaload
L514:   iload 12
L516:   isub
L517:   iload 14
L519:   imul
L520:   bipush 16
L522:   ishr
L523:   iadd
L524:   bipush 9
L526:   ishl
L527:   bipush 50
L529:   idiv
L530:   iadd
L531:   iastore
L532:   getstatic Field eb Eb [I
L535:   iload 4
L537:   iinc 4 1
L540:   iload 13
L542:   aload_0
L543:   getfield Field eb v [I
L546:   iload_1
L547:   iaload
L548:   iload 13
L550:   isub
L551:   iload 14
L553:   imul
L554:   bipush 16
L556:   ishr
L557:   iadd
L558:   iastore
L559:   iload 10
L561:   bipush 50
L563:   if_icmplt L674
L566:   bipush 50
L568:   iload 9
L570:   isub
L571:   getstatic Field eb Qb [I
L574:   iload 10
L576:   iload 9
L578:   isub
L579:   iaload
L580:   imul
L581:   istore 14
L583:   getstatic Field eb Cb [I
L586:   iload 4
L588:   iload_2
L589:   iload 11
L591:   getstatic Field eb sb [I
L594:   iload 7
L596:   iaload
L597:   iload 11
L599:   isub
L600:   iload 14
L602:   imul
L603:   bipush 16
L605:   ishr
L606:   iadd
L607:   bipush 9
L609:   ishl
L610:   bipush 50
L612:   idiv
L613:   iadd
L614:   iastore
L615:   getstatic Field eb Db [I
L618:   iload 4
L620:   iload_3
L621:   iload 12
L623:   getstatic Field eb tb [I
L626:   iload 7
L628:   iaload
L629:   iload 12
L631:   isub
L632:   iload 14
L634:   imul
L635:   bipush 16
L637:   ishr
L638:   iadd
L639:   bipush 9
L641:   ishl
L642:   bipush 50
L644:   idiv
L645:   iadd
L646:   iastore
L647:   getstatic Field eb Eb [I
L650:   iload 4
L652:   iinc 4 1
L655:   iload 13
L657:   aload_0
L658:   getfield Field eb x [I
L661:   iload_1
L662:   iaload
L663:   iload 13
L665:   isub
L666:   iload 14
L668:   imul
L669:   bipush 16
L671:   ishr
L672:   iadd
L673:   iastore
L674:   iload 10
L676:   bipush 50
L678:   if_icmplt L725
L681:   getstatic Field eb Cb [I
L684:   iload 4
L686:   getstatic Field eb pb [I
L689:   iload 7
L691:   iaload
L692:   iastore
L693:   getstatic Field eb Db [I
L696:   iload 4
L698:   getstatic Field eb qb [I
L701:   iload 7
L703:   iaload
L704:   iastore
L705:   getstatic Field eb Eb [I
L708:   iload 4
L710:   iinc 4 1
L713:   aload_0
L714:   getfield Field eb x [I
L717:   iload_1
L718:   iaload
L719:   iastore
L720:   iload 22
L722:   ifeq L979
L725:   getstatic Field eb sb [I
L728:   iload 7
L730:   iaload
L731:   istore 11
L733:   getstatic Field eb tb [I
L736:   iload 7
L738:   iaload
L739:   istore 12
L741:   aload_0
L742:   getfield Field eb x [I
L745:   iload_1
L746:   iaload
L747:   istore 13
L749:   iload 9
L751:   bipush 50
L753:   if_icmplt L864
L756:   bipush 50
L758:   iload 10
L760:   isub
L761:   getstatic Field eb Qb [I
L764:   iload 9
L766:   iload 10
L768:   isub
L769:   iaload
L770:   imul
L771:   istore 14
L773:   getstatic Field eb Cb [I
L776:   iload 4
L778:   iload_2
L779:   iload 11
L781:   getstatic Field eb sb [I
L784:   iload 6
L786:   iaload
L787:   iload 11
L789:   isub
L790:   iload 14
L792:   imul
L793:   bipush 16
L795:   ishr
L796:   iadd
L797:   bipush 9
L799:   ishl
L800:   bipush 50
L802:   idiv
L803:   iadd
L804:   iastore
L805:   getstatic Field eb Db [I
L808:   iload 4
L810:   iload_3
L811:   iload 12
L813:   getstatic Field eb tb [I
L816:   iload 6
L818:   iaload
L819:   iload 12
L821:   isub
L822:   iload 14
L824:   imul
L825:   bipush 16
L827:   ishr
L828:   iadd
L829:   bipush 9
L831:   ishl
L832:   bipush 50
L834:   idiv
L835:   iadd
L836:   iastore
L837:   getstatic Field eb Eb [I
L840:   iload 4
L842:   iinc 4 1
L845:   iload 13
L847:   aload_0
L848:   getfield Field eb w [I
L851:   iload_1
L852:   iaload
L853:   iload 13
L855:   isub
L856:   iload 14
L858:   imul
L859:   bipush 16
L861:   ishr
L862:   iadd
L863:   iastore
L864:   iload 8
L866:   bipush 50
L868:   if_icmplt L979
L871:   bipush 50
L873:   iload 10
L875:   isub
L876:   getstatic Field eb Qb [I
L879:   iload 8
L881:   iload 10
L883:   isub
L884:   iaload
L885:   imul
L886:   istore 14
L888:   getstatic Field eb Cb [I
L891:   iload 4
L893:   iload_2
L894:   iload 11
L896:   getstatic Field eb sb [I
L899:   iload 5
L901:   iaload
L902:   iload 11
L904:   isub
L905:   iload 14
L907:   imul
L908:   bipush 16
L910:   ishr
L911:   iadd
L912:   bipush 9
L914:   ishl
L915:   bipush 50
L917:   idiv
L918:   iadd
L919:   iastore
L920:   getstatic Field eb Db [I
L923:   iload 4
L925:   iload_3
L926:   iload 12
L928:   getstatic Field eb tb [I
L931:   iload 5
L933:   iaload
L934:   iload 12
L936:   isub
L937:   iload 14
L939:   imul
L940:   bipush 16
L942:   ishr
L943:   iadd
L944:   bipush 9
L946:   ishl
L947:   bipush 50
L949:   idiv
L950:   iadd
L951:   iastore
L952:   getstatic Field eb Eb [I
L955:   iload 4
L957:   iinc 4 1
L960:   iload 13
L962:   aload_0
L963:   getfield Field eb v [I
L966:   iload_1
L967:   iaload
L968:   iload 13
L970:   isub
L971:   iload 14
L973:   imul
L974:   bipush 16
L976:   ishr
L977:   iadd
L978:   iastore
L979:   getstatic Field eb Cb [I
L982:   iconst_0
L983:   iaload
L984:   istore 11
L986:   getstatic Field eb Cb [I
L989:   iconst_1
L990:   iaload
L991:   istore 12
L993:   getstatic Field eb Cb [I
L996:   iconst_2
L997:   iaload
L998:   istore 13
L1000:  getstatic Field eb Db [I
L1003:  iconst_0
L1004:  iaload
L1005:  istore 14
L1007:  getstatic Field eb Db [I
L1010:  iconst_1
L1011:  iaload
L1012:  istore 15
L1014:  getstatic Field eb Db [I
L1017:  iconst_2
L1018:  iaload
L1019:  istore 16
L1021:  iload 11
L1023:  iload 12
L1025:  isub
L1026:  iload 16
L1028:  iload 15
L1030:  isub
L1031:  imul
L1032:  iload 14
L1034:  iload 15
L1036:  isub
L1037:  iload 13
L1039:  iload 12
L1041:  isub
L1042:  imul
L1043:  isub
L1044:  ifle L2164
L1047:  iconst_0
L1048:  putstatic Field gb B Z
L1051:  iload 4
L1053:  iconst_3
L1054:  if_icmpne L1475
L1057:  iload 11
L1059:  iflt L1096
L1062:  iload 12
L1064:  iflt L1096
L1067:  iload 13
L1069:  iflt L1096
L1072:  iload 11
L1074:  getstatic Field fb r I
L1077:  if_icmpgt L1096
L1080:  iload 12
L1082:  getstatic Field fb r I
L1085:  if_icmpgt L1096
L1088:  iload 13
L1090:  getstatic Field fb r I
L1093:  if_icmple L1100
L1096:  iconst_1
L1097:  putstatic Field gb B Z
L1100:  aload_0
L1101:  getfield Field eb y [I
L1104:  ifnonnull L1115
L1107:  iconst_0
L1108:  istore 17
L1110:  iload 22
L1112:  ifeq L1125
L1115:  aload_0
L1116:  getfield Field eb y [I
L1119:  iload_1
L1120:  iaload
L1121:  iconst_3
L1122:  iand
L1123:  istore 17
L1125:  iload 17
L1127:  ifne L1165
L1130:  iload 14
L1132:  iload 15
L1134:  iload 16
L1136:  iload 11
L1138:  iload 12
L1140:  iload 13
L1142:  getstatic Field eb Eb [I
L1145:  iconst_0
L1146:  iaload
L1147:  getstatic Field eb Eb [I
L1150:  iconst_1
L1151:  iaload
L1152:  getstatic Field eb Eb [I
L1155:  iconst_2
L1156:  iaload
L1157:  invokestatic Method gb a (IIIIIIIII)V
L1160:  iload 22
L1162:  ifeq L1475
L1165:  iload 17
L1167:  iconst_1
L1168:  if_icmpne L1201
L1171:  iload 14
L1173:  iload 15
L1175:  iload 16
L1177:  iload 11
L1179:  iload 12
L1181:  iload 13
L1183:  getstatic Field eb Pb [I
L1186:  aload_0
L1187:  getfield Field eb v [I
L1190:  iload_1
L1191:  iaload
L1192:  iaload
L1193:  invokestatic Method gb a (IIIIIII)V
L1196:  iload 22
L1198:  ifeq L1475
L1201:  iload 17
L1203:  iconst_2
L1204:  if_icmpne L1339
L1207:  aload_0
L1208:  getfield Field eb y [I
L1211:  iload_1
L1212:  iaload
L1213:  iconst_2
L1214:  ishr
L1215:  istore 18
L1217:  aload_0
L1218:  getfield Field eb E [I
L1221:  iload 18
L1223:  iaload
L1224:  istore 19
L1226:  aload_0
L1227:  getfield Field eb F [I
L1230:  iload 18
L1232:  iaload
L1233:  istore 20
L1235:  aload_0
L1236:  getfield Field eb G [I
L1239:  iload 18
L1241:  iaload
L1242:  istore 21
L1244:  iload 14
L1246:  iload 15
L1248:  iload 16
L1250:  iload 11
L1252:  iload 12
L1254:  iload 13
L1256:  getstatic Field eb Eb [I
L1259:  iconst_0
L1260:  iaload
L1261:  getstatic Field eb Eb [I
L1264:  iconst_1
L1265:  iaload
L1266:  getstatic Field eb Eb [I
L1269:  iconst_2
L1270:  iaload
L1271:  getstatic Field eb sb [I
L1274:  iload 19
L1276:  iaload
L1277:  getstatic Field eb sb [I
L1280:  iload 20
L1282:  iaload
L1283:  getstatic Field eb sb [I
L1286:  iload 21
L1288:  iaload
L1289:  getstatic Field eb tb [I
L1292:  iload 19
L1294:  iaload
L1295:  getstatic Field eb tb [I
L1298:  iload 20
L1300:  iaload
L1301:  getstatic Field eb tb [I
L1304:  iload 21
L1306:  iaload
L1307:  getstatic Field eb ub [I
L1310:  iload 19
L1312:  iaload
L1313:  getstatic Field eb ub [I
L1316:  iload 20
L1318:  iaload
L1319:  getstatic Field eb ub [I
L1322:  iload 21
L1324:  iaload
L1325:  aload_0
L1326:  getfield Field eb B [I
L1329:  iload_1
L1330:  iaload
L1331:  invokestatic Method gb a (IIIIIIIIIIIIIIIIIII)V
L1334:  iload 22
L1336:  ifeq L1475
L1339:  iload 17
L1341:  iconst_3
L1342:  if_icmpne L1475
L1345:  aload_0
L1346:  getfield Field eb y [I
L1349:  iload_1
L1350:  iaload
L1351:  iconst_2
L1352:  ishr
L1353:  istore 18
L1355:  aload_0
L1356:  getfield Field eb E [I
L1359:  iload 18
L1361:  iaload
L1362:  istore 19
L1364:  aload_0
L1365:  getfield Field eb F [I
L1368:  iload 18
L1370:  iaload
L1371:  istore 20
L1373:  aload_0
L1374:  getfield Field eb G [I
L1377:  iload 18
L1379:  iaload
L1380:  istore 21
L1382:  iload 14
L1384:  iload 15
L1386:  iload 16
L1388:  iload 11
L1390:  iload 12
L1392:  iload 13
L1394:  aload_0
L1395:  getfield Field eb v [I
L1398:  iload_1
L1399:  iaload
L1400:  aload_0
L1401:  getfield Field eb v [I
L1404:  iload_1
L1405:  iaload
L1406:  aload_0
L1407:  getfield Field eb v [I
L1410:  iload_1
L1411:  iaload
L1412:  getstatic Field eb sb [I
L1415:  iload 19
L1417:  iaload
L1418:  getstatic Field eb sb [I
L1421:  iload 20
L1423:  iaload
L1424:  getstatic Field eb sb [I
L1427:  iload 21
L1429:  iaload
L1430:  getstatic Field eb tb [I
L1433:  iload 19
L1435:  iaload
L1436:  getstatic Field eb tb [I
L1439:  iload 20
L1441:  iaload
L1442:  getstatic Field eb tb [I
L1445:  iload 21
L1447:  iaload
L1448:  getstatic Field eb ub [I
L1451:  iload 19
L1453:  iaload
L1454:  getstatic Field eb ub [I
L1457:  iload 20
L1459:  iaload
L1460:  getstatic Field eb ub [I
L1463:  iload 21
L1465:  iaload
L1466:  aload_0
L1467:  getfield Field eb B [I
L1470:  iload_1
L1471:  iaload
L1472:  invokestatic Method gb a (IIIIIIIIIIIIIIIIIII)V
L1475:  iload 4
L1477:  iconst_4
L1478:  if_icmpne L2164
L1481:  iload 11
L1483:  iflt L1539
L1486:  iload 12
L1488:  iflt L1539
L1491:  iload 13
L1493:  iflt L1539
L1496:  iload 11
L1498:  getstatic Field fb r I
L1501:  if_icmpgt L1539
L1504:  iload 12
L1506:  getstatic Field fb r I
L1509:  if_icmpgt L1539
L1512:  iload 13
L1514:  getstatic Field fb r I
L1517:  if_icmpgt L1539
L1520:  getstatic Field eb Cb [I
L1523:  iconst_3
L1524:  iaload
L1525:  iflt L1539
L1528:  getstatic Field eb Cb [I
L1531:  iconst_3
L1532:  iaload
L1533:  getstatic Field fb r I
L1536:  if_icmple L1543
L1539:  iconst_1
L1540:  putstatic Field gb B Z
L1543:  aload_0
L1544:  getfield Field eb y [I
L1547:  ifnonnull L1558
L1550:  iconst_0
L1551:  istore 17
L1553:  iload 22
L1555:  ifeq L1568
L1558:  aload_0
L1559:  getfield Field eb y [I
L1562:  iload_1
L1563:  iaload
L1564:  iconst_3
L1565:  iand
L1566:  istore 17
L1568:  iload 17
L1570:  ifne L1640
L1573:  iload 14
L1575:  iload 15
L1577:  iload 16
L1579:  iload 11
L1581:  iload 12
L1583:  iload 13
L1585:  getstatic Field eb Eb [I
L1588:  iconst_0
L1589:  iaload
L1590:  getstatic Field eb Eb [I
L1593:  iconst_1
L1594:  iaload
L1595:  getstatic Field eb Eb [I
L1598:  iconst_2
L1599:  iaload
L1600:  invokestatic Method gb a (IIIIIIIII)V
L1603:  iload 14
L1605:  iload 16
L1607:  getstatic Field eb Db [I
L1610:  iconst_3
L1611:  iaload
L1612:  iload 11
L1614:  iload 13
L1616:  getstatic Field eb Cb [I
L1619:  iconst_3
L1620:  iaload
L1621:  getstatic Field eb Eb [I
L1624:  iconst_0
L1625:  iaload
L1626:  getstatic Field eb Eb [I
L1629:  iconst_2
L1630:  iaload
L1631:  getstatic Field eb Eb [I
L1634:  iconst_3
L1635:  iaload
L1636:  invokestatic Method gb a (IIIIIIIII)V
L1639:  return
L1640:  iload 17
L1642:  iconst_1
L1643:  if_icmpne L1699
L1646:  getstatic Field eb Pb [I
L1649:  aload_0
L1650:  getfield Field eb v [I
L1653:  iload_1
L1654:  iaload
L1655:  iaload
L1656:  istore 18
L1658:  iload 14
L1660:  iload 15
L1662:  iload 16
L1664:  iload 11
L1666:  iload 12
L1668:  iload 13
L1670:  iload 18
L1672:  invokestatic Method gb a (IIIIIII)V
L1675:  iload 14
L1677:  iload 16
L1679:  getstatic Field eb Db [I
L1682:  iconst_3
L1683:  iaload
L1684:  iload 11
L1686:  iload 13
L1688:  getstatic Field eb Cb [I
L1691:  iconst_3
L1692:  iaload
L1693:  iload 18
L1695:  invokestatic Method gb a (IIIIIII)V
L1698:  return
L1699:  iload 17
L1701:  iconst_2
L1702:  if_icmpne L1929
L1705:  aload_0
L1706:  getfield Field eb y [I
L1709:  iload_1
L1710:  iaload
L1711:  iconst_2
L1712:  ishr
L1713:  istore 18
L1715:  aload_0
L1716:  getfield Field eb E [I
L1719:  iload 18
L1721:  iaload
L1722:  istore 19
L1724:  aload_0
L1725:  getfield Field eb F [I
L1728:  iload 18
L1730:  iaload
L1731:  istore 20
L1733:  aload_0
L1734:  getfield Field eb G [I
L1737:  iload 18
L1739:  iaload
L1740:  istore 21
L1742:  iload 14
L1744:  iload 15
L1746:  iload 16
L1748:  iload 11
L1750:  iload 12
L1752:  iload 13
L1754:  getstatic Field eb Eb [I
L1757:  iconst_0
L1758:  iaload
L1759:  getstatic Field eb Eb [I
L1762:  iconst_1
L1763:  iaload
L1764:  getstatic Field eb Eb [I
L1767:  iconst_2
L1768:  iaload
L1769:  getstatic Field eb sb [I
L1772:  iload 19
L1774:  iaload
L1775:  getstatic Field eb sb [I
L1778:  iload 20
L1780:  iaload
L1781:  getstatic Field eb sb [I
L1784:  iload 21
L1786:  iaload
L1787:  getstatic Field eb tb [I
L1790:  iload 19
L1792:  iaload
L1793:  getstatic Field eb tb [I
L1796:  iload 20
L1798:  iaload
L1799:  getstatic Field eb tb [I
L1802:  iload 21
L1804:  iaload
L1805:  getstatic Field eb ub [I
L1808:  iload 19
L1810:  iaload
L1811:  getstatic Field eb ub [I
L1814:  iload 20
L1816:  iaload
L1817:  getstatic Field eb ub [I
L1820:  iload 21
L1822:  iaload
L1823:  aload_0
L1824:  getfield Field eb B [I
L1827:  iload_1
L1828:  iaload
L1829:  invokestatic Method gb a (IIIIIIIIIIIIIIIIIII)V
L1832:  iload 14
L1834:  iload 16
L1836:  getstatic Field eb Db [I
L1839:  iconst_3
L1840:  iaload
L1841:  iload 11
L1843:  iload 13
L1845:  getstatic Field eb Cb [I
L1848:  iconst_3
L1849:  iaload
L1850:  getstatic Field eb Eb [I
L1853:  iconst_0
L1854:  iaload
L1855:  getstatic Field eb Eb [I
L1858:  iconst_2
L1859:  iaload
L1860:  getstatic Field eb Eb [I
L1863:  iconst_3
L1864:  iaload
L1865:  getstatic Field eb sb [I
L1868:  iload 19
L1870:  iaload
L1871:  getstatic Field eb sb [I
L1874:  iload 20
L1876:  iaload
L1877:  getstatic Field eb sb [I
L1880:  iload 21
L1882:  iaload
L1883:  getstatic Field eb tb [I
L1886:  iload 19
L1888:  iaload
L1889:  getstatic Field eb tb [I
L1892:  iload 20
L1894:  iaload
L1895:  getstatic Field eb tb [I
L1898:  iload 21
L1900:  iaload
L1901:  getstatic Field eb ub [I
L1904:  iload 19
L1906:  iaload
L1907:  getstatic Field eb ub [I
L1910:  iload 20
L1912:  iaload
L1913:  getstatic Field eb ub [I
L1916:  iload 21
L1918:  iaload
L1919:  aload_0
L1920:  getfield Field eb B [I
L1923:  iload_1
L1924:  iaload
L1925:  invokestatic Method gb a (IIIIIIIIIIIIIIIIIII)V
L1928:  return
L1929:  iload 17
L1931:  iconst_3
L1932:  if_icmpne L2164
L1935:  aload_0
L1936:  getfield Field eb y [I
L1939:  iload_1
L1940:  iaload
L1941:  iconst_2
L1942:  ishr
L1943:  istore 18
L1945:  aload_0
L1946:  getfield Field eb E [I
L1949:  iload 18
L1951:  iaload
L1952:  istore 19
L1954:  aload_0
L1955:  getfield Field eb F [I
L1958:  iload 18
L1960:  iaload
L1961:  istore 20
L1963:  aload_0
L1964:  getfield Field eb G [I
L1967:  iload 18
L1969:  iaload
L1970:  istore 21
L1972:  iload 14
L1974:  iload 15
L1976:  iload 16
L1978:  iload 11
L1980:  iload 12
L1982:  iload 13
L1984:  aload_0
L1985:  getfield Field eb v [I
L1988:  iload_1
L1989:  iaload
L1990:  aload_0
L1991:  getfield Field eb v [I
L1994:  iload_1
L1995:  iaload
L1996:  aload_0
L1997:  getfield Field eb v [I
L2000:  iload_1
L2001:  iaload
L2002:  getstatic Field eb sb [I
L2005:  iload 19
L2007:  iaload
L2008:  getstatic Field eb sb [I
L2011:  iload 20
L2013:  iaload
L2014:  getstatic Field eb sb [I
L2017:  iload 21
L2019:  iaload
L2020:  getstatic Field eb tb [I
L2023:  iload 19
L2025:  iaload
L2026:  getstatic Field eb tb [I
L2029:  iload 20
L2031:  iaload
L2032:  getstatic Field eb tb [I
L2035:  iload 21
L2037:  iaload
L2038:  getstatic Field eb ub [I
L2041:  iload 19
L2043:  iaload
L2044:  getstatic Field eb ub [I
L2047:  iload 20
L2049:  iaload
L2050:  getstatic Field eb ub [I
L2053:  iload 21
L2055:  iaload
L2056:  aload_0
L2057:  getfield Field eb B [I
L2060:  iload_1
L2061:  iaload
L2062:  invokestatic Method gb a (IIIIIIIIIIIIIIIIIII)V
L2065:  iload 14
L2067:  iload 16
L2069:  getstatic Field eb Db [I
L2072:  iconst_3
L2073:  iaload
L2074:  iload 11
L2076:  iload 13
L2078:  getstatic Field eb Cb [I
L2081:  iconst_3
L2082:  iaload
L2083:  aload_0
L2084:  getfield Field eb v [I
L2087:  iload_1
L2088:  iaload
L2089:  aload_0
L2090:  getfield Field eb v [I
L2093:  iload_1
L2094:  iaload
L2095:  aload_0
L2096:  getfield Field eb v [I
L2099:  iload_1
L2100:  iaload
L2101:  getstatic Field eb sb [I
L2104:  iload 19
L2106:  iaload
L2107:  getstatic Field eb sb [I
L2110:  iload 20
L2112:  iaload
L2113:  getstatic Field eb sb [I
L2116:  iload 21
L2118:  iaload
L2119:  getstatic Field eb tb [I
L2122:  iload 19
L2124:  iaload
L2125:  getstatic Field eb tb [I
L2128:  iload 20
L2130:  iaload
L2131:  getstatic Field eb tb [I
L2134:  iload 21
L2136:  iaload
L2137:  getstatic Field eb ub [I
L2140:  iload 19
L2142:  iaload
L2143:  getstatic Field eb ub [I
L2146:  iload 20
L2148:  iaload
L2149:  getstatic Field eb ub [I
L2152:  iload 21
L2154:  iaload
L2155:  aload_0
L2156:  getfield Field eb B [I
L2159:  iload_1
L2160:  iaload
L2161:  invokestatic Method gb a (IIIIIIIIIIIIIIIIIII)V
L2164:  return
L2165:  
    .end code
.end method

.method private final a : (IIIIIIII)Z
    .code stack 2 locals 9
L0:     iload_2
L1:     iload_3
L2:     if_icmpge L19
L5:     iload_2
L6:     iload 4
L8:     if_icmpge L19
L11:    iload_2
L12:    iload 5
L14:    if_icmpge L19
L17:    iconst_0
L18:    ireturn
L19:    iload_2
L20:    iload_3
L21:    if_icmple L38
L24:    iload_2
L25:    iload 4
L27:    if_icmple L38
L30:    iload_2
L31:    iload 5
L33:    if_icmple L38
L36:    iconst_0
L37:    ireturn
L38:    iload_1
L39:    iload 6
L41:    if_icmpge L58
L44:    iload_1
L45:    iload 7
L47:    if_icmpge L58
L50:    iload_1
L51:    iload 8
L53:    if_icmpge L58
L56:    iconst_0
L57:    ireturn
L58:    iload_1
L59:    iload 6
L61:    if_icmple L78
L64:    iload_1
L65:    iload 7
L67:    if_icmple L78
L70:    iload_1
L71:    iload 8
L73:    if_icmple L78
L76:    iconst_0
L77:    ireturn
L78:    iconst_1
L79:    ireturn
L80:    
    .end code
.end method

.method static <clinit> : ()V
    .code stack 2 locals 0
L0:     sipush 4096
L3:     newarray boolean
L5:     putstatic Field eb nb [Z
L8:     sipush 4096
L11:    newarray boolean
L13:    putstatic Field eb ob [Z
L16:    sipush 4096
L19:    newarray int
L21:    putstatic Field eb pb [I
L24:    sipush 4096
L27:    newarray int
L29:    putstatic Field eb qb [I
L32:    sipush 4096
L35:    newarray int
L37:    putstatic Field eb rb [I
L40:    sipush 4096
L43:    newarray int
L45:    putstatic Field eb sb [I
L48:    sipush 4096
L51:    newarray int
L53:    putstatic Field eb tb [I
L56:    sipush 4096
L59:    newarray int
L61:    putstatic Field eb ub [I
L64:    sipush 1500
L67:    newarray int
L69:    putstatic Field eb vb [I
L72:    sipush 1500
L75:    sipush 512
L78:    multianewarray [[I 2
L82:    putstatic Field eb wb [[I
L85:    bipush 12
L87:    newarray int
L89:    putstatic Field eb xb [I
L92:    bipush 12
L94:    sipush 2000
L97:    multianewarray [[I 2
L101:   putstatic Field eb yb [[I
L104:   sipush 2000
L107:   newarray int
L109:   putstatic Field eb zb [I
L112:   sipush 2000
L115:   newarray int
L117:   putstatic Field eb Ab [I
L120:   bipush 12
L122:   newarray int
L124:   putstatic Field eb Bb [I
L127:   bipush 10
L129:   newarray int
L131:   putstatic Field eb Cb [I
L134:   bipush 10
L136:   newarray int
L138:   putstatic Field eb Db [I
L141:   bipush 10
L143:   newarray int
L145:   putstatic Field eb Eb [I
L148:   sipush 1000
L151:   newarray int
L153:   putstatic Field eb Mb [I
L156:   getstatic Field gb J [I
L159:   putstatic Field eb Nb [I
L162:   getstatic Field gb K [I
L165:   putstatic Field eb Ob [I
L168:   getstatic Field gb V [I
L171:   putstatic Field eb Pb [I
L174:   getstatic Field gb I [I
L177:   putstatic Field eb Qb [I
L180:   return
L181:   
    .end code
.end method
.end class
