.version 45 3
.class public final super mc
.super java/lang/Object
.field private static a Z
.field private static b I
.field private static c I
.field private static d I
.field private static e I
.field private static f I
.field private static g B
.field private static h I
.field private static i Z
.field private static j [I
.field private static k [[C
.field private static l [[[B
.field private static m [[C
.field private static n [[C
.field private static o [I
.field private static final p [Ljava/lang/String;
.field public static q I

.method public static final a : (Lub;)V
    .code stack 8 locals 6
L0:     getstatic Field mc q I
L3:     istore 5
L5:     new kb
L8:     dup
L9:     sipush 363
L12:    aload_0
L13:    ldc "fragmentsenc.txt"
L15:    aconst_null
L16:    iconst_2
L17:    invokevirtual Method ub a (Ljava/lang/String;[BB)[B
L20:    invokespecial Method kb <init> (I[B)V
L23:    astore_1
L24:    new kb
L27:    dup
L28:    sipush 363
L31:    aload_0
L32:    ldc "badenc.txt"
L34:    aconst_null
L35:    iconst_2
L36:    invokevirtual Method ub a (Ljava/lang/String;[BB)[B
L39:    invokespecial Method kb <init> (I[B)V
L42:    astore_2
L43:    new kb
L46:    dup
L47:    sipush 363
L50:    aload_0
L51:    ldc "domainenc.txt"
L53:    aconst_null
L54:    iconst_2
L55:    invokevirtual Method ub a (Ljava/lang/String;[BB)[B
L58:    invokespecial Method kb <init> (I[B)V
L61:    astore_3
L62:    new kb
L65:    dup
L66:    sipush 363
L69:    aload_0
L70:    ldc "tldlist.txt"
L72:    aconst_null
L73:    iconst_2
L74:    invokevirtual Method ub a (Ljava/lang/String;[BB)[B
L77:    invokespecial Method kb <init> (I[B)V
L80:    astore 4
L82:    aload_1
L83:    aload_2
L84:    aload_3
L85:    aload 4
L87:    invokestatic Method mc a (Lkb;Lkb;Lkb;Lkb;)V
L90:    getstatic Field u d I
L93:    ifeq L104
L96:    iinc 5 1
L99:    iload 5
L101:   putstatic Field mc q I
L104:   return
L105:   
    .end code
.end method

.method private static final a : (Lkb;Lkb;Lkb;Lkb;)V
    .code stack 2 locals 4
L0:     ldc -33152
L2:     aload_1
L3:     invokestatic Method mc a (ILkb;)V
L6:     aload_2
L7:     sipush -717
L10:    invokestatic Method mc a (Lkb;I)V
L13:    sipush 24882
L16:    aload_0
L17:    invokestatic Method mc b (ILkb;)V
L20:    iconst_1
L21:    aload_3
L22:    invokestatic Method mc a (ZLkb;)V
L25:    return
L26:    
    .end code
.end method

.method private static final a : (ZLkb;)V
    .code stack 4 locals 7
L0:     getstatic Field mc q I
L3:     istore 6
        .catch java/lang/RuntimeException from L5 to L97 using L98
L5:     aload_1
L6:     invokevirtual Method kb h ()I
L9:     istore_2
L10:    iload_2
L11:    multianewarray [[C 1
L15:    putstatic Field mc n [[C
L18:    iload_2
L19:    newarray int
L21:    putstatic Field mc o [I
L24:    iload_0
L25:    ifne L29
L28:    return
L29:    iconst_0
L30:    istore_3
L31:    iload 6
L33:    ifeq L92
L36:    getstatic Field mc o [I
L39:    iload_3
L40:    aload_1
L41:    invokevirtual Method kb c ()I
L44:    iastore
L45:    aload_1
L46:    invokevirtual Method kb c ()I
L49:    newarray char
L51:    astore 4
L53:    iconst_0
L54:    istore 5
L56:    iload 6
L58:    ifeq L74
L61:    aload 4
L63:    iload 5
L65:    aload_1
L66:    invokevirtual Method kb c ()I
L69:    i2c
L70:    castore
L71:    iinc 5 1
L74:    iload 5
L76:    aload 4
L78:    arraylength
L79:    if_icmplt L61
L82:    getstatic Field mc n [[C
L85:    iload_3
L86:    aload 4
L88:    aastore
L89:    iinc 3 1
L92:    iload_3
L93:    iload_2
L94:    if_icmplt L36
L97:    return
L98:    astore_2
L99:    new java/lang/StringBuffer
L102:   dup
L103:   ldc "86833, "
L105:   invokespecial Method java/lang/StringBuffer <init> (Ljava/lang/String;)V
L108:   iload_0
L109:   invokevirtual Method java/lang/StringBuffer append (Z)Ljava/lang/StringBuffer;
L112:   ldc ", "
L114:   invokevirtual Method java/lang/StringBuffer append (Ljava/lang/String;)Ljava/lang/StringBuffer;
L117:   aload_1
L118:   invokevirtual Method java/lang/StringBuffer append (Ljava/lang/Object;)Ljava/lang/StringBuffer;
L121:   ldc ", "
L123:   invokevirtual Method java/lang/StringBuffer append (Ljava/lang/String;)Ljava/lang/StringBuffer;
L126:   aload_2
L127:   invokevirtual Method java/lang/Throwable toString ()Ljava/lang/String;
L130:   invokevirtual Method java/lang/StringBuffer append (Ljava/lang/String;)Ljava/lang/StringBuffer;
L133:   invokevirtual Method java/lang/StringBuffer toString ()Ljava/lang/String;
L136:   invokestatic Method sign/signlink reporterror (Ljava/lang/String;)V
L139:   new java/lang/RuntimeException
L142:   dup
L143:   invokespecial Method java/lang/RuntimeException <init> ()V
L146:   athrow
L147:   
    .end code
.end method

.method private static final a : (ILkb;)V
    .code stack 5 locals 4
        .catch java/lang/RuntimeException from L0 to L53 using L54
L0:     aload_1
L1:     invokevirtual Method kb h ()I
L4:     istore_2
L5:     iload_0
L6:     ldc -33152
L8:     if_icmpeq L26
L11:    iconst_1
L12:    istore_3
L13:    getstatic Field mc q I
L16:    ifeq L22
L19:    iinc 3 1
L22:    iload_3
L23:    ifgt L19
L26:    iload_2
L27:    multianewarray [[C 1
L31:    putstatic Field mc k [[C
L34:    iload_2
L35:    multianewarray [[[B 1
L39:    putstatic Field mc l [[[B
L42:    getstatic Field mc l [[[B
L45:    getstatic Field mc k [[C
L48:    aload_1
L49:    iconst_1
L50:    invokestatic Method mc a ([[[B[[CLkb;B)V
L53:    return
L54:    astore_2
L55:    new java/lang/StringBuffer
L58:    dup
L59:    ldc "34550, "
L61:    invokespecial Method java/lang/StringBuffer <init> (Ljava/lang/String;)V
L64:    iload_0
L65:    invokevirtual Method java/lang/StringBuffer append (I)Ljava/lang/StringBuffer;
L68:    ldc ", "
L70:    invokevirtual Method java/lang/StringBuffer append (Ljava/lang/String;)Ljava/lang/StringBuffer;
L73:    aload_1
L74:    invokevirtual Method java/lang/StringBuffer append (Ljava/lang/Object;)Ljava/lang/StringBuffer;
L77:    ldc ", "
L79:    invokevirtual Method java/lang/StringBuffer append (Ljava/lang/String;)Ljava/lang/StringBuffer;
L82:    aload_2
L83:    invokevirtual Method java/lang/Throwable toString ()Ljava/lang/String;
L86:    invokevirtual Method java/lang/StringBuffer append (Ljava/lang/String;)Ljava/lang/StringBuffer;
L89:    invokevirtual Method java/lang/StringBuffer toString ()Ljava/lang/String;
L92:    invokestatic Method sign/signlink reporterror (Ljava/lang/String;)V
L95:    new java/lang/RuntimeException
L98:    dup
L99:    invokespecial Method java/lang/RuntimeException <init> ()V
L102:   athrow
L103:   
    .end code
.end method

.method private static final a : (Lkb;I)V
    .code stack 3 locals 3
        .catch java/lang/RuntimeException from L0 to L28 using L29
L0:     aload_0
L1:     invokevirtual Method kb h ()I
L4:     istore_2
L5:     iload_1
L6:     iflt L10
L9:     return
L10:    iload_2
L11:    multianewarray [[C 1
L15:    putstatic Field mc m [[C
L18:    sipush -178
L21:    aload_0
L22:    getstatic Field mc m [[C
L25:    invokestatic Method mc a (ILkb;[[C)V
L28:    return
L29:    astore_2
L30:    new java/lang/StringBuffer
L33:    dup
L34:    ldc "77072, "
L36:    invokespecial Method java/lang/StringBuffer <init> (Ljava/lang/String;)V
L39:    aload_0
L40:    invokevirtual Method java/lang/StringBuffer append (Ljava/lang/Object;)Ljava/lang/StringBuffer;
L43:    ldc ", "
L45:    invokevirtual Method java/lang/StringBuffer append (Ljava/lang/String;)Ljava/lang/StringBuffer;
L48:    iload_1
L49:    invokevirtual Method java/lang/StringBuffer append (I)Ljava/lang/StringBuffer;
L52:    ldc ", "
L54:    invokevirtual Method java/lang/StringBuffer append (Ljava/lang/String;)Ljava/lang/StringBuffer;
L57:    aload_2
L58:    invokevirtual Method java/lang/Throwable toString ()Ljava/lang/String;
L61:    invokevirtual Method java/lang/StringBuffer append (Ljava/lang/String;)Ljava/lang/StringBuffer;
L64:    invokevirtual Method java/lang/StringBuffer toString ()Ljava/lang/String;
L67:    invokestatic Method sign/signlink reporterror (Ljava/lang/String;)V
L70:    new java/lang/RuntimeException
L73:    dup
L74:    invokespecial Method java/lang/RuntimeException <init> ()V
L77:    athrow
L78:    
    .end code
.end method

.method private static final b : (ILkb;)V
    .code stack 4 locals 3
        .catch java/lang/RuntimeException from L0 to L58 using L59
L0:     aload_1
L1:     invokevirtual Method kb h ()I
L4:     newarray int
L6:     putstatic Field mc j [I
L9:     iconst_0
L10:    istore_2
L11:    getstatic Field mc q I
L14:    ifeq L29
L17:    getstatic Field mc j [I
L20:    iload_2
L21:    aload_1
L22:    invokevirtual Method kb e ()I
L25:    iastore
L26:    iinc 2 1
L29:    iload_2
L30:    getstatic Field mc j [I
L33:    arraylength
L34:    if_icmplt L17
L37:    iload_0
L38:    getstatic Field mc b I
L41:    if_icmpeq L108
L44:    getstatic Field mc a Z
L47:    ifeq L54
L50:    iconst_0
L51:    goto L55
L54:    iconst_1
L55:    putstatic Field mc a Z
L58:    return
L59:    astore_2
L60:    new java/lang/StringBuffer
L63:    dup
L64:    ldc "14267, "
L66:    invokespecial Method java/lang/StringBuffer <init> (Ljava/lang/String;)V
L69:    iload_0
L70:    invokevirtual Method java/lang/StringBuffer append (I)Ljava/lang/StringBuffer;
L73:    ldc ", "
L75:    invokevirtual Method java/lang/StringBuffer append (Ljava/lang/String;)Ljava/lang/StringBuffer;
L78:    aload_1
L79:    invokevirtual Method java/lang/StringBuffer append (Ljava/lang/Object;)Ljava/lang/StringBuffer;
L82:    ldc ", "
L84:    invokevirtual Method java/lang/StringBuffer append (Ljava/lang/String;)Ljava/lang/StringBuffer;
L87:    aload_2
L88:    invokevirtual Method java/lang/Throwable toString ()Ljava/lang/String;
L91:    invokevirtual Method java/lang/StringBuffer append (Ljava/lang/String;)Ljava/lang/StringBuffer;
L94:    invokevirtual Method java/lang/StringBuffer toString ()Ljava/lang/String;
L97:    invokestatic Method sign/signlink reporterror (Ljava/lang/String;)V
L100:   new java/lang/RuntimeException
L103:   dup
L104:   invokespecial Method java/lang/RuntimeException <init> ()V
L107:   athrow
L108:   return
L109:   
    .end code
.end method

.method private static final a : ([[[B[[CLkb;B)V
    .code stack 4 locals 10
L0:     getstatic Field mc q I
L3:     istore 9
        .catch java/lang/RuntimeException from L5 to L145 using L146
L5:     iload_3
L6:     iconst_1
L7:     if_icmpne L17
L10:    iconst_0
L11:    istore_3
L12:    iload 9
L14:    ifeq L18
L17:    return
L18:    iconst_0
L19:    istore 4
L21:    iload 9
L23:    ifeq L138
L26:    aload_2
L27:    invokevirtual Method kb c ()I
L30:    newarray char
L32:    astore 5
L34:    iconst_0
L35:    istore 6
L37:    iload 9
L39:    ifeq L55
L42:    aload 5
L44:    iload 6
L46:    aload_2
L47:    invokevirtual Method kb c ()I
L50:    i2c
L51:    castore
L52:    iinc 6 1
L55:    iload 6
L57:    aload 5
L59:    arraylength
L60:    if_icmplt L42
L63:    aload_1
L64:    iload 4
L66:    aload 5
L68:    aastore
L69:    aload_2
L70:    invokevirtual Method kb c ()I
L73:    iconst_2
L74:    multianewarray [[B 2
L78:    astore 7
L80:    iconst_0
L81:    istore 8
L83:    iload 9
L85:    ifeq L115
L88:    aload 7
L90:    iload 8
L92:    aaload
L93:    iconst_0
L94:    aload_2
L95:    invokevirtual Method kb c ()I
L98:    i2b
L99:    bastore
L100:   aload 7
L102:   iload 8
L104:   aaload
L105:   iconst_1
L106:   aload_2
L107:   invokevirtual Method kb c ()I
L110:   i2b
L111:   bastore
L112:   iinc 8 1
L115:   iload 8
L117:   aload 7
L119:   arraylength
L120:   if_icmplt L88
L123:   aload 7
L125:   arraylength
L126:   ifle L135
L129:   aload_0
L130:   iload 4
L132:   aload 7
L134:   aastore
L135:   iinc 4 1
L138:   iload 4
L140:   aload_1
L141:   arraylength
L142:   if_icmplt L26
L145:   return
L146:   astore 4
L148:   new java/lang/StringBuffer
L151:   dup
L152:   ldc "31506, "
L154:   invokespecial Method java/lang/StringBuffer <init> (Ljava/lang/String;)V
L157:   aload_0
L158:   invokevirtual Method java/lang/StringBuffer append (Ljava/lang/Object;)Ljava/lang/StringBuffer;
L161:   ldc ", "
L163:   invokevirtual Method java/lang/StringBuffer append (Ljava/lang/String;)Ljava/lang/StringBuffer;
L166:   aload_1
L167:   invokevirtual Method java/lang/StringBuffer append (Ljava/lang/Object;)Ljava/lang/StringBuffer;
L170:   ldc ", "
L172:   invokevirtual Method java/lang/StringBuffer append (Ljava/lang/String;)Ljava/lang/StringBuffer;
L175:   aload_2
L176:   invokevirtual Method java/lang/StringBuffer append (Ljava/lang/Object;)Ljava/lang/StringBuffer;
L179:   ldc ", "
L181:   invokevirtual Method java/lang/StringBuffer append (Ljava/lang/String;)Ljava/lang/StringBuffer;
L184:   iload_3
L185:   invokevirtual Method java/lang/StringBuffer append (I)Ljava/lang/StringBuffer;
L188:   ldc ", "
L190:   invokevirtual Method java/lang/StringBuffer append (Ljava/lang/String;)Ljava/lang/StringBuffer;
L193:   aload 4
L195:   invokevirtual Method java/lang/Throwable toString ()Ljava/lang/String;
L198:   invokevirtual Method java/lang/StringBuffer append (Ljava/lang/String;)Ljava/lang/StringBuffer;
L201:   invokevirtual Method java/lang/StringBuffer toString ()Ljava/lang/String;
L204:   invokestatic Method sign/signlink reporterror (Ljava/lang/String;)V
L207:   new java/lang/RuntimeException
L210:   dup
L211:   invokespecial Method java/lang/RuntimeException <init> ()V
L214:   athrow
L215:   
    .end code
.end method

.method private static final a : (ILkb;[[C)V
    .code stack 4 locals 7
L0:     getstatic Field mc q I
L3:     istore 6
        .catch java/lang/RuntimeException from L5 to L86 using L87
L5:     iload 6
L7:     ifeq L24
L10:    iconst_1
L11:    istore_3
L12:    iload 6
L14:    ifeq L20
L17:    iinc 3 1
L20:    iload_3
L21:    ifgt L17
L24:    iload_0
L25:    ifge L10
L28:    iconst_0
L29:    istore_3
L30:    iload 6
L32:    ifeq L80
L35:    aload_1
L36:    invokevirtual Method kb c ()I
L39:    newarray char
L41:    astore 4
L43:    iconst_0
L44:    istore 5
L46:    iload 6
L48:    ifeq L64
L51:    aload 4
L53:    iload 5
L55:    aload_1
L56:    invokevirtual Method kb c ()I
L59:    i2c
L60:    castore
L61:    iinc 5 1
L64:    iload 5
L66:    aload 4
L68:    arraylength
L69:    if_icmplt L51
L72:    aload_2
L73:    iload_3
L74:    aload 4
L76:    aastore
L77:    iinc 3 1
L80:    iload_3
L81:    aload_2
L82:    arraylength
L83:    if_icmplt L35
L86:    return
L87:    astore_3
L88:    new java/lang/StringBuffer
L91:    dup
L92:    ldc "81110, "
L94:    invokespecial Method java/lang/StringBuffer <init> (Ljava/lang/String;)V
L97:    iload_0
L98:    invokevirtual Method java/lang/StringBuffer append (I)Ljava/lang/StringBuffer;
L101:   ldc ", "
L103:   invokevirtual Method java/lang/StringBuffer append (Ljava/lang/String;)Ljava/lang/StringBuffer;
L106:   aload_1
L107:   invokevirtual Method java/lang/StringBuffer append (Ljava/lang/Object;)Ljava/lang/StringBuffer;
L110:   ldc ", "
L112:   invokevirtual Method java/lang/StringBuffer append (Ljava/lang/String;)Ljava/lang/StringBuffer;
L115:   aload_2
L116:   invokevirtual Method java/lang/StringBuffer append (Ljava/lang/Object;)Ljava/lang/StringBuffer;
L119:   ldc ", "
L121:   invokevirtual Method java/lang/StringBuffer append (Ljava/lang/String;)Ljava/lang/StringBuffer;
L124:   aload_3
L125:   invokevirtual Method java/lang/Throwable toString ()Ljava/lang/String;
L128:   invokevirtual Method java/lang/StringBuffer append (Ljava/lang/String;)Ljava/lang/StringBuffer;
L131:   invokevirtual Method java/lang/StringBuffer toString ()Ljava/lang/String;
L134:   invokestatic Method sign/signlink reporterror (Ljava/lang/String;)V
L137:   new java/lang/RuntimeException
L140:   dup
L141:   invokespecial Method java/lang/RuntimeException <init> ()V
L144:   athrow
L145:   
    .end code
.end method

.method private static final a : ([CI)V
    .code stack 5 locals 6
L0:     getstatic Field mc q I
L3:     istore 5
        .catch java/lang/RuntimeException from L5 to L118 using L119
L5:     iconst_0
L6:     istore_2
L7:     iconst_0
L8:     istore_3
L9:     iload 5
L11:    ifeq L70
L14:    sipush 16180
L17:    aload_0
L18:    iload_3
L19:    caload
L20:    invokestatic Method mc a (IC)Z
L23:    ifeq L37
L26:    aload_0
L27:    iload_2
L28:    aload_0
L29:    iload_3
L30:    caload
L31:    castore
L32:    iload 5
L34:    ifeq L42
L37:    aload_0
L38:    iload_2
L39:    bipush 32
L41:    castore
L42:    iload_2
L43:    ifeq L64
L46:    aload_0
L47:    iload_2
L48:    caload
L49:    bipush 32
L51:    if_icmpne L64
L54:    aload_0
L55:    iload_2
L56:    iconst_1
L57:    isub
L58:    caload
L59:    bipush 32
L61:    if_icmpeq L67
L64:    iinc 2 1
L67:    iinc 3 1
L70:    iload_3
L71:    aload_0
L72:    arraylength
L73:    if_icmplt L14
L76:    iload_1
L77:    ifeq L94
L80:    getstatic Field mc a Z
L83:    ifeq L90
L86:    iconst_0
L87:    goto L91
L90:    iconst_1
L91:    putstatic Field mc a Z
L94:    iload_2
L95:    istore 4
L97:    iload 5
L99:    ifeq L111
L102:   aload_0
L103:   iload 4
L105:   bipush 32
L107:   castore
L108:   iinc 4 1
L111:   iload 4
L113:   aload_0
L114:   arraylength
L115:   if_icmplt L102
L118:   return
L119:   astore_2
L120:   new java/lang/StringBuffer
L123:   dup
L124:   ldc "86890, "
L126:   invokespecial Method java/lang/StringBuffer <init> (Ljava/lang/String;)V
L129:   aload_0
L130:   invokevirtual Method java/lang/StringBuffer append ([C)Ljava/lang/StringBuffer;
L133:   ldc ", "
L135:   invokevirtual Method java/lang/StringBuffer append (Ljava/lang/String;)Ljava/lang/StringBuffer;
L138:   iload_1
L139:   invokevirtual Method java/lang/StringBuffer append (I)Ljava/lang/StringBuffer;
L142:   ldc ", "
L144:   invokevirtual Method java/lang/StringBuffer append (Ljava/lang/String;)Ljava/lang/StringBuffer;
L147:   aload_2
L148:   invokevirtual Method java/lang/Throwable toString ()Ljava/lang/String;
L151:   invokevirtual Method java/lang/StringBuffer append (Ljava/lang/String;)Ljava/lang/StringBuffer;
L154:   invokevirtual Method java/lang/StringBuffer toString ()Ljava/lang/String;
L157:   invokestatic Method sign/signlink reporterror (Ljava/lang/String;)V
L160:   new java/lang/RuntimeException
L163:   dup
L164:   invokespecial Method java/lang/RuntimeException <init> ()V
L167:   athrow
L168:   
    .end code
.end method

.method private static final a : (IC)Z
    .code stack 3 locals 3
        .catch java/lang/RuntimeException from L0 to L63 using L63
L0:     iload_0
L1:     getstatic Field mc e I
L4:     if_icmpeq L15
L7:     new java/lang/NullPointerException
L10:    dup
L11:    invokespecial Method java/lang/NullPointerException <init> ()V
L14:    athrow
L15:    iload_1
L16:    bipush 32
L18:    if_icmplt L27
L21:    iload_1
L22:    bipush 127
L24:    if_icmple L61
L27:    iload_1
L28:    bipush 32
L30:    if_icmpeq L61
L33:    iload_1
L34:    bipush 10
L36:    if_icmpeq L61
L39:    iload_1
L40:    bipush 9
L42:    if_icmpeq L61
L45:    iload_1
L46:    sipush 163
L49:    if_icmpeq L61
L52:    iload_1
L53:    sipush 8364
L56:    if_icmpeq L61
L59:    iconst_0
L60:    ireturn
L61:    iconst_1
L62:    ireturn
L63:    astore_2
L64:    new java/lang/StringBuffer
L67:    dup
L68:    ldc "68887, "
L70:    invokespecial Method java/lang/StringBuffer <init> (Ljava/lang/String;)V
L73:    iload_0
L74:    invokevirtual Method java/lang/StringBuffer append (I)Ljava/lang/StringBuffer;
L77:    ldc ", "
L79:    invokevirtual Method java/lang/StringBuffer append (Ljava/lang/String;)Ljava/lang/StringBuffer;
L82:    iload_1
L83:    invokevirtual Method java/lang/StringBuffer append (C)Ljava/lang/StringBuffer;
L86:    ldc ", "
L88:    invokevirtual Method java/lang/StringBuffer append (Ljava/lang/String;)Ljava/lang/StringBuffer;
L91:    aload_2
L92:    invokevirtual Method java/lang/Throwable toString ()Ljava/lang/String;
L95:    invokevirtual Method java/lang/StringBuffer append (Ljava/lang/String;)Ljava/lang/StringBuffer;
L98:    invokevirtual Method java/lang/StringBuffer toString ()Ljava/lang/String;
L101:   invokestatic Method sign/signlink reporterror (Ljava/lang/String;)V
L104:   new java/lang/RuntimeException
L107:   dup
L108:   invokespecial Method java/lang/RuntimeException <init> ()V
L111:   athrow
L112:   
    .end code
.end method

.method public static final a : (Ljava/lang/String;I)Ljava/lang/String;
    .code stack 5 locals 13
L0:     getstatic Field mc q I
L3:     istore 11
        .catch java/lang/RuntimeException from L5 to L242 using L242
L5:     invokestatic Method java/lang/System currentTimeMillis ()J
L8:     lstore_2
L9:     aload_0
L10:    invokevirtual Method java/lang/String toCharArray ()[C
L13:    astore 4
L15:    aload 4
L17:    iconst_0
L18:    invokestatic Method mc a ([CI)V
L21:    new java/lang/String
L24:    dup
L25:    aload 4
L27:    invokespecial Method java/lang/String <init> ([C)V
L30:    invokevirtual Method java/lang/String trim ()Ljava/lang/String;
L33:    astore 5
L35:    aload 5
L37:    invokevirtual Method java/lang/String toLowerCase ()Ljava/lang/String;
L40:    invokevirtual Method java/lang/String toCharArray ()[C
L43:    astore 4
L45:    aload 5
L47:    invokevirtual Method java/lang/String toLowerCase ()Ljava/lang/String;
L50:    astore 6
L52:    aload 4
L54:    iconst_0
L55:    invokestatic Method mc b ([CI)V
L58:    iconst_1
L59:    aload 4
L61:    invokestatic Method mc a (Z[C)V
L64:    bipush 120
L66:    aload 4
L68:    invokestatic Method mc b (B[C)V
L71:    bipush 8
L73:    aload 4
L75:    invokestatic Method mc a (I[C)V
L78:    iconst_0
L79:    istore 7
L81:    iload 11
L83:    ifeq L175
L86:    getstatic Field u d I
L89:    istore 12
L91:    iinc 12 1
L94:    iload 12
L96:    putstatic Field u d I
L99:    iconst_m1
L100:   istore 8
L102:   iload 11
L104:   ifeq L150
L107:   getstatic Field mc p [Ljava/lang/String;
L110:   iload 7
L112:   aaload
L113:   invokevirtual Method java/lang/String toCharArray ()[C
L116:   astore 9
L118:   iconst_0
L119:   istore 10
L121:   iload 11
L123:   ifeq L142
L126:   aload 4
L128:   iload 10
L130:   iload 8
L132:   iadd
L133:   aload 9
L135:   iload 10
L137:   caload
L138:   castore
L139:   iinc 10 1
L142:   iload 10
L144:   aload 9
L146:   arraylength
L147:   if_icmplt L126
L150:   aload 6
L152:   getstatic Field mc p [Ljava/lang/String;
L155:   iload 7
L157:   aaload
L158:   iload 8
L160:   iconst_1
L161:   iadd
L162:   invokevirtual Method java/lang/String indexOf (Ljava/lang/String;I)I
L165:   dup
L166:   istore 8
L168:   iconst_m1
L169:   if_icmpne L107
L172:   iinc 7 1
L175:   iload 7
L177:   getstatic Field mc p [Ljava/lang/String;
L180:   arraylength
L181:   if_icmplt L99
L184:   iload_1
L185:   ifeq L204
L188:   iconst_1
L189:   istore 8
L191:   iload 11
L193:   ifeq L199
L196:   iinc 8 1
L199:   iload 8
L201:   ifgt L196
L204:   aload 4
L206:   sipush 135
L209:   aload 5
L211:   invokevirtual Method java/lang/String toCharArray ()[C
L214:   invokestatic Method mc a ([CI[C)V
L217:   bipush 6
L219:   aload 4
L221:   invokestatic Method mc a (B[C)V
L224:   invokestatic Method java/lang/System currentTimeMillis ()J
L227:   lstore 8
L229:   new java/lang/String
L232:   dup
L233:   aload 4
L235:   invokespecial Method java/lang/String <init> ([C)V
L238:   invokevirtual Method java/lang/String trim ()Ljava/lang/String;
L241:   areturn
L242:   astore_2
L243:   new java/lang/StringBuffer
L246:   dup
L247:   ldc "37188, "
L249:   invokespecial Method java/lang/StringBuffer <init> (Ljava/lang/String;)V
L252:   aload_0
L253:   invokevirtual Method java/lang/StringBuffer append (Ljava/lang/String;)Ljava/lang/StringBuffer;
L256:   ldc ", "
L258:   invokevirtual Method java/lang/StringBuffer append (Ljava/lang/String;)Ljava/lang/StringBuffer;
L261:   iload_1
L262:   invokevirtual Method java/lang/StringBuffer append (I)Ljava/lang/StringBuffer;
L265:   ldc ", "
L267:   invokevirtual Method java/lang/StringBuffer append (Ljava/lang/String;)Ljava/lang/StringBuffer;
L270:   aload_2
L271:   invokevirtual Method java/lang/Throwable toString ()Ljava/lang/String;
L274:   invokevirtual Method java/lang/StringBuffer append (Ljava/lang/String;)Ljava/lang/StringBuffer;
L277:   invokevirtual Method java/lang/StringBuffer toString ()Ljava/lang/String;
L280:   invokestatic Method sign/signlink reporterror (Ljava/lang/String;)V
L283:   new java/lang/RuntimeException
L286:   dup
L287:   invokespecial Method java/lang/RuntimeException <init> ()V
L290:   athrow
L291:   
    .end code
.end method

.method private static final a : ([CI[C)V
    .code stack 5 locals 4
        .catch java/lang/RuntimeException from L0 to L46 using L47
L0:     iconst_0
L1:     istore_3
L2:     getstatic Field mc q I
L5:     ifeq L35
L8:     aload_0
L9:     iload_3
L10:    caload
L11:    bipush 42
L13:    if_icmpeq L32
L16:    iconst_0
L17:    aload_2
L18:    iload_3
L19:    caload
L20:    invokestatic Method mc d (IC)Z
L23:    ifeq L32
L26:    aload_0
L27:    iload_3
L28:    aload_2
L29:    iload_3
L30:    caload
L31:    castore
L32:    iinc 3 1
L35:    iload_3
L36:    aload_2
L37:    arraylength
L38:    if_icmplt L8
L41:    bipush 76
L43:    iload_1
L44:    idiv
L45:    istore_1
L46:    return
L47:    astore_3
L48:    new java/lang/StringBuffer
L51:    dup
L52:    ldc "76099, "
L54:    invokespecial Method java/lang/StringBuffer <init> (Ljava/lang/String;)V
L57:    aload_0
L58:    invokevirtual Method java/lang/StringBuffer append ([C)Ljava/lang/StringBuffer;
L61:    ldc ", "
L63:    invokevirtual Method java/lang/StringBuffer append (Ljava/lang/String;)Ljava/lang/StringBuffer;
L66:    iload_1
L67:    invokevirtual Method java/lang/StringBuffer append (I)Ljava/lang/StringBuffer;
L70:    ldc ", "
L72:    invokevirtual Method java/lang/StringBuffer append (Ljava/lang/String;)Ljava/lang/StringBuffer;
L75:    aload_2
L76:    invokevirtual Method java/lang/StringBuffer append ([C)Ljava/lang/StringBuffer;
L79:    ldc ", "
L81:    invokevirtual Method java/lang/StringBuffer append (Ljava/lang/String;)Ljava/lang/StringBuffer;
L84:    aload_3
L85:    invokevirtual Method java/lang/Throwable toString ()Ljava/lang/String;
L88:    invokevirtual Method java/lang/StringBuffer append (Ljava/lang/String;)Ljava/lang/StringBuffer;
L91:    invokevirtual Method java/lang/StringBuffer toString ()Ljava/lang/String;
L94:    invokestatic Method sign/signlink reporterror (Ljava/lang/String;)V
L97:    new java/lang/RuntimeException
L100:   dup
L101:   invokespecial Method java/lang/RuntimeException <init> ()V
L104:   athrow
L105:   
    .end code
.end method

.method private static final a : (B[C)V
    .code stack 5 locals 6
L0:     getstatic Field mc q I
L3:     istore 5
        .catch java/lang/RuntimeException from L5 to L101 using L102
L5:     iconst_1
L6:     istore_2
L7:     iload_0
L8:     bipush 6
L10:    if_icmpne L20
L13:    iconst_0
L14:    istore_0
L15:    iload 5
L17:    ifeq L21
L20:    return
L21:    iconst_0
L22:    istore_3
L23:    iload 5
L25:    ifeq L95
L28:    aload_1
L29:    iload_3
L30:    caload
L31:    istore 4
L33:    sipush -175
L36:    iload 4
L38:    invokestatic Method mc c (IC)Z
L41:    ifeq L90
L44:    iload_2
L45:    ifeq L64
L48:    iconst_0
L49:    iload 4
L51:    invokestatic Method mc a (BC)Z
L54:    ifeq L92
L57:    iconst_0
L58:    istore_2
L59:    iload 5
L61:    ifeq L92
L64:    iconst_0
L65:    iload 4
L67:    invokestatic Method mc d (IC)Z
L70:    ifeq L92
L73:    aload_1
L74:    iload_3
L75:    iload 4
L77:    bipush 97
L79:    iadd
L80:    bipush 65
L82:    isub
L83:    i2c
L84:    castore
L85:    iload 5
L87:    ifeq L92
L90:    iconst_1
L91:    istore_2
L92:    iinc 3 1
L95:    iload_3
L96:    aload_1
L97:    arraylength
L98:    if_icmplt L28
L101:   return
L102:   astore_2
L103:   new java/lang/StringBuffer
L106:   dup
L107:   ldc "18272, "
L109:   invokespecial Method java/lang/StringBuffer <init> (Ljava/lang/String;)V
L112:   iload_0
L113:   invokevirtual Method java/lang/StringBuffer append (I)Ljava/lang/StringBuffer;
L116:   ldc ", "
L118:   invokevirtual Method java/lang/StringBuffer append (Ljava/lang/String;)Ljava/lang/StringBuffer;
L121:   aload_1
L122:   invokevirtual Method java/lang/StringBuffer append ([C)Ljava/lang/StringBuffer;
L125:   ldc ", "
L127:   invokevirtual Method java/lang/StringBuffer append (Ljava/lang/String;)Ljava/lang/StringBuffer;
L130:   aload_2
L131:   invokevirtual Method java/lang/Throwable toString ()Ljava/lang/String;
L134:   invokevirtual Method java/lang/StringBuffer append (Ljava/lang/String;)Ljava/lang/StringBuffer;
L137:   invokevirtual Method java/lang/StringBuffer toString ()Ljava/lang/String;
L140:   invokestatic Method sign/signlink reporterror (Ljava/lang/String;)V
L143:   new java/lang/RuntimeException
L146:   dup
L147:   invokespecial Method java/lang/RuntimeException <init> ()V
L150:   athrow
L151:   
    .end code
.end method

.method private static final a : (Z[C)V
    .code stack 6 locals 5
L0:     getstatic Field mc q I
L3:     istore 4
        .catch java/lang/RuntimeException from L5 to L60 using L60
L5:     iconst_0
L6:     istore_2
L7:     iload 4
L9:     ifeq L50
L12:    getstatic Field mc k [[C
L15:    arraylength
L16:    iconst_1
L17:    isub
L18:    istore_3
L19:    iload 4
L21:    ifeq L43
L24:    bipush -102
L26:    getstatic Field mc l [[[B
L29:    iload_3
L30:    aaload
L31:    aload_1
L32:    getstatic Field mc k [[C
L35:    iload_3
L36:    aaload
L37:    invokestatic Method mc a (B[[B[C[C)V
L40:    iinc 3 -1
L43:    iload_3
L44:    ifge L24
L47:    iinc 2 1
L50:    iload_2
L51:    iconst_2
L52:    if_icmplt L12
L55:    iload_0
L56:    ifne L109
L59:    return
L60:    astore_2
L61:    new java/lang/StringBuffer
L64:    dup
L65:    ldc "90308, "
L67:    invokespecial Method java/lang/StringBuffer <init> (Ljava/lang/String;)V
L70:    iload_0
L71:    invokevirtual Method java/lang/StringBuffer append (Z)Ljava/lang/StringBuffer;
L74:    ldc ", "
L76:    invokevirtual Method java/lang/StringBuffer append (Ljava/lang/String;)Ljava/lang/StringBuffer;
L79:    aload_1
L80:    invokevirtual Method java/lang/StringBuffer append ([C)Ljava/lang/StringBuffer;
L83:    ldc ", "
L85:    invokevirtual Method java/lang/StringBuffer append (Ljava/lang/String;)Ljava/lang/StringBuffer;
L88:    aload_2
L89:    invokevirtual Method java/lang/Throwable toString ()Ljava/lang/String;
L92:    invokevirtual Method java/lang/StringBuffer append (Ljava/lang/String;)Ljava/lang/StringBuffer;
L95:    invokevirtual Method java/lang/StringBuffer toString ()Ljava/lang/String;
L98:    invokestatic Method sign/signlink reporterror (Ljava/lang/String;)V
L101:   new java/lang/RuntimeException
L104:   dup
L105:   invokespecial Method java/lang/RuntimeException <init> ()V
L108:   athrow
L109:   return
L110:   
    .end code
.end method

.method private static final b : (B[C)V
    .code stack 6 locals 7
        .catch java/lang/RuntimeException from L0 to L119 using L120
L0:     aload_1
L1:     invokevirtual Method java/lang/Object clone ()Ljava/lang/Object;
L4:     checkcast [C
L7:     astore_2
L8:     iconst_3
L9:     newarray char
L11:    dup
L12:    iconst_0
L13:    bipush 40
L15:    castore
L16:    dup
L17:    iconst_1
L18:    bipush 97
L20:    castore
L21:    dup
L22:    iconst_2
L23:    bipush 41
L25:    castore
L26:    astore_3
L27:    bipush -102
L29:    aconst_null
L30:    aload_2
L31:    aload_3
L32:    invokestatic Method mc a (B[[B[C[C)V
L35:    aload_1
L36:    invokevirtual Method java/lang/Object clone ()Ljava/lang/Object;
L39:    checkcast [C
L42:    astore 4
L44:    iconst_3
L45:    newarray char
L47:    dup
L48:    iconst_0
L49:    bipush 100
L51:    castore
L52:    dup
L53:    iconst_1
L54:    bipush 111
L56:    castore
L57:    dup
L58:    iconst_2
L59:    bipush 116
L61:    castore
L62:    astore 5
L64:    bipush -102
L66:    aconst_null
L67:    aload 4
L69:    aload 5
L71:    invokestatic Method mc a (B[[B[C[C)V
L74:    iload_0
L75:    bipush 120
L77:    if_icmpeq L81
L80:    return
L81:    getstatic Field mc m [[C
L84:    arraylength
L85:    iconst_1
L86:    isub
L87:    istore 6
L89:    getstatic Field mc q I
L92:    ifeq L114
L95:    aload 4
L97:    sipush -706
L100:   aload_2
L101:   getstatic Field mc m [[C
L104:   iload 6
L106:   aaload
L107:   aload_1
L108:   invokestatic Method mc a ([CI[C[C[C)V
L111:   iinc 6 -1
L114:   iload 6
L116:   ifge L95
L119:   return
L120:   astore_2
L121:   new java/lang/StringBuffer
L124:   dup
L125:   ldc "68434, "
L127:   invokespecial Method java/lang/StringBuffer <init> (Ljava/lang/String;)V
L130:   iload_0
L131:   invokevirtual Method java/lang/StringBuffer append (I)Ljava/lang/StringBuffer;
L134:   ldc ", "
L136:   invokevirtual Method java/lang/StringBuffer append (Ljava/lang/String;)Ljava/lang/StringBuffer;
L139:   aload_1
L140:   invokevirtual Method java/lang/StringBuffer append ([C)Ljava/lang/StringBuffer;
L143:   ldc ", "
L145:   invokevirtual Method java/lang/StringBuffer append (Ljava/lang/String;)Ljava/lang/StringBuffer;
L148:   aload_2
L149:   invokevirtual Method java/lang/Throwable toString ()Ljava/lang/String;
L152:   invokevirtual Method java/lang/StringBuffer append (Ljava/lang/String;)Ljava/lang/StringBuffer;
L155:   invokevirtual Method java/lang/StringBuffer toString ()Ljava/lang/String;
L158:   invokestatic Method sign/signlink reporterror (Ljava/lang/String;)V
L161:   new java/lang/RuntimeException
L164:   dup
L165:   invokespecial Method java/lang/RuntimeException <init> ()V
L168:   athrow
L169:   
    .end code
.end method

.method private static final a : ([CI[C[C[C)V
    .code stack 6 locals 14
L0:     getstatic Field mc q I
L3:     istore 13
        .catch java/lang/RuntimeException from L5 to L301 using L302
L5:     aload_3
L6:     arraylength
L7:     aload 4
L9:     arraylength
L10:    if_icmple L14
L13:    return
L14:    iconst_1
L15:    istore 5
L17:    iload_1
L18:    iflt L27
L21:    sipush -499
L24:    putstatic Field mc e I
L27:    iconst_0
L28:    istore 6
L30:    iload 13
L32:    ifeq L290
L35:    iload 6
L37:    istore 7
L39:    iconst_0
L40:    istore 8
L42:    iconst_1
L43:    istore 5
L45:    iload 13
L47:    ifeq L192
L50:    iconst_0
L51:    istore 9
L53:    aload 4
L55:    iload 7
L57:    caload
L58:    istore 10
L60:    iconst_0
L61:    istore 11
L63:    iload 7
L65:    iconst_1
L66:    iadd
L67:    aload 4
L69:    arraylength
L70:    if_icmpge L82
L73:    aload 4
L75:    iload 7
L77:    iconst_1
L78:    iadd
L79:    caload
L80:    istore 11
L82:    iload 8
L84:    aload_3
L85:    arraylength
L86:    if_icmpge L123
L89:    bipush -81
L91:    iload 11
L93:    aload_3
L94:    iload 8
L96:    caload
L97:    iload 10
L99:    invokestatic Method mc a (ICCC)I
L102:   dup
L103:   istore 9
L105:   ifle L123
L108:   iload 7
L110:   iload 9
L112:   iadd
L113:   istore 7
L115:   iinc 8 1
L118:   iload 13
L120:   ifeq L192
L123:   iload 8
L125:   ifeq L200
L128:   bipush -81
L130:   iload 11
L132:   aload_3
L133:   iload 8
L135:   iconst_1
L136:   isub
L137:   caload
L138:   iload 10
L140:   invokestatic Method mc a (ICCC)I
L143:   dup
L144:   istore 9
L146:   ifle L170
L149:   iload 7
L151:   iload 9
L153:   iadd
L154:   istore 7
L156:   iload 8
L158:   iconst_1
L159:   if_icmpne L192
L162:   iinc 5 1
L165:   iload 13
L167:   ifeq L192
L170:   iload 8
L172:   aload_3
L173:   arraylength
L174:   if_icmpge L200
L177:   iload 10
L179:   iconst_2
L180:   invokestatic Method mc a (CI)Z
L183:   ifeq L200
L186:   iinc 7 1
L189:   goto L192
L192:   iload 7
L194:   aload 4
L196:   arraylength
L197:   if_icmplt L50
L200:   iload 8
L202:   aload_3
L203:   arraylength
L204:   if_icmplt L283
L207:   iconst_0
L208:   istore 9
L210:   iload 6
L212:   aload 4
L214:   bipush 6
L216:   aload_2
L217:   invokestatic Method mc a (I[CB[C)I
L220:   istore 10
L222:   aload_0
L223:   aload 4
L225:   iload 7
L227:   iconst_1
L228:   isub
L229:   sipush -808
L232:   invokestatic Method mc a ([C[CII)I
L235:   istore 11
L237:   iload 10
L239:   iconst_2
L240:   if_icmpgt L249
L243:   iload 11
L245:   iconst_2
L246:   if_icmple L252
L249:   iconst_1
L250:   istore 9
L252:   iload 9
L254:   ifeq L283
L257:   iload 6
L259:   istore 12
L261:   iload 13
L263:   ifeq L276
L266:   aload 4
L268:   iload 12
L270:   bipush 42
L272:   castore
L273:   iinc 12 1
L276:   iload 12
L278:   iload 7
L280:   if_icmplt L266
L283:   iload 6
L285:   iload 5
L287:   iadd
L288:   istore 6
L290:   iload 6
L292:   aload 4
L294:   arraylength
L295:   aload_3
L296:   arraylength
L297:   isub
L298:   if_icmple L35
L301:   return
L302:   astore 5
L304:   new java/lang/StringBuffer
L307:   dup
L308:   ldc "98022, "
L310:   invokespecial Method java/lang/StringBuffer <init> (Ljava/lang/String;)V
L313:   aload_0
L314:   invokevirtual Method java/lang/StringBuffer append ([C)Ljava/lang/StringBuffer;
L317:   ldc ", "
L319:   invokevirtual Method java/lang/StringBuffer append (Ljava/lang/String;)Ljava/lang/StringBuffer;
L322:   iload_1
L323:   invokevirtual Method java/lang/StringBuffer append (I)Ljava/lang/StringBuffer;
L326:   ldc ", "
L328:   invokevirtual Method java/lang/StringBuffer append (Ljava/lang/String;)Ljava/lang/StringBuffer;
L331:   aload_2
L332:   invokevirtual Method java/lang/StringBuffer append ([C)Ljava/lang/StringBuffer;
L335:   ldc ", "
L337:   invokevirtual Method java/lang/StringBuffer append (Ljava/lang/String;)Ljava/lang/StringBuffer;
L340:   aload_3
L341:   invokevirtual Method java/lang/StringBuffer append ([C)Ljava/lang/StringBuffer;
L344:   ldc ", "
L346:   invokevirtual Method java/lang/StringBuffer append (Ljava/lang/String;)Ljava/lang/StringBuffer;
L349:   aload 4
L351:   invokevirtual Method java/lang/StringBuffer append ([C)Ljava/lang/StringBuffer;
L354:   ldc ", "
L356:   invokevirtual Method java/lang/StringBuffer append (Ljava/lang/String;)Ljava/lang/StringBuffer;
L359:   aload 5
L361:   invokevirtual Method java/lang/Throwable toString ()Ljava/lang/String;
L364:   invokevirtual Method java/lang/StringBuffer append (Ljava/lang/String;)Ljava/lang/StringBuffer;
L367:   invokevirtual Method java/lang/StringBuffer toString ()Ljava/lang/String;
L370:   invokestatic Method sign/signlink reporterror (Ljava/lang/String;)V
L373:   new java/lang/RuntimeException
L376:   dup
L377:   invokespecial Method java/lang/RuntimeException <init> ()V
L380:   athrow
L381:   
    .end code
.end method

.method private static final a : (I[CB[C)I
    .code stack 4 locals 8
L0:     getstatic Field mc q I
L3:     istore 7
        .catch java/lang/RuntimeException from L5 to L140 using L140
L5:     iload_0
L6:     ifne L11
L9:     iconst_2
L10:    ireturn
L11:    iload_0
L12:    iconst_1
L13:    isub
L14:    istore 4
L16:    iload 7
L18:    ifeq L46
L21:    aload_1
L22:    iload 4
L24:    caload
L25:    iconst_2
L26:    invokestatic Method mc a (CI)Z
L29:    ifeq L51
L32:    aload_1
L33:    iload 4
L35:    caload
L36:    bipush 64
L38:    if_icmpne L43
L41:    iconst_3
L42:    ireturn
L43:    iinc 4 -1
L46:    iload 4
L48:    ifge L21
L51:    iload_2
L52:    getstatic Field mc g B
L55:    if_icmpne L65
L58:    iconst_0
L59:    istore_2
L60:    iload 7
L62:    ifeq L69
L65:    getstatic Field mc c I
L68:    ireturn
L69:    iconst_0
L70:    istore 5
L72:    iload_0
L73:    iconst_1
L74:    isub
L75:    istore 6
L77:    iload 7
L79:    ifeq L111
L82:    aload_3
L83:    iload 6
L85:    caload
L86:    iconst_2
L87:    invokestatic Method mc a (CI)Z
L90:    ifeq L116
L93:    aload_3
L94:    iload 6
L96:    caload
L97:    bipush 42
L99:    if_icmpne L108
L102:   iinc 5 1
L105:   goto L108
L108:   iinc 6 -1
L111:   iload 6
L113:   ifge L82
L116:   iload 5
L118:   iconst_3
L119:   if_icmplt L124
L122:   iconst_4
L123:   ireturn
L124:   aload_1
L125:   iload_0
L126:   iconst_1
L127:   isub
L128:   caload
L129:   iconst_2
L130:   invokestatic Method mc a (CI)Z
L133:   ifeq L138
L136:   iconst_1
L137:   ireturn
L138:   iconst_0
L139:   ireturn
L140:   astore 4
L142:   new java/lang/StringBuffer
L145:   dup
L146:   ldc "51966, "
L148:   invokespecial Method java/lang/StringBuffer <init> (Ljava/lang/String;)V
L151:   iload_0
L152:   invokevirtual Method java/lang/StringBuffer append (I)Ljava/lang/StringBuffer;
L155:   ldc ", "
L157:   invokevirtual Method java/lang/StringBuffer append (Ljava/lang/String;)Ljava/lang/StringBuffer;
L160:   aload_1
L161:   invokevirtual Method java/lang/StringBuffer append ([C)Ljava/lang/StringBuffer;
L164:   ldc ", "
L166:   invokevirtual Method java/lang/StringBuffer append (Ljava/lang/String;)Ljava/lang/StringBuffer;
L169:   iload_2
L170:   invokevirtual Method java/lang/StringBuffer append (I)Ljava/lang/StringBuffer;
L173:   ldc ", "
L175:   invokevirtual Method java/lang/StringBuffer append (Ljava/lang/String;)Ljava/lang/StringBuffer;
L178:   aload_3
L179:   invokevirtual Method java/lang/StringBuffer append ([C)Ljava/lang/StringBuffer;
L182:   ldc ", "
L184:   invokevirtual Method java/lang/StringBuffer append (Ljava/lang/String;)Ljava/lang/StringBuffer;
L187:   aload 4
L189:   invokevirtual Method java/lang/Throwable toString ()Ljava/lang/String;
L192:   invokevirtual Method java/lang/StringBuffer append (Ljava/lang/String;)Ljava/lang/StringBuffer;
L195:   invokevirtual Method java/lang/StringBuffer toString ()Ljava/lang/String;
L198:   invokestatic Method sign/signlink reporterror (Ljava/lang/String;)V
L201:   new java/lang/RuntimeException
L204:   dup
L205:   invokespecial Method java/lang/RuntimeException <init> ()V
L208:   athrow
L209:   
    .end code
.end method

.method private static final a : ([C[CII)I
    .code stack 4 locals 8
L0:     getstatic Field mc q I
L3:     istore 7
        .catch java/lang/RuntimeException from L5 to L147 using L147
L5:     iload_3
L6:     iflt L13
L9:     getstatic Field mc d I
L12:    ireturn
L13:    iload_2
L14:    iconst_1
L15:    iadd
L16:    aload_1
L17:    arraylength
L18:    if_icmpne L23
L21:    iconst_2
L22:    ireturn
L23:    iload_2
L24:    iconst_1
L25:    iadd
L26:    istore 4
L28:    iload 7
L30:    ifeq L67
L33:    aload_1
L34:    iload 4
L36:    caload
L37:    iconst_2
L38:    invokestatic Method mc a (CI)Z
L41:    ifeq L74
L44:    aload_1
L45:    iload 4
L47:    caload
L48:    bipush 46
L50:    if_icmpeq L62
L53:    aload_1
L54:    iload 4
L56:    caload
L57:    bipush 44
L59:    if_icmpne L64
L62:    iconst_3
L63:    ireturn
L64:    iinc 4 1
L67:    iload 4
L69:    aload_1
L70:    arraylength
L71:    if_icmplt L33
L74:    iconst_0
L75:    istore 5
L77:    iload_2
L78:    iconst_1
L79:    iadd
L80:    istore 6
L82:    iload 7
L84:    ifeq L116
L87:    aload_0
L88:    iload 6
L90:    caload
L91:    iconst_2
L92:    invokestatic Method mc a (CI)Z
L95:    ifeq L123
L98:    aload_0
L99:    iload 6
L101:   caload
L102:   bipush 42
L104:   if_icmpne L113
L107:   iinc 5 1
L110:   goto L113
L113:   iinc 6 1
L116:   iload 6
L118:   aload_1
L119:   arraylength
L120:   if_icmplt L87
L123:   iload 5
L125:   iconst_3
L126:   if_icmplt L131
L129:   iconst_4
L130:   ireturn
L131:   aload_1
L132:   iload_2
L133:   iconst_1
L134:   iadd
L135:   caload
L136:   iconst_2
L137:   invokestatic Method mc a (CI)Z
L140:   ifeq L145
L143:   iconst_1
L144:   ireturn
L145:   iconst_0
L146:   ireturn
L147:   astore 4
L149:   new java/lang/StringBuffer
L152:   dup
L153:   ldc "48464, "
L155:   invokespecial Method java/lang/StringBuffer <init> (Ljava/lang/String;)V
L158:   aload_0
L159:   invokevirtual Method java/lang/StringBuffer append ([C)Ljava/lang/StringBuffer;
L162:   ldc ", "
L164:   invokevirtual Method java/lang/StringBuffer append (Ljava/lang/String;)Ljava/lang/StringBuffer;
L167:   aload_1
L168:   invokevirtual Method java/lang/StringBuffer append ([C)Ljava/lang/StringBuffer;
L171:   ldc ", "
L173:   invokevirtual Method java/lang/StringBuffer append (Ljava/lang/String;)Ljava/lang/StringBuffer;
L176:   iload_2
L177:   invokevirtual Method java/lang/StringBuffer append (I)Ljava/lang/StringBuffer;
L180:   ldc ", "
L182:   invokevirtual Method java/lang/StringBuffer append (Ljava/lang/String;)Ljava/lang/StringBuffer;
L185:   iload_3
L186:   invokevirtual Method java/lang/StringBuffer append (I)Ljava/lang/StringBuffer;
L189:   ldc ", "
L191:   invokevirtual Method java/lang/StringBuffer append (Ljava/lang/String;)Ljava/lang/StringBuffer;
L194:   aload 4
L196:   invokevirtual Method java/lang/Throwable toString ()Ljava/lang/String;
L199:   invokevirtual Method java/lang/StringBuffer append (Ljava/lang/String;)Ljava/lang/StringBuffer;
L202:   invokevirtual Method java/lang/StringBuffer toString ()Ljava/lang/String;
L205:   invokestatic Method sign/signlink reporterror (Ljava/lang/String;)V
L208:   new java/lang/RuntimeException
L211:   dup
L212:   invokespecial Method java/lang/RuntimeException <init> ()V
L215:   athrow
L216:   
    .end code
.end method

.method private static final b : ([CI)V
    .code stack 7 locals 7
        .catch java/lang/RuntimeException from L0 to L143 using L144
L0:     aload_0
L1:     invokevirtual Method java/lang/Object clone ()Ljava/lang/Object;
L4:     checkcast [C
L7:     astore_2
L8:     iconst_3
L9:     newarray char
L11:    dup
L12:    iconst_0
L13:    bipush 100
L15:    castore
L16:    dup
L17:    iconst_1
L18:    bipush 111
L20:    castore
L21:    dup
L22:    iconst_2
L23:    bipush 116
L25:    castore
L26:    astore_3
L27:    bipush -102
L29:    aconst_null
L30:    aload_2
L31:    aload_3
L32:    invokestatic Method mc a (B[[B[C[C)V
L35:    aload_0
L36:    invokevirtual Method java/lang/Object clone ()Ljava/lang/Object;
L39:    checkcast [C
L42:    astore 4
L44:    iconst_5
L45:    newarray char
L47:    dup
L48:    iconst_0
L49:    bipush 115
L51:    castore
L52:    dup
L53:    iconst_1
L54:    bipush 108
L56:    castore
L57:    dup
L58:    iconst_2
L59:    bipush 97
L61:    castore
L62:    dup
L63:    iconst_3
L64:    bipush 115
L66:    castore
L67:    dup
L68:    iconst_4
L69:    bipush 104
L71:    castore
L72:    astore 5
L74:    iload_1
L75:    ifeq L92
L78:    getstatic Field mc a Z
L81:    ifeq L88
L84:    iconst_0
L85:    goto L89
L88:    iconst_1
L89:    putstatic Field mc a Z
L92:    bipush -102
L94:    aconst_null
L95:    aload 4
L97:    aload 5
L99:    invokestatic Method mc a (B[[B[C[C)V
L102:   iconst_0
L103:   istore 6
L105:   getstatic Field mc q I
L108:   ifeq L134
L111:   aload 4
L113:   getstatic Field mc o [I
L116:   iload 6
L118:   iaload
L119:   iconst_1
L120:   aload_0
L121:   getstatic Field mc n [[C
L124:   iload 6
L126:   aaload
L127:   aload_2
L128:   invokestatic Method mc a ([CIZ[C[C[C)V
L131:   iinc 6 1
L134:   iload 6
L136:   getstatic Field mc n [[C
L139:   arraylength
L140:   if_icmplt L111
L143:   return
L144:   astore_2
L145:   new java/lang/StringBuffer
L148:   dup
L149:   ldc "31380, "
L151:   invokespecial Method java/lang/StringBuffer <init> (Ljava/lang/String;)V
L154:   aload_0
L155:   invokevirtual Method java/lang/StringBuffer append ([C)Ljava/lang/StringBuffer;
L158:   ldc ", "
L160:   invokevirtual Method java/lang/StringBuffer append (Ljava/lang/String;)Ljava/lang/StringBuffer;
L163:   iload_1
L164:   invokevirtual Method java/lang/StringBuffer append (I)Ljava/lang/StringBuffer;
L167:   ldc ", "
L169:   invokevirtual Method java/lang/StringBuffer append (Ljava/lang/String;)Ljava/lang/StringBuffer;
L172:   aload_2
L173:   invokevirtual Method java/lang/Throwable toString ()Ljava/lang/String;
L176:   invokevirtual Method java/lang/StringBuffer append (Ljava/lang/String;)Ljava/lang/StringBuffer;
L179:   invokevirtual Method java/lang/StringBuffer toString ()Ljava/lang/String;
L182:   invokestatic Method sign/signlink reporterror (Ljava/lang/String;)V
L185:   new java/lang/RuntimeException
L188:   dup
L189:   invokespecial Method java/lang/RuntimeException <init> ()V
L192:   athrow
L193:   
    .end code
.end method

.method private static final a : ([CIZ[C[C[C)V
    .code stack 6 locals 18
L0:     getstatic Field mc q I
L3:     istore 17
        .catch java/lang/RuntimeException from L5 to L675 using L676
L5:     iload_2
L6:     ifne L25
L9:     iconst_1
L10:    istore 6
L12:    iload 17
L14:    ifeq L20
L17:    iinc 6 1
L20:    iload 6
L22:    ifgt L17
L25:    aload 4
L27:    arraylength
L28:    aload_3
L29:    arraylength
L30:    if_icmple L34
L33:    return
L34:    iconst_1
L35:    istore 6
L37:    iconst_0
L38:    istore 7
L40:    iload 17
L42:    ifeq L664
L45:    iload 7
L47:    istore 8
L49:    iconst_0
L50:    istore 9
L52:    iconst_1
L53:    istore 6
L55:    iload 17
L57:    ifeq L203
L60:    iconst_0
L61:    istore 10
L63:    aload_3
L64:    iload 8
L66:    caload
L67:    istore 11
L69:    iconst_0
L70:    istore 12
L72:    iload 8
L74:    iconst_1
L75:    iadd
L76:    aload_3
L77:    arraylength
L78:    if_icmpge L89
L81:    aload_3
L82:    iload 8
L84:    iconst_1
L85:    iadd
L86:    caload
L87:    istore 12
L89:    iload 9
L91:    aload 4
L93:    arraylength
L94:    if_icmpge L132
L97:    bipush -81
L99:    iload 12
L101:   aload 4
L103:   iload 9
L105:   caload
L106:   iload 11
L108:   invokestatic Method mc a (ICCC)I
L111:   dup
L112:   istore 10
L114:   ifle L132
L117:   iload 8
L119:   iload 10
L121:   iadd
L122:   istore 8
L124:   iinc 9 1
L127:   iload 17
L129:   ifeq L203
L132:   iload 9
L134:   ifeq L210
L137:   bipush -81
L139:   iload 12
L141:   aload 4
L143:   iload 9
L145:   iconst_1
L146:   isub
L147:   caload
L148:   iload 11
L150:   invokestatic Method mc a (ICCC)I
L153:   dup
L154:   istore 10
L156:   ifle L180
L159:   iload 8
L161:   iload 10
L163:   iadd
L164:   istore 8
L166:   iload 9
L168:   iconst_1
L169:   if_icmpne L203
L172:   iinc 6 1
L175:   iload 17
L177:   ifeq L203
L180:   iload 9
L182:   aload 4
L184:   arraylength
L185:   if_icmpge L210
L188:   iload 11
L190:   iconst_2
L191:   invokestatic Method mc a (CI)Z
L194:   ifeq L210
L197:   iinc 8 1
L200:   goto L203
L203:   iload 8
L205:   aload_3
L206:   arraylength
L207:   if_icmplt L60
L210:   iload 9
L212:   aload 4
L214:   arraylength
L215:   if_icmplt L657
L218:   iconst_0
L219:   istore 10
L221:   aload_3
L222:   iconst_0
L223:   aload 5
L225:   iload 7
L227:   invokestatic Method mc a ([CZ[CI)I
L230:   istore 11
L232:   aload_0
L233:   sipush -678
L236:   iload 8
L238:   iconst_1
L239:   isub
L240:   aload_3
L241:   invokestatic Method mc a ([CII[C)I
L244:   istore 12
L246:   iload_1
L247:   iconst_1
L248:   if_icmpne L264
L251:   iload 11
L253:   ifle L264
L256:   iload 12
L258:   ifle L264
L261:   iconst_1
L262:   istore 10
L264:   iload_1
L265:   iconst_2
L266:   if_icmpne L294
L269:   iload 11
L271:   iconst_2
L272:   if_icmple L280
L275:   iload 12
L277:   ifgt L291
L280:   iload 11
L282:   ifle L294
L285:   iload 12
L287:   iconst_2
L288:   if_icmple L294
L291:   iconst_1
L292:   istore 10
L294:   iload_1
L295:   iconst_3
L296:   if_icmpne L313
L299:   iload 11
L301:   ifle L313
L304:   iload 12
L306:   iconst_2
L307:   if_icmple L313
L310:   iconst_1
L311:   istore 10
L313:   iload_1
L314:   iconst_3
L315:   if_icmpne L329
L318:   iload 11
L320:   iconst_2
L321:   if_icmple L329
L324:   iload 12
L326:   ifgt L333
L329:   iconst_0
L330:   goto L334
L333:   iconst_1
L334:   pop
L335:   iload 10
L337:   ifeq L657
L340:   iload 7
L342:   istore 13
L344:   iload 8
L346:   iconst_1
L347:   isub
L348:   istore 14
L350:   iload 11
L352:   iconst_2
L353:   if_icmple L490
L356:   iload 11
L358:   iconst_4
L359:   if_icmpne L425
L362:   iconst_0
L363:   istore 15
L365:   iload 13
L367:   iconst_1
L368:   isub
L369:   istore 16
L371:   iload 17
L373:   ifeq L420
L376:   iload 15
L378:   ifeq L400
L381:   aload 5
L383:   iload 16
L385:   caload
L386:   bipush 42
L388:   if_icmpne L425
L391:   iload 16
L393:   istore 13
L395:   iload 17
L397:   ifeq L417
L400:   aload 5
L402:   iload 16
L404:   caload
L405:   bipush 42
L407:   if_icmpne L417
L410:   iload 16
L412:   istore 13
L414:   iconst_1
L415:   istore 15
L417:   iinc 16 -1
L420:   iload 16
L422:   ifge L376
L425:   iconst_0
L426:   istore 15
L428:   iload 13
L430:   iconst_1
L431:   isub
L432:   istore 16
L434:   iload 17
L436:   ifeq L485
L439:   iload 15
L441:   ifeq L464
L444:   aload_3
L445:   iload 16
L447:   caload
L448:   iconst_2
L449:   invokestatic Method mc a (CI)Z
L452:   ifne L490
L455:   iload 16
L457:   istore 13
L459:   iload 17
L461:   ifeq L482
L464:   aload_3
L465:   iload 16
L467:   caload
L468:   iconst_2
L469:   invokestatic Method mc a (CI)Z
L472:   ifne L482
L475:   iconst_1
L476:   istore 15
L478:   iload 16
L480:   istore 13
L482:   iinc 16 -1
L485:   iload 16
L487:   ifge L439
L490:   iload 12
L492:   iconst_2
L493:   if_icmple L632
L496:   iload 12
L498:   iconst_4
L499:   if_icmpne L565
L502:   iconst_0
L503:   istore 15
L505:   iload 14
L507:   iconst_1
L508:   iadd
L509:   istore 16
L511:   iload 17
L513:   ifeq L558
L516:   iload 15
L518:   ifeq L539
L521:   aload_0
L522:   iload 16
L524:   caload
L525:   bipush 42
L527:   if_icmpne L565
L530:   iload 16
L532:   istore 14
L534:   iload 17
L536:   ifeq L555
L539:   aload_0
L540:   iload 16
L542:   caload
L543:   bipush 42
L545:   if_icmpne L555
L548:   iload 16
L550:   istore 14
L552:   iconst_1
L553:   istore 15
L555:   iinc 16 1
L558:   iload 16
L560:   aload_3
L561:   arraylength
L562:   if_icmplt L516
L565:   iconst_0
L566:   istore 15
L568:   iload 14
L570:   iconst_1
L571:   iadd
L572:   istore 16
L574:   iload 17
L576:   ifeq L625
L579:   iload 15
L581:   ifeq L604
L584:   aload_3
L585:   iload 16
L587:   caload
L588:   iconst_2
L589:   invokestatic Method mc a (CI)Z
L592:   ifne L632
L595:   iload 16
L597:   istore 14
L599:   iload 17
L601:   ifeq L622
L604:   aload_3
L605:   iload 16
L607:   caload
L608:   iconst_2
L609:   invokestatic Method mc a (CI)Z
L612:   ifne L622
L615:   iconst_1
L616:   istore 15
L618:   iload 16
L620:   istore 14
L622:   iinc 16 1
L625:   iload 16
L627:   aload_3
L628:   arraylength
L629:   if_icmplt L579
L632:   iload 13
L634:   istore 15
L636:   iload 17
L638:   ifeq L650
L641:   aload_3
L642:   iload 15
L644:   bipush 42
L646:   castore
L647:   iinc 15 1
L650:   iload 15
L652:   iload 14
L654:   if_icmple L641
L657:   iload 7
L659:   iload 6
L661:   iadd
L662:   istore 7
L664:   iload 7
L666:   aload_3
L667:   arraylength
L668:   aload 4
L670:   arraylength
L671:   isub
L672:   if_icmple L45
L675:   return
L676:   astore 6
L678:   new java/lang/StringBuffer
L681:   dup
L682:   ldc "17147, "
L684:   invokespecial Method java/lang/StringBuffer <init> (Ljava/lang/String;)V
L687:   aload_0
L688:   invokevirtual Method java/lang/StringBuffer append ([C)Ljava/lang/StringBuffer;
L691:   ldc ", "
L693:   invokevirtual Method java/lang/StringBuffer append (Ljava/lang/String;)Ljava/lang/StringBuffer;
L696:   iload_1
L697:   invokevirtual Method java/lang/StringBuffer append (I)Ljava/lang/StringBuffer;
L700:   ldc ", "
L702:   invokevirtual Method java/lang/StringBuffer append (Ljava/lang/String;)Ljava/lang/StringBuffer;
L705:   iload_2
L706:   invokevirtual Method java/lang/StringBuffer append (Z)Ljava/lang/StringBuffer;
L709:   ldc ", "
L711:   invokevirtual Method java/lang/StringBuffer append (Ljava/lang/String;)Ljava/lang/StringBuffer;
L714:   aload_3
L715:   invokevirtual Method java/lang/StringBuffer append ([C)Ljava/lang/StringBuffer;
L718:   ldc ", "
L720:   invokevirtual Method java/lang/StringBuffer append (Ljava/lang/String;)Ljava/lang/StringBuffer;
L723:   aload 4
L725:   invokevirtual Method java/lang/StringBuffer append ([C)Ljava/lang/StringBuffer;
L728:   ldc ", "
L730:   invokevirtual Method java/lang/StringBuffer append (Ljava/lang/String;)Ljava/lang/StringBuffer;
L733:   aload 5
L735:   invokevirtual Method java/lang/StringBuffer append ([C)Ljava/lang/StringBuffer;
L738:   ldc ", "
L740:   invokevirtual Method java/lang/StringBuffer append (Ljava/lang/String;)Ljava/lang/StringBuffer;
L743:   aload 6
L745:   invokevirtual Method java/lang/Throwable toString ()Ljava/lang/String;
L748:   invokevirtual Method java/lang/StringBuffer append (Ljava/lang/String;)Ljava/lang/StringBuffer;
L751:   invokevirtual Method java/lang/StringBuffer toString ()Ljava/lang/String;
L754:   invokestatic Method sign/signlink reporterror (Ljava/lang/String;)V
L757:   new java/lang/RuntimeException
L760:   dup
L761:   invokespecial Method java/lang/RuntimeException <init> ()V
L764:   athrow
L765:   
    .end code
.end method

.method private static final a : ([CZ[CI)I
    .code stack 4 locals 8
L0:     getstatic Field mc q I
L3:     istore 7
        .catch java/lang/RuntimeException from L5 to L151 using L151
L5:     iload_3
L6:     ifne L11
L9:     iconst_2
L10:    ireturn
L11:    iload_3
L12:    iconst_1
L13:    isub
L14:    istore 4
L16:    iload 7
L18:    ifeq L55
L21:    aload_0
L22:    iload 4
L24:    caload
L25:    iconst_2
L26:    invokestatic Method mc a (CI)Z
L29:    ifeq L60
L32:    aload_0
L33:    iload 4
L35:    caload
L36:    bipush 44
L38:    if_icmpeq L50
L41:    aload_0
L42:    iload 4
L44:    caload
L45:    bipush 46
L47:    if_icmpne L52
L50:    iconst_3
L51:    ireturn
L52:    iinc 4 -1
L55:    iload 4
L57:    ifge L21
L60:    iconst_0
L61:    istore 5
L63:    iload_1
L64:    ifeq L83
L67:    iconst_1
L68:    istore 6
L70:    iload 7
L72:    ifeq L78
L75:    iinc 6 1
L78:    iload 6
L80:    ifgt L75
L83:    iload_3
L84:    iconst_1
L85:    isub
L86:    istore 6
L88:    iload 7
L90:    ifeq L122
L93:    aload_2
L94:    iload 6
L96:    caload
L97:    iconst_2
L98:    invokestatic Method mc a (CI)Z
L101:   ifeq L127
L104:   aload_2
L105:   iload 6
L107:   caload
L108:   bipush 42
L110:   if_icmpne L119
L113:   iinc 5 1
L116:   goto L119
L119:   iinc 6 -1
L122:   iload 6
L124:   ifge L93
L127:   iload 5
L129:   iconst_3
L130:   if_icmplt L135
L133:   iconst_4
L134:   ireturn
L135:   aload_0
L136:   iload_3
L137:   iconst_1
L138:   isub
L139:   caload
L140:   iconst_2
L141:   invokestatic Method mc a (CI)Z
L144:   ifeq L149
L147:   iconst_1
L148:   ireturn
L149:   iconst_0
L150:   ireturn
L151:   astore 4
L153:   new java/lang/StringBuffer
L156:   dup
L157:   ldc "73918, "
L159:   invokespecial Method java/lang/StringBuffer <init> (Ljava/lang/String;)V
L162:   aload_0
L163:   invokevirtual Method java/lang/StringBuffer append ([C)Ljava/lang/StringBuffer;
L166:   ldc ", "
L168:   invokevirtual Method java/lang/StringBuffer append (Ljava/lang/String;)Ljava/lang/StringBuffer;
L171:   iload_1
L172:   invokevirtual Method java/lang/StringBuffer append (Z)Ljava/lang/StringBuffer;
L175:   ldc ", "
L177:   invokevirtual Method java/lang/StringBuffer append (Ljava/lang/String;)Ljava/lang/StringBuffer;
L180:   aload_2
L181:   invokevirtual Method java/lang/StringBuffer append ([C)Ljava/lang/StringBuffer;
L184:   ldc ", "
L186:   invokevirtual Method java/lang/StringBuffer append (Ljava/lang/String;)Ljava/lang/StringBuffer;
L189:   iload_3
L190:   invokevirtual Method java/lang/StringBuffer append (I)Ljava/lang/StringBuffer;
L193:   ldc ", "
L195:   invokevirtual Method java/lang/StringBuffer append (Ljava/lang/String;)Ljava/lang/StringBuffer;
L198:   aload 4
L200:   invokevirtual Method java/lang/Throwable toString ()Ljava/lang/String;
L203:   invokevirtual Method java/lang/StringBuffer append (Ljava/lang/String;)Ljava/lang/StringBuffer;
L206:   invokevirtual Method java/lang/StringBuffer toString ()Ljava/lang/String;
L209:   invokestatic Method sign/signlink reporterror (Ljava/lang/String;)V
L212:   new java/lang/RuntimeException
L215:   dup
L216:   invokespecial Method java/lang/RuntimeException <init> ()V
L219:   athrow
L220:   
    .end code
.end method

.method private static final a : ([CII[C)I
    .code stack 4 locals 8
L0:     getstatic Field mc q I
L3:     istore 7
        .catch java/lang/RuntimeException from L5 to L145 using L145
L5:     iload_2
L6:     iconst_1
L7:     iadd
L8:     aload_3
L9:     arraylength
L10:    if_icmpne L15
L13:    iconst_2
L14:    ireturn
L15:    iload_2
L16:    iconst_1
L17:    iadd
L18:    istore 4
L20:    iload 7
L22:    ifeq L59
L25:    aload_3
L26:    iload 4
L28:    caload
L29:    iconst_2
L30:    invokestatic Method mc a (CI)Z
L33:    ifeq L66
L36:    aload_3
L37:    iload 4
L39:    caload
L40:    bipush 92
L42:    if_icmpeq L54
L45:    aload_3
L46:    iload 4
L48:    caload
L49:    bipush 47
L51:    if_icmpne L56
L54:    iconst_3
L55:    ireturn
L56:    iinc 4 1
L59:    iload 4
L61:    aload_3
L62:    arraylength
L63:    if_icmplt L25
L66:    iconst_0
L67:    istore 5
L69:    iload_2
L70:    iconst_1
L71:    iadd
L72:    istore 6
L74:    iload 7
L76:    ifeq L108
L79:    aload_0
L80:    iload 6
L82:    caload
L83:    iconst_2
L84:    invokestatic Method mc a (CI)Z
L87:    ifeq L115
L90:    aload_0
L91:    iload 6
L93:    caload
L94:    bipush 42
L96:    if_icmpne L105
L99:    iinc 5 1
L102:   goto L105
L105:   iinc 6 1
L108:   iload 6
L110:   aload_3
L111:   arraylength
L112:   if_icmplt L79
L115:   iload_1
L116:   iflt L121
L119:   iconst_3
L120:   ireturn
L121:   iload 5
L123:   iconst_5
L124:   if_icmplt L129
L127:   iconst_4
L128:   ireturn
L129:   aload_3
L130:   iload_2
L131:   iconst_1
L132:   iadd
L133:   caload
L134:   iconst_2
L135:   invokestatic Method mc a (CI)Z
L138:   ifeq L143
L141:   iconst_1
L142:   ireturn
L143:   iconst_0
L144:   ireturn
L145:   astore 4
L147:   new java/lang/StringBuffer
L150:   dup
L151:   ldc "17610, "
L153:   invokespecial Method java/lang/StringBuffer <init> (Ljava/lang/String;)V
L156:   aload_0
L157:   invokevirtual Method java/lang/StringBuffer append ([C)Ljava/lang/StringBuffer;
L160:   ldc ", "
L162:   invokevirtual Method java/lang/StringBuffer append (Ljava/lang/String;)Ljava/lang/StringBuffer;
L165:   iload_1
L166:   invokevirtual Method java/lang/StringBuffer append (I)Ljava/lang/StringBuffer;
L169:   ldc ", "
L171:   invokevirtual Method java/lang/StringBuffer append (Ljava/lang/String;)Ljava/lang/StringBuffer;
L174:   iload_2
L175:   invokevirtual Method java/lang/StringBuffer append (I)Ljava/lang/StringBuffer;
L178:   ldc ", "
L180:   invokevirtual Method java/lang/StringBuffer append (Ljava/lang/String;)Ljava/lang/StringBuffer;
L183:   aload_3
L184:   invokevirtual Method java/lang/StringBuffer append ([C)Ljava/lang/StringBuffer;
L187:   ldc ", "
L189:   invokevirtual Method java/lang/StringBuffer append (Ljava/lang/String;)Ljava/lang/StringBuffer;
L192:   aload 4
L194:   invokevirtual Method java/lang/Throwable toString ()Ljava/lang/String;
L197:   invokevirtual Method java/lang/StringBuffer append (Ljava/lang/String;)Ljava/lang/StringBuffer;
L200:   invokevirtual Method java/lang/StringBuffer toString ()Ljava/lang/String;
L203:   invokestatic Method sign/signlink reporterror (Ljava/lang/String;)V
L206:   new java/lang/RuntimeException
L209:   dup
L210:   invokespecial Method java/lang/RuntimeException <init> ()V
L213:   athrow
L214:   
    .end code
.end method

.method public static final a : (B[[B[C[C)V
    .code stack 6 locals 21
L0:     getstatic Field mc q I
L3:     istore 20
        .catch java/lang/RuntimeException from L5 to L839 using L840
L5:     aload_3
L6:     arraylength
L7:     aload_2
L8:     arraylength
L9:     if_icmple L13
L12:    return
L13:    iconst_1
L14:    istore 4
L16:    iload_0
L17:    bipush -102
L19:    if_icmpeq L28
L22:    sipush -198
L25:    putstatic Field mc f I
L28:    iconst_0
L29:    istore 5
L31:    iload 20
L33:    ifeq L829
L36:    iload 5
L38:    istore 6
L40:    iconst_0
L41:    istore 7
L43:    iconst_0
L44:    istore 8
L46:    iconst_1
L47:    istore 4
L49:    iconst_0
L50:    istore 9
L52:    iconst_0
L53:    istore 10
L55:    iconst_0
L56:    istore 11
L58:    iload 20
L60:    ifeq L310
L63:    iconst_0
L64:    istore 12
L66:    aload_2
L67:    iload 6
L69:    caload
L70:    istore 13
L72:    iconst_0
L73:    istore 14
L75:    iload 6
L77:    iconst_1
L78:    iadd
L79:    aload_2
L80:    arraylength
L81:    if_icmpge L92
L84:    aload_2
L85:    iload 6
L87:    iconst_1
L88:    iadd
L89:    caload
L90:    istore 14
L92:    iload 7
L94:    aload_3
L95:    arraylength
L96:    if_icmpge L185
L99:    iload 14
L101:   aload_3
L102:   iload 7
L104:   caload
L105:   iload 13
L107:   sipush 7326
L110:   invokestatic Method mc a (CCCI)I
L113:   dup
L114:   istore 12
L116:   ifle L185
L119:   iload 12
L121:   iconst_1
L122:   if_icmpne L139
L125:   iload 13
L127:   sipush 10361
L130:   invokestatic Method mc b (CI)Z
L133:   ifeq L139
L136:   iconst_1
L137:   istore 10
L139:   iload 12
L141:   iconst_2
L142:   if_icmpne L170
L145:   iload 13
L147:   sipush 10361
L150:   invokestatic Method mc b (CI)Z
L153:   ifne L167
L156:   iload 14
L158:   sipush 10361
L161:   invokestatic Method mc b (CI)Z
L164:   ifeq L170
L167:   iconst_1
L168:   istore 10
L170:   iload 6
L172:   iload 12
L174:   iadd
L175:   istore 6
L177:   iinc 7 1
L180:   iload 20
L182:   ifeq L310
L185:   iload 7
L187:   ifeq L327
L190:   iload 14
L192:   aload_3
L193:   iload 7
L195:   iconst_1
L196:   isub
L197:   caload
L198:   iload 13
L200:   sipush 7326
L203:   invokestatic Method mc a (CCCI)I
L206:   dup
L207:   istore 12
L209:   ifle L233
L212:   iload 6
L214:   iload 12
L216:   iadd
L217:   istore 6
L219:   iload 7
L221:   iconst_1
L222:   if_icmpne L310
L225:   iinc 4 1
L228:   iload 20
L230:   ifeq L310
L233:   iload 7
L235:   aload_3
L236:   arraylength
L237:   if_icmpge L327
L240:   iload 13
L242:   bipush 13
L244:   invokestatic Method mc a (CB)Z
L247:   ifeq L327
L250:   iload 13
L252:   iconst_2
L253:   invokestatic Method mc a (CI)Z
L256:   ifeq L269
L259:   iload 13
L261:   bipush 39
L263:   if_icmpeq L269
L266:   iconst_1
L267:   istore 9
L269:   iload 13
L271:   sipush 10361
L274:   invokestatic Method mc b (CI)Z
L277:   ifeq L283
L280:   iconst_1
L281:   istore 11
L283:   iinc 6 1
L286:   iinc 8 1
L289:   iload 8
L291:   bipush 100
L293:   imul
L294:   iload 6
L296:   iload 5
L298:   isub
L299:   idiv
L300:   bipush 90
L302:   if_icmple L310
L305:   iload 20
L307:   ifeq L327
L310:   iload 6
L312:   aload_2
L313:   arraylength
L314:   if_icmpge L327
L317:   iload 10
L319:   ifeq L63
L322:   iload 11
L324:   ifeq L63
L327:   iload 7
L329:   aload_3
L330:   arraylength
L331:   if_icmplt L822
L334:   iload 10
L336:   ifeq L344
L339:   iload 11
L341:   ifne L822
L344:   iconst_1
L345:   istore 12
L347:   iload 9
L349:   ifne L430
L352:   bipush 32
L354:   istore 13
L356:   iload 5
L358:   iconst_1
L359:   isub
L360:   iflt L371
L363:   aload_2
L364:   iload 5
L366:   iconst_1
L367:   isub
L368:   caload
L369:   istore 13
L371:   bipush 32
L373:   istore 14
L375:   iload 6
L377:   aload_2
L378:   arraylength
L379:   if_icmpge L388
L382:   aload_2
L383:   iload 6
L385:   caload
L386:   istore 14
L388:   iconst_0
L389:   iload 13
L391:   invokestatic Method mc b (IC)B
L394:   istore 15
L396:   iconst_0
L397:   iload 14
L399:   invokestatic Method mc b (IC)B
L402:   istore 16
L404:   aload_1
L405:   ifnull L723
L408:   sipush 841
L411:   iload 15
L413:   aload_1
L414:   iload 16
L416:   invokestatic Method mc a (IB[[BB)Z
L419:   ifeq L723
L422:   iconst_0
L423:   istore 12
L425:   iload 20
L427:   ifeq L723
L430:   iconst_0
L431:   istore 13
L433:   iconst_0
L434:   istore 14
L436:   iload 5
L438:   iconst_1
L439:   isub
L440:   iflt L467
L443:   aload_2
L444:   iload 5
L446:   iconst_1
L447:   isub
L448:   caload
L449:   iconst_2
L450:   invokestatic Method mc a (CI)Z
L453:   ifeq L470
L456:   aload_2
L457:   iload 5
L459:   iconst_1
L460:   isub
L461:   caload
L462:   bipush 39
L464:   if_icmpeq L470
L467:   iconst_1
L468:   istore 13
L470:   iload 6
L472:   aload_2
L473:   arraylength
L474:   if_icmpge L497
L477:   aload_2
L478:   iload 6
L480:   caload
L481:   iconst_2
L482:   invokestatic Method mc a (CI)Z
L485:   ifeq L500
L488:   aload_2
L489:   iload 6
L491:   caload
L492:   bipush 39
L494:   if_icmpeq L500
L497:   iconst_1
L498:   istore 14
L500:   iload 13
L502:   ifeq L510
L505:   iload 14
L507:   ifne L723
L510:   iconst_0
L511:   istore 15
L513:   iload 5
L515:   iconst_2
L516:   isub
L517:   istore 16
L519:   iload 13
L521:   ifeq L703
L524:   iload 5
L526:   istore 16
L528:   iload 20
L530:   ifeq L703
L533:   iload 16
L535:   iflt L700
L538:   aload_2
L539:   iload 16
L541:   caload
L542:   iconst_2
L543:   invokestatic Method mc a (CI)Z
L546:   ifeq L558
L549:   aload_2
L550:   iload 16
L552:   caload
L553:   bipush 39
L555:   if_icmpne L700
L558:   iconst_3
L559:   newarray char
L561:   astore 17
L563:   iconst_0
L564:   istore 18
L566:   iload 20
L568:   ifeq L625
L571:   iload 16
L573:   iload 18
L575:   iadd
L576:   aload_2
L577:   arraylength
L578:   if_icmpge L631
L581:   aload_2
L582:   iload 16
L584:   iload 18
L586:   iadd
L587:   caload
L588:   iconst_2
L589:   invokestatic Method mc a (CI)Z
L592:   ifeq L607
L595:   aload_2
L596:   iload 16
L598:   iload 18
L600:   iadd
L601:   caload
L602:   bipush 39
L604:   if_icmpne L631
L607:   aload 17
L609:   iload 18
L611:   aload_2
L612:   iload 16
L614:   iload 18
L616:   iadd
L617:   caload
L618:   castore
L619:   goto L622
L622:   iinc 18 1
L625:   iload 18
L627:   iconst_3
L628:   if_icmplt L571
L631:   iconst_1
L632:   istore 19
L634:   iload 18
L636:   ifne L642
L639:   iconst_0
L640:   istore 19
L642:   iload 18
L644:   iconst_3
L645:   if_icmpge L682
L648:   iload 16
L650:   iconst_1
L651:   isub
L652:   iflt L682
L655:   aload_2
L656:   iload 16
L658:   iconst_1
L659:   isub
L660:   caload
L661:   iconst_2
L662:   invokestatic Method mc a (CI)Z
L665:   ifeq L679
L668:   aload_2
L669:   iload 16
L671:   iconst_1
L672:   isub
L673:   caload
L674:   bipush 39
L676:   if_icmpne L682
L679:   iconst_0
L680:   istore 19
L682:   iload 19
L684:   ifeq L700
L687:   aload 17
L689:   bipush 6
L691:   invokestatic Method mc c ([CI)Z
L694:   ifne L700
L697:   iconst_1
L698:   istore 15
L700:   iinc 16 1
L703:   iload 15
L705:   ifne L715
L708:   iload 16
L710:   iload 6
L712:   if_icmplt L533
L715:   iload 15
L717:   ifne L723
L720:   iconst_0
L721:   istore 12
L723:   iload 12
L725:   ifeq L822
L728:   iconst_0
L729:   istore 13
L731:   iconst_0
L732:   istore 14
L734:   iload 5
L736:   istore 15
L738:   iload 20
L740:   ifeq L783
L743:   aload_2
L744:   iload 15
L746:   caload
L747:   sipush 10361
L750:   invokestatic Method mc b (CI)Z
L753:   ifeq L764
L756:   iinc 13 1
L759:   iload 20
L761:   ifeq L780
L764:   sipush -175
L767:   aload_2
L768:   iload 15
L770:   caload
L771:   invokestatic Method mc c (IC)Z
L774:   ifeq L780
L777:   iinc 14 1
L780:   iinc 15 1
L783:   iload 15
L785:   iload 6
L787:   if_icmplt L743
L790:   iload 13
L792:   iload 14
L794:   if_icmpgt L822
L797:   iload 5
L799:   istore 16
L801:   iload 20
L803:   ifeq L815
L806:   aload_2
L807:   iload 16
L809:   bipush 42
L811:   castore
L812:   iinc 16 1
L815:   iload 16
L817:   iload 6
L819:   if_icmplt L806
L822:   iload 5
L824:   iload 4
L826:   iadd
L827:   istore 5
L829:   iload 5
L831:   aload_2
L832:   arraylength
L833:   aload_3
L834:   arraylength
L835:   isub
L836:   if_icmple L36
L839:   return
L840:   astore 4
L842:   new java/lang/StringBuffer
L845:   dup
L846:   ldc "10220, "
L848:   invokespecial Method java/lang/StringBuffer <init> (Ljava/lang/String;)V
L851:   iload_0
L852:   invokevirtual Method java/lang/StringBuffer append (I)Ljava/lang/StringBuffer;
L855:   ldc ", "
L857:   invokevirtual Method java/lang/StringBuffer append (Ljava/lang/String;)Ljava/lang/StringBuffer;
L860:   aload_1
L861:   invokevirtual Method java/lang/StringBuffer append (Ljava/lang/Object;)Ljava/lang/StringBuffer;
L864:   ldc ", "
L866:   invokevirtual Method java/lang/StringBuffer append (Ljava/lang/String;)Ljava/lang/StringBuffer;
L869:   aload_2
L870:   invokevirtual Method java/lang/StringBuffer append ([C)Ljava/lang/StringBuffer;
L873:   ldc ", "
L875:   invokevirtual Method java/lang/StringBuffer append (Ljava/lang/String;)Ljava/lang/StringBuffer;
L878:   aload_3
L879:   invokevirtual Method java/lang/StringBuffer append ([C)Ljava/lang/StringBuffer;
L882:   ldc ", "
L884:   invokevirtual Method java/lang/StringBuffer append (Ljava/lang/String;)Ljava/lang/StringBuffer;
L887:   aload 4
L889:   invokevirtual Method java/lang/Throwable toString ()Ljava/lang/String;
L892:   invokevirtual Method java/lang/StringBuffer append (Ljava/lang/String;)Ljava/lang/StringBuffer;
L895:   invokevirtual Method java/lang/StringBuffer toString ()Ljava/lang/String;
L898:   invokestatic Method sign/signlink reporterror (Ljava/lang/String;)V
L901:   new java/lang/RuntimeException
L904:   dup
L905:   invokespecial Method java/lang/RuntimeException <init> ()V
L908:   athrow
L909:   
    .end code
.end method

.method private static final a : (IB[[BB)Z
    .code stack 4 locals 7
        .catch java/lang/RuntimeException from L0 to L164 using L164
L0:     iload_0
L1:     ifgt L18
L4:     getstatic Field mc i Z
L7:     ifeq L14
L10:    iconst_0
L11:    goto L15
L14:    iconst_1
L15:    putstatic Field mc i Z
L18:    iconst_0
L19:    istore 4
L21:    aload_2
L22:    iload 4
L24:    aaload
L25:    iconst_0
L26:    baload
L27:    iload_1
L28:    if_icmpne L43
L31:    aload_2
L32:    iload 4
L34:    aaload
L35:    iconst_1
L36:    baload
L37:    iload_3
L38:    if_icmpne L43
L41:    iconst_1
L42:    ireturn
L43:    aload_2
L44:    arraylength
L45:    iconst_1
L46:    isub
L47:    istore 5
L49:    aload_2
L50:    iload 5
L52:    aaload
L53:    iconst_0
L54:    baload
L55:    iload_1
L56:    if_icmpne L71
L59:    aload_2
L60:    iload 5
L62:    aaload
L63:    iconst_1
L64:    baload
L65:    iload_3
L66:    if_icmpne L71
L69:    iconst_1
L70:    ireturn
L71:    iload 4
L73:    iload 5
L75:    iadd
L76:    iconst_2
L77:    idiv
L78:    istore 6
L80:    aload_2
L81:    iload 6
L83:    aaload
L84:    iconst_0
L85:    baload
L86:    iload_1
L87:    if_icmpne L102
L90:    aload_2
L91:    iload 6
L93:    aaload
L94:    iconst_1
L95:    baload
L96:    iload_3
L97:    if_icmpne L102
L100:   iconst_1
L101:   ireturn
L102:   iload_1
L103:   aload_2
L104:   iload 6
L106:   aaload
L107:   iconst_0
L108:   baload
L109:   if_icmplt L132
L112:   iload_1
L113:   aload_2
L114:   iload 6
L116:   aaload
L117:   iconst_0
L118:   baload
L119:   if_icmpne L142
L122:   iload_3
L123:   aload_2
L124:   iload 6
L126:   aaload
L127:   iconst_1
L128:   baload
L129:   if_icmpge L142
L132:   iload 6
L134:   istore 5
L136:   getstatic Field mc q I
L139:   ifeq L146
L142:   iload 6
L144:   istore 4
L146:   iload 4
L148:   iload 5
L150:   if_icmpeq L162
L153:   iload 4
L155:   iconst_1
L156:   iadd
L157:   iload 5
L159:   if_icmpne L71
L162:   iconst_0
L163:   ireturn
L164:   astore 4
L166:   new java/lang/StringBuffer
L169:   dup
L170:   ldc "65186, "
L172:   invokespecial Method java/lang/StringBuffer <init> (Ljava/lang/String;)V
L175:   iload_0
L176:   invokevirtual Method java/lang/StringBuffer append (I)Ljava/lang/StringBuffer;
L179:   ldc ", "
L181:   invokevirtual Method java/lang/StringBuffer append (Ljava/lang/String;)Ljava/lang/StringBuffer;
L184:   iload_1
L185:   invokevirtual Method java/lang/StringBuffer append (I)Ljava/lang/StringBuffer;
L188:   ldc ", "
L190:   invokevirtual Method java/lang/StringBuffer append (Ljava/lang/String;)Ljava/lang/StringBuffer;
L193:   aload_2
L194:   invokevirtual Method java/lang/StringBuffer append (Ljava/lang/Object;)Ljava/lang/StringBuffer;
L197:   ldc ", "
L199:   invokevirtual Method java/lang/StringBuffer append (Ljava/lang/String;)Ljava/lang/StringBuffer;
L202:   iload_3
L203:   invokevirtual Method java/lang/StringBuffer append (I)Ljava/lang/StringBuffer;
L206:   ldc ", "
L208:   invokevirtual Method java/lang/StringBuffer append (Ljava/lang/String;)Ljava/lang/StringBuffer;
L211:   aload 4
L213:   invokevirtual Method java/lang/Throwable toString ()Ljava/lang/String;
L216:   invokevirtual Method java/lang/StringBuffer append (Ljava/lang/String;)Ljava/lang/StringBuffer;
L219:   invokevirtual Method java/lang/StringBuffer toString ()Ljava/lang/String;
L222:   invokestatic Method sign/signlink reporterror (Ljava/lang/String;)V
L225:   new java/lang/RuntimeException
L228:   dup
L229:   invokespecial Method java/lang/RuntimeException <init> ()V
L232:   athrow
L233:   
    .end code
.end method

.method private static final a : (ICCC)I
    .code stack 4 locals 6
L0:     getstatic Field mc q I
L3:     istore 5
        .catch java/lang/RuntimeException from L5 to L142 using L142
L5:     iload 5
L7:     ifeq L26
L10:    iconst_1
L11:    istore 4
L13:    iload 5
L15:    ifeq L21
L18:    iinc 4 1
L21:    iload 4
L23:    ifgt L18
L26:    iload_0
L27:    ifge L10
L30:    iload_2
L31:    iload_3
L32:    if_icmpne L37
L35:    iconst_1
L36:    ireturn
L37:    iload_2
L38:    bipush 111
L40:    if_icmpne L51
L43:    iload_3
L44:    bipush 48
L46:    if_icmpne L51
L49:    iconst_1
L50:    ireturn
L51:    iload_2
L52:    bipush 111
L54:    if_icmpne L71
L57:    iload_3
L58:    bipush 40
L60:    if_icmpne L71
L63:    iload_1
L64:    bipush 41
L66:    if_icmpne L71
L69:    iconst_2
L70:    ireturn
L71:    iload_2
L72:    bipush 99
L74:    if_icmpne L97
L77:    iload_3
L78:    bipush 40
L80:    if_icmpeq L95
L83:    iload_3
L84:    bipush 60
L86:    if_icmpeq L95
L89:    iload_3
L90:    bipush 91
L92:    if_icmpne L97
L95:    iconst_1
L96:    ireturn
L97:    iload_2
L98:    bipush 101
L100:   if_icmpne L112
L103:   iload_3
L104:   sipush 8364
L107:   if_icmpne L112
L110:   iconst_1
L111:   ireturn
L112:   iload_2
L113:   bipush 115
L115:   if_icmpne L126
L118:   iload_3
L119:   bipush 36
L121:   if_icmpne L126
L124:   iconst_1
L125:   ireturn
L126:   iload_2
L127:   bipush 108
L129:   if_icmpne L140
L132:   iload_3
L133:   bipush 105
L135:   if_icmpne L140
L138:   iconst_1
L139:   ireturn
L140:   iconst_0
L141:   ireturn
L142:   astore 4
L144:   new java/lang/StringBuffer
L147:   dup
L148:   ldc "22330, "
L150:   invokespecial Method java/lang/StringBuffer <init> (Ljava/lang/String;)V
L153:   iload_0
L154:   invokevirtual Method java/lang/StringBuffer append (I)Ljava/lang/StringBuffer;
L157:   ldc ", "
L159:   invokevirtual Method java/lang/StringBuffer append (Ljava/lang/String;)Ljava/lang/StringBuffer;
L162:   iload_1
L163:   invokevirtual Method java/lang/StringBuffer append (C)Ljava/lang/StringBuffer;
L166:   ldc ", "
L168:   invokevirtual Method java/lang/StringBuffer append (Ljava/lang/String;)Ljava/lang/StringBuffer;
L171:   iload_2
L172:   invokevirtual Method java/lang/StringBuffer append (C)Ljava/lang/StringBuffer;
L175:   ldc ", "
L177:   invokevirtual Method java/lang/StringBuffer append (Ljava/lang/String;)Ljava/lang/StringBuffer;
L180:   iload_3
L181:   invokevirtual Method java/lang/StringBuffer append (C)Ljava/lang/StringBuffer;
L184:   ldc ", "
L186:   invokevirtual Method java/lang/StringBuffer append (Ljava/lang/String;)Ljava/lang/StringBuffer;
L189:   aload 4
L191:   invokevirtual Method java/lang/Throwable toString ()Ljava/lang/String;
L194:   invokevirtual Method java/lang/StringBuffer append (Ljava/lang/String;)Ljava/lang/StringBuffer;
L197:   invokevirtual Method java/lang/StringBuffer toString ()Ljava/lang/String;
L200:   invokestatic Method sign/signlink reporterror (Ljava/lang/String;)V
L203:   new java/lang/RuntimeException
L206:   dup
L207:   invokespecial Method java/lang/RuntimeException <init> ()V
L210:   athrow
L211:   
    .end code
.end method

.method private static final a : (CCCI)I
    .code stack 4 locals 5
        .catch java/lang/RuntimeException from L0 to L887 using L887
L0:     iload_3
L1:     sipush 7326
L4:     if_icmpeq L24
L7:     iconst_1
L8:     istore 4
L10:    getstatic Field mc q I
L13:    ifeq L19
L16:    iinc 4 1
L19:    iload 4
L21:    ifgt L16
L24:    iload_1
L25:    iload_2
L26:    if_icmpne L31
L29:    iconst_1
L30:    ireturn
L31:    iload_1
L32:    bipush 97
L34:    if_icmplt L379
L37:    iload_1
L38:    bipush 109
L40:    if_icmpgt L379
L43:    iload_1
L44:    bipush 97
L46:    if_icmpne L85
L49:    iload_2
L50:    bipush 52
L52:    if_icmpeq L67
L55:    iload_2
L56:    bipush 64
L58:    if_icmpeq L67
L61:    iload_2
L62:    bipush 94
L64:    if_icmpne L69
L67:    iconst_1
L68:    ireturn
L69:    iload_2
L70:    bipush 47
L72:    if_icmpne L83
L75:    iload_0
L76:    bipush 92
L78:    if_icmpne L83
L81:    iconst_2
L82:    ireturn
L83:    iconst_0
L84:    ireturn
L85:    iload_1
L86:    bipush 98
L88:    if_icmpne L121
L91:    iload_2
L92:    bipush 54
L94:    if_icmpeq L103
L97:    iload_2
L98:    bipush 56
L100:   if_icmpne L105
L103:   iconst_1
L104:   ireturn
L105:   iload_2
L106:   bipush 49
L108:   if_icmpne L119
L111:   iload_0
L112:   bipush 51
L114:   if_icmpne L119
L117:   iconst_2
L118:   ireturn
L119:   iconst_0
L120:   ireturn
L121:   iload_1
L122:   bipush 99
L124:   if_icmpne L155
L127:   iload_2
L128:   bipush 40
L130:   if_icmpeq L151
L133:   iload_2
L134:   bipush 60
L136:   if_icmpeq L151
L139:   iload_2
L140:   bipush 123
L142:   if_icmpeq L151
L145:   iload_2
L146:   bipush 91
L148:   if_icmpne L153
L151:   iconst_1
L152:   ireturn
L153:   iconst_0
L154:   ireturn
L155:   iload_1
L156:   bipush 100
L158:   if_icmpne L177
L161:   iload_2
L162:   bipush 91
L164:   if_icmpne L175
L167:   iload_0
L168:   bipush 41
L170:   if_icmpne L175
L173:   iconst_2
L174:   ireturn
L175:   iconst_0
L176:   ireturn
L177:   iload_1
L178:   bipush 101
L180:   if_icmpne L200
L183:   iload_2
L184:   bipush 51
L186:   if_icmpeq L196
L189:   iload_2
L190:   sipush 8364
L193:   if_icmpne L198
L196:   iconst_1
L197:   ireturn
L198:   iconst_0
L199:   ireturn
L200:   iload_1
L201:   bipush 102
L203:   if_icmpne L231
L206:   iload_2
L207:   bipush 112
L209:   if_icmpne L220
L212:   iload_0
L213:   bipush 104
L215:   if_icmpne L220
L218:   iconst_2
L219:   ireturn
L220:   iload_2
L221:   sipush 163
L224:   if_icmpne L229
L227:   iconst_1
L228:   ireturn
L229:   iconst_0
L230:   ireturn
L231:   iload_1
L232:   bipush 103
L234:   if_icmpne L253
L237:   iload_2
L238:   bipush 57
L240:   if_icmpeq L249
L243:   iload_2
L244:   bipush 54
L246:   if_icmpne L251
L249:   iconst_1
L250:   ireturn
L251:   iconst_0
L252:   ireturn
L253:   iload_1
L254:   bipush 104
L256:   if_icmpne L269
L259:   iload_2
L260:   bipush 35
L262:   if_icmpne L267
L265:   iconst_1
L266:   ireturn
L267:   iconst_0
L268:   ireturn
L269:   iload_1
L270:   bipush 105
L272:   if_icmpne L327
L275:   iload_2
L276:   bipush 121
L278:   if_icmpeq L323
L281:   iload_2
L282:   bipush 108
L284:   if_icmpeq L323
L287:   iload_2
L288:   bipush 106
L290:   if_icmpeq L323
L293:   iload_2
L294:   bipush 49
L296:   if_icmpeq L323
L299:   iload_2
L300:   bipush 33
L302:   if_icmpeq L323
L305:   iload_2
L306:   bipush 58
L308:   if_icmpeq L323
L311:   iload_2
L312:   bipush 59
L314:   if_icmpeq L323
L317:   iload_2
L318:   bipush 124
L320:   if_icmpne L325
L323:   iconst_1
L324:   ireturn
L325:   iconst_0
L326:   ireturn
L327:   iload_1
L328:   bipush 106
L330:   if_icmpne L335
L333:   iconst_0
L334:   ireturn
L335:   iload_1
L336:   bipush 107
L338:   if_icmpne L343
L341:   iconst_0
L342:   ireturn
L343:   iload_1
L344:   bipush 108
L346:   if_icmpne L371
L349:   iload_2
L350:   bipush 49
L352:   if_icmpeq L367
L355:   iload_2
L356:   bipush 124
L358:   if_icmpeq L367
L361:   iload_2
L362:   bipush 105
L364:   if_icmpne L369
L367:   iconst_1
L368:   ireturn
L369:   iconst_0
L370:   ireturn
L371:   iload_1
L372:   bipush 109
L374:   if_icmpne L379
L377:   iconst_0
L378:   ireturn
L379:   iload_1
L380:   bipush 110
L382:   if_icmplt L747
L385:   iload_1
L386:   bipush 122
L388:   if_icmpgt L747
L391:   iload_1
L392:   bipush 110
L394:   if_icmpne L399
L397:   iconst_0
L398:   ireturn
L399:   iload_1
L400:   bipush 111
L402:   if_icmpne L471
L405:   iload_2
L406:   bipush 48
L408:   if_icmpeq L417
L411:   iload_2
L412:   bipush 42
L414:   if_icmpne L419
L417:   iconst_1
L418:   ireturn
L419:   iload_2
L420:   bipush 40
L422:   if_icmpne L431
L425:   iload_0
L426:   bipush 41
L428:   if_icmpeq L467
L431:   iload_2
L432:   bipush 91
L434:   if_icmpne L443
L437:   iload_0
L438:   bipush 93
L440:   if_icmpeq L467
L443:   iload_2
L444:   bipush 123
L446:   if_icmpne L455
L449:   iload_0
L450:   bipush 125
L452:   if_icmpeq L467
L455:   iload_2
L456:   bipush 60
L458:   if_icmpne L469
L461:   iload_0
L462:   bipush 62
L464:   if_icmpne L469
L467:   iconst_2
L468:   ireturn
L469:   iconst_0
L470:   ireturn
L471:   iload_1
L472:   bipush 112
L474:   if_icmpne L479
L477:   iconst_0
L478:   ireturn
L479:   iload_1
L480:   bipush 113
L482:   if_icmpne L487
L485:   iconst_0
L486:   ireturn
L487:   iload_1
L488:   bipush 114
L490:   if_icmpne L495
L493:   iconst_0
L494:   ireturn
L495:   iload_1
L496:   bipush 115
L498:   if_icmpne L529
L501:   iload_2
L502:   bipush 53
L504:   if_icmpeq L525
L507:   iload_2
L508:   bipush 122
L510:   if_icmpeq L525
L513:   iload_2
L514:   bipush 36
L516:   if_icmpeq L525
L519:   iload_2
L520:   bipush 50
L522:   if_icmpne L527
L525:   iconst_1
L526:   ireturn
L527:   iconst_0
L528:   ireturn
L529:   iload_1
L530:   bipush 116
L532:   if_icmpne L551
L535:   iload_2
L536:   bipush 55
L538:   if_icmpeq L547
L541:   iload_2
L542:   bipush 43
L544:   if_icmpne L549
L547:   iconst_1
L548:   ireturn
L549:   iconst_0
L550:   ireturn
L551:   iload_1
L552:   bipush 117
L554:   if_icmpne L605
L557:   iload_2
L558:   bipush 118
L560:   if_icmpne L565
L563:   iconst_1
L564:   ireturn
L565:   iload_2
L566:   bipush 92
L568:   if_icmpne L577
L571:   iload_0
L572:   bipush 47
L574:   if_icmpeq L601
L577:   iload_2
L578:   bipush 92
L580:   if_icmpne L589
L583:   iload_0
L584:   bipush 124
L586:   if_icmpeq L601
L589:   iload_2
L590:   bipush 124
L592:   if_icmpne L603
L595:   iload_0
L596:   bipush 47
L598:   if_icmpne L603
L601:   iconst_2
L602:   ireturn
L603:   iconst_0
L604:   ireturn
L605:   iload_1
L606:   bipush 118
L608:   if_icmpne L651
L611:   iload_2
L612:   bipush 92
L614:   if_icmpne L623
L617:   iload_0
L618:   bipush 47
L620:   if_icmpeq L647
L623:   iload_2
L624:   bipush 92
L626:   if_icmpne L635
L629:   iload_0
L630:   bipush 124
L632:   if_icmpeq L647
L635:   iload_2
L636:   bipush 124
L638:   if_icmpne L649
L641:   iload_0
L642:   bipush 47
L644:   if_icmpne L649
L647:   iconst_2
L648:   ireturn
L649:   iconst_0
L650:   ireturn
L651:   iload_1
L652:   bipush 119
L654:   if_icmpne L673
L657:   iload_2
L658:   bipush 118
L660:   if_icmpne L671
L663:   iload_0
L664:   bipush 118
L666:   if_icmpne L671
L669:   iconst_2
L670:   ireturn
L671:   iconst_0
L672:   ireturn
L673:   iload_1
L674:   bipush 120
L676:   if_icmpne L731
L679:   iload_2
L680:   bipush 41
L682:   if_icmpne L691
L685:   iload_0
L686:   bipush 40
L688:   if_icmpeq L727
L691:   iload_2
L692:   bipush 125
L694:   if_icmpne L703
L697:   iload_0
L698:   bipush 123
L700:   if_icmpeq L727
L703:   iload_2
L704:   bipush 93
L706:   if_icmpne L715
L709:   iload_0
L710:   bipush 91
L712:   if_icmpeq L727
L715:   iload_2
L716:   bipush 62
L718:   if_icmpne L729
L721:   iload_0
L722:   bipush 60
L724:   if_icmpne L729
L727:   iconst_2
L728:   ireturn
L729:   iconst_0
L730:   ireturn
L731:   iload_1
L732:   bipush 121
L734:   if_icmpne L739
L737:   iconst_0
L738:   ireturn
L739:   iload_1
L740:   bipush 122
L742:   if_icmpne L747
L745:   iconst_0
L746:   ireturn
L747:   iload_1
L748:   bipush 48
L750:   if_icmplt L837
L753:   iload_1
L754:   bipush 57
L756:   if_icmpgt L837
L759:   iload_1
L760:   bipush 48
L762:   if_icmpne L819
L765:   iload_2
L766:   bipush 111
L768:   if_icmpeq L777
L771:   iload_2
L772:   bipush 79
L774:   if_icmpne L779
L777:   iconst_1
L778:   ireturn
L779:   iload_2
L780:   bipush 40
L782:   if_icmpne L791
L785:   iload_0
L786:   bipush 41
L788:   if_icmpeq L815
L791:   iload_2
L792:   bipush 123
L794:   if_icmpne L803
L797:   iload_0
L798:   bipush 125
L800:   if_icmpeq L815
L803:   iload_2
L804:   bipush 91
L806:   if_icmpne L817
L809:   iload_0
L810:   bipush 93
L812:   if_icmpne L817
L815:   iconst_2
L816:   ireturn
L817:   iconst_0
L818:   ireturn
L819:   iload_1
L820:   bipush 49
L822:   if_icmpne L835
L825:   iload_2
L826:   bipush 108
L828:   if_icmpne L833
L831:   iconst_1
L832:   ireturn
L833:   iconst_0
L834:   ireturn
L835:   iconst_0
L836:   ireturn
L837:   iload_1
L838:   bipush 44
L840:   if_icmpne L853
L843:   iload_2
L844:   bipush 46
L846:   if_icmpne L851
L849:   iconst_1
L850:   ireturn
L851:   iconst_0
L852:   ireturn
L853:   iload_1
L854:   bipush 46
L856:   if_icmpne L869
L859:   iload_2
L860:   bipush 44
L862:   if_icmpne L867
L865:   iconst_1
L866:   ireturn
L867:   iconst_0
L868:   ireturn
L869:   iload_1
L870:   bipush 33
L872:   if_icmpne L885
L875:   iload_2
L876:   bipush 105
L878:   if_icmpne L883
L881:   iconst_1
L882:   ireturn
L883:   iconst_0
L884:   ireturn
L885:   iconst_0
L886:   ireturn
L887:   astore 4
L889:   new java/lang/StringBuffer
L892:   dup
L893:   ldc "72478, "
L895:   invokespecial Method java/lang/StringBuffer <init> (Ljava/lang/String;)V
L898:   iload_0
L899:   invokevirtual Method java/lang/StringBuffer append (C)Ljava/lang/StringBuffer;
L902:   ldc ", "
L904:   invokevirtual Method java/lang/StringBuffer append (Ljava/lang/String;)Ljava/lang/StringBuffer;
L907:   iload_1
L908:   invokevirtual Method java/lang/StringBuffer append (C)Ljava/lang/StringBuffer;
L911:   ldc ", "
L913:   invokevirtual Method java/lang/StringBuffer append (Ljava/lang/String;)Ljava/lang/StringBuffer;
L916:   iload_2
L917:   invokevirtual Method java/lang/StringBuffer append (C)Ljava/lang/StringBuffer;
L920:   ldc ", "
L922:   invokevirtual Method java/lang/StringBuffer append (Ljava/lang/String;)Ljava/lang/StringBuffer;
L925:   iload_3
L926:   invokevirtual Method java/lang/StringBuffer append (I)Ljava/lang/StringBuffer;
L929:   ldc ", "
L931:   invokevirtual Method java/lang/StringBuffer append (Ljava/lang/String;)Ljava/lang/StringBuffer;
L934:   aload 4
L936:   invokevirtual Method java/lang/Throwable toString ()Ljava/lang/String;
L939:   invokevirtual Method java/lang/StringBuffer append (Ljava/lang/String;)Ljava/lang/StringBuffer;
L942:   invokevirtual Method java/lang/StringBuffer toString ()Ljava/lang/String;
L945:   invokestatic Method sign/signlink reporterror (Ljava/lang/String;)V
L948:   new java/lang/RuntimeException
L951:   dup
L952:   invokespecial Method java/lang/RuntimeException <init> ()V
L955:   athrow
L956:   
    .end code
.end method

.method private static final b : (IC)B
    .code stack 3 locals 3
        .catch java/lang/RuntimeException from L0 to L65 using L65
L0:     iload_0
L1:     ifeq L12
L4:     new java/lang/NullPointerException
L7:     dup
L8:     invokespecial Method java/lang/NullPointerException <init> ()V
L11:    athrow
L12:    iload_1
L13:    bipush 97
L15:    if_icmplt L32
L18:    iload_1
L19:    bipush 122
L21:    if_icmpgt L32
L24:    iload_1
L25:    bipush 97
L27:    isub
L28:    iconst_1
L29:    iadd
L30:    i2b
L31:    ireturn
L32:    iload_1
L33:    bipush 39
L35:    if_icmpne L41
L38:    bipush 28
L40:    ireturn
L41:    iload_1
L42:    bipush 48
L44:    if_icmplt L62
L47:    iload_1
L48:    bipush 57
L50:    if_icmpgt L62
L53:    iload_1
L54:    bipush 48
L56:    isub
L57:    bipush 29
L59:    iadd
L60:    i2b
L61:    ireturn
L62:    bipush 27
L64:    ireturn
L65:    astore_2
L66:    new java/lang/StringBuffer
L69:    dup
L70:    ldc "37807, "
L72:    invokespecial Method java/lang/StringBuffer <init> (Ljava/lang/String;)V
L75:    iload_0
L76:    invokevirtual Method java/lang/StringBuffer append (I)Ljava/lang/StringBuffer;
L79:    ldc ", "
L81:    invokevirtual Method java/lang/StringBuffer append (Ljava/lang/String;)Ljava/lang/StringBuffer;
L84:    iload_1
L85:    invokevirtual Method java/lang/StringBuffer append (C)Ljava/lang/StringBuffer;
L88:    ldc ", "
L90:    invokevirtual Method java/lang/StringBuffer append (Ljava/lang/String;)Ljava/lang/StringBuffer;
L93:    aload_2
L94:    invokevirtual Method java/lang/Throwable toString ()Ljava/lang/String;
L97:    invokevirtual Method java/lang/StringBuffer append (Ljava/lang/String;)Ljava/lang/StringBuffer;
L100:   invokevirtual Method java/lang/StringBuffer toString ()Ljava/lang/String;
L103:   invokestatic Method sign/signlink reporterror (Ljava/lang/String;)V
L106:   new java/lang/RuntimeException
L109:   dup
L110:   invokespecial Method java/lang/RuntimeException <init> ()V
L113:   athrow
L114:   
    .end code
.end method

.method private static final a : (I[C)V
    .code stack 4 locals 12
L0:     getstatic Field mc q I
L3:     istore 11
        .catch java/lang/RuntimeException from L5 to L216 using L217
L5:     iconst_0
L6:     istore_2
L7:     iconst_0
L8:     istore_3
L9:     iload_0
L10:    bipush 8
L12:    if_icmpeq L16
L15:    return
L16:    iconst_0
L17:    istore 4
L19:    iconst_0
L20:    istore 5
L22:    iload 11
L24:    ifeq L202
L27:    iconst_0
L28:    istore 6
L30:    iload_3
L31:    istore 7
L33:    iload 11
L35:    ifeq L67
L38:    aload_1
L39:    iload 7
L41:    caload
L42:    iconst_2
L43:    invokestatic Method mc a (CI)Z
L46:    ifne L64
L49:    aload_1
L50:    iload 7
L52:    caload
L53:    bipush 13
L55:    invokestatic Method mc a (CB)Z
L58:    ifne L64
L61:    iconst_1
L62:    istore 6
L64:    iinc 7 1
L67:    iload 7
L69:    iflt L83
L72:    iload 7
L74:    iload_2
L75:    if_icmpge L83
L78:    iload 6
L80:    ifeq L38
L83:    iload 6
L85:    ifeq L91
L88:    iconst_0
L89:    istore 4
L91:    iload 4
L93:    ifne L99
L96:    iload_2
L97:    istore 5
L99:    bipush 6
L101:   iload_2
L102:   aload_1
L103:   invokestatic Method mc a (II[C)I
L106:   istore_3
L107:   iconst_0
L108:   istore 8
L110:   iload_2
L111:   istore 9
L113:   iload 11
L115:   ifeq L136
L118:   iload 8
L120:   bipush 10
L122:   imul
L123:   aload_1
L124:   iload 9
L126:   caload
L127:   iadd
L128:   bipush 48
L130:   isub
L131:   istore 8
L133:   iinc 9 1
L136:   iload 9
L138:   iload_3
L139:   if_icmplt L118
L142:   iload 8
L144:   sipush 255
L147:   if_icmpgt L158
L150:   iload_3
L151:   iload_2
L152:   isub
L153:   bipush 8
L155:   if_icmple L166
L158:   iconst_0
L159:   istore 4
L161:   iload 11
L163:   ifeq L169
L166:   iinc 4 1
L169:   iload 4
L171:   iconst_4
L172:   if_icmpne L202
L175:   iload 5
L177:   istore 10
L179:   iload 11
L181:   ifeq L193
L184:   aload_1
L185:   iload 10
L187:   bipush 42
L189:   castore
L190:   iinc 10 1
L193:   iload 10
L195:   iload_3
L196:   if_icmplt L184
L199:   iconst_0
L200:   istore 4
L202:   sipush 149
L205:   aload_1
L206:   iload_3
L207:   invokestatic Method mc a (I[CI)I
L210:   dup
L211:   istore_2
L212:   iconst_m1
L213:   if_icmpne L27
L216:   return
L217:   astore_2
L218:   new java/lang/StringBuffer
L221:   dup
L222:   ldc "18716, "
L224:   invokespecial Method java/lang/StringBuffer <init> (Ljava/lang/String;)V
L227:   iload_0
L228:   invokevirtual Method java/lang/StringBuffer append (I)Ljava/lang/StringBuffer;
L231:   ldc ", "
L233:   invokevirtual Method java/lang/StringBuffer append (Ljava/lang/String;)Ljava/lang/StringBuffer;
L236:   aload_1
L237:   invokevirtual Method java/lang/StringBuffer append ([C)Ljava/lang/StringBuffer;
L240:   ldc ", "
L242:   invokevirtual Method java/lang/StringBuffer append (Ljava/lang/String;)Ljava/lang/StringBuffer;
L245:   aload_2
L246:   invokevirtual Method java/lang/Throwable toString ()Ljava/lang/String;
L249:   invokevirtual Method java/lang/StringBuffer append (Ljava/lang/String;)Ljava/lang/StringBuffer;
L252:   invokevirtual Method java/lang/StringBuffer toString ()Ljava/lang/String;
L255:   invokestatic Method sign/signlink reporterror (Ljava/lang/String;)V
L258:   new java/lang/RuntimeException
L261:   dup
L262:   invokespecial Method java/lang/RuntimeException <init> ()V
L265:   athrow
L266:   
    .end code
.end method

.method private static final a : (I[CI)I
    .code stack 4 locals 4
        .catch java/lang/RuntimeException from L0 to L46 using L46
L0:     bipush 66
L2:     iload_0
L3:     idiv
L4:     istore_0
L5:     iload_2
L6:     istore_3
L7:     getstatic Field mc q I
L10:    ifeq L34
L13:    aload_1
L14:    iload_3
L15:    caload
L16:    bipush 48
L18:    if_icmplt L31
L21:    aload_1
L22:    iload_3
L23:    caload
L24:    bipush 57
L26:    if_icmpgt L31
L29:    iload_3
L30:    ireturn
L31:    iinc 3 1
L34:    iload_3
L35:    aload_1
L36:    arraylength
L37:    if_icmpge L44
L40:    iload_3
L41:    ifge L13
L44:    iconst_m1
L45:    ireturn
L46:    astore_3
L47:    new java/lang/StringBuffer
L50:    dup
L51:    ldc "34666, "
L53:    invokespecial Method java/lang/StringBuffer <init> (Ljava/lang/String;)V
L56:    iload_0
L57:    invokevirtual Method java/lang/StringBuffer append (I)Ljava/lang/StringBuffer;
L60:    ldc ", "
L62:    invokevirtual Method java/lang/StringBuffer append (Ljava/lang/String;)Ljava/lang/StringBuffer;
L65:    aload_1
L66:    invokevirtual Method java/lang/StringBuffer append ([C)Ljava/lang/StringBuffer;
L69:    ldc ", "
L71:    invokevirtual Method java/lang/StringBuffer append (Ljava/lang/String;)Ljava/lang/StringBuffer;
L74:    iload_2
L75:    invokevirtual Method java/lang/StringBuffer append (I)Ljava/lang/StringBuffer;
L78:    ldc ", "
L80:    invokevirtual Method java/lang/StringBuffer append (Ljava/lang/String;)Ljava/lang/StringBuffer;
L83:    aload_3
L84:    invokevirtual Method java/lang/Throwable toString ()Ljava/lang/String;
L87:    invokevirtual Method java/lang/StringBuffer append (Ljava/lang/String;)Ljava/lang/StringBuffer;
L90:    invokevirtual Method java/lang/StringBuffer toString ()Ljava/lang/String;
L93:    invokestatic Method sign/signlink reporterror (Ljava/lang/String;)V
L96:    new java/lang/RuntimeException
L99:    dup
L100:   invokespecial Method java/lang/RuntimeException <init> ()V
L103:   athrow
L104:   
    .end code
.end method

.method private static final a : (II[C)I
    .code stack 4 locals 4
        .catch java/lang/RuntimeException from L0 to L50 using L50
L0:     iload_0
L1:     bipush 6
L3:     if_icmpeq L8
L6:     iconst_4
L7:     ireturn
L8:     iload_1
L9:     istore_3
L10:    getstatic Field mc q I
L13:    ifeq L37
L16:    aload_2
L17:    iload_3
L18:    caload
L19:    bipush 48
L21:    if_icmplt L32
L24:    aload_2
L25:    iload_3
L26:    caload
L27:    bipush 57
L29:    if_icmple L34
L32:    iload_3
L33:    ireturn
L34:    iinc 3 1
L37:    iload_3
L38:    aload_2
L39:    arraylength
L40:    if_icmpge L47
L43:    iload_3
L44:    ifge L16
L47:    aload_2
L48:    arraylength
L49:    ireturn
L50:    astore_3
L51:    new java/lang/StringBuffer
L54:    dup
L55:    ldc "22999, "
L57:    invokespecial Method java/lang/StringBuffer <init> (Ljava/lang/String;)V
L60:    iload_0
L61:    invokevirtual Method java/lang/StringBuffer append (I)Ljava/lang/StringBuffer;
L64:    ldc ", "
L66:    invokevirtual Method java/lang/StringBuffer append (Ljava/lang/String;)Ljava/lang/StringBuffer;
L69:    iload_1
L70:    invokevirtual Method java/lang/StringBuffer append (I)Ljava/lang/StringBuffer;
L73:    ldc ", "
L75:    invokevirtual Method java/lang/StringBuffer append (Ljava/lang/String;)Ljava/lang/StringBuffer;
L78:    aload_2
L79:    invokevirtual Method java/lang/StringBuffer append ([C)Ljava/lang/StringBuffer;
L82:    ldc ", "
L84:    invokevirtual Method java/lang/StringBuffer append (Ljava/lang/String;)Ljava/lang/StringBuffer;
L87:    aload_3
L88:    invokevirtual Method java/lang/Throwable toString ()Ljava/lang/String;
L91:    invokevirtual Method java/lang/StringBuffer append (Ljava/lang/String;)Ljava/lang/StringBuffer;
L94:    invokevirtual Method java/lang/StringBuffer toString ()Ljava/lang/String;
L97:    invokestatic Method sign/signlink reporterror (Ljava/lang/String;)V
L100:   new java/lang/RuntimeException
L103:   dup
L104:   invokespecial Method java/lang/RuntimeException <init> ()V
L107:   athrow
L108:   
    .end code
.end method

.method private static final a : (CI)Z
    .code stack 3 locals 3
        .catch java/lang/RuntimeException from L0 to L37 using L37
L0:     iload_1
L1:     iconst_2
L2:     if_icmpeq L13
L5:     new java/lang/NullPointerException
L8:     dup
L9:     invokespecial Method java/lang/NullPointerException <init> ()V
L12:    athrow
L13:    sipush -175
L16:    iload_0
L17:    invokestatic Method mc c (IC)Z
L20:    ifne L33
L23:    iload_0
L24:    sipush 10361
L27:    invokestatic Method mc b (CI)Z
L30:    ifeq L35
L33:    iconst_0
L34:    ireturn
L35:    iconst_1
L36:    ireturn
L37:    astore_2
L38:    new java/lang/StringBuffer
L41:    dup
L42:    ldc "40138, "
L44:    invokespecial Method java/lang/StringBuffer <init> (Ljava/lang/String;)V
L47:    iload_0
L48:    invokevirtual Method java/lang/StringBuffer append (C)Ljava/lang/StringBuffer;
L51:    ldc ", "
L53:    invokevirtual Method java/lang/StringBuffer append (Ljava/lang/String;)Ljava/lang/StringBuffer;
L56:    iload_1
L57:    invokevirtual Method java/lang/StringBuffer append (I)Ljava/lang/StringBuffer;
L60:    ldc ", "
L62:    invokevirtual Method java/lang/StringBuffer append (Ljava/lang/String;)Ljava/lang/StringBuffer;
L65:    aload_2
L66:    invokevirtual Method java/lang/Throwable toString ()Ljava/lang/String;
L69:    invokevirtual Method java/lang/StringBuffer append (Ljava/lang/String;)Ljava/lang/StringBuffer;
L72:    invokevirtual Method java/lang/StringBuffer toString ()Ljava/lang/String;
L75:    invokestatic Method sign/signlink reporterror (Ljava/lang/String;)V
L78:    new java/lang/RuntimeException
L81:    dup
L82:    invokespecial Method java/lang/RuntimeException <init> ()V
L85:    athrow
L86:    
    .end code
.end method

.method private static final a : (CB)Z
    .code stack 3 locals 3
        .catch java/lang/RuntimeException from L0 to L62 using L62
L0:     iload_1
L1:     bipush 13
L3:     if_icmpeq L14
L6:     new java/lang/NullPointerException
L9:     dup
L10:    invokespecial Method java/lang/NullPointerException <init> ()V
L13:    athrow
L14:    iload_0
L15:    bipush 97
L17:    if_icmplt L26
L20:    iload_0
L21:    bipush 122
L23:    if_icmple L28
L26:    iconst_1
L27:    ireturn
L28:    iload_0
L29:    bipush 118
L31:    if_icmpeq L58
L34:    iload_0
L35:    bipush 120
L37:    if_icmpeq L58
L40:    iload_0
L41:    bipush 106
L43:    if_icmpeq L58
L46:    iload_0
L47:    bipush 113
L49:    if_icmpeq L58
L52:    iload_0
L53:    bipush 122
L55:    if_icmpne L60
L58:    iconst_1
L59:    ireturn
L60:    iconst_0
L61:    ireturn
L62:    astore_2
L63:    new java/lang/StringBuffer
L66:    dup
L67:    ldc "85337, "
L69:    invokespecial Method java/lang/StringBuffer <init> (Ljava/lang/String;)V
L72:    iload_0
L73:    invokevirtual Method java/lang/StringBuffer append (C)Ljava/lang/StringBuffer;
L76:    ldc ", "
L78:    invokevirtual Method java/lang/StringBuffer append (Ljava/lang/String;)Ljava/lang/StringBuffer;
L81:    iload_1
L82:    invokevirtual Method java/lang/StringBuffer append (I)Ljava/lang/StringBuffer;
L85:    ldc ", "
L87:    invokevirtual Method java/lang/StringBuffer append (Ljava/lang/String;)Ljava/lang/StringBuffer;
L90:    aload_2
L91:    invokevirtual Method java/lang/Throwable toString ()Ljava/lang/String;
L94:    invokevirtual Method java/lang/StringBuffer append (Ljava/lang/String;)Ljava/lang/StringBuffer;
L97:    invokevirtual Method java/lang/StringBuffer toString ()Ljava/lang/String;
L100:   invokestatic Method sign/signlink reporterror (Ljava/lang/String;)V
L103:   new java/lang/RuntimeException
L106:   dup
L107:   invokespecial Method java/lang/RuntimeException <init> ()V
L110:   athrow
L111:   
    .end code
.end method

.method private static final c : (IC)Z
    .code stack 3 locals 3
        .catch java/lang/RuntimeException from L0 to L40 using L40
L0:     iload_0
L1:     iflt L12
L4:     new java/lang/NullPointerException
L7:     dup
L8:     invokespecial Method java/lang/NullPointerException <init> ()V
L11:    athrow
L12:    iload_1
L13:    bipush 97
L15:    if_icmplt L24
L18:    iload_1
L19:    bipush 122
L21:    if_icmple L38
L24:    iload_1
L25:    bipush 65
L27:    if_icmplt L36
L30:    iload_1
L31:    bipush 90
L33:    if_icmple L38
L36:    iconst_0
L37:    ireturn
L38:    iconst_1
L39:    ireturn
L40:    astore_2
L41:    new java/lang/StringBuffer
L44:    dup
L45:    ldc "88324, "
L47:    invokespecial Method java/lang/StringBuffer <init> (Ljava/lang/String;)V
L50:    iload_0
L51:    invokevirtual Method java/lang/StringBuffer append (I)Ljava/lang/StringBuffer;
L54:    ldc ", "
L56:    invokevirtual Method java/lang/StringBuffer append (Ljava/lang/String;)Ljava/lang/StringBuffer;
L59:    iload_1
L60:    invokevirtual Method java/lang/StringBuffer append (C)Ljava/lang/StringBuffer;
L63:    ldc ", "
L65:    invokevirtual Method java/lang/StringBuffer append (Ljava/lang/String;)Ljava/lang/StringBuffer;
L68:    aload_2
L69:    invokevirtual Method java/lang/Throwable toString ()Ljava/lang/String;
L72:    invokevirtual Method java/lang/StringBuffer append (Ljava/lang/String;)Ljava/lang/StringBuffer;
L75:    invokevirtual Method java/lang/StringBuffer toString ()Ljava/lang/String;
L78:    invokestatic Method sign/signlink reporterror (Ljava/lang/String;)V
L81:    new java/lang/RuntimeException
L84:    dup
L85:    invokespecial Method java/lang/RuntimeException <init> ()V
L88:    athrow
L89:    
    .end code
.end method

.method private static final b : (CI)Z
    .code stack 3 locals 3
        .catch java/lang/RuntimeException from L0 to L28 using L28
L0:     iload_1
L1:     sipush 10361
L4:     if_icmpeq L12
L7:     bipush -124
L9:     putstatic Field mc b I
L12:    iload_0
L13:    bipush 48
L15:    if_icmplt L24
L18:    iload_0
L19:    bipush 57
L21:    if_icmple L26
L24:    iconst_0
L25:    ireturn
L26:    iconst_1
L27:    ireturn
L28:    astore_2
L29:    new java/lang/StringBuffer
L32:    dup
L33:    ldc "12677, "
L35:    invokespecial Method java/lang/StringBuffer <init> (Ljava/lang/String;)V
L38:    iload_0
L39:    invokevirtual Method java/lang/StringBuffer append (C)Ljava/lang/StringBuffer;
L42:    ldc ", "
L44:    invokevirtual Method java/lang/StringBuffer append (Ljava/lang/String;)Ljava/lang/StringBuffer;
L47:    iload_1
L48:    invokevirtual Method java/lang/StringBuffer append (I)Ljava/lang/StringBuffer;
L51:    ldc ", "
L53:    invokevirtual Method java/lang/StringBuffer append (Ljava/lang/String;)Ljava/lang/StringBuffer;
L56:    aload_2
L57:    invokevirtual Method java/lang/Throwable toString ()Ljava/lang/String;
L60:    invokevirtual Method java/lang/StringBuffer append (Ljava/lang/String;)Ljava/lang/StringBuffer;
L63:    invokevirtual Method java/lang/StringBuffer toString ()Ljava/lang/String;
L66:    invokestatic Method sign/signlink reporterror (Ljava/lang/String;)V
L69:    new java/lang/RuntimeException
L72:    dup
L73:    invokespecial Method java/lang/RuntimeException <init> ()V
L76:    athrow
L77:    
    .end code
.end method

.method private static final a : (BC)Z
    .code stack 3 locals 3
        .catch java/lang/RuntimeException from L0 to L26 using L26
L0:     iload_0
L1:     ifeq L10
L4:     sipush -254
L7:     putstatic Field mc c I
L10:    iload_1
L11:    bipush 97
L13:    if_icmplt L22
L16:    iload_1
L17:    bipush 122
L19:    if_icmple L24
L22:    iconst_0
L23:    ireturn
L24:    iconst_1
L25:    ireturn
L26:    astore_2
L27:    new java/lang/StringBuffer
L30:    dup
L31:    ldc "54545, "
L33:    invokespecial Method java/lang/StringBuffer <init> (Ljava/lang/String;)V
L36:    iload_0
L37:    invokevirtual Method java/lang/StringBuffer append (I)Ljava/lang/StringBuffer;
L40:    ldc ", "
L42:    invokevirtual Method java/lang/StringBuffer append (Ljava/lang/String;)Ljava/lang/StringBuffer;
L45:    iload_1
L46:    invokevirtual Method java/lang/StringBuffer append (C)Ljava/lang/StringBuffer;
L49:    ldc ", "
L51:    invokevirtual Method java/lang/StringBuffer append (Ljava/lang/String;)Ljava/lang/StringBuffer;
L54:    aload_2
L55:    invokevirtual Method java/lang/Throwable toString ()Ljava/lang/String;
L58:    invokevirtual Method java/lang/StringBuffer append (Ljava/lang/String;)Ljava/lang/StringBuffer;
L61:    invokevirtual Method java/lang/StringBuffer toString ()Ljava/lang/String;
L64:    invokestatic Method sign/signlink reporterror (Ljava/lang/String;)V
L67:    new java/lang/RuntimeException
L70:    dup
L71:    invokespecial Method java/lang/RuntimeException <init> ()V
L74:    athrow
L75:    
    .end code
.end method

.method private static final d : (IC)Z
    .code stack 3 locals 3
        .catch java/lang/RuntimeException from L0 to L38 using L38
L0:     iload_0
L1:     iflt L8
L4:     iload_0
L5:     ifle L22
L8:     getstatic Field mc a Z
L11:    ifeq L18
L14:    iconst_0
L15:    goto L19
L18:    iconst_1
L19:    putstatic Field mc a Z
L22:    iload_1
L23:    bipush 65
L25:    if_icmplt L34
L28:    iload_1
L29:    bipush 90
L31:    if_icmple L36
L34:    iconst_0
L35:    ireturn
L36:    iconst_1
L37:    ireturn
L38:    astore_2
L39:    new java/lang/StringBuffer
L42:    dup
L43:    ldc "31350, "
L45:    invokespecial Method java/lang/StringBuffer <init> (Ljava/lang/String;)V
L48:    iload_0
L49:    invokevirtual Method java/lang/StringBuffer append (I)Ljava/lang/StringBuffer;
L52:    ldc ", "
L54:    invokevirtual Method java/lang/StringBuffer append (Ljava/lang/String;)Ljava/lang/StringBuffer;
L57:    iload_1
L58:    invokevirtual Method java/lang/StringBuffer append (C)Ljava/lang/StringBuffer;
L61:    ldc ", "
L63:    invokevirtual Method java/lang/StringBuffer append (Ljava/lang/String;)Ljava/lang/StringBuffer;
L66:    aload_2
L67:    invokevirtual Method java/lang/Throwable toString ()Ljava/lang/String;
L70:    invokevirtual Method java/lang/StringBuffer append (Ljava/lang/String;)Ljava/lang/StringBuffer;
L73:    invokevirtual Method java/lang/StringBuffer toString ()Ljava/lang/String;
L76:    invokestatic Method sign/signlink reporterror (Ljava/lang/String;)V
L79:    new java/lang/RuntimeException
L82:    dup
L83:    invokespecial Method java/lang/RuntimeException <init> ()V
L86:    athrow
L87:    
    .end code
.end method

.method private static final c : ([CI)Z
    .code stack 4 locals 9
L0:     getstatic Field mc q I
L3:     istore 8
        .catch java/lang/RuntimeException from L5 to L177 using L177
L5:     iconst_1
L6:     istore_2
L7:     iconst_0
L8:     istore_3
L9:     iload 8
L11:    ifeq L37
L14:    aload_0
L15:    iload_3
L16:    caload
L17:    sipush 10361
L20:    invokestatic Method mc b (CI)Z
L23:    ifne L34
L26:    aload_0
L27:    iload_3
L28:    caload
L29:    ifeq L34
L32:    iconst_0
L33:    istore_2
L34:    iinc 3 1
L37:    iload_3
L38:    aload_0
L39:    arraylength
L40:    if_icmplt L14
L43:    iload_2
L44:    ifeq L49
L47:    iconst_1
L48:    ireturn
L49:    iconst_5
L50:    aload_0
L51:    invokestatic Method mc b (I[C)I
L54:    istore 4
L56:    iconst_0
L57:    istore 5
L59:    iload_1
L60:    bipush 6
L62:    if_icmpeq L81
L65:    iconst_1
L66:    istore 6
L68:    iload 8
L70:    ifeq L76
L73:    iinc 6 1
L76:    iload 6
L78:    ifgt L73
L81:    getstatic Field mc j [I
L84:    arraylength
L85:    iconst_1
L86:    isub
L87:    istore 6
L89:    iload 4
L91:    getstatic Field mc j [I
L94:    iload 5
L96:    iaload
L97:    if_icmpeq L111
L100:   iload 4
L102:   getstatic Field mc j [I
L105:   iload 6
L107:   iaload
L108:   if_icmpne L113
L111:   iconst_1
L112:   ireturn
L113:   iload 5
L115:   iload 6
L117:   iadd
L118:   iconst_2
L119:   idiv
L120:   istore 7
L122:   iload 4
L124:   getstatic Field mc j [I
L127:   iload 7
L129:   iaload
L130:   if_icmpne L135
L133:   iconst_1
L134:   ireturn
L135:   iload 4
L137:   getstatic Field mc j [I
L140:   iload 7
L142:   iaload
L143:   if_icmpge L155
L146:   iload 7
L148:   istore 6
L150:   iload 8
L152:   ifeq L159
L155:   iload 7
L157:   istore 5
L159:   iload 5
L161:   iload 6
L163:   if_icmpeq L175
L166:   iload 5
L168:   iconst_1
L169:   iadd
L170:   iload 6
L172:   if_icmpne L113
L175:   iconst_0
L176:   ireturn
L177:   astore_2
L178:   new java/lang/StringBuffer
L181:   dup
L182:   ldc "69798, "
L184:   invokespecial Method java/lang/StringBuffer <init> (Ljava/lang/String;)V
L187:   aload_0
L188:   invokevirtual Method java/lang/StringBuffer append ([C)Ljava/lang/StringBuffer;
L191:   ldc ", "
L193:   invokevirtual Method java/lang/StringBuffer append (Ljava/lang/String;)Ljava/lang/StringBuffer;
L196:   iload_1
L197:   invokevirtual Method java/lang/StringBuffer append (I)Ljava/lang/StringBuffer;
L200:   ldc ", "
L202:   invokevirtual Method java/lang/StringBuffer append (Ljava/lang/String;)Ljava/lang/StringBuffer;
L205:   aload_2
L206:   invokevirtual Method java/lang/Throwable toString ()Ljava/lang/String;
L209:   invokevirtual Method java/lang/StringBuffer append (Ljava/lang/String;)Ljava/lang/StringBuffer;
L212:   invokevirtual Method java/lang/StringBuffer toString ()Ljava/lang/String;
L215:   invokestatic Method sign/signlink reporterror (Ljava/lang/String;)V
L218:   new java/lang/RuntimeException
L221:   dup
L222:   invokespecial Method java/lang/RuntimeException <init> ()V
L225:   athrow
L226:   
    .end code
.end method

.method public static final b : (I[C)I
    .code stack 4 locals 6
L0:     getstatic Field mc q I
L3:     istore 5
        .catch java/lang/RuntimeException from L5 to L162 using L162
L5:     aload_1
L6:     arraylength
L7:     bipush 6
L9:     if_icmple L14
L12:    iconst_0
L13:    ireturn
L14:    iconst_0
L15:    istore_2
L16:    iconst_0
L17:    istore_3
L18:    iload 5
L20:    ifeq L128
L23:    aload_1
L24:    aload_1
L25:    arraylength
L26:    iload_3
L27:    isub
L28:    iconst_1
L29:    isub
L30:    caload
L31:    istore 4
L33:    iload 4
L35:    bipush 97
L37:    if_icmplt L65
L40:    iload 4
L42:    bipush 122
L44:    if_icmpgt L65
L47:    iload_2
L48:    bipush 38
L50:    imul
L51:    iload 4
L53:    bipush 97
L55:    isub
L56:    iconst_1
L57:    iadd
L58:    iadd
L59:    istore_2
L60:    iload 5
L62:    ifeq L125
L65:    iload 4
L67:    bipush 39
L69:    if_icmpne L85
L72:    iload_2
L73:    bipush 38
L75:    imul
L76:    bipush 27
L78:    iadd
L79:    istore_2
L80:    iload 5
L82:    ifeq L125
L85:    iload 4
L87:    bipush 48
L89:    if_icmplt L118
L92:    iload 4
L94:    bipush 57
L96:    if_icmpgt L118
L99:    iload_2
L100:   bipush 38
L102:   imul
L103:   iload 4
L105:   bipush 48
L107:   isub
L108:   bipush 28
L110:   iadd
L111:   iadd
L112:   istore_2
L113:   iload 5
L115:   ifeq L125
L118:   iload 4
L120:   ifeq L125
L123:   iconst_0
L124:   ireturn
L125:   iinc 3 1
L128:   iload_3
L129:   aload_1
L130:   arraylength
L131:   if_icmplt L23
L134:   iload_0
L135:   iconst_5
L136:   if_icmplt L144
L139:   iload_0
L140:   iconst_5
L141:   if_icmple L160
L144:   iconst_1
L145:   istore 4
L147:   iload 5
L149:   ifeq L155
L152:   iinc 4 1
L155:   iload 4
L157:   ifgt L152
L160:   iload_2
L161:   ireturn
L162:   astore_2
L163:   new java/lang/StringBuffer
L166:   dup
L167:   ldc "78520, "
L169:   invokespecial Method java/lang/StringBuffer <init> (Ljava/lang/String;)V
L172:   iload_0
L173:   invokevirtual Method java/lang/StringBuffer append (I)Ljava/lang/StringBuffer;
L176:   ldc ", "
L178:   invokevirtual Method java/lang/StringBuffer append (Ljava/lang/String;)Ljava/lang/StringBuffer;
L181:   aload_1
L182:   invokevirtual Method java/lang/StringBuffer append ([C)Ljava/lang/StringBuffer;
L185:   ldc ", "
L187:   invokevirtual Method java/lang/StringBuffer append (Ljava/lang/String;)Ljava/lang/StringBuffer;
L190:   aload_2
L191:   invokevirtual Method java/lang/Throwable toString ()Ljava/lang/String;
L194:   invokevirtual Method java/lang/StringBuffer append (Ljava/lang/String;)Ljava/lang/StringBuffer;
L197:   invokevirtual Method java/lang/StringBuffer toString ()Ljava/lang/String;
L200:   invokestatic Method sign/signlink reporterror (Ljava/lang/String;)V
L203:   new java/lang/RuntimeException
L206:   dup
L207:   invokespecial Method java/lang/RuntimeException <init> ()V
L210:   athrow
L211:   
    .end code
.end method

.method static <clinit> : ()V
    .code stack 4 locals 0
L0:     sipush 24882
L3:     putstatic Field mc b I
L6:     sipush -178
L9:     putstatic Field mc c I
L12:    sipush 16180
L15:    putstatic Field mc e I
L18:    sipush 383
L21:    putstatic Field mc f I
L24:    bipush 6
L26:    putstatic Field mc g B
L29:    bipush -81
L31:    putstatic Field mc h I
L34:    iconst_5
L35:    anewarray java/lang/String
L38:    dup
L39:    iconst_0
L40:    ldc "cook"
L42:    aastore
L43:    dup
L44:    iconst_1
L45:    ldc "cook's"
L47:    aastore
L48:    dup
L49:    iconst_2
L50:    ldc "cooks"
L52:    aastore
L53:    dup
L54:    iconst_3
L55:    ldc "seeks"
L57:    aastore
L58:    dup
L59:    iconst_4
L60:    ldc "sheet"
L62:    aastore
L63:    putstatic Field mc p [Ljava/lang/String;
L66:    return
L67:    
    .end code
.end method
.end class
