.version 45 3
.class public super passwordapp_de
.super java/applet/Applet
.implements java/awt/event/ActionListener
.implements java/awt/event/KeyListener
.implements java/awt/event/TextListener
.implements java/lang/Runnable
.field private static final allowedlist [Ljava/lang/String;
.field private codebase Ljava/lang/String;
.field private question [Ljava/awt/TextField;
.field private recov [Ljava/awt/TextField;
.field private norecovcheck Ljava/awt/Checkbox;
.field private password1 Ljava/awt/TextField;
.field private key_e Ljava/math/BigInteger;
.field private key_n Ljava/math/BigInteger;
.field private onreversepath Z
.field private hidepanel Ljava/awt/Panel;
.field private showpanel Ljava/awt/Panel;
.field private static final PROTOCOL_VERSION I = 2
.field private static final TYPE_CHANGEQUESTIONS I = 2
.field private static final TYPE_DEBUG I = 4
.field private type I
.field private username Ljava/lang/String;
.field private uid I
.field private processingpage Ljava/awt/Panel;
.field private system_error_page Ljava/awt/Panel;
.field private blocked_query_page Ljava/awt/Panel;
.field private blocked_attack_page Ljava/awt/Panel;
.field private wrongpassword_page Ljava/awt/Panel;
.field private change_questions_success_page_active Ljava/awt/Panel;
.field private change_questions_success_page_pending Ljava/awt/Panel;
.field private change_questions_tooshort_page Ljava/awt/Panel;
.field private change_questions_samequestions_page Ljava/awt/Panel;
.field private change_questions_sameanswers_page Ljava/awt/Panel;
.field private change_questions_qandamatch_page Ljava/awt/Panel;
.field private change_questions_page Ljava/awt/Panel;
.field private example_questions [Ljava/lang/String;
.field initialised Z
.field private debug_panel I

.method public init : ()V
    .code stack 3 locals 2
L0:     getstatic Field java/lang/System out Ljava/io/PrintStream;
L3:     ldc "Version: 3 DE"
L5:     invokevirtual Method java/io/PrintStream println (Ljava/lang/String;)V
L8:     new java/lang/Thread
L11:    dup
L12:    aload_0
L13:    invokespecial Method java/lang/Thread <init> (Ljava/lang/Runnable;)V
L16:    astore_1
L17:    aload_1
L18:    iconst_1
L19:    invokevirtual Method java/lang/Thread setDaemon (Z)V
L22:    aload_1
L23:    invokevirtual Method java/lang/Thread start ()V
L26:    return
L27:    
        .linenumbertable
            L0 68
            L8 69
            L17 70
            L22 71
            L26 67
        .end linenumbertable
    .end code
.end method

.method private init_messages : ()V
    .code stack 6 locals 4
L0:     aload_0
L1:     new java/awt/Panel
L4:     dup
L5:     aconst_null
L6:     invokespecial Method java/awt/Panel <init> (Ljava/awt/LayoutManager;)V
L9:     putfield Field passwordapp_de processingpage Ljava/awt/Panel;
L12:    aload_0
L13:    getfield Field passwordapp_de processingpage Ljava/awt/Panel;
L16:    aload_0
L17:    invokevirtual Method java/awt/Component getSize ()Ljava/awt/Dimension;
L20:    invokevirtual Method java/awt/Component setSize (Ljava/awt/Dimension;)V
L23:    aload_0
L24:    ldc "Ihre Anfrage wird bearbeitet."
L26:    sipush 180
L29:    aload_0
L30:    invokevirtual Method java/awt/Component getSize ()Ljava/awt/Dimension;
L33:    getfield Field java/awt/Dimension height I
L36:    iconst_2
L37:    idiv
L38:    bipush 10
L40:    isub
L41:    invokespecial Method passwordapp_de getLabel (Ljava/lang/String;II)Ljava/awt/Label;
L44:    astore_1
L45:    aload_1
L46:    new java/awt/Font
L49:    dup
L50:    ldc "Arial"
L52:    iconst_1
L53:    bipush 13
L55:    invokespecial Method java/awt/Font <init> (Ljava/lang/String;II)V
L58:    invokevirtual Method java/awt/Component setFont (Ljava/awt/Font;)V
L61:    aload_0
L62:    getfield Field passwordapp_de processingpage Ljava/awt/Panel;
L65:    aload_1
L66:    invokevirtual Method java/awt/Container add (Ljava/awt/Component;)Ljava/awt/Component;
L69:    pop
L70:    aload_0
L71:    getfield Field passwordapp_de processingpage Ljava/awt/Panel;
L74:    iconst_0
L75:    invokevirtual Method java/awt/Component setVisible (Z)V
L78:    aload_0
L79:    aload_0
L80:    getfield Field passwordapp_de processingpage Ljava/awt/Panel;
L83:    invokevirtual Method java/awt/Container add (Ljava/awt/Component;)Ljava/awt/Component;
L86:    pop
L87:    aload_0
L88:    new java/awt/Panel
L91:    dup
L92:    aconst_null
L93:    invokespecial Method java/awt/Panel <init> (Ljava/awt/LayoutManager;)V
L96:    putfield Field passwordapp_de change_questions_success_page_active Ljava/awt/Panel;
L99:    aload_0
L100:   getfield Field passwordapp_de change_questions_success_page_active Ljava/awt/Panel;
L103:   aload_0
L104:   invokevirtual Method java/awt/Component getSize ()Ljava/awt/Dimension;
L107:   invokevirtual Method java/awt/Component setSize (Ljava/awt/Dimension;)V
L110:   aload_0
L111:   getfield Field passwordapp_de change_questions_success_page_active Ljava/awt/Panel;
L114:   aload_0
L115:   ldc "Ihre Sicherheitsfragen und -antworten sind auf dem neuesten"
L117:   bipush 30
L119:   aload_0
L120:   invokevirtual Method java/awt/Component getSize ()Ljava/awt/Dimension;
L123:   getfield Field java/awt/Dimension height I
L126:   iconst_2
L127:   idiv
L128:   bipush 10
L130:   isub
L131:   invokespecial Method passwordapp_de getLabel (Ljava/lang/String;II)Ljava/awt/Label;
L134:   invokevirtual Method java/awt/Container add (Ljava/awt/Component;)Ljava/awt/Component;
L137:   pop
L138:   aload_0
L139:   getfield Field passwordapp_de change_questions_success_page_active Ljava/awt/Panel;
L142:   aload_0
L143:   ldc "Stand und aktiviert worden. "
L145:   bipush 30
L147:   aload_0
L148:   invokevirtual Method java/awt/Component getSize ()Ljava/awt/Dimension;
L151:   getfield Field java/awt/Dimension height I
L154:   iconst_2
L155:   idiv
L156:   bipush 10
L158:   iadd
L159:   invokespecial Method passwordapp_de getLabel (Ljava/lang/String;II)Ljava/awt/Label;
L162:   invokevirtual Method java/awt/Container add (Ljava/awt/Component;)Ljava/awt/Component;
L165:   pop
L166:   aload_0
L167:   getfield Field passwordapp_de change_questions_success_page_active Ljava/awt/Panel;
L170:   iconst_0
L171:   invokevirtual Method java/awt/Component setVisible (Z)V
L174:   aload_0
L175:   aload_0
L176:   getfield Field passwordapp_de change_questions_success_page_active Ljava/awt/Panel;
L179:   invokevirtual Method java/awt/Container add (Ljava/awt/Component;)Ljava/awt/Component;
L182:   pop
L183:   aload_0
L184:   new java/awt/Panel
L187:   dup
L188:   aconst_null
L189:   invokespecial Method java/awt/Panel <init> (Ljava/awt/LayoutManager;)V
L192:   putfield Field passwordapp_de change_questions_success_page_pending Ljava/awt/Panel;
L195:   aload_0
L196:   getfield Field passwordapp_de change_questions_success_page_pending Ljava/awt/Panel;
L199:   aload_0
L200:   invokevirtual Method java/awt/Component getSize ()Ljava/awt/Dimension;
L203:   invokevirtual Method java/awt/Component setSize (Ljava/awt/Dimension;)V
L206:   aload_0
L207:   getfield Field passwordapp_de change_questions_success_page_pending Ljava/awt/Panel;
L210:   aload_0
L211:   ldc "Ihre Sicherheitsfragen und -antworten sind eingestellt worden."
L213:   bipush 30
L215:   aload_0
L216:   invokevirtual Method java/awt/Component getSize ()Ljava/awt/Dimension;
L219:   getfield Field java/awt/Dimension height I
L222:   iconst_2
L223:   idiv
L224:   bipush 10
L226:   isub
L227:   invokespecial Method passwordapp_de getLabel (Ljava/lang/String;II)Ljava/awt/Label;
L230:   invokevirtual Method java/awt/Container add (Ljava/awt/Component;)Ljava/awt/Component;
L233:   pop
L234:   aload_0
L235:   getfield Field passwordapp_de change_questions_success_page_pending Ljava/awt/Panel;
L238:   aload_0
L239:   ldc "In 14 Tagen werden sie aktiviert."
L241:   bipush 30
L243:   aload_0
L244:   invokevirtual Method java/awt/Component getSize ()Ljava/awt/Dimension;
L247:   getfield Field java/awt/Dimension height I
L250:   iconst_2
L251:   idiv
L252:   bipush 10
L254:   iadd
L255:   invokespecial Method passwordapp_de getLabel (Ljava/lang/String;II)Ljava/awt/Label;
L258:   invokevirtual Method java/awt/Container add (Ljava/awt/Component;)Ljava/awt/Component;
L261:   pop
L262:   aload_0
L263:   getfield Field passwordapp_de change_questions_success_page_pending Ljava/awt/Panel;
L266:   iconst_0
L267:   invokevirtual Method java/awt/Component setVisible (Z)V
L270:   aload_0
L271:   aload_0
L272:   getfield Field passwordapp_de change_questions_success_page_pending Ljava/awt/Panel;
L275:   invokevirtual Method java/awt/Container add (Ljava/awt/Component;)Ljava/awt/Component;
L278:   pop
L279:   aload_0
L280:   invokevirtual Method java/awt/Component getSize ()Ljava/awt/Dimension;
L283:   getfield Field java/awt/Dimension height I
L286:   iconst_2
L287:   idiv
L288:   bipush 50
L290:   isub
L291:   istore_2
L292:   aload_0
L293:   new java/awt/Panel
L296:   dup
L297:   aconst_null
L298:   invokespecial Method java/awt/Panel <init> (Ljava/awt/LayoutManager;)V
L301:   putfield Field passwordapp_de system_error_page Ljava/awt/Panel;
L304:   aload_0
L305:   getfield Field passwordapp_de system_error_page Ljava/awt/Panel;
L308:   aload_0
L309:   invokevirtual Method java/awt/Component getSize ()Ljava/awt/Dimension;
L312:   invokevirtual Method java/awt/Component setSize (Ljava/awt/Dimension;)V
L315:   aload_0
L316:   ldc "Bei der Bearbeitung Ihrer Anfrage ist ein Fehler aufgetreten."
L318:   bipush 55
L320:   iload_2
L321:   invokespecial Method passwordapp_de getLabel (Ljava/lang/String;II)Ljava/awt/Label;
L324:   astore_1
L325:   aload_1
L326:   new java/awt/Font
L329:   dup
L330:   ldc "Arial"
L332:   iconst_1
L333:   bipush 13
L335:   invokespecial Method java/awt/Font <init> (Ljava/lang/String;II)V
L338:   invokevirtual Method java/awt/Component setFont (Ljava/awt/Font;)V
L341:   aload_0
L342:   getfield Field passwordapp_de system_error_page Ljava/awt/Panel;
L345:   aload_1
L346:   invokevirtual Method java/awt/Container add (Ljava/awt/Component;)Ljava/awt/Component;
L349:   pop
L350:   aload_0
L351:   getfield Field passwordapp_de system_error_page Ljava/awt/Panel;
L354:   aload_0
L355:   ldc "Leider ist bei der Bearbeitung Ihrer Anfrage ein Fehler aufgetreten."
L357:   bipush 55
L359:   iload_2
L360:   bipush 30
L362:   iadd
L363:   invokespecial Method passwordapp_de getLabel (Ljava/lang/String;II)Ljava/awt/Label;
L366:   invokevirtual Method java/awt/Container add (Ljava/awt/Component;)Ljava/awt/Component;
L369:   pop
L370:   aload_0
L371:   getfield Field passwordapp_de system_error_page Ljava/awt/Panel;
L374:   aload_0
L375:   ldc "Bitte versuchen Sie es sp\u00E4ter noch einmal."
L377:   sipush 130
L380:   iload_2
L381:   bipush 50
L383:   iadd
L384:   invokespecial Method passwordapp_de getLabel (Ljava/lang/String;II)Ljava/awt/Label;
L387:   invokevirtual Method java/awt/Container add (Ljava/awt/Component;)Ljava/awt/Component;
L390:   pop
L391:   new java/awt/Button
L394:   dup
L395:   ldc "Gehen Sie zur\u00FCck und versuchen Sie es erneut."
L397:   invokespecial Method java/awt/Button <init> (Ljava/lang/String;)V
L400:   astore_3
L401:   aload_3
L402:   bipush 110
L404:   iload_2
L405:   bipush 80
L407:   iadd
L408:   sipush 300
L411:   bipush 22
L413:   invokevirtual Method java/awt/Component setBounds (IIII)V
L416:   aload_3
L417:   aload_0
L418:   invokevirtual Method java/awt/Button addActionListener (Ljava/awt/event/ActionListener;)V
L421:   aload_0
L422:   getfield Field passwordapp_de system_error_page Ljava/awt/Panel;
L425:   aload_3
L426:   invokevirtual Method java/awt/Container add (Ljava/awt/Component;)Ljava/awt/Component;
L429:   pop
L430:   aload_0
L431:   getfield Field passwordapp_de system_error_page Ljava/awt/Panel;
L434:   iconst_0
L435:   invokevirtual Method java/awt/Component setVisible (Z)V
L438:   aload_0
L439:   aload_0
L440:   getfield Field passwordapp_de system_error_page Ljava/awt/Panel;
L443:   invokevirtual Method java/awt/Container add (Ljava/awt/Component;)Ljava/awt/Component;
L446:   pop
L447:   aload_0
L448:   new java/awt/Panel
L451:   dup
L452:   aconst_null
L453:   invokespecial Method java/awt/Panel <init> (Ljava/awt/LayoutManager;)V
L456:   putfield Field passwordapp_de blocked_query_page Ljava/awt/Panel;
L459:   aload_0
L460:   getfield Field passwordapp_de blocked_query_page Ljava/awt/Panel;
L463:   aload_0
L464:   invokevirtual Method java/awt/Component getSize ()Ljava/awt/Dimension;
L467:   invokevirtual Method java/awt/Component setSize (Ljava/awt/Dimension;)V
L470:   aload_0
L471:   getfield Field passwordapp_de blocked_query_page Ljava/awt/Panel;
L474:   aload_0
L475:   ldc "Aufgrund vermehrter Probleme mit diesem Spielkonto ist es nicht mehr"
L477:   bipush 80
L479:   aload_0
L480:   invokevirtual Method java/awt/Component getSize ()Ljava/awt/Dimension;
L483:   getfield Field java/awt/Dimension height I
L486:   iconst_2
L487:   idiv
L488:   bipush 20
L490:   isub
L491:   invokespecial Method passwordapp_de getLabel (Ljava/lang/String;II)Ljava/awt/Label;
L494:   invokevirtual Method java/awt/Container add (Ljava/awt/Component;)Ljava/awt/Component;
L497:   pop
L498:   aload_0
L499:   getfield Field passwordapp_de blocked_query_page Ljava/awt/Panel;
L502:   aload_0
L503:   ldc "m\u00F6glich, Passwort-Anfragen f\u00FCr dieses Spielkonto zu bearbeiten."
L505:   bipush 95
L507:   aload_0
L508:   invokevirtual Method java/awt/Component getSize ()Ljava/awt/Dimension;
L511:   getfield Field java/awt/Dimension height I
L514:   iconst_2
L515:   idiv
L516:   invokespecial Method passwordapp_de getLabel (Ljava/lang/String;II)Ljava/awt/Label;
L519:   invokevirtual Method java/awt/Container add (Ljava/awt/Component;)Ljava/awt/Component;
L522:   pop
L523:   aload_0
L524:   getfield Field passwordapp_de blocked_query_page Ljava/awt/Panel;
L527:   iconst_0
L528:   invokevirtual Method java/awt/Component setVisible (Z)V
L531:   aload_0
L532:   aload_0
L533:   getfield Field passwordapp_de blocked_query_page Ljava/awt/Panel;
L536:   invokevirtual Method java/awt/Container add (Ljava/awt/Component;)Ljava/awt/Component;
L539:   pop
L540:   aload_0
L541:   new java/awt/Panel
L544:   dup
L545:   aconst_null
L546:   invokespecial Method java/awt/Panel <init> (Ljava/awt/LayoutManager;)V
L549:   putfield Field passwordapp_de blocked_attack_page Ljava/awt/Panel;
L552:   aload_0
L553:   getfield Field passwordapp_de blocked_attack_page Ljava/awt/Panel;
L556:   aload_0
L557:   invokevirtual Method java/awt/Component getSize ()Ljava/awt/Dimension;
L560:   invokevirtual Method java/awt/Component setSize (Ljava/awt/Dimension;)V
L563:   aload_0
L564:   getfield Field passwordapp_de blocked_attack_page Ljava/awt/Panel;
L567:   aload_0
L568:   ldc "Aufgrund wiederholter Versuche von Ihrer IP-Adresse, das Passwort"
L570:   bipush 80
L572:   aload_0
L573:   invokevirtual Method java/awt/Component getSize ()Ljava/awt/Dimension;
L576:   getfield Field java/awt/Dimension height I
L579:   iconst_2
L580:   idiv
L581:   bipush 40
L583:   isub
L584:   invokespecial Method passwordapp_de getLabel (Ljava/lang/String;II)Ljava/awt/Label;
L587:   invokevirtual Method java/awt/Container add (Ljava/awt/Component;)Ljava/awt/Component;
L590:   pop
L591:   aload_0
L592:   getfield Field passwordapp_de blocked_attack_page Ljava/awt/Panel;
L595:   aload_0
L596:   ldc "dieses Spielkontos zu \u00E4ndern, wurde Ihre Anfrage abgelehnt."
L598:   bipush 100
L600:   aload_0
L601:   invokevirtual Method java/awt/Component getSize ()Ljava/awt/Dimension;
L604:   getfield Field java/awt/Dimension height I
L607:   iconst_2
L608:   idiv
L609:   bipush 20
L611:   isub
L612:   invokespecial Method passwordapp_de getLabel (Ljava/lang/String;II)Ljava/awt/Label;
L615:   invokevirtual Method java/awt/Container add (Ljava/awt/Component;)Ljava/awt/Component;
L618:   pop
L619:   aload_0
L620:   getfield Field passwordapp_de blocked_attack_page Ljava/awt/Panel;
L623:   aload_0
L624:   ldc "Bitte versuchen Sie es sp\u00E4ter noch einmal."
L626:   sipush 150
L629:   aload_0
L630:   invokevirtual Method java/awt/Component getSize ()Ljava/awt/Dimension;
L633:   getfield Field java/awt/Dimension height I
L636:   iconst_2
L637:   idiv
L638:   invokespecial Method passwordapp_de getLabel (Ljava/lang/String;II)Ljava/awt/Label;
L641:   invokevirtual Method java/awt/Container add (Ljava/awt/Component;)Ljava/awt/Component;
L644:   pop
L645:   aload_0
L646:   getfield Field passwordapp_de blocked_attack_page Ljava/awt/Panel;
L649:   iconst_0
L650:   invokevirtual Method java/awt/Component setVisible (Z)V
L653:   aload_0
L654:   aload_0
L655:   getfield Field passwordapp_de blocked_attack_page Ljava/awt/Panel;
L658:   invokevirtual Method java/awt/Container add (Ljava/awt/Component;)Ljava/awt/Component;
L661:   pop
L662:   aload_0
L663:   invokevirtual Method java/awt/Component getSize ()Ljava/awt/Dimension;
L666:   getfield Field java/awt/Dimension height I
L669:   iconst_2
L670:   idiv
L671:   bipush 20
L673:   isub
L674:   istore_2
L675:   aload_0
L676:   new java/awt/Panel
L679:   dup
L680:   aconst_null
L681:   invokespecial Method java/awt/Panel <init> (Ljava/awt/LayoutManager;)V
L684:   putfield Field passwordapp_de wrongpassword_page Ljava/awt/Panel;
L687:   aload_0
L688:   getfield Field passwordapp_de wrongpassword_page Ljava/awt/Panel;
L691:   aload_0
L692:   invokevirtual Method java/awt/Component getSize ()Ljava/awt/Dimension;
L695:   invokevirtual Method java/awt/Component setSize (Ljava/awt/Dimension;)V
L698:   aload_0
L699:   getfield Field passwordapp_de wrongpassword_page Ljava/awt/Panel;
L702:   aload_0
L703:   ldc "Sie haben Ihr derzeitiges Passwort falsch eingegeben."
L705:   bipush 90
L707:   iload_2
L708:   invokespecial Method passwordapp_de getLabel (Ljava/lang/String;II)Ljava/awt/Label;
L711:   invokevirtual Method java/awt/Container add (Ljava/awt/Component;)Ljava/awt/Component;
L714:   pop
L715:   aload_0
L716:   getfield Field passwordapp_de wrongpassword_page Ljava/awt/Panel;
L719:   iconst_0
L720:   invokevirtual Method java/awt/Component setVisible (Z)V
L723:   new java/awt/Button
L726:   dup
L727:   ldc "Zur\u00FCck"
L729:   invokespecial Method java/awt/Button <init> (Ljava/lang/String;)V
L732:   astore_3
L733:   aload_3
L734:   sipush 150
L737:   iload_2
L738:   bipush 30
L740:   iadd
L741:   sipush 200
L744:   bipush 22
L746:   invokevirtual Method java/awt/Component setBounds (IIII)V
L749:   aload_3
L750:   aload_0
L751:   invokevirtual Method java/awt/Button addActionListener (Ljava/awt/event/ActionListener;)V
L754:   aload_0
L755:   getfield Field passwordapp_de wrongpassword_page Ljava/awt/Panel;
L758:   aload_3
L759:   invokevirtual Method java/awt/Container add (Ljava/awt/Component;)Ljava/awt/Component;
L762:   pop
L763:   aload_0
L764:   aload_0
L765:   getfield Field passwordapp_de wrongpassword_page Ljava/awt/Panel;
L768:   invokevirtual Method java/awt/Container add (Ljava/awt/Component;)Ljava/awt/Component;
L771:   pop
L772:   aload_0
L773:   new java/awt/Panel
L776:   dup
L777:   aconst_null
L778:   invokespecial Method java/awt/Panel <init> (Ljava/awt/LayoutManager;)V
L781:   putfield Field passwordapp_de change_questions_tooshort_page Ljava/awt/Panel;
L784:   aload_0
L785:   getfield Field passwordapp_de change_questions_tooshort_page Ljava/awt/Panel;
L788:   aload_0
L789:   invokevirtual Method java/awt/Component getSize ()Ljava/awt/Dimension;
L792:   invokevirtual Method java/awt/Component setSize (Ljava/awt/Dimension;)V
L795:   aload_0
L796:   getfield Field passwordapp_de change_questions_tooshort_page Ljava/awt/Panel;
L799:   aload_0
L800:   ldc "Eine oder mehrere Ihrer Fragen oder Antworten"
L802:   bipush 110
L804:   sipush 200
L807:   invokespecial Method passwordapp_de getLabel (Ljava/lang/String;II)Ljava/awt/Label;
L810:   invokevirtual Method java/awt/Container add (Ljava/awt/Component;)Ljava/awt/Component;
L813:   pop
L814:   aload_0
L815:   getfield Field passwordapp_de change_questions_tooshort_page Ljava/awt/Panel;
L818:   aload_0
L819:   ldc "waren zu kurz oder nicht vorhanden."
L821:   sipush 145
L824:   sipush 220
L827:   invokespecial Method passwordapp_de getLabel (Ljava/lang/String;II)Ljava/awt/Label;
L830:   invokevirtual Method java/awt/Container add (Ljava/awt/Component;)Ljava/awt/Component;
L833:   pop
L834:   aload_0
L835:   getfield Field passwordapp_de change_questions_tooshort_page Ljava/awt/Panel;
L838:   iconst_0
L839:   invokevirtual Method java/awt/Component setVisible (Z)V
L842:   new java/awt/Button
L845:   dup
L846:   ldc "Zur\u00FCck"
L848:   invokespecial Method java/awt/Button <init> (Ljava/lang/String;)V
L851:   astore_3
L852:   aload_3
L853:   sipush 150
L856:   sipush 250
L859:   sipush 200
L862:   bipush 22
L864:   invokevirtual Method java/awt/Component setBounds (IIII)V
L867:   aload_3
L868:   aload_0
L869:   invokevirtual Method java/awt/Button addActionListener (Ljava/awt/event/ActionListener;)V
L872:   aload_0
L873:   getfield Field passwordapp_de change_questions_tooshort_page Ljava/awt/Panel;
L876:   aload_3
L877:   invokevirtual Method java/awt/Container add (Ljava/awt/Component;)Ljava/awt/Component;
L880:   pop
L881:   aload_0
L882:   aload_0
L883:   getfield Field passwordapp_de change_questions_tooshort_page Ljava/awt/Panel;
L886:   invokevirtual Method java/awt/Container add (Ljava/awt/Component;)Ljava/awt/Component;
L889:   pop
L890:   aload_0
L891:   new java/awt/Panel
L894:   dup
L895:   aconst_null
L896:   invokespecial Method java/awt/Panel <init> (Ljava/awt/LayoutManager;)V
L899:   putfield Field passwordapp_de change_questions_samequestions_page Ljava/awt/Panel;
L902:   aload_0
L903:   getfield Field passwordapp_de change_questions_samequestions_page Ljava/awt/Panel;
L906:   aload_0
L907:   invokevirtual Method java/awt/Component getSize ()Ljava/awt/Dimension;
L910:   invokevirtual Method java/awt/Component setSize (Ljava/awt/Dimension;)V
L913:   aload_0
L914:   getfield Field passwordapp_de change_questions_samequestions_page Ljava/awt/Panel;
L917:   aload_0
L918:   ldc "Zwei oder mehr der von Ihnen eingestellten Fragen waren"
L920:   bipush 80
L922:   sipush 200
L925:   invokespecial Method passwordapp_de getLabel (Ljava/lang/String;II)Ljava/awt/Label;
L928:   invokevirtual Method java/awt/Container add (Ljava/awt/Component;)Ljava/awt/Component;
L931:   pop
L932:   aload_0
L933:   getfield Field passwordapp_de change_questions_samequestions_page Ljava/awt/Panel;
L936:   aload_0
L937:   ldc "identisch. Bitte w\u00E4hlen Sie unterschiedliche Fragen."
L939:   bipush 100
L941:   sipush 220
L944:   invokespecial Method passwordapp_de getLabel (Ljava/lang/String;II)Ljava/awt/Label;
L947:   invokevirtual Method java/awt/Container add (Ljava/awt/Component;)Ljava/awt/Component;
L950:   pop
L951:   aload_0
L952:   getfield Field passwordapp_de change_questions_samequestions_page Ljava/awt/Panel;
L955:   iconst_0
L956:   invokevirtual Method java/awt/Component setVisible (Z)V
L959:   new java/awt/Button
L962:   dup
L963:   ldc "Zur\u00FCck"
L965:   invokespecial Method java/awt/Button <init> (Ljava/lang/String;)V
L968:   astore_3
L969:   aload_3
L970:   sipush 150
L973:   sipush 250
L976:   sipush 200
L979:   bipush 22
L981:   invokevirtual Method java/awt/Component setBounds (IIII)V
L984:   aload_3
L985:   aload_0
L986:   invokevirtual Method java/awt/Button addActionListener (Ljava/awt/event/ActionListener;)V
L989:   aload_0
L990:   getfield Field passwordapp_de change_questions_samequestions_page Ljava/awt/Panel;
L993:   aload_3
L994:   invokevirtual Method java/awt/Container add (Ljava/awt/Component;)Ljava/awt/Component;
L997:   pop
L998:   aload_0
L999:   aload_0
L1000:  getfield Field passwordapp_de change_questions_samequestions_page Ljava/awt/Panel;
L1003:  invokevirtual Method java/awt/Container add (Ljava/awt/Component;)Ljava/awt/Component;
L1006:  pop
L1007:  aload_0
L1008:  new java/awt/Panel
L1011:  dup
L1012:  aconst_null
L1013:  invokespecial Method java/awt/Panel <init> (Ljava/awt/LayoutManager;)V
L1016:  putfield Field passwordapp_de change_questions_sameanswers_page Ljava/awt/Panel;
L1019:  aload_0
L1020:  getfield Field passwordapp_de change_questions_sameanswers_page Ljava/awt/Panel;
L1023:  aload_0
L1024:  invokevirtual Method java/awt/Component getSize ()Ljava/awt/Dimension;
L1027:  invokevirtual Method java/awt/Component setSize (Ljava/awt/Dimension;)V
L1030:  aload_0
L1031:  getfield Field passwordapp_de change_questions_sameanswers_page Ljava/awt/Panel;
L1034:  aload_0
L1035:  ldc "Zwei oder mehr der von Ihnen eingetragenen Antworten waren"
L1037:  bipush 70
L1039:  sipush 200
L1042:  invokespecial Method passwordapp_de getLabel (Ljava/lang/String;II)Ljava/awt/Label;
L1045:  invokevirtual Method java/awt/Container add (Ljava/awt/Component;)Ljava/awt/Component;
L1048:  pop
L1049:  aload_0
L1050:  getfield Field passwordapp_de change_questions_sameanswers_page Ljava/awt/Panel;
L1053:  aload_0
L1054:  ldc "identisch. Bitte w\u00E4hlen Sie unterschiedliche Antworten."
L1056:  bipush 90
L1058:  sipush 220
L1061:  invokespecial Method passwordapp_de getLabel (Ljava/lang/String;II)Ljava/awt/Label;
L1064:  invokevirtual Method java/awt/Container add (Ljava/awt/Component;)Ljava/awt/Component;
L1067:  pop
L1068:  aload_0
L1069:  getfield Field passwordapp_de change_questions_sameanswers_page Ljava/awt/Panel;
L1072:  iconst_0
L1073:  invokevirtual Method java/awt/Component setVisible (Z)V
L1076:  new java/awt/Button
L1079:  dup
L1080:  ldc "Zur\u00FCck"
L1082:  invokespecial Method java/awt/Button <init> (Ljava/lang/String;)V
L1085:  astore_3
L1086:  aload_3
L1087:  sipush 150
L1090:  sipush 250
L1093:  sipush 200
L1096:  bipush 22
L1098:  invokevirtual Method java/awt/Component setBounds (IIII)V
L1101:  aload_3
L1102:  aload_0
L1103:  invokevirtual Method java/awt/Button addActionListener (Ljava/awt/event/ActionListener;)V
L1106:  aload_0
L1107:  getfield Field passwordapp_de change_questions_sameanswers_page Ljava/awt/Panel;
L1110:  aload_3
L1111:  invokevirtual Method java/awt/Container add (Ljava/awt/Component;)Ljava/awt/Component;
L1114:  pop
L1115:  aload_0
L1116:  aload_0
L1117:  getfield Field passwordapp_de change_questions_sameanswers_page Ljava/awt/Panel;
L1120:  invokevirtual Method java/awt/Container add (Ljava/awt/Component;)Ljava/awt/Component;
L1123:  pop
L1124:  aload_0
L1125:  new java/awt/Panel
L1128:  dup
L1129:  aconst_null
L1130:  invokespecial Method java/awt/Panel <init> (Ljava/awt/LayoutManager;)V
L1133:  putfield Field passwordapp_de change_questions_qandamatch_page Ljava/awt/Panel;
L1136:  aload_0
L1137:  getfield Field passwordapp_de change_questions_qandamatch_page Ljava/awt/Panel;
L1140:  aload_0
L1141:  invokevirtual Method java/awt/Component getSize ()Ljava/awt/Dimension;
L1144:  invokevirtual Method java/awt/Component setSize (Ljava/awt/Dimension;)V
L1147:  aload_0
L1148:  getfield Field passwordapp_de change_questions_qandamatch_page Ljava/awt/Panel;
L1151:  aload_0
L1152:  ldc "Eine oder mehrere Ihrer Fragen hat den gleichen Wortlaut"
L1154:  bipush 120
L1156:  sipush 200
L1159:  invokespecial Method passwordapp_de getLabel (Ljava/lang/String;II)Ljava/awt/Label;
L1162:  invokevirtual Method java/awt/Container add (Ljava/awt/Component;)Ljava/awt/Component;
L1165:  pop
L1166:  aload_0
L1167:  getfield Field passwordapp_de change_questions_qandamatch_page Ljava/awt/Panel;
L1170:  aload_0
L1171:  ldc "wie eine der Antworten, die Sie angegeben haben."
L1173:  sipush 130
L1176:  sipush 220
L1179:  invokespecial Method passwordapp_de getLabel (Ljava/lang/String;II)Ljava/awt/Label;
L1182:  invokevirtual Method java/awt/Container add (Ljava/awt/Component;)Ljava/awt/Component;
L1185:  pop
L1186:  aload_0
L1187:  getfield Field passwordapp_de change_questions_qandamatch_page Ljava/awt/Panel;
L1190:  aload_0
L1191:  ldc "Bitte achten Sie darauf, dass die die Antworten"
L1193:  sipush 130
L1196:  sipush 240
L1199:  invokespecial Method passwordapp_de getLabel (Ljava/lang/String;II)Ljava/awt/Label;
L1202:  invokevirtual Method java/awt/Container add (Ljava/awt/Component;)Ljava/awt/Component;
L1205:  pop
L1206:  aload_0
L1207:  getfield Field passwordapp_de change_questions_qandamatch_page Ljava/awt/Panel;
L1210:  aload_0
L1211:  ldc "nicht genauso wie die Fragen lauten."
L1213:  sipush 130
L1216:  sipush 260
L1219:  invokespecial Method passwordapp_de getLabel (Ljava/lang/String;II)Ljava/awt/Label;
L1222:  invokevirtual Method java/awt/Container add (Ljava/awt/Component;)Ljava/awt/Component;
L1225:  pop
L1226:  aload_0
L1227:  getfield Field passwordapp_de change_questions_qandamatch_page Ljava/awt/Panel;
L1230:  iconst_0
L1231:  invokevirtual Method java/awt/Component setVisible (Z)V
L1234:  new java/awt/Button
L1237:  dup
L1238:  ldc "Zur\u00FCck"
L1240:  invokespecial Method java/awt/Button <init> (Ljava/lang/String;)V
L1243:  astore_3
L1244:  aload_3
L1245:  sipush 150
L1248:  sipush 290
L1251:  sipush 200
L1254:  bipush 22
L1256:  invokevirtual Method java/awt/Component setBounds (IIII)V
L1259:  aload_3
L1260:  aload_0
L1261:  invokevirtual Method java/awt/Button addActionListener (Ljava/awt/event/ActionListener;)V
L1264:  aload_0
L1265:  getfield Field passwordapp_de change_questions_qandamatch_page Ljava/awt/Panel;
L1268:  aload_3
L1269:  invokevirtual Method java/awt/Container add (Ljava/awt/Component;)Ljava/awt/Component;
L1272:  pop
L1273:  aload_0
L1274:  aload_0
L1275:  getfield Field passwordapp_de change_questions_qandamatch_page Ljava/awt/Panel;
L1278:  invokevirtual Method java/awt/Container add (Ljava/awt/Component;)Ljava/awt/Component;
L1281:  pop
L1282:  return
L1283:  
        .linenumbertable
            L0 75
            L12 76
            L23 77
            L45 78
            L61 79
            L70 80
            L78 81
            L87 84
            L99 85
            L110 86
            L138 87
            L166 88
            L174 89
            L183 91
            L195 92
            L206 93
            L234 94
            L262 95
            L270 96
            L279 99
            L292 100
            L304 101
            L315 102
            L325 103
            L341 104
            L350 105
            L370 106
            L391 107
            L401 108
            L416 109
            L421 110
            L430 111
            L438 112
            L447 114
            L459 115
            L470 116
            L498 117
            L523 118
            L531 119
            L540 123
            L552 124
            L563 125
            L591 126
            L619 127
            L645 128
            L653 129
            L662 132
            L675 133
            L687 134
            L698 135
            L715 136
            L723 137
            L733 138
            L749 139
            L754 140
            L763 141
            L772 144
            L784 145
            L795 146
            L814 147
            L834 148
            L842 149
            L852 150
            L867 151
            L872 152
            L881 153
            L890 156
            L902 157
            L913 158
            L932 159
            L951 160
            L959 161
            L969 162
            L984 163
            L989 164
            L998 165
            L1007 168
            L1019 169
            L1030 170
            L1049 171
            L1068 172
            L1076 173
            L1086 174
            L1101 175
            L1106 176
            L1115 177
            L1124 179
            L1136 180
            L1147 181
            L1166 182
            L1186 183
            L1206 184
            L1226 185
            L1234 186
            L1244 187
            L1259 188
            L1264 189
            L1273 190
            L1282 74
        .end linenumbertable
    .end code
.end method

.method private init_change_questions : ()V
    .code stack 9 locals 5
L0:     aload_0
L1:     new java/awt/Panel
L4:     dup
L5:     aconst_null
L6:     invokespecial Method java/awt/Panel <init> (Ljava/awt/LayoutManager;)V
L9:     putfield Field passwordapp_de change_questions_page Ljava/awt/Panel;
L12:    bipush 100
L14:    istore_1
L15:    aload_0
L16:    aload_0
L17:    bipush 20
L19:    sipush 150
L22:    iconst_0
L23:    sipush 150
L26:    bipush 20
L28:    iconst_1
L29:    invokespecial Method passwordapp_de getTextField (IIIIIZ)Ljava/awt/TextField;
L32:    putfield Field passwordapp_de password1 Ljava/awt/TextField;
L35:    aload_0
L36:    getfield Field passwordapp_de question [Ljava/awt/TextField;
L39:    iconst_0
L40:    aload_0
L41:    bipush 40
L43:    iload_1
L44:    bipush 70
L46:    sipush 250
L49:    bipush 20
L51:    iconst_0
L52:    invokespecial Method passwordapp_de getTextField (IIIIIZ)Ljava/awt/TextField;
L55:    aastore
L56:    aload_0
L57:    getfield Field passwordapp_de question [Ljava/awt/TextField;
L60:    iconst_0
L61:    aaload
L62:    aload_0
L63:    getfield Field passwordapp_de example_questions [Ljava/lang/String;
L66:    iconst_0
L67:    aaload
L68:    invokevirtual Method java/awt/TextComponent setText (Ljava/lang/String;)V
L71:    aload_0
L72:    getfield Field passwordapp_de recov [Ljava/awt/TextField;
L75:    iconst_0
L76:    aload_0
L77:    bipush 40
L79:    iload_1
L80:    bipush 100
L82:    sipush 250
L85:    bipush 20
L87:    iconst_1
L88:    invokespecial Method passwordapp_de getTextField (IIIIIZ)Ljava/awt/TextField;
L91:    aastore
L92:    aload_0
L93:    getfield Field passwordapp_de question [Ljava/awt/TextField;
L96:    iconst_1
L97:    aload_0
L98:    bipush 40
L100:   iload_1
L101:   sipush 170
L104:   sipush 250
L107:   bipush 20
L109:   iconst_0
L110:   invokespecial Method passwordapp_de getTextField (IIIIIZ)Ljava/awt/TextField;
L113:   aastore
L114:   aload_0
L115:   getfield Field passwordapp_de question [Ljava/awt/TextField;
L118:   iconst_1
L119:   aaload
L120:   aload_0
L121:   getfield Field passwordapp_de example_questions [Ljava/lang/String;
L124:   iconst_1
L125:   aaload
L126:   invokevirtual Method java/awt/TextComponent setText (Ljava/lang/String;)V
L129:   aload_0
L130:   getfield Field passwordapp_de recov [Ljava/awt/TextField;
L133:   iconst_1
L134:   aload_0
L135:   bipush 40
L137:   iload_1
L138:   sipush 200
L141:   sipush 250
L144:   bipush 20
L146:   iconst_1
L147:   invokespecial Method passwordapp_de getTextField (IIIIIZ)Ljava/awt/TextField;
L150:   aastore
L151:   aload_0
L152:   getfield Field passwordapp_de question [Ljava/awt/TextField;
L155:   iconst_2
L156:   aload_0
L157:   bipush 40
L159:   iload_1
L160:   sipush 270
L163:   sipush 250
L166:   bipush 20
L168:   iconst_0
L169:   invokespecial Method passwordapp_de getTextField (IIIIIZ)Ljava/awt/TextField;
L172:   aastore
L173:   aload_0
L174:   getfield Field passwordapp_de question [Ljava/awt/TextField;
L177:   iconst_2
L178:   aaload
L179:   aload_0
L180:   getfield Field passwordapp_de example_questions [Ljava/lang/String;
L183:   iconst_2
L184:   aaload
L185:   invokevirtual Method java/awt/TextComponent setText (Ljava/lang/String;)V
L188:   aload_0
L189:   getfield Field passwordapp_de recov [Ljava/awt/TextField;
L192:   iconst_2
L193:   aload_0
L194:   bipush 40
L196:   iload_1
L197:   sipush 300
L200:   sipush 250
L203:   bipush 20
L205:   iconst_1
L206:   invokespecial Method passwordapp_de getTextField (IIIIIZ)Ljava/awt/TextField;
L209:   aastore
L210:   aload_0
L211:   getfield Field passwordapp_de question [Ljava/awt/TextField;
L214:   iconst_3
L215:   aload_0
L216:   bipush 40
L218:   iload_1
L219:   sipush 370
L222:   sipush 250
L225:   bipush 20
L227:   iconst_0
L228:   invokespecial Method passwordapp_de getTextField (IIIIIZ)Ljava/awt/TextField;
L231:   aastore
L232:   aload_0
L233:   getfield Field passwordapp_de question [Ljava/awt/TextField;
L236:   iconst_3
L237:   aaload
L238:   aload_0
L239:   getfield Field passwordapp_de example_questions [Ljava/lang/String;
L242:   iconst_3
L243:   aaload
L244:   invokevirtual Method java/awt/TextComponent setText (Ljava/lang/String;)V
L247:   aload_0
L248:   getfield Field passwordapp_de recov [Ljava/awt/TextField;
L251:   iconst_3
L252:   aload_0
L253:   bipush 40
L255:   iload_1
L256:   sipush 400
L259:   sipush 250
L262:   bipush 20
L264:   iconst_1
L265:   invokespecial Method passwordapp_de getTextField (IIIIIZ)Ljava/awt/TextField;
L268:   aastore
L269:   aload_0
L270:   getfield Field passwordapp_de question [Ljava/awt/TextField;
L273:   iconst_4
L274:   aload_0
L275:   bipush 40
L277:   iload_1
L278:   sipush 470
L281:   sipush 250
L284:   bipush 20
L286:   iconst_0
L287:   invokespecial Method passwordapp_de getTextField (IIIIIZ)Ljava/awt/TextField;
L290:   aastore
L291:   aload_0
L292:   getfield Field passwordapp_de question [Ljava/awt/TextField;
L295:   iconst_4
L296:   aaload
L297:   aload_0
L298:   getfield Field passwordapp_de example_questions [Ljava/lang/String;
L301:   iconst_4
L302:   aaload
L303:   invokevirtual Method java/awt/TextComponent setText (Ljava/lang/String;)V
L306:   aload_0
L307:   getfield Field passwordapp_de recov [Ljava/awt/TextField;
L310:   iconst_4
L311:   aload_0
L312:   bipush 40
L314:   iload_1
L315:   sipush 500
L318:   sipush 250
L321:   bipush 20
L323:   iconst_1
L324:   invokespecial Method passwordapp_de getTextField (IIIIIZ)Ljava/awt/TextField;
L327:   aastore
L328:   aload_0
L329:   getfield Field passwordapp_de change_questions_page Ljava/awt/Panel;
L332:   getstatic Field java/awt/Color black Ljava/awt/Color;
L335:   invokevirtual Method java/awt/Component setBackground (Ljava/awt/Color;)V
L338:   aload_0
L339:   getfield Field passwordapp_de change_questions_page Ljava/awt/Panel;
L342:   aload_0
L343:   ldc "Momentanes Passwort:"
L345:   iconst_0
L346:   iconst_0
L347:   sipush 150
L350:   bipush 20
L352:   invokespecial Method passwordapp_de getLabel (Ljava/lang/String;IIII)Ljava/awt/Label;
L355:   invokevirtual Method java/awt/Container add (Ljava/awt/Component;)Ljava/awt/Component;
L358:   pop
L359:   aload_0
L360:   getfield Field passwordapp_de change_questions_page Ljava/awt/Panel;
L363:   aload_0
L364:   getfield Field passwordapp_de password1 Ljava/awt/TextField;
L367:   invokevirtual Method java/awt/Container add (Ljava/awt/Component;)Ljava/awt/Component;
L370:   pop
L371:   aload_0
L372:   ldc "Sicherheitsfrage 1"
L374:   iconst_0
L375:   bipush 40
L377:   invokespecial Method passwordapp_de getLabel (Ljava/lang/String;II)Ljava/awt/Label;
L380:   astore_2
L381:   aload_2
L382:   new java/awt/Font
L385:   dup
L386:   ldc "Arial"
L388:   iconst_1
L389:   bipush 13
L391:   invokespecial Method java/awt/Font <init> (Ljava/lang/String;II)V
L394:   invokevirtual Method java/awt/Component setFont (Ljava/awt/Font;)V
L397:   aload_0
L398:   getfield Field passwordapp_de change_questions_page Ljava/awt/Panel;
L401:   aload_2
L402:   invokevirtual Method java/awt/Container add (Ljava/awt/Component;)Ljava/awt/Component;
L405:   pop
L406:   aload_0
L407:   getfield Field passwordapp_de change_questions_page Ljava/awt/Panel;
L410:   aload_0
L411:   ldc "Frage:"
L413:   iconst_0
L414:   bipush 70
L416:   bipush 100
L418:   bipush 20
L420:   invokespecial Method passwordapp_de getLabel (Ljava/lang/String;IIII)Ljava/awt/Label;
L423:   invokevirtual Method java/awt/Container add (Ljava/awt/Component;)Ljava/awt/Component;
L426:   pop
L427:   aload_0
L428:   getfield Field passwordapp_de change_questions_page Ljava/awt/Panel;
L431:   aload_0
L432:   getfield Field passwordapp_de question [Ljava/awt/TextField;
L435:   iconst_0
L436:   aaload
L437:   invokevirtual Method java/awt/Container add (Ljava/awt/Component;)Ljava/awt/Component;
L440:   pop
L441:   new java/awt/Button
L444:   dup
L445:   ldc "Neue Frage:"
L447:   invokespecial Method java/awt/Button <init> (Ljava/lang/String;)V
L450:   astore_3
L451:   aload_3
L452:   ldc "NEWRQ1"
L454:   invokevirtual Method java/awt/Button setActionCommand (Ljava/lang/String;)V
L457:   aload_3
L458:   sipush 360
L461:   bipush 70
L463:   sipush 140
L466:   bipush 22
L468:   invokevirtual Method java/awt/Component setBounds (IIII)V
L471:   aload_3
L472:   aload_0
L473:   invokevirtual Method java/awt/Button addActionListener (Ljava/awt/event/ActionListener;)V
L476:   aload_0
L477:   getfield Field passwordapp_de change_questions_page Ljava/awt/Panel;
L480:   aload_3
L481:   invokevirtual Method java/awt/Container add (Ljava/awt/Component;)Ljava/awt/Component;
L484:   pop
L485:   aload_0
L486:   getfield Field passwordapp_de change_questions_page Ljava/awt/Panel;
L489:   aload_0
L490:   ldc "Antwort:"
L492:   iconst_0
L493:   bipush 100
L495:   bipush 100
L497:   bipush 20
L499:   invokespecial Method passwordapp_de getLabel (Ljava/lang/String;IIII)Ljava/awt/Label;
L502:   invokevirtual Method java/awt/Container add (Ljava/awt/Component;)Ljava/awt/Component;
L505:   pop
L506:   aload_0
L507:   getfield Field passwordapp_de change_questions_page Ljava/awt/Panel;
L510:   aload_0
L511:   getfield Field passwordapp_de recov [Ljava/awt/TextField;
L514:   iconst_0
L515:   aaload
L516:   invokevirtual Method java/awt/Container add (Ljava/awt/Component;)Ljava/awt/Component;
L519:   pop
L520:   aload_0
L521:   ldc "Sicherheitsfrage 2"
L523:   iconst_0
L524:   sipush 140
L527:   invokespecial Method passwordapp_de getLabel (Ljava/lang/String;II)Ljava/awt/Label;
L530:   astore_2
L531:   aload_2
L532:   new java/awt/Font
L535:   dup
L536:   ldc "Arial"
L538:   iconst_1
L539:   bipush 13
L541:   invokespecial Method java/awt/Font <init> (Ljava/lang/String;II)V
L544:   invokevirtual Method java/awt/Component setFont (Ljava/awt/Font;)V
L547:   aload_0
L548:   getfield Field passwordapp_de change_questions_page Ljava/awt/Panel;
L551:   aload_2
L552:   invokevirtual Method java/awt/Container add (Ljava/awt/Component;)Ljava/awt/Component;
L555:   pop
L556:   aload_0
L557:   getfield Field passwordapp_de change_questions_page Ljava/awt/Panel;
L560:   aload_0
L561:   ldc "Frage:"
L563:   iconst_0
L564:   sipush 170
L567:   bipush 100
L569:   bipush 20
L571:   invokespecial Method passwordapp_de getLabel (Ljava/lang/String;IIII)Ljava/awt/Label;
L574:   invokevirtual Method java/awt/Container add (Ljava/awt/Component;)Ljava/awt/Component;
L577:   pop
L578:   aload_0
L579:   getfield Field passwordapp_de change_questions_page Ljava/awt/Panel;
L582:   aload_0
L583:   getfield Field passwordapp_de question [Ljava/awt/TextField;
L586:   iconst_1
L587:   aaload
L588:   invokevirtual Method java/awt/Container add (Ljava/awt/Component;)Ljava/awt/Component;
L591:   pop
L592:   new java/awt/Button
L595:   dup
L596:   ldc "Neue Frage:"
L598:   invokespecial Method java/awt/Button <init> (Ljava/lang/String;)V
L601:   astore_3
L602:   aload_3
L603:   ldc "NEWRQ2"
L605:   invokevirtual Method java/awt/Button setActionCommand (Ljava/lang/String;)V
L608:   aload_3
L609:   sipush 360
L612:   sipush 170
L615:   sipush 140
L618:   bipush 22
L620:   invokevirtual Method java/awt/Component setBounds (IIII)V
L623:   aload_3
L624:   aload_0
L625:   invokevirtual Method java/awt/Button addActionListener (Ljava/awt/event/ActionListener;)V
L628:   aload_0
L629:   getfield Field passwordapp_de change_questions_page Ljava/awt/Panel;
L632:   aload_3
L633:   invokevirtual Method java/awt/Container add (Ljava/awt/Component;)Ljava/awt/Component;
L636:   pop
L637:   aload_0
L638:   getfield Field passwordapp_de change_questions_page Ljava/awt/Panel;
L641:   aload_0
L642:   ldc "Antwort:"
L644:   iconst_0
L645:   sipush 200
L648:   bipush 100
L650:   bipush 20
L652:   invokespecial Method passwordapp_de getLabel (Ljava/lang/String;IIII)Ljava/awt/Label;
L655:   invokevirtual Method java/awt/Container add (Ljava/awt/Component;)Ljava/awt/Component;
L658:   pop
L659:   aload_0
L660:   getfield Field passwordapp_de change_questions_page Ljava/awt/Panel;
L663:   aload_0
L664:   getfield Field passwordapp_de recov [Ljava/awt/TextField;
L667:   iconst_1
L668:   aaload
L669:   invokevirtual Method java/awt/Container add (Ljava/awt/Component;)Ljava/awt/Component;
L672:   pop
L673:   aload_0
L674:   ldc "Sicherheitsfrage 3"
L676:   iconst_0
L677:   sipush 240
L680:   invokespecial Method passwordapp_de getLabel (Ljava/lang/String;II)Ljava/awt/Label;
L683:   astore_2
L684:   aload_2
L685:   new java/awt/Font
L688:   dup
L689:   ldc "Arial"
L691:   iconst_1
L692:   bipush 13
L694:   invokespecial Method java/awt/Font <init> (Ljava/lang/String;II)V
L697:   invokevirtual Method java/awt/Component setFont (Ljava/awt/Font;)V
L700:   aload_0
L701:   getfield Field passwordapp_de change_questions_page Ljava/awt/Panel;
L704:   aload_2
L705:   invokevirtual Method java/awt/Container add (Ljava/awt/Component;)Ljava/awt/Component;
L708:   pop
L709:   aload_0
L710:   getfield Field passwordapp_de change_questions_page Ljava/awt/Panel;
L713:   aload_0
L714:   ldc "Frage:"
L716:   iconst_0
L717:   sipush 270
L720:   bipush 100
L722:   bipush 20
L724:   invokespecial Method passwordapp_de getLabel (Ljava/lang/String;IIII)Ljava/awt/Label;
L727:   invokevirtual Method java/awt/Container add (Ljava/awt/Component;)Ljava/awt/Component;
L730:   pop
L731:   aload_0
L732:   getfield Field passwordapp_de change_questions_page Ljava/awt/Panel;
L735:   aload_0
L736:   getfield Field passwordapp_de question [Ljava/awt/TextField;
L739:   iconst_2
L740:   aaload
L741:   invokevirtual Method java/awt/Container add (Ljava/awt/Component;)Ljava/awt/Component;
L744:   pop
L745:   new java/awt/Button
L748:   dup
L749:   ldc "Neue Frage:"
L751:   invokespecial Method java/awt/Button <init> (Ljava/lang/String;)V
L754:   astore_3
L755:   aload_3
L756:   ldc "NEWRQ3"
L758:   invokevirtual Method java/awt/Button setActionCommand (Ljava/lang/String;)V
L761:   aload_3
L762:   sipush 360
L765:   sipush 270
L768:   sipush 140
L771:   bipush 22
L773:   invokevirtual Method java/awt/Component setBounds (IIII)V
L776:   aload_3
L777:   aload_0
L778:   invokevirtual Method java/awt/Button addActionListener (Ljava/awt/event/ActionListener;)V
L781:   aload_0
L782:   getfield Field passwordapp_de change_questions_page Ljava/awt/Panel;
L785:   aload_3
L786:   invokevirtual Method java/awt/Container add (Ljava/awt/Component;)Ljava/awt/Component;
L789:   pop
L790:   aload_0
L791:   getfield Field passwordapp_de change_questions_page Ljava/awt/Panel;
L794:   aload_0
L795:   ldc "Antwort:"
L797:   iconst_0
L798:   sipush 300
L801:   bipush 100
L803:   bipush 20
L805:   invokespecial Method passwordapp_de getLabel (Ljava/lang/String;IIII)Ljava/awt/Label;
L808:   invokevirtual Method java/awt/Container add (Ljava/awt/Component;)Ljava/awt/Component;
L811:   pop
L812:   aload_0
L813:   getfield Field passwordapp_de change_questions_page Ljava/awt/Panel;
L816:   aload_0
L817:   getfield Field passwordapp_de recov [Ljava/awt/TextField;
L820:   iconst_2
L821:   aaload
L822:   invokevirtual Method java/awt/Container add (Ljava/awt/Component;)Ljava/awt/Component;
L825:   pop
L826:   aload_0
L827:   ldc "Sicherheitsfrage 4"
L829:   iconst_0
L830:   sipush 340
L833:   invokespecial Method passwordapp_de getLabel (Ljava/lang/String;II)Ljava/awt/Label;
L836:   astore_2
L837:   aload_2
L838:   new java/awt/Font
L841:   dup
L842:   ldc "Arial"
L844:   iconst_1
L845:   bipush 13
L847:   invokespecial Method java/awt/Font <init> (Ljava/lang/String;II)V
L850:   invokevirtual Method java/awt/Component setFont (Ljava/awt/Font;)V
L853:   aload_0
L854:   getfield Field passwordapp_de change_questions_page Ljava/awt/Panel;
L857:   aload_2
L858:   invokevirtual Method java/awt/Container add (Ljava/awt/Component;)Ljava/awt/Component;
L861:   pop
L862:   aload_0
L863:   getfield Field passwordapp_de change_questions_page Ljava/awt/Panel;
L866:   aload_0
L867:   ldc "Frage:"
L869:   iconst_0
L870:   sipush 370
L873:   bipush 100
L875:   bipush 20
L877:   invokespecial Method passwordapp_de getLabel (Ljava/lang/String;IIII)Ljava/awt/Label;
L880:   invokevirtual Method java/awt/Container add (Ljava/awt/Component;)Ljava/awt/Component;
L883:   pop
L884:   aload_0
L885:   getfield Field passwordapp_de change_questions_page Ljava/awt/Panel;
L888:   aload_0
L889:   getfield Field passwordapp_de question [Ljava/awt/TextField;
L892:   iconst_3
L893:   aaload
L894:   invokevirtual Method java/awt/Container add (Ljava/awt/Component;)Ljava/awt/Component;
L897:   pop
L898:   new java/awt/Button
L901:   dup
L902:   ldc "Neue Frage:"
L904:   invokespecial Method java/awt/Button <init> (Ljava/lang/String;)V
L907:   astore_3
L908:   aload_3
L909:   ldc "NEWRQ4"
L911:   invokevirtual Method java/awt/Button setActionCommand (Ljava/lang/String;)V
L914:   aload_3
L915:   sipush 360
L918:   sipush 370
L921:   sipush 140
L924:   bipush 22
L926:   invokevirtual Method java/awt/Component setBounds (IIII)V
L929:   aload_3
L930:   aload_0
L931:   invokevirtual Method java/awt/Button addActionListener (Ljava/awt/event/ActionListener;)V
L934:   aload_0
L935:   getfield Field passwordapp_de change_questions_page Ljava/awt/Panel;
L938:   aload_3
L939:   invokevirtual Method java/awt/Container add (Ljava/awt/Component;)Ljava/awt/Component;
L942:   pop
L943:   aload_0
L944:   getfield Field passwordapp_de change_questions_page Ljava/awt/Panel;
L947:   aload_0
L948:   ldc "Antwort:"
L950:   iconst_0
L951:   sipush 400
L954:   bipush 100
L956:   bipush 20
L958:   invokespecial Method passwordapp_de getLabel (Ljava/lang/String;IIII)Ljava/awt/Label;
L961:   invokevirtual Method java/awt/Container add (Ljava/awt/Component;)Ljava/awt/Component;
L964:   pop
L965:   aload_0
L966:   getfield Field passwordapp_de change_questions_page Ljava/awt/Panel;
L969:   aload_0
L970:   getfield Field passwordapp_de recov [Ljava/awt/TextField;
L973:   iconst_3
L974:   aaload
L975:   invokevirtual Method java/awt/Container add (Ljava/awt/Component;)Ljava/awt/Component;
L978:   pop
L979:   aload_0
L980:   ldc "Sicherheitsfrage 5"
L982:   iconst_0
L983:   sipush 440
L986:   invokespecial Method passwordapp_de getLabel (Ljava/lang/String;II)Ljava/awt/Label;
L989:   astore_2
L990:   aload_2
L991:   new java/awt/Font
L994:   dup
L995:   ldc "Arial"
L997:   iconst_1
L998:   bipush 13
L1000:  invokespecial Method java/awt/Font <init> (Ljava/lang/String;II)V
L1003:  invokevirtual Method java/awt/Component setFont (Ljava/awt/Font;)V
L1006:  aload_0
L1007:  getfield Field passwordapp_de change_questions_page Ljava/awt/Panel;
L1010:  aload_2
L1011:  invokevirtual Method java/awt/Container add (Ljava/awt/Component;)Ljava/awt/Component;
L1014:  pop
L1015:  aload_0
L1016:  getfield Field passwordapp_de change_questions_page Ljava/awt/Panel;
L1019:  aload_0
L1020:  ldc "Frage:"
L1022:  iconst_0
L1023:  sipush 470
L1026:  bipush 100
L1028:  bipush 20
L1030:  invokespecial Method passwordapp_de getLabel (Ljava/lang/String;IIII)Ljava/awt/Label;
L1033:  invokevirtual Method java/awt/Container add (Ljava/awt/Component;)Ljava/awt/Component;
L1036:  pop
L1037:  aload_0
L1038:  getfield Field passwordapp_de change_questions_page Ljava/awt/Panel;
L1041:  aload_0
L1042:  getfield Field passwordapp_de question [Ljava/awt/TextField;
L1045:  iconst_4
L1046:  aaload
L1047:  invokevirtual Method java/awt/Container add (Ljava/awt/Component;)Ljava/awt/Component;
L1050:  pop
L1051:  new java/awt/Button
L1054:  dup
L1055:  ldc "Neue Frage:"
L1057:  invokespecial Method java/awt/Button <init> (Ljava/lang/String;)V
L1060:  astore_3
L1061:  aload_3
L1062:  ldc "NEWRQ5"
L1064:  invokevirtual Method java/awt/Button setActionCommand (Ljava/lang/String;)V
L1067:  aload_3
L1068:  sipush 360
L1071:  sipush 470
L1074:  sipush 140
L1077:  bipush 22
L1079:  invokevirtual Method java/awt/Component setBounds (IIII)V
L1082:  aload_3
L1083:  aload_0
L1084:  invokevirtual Method java/awt/Button addActionListener (Ljava/awt/event/ActionListener;)V
L1087:  aload_0
L1088:  getfield Field passwordapp_de change_questions_page Ljava/awt/Panel;
L1091:  aload_3
L1092:  invokevirtual Method java/awt/Container add (Ljava/awt/Component;)Ljava/awt/Component;
L1095:  pop
L1096:  aload_0
L1097:  getfield Field passwordapp_de change_questions_page Ljava/awt/Panel;
L1100:  aload_0
L1101:  ldc "Antwort:"
L1103:  iconst_0
L1104:  sipush 500
L1107:  bipush 100
L1109:  bipush 20
L1111:  invokespecial Method passwordapp_de getLabel (Ljava/lang/String;IIII)Ljava/awt/Label;
L1114:  invokevirtual Method java/awt/Container add (Ljava/awt/Component;)Ljava/awt/Component;
L1117:  pop
L1118:  aload_0
L1119:  getfield Field passwordapp_de change_questions_page Ljava/awt/Panel;
L1122:  aload_0
L1123:  getfield Field passwordapp_de recov [Ljava/awt/TextField;
L1126:  iconst_4
L1127:  aaload
L1128:  invokevirtual Method java/awt/Container add (Ljava/awt/Component;)Ljava/awt/Component;
L1131:  pop
L1132:  new java/awt/Button
L1135:  dup
L1136:  ldc "Abschicken"
L1138:  invokespecial Method java/awt/Button <init> (Ljava/lang/String;)V
L1141:  astore 4
L1143:  aload 4
L1145:  sipush 150
L1148:  sipush 540
L1151:  sipush 200
L1154:  bipush 22
L1156:  invokevirtual Method java/awt/Component setBounds (IIII)V
L1159:  aload 4
L1161:  aload_0
L1162:  invokevirtual Method java/awt/Button addActionListener (Ljava/awt/event/ActionListener;)V
L1165:  aload_0
L1166:  getfield Field passwordapp_de change_questions_page Ljava/awt/Panel;
L1169:  aload 4
L1171:  invokevirtual Method java/awt/Container add (Ljava/awt/Component;)Ljava/awt/Component;
L1174:  pop
L1175:  aload_0
L1176:  getfield Field passwordapp_de change_questions_page Ljava/awt/Panel;
L1179:  aload_0
L1180:  invokevirtual Method java/awt/Component getSize ()Ljava/awt/Dimension;
L1183:  invokevirtual Method java/awt/Component setSize (Ljava/awt/Dimension;)V
L1186:  aload_0
L1187:  aload_0
L1188:  getfield Field passwordapp_de change_questions_page Ljava/awt/Panel;
L1191:  invokevirtual Method java/awt/Container add (Ljava/awt/Component;)Ljava/awt/Component;
L1194:  pop
L1195:  return
L1196:  
        .linenumbertable
            L0 196
            L12 198
            L15 200
            L35 201
            L56 202
            L71 203
            L92 204
            L114 205
            L129 206
            L151 207
            L173 208
            L188 209
            L210 210
            L232 211
            L247 212
            L269 213
            L291 214
            L306 215
            L328 217
            L338 219
            L359 220
            L371 222
            L381 223
            L397 224
            L406 226
            L427 227
            L441 228
            L451 229
            L457 230
            L471 231
            L476 232
            L485 233
            L506 234
            L520 236
            L531 237
            L547 238
            L556 240
            L578 241
            L592 242
            L602 243
            L608 244
            L623 245
            L628 246
            L637 247
            L659 248
            L673 250
            L684 251
            L700 252
            L709 254
            L731 255
            L745 256
            L755 257
            L761 258
            L776 259
            L781 260
            L790 261
            L812 262
            L826 264
            L837 265
            L853 266
            L862 268
            L884 269
            L898 270
            L908 271
            L914 272
            L929 273
            L934 274
            L943 275
            L965 276
            L979 278
            L990 279
            L1006 280
            L1015 282
            L1037 283
            L1051 284
            L1061 285
            L1067 286
            L1082 287
            L1087 288
            L1096 289
            L1118 290
            L1132 292
            L1143 293
            L1159 294
            L1165 295
            L1175 297
            L1186 298
            L1195 194
        .end linenumbertable
    .end code
.end method

.method private getLabel : (Ljava/lang/String;II)Ljava/awt/Label;
    .code stack 6 locals 4
L0:     aload_0
L1:     aload_1
L2:     iload_2
L3:     iload_3
L4:     aload_1
L5:     invokevirtual Method java/lang/String length ()I
L8:     bipush 8
L10:    imul
L11:    bipush 20
L13:    invokespecial Method passwordapp_de getLabel (Ljava/lang/String;IIII)Ljava/awt/Label;
L16:    areturn
L17:    
        .linenumbertable
            L0 305
        .end linenumbertable
    .end code
.end method

.method private getLabel : (Ljava/lang/String;IIII)Ljava/awt/Label;
    .code stack 6 locals 7
L0:     new java/awt/Label
L3:     dup
L4:     aload_1
L5:     iconst_0
L6:     invokespecial Method java/awt/Label <init> (Ljava/lang/String;I)V
L9:     astore 6
L11:    aload 6
L13:    getstatic Field java/awt/Color white Ljava/awt/Color;
L16:    invokevirtual Method java/awt/Component setForeground (Ljava/awt/Color;)V
L19:    aload 6
L21:    getstatic Field java/awt/Color black Ljava/awt/Color;
L24:    invokevirtual Method java/awt/Component setBackground (Ljava/awt/Color;)V
L27:    aload 6
L29:    new java/awt/Font
L32:    dup
L33:    ldc "Arial"
L35:    iconst_0
L36:    bipush 13
L38:    invokespecial Method java/awt/Font <init> (Ljava/lang/String;II)V
L41:    invokevirtual Method java/awt/Component setFont (Ljava/awt/Font;)V
L44:    aload 6
L46:    iload_2
L47:    iload_3
L48:    iload 4
L50:    iload 5
L52:    invokevirtual Method java/awt/Component setBounds (IIII)V
L55:    aload 6
L57:    areturn
L58:    
        .linenumbertable
            L0 312
            L11 313
            L19 314
            L27 315
            L44 316
            L55 317
        .end linenumbertable
    .end code
.end method

.method private getTextField : (IIIIIZ)Ljava/awt/TextField;
    .code stack 5 locals 8
L0:     new java/awt/TextField
L3:     dup
L4:     iload_1
L5:     invokespecial Method java/awt/TextField <init> (I)V
L8:     astore 7
L10:    aload 7
L12:    iload_2
L13:    iload_3
L14:    iload 4
L16:    iload 5
L18:    invokevirtual Method java/awt/Component setBounds (IIII)V
L21:    iload 6
L23:    ifeq L33
L26:    aload 7
L28:    bipush 42
L30:    invokevirtual Method java/awt/TextField setEchoChar (C)V
L33:    aload 7
L35:    aload_0
L36:    invokevirtual Method java/awt/TextComponent addTextListener (Ljava/awt/event/TextListener;)V
L39:    aload 7
L41:    aload_0
L42:    invokevirtual Method java/awt/Component addKeyListener (Ljava/awt/event/KeyListener;)V
L45:    aload 7
L47:    getstatic Field java/awt/Color black Ljava/awt/Color;
L50:    invokevirtual Method java/awt/Component setForeground (Ljava/awt/Color;)V
L53:    aload 7
L55:    getstatic Field java/awt/Color white Ljava/awt/Color;
L58:    invokevirtual Method java/awt/Component setBackground (Ljava/awt/Color;)V
L61:    aload 7
L63:    areturn
L64:    
        .linenumbertable
            L0 321
            L10 322
            L21 323
            L33 324
            L39 325
            L45 326
            L53 327
            L61 328
        .end linenumbertable
    .end code
.end method

.method private safesizestring : (Ljava/lang/String;I)Ljava/lang/String;
    .code stack 3 locals 3
L0:     aload_1
L1:     invokevirtual Method java/lang/String trim ()Ljava/lang/String;
L4:     astore_1
L5:     aload_1
L6:     invokevirtual Method java/lang/String length ()I
L9:     iload_2
L10:    if_icmple L20
L13:    aload_1
L14:    iconst_0
L15:    iload_2
L16:    invokevirtual Method java/lang/String substring (II)Ljava/lang/String;
L19:    areturn
L20:    aload_1
L21:    areturn
L22:    
        .linenumbertable
            L0 336
            L5 337
            L20 338
        .end linenumbertable
    .end code
.end method

.method public static tidyrecoveryanswer : (Ljava/lang/String;)Ljava/lang/String;
    .code stack 2 locals 4
L0:     aload_0
L1:     invokevirtual Method java/lang/String toLowerCase ()Ljava/lang/String;
L4:     astore_0
L5:     new java/lang/StringBuffer
L8:     dup
L9:     invokespecial Method java/lang/StringBuffer <init> ()V
L12:    astore_1
L13:    iconst_0
L14:    istore_2
L15:    goto L63
L18:    aload_0
L19:    iload_2
L20:    invokevirtual Method java/lang/String charAt (I)C
L23:    istore_3
L24:    iload_3
L25:    bipush 97
L27:    if_icmplt L42
L30:    iload_3
L31:    bipush 122
L33:    if_icmpgt L42
L36:    aload_1
L37:    iload_3
L38:    invokevirtual Method java/lang/StringBuffer append (C)Ljava/lang/StringBuffer;
L41:    pop
L42:    iload_3
L43:    bipush 48
L45:    if_icmplt L60
L48:    iload_3
L49:    bipush 57
L51:    if_icmpgt L60
L54:    aload_1
L55:    iload_3
L56:    invokevirtual Method java/lang/StringBuffer append (C)Ljava/lang/StringBuffer;
L59:    pop
L60:    iinc 2 1
L63:    iload_2
L64:    aload_0
L65:    invokevirtual Method java/lang/String length ()I
L68:    if_icmpge L77
L71:    iload_2
L72:    bipush 50
L74:    if_icmplt L18
L77:    aload_1
L78:    invokevirtual Method java/lang/StringBuffer toString ()Ljava/lang/String;
L81:    areturn
L82:    
        .linenumbertable
            L0 345
            L5 346
            L13 347
            L18 348
            L24 349
            L42 350
            L60 347
            L77 352
        .end linenumbertable
    .end code
.end method

.method public static urlencode : (Ljava/lang/String;)Ljava/lang/String;
    .code stack 3 locals 5
L0:     new java/lang/StringBuffer
L3:     dup
L4:     aload_0
L5:     invokevirtual Method java/lang/String length ()I
L8:     invokespecial Method java/lang/StringBuffer <init> (I)V
L11:    astore_1
L12:    iconst_0
L13:    istore_2
L14:    goto L200
L17:    aload_0
L18:    iload_2
L19:    invokevirtual Method java/lang/String charAt (I)C
L22:    istore_3
L23:    iload_3
L24:    bipush 48
L26:    if_icmplt L35
L29:    iload_3
L30:    bipush 57
L32:    if_icmple L59
L35:    iload_3
L36:    bipush 97
L38:    if_icmplt L47
L41:    iload_3
L42:    bipush 122
L44:    if_icmple L59
L47:    iload_3
L48:    bipush 65
L50:    if_icmplt L68
L53:    iload_3
L54:    bipush 90
L56:    if_icmpgt L68
L59:    aload_1
L60:    iload_3
L61:    invokevirtual Method java/lang/StringBuffer append (C)Ljava/lang/StringBuffer;
L64:    pop
L65:    goto L197
L68:    aload_1
L69:    ldc "%"
L71:    invokevirtual Method java/lang/StringBuffer append (Ljava/lang/String;)Ljava/lang/StringBuffer;
L74:    pop
L75:    iload_3
L76:    iconst_4
L77:    ishr
L78:    bipush 15
L80:    iand
L81:    istore 4
L83:    iload 4
L85:    iflt L109
L88:    iload 4
L90:    bipush 9
L92:    if_icmpgt L109
L95:    aload_1
L96:    iload 4
L98:    bipush 48
L100:   iadd
L101:   i2c
L102:   invokevirtual Method java/lang/StringBuffer append (C)Ljava/lang/StringBuffer;
L105:   pop
L106:   goto L137
L109:   iload 4
L111:   bipush 10
L113:   if_icmplt L137
L116:   iload 4
L118:   bipush 15
L120:   if_icmpgt L137
L123:   aload_1
L124:   iload 4
L126:   bipush 10
L128:   isub
L129:   bipush 65
L131:   iadd
L132:   i2c
L133:   invokevirtual Method java/lang/StringBuffer append (C)Ljava/lang/StringBuffer;
L136:   pop
L137:   iload_3
L138:   bipush 15
L140:   iand
L141:   istore 4
L143:   iload 4
L145:   iflt L169
L148:   iload 4
L150:   bipush 9
L152:   if_icmpgt L169
L155:   aload_1
L156:   iload 4
L158:   bipush 48
L160:   iadd
L161:   i2c
L162:   invokevirtual Method java/lang/StringBuffer append (C)Ljava/lang/StringBuffer;
L165:   pop
L166:   goto L197
L169:   iload 4
L171:   bipush 10
L173:   if_icmplt L197
L176:   iload 4
L178:   bipush 15
L180:   if_icmpgt L197
L183:   aload_1
L184:   iload 4
L186:   bipush 10
L188:   isub
L189:   bipush 65
L191:   iadd
L192:   i2c
L193:   invokevirtual Method java/lang/StringBuffer append (C)Ljava/lang/StringBuffer;
L196:   pop
L197:   iinc 2 1
L200:   iload_2
L201:   aload_0
L202:   invokevirtual Method java/lang/String length ()I
L205:   if_icmplt L17
L208:   aload_1
L209:   invokevirtual Method java/lang/StringBuffer toString ()Ljava/lang/String;
L212:   areturn
L213:   
        .linenumbertable
            L0 360
            L12 361
            L17 362
            L23 363
            L68 365
            L75 366
            L83 367
            L109 368
            L137 369
            L143 370
            L169 371
            L197 361
            L208 374
        .end linenumbertable
    .end code
.end method

.method public actionPerformed : (Ljava/awt/event/ActionEvent;)V
    .code stack 5 locals 9
L0:     aload_0
L1:     getfield Field passwordapp_de onreversepath Z
L4:     ifeq L53
L7:     aload_0
L8:     getfield Field passwordapp_de hidepanel Ljava/awt/Panel;
L11:    ifnull L27
L14:    aload_0
L15:    getfield Field passwordapp_de hidepanel Ljava/awt/Panel;
L18:    iconst_0
L19:    invokevirtual Method java/awt/Component setVisible (Z)V
L22:    aload_0
L23:    aconst_null
L24:    putfield Field passwordapp_de hidepanel Ljava/awt/Panel;
L27:    aload_0
L28:    getfield Field passwordapp_de showpanel Ljava/awt/Panel;
L31:    ifnull L47
L34:    aload_0
L35:    getfield Field passwordapp_de showpanel Ljava/awt/Panel;
L38:    iconst_1
L39:    invokevirtual Method java/awt/Component setVisible (Z)V
L42:    aload_0
L43:    aconst_null
L44:    putfield Field passwordapp_de showpanel Ljava/awt/Panel;
L47:    aload_0
L48:    iconst_0
L49:    putfield Field passwordapp_de onreversepath Z
L52:    return
L53:    aload_0
L54:    getfield Field passwordapp_de type I
L57:    iconst_2
L58:    if_icmpne L674
L61:    aload_1
L62:    invokevirtual Method java/awt/event/ActionEvent getActionCommand ()Ljava/lang/String;
L65:    astore_2
L66:    aload_2
L67:    ifnull L196
L70:    aload_2
L71:    ldc "NEWRQ"
L73:    invokevirtual Method java/lang/String startsWith (Ljava/lang/String;)Z
L76:    ifeq L196
L79:    aload_0
L80:    getfield Field passwordapp_de example_questions [Ljava/lang/String;
L83:    invokestatic Method java/lang/Math random ()D
L86:    aload_0
L87:    getfield Field passwordapp_de example_questions [Ljava/lang/String;
L90:    arraylength
L91:    i2d
L92:    dmul
L93:    d2i
L94:    aaload
L95:    astore_3
L96:    aload_2
L97:    ldc "NEWRQ1"
L99:    invokevirtual Method java/lang/String equals (Ljava/lang/Object;)Z
L102:   ifeq L116
L105:   aload_0
L106:   getfield Field passwordapp_de question [Ljava/awt/TextField;
L109:   iconst_0
L110:   aaload
L111:   aload_3
L112:   invokevirtual Method java/awt/TextComponent setText (Ljava/lang/String;)V
L115:   return
L116:   aload_2
L117:   ldc "NEWRQ2"
L119:   invokevirtual Method java/lang/String equals (Ljava/lang/Object;)Z
L122:   ifeq L136
L125:   aload_0
L126:   getfield Field passwordapp_de question [Ljava/awt/TextField;
L129:   iconst_1
L130:   aaload
L131:   aload_3
L132:   invokevirtual Method java/awt/TextComponent setText (Ljava/lang/String;)V
L135:   return
L136:   aload_2
L137:   ldc "NEWRQ3"
L139:   invokevirtual Method java/lang/String equals (Ljava/lang/Object;)Z
L142:   ifeq L156
L145:   aload_0
L146:   getfield Field passwordapp_de question [Ljava/awt/TextField;
L149:   iconst_2
L150:   aaload
L151:   aload_3
L152:   invokevirtual Method java/awt/TextComponent setText (Ljava/lang/String;)V
L155:   return
L156:   aload_2
L157:   ldc "NEWRQ4"
L159:   invokevirtual Method java/lang/String equals (Ljava/lang/Object;)Z
L162:   ifeq L176
L165:   aload_0
L166:   getfield Field passwordapp_de question [Ljava/awt/TextField;
L169:   iconst_3
L170:   aaload
L171:   aload_3
L172:   invokevirtual Method java/awt/TextComponent setText (Ljava/lang/String;)V
L175:   return
L176:   aload_2
L177:   ldc "NEWRQ5"
L179:   invokevirtual Method java/lang/String equals (Ljava/lang/Object;)Z
L182:   ifeq L195
L185:   aload_0
L186:   getfield Field passwordapp_de question [Ljava/awt/TextField;
L189:   iconst_4
L190:   aaload
L191:   aload_3
L192:   invokevirtual Method java/awt/TextComponent setText (Ljava/lang/String;)V
L195:   return
L196:   aload_0
L197:   getfield Field passwordapp_de change_questions_page Ljava/awt/Panel;
L200:   iconst_0
L201:   invokevirtual Method java/awt/Component setVisible (Z)V
L204:   aload_0
L205:   getfield Field passwordapp_de password1 Ljava/awt/TextField;
L208:   invokevirtual Method java/awt/TextComponent getText ()Ljava/lang/String;
L211:   invokevirtual Method java/lang/String length ()I
L214:   iconst_1
L215:   if_icmplt L233
L218:   aload_0
L219:   getfield Field passwordapp_de password1 Ljava/awt/TextField;
L222:   invokevirtual Method java/awt/TextComponent getText ()Ljava/lang/String;
L225:   invokevirtual Method java/lang/String length ()I
L228:   bipush 20
L230:   if_icmple L263
L233:   aload_0
L234:   getfield Field passwordapp_de wrongpassword_page Ljava/awt/Panel;
L237:   iconst_1
L238:   invokevirtual Method java/awt/Component setVisible (Z)V
L241:   aload_0
L242:   iconst_1
L243:   putfield Field passwordapp_de onreversepath Z
L246:   aload_0
L247:   aload_0
L248:   getfield Field passwordapp_de change_questions_page Ljava/awt/Panel;
L251:   putfield Field passwordapp_de showpanel Ljava/awt/Panel;
L254:   aload_0
L255:   aload_0
L256:   getfield Field passwordapp_de wrongpassword_page Ljava/awt/Panel;
L259:   putfield Field passwordapp_de hidepanel Ljava/awt/Panel;
L262:   return
L263:   iconst_0
L264:   istore_3
L265:   goto L339
L268:   aload_0
L269:   getfield Field passwordapp_de question [Ljava/awt/TextField;
L272:   iload_3
L273:   aaload
L274:   invokevirtual Method java/awt/TextComponent getText ()Ljava/lang/String;
L277:   invokevirtual Method java/lang/String trim ()Ljava/lang/String;
L280:   invokevirtual Method java/lang/String length ()I
L283:   iconst_3
L284:   if_icmplt L306
L287:   aload_0
L288:   getfield Field passwordapp_de recov [Ljava/awt/TextField;
L291:   iload_3
L292:   aaload
L293:   invokevirtual Method java/awt/TextComponent getText ()Ljava/lang/String;
L296:   invokestatic Method passwordapp_de tidyrecoveryanswer (Ljava/lang/String;)Ljava/lang/String;
L299:   invokevirtual Method java/lang/String length ()I
L302:   iconst_3
L303:   if_icmpge L336
L306:   aload_0
L307:   getfield Field passwordapp_de change_questions_tooshort_page Ljava/awt/Panel;
L310:   iconst_1
L311:   invokevirtual Method java/awt/Component setVisible (Z)V
L314:   aload_0
L315:   iconst_1
L316:   putfield Field passwordapp_de onreversepath Z
L319:   aload_0
L320:   aload_0
L321:   getfield Field passwordapp_de change_questions_page Ljava/awt/Panel;
L324:   putfield Field passwordapp_de showpanel Ljava/awt/Panel;
L327:   aload_0
L328:   aload_0
L329:   getfield Field passwordapp_de change_questions_tooshort_page Ljava/awt/Panel;
L332:   putfield Field passwordapp_de hidepanel Ljava/awt/Panel;
L335:   return
L336:   iinc 3 1
L339:   iload_3
L340:   iconst_5
L341:   if_icmplt L268
L344:   iconst_0
L345:   istore 4
L347:   goto L444
L350:   aload_0
L351:   getfield Field passwordapp_de question [Ljava/awt/TextField;
L354:   iload 4
L356:   aaload
L357:   invokevirtual Method java/awt/TextComponent getText ()Ljava/lang/String;
L360:   invokevirtual Method java/lang/String trim ()Ljava/lang/String;
L363:   astore 5
L365:   aload 5
L367:   ldc ""
L369:   invokevirtual Method java/lang/String equals (Ljava/lang/Object;)Z
L372:   ifne L441
L375:   iload 4
L377:   iconst_1
L378:   iadd
L379:   istore 6
L381:   goto L435
L384:   aload 5
L386:   aload_0
L387:   getfield Field passwordapp_de question [Ljava/awt/TextField;
L390:   iload 6
L392:   aaload
L393:   invokevirtual Method java/awt/TextComponent getText ()Ljava/lang/String;
L396:   invokevirtual Method java/lang/String equalsIgnoreCase (Ljava/lang/String;)Z
L399:   ifeq L432
L402:   aload_0
L403:   getfield Field passwordapp_de change_questions_samequestions_page Ljava/awt/Panel;
L406:   iconst_1
L407:   invokevirtual Method java/awt/Component setVisible (Z)V
L410:   aload_0
L411:   iconst_1
L412:   putfield Field passwordapp_de onreversepath Z
L415:   aload_0
L416:   aload_0
L417:   getfield Field passwordapp_de change_questions_page Ljava/awt/Panel;
L420:   putfield Field passwordapp_de showpanel Ljava/awt/Panel;
L423:   aload_0
L424:   aload_0
L425:   getfield Field passwordapp_de change_questions_samequestions_page Ljava/awt/Panel;
L428:   putfield Field passwordapp_de hidepanel Ljava/awt/Panel;
L431:   return
L432:   iinc 6 1
L435:   iload 6
L437:   iconst_5
L438:   if_icmplt L384
L441:   iinc 4 1
L444:   iload 4
L446:   iconst_5
L447:   if_icmplt L350
L450:   iconst_0
L451:   istore 5
L453:   goto L559
L456:   aload_0
L457:   getfield Field passwordapp_de recov [Ljava/awt/TextField;
L460:   iload 5
L462:   aaload
L463:   invokevirtual Method java/awt/TextComponent getText ()Ljava/lang/String;
L466:   invokestatic Method passwordapp_de tidyrecoveryanswer (Ljava/lang/String;)Ljava/lang/String;
L469:   invokevirtual Method java/lang/String trim ()Ljava/lang/String;
L472:   astore 6
L474:   aload 6
L476:   ldc ""
L478:   invokevirtual Method java/lang/String equals (Ljava/lang/Object;)Z
L481:   ifne L556
L484:   iload 5
L486:   iconst_1
L487:   iadd
L488:   istore 7
L490:   goto L550
L493:   aload 6
L495:   invokestatic Method passwordapp_de tidyrecoveryanswer (Ljava/lang/String;)Ljava/lang/String;
L498:   aload_0
L499:   getfield Field passwordapp_de recov [Ljava/awt/TextField;
L502:   iload 7
L504:   aaload
L505:   invokevirtual Method java/awt/TextComponent getText ()Ljava/lang/String;
L508:   invokestatic Method passwordapp_de tidyrecoveryanswer (Ljava/lang/String;)Ljava/lang/String;
L511:   invokevirtual Method java/lang/String equalsIgnoreCase (Ljava/lang/String;)Z
L514:   ifeq L547
L517:   aload_0
L518:   getfield Field passwordapp_de change_questions_sameanswers_page Ljava/awt/Panel;
L521:   iconst_1
L522:   invokevirtual Method java/awt/Component setVisible (Z)V
L525:   aload_0
L526:   iconst_1
L527:   putfield Field passwordapp_de onreversepath Z
L530:   aload_0
L531:   aload_0
L532:   getfield Field passwordapp_de change_questions_page Ljava/awt/Panel;
L535:   putfield Field passwordapp_de showpanel Ljava/awt/Panel;
L538:   aload_0
L539:   aload_0
L540:   getfield Field passwordapp_de change_questions_sameanswers_page Ljava/awt/Panel;
L543:   putfield Field passwordapp_de hidepanel Ljava/awt/Panel;
L546:   return
L547:   iinc 7 1
L550:   iload 7
L552:   iconst_5
L553:   if_icmplt L493
L556:   iinc 5 1
L559:   iload 5
L561:   iconst_5
L562:   if_icmplt L456
L565:   iconst_0
L566:   istore 6
L568:   goto L668
L571:   aload_0
L572:   getfield Field passwordapp_de recov [Ljava/awt/TextField;
L575:   iload 6
L577:   aaload
L578:   invokevirtual Method java/awt/TextComponent getText ()Ljava/lang/String;
L581:   invokestatic Method passwordapp_de tidyrecoveryanswer (Ljava/lang/String;)Ljava/lang/String;
L584:   invokevirtual Method java/lang/String trim ()Ljava/lang/String;
L587:   astore 7
L589:   aload 7
L591:   ldc ""
L593:   invokevirtual Method java/lang/String equals (Ljava/lang/Object;)Z
L596:   ifne L665
L599:   iconst_0
L600:   istore 8
L602:   goto L659
L605:   aload 7
L607:   aload_0
L608:   getfield Field passwordapp_de question [Ljava/awt/TextField;
L611:   iload 8
L613:   aaload
L614:   invokevirtual Method java/awt/TextComponent getText ()Ljava/lang/String;
L617:   invokestatic Method passwordapp_de tidyrecoveryanswer (Ljava/lang/String;)Ljava/lang/String;
L620:   invokevirtual Method java/lang/String equalsIgnoreCase (Ljava/lang/String;)Z
L623:   ifeq L656
L626:   aload_0
L627:   getfield Field passwordapp_de change_questions_qandamatch_page Ljava/awt/Panel;
L630:   iconst_1
L631:   invokevirtual Method java/awt/Component setVisible (Z)V
L634:   aload_0
L635:   iconst_1
L636:   putfield Field passwordapp_de onreversepath Z
L639:   aload_0
L640:   aload_0
L641:   getfield Field passwordapp_de change_questions_page Ljava/awt/Panel;
L644:   putfield Field passwordapp_de showpanel Ljava/awt/Panel;
L647:   aload_0
L648:   aload_0
L649:   getfield Field passwordapp_de change_questions_qandamatch_page Ljava/awt/Panel;
L652:   putfield Field passwordapp_de hidepanel Ljava/awt/Panel;
L655:   return
L656:   iinc 8 1
L659:   iload 8
L661:   iconst_5
L662:   if_icmplt L605
L665:   iinc 6 1
L668:   iload 6
L670:   iconst_5
L671:   if_icmplt L571
L674:   aload_0
L675:   getfield Field passwordapp_de processingpage Ljava/awt/Panel;
L678:   iconst_1
L679:   invokevirtual Method java/awt/Component setVisible (Z)V
L682:   new java/lang/Thread
L685:   dup
L686:   aload_0
L687:   invokespecial Method java/lang/Thread <init> (Ljava/lang/Runnable;)V
L690:   astore_2
L691:   aload_2
L692:   iconst_1
L693:   invokevirtual Method java/lang/Thread setDaemon (Z)V
L696:   aload_2
L697:   invokevirtual Method java/lang/Thread start ()V
L700:   return
L701:   
        .linenumbertable
            L0 383
            L7 384
            L14 385
            L22 386
            L27 388
            L34 389
            L42 390
            L47 392
            L52 393
            L53 396
            L61 398
            L66 399
            L79 400
            L96 401
            L105 402
            L115 401
            L116 404
            L125 405
            L135 404
            L136 407
            L145 408
            L155 407
            L156 410
            L165 411
            L175 410
            L176 413
            L185 414
            L195 416
            L196 419
            L204 421
            L233 422
            L241 423
            L246 424
            L254 425
            L262 426
            L263 430
            L268 431
            L306 432
            L314 433
            L319 434
            L327 435
            L335 436
            L336 430
            L344 441
            L350 442
            L365 443
            L375 444
            L384 445
            L402 446
            L410 447
            L415 448
            L423 449
            L431 450
            L432 444
            L441 441
            L450 456
            L456 457
            L474 458
            L484 459
            L493 460
            L517 461
            L525 462
            L530 463
            L538 464
            L546 465
            L547 459
            L556 456
            L565 471
            L571 472
            L589 473
            L599 474
            L605 475
            L626 476
            L634 477
            L639 478
            L647 479
            L655 480
            L656 474
            L665 471
            L674 488
            L682 491
            L691 492
            L696 493
            L700 381
        .end linenumbertable
    .end code
.end method

.method public run : ()V
    .code stack 5 locals 18
L0:     aload_0
L1:     getfield Field passwordapp_de initialised Z
L4:     ifne L166
L7:     aload_0
L8:     aload_0
L9:     invokevirtual Method java/applet/Applet getCodeBase ()Ljava/net/URL;
L12:    invokevirtual Method java/net/URL toString ()Ljava/lang/String;
L15:    putfield Field passwordapp_de codebase Ljava/lang/String;
L18:    iconst_0
L19:    istore_1
L20:    iconst_0
L21:    istore_2
L22:    goto L48
L25:    aload_0
L26:    getfield Field passwordapp_de codebase Ljava/lang/String;
L29:    getstatic Field passwordapp_de allowedlist [Ljava/lang/String;
L32:    iload_2
L33:    aaload
L34:    invokevirtual Method java/lang/String startsWith (Ljava/lang/String;)Z
L37:    ifeq L45
L40:    iconst_1
L41:    istore_1
L42:    goto L56
L45:    iinc 2 1
L48:    iload_2
L49:    getstatic Field passwordapp_de allowedlist [Ljava/lang/String;
L52:    arraylength
L53:    if_icmplt L25
L56:    iload_1
L57:    ifne L66
L60:    aload_0
L61:    ldc "http://recovery_questions.runescape.com/"
L63:    putfield Field passwordapp_de codebase Ljava/lang/String;
L66:    aload_0
L67:    aconst_null
L68:    invokevirtual Method java/awt/Container setLayout (Ljava/awt/LayoutManager;)V
L71:    aload_0
L72:    getstatic Field java/awt/Color black Ljava/awt/Color;
L75:    invokevirtual Method java/awt/Component setBackground (Ljava/awt/Color;)V
L78:    aload_0
L79:    invokespecial Method passwordapp_de init_messages ()V
L82:    aload_0
L83:    aload_0
L84:    ldc "type"
L86:    invokevirtual Method java/applet/Applet getParameter (Ljava/lang/String;)Ljava/lang/String;
L89:    invokestatic Method java/lang/Integer parseInt (Ljava/lang/String;)I
L92:    putfield Field passwordapp_de type I
L95:    aload_0
L96:    aload_0
L97:    ldc "username"
L99:    invokevirtual Method java/applet/Applet getParameter (Ljava/lang/String;)Ljava/lang/String;
L102:   putfield Field passwordapp_de username Ljava/lang/String;
L105:   aload_0
L106:   invokestatic Method passwordapp_de findcachedir ()Ljava/lang/String;
L109:   invokestatic Method passwordapp_de getuid (Ljava/lang/String;)I
L112:   putfield Field passwordapp_de uid I
L115:   aload_0
L116:   getfield Field passwordapp_de type I
L119:   iconst_2
L120:   if_icmpne L130
L123:   aload_0
L124:   invokespecial Method passwordapp_de init_change_questions ()V
L127:   goto L160
L130:   aload_0
L131:   getfield Field passwordapp_de type I
L134:   iconst_4
L135:   if_icmpne L150
L138:   aload_0
L139:   invokespecial Method passwordapp_de init_change_questions ()V
L142:   aload_0
L143:   aload_0
L144:   invokevirtual Method java/awt/Component addKeyListener (Ljava/awt/event/KeyListener;)V
L147:   goto L160
L150:   new java/lang/RuntimeException
L153:   dup
L154:   ldc "Not enough parameters"
L156:   invokespecial Method java/lang/RuntimeException <init> (Ljava/lang/String;)V
L159:   athrow
L160:   aload_0
L161:   iconst_1
L162:   putfield Field passwordapp_de initialised Z
L165:   return
L166:   new java/security/SecureRandom
L169:   dup
L170:   invokespecial Method java/security/SecureRandom <init> ()V
L173:   astore_1
L174:   iconst_4
L175:   newarray int
L177:   astore_2
L178:   iconst_0
L179:   istore_3
L180:   goto L193
L183:   aload_2
L184:   iload_3
L185:   aload_1
L186:   invokevirtual Method java/util/Random nextInt ()I
L189:   iastore
L190:   iinc 3 1
L193:   iload_3
L194:   aload_2
L195:   arraylength
L196:   if_icmplt L183
L199:   new packet
L202:   dup
L203:   bipush 66
L205:   newarray byte
L207:   invokespecial Method packet <init> ([B)V
L210:   astore 4
L212:   aload 4
L214:   iconst_1
L215:   invokevirtual Method packet p1 (I)V
L218:   iconst_0
L219:   istore 5
L221:   goto L236
L224:   aload 4
L226:   aload_2
L227:   iload 5
L229:   iaload
L230:   invokevirtual Method packet p4 (I)V
L233:   iinc 5 1
L236:   iload 5
L238:   aload_2
L239:   arraylength
L240:   if_icmplt L224
L243:   aload 4
L245:   aload_0
L246:   getfield Field passwordapp_de key_e Ljava/math/BigInteger;
L249:   aload_0
L250:   getfield Field passwordapp_de key_n Ljava/math/BigInteger;
L253:   invokevirtual Method packet rsaenc (Ljava/math/BigInteger;Ljava/math/BigInteger;)V
L256:   aload 4
L258:   getfield Field packet pos I
L261:   istore 6
L263:   aload 4
L265:   iconst_0
L266:   putfield Field packet pos I
L269:   aload 4
L271:   iload 6
L273:   invokevirtual Method packet g64encoded (I)Ljava/lang/String;
L276:   astore 7
L278:   new packet
L281:   dup
L282:   sipush 2048
L285:   newarray byte
L287:   invokespecial Method packet <init> ([B)V
L290:   astore 8
L292:   aload 8
L294:   iconst_2
L295:   invokevirtual Method packet p4 (I)V
L298:   aload 8
L300:   aload_0
L301:   getfield Field passwordapp_de username Ljava/lang/String;
L304:   invokevirtual Method packet pjstr (Ljava/lang/String;)V
L307:   aload 8
L309:   aload_0
L310:   getfield Field passwordapp_de uid I
L313:   invokevirtual Method packet p4 (I)V
L316:   aload_0
L317:   getfield Field passwordapp_de type I
L320:   iconst_2
L321:   if_icmpne L564
L324:   aload 8
L326:   aload_0
L327:   aload_0
L328:   getfield Field passwordapp_de password1 Ljava/awt/TextField;
L331:   invokevirtual Method java/awt/TextComponent getText ()Ljava/lang/String;
L334:   bipush 20
L336:   invokespecial Method passwordapp_de safesizestring (Ljava/lang/String;I)Ljava/lang/String;
L339:   invokevirtual Method packet pjstr (Ljava/lang/String;)V
L342:   aload 8
L344:   aload_0
L345:   aload_0
L346:   getfield Field passwordapp_de question [Ljava/awt/TextField;
L349:   iconst_0
L350:   aaload
L351:   invokevirtual Method java/awt/TextComponent getText ()Ljava/lang/String;
L354:   bipush 40
L356:   invokespecial Method passwordapp_de safesizestring (Ljava/lang/String;I)Ljava/lang/String;
L359:   invokevirtual Method packet pjstr (Ljava/lang/String;)V
L362:   aload 8
L364:   aload_0
L365:   aload_0
L366:   getfield Field passwordapp_de recov [Ljava/awt/TextField;
L369:   iconst_0
L370:   aaload
L371:   invokevirtual Method java/awt/TextComponent getText ()Ljava/lang/String;
L374:   invokestatic Method passwordapp_de tidyrecoveryanswer (Ljava/lang/String;)Ljava/lang/String;
L377:   bipush 40
L379:   invokespecial Method passwordapp_de safesizestring (Ljava/lang/String;I)Ljava/lang/String;
L382:   invokevirtual Method packet pjstr (Ljava/lang/String;)V
L385:   aload 8
L387:   aload_0
L388:   aload_0
L389:   getfield Field passwordapp_de question [Ljava/awt/TextField;
L392:   iconst_1
L393:   aaload
L394:   invokevirtual Method java/awt/TextComponent getText ()Ljava/lang/String;
L397:   bipush 40
L399:   invokespecial Method passwordapp_de safesizestring (Ljava/lang/String;I)Ljava/lang/String;
L402:   invokevirtual Method packet pjstr (Ljava/lang/String;)V
L405:   aload 8
L407:   aload_0
L408:   aload_0
L409:   getfield Field passwordapp_de recov [Ljava/awt/TextField;
L412:   iconst_1
L413:   aaload
L414:   invokevirtual Method java/awt/TextComponent getText ()Ljava/lang/String;
L417:   invokestatic Method passwordapp_de tidyrecoveryanswer (Ljava/lang/String;)Ljava/lang/String;
L420:   bipush 40
L422:   invokespecial Method passwordapp_de safesizestring (Ljava/lang/String;I)Ljava/lang/String;
L425:   invokevirtual Method packet pjstr (Ljava/lang/String;)V
L428:   aload 8
L430:   aload_0
L431:   aload_0
L432:   getfield Field passwordapp_de question [Ljava/awt/TextField;
L435:   iconst_2
L436:   aaload
L437:   invokevirtual Method java/awt/TextComponent getText ()Ljava/lang/String;
L440:   bipush 40
L442:   invokespecial Method passwordapp_de safesizestring (Ljava/lang/String;I)Ljava/lang/String;
L445:   invokevirtual Method packet pjstr (Ljava/lang/String;)V
L448:   aload 8
L450:   aload_0
L451:   aload_0
L452:   getfield Field passwordapp_de recov [Ljava/awt/TextField;
L455:   iconst_2
L456:   aaload
L457:   invokevirtual Method java/awt/TextComponent getText ()Ljava/lang/String;
L460:   invokestatic Method passwordapp_de tidyrecoveryanswer (Ljava/lang/String;)Ljava/lang/String;
L463:   bipush 40
L465:   invokespecial Method passwordapp_de safesizestring (Ljava/lang/String;I)Ljava/lang/String;
L468:   invokevirtual Method packet pjstr (Ljava/lang/String;)V
L471:   aload 8
L473:   aload_0
L474:   aload_0
L475:   getfield Field passwordapp_de question [Ljava/awt/TextField;
L478:   iconst_3
L479:   aaload
L480:   invokevirtual Method java/awt/TextComponent getText ()Ljava/lang/String;
L483:   bipush 40
L485:   invokespecial Method passwordapp_de safesizestring (Ljava/lang/String;I)Ljava/lang/String;
L488:   invokevirtual Method packet pjstr (Ljava/lang/String;)V
L491:   aload 8
L493:   aload_0
L494:   aload_0
L495:   getfield Field passwordapp_de recov [Ljava/awt/TextField;
L498:   iconst_3
L499:   aaload
L500:   invokevirtual Method java/awt/TextComponent getText ()Ljava/lang/String;
L503:   invokestatic Method passwordapp_de tidyrecoveryanswer (Ljava/lang/String;)Ljava/lang/String;
L506:   bipush 40
L508:   invokespecial Method passwordapp_de safesizestring (Ljava/lang/String;I)Ljava/lang/String;
L511:   invokevirtual Method packet pjstr (Ljava/lang/String;)V
L514:   aload 8
L516:   aload_0
L517:   aload_0
L518:   getfield Field passwordapp_de question [Ljava/awt/TextField;
L521:   iconst_4
L522:   aaload
L523:   invokevirtual Method java/awt/TextComponent getText ()Ljava/lang/String;
L526:   bipush 40
L528:   invokespecial Method passwordapp_de safesizestring (Ljava/lang/String;I)Ljava/lang/String;
L531:   invokevirtual Method packet pjstr (Ljava/lang/String;)V
L534:   aload 8
L536:   aload_0
L537:   aload_0
L538:   getfield Field passwordapp_de recov [Ljava/awt/TextField;
L541:   iconst_4
L542:   aaload
L543:   invokevirtual Method java/awt/TextComponent getText ()Ljava/lang/String;
L546:   invokestatic Method passwordapp_de tidyrecoveryanswer (Ljava/lang/String;)Ljava/lang/String;
L549:   bipush 40
L551:   invokespecial Method passwordapp_de safesizestring (Ljava/lang/String;I)Ljava/lang/String;
L554:   invokevirtual Method packet pjstr (Ljava/lang/String;)V
L557:   ldc "changequestions.cgi"
L559:   astore 9
L561:   goto L565
L564:   return
L565:   aload 8
L567:   invokevirtual Method packet addcrc ()I
L570:   pop
L571:   aload 8
L573:   getfield Field packet pos I
L576:   istore 10
L578:   aload 8
L580:   aload_2
L581:   invokevirtual Method packet tinyenc ([I)V
L584:   aload 8
L586:   iconst_0
L587:   putfield Field packet pos I
L590:   aload 8
L592:   iload 10
L594:   invokevirtual Method packet g64encoded (I)Ljava/lang/String;
L597:   astore 11
L599:   new java/lang/StringBuffer
L602:   dup
L603:   aload_0
L604:   getfield Field passwordapp_de codebase Ljava/lang/String;
L607:   invokestatic Method java/lang/String valueOf (Ljava/lang/Object;)Ljava/lang/String;
L610:   invokespecial Method java/lang/StringBuffer <init> (Ljava/lang/String;)V
L613:   aload 9
L615:   invokevirtual Method java/lang/StringBuffer append (Ljava/lang/String;)Ljava/lang/StringBuffer;
L618:   invokevirtual Method java/lang/StringBuffer toString ()Ljava/lang/String;
L621:   astore 12
        .catch java/lang/Throwable from L623 to L939 using L940
L623:   new java/net/URL
L626:   dup
L627:   aload 12
L629:   invokespecial Method java/net/URL <init> (Ljava/lang/String;)V
L632:   astore 13
L634:   aload 13
L636:   invokevirtual Method java/net/URL openConnection ()Ljava/net/URLConnection;
L639:   astore 14
L641:   aload 14
L643:   iconst_1
L644:   invokevirtual Method java/net/URLConnection setDoInput (Z)V
L647:   aload 14
L649:   iconst_1
L650:   invokevirtual Method java/net/URLConnection setDoOutput (Z)V
L653:   new java/io/OutputStreamWriter
L656:   dup
L657:   aload 14
L659:   invokevirtual Method java/net/URLConnection getOutputStream ()Ljava/io/OutputStream;
L662:   invokespecial Method java/io/OutputStreamWriter <init> (Ljava/io/OutputStream;)V
L665:   astore 15
L667:   aload 15
L669:   new java/lang/StringBuffer
L672:   dup
L673:   ldc "data1="
L675:   invokespecial Method java/lang/StringBuffer <init> (Ljava/lang/String;)V
L678:   aload 7
L680:   invokestatic Method passwordapp_de urlencode (Ljava/lang/String;)Ljava/lang/String;
L683:   invokevirtual Method java/lang/StringBuffer append (Ljava/lang/String;)Ljava/lang/StringBuffer;
L686:   ldc "&data2="
L688:   invokevirtual Method java/lang/StringBuffer append (Ljava/lang/String;)Ljava/lang/StringBuffer;
L691:   aload 11
L693:   invokestatic Method passwordapp_de urlencode (Ljava/lang/String;)Ljava/lang/String;
L696:   invokevirtual Method java/lang/StringBuffer append (Ljava/lang/String;)Ljava/lang/StringBuffer;
L699:   invokevirtual Method java/lang/StringBuffer toString ()Ljava/lang/String;
L702:   invokevirtual Method java/io/Writer write (Ljava/lang/String;)V
L705:   aload 15
L707:   invokevirtual Method java/io/OutputStreamWriter flush ()V
L710:   aload 14
L712:   invokevirtual Method java/net/URLConnection getInputStream ()Ljava/io/InputStream;
L715:   astore 16
L717:   aload 8
L719:   iconst_0
L720:   putfield Field packet pos I
L723:   goto L760
L726:   aload 16
L728:   aload 8
L730:   getfield Field packet data [B
L733:   aload 8
L735:   getfield Field packet pos I
L738:   aload 8
L740:   getfield Field packet data [B
L743:   arraylength
L744:   aload 8
L746:   getfield Field packet pos I
L749:   isub
L750:   invokevirtual Method java/io/InputStream read ([BII)I
L753:   iconst_m1
L754:   if_icmpne L760
L757:   goto L774
L760:   aload 8
L762:   getfield Field packet pos I
L765:   aload 8
L767:   getfield Field packet data [B
L770:   arraylength
L771:   if_icmplt L726
L774:   aload 8
L776:   iconst_0
L777:   putfield Field packet pos I
L780:   aload 15
L782:   invokevirtual Method java/io/OutputStreamWriter close ()V
L785:   aload 16
L787:   invokevirtual Method java/io/InputStream close ()V
L790:   aload 8
L792:   invokevirtual Method packet gstr ()Ljava/lang/String;
L795:   astore 17
L797:   aload_0
L798:   getfield Field passwordapp_de processingpage Ljava/awt/Panel;
L801:   iconst_0
L802:   invokevirtual Method java/awt/Component setVisible (Z)V
L805:   aload 17
L807:   ldc "ATTACK"
L809:   invokevirtual Method java/lang/String startsWith (Ljava/lang/String;)Z
L812:   ifeq L824
L815:   aload_0
L816:   getfield Field passwordapp_de blocked_attack_page Ljava/awt/Panel;
L819:   iconst_1
L820:   invokevirtual Method java/awt/Component setVisible (Z)V
L823:   return
L824:   aload_0
L825:   getfield Field passwordapp_de type I
L828:   iconst_2
L829:   if_icmpne L992
L832:   aload 17
L834:   ldc "PENDING"
L836:   invokevirtual Method java/lang/String startsWith (Ljava/lang/String;)Z
L839:   ifeq L851
L842:   aload_0
L843:   getfield Field passwordapp_de change_questions_success_page_pending Ljava/awt/Panel;
L846:   iconst_1
L847:   invokevirtual Method java/awt/Component setVisible (Z)V
L850:   return
L851:   aload 17
L853:   ldc "ACTIVE"
L855:   invokevirtual Method java/lang/String startsWith (Ljava/lang/String;)Z
L858:   ifeq L870
L861:   aload_0
L862:   getfield Field passwordapp_de change_questions_success_page_active Ljava/awt/Panel;
L865:   iconst_1
L866:   invokevirtual Method java/awt/Component setVisible (Z)V
L869:   return
L870:   aload 17
L872:   ldc "WRONG"
L874:   invokevirtual Method java/lang/String startsWith (Ljava/lang/String;)Z
L877:   ifeq L910
L880:   aload_0
L881:   getfield Field passwordapp_de wrongpassword_page Ljava/awt/Panel;
L884:   iconst_1
L885:   invokevirtual Method java/awt/Component setVisible (Z)V
L888:   aload_0
L889:   iconst_1
L890:   putfield Field passwordapp_de onreversepath Z
L893:   aload_0
L894:   aload_0
L895:   getfield Field passwordapp_de change_questions_page Ljava/awt/Panel;
L898:   putfield Field passwordapp_de showpanel Ljava/awt/Panel;
L901:   aload_0
L902:   aload_0
L903:   getfield Field passwordapp_de wrongpassword_page Ljava/awt/Panel;
L906:   putfield Field passwordapp_de hidepanel Ljava/awt/Panel;
L909:   return
L910:   aload_0
L911:   getfield Field passwordapp_de system_error_page Ljava/awt/Panel;
L914:   iconst_1
L915:   invokevirtual Method java/awt/Component setVisible (Z)V
L918:   aload_0
L919:   iconst_1
L920:   putfield Field passwordapp_de onreversepath Z
L923:   aload_0
L924:   aload_0
L925:   getfield Field passwordapp_de change_questions_page Ljava/awt/Panel;
L928:   putfield Field passwordapp_de showpanel Ljava/awt/Panel;
L931:   aload_0
L932:   aload_0
L933:   getfield Field passwordapp_de system_error_page Ljava/awt/Panel;
L936:   putfield Field passwordapp_de hidepanel Ljava/awt/Panel;
L939:   return
L940:   astore 13
L942:   aload 13
L944:   invokevirtual Method java/lang/Throwable printStackTrace ()V
L947:   aload_0
L948:   getfield Field passwordapp_de processingpage Ljava/awt/Panel;
L951:   iconst_0
L952:   invokevirtual Method java/awt/Component setVisible (Z)V
L955:   aload_0
L956:   getfield Field passwordapp_de system_error_page Ljava/awt/Panel;
L959:   iconst_1
L960:   invokevirtual Method java/awt/Component setVisible (Z)V
L963:   aload_0
L964:   iconst_1
L965:   putfield Field passwordapp_de onreversepath Z
L968:   aload_0
L969:   aload_0
L970:   getfield Field passwordapp_de system_error_page Ljava/awt/Panel;
L973:   putfield Field passwordapp_de hidepanel Ljava/awt/Panel;
L976:   aload_0
L977:   getfield Field passwordapp_de type I
L980:   iconst_2
L981:   if_icmpne L992
L984:   aload_0
L985:   aload_0
L986:   getfield Field passwordapp_de change_questions_page Ljava/awt/Panel;
L989:   putfield Field passwordapp_de showpanel Ljava/awt/Panel;
L992:   return
L993:   
        .linenumbertable
            L0 497
            L7 498
            L18 499
            L20 500
            L25 501
            L45 500
            L56 503
            L66 504
            L71 505
            L78 506
            L82 507
            L95 508
            L105 509
            L115 510
            L123 511
            L127 510
            L130 512
            L138 513
            L142 514
            L147 512
            L150 517
            L160 519
            L165 520
            L166 524
            L174 525
            L178 526
            L183 527
            L190 526
            L199 530
            L212 531
            L218 532
            L224 533
            L233 532
            L243 535
            L256 536
            L263 537
            L269 538
            L278 541
            L292 542
            L298 543
            L307 544
            L316 547
            L324 548
            L342 549
            L362 550
            L385 551
            L405 552
            L428 553
            L448 554
            L471 555
            L491 556
            L514 557
            L534 558
            L557 559
            L561 547
            L564 561
            L565 565
            L571 568
            L578 569
            L584 570
            L590 571
            L599 574
            L623 575
            L623 577
            L634 578
            L641 579
            L647 580
            L653 581
            L667 582
            L705 583
            L710 584
            L717 586
            L723 587
            L726 588
            L760 587
            L774 590
            L780 591
            L785 592
            L790 594
            L797 596
            L805 598
            L815 600
            L823 598
            L824 601
            L832 602
            L842 604
            L850 602
            L851 605
            L861 607
            L869 605
            L870 608
            L880 610
            L888 611
            L893 612
            L901 613
            L909 608
            L910 615
            L918 616
            L923 617
            L931 618
            L939 575
            L940 621
            L942 622
            L947 624
            L955 625
            L963 626
            L968 627
            L976 629
            L984 630
            L992 496
        .end linenumbertable
    .end code
.end method

.method public keyReleased : (Ljava/awt/event/KeyEvent;)V
    .code stack 0 locals 2
L0:     return
L1:     
        .linenumbertable
            L0 635
        .end linenumbertable
    .end code
.end method

.method public keyTyped : (Ljava/awt/event/KeyEvent;)V
    .code stack 0 locals 2
L0:     return
L1:     
        .linenumbertable
            L0 638
        .end linenumbertable
    .end code
.end method

.method public keyPressed : (Ljava/awt/event/KeyEvent;)V
    .code stack 5 locals 5
L0:     aload_1
L1:     invokevirtual Method java/awt/event/KeyEvent getKeyCode ()I
L4:     istore_2
L5:     aload_0
L6:     getfield Field passwordapp_de type I
L9:     iconst_4
L10:    if_icmpne L308
L13:    iconst_0
L14:    istore_3
L15:    iload_2
L16:    bipush 37
L18:    if_icmpne L44
L21:    aload_0
L22:    aload_0
L23:    dup
L24:    getfield Field passwordapp_de debug_panel I
L27:    dup_x1
L28:    iconst_1
L29:    isub
L30:    putfield Field passwordapp_de debug_panel I
L33:    bipush 28
L35:    irem
L36:    putfield Field passwordapp_de debug_panel I
L39:    iconst_1
L40:    istore_3
L41:    goto L62
L44:    iload_2
L45:    bipush 39
L47:    if_icmpne L62
L50:    aload_0
L51:    dup
L52:    getfield Field passwordapp_de debug_panel I
L55:    iconst_1
L56:    iadd
L57:    putfield Field passwordapp_de debug_panel I
L60:    iconst_1
L61:    istore_3
L62:    iload_3
L63:    ifeq L300
L66:    aload_0
L67:    getfield Field passwordapp_de processingpage Ljava/awt/Panel;
L70:    iconst_0
L71:    invokevirtual Method java/awt/Component setVisible (Z)V
L74:    aload_0
L75:    getfield Field passwordapp_de system_error_page Ljava/awt/Panel;
L78:    iconst_0
L79:    invokevirtual Method java/awt/Component setVisible (Z)V
L82:    aload_0
L83:    getfield Field passwordapp_de blocked_query_page Ljava/awt/Panel;
L86:    iconst_0
L87:    invokevirtual Method java/awt/Component setVisible (Z)V
L90:    aload_0
L91:    getfield Field passwordapp_de blocked_attack_page Ljava/awt/Panel;
L94:    iconst_0
L95:    invokevirtual Method java/awt/Component setVisible (Z)V
L98:    aload_0
L99:    getfield Field passwordapp_de wrongpassword_page Ljava/awt/Panel;
L102:   iconst_0
L103:   invokevirtual Method java/awt/Component setVisible (Z)V
L106:   aload_0
L107:   getfield Field passwordapp_de change_questions_tooshort_page Ljava/awt/Panel;
L110:   iconst_0
L111:   invokevirtual Method java/awt/Component setVisible (Z)V
L114:   aload_0
L115:   getfield Field passwordapp_de change_questions_samequestions_page Ljava/awt/Panel;
L118:   iconst_0
L119:   invokevirtual Method java/awt/Component setVisible (Z)V
L122:   aload_0
L123:   getfield Field passwordapp_de change_questions_sameanswers_page Ljava/awt/Panel;
L126:   iconst_0
L127:   invokevirtual Method java/awt/Component setVisible (Z)V
L130:   aload_0
L131:   getfield Field passwordapp_de change_questions_page Ljava/awt/Panel;
L134:   iconst_0
L135:   invokevirtual Method java/awt/Component setVisible (Z)V
L138:   aload_0
L139:   getfield Field passwordapp_de debug_panel I
L142:   tableswitch 0
            L192
            L203
            L214
            L225
            L236
            L247
            L258
            L269
            L280
            default : L291
L192:   aload_0
L193:   getfield Field passwordapp_de processingpage Ljava/awt/Panel;
L196:   iconst_1
L197:   invokevirtual Method java/awt/Component setVisible (Z)V
L200:   goto L291
L203:   aload_0
L204:   getfield Field passwordapp_de system_error_page Ljava/awt/Panel;
L207:   iconst_1
L208:   invokevirtual Method java/awt/Component setVisible (Z)V
L211:   goto L291
L214:   aload_0
L215:   getfield Field passwordapp_de blocked_query_page Ljava/awt/Panel;
L218:   iconst_1
L219:   invokevirtual Method java/awt/Component setVisible (Z)V
L222:   goto L291
L225:   aload_0
L226:   getfield Field passwordapp_de blocked_attack_page Ljava/awt/Panel;
L229:   iconst_1
L230:   invokevirtual Method java/awt/Component setVisible (Z)V
L233:   goto L291
L236:   aload_0
L237:   getfield Field passwordapp_de wrongpassword_page Ljava/awt/Panel;
L240:   iconst_1
L241:   invokevirtual Method java/awt/Component setVisible (Z)V
L244:   goto L291
L247:   aload_0
L248:   getfield Field passwordapp_de change_questions_tooshort_page Ljava/awt/Panel;
L251:   iconst_1
L252:   invokevirtual Method java/awt/Component setVisible (Z)V
L255:   goto L291
L258:   aload_0
L259:   getfield Field passwordapp_de change_questions_samequestions_page Ljava/awt/Panel;
L262:   iconst_1
L263:   invokevirtual Method java/awt/Component setVisible (Z)V
L266:   goto L291
L269:   aload_0
L270:   getfield Field passwordapp_de change_questions_sameanswers_page Ljava/awt/Panel;
L273:   iconst_1
L274:   invokevirtual Method java/awt/Component setVisible (Z)V
L277:   goto L291
L280:   aload_0
L281:   getfield Field passwordapp_de change_questions_page Ljava/awt/Panel;
L284:   iconst_1
L285:   invokevirtual Method java/awt/Component setVisible (Z)V
L288:   goto L291
L291:   aload_0
L292:   invokevirtual Method java/awt/Container validate ()V
L295:   aload_1
L296:   invokevirtual Method java/awt/event/InputEvent consume ()V
L299:   return
L300:   getstatic Field java/lang/System out Ljava/io/PrintStream;
L303:   ldc "Didn't call change_panel!"
L305:   invokevirtual Method java/io/PrintStream println (Ljava/lang/String;)V
L308:   iload_2
L309:   bipush 8
L311:   if_icmpeq L346
L314:   iload_2
L315:   bipush 127
L317:   if_icmpeq L346
L320:   aload_1
L321:   invokevirtual Method java/awt/event/KeyEvent isActionKey ()Z
L324:   ifne L346
L327:   aload_1
L328:   invokevirtual Method java/awt/event/InputEvent getModifiers ()I
L331:   iconst_2
L332:   iand
L333:   ifne L346
L336:   aload_1
L337:   invokevirtual Method java/awt/event/InputEvent getModifiers ()I
L340:   bipush 8
L342:   iand
L343:   ifeq L347
L346:   return
L347:   aload_1
L348:   invokevirtual Method java/util/EventObject getSource ()Ljava/lang/Object;
L351:   astore_3
L352:   aload_3
L353:   instanceof java/awt/TextField
L356:   ifeq L399
L359:   aload_3
L360:   checkcast java/awt/TextField
L363:   astore 4
L365:   aload 4
L367:   invokevirtual Method java/awt/TextComponent getText ()Ljava/lang/String;
L370:   invokevirtual Method java/lang/String length ()I
L373:   aload 4
L375:   invokevirtual Method java/awt/TextField getColumns ()I
L378:   if_icmplt L443
L381:   aload 4
L383:   invokevirtual Method java/awt/TextComponent getSelectedText ()Ljava/lang/String;
L386:   ldc ""
L388:   invokevirtual Method java/lang/String equals (Ljava/lang/Object;)Z
L391:   ifeq L443
L394:   aload_1
L395:   invokevirtual Method java/awt/event/InputEvent consume ()V
L398:   return
L399:   aload_3
L400:   instanceof java/awt/TextArea
L403:   ifeq L443
L406:   aload_3
L407:   checkcast java/awt/TextArea
L410:   astore 4
L412:   aload 4
L414:   invokevirtual Method java/awt/TextComponent getText ()Ljava/lang/String;
L417:   invokevirtual Method java/lang/String length ()I
L420:   sipush 400
L423:   if_icmplt L443
L426:   aload 4
L428:   invokevirtual Method java/awt/TextComponent getSelectedText ()Ljava/lang/String;
L431:   ldc ""
L433:   invokevirtual Method java/lang/String equals (Ljava/lang/Object;)Z
L436:   ifeq L443
L439:   aload_1
L440:   invokevirtual Method java/awt/event/InputEvent consume ()V
L443:   return
L444:   
        .linenumbertable
            L0 645
            L5 647
            L13 648
            L15 650
            L21 651
            L39 652
            L41 650
            L44 654
            L50 655
            L60 656
            L62 659
            L66 660
            L74 661
            L82 662
            L90 663
            L98 664
            L106 665
            L114 666
            L122 667
            L130 668
            L138 670
            L192 672
            L200 673
            L203 675
            L211 676
            L214 678
            L222 679
            L225 681
            L233 682
            L236 684
            L244 685
            L247 687
            L255 688
            L258 690
            L266 691
            L269 693
            L277 694
            L280 696
            L288 697
            L291 699
            L295 700
            L299 701
            L300 703
            L308 705
            L347 707
            L352 708
            L359 709
            L365 710
            L398 708
            L399 712
            L406 713
            L412 714
            L443 644
        .end linenumbertable
    .end code
.end method

.method public textValueChanged : (Ljava/awt/event/TextEvent;)V
    .code stack 4 locals 4
L0:     aload_1
L1:     invokevirtual Method java/util/EventObject getSource ()Ljava/lang/Object;
L4:     astore_2
L5:     aload_2
L6:     instanceof java/awt/TextField
L9:     ifeq L56
L12:    aload_2
L13:    checkcast java/awt/TextField
L16:    astore_3
L17:    aload_3
L18:    invokevirtual Method java/awt/TextComponent getText ()Ljava/lang/String;
L21:    invokevirtual Method java/lang/String length ()I
L24:    aload_3
L25:    invokevirtual Method java/awt/TextField getColumns ()I
L28:    if_icmple L103
L31:    aload_3
L32:    aload_3
L33:    invokevirtual Method java/awt/TextComponent getText ()Ljava/lang/String;
L36:    iconst_0
L37:    aload_3
L38:    invokevirtual Method java/awt/TextField getColumns ()I
L41:    invokevirtual Method java/lang/String substring (II)Ljava/lang/String;
L44:    invokevirtual Method java/awt/TextComponent setText (Ljava/lang/String;)V
L47:    aload_3
L48:    aload_3
L49:    invokevirtual Method java/awt/TextField getColumns ()I
L52:    invokevirtual Method java/awt/TextComponent setCaretPosition (I)V
L55:    return
L56:    aload_2
L57:    instanceof java/awt/TextArea
L60:    ifeq L103
L63:    aload_2
L64:    checkcast java/awt/TextArea
L67:    astore_3
L68:    aload_3
L69:    invokevirtual Method java/awt/TextComponent getText ()Ljava/lang/String;
L72:    invokevirtual Method java/lang/String length ()I
L75:    sipush 400
L78:    if_icmple L103
L81:    aload_3
L82:    aload_3
L83:    invokevirtual Method java/awt/TextComponent getText ()Ljava/lang/String;
L86:    iconst_0
L87:    sipush 400
L90:    invokevirtual Method java/lang/String substring (II)Ljava/lang/String;
L93:    invokevirtual Method java/awt/TextComponent setText (Ljava/lang/String;)V
L96:    aload_3
L97:    sipush 400
L100:   invokevirtual Method java/awt/TextComponent setCaretPosition (I)V
L103:   return
L104:   
        .linenumbertable
            L0 719
            L5 720
            L12 721
            L17 722
            L31 723
            L47 724
            L55 720
            L56 727
            L63 728
            L68 729
            L81 730
            L96 731
            L103 718
        .end linenumbertable
    .end code
.end method

.method public destroy : ()V
    .code stack 0 locals 1
L0:     return
L1:     
        .linenumbertable
            L0 736
        .end linenumbertable
    .end code
.end method

.method public static final findcachedir : ()Ljava/lang/String;
    .code stack 5 locals 5
L0:     bipush 12
L2:     anewarray java/lang/String
L5:     dup
L6:     iconst_0
L7:     ldc "c:/windows/"
L9:     aastore
L10:    dup
L11:    iconst_1
L12:    ldc "c:/winnt/"
L14:    aastore
L15:    dup
L16:    iconst_2
L17:    ldc "d:/windows/"
L19:    aastore
L20:    dup
L21:    iconst_3
L22:    ldc "d:/winnt/"
L24:    aastore
L25:    dup
L26:    iconst_4
L27:    ldc "e:/windows/"
L29:    aastore
L30:    dup
L31:    iconst_5
L32:    ldc "e:/winnt/"
L34:    aastore
L35:    dup
L36:    bipush 6
L38:    ldc "f:/windows/"
L40:    aastore
L41:    dup
L42:    bipush 7
L44:    ldc "f:/winnt/"
L46:    aastore
L47:    dup
L48:    bipush 8
L50:    ldc "c:/"
L52:    aastore
L53:    dup
L54:    bipush 9
L56:    ldc "~/"
L58:    aastore
L59:    dup
L60:    bipush 10
L62:    ldc "/tmp/"
L64:    aastore
L65:    dup
L66:    bipush 11
L68:    ldc ""
L70:    aastore
L71:    astore_0
L72:    ldc ".file_store_32"
L74:    astore_1
L75:    iconst_0
L76:    istore_2
L77:    goto L189
        .catch java/lang/Exception from L80 to L182 using L182
L80:    aload_0
L81:    iload_2
L82:    aaload
L83:    astore_3
L84:    aload_3
L85:    invokevirtual Method java/lang/String length ()I
L88:    ifle L112
L91:    new java/io/File
L94:    dup
L95:    aload_3
L96:    invokespecial Method java/io/File <init> (Ljava/lang/String;)V
L99:    astore 4
L101:   aload 4
L103:   invokevirtual Method java/io/File exists ()Z
L106:   ifne L112
L109:   goto L186
L112:   new java/io/File
L115:   dup
L116:   new java/lang/StringBuffer
L119:   dup
L120:   aload_3
L121:   invokestatic Method java/lang/String valueOf (Ljava/lang/Object;)Ljava/lang/String;
L124:   invokespecial Method java/lang/StringBuffer <init> (Ljava/lang/String;)V
L127:   aload_1
L128:   invokevirtual Method java/lang/StringBuffer append (Ljava/lang/String;)Ljava/lang/StringBuffer;
L131:   invokevirtual Method java/lang/StringBuffer toString ()Ljava/lang/String;
L134:   invokespecial Method java/io/File <init> (Ljava/lang/String;)V
L137:   astore 4
L139:   aload 4
L141:   invokevirtual Method java/io/File exists ()Z
L144:   ifne L158
L147:   aload 4
L149:   invokevirtual Method java/io/File mkdir ()Z
L152:   ifne L158
L155:   goto L186
L158:   new java/lang/StringBuffer
L161:   dup
L162:   aload_3
L163:   invokestatic Method java/lang/String valueOf (Ljava/lang/Object;)Ljava/lang/String;
L166:   invokespecial Method java/lang/StringBuffer <init> (Ljava/lang/String;)V
L169:   aload_1
L170:   invokevirtual Method java/lang/StringBuffer append (Ljava/lang/String;)Ljava/lang/StringBuffer;
L173:   ldc "/"
L175:   invokevirtual Method java/lang/StringBuffer append (Ljava/lang/String;)Ljava/lang/StringBuffer;
L178:   invokevirtual Method java/lang/StringBuffer toString ()Ljava/lang/String;
L181:   areturn
L182:   pop
L183:   goto L186
L186:   iinc 2 1
L189:   iload_2
L190:   aload_0
L191:   arraylength
L192:   if_icmplt L80
L195:   aconst_null
L196:   areturn
L197:   
        .linenumbertable
            L0 742
            L72 743
            L75 744
            L80 745
            L80 747
            L84 748
            L112 750
            L139 751
            L158 753
            L182 755
            L183 745
            L186 744
            L195 757
        .end linenumbertable
    .end code
.end method

.method private static final getuid : (Ljava/lang/String;)I
    .code stack 7 locals 3
        .catch java/lang/Exception from L0 to L95 using L98
L0:     new java/io/File
L3:     dup
L4:     new java/lang/StringBuffer
L7:     dup
L8:     aload_0
L9:     invokestatic Method java/lang/String valueOf (Ljava/lang/Object;)Ljava/lang/String;
L12:    invokespecial Method java/lang/StringBuffer <init> (Ljava/lang/String;)V
L15:    ldc "uid.dat"
L17:    invokevirtual Method java/lang/StringBuffer append (Ljava/lang/String;)Ljava/lang/StringBuffer;
L20:    invokevirtual Method java/lang/StringBuffer toString ()Ljava/lang/String;
L23:    invokespecial Method java/io/File <init> (Ljava/lang/String;)V
L26:    astore_1
L27:    aload_1
L28:    invokevirtual Method java/io/File exists ()Z
L31:    ifeq L45
L34:    aload_1
L35:    invokevirtual Method java/io/File length ()J
L38:    ldc2_w 4L
L41:    lcmp
L42:    ifge L99
L45:    new java/io/DataOutputStream
L48:    dup
L49:    new java/io/FileOutputStream
L52:    dup
L53:    new java/lang/StringBuffer
L56:    dup
L57:    aload_0
L58:    invokestatic Method java/lang/String valueOf (Ljava/lang/Object;)Ljava/lang/String;
L61:    invokespecial Method java/lang/StringBuffer <init> (Ljava/lang/String;)V
L64:    ldc "uid.dat"
L66:    invokevirtual Method java/lang/StringBuffer append (Ljava/lang/String;)Ljava/lang/StringBuffer;
L69:    invokevirtual Method java/lang/StringBuffer toString ()Ljava/lang/String;
L72:    invokespecial Method java/io/FileOutputStream <init> (Ljava/lang/String;)V
L75:    invokespecial Method java/io/DataOutputStream <init> (Ljava/io/OutputStream;)V
L78:    astore_2
L79:    aload_2
L80:    invokestatic Method java/lang/Math random ()D
L83:    ldc2_w 9.9999999e7
L86:    dmul
L87:    d2i
L88:    invokevirtual Method java/io/DataOutputStream writeInt (I)V
L91:    aload_2
L92:    invokevirtual Method java/io/FilterOutputStream close ()V
L95:    goto L99
L98:    pop
        .catch java/lang/Exception from L99 to L146 using L146
L99:    new java/io/DataInputStream
L102:   dup
L103:   new java/io/FileInputStream
L106:   dup
L107:   new java/lang/StringBuffer
L110:   dup
L111:   aload_0
L112:   invokestatic Method java/lang/String valueOf (Ljava/lang/Object;)Ljava/lang/String;
L115:   invokespecial Method java/lang/StringBuffer <init> (Ljava/lang/String;)V
L118:   ldc "uid.dat"
L120:   invokevirtual Method java/lang/StringBuffer append (Ljava/lang/String;)Ljava/lang/StringBuffer;
L123:   invokevirtual Method java/lang/StringBuffer toString ()Ljava/lang/String;
L126:   invokespecial Method java/io/FileInputStream <init> (Ljava/lang/String;)V
L129:   invokespecial Method java/io/DataInputStream <init> (Ljava/io/InputStream;)V
L132:   astore_1
L133:   aload_1
L134:   invokevirtual Method java/io/DataInputStream readInt ()I
L137:   istore_2
L138:   aload_1
L139:   invokevirtual Method java/io/FilterInputStream close ()V
L142:   iload_2
L143:   iconst_1
L144:   iadd
L145:   ireturn
L146:   pop
L147:   iconst_0
L148:   ireturn
L149:   
        .linenumbertable
            L0 762
            L0 763
            L27 764
            L45 765
            L79 766
            L95 762
            L98 769
            L99 771
            L99 772
            L133 773
            L142 774
            L146 776
            L147 777
        .end linenumbertable
    .end code
.end method

.method public <init> : ()V
    .code stack 5 locals 1
L0:     aload_0
L1:     invokespecial Method java/applet/Applet <init> ()V
L4:     aload_0
L5:     iconst_5
L6:     anewarray java/awt/TextField
L9:     putfield Field passwordapp_de question [Ljava/awt/TextField;
L12:    aload_0
L13:    iconst_5
L14:    anewarray java/awt/TextField
L17:    putfield Field passwordapp_de recov [Ljava/awt/TextField;
L20:    aload_0
L21:    new java/math/BigInteger
L24:    dup
L25:    ldc "78609176622342907144495556282156869501821674615375259616632158913026262002609"
L27:    invokespecial Method java/math/BigInteger <init> (Ljava/lang/String;)V
L30:    putfield Field passwordapp_de key_e Ljava/math/BigInteger;
L33:    aload_0
L34:    new java/math/BigInteger
L37:    dup
L38:    ldc "8520946092827349680104442275636555624577884266514482949166183637641027716807216207253679971387983199046976999249798814352350744205728948100629864118760909"
L40:    invokespecial Method java/math/BigInteger <init> (Ljava/lang/String;)V
L43:    putfield Field passwordapp_de key_n Ljava/math/BigInteger;
L46:    aload_0
L47:    bipush 17
L49:    anewarray java/lang/String
L52:    dup
L53:    iconst_0
L54:    ldc "Wo wurden Sie geboren?"
L56:    aastore
L57:    dup
L58:    iconst_1
L59:    ldc "Wie hie\u00DF Ihr erster Lehrer (Nachname)?"
L61:    aastore
L62:    dup
L63:    iconst_2
L64:    ldc "Welchen 2. Vornamen hat Ihr Vater?"
L66:    aastore
L67:    dup
L68:    iconst_3
L69:    ldc "Welchen 2. Vornamen hat Ihre Mutter?"
L71:    aastore
L72:    dup
L73:    iconst_4
L74:    ldc "Wie hie\u00DF Ihr erster bester Freund?"
L76:    aastore
L77:    dup
L78:    iconst_5
L79:    ldc "Wie hei\u00DFt Ihr Lieblingsurlaubsort?"
L81:    aastore
L82:    dup
L83:    bipush 6
L85:    ldc "Wie hie\u00DF Ihr erstes Haustier?"
L87:    aastore
L88:    dup
L89:    bipush 7
L91:    ldc "Wie lautet der Name Ihrer ersten Schule?"
L93:    aastore
L94:    dup
L95:    bipush 8
L97:    ldc "Wie lautet der M\u00E4dchenname Ihrer Mutter?"
L99:    aastore
L100:   dup
L101:   bipush 9
L103:   ldc "Wie hie\u00DF Ihr(e) erste(r) Freund(in)?"
L105:   aastore
L106:   dup
L107:   bipush 10
L109:   ldc "Wer ist Ihr/e Lieblingsschauspieler/in?"
L111:   aastore
L112:   dup
L113:   bipush 11
L115:   ldc "Wer ist Ihr/e Lieblingsautor/in?"
L117:   aastore
L118:   dup
L119:   bipush 12
L121:   ldc "Wer ist Ihr/e Lieblingsmusiker/in?"
L123:   aastore
L124:   dup
L125:   bipush 13
L127:   ldc "Wer ist Ihre Lieblingscomicfigur?"
L129:   aastore
L130:   dup
L131:   bipush 14
L133:   ldc "Wie hei\u00DFt Ihr Lieblingsbuch?"
L135:   aastore
L136:   dup
L137:   bipush 15
L139:   ldc "Was ist Ihr Leibgericht?"
L141:   aastore
L142:   dup
L143:   bipush 16
L145:   ldc "Wie hei\u00DFt Ihr Lieblingsfilm?"
L147:   aastore
L148:   putfield Field passwordapp_de example_questions [Ljava/lang/String;
L151:   aload_0
L152:   iconst_0
L153:   putfield Field passwordapp_de initialised Z
L156:   return
L157:   
        .linenumbertable
            L0 9
            L4 19
            L12 20
            L20 25
            L33 26
            L46 62
            L151 64
            L156 9
        .end linenumbertable
    .end code
.end method

.method static <clinit> : ()V
    .code stack 4 locals 0
L0:     iconst_4
L1:     anewarray java/lang/String
L4:     dup
L5:     iconst_0
L6:     ldc "http://recovery_questions.runescape.com/"
L8:     aastore
L9:     dup
L10:    iconst_1
L11:    ldc "http://webtestwip1.runescape.com:16304/"
L13:    aastore
L14:    dup
L15:    iconst_2
L16:    ldc "http://webtestrc1.runescape.com:16304/"
L18:    aastore
L19:    dup
L20:    iconst_3
L21:    ldc "http://local.runescape.com:16304/"
L23:    aastore
L24:    putstatic Field passwordapp_de allowedlist [Ljava/lang/String;
L27:    return
L28:    
        .linenumbertable
            L0 11
            L11 12
            L13 11
            L16 13
            L18 11
            L21 14
            L23 11
            L27 9
        .end linenumbertable
    .end code
.end method
.sourcefile "passwordapp_de.java"
.end class
