.version 45 3
.class public final super RKAYAFDQ
.super java/lang/Object
.field private static a I
.field private static b Z
.field private static c I
.field private static d I
.field private static e Z
.field private static f I
.field private static g B
.field private static h I
.field private static i Z
.field private static j I
.field private static k I
.field private static l B
.field private static m I
.field private static n Z
.field private static o [I
.field private static p [[C
.field private static q [[[B
.field private static r [[C
.field private static s [[C
.field private static t [I
.field private static final u [Ljava/lang/String;
.field public static v Z

.method public static final a : (LXTGLDHGX;)V
    .code stack 6 locals 6
L0:     getstatic Field RKAYAFDQ v Z
L3:     istore 5
L5:     new MBMGIXGO
L8:     dup
L9:     aload_0
L10:    ldc "fragmentsenc.txt"
L12:    aconst_null
L13:    invokevirtual Method XTGLDHGX a (Ljava/lang/String;[B)[B
L16:    sipush 891
L19:    invokespecial Method MBMGIXGO <init> ([BI)V
L22:    astore_1
L23:    new MBMGIXGO
L26:    dup
L27:    aload_0
L28:    ldc "badenc.txt"
L30:    aconst_null
L31:    invokevirtual Method XTGLDHGX a (Ljava/lang/String;[B)[B
L34:    sipush 891
L37:    invokespecial Method MBMGIXGO <init> ([BI)V
L40:    astore_2
L41:    new MBMGIXGO
L44:    dup
L45:    aload_0
L46:    ldc "domainenc.txt"
L48:    aconst_null
L49:    invokevirtual Method XTGLDHGX a (Ljava/lang/String;[B)[B
L52:    sipush 891
L55:    invokespecial Method MBMGIXGO <init> ([BI)V
L58:    astore_3
L59:    new MBMGIXGO
L62:    dup
L63:    aload_0
L64:    ldc "tldlist.txt"
L66:    aconst_null
L67:    invokevirtual Method XTGLDHGX a (Ljava/lang/String;[B)[B
L70:    sipush 891
L73:    invokespecial Method MBMGIXGO <init> ([BI)V
L76:    astore 4
L78:    aload_1
L79:    aload_2
L80:    aload_3
L81:    aload 4
L83:    invokestatic Method RKAYAFDQ a (LMBMGIXGO;LMBMGIXGO;LMBMGIXGO;LMBMGIXGO;)V
L86:    getstatic Field PKVMXVTO e Z
L89:    ifeq L105
L92:    iload 5
L94:    ifeq L101
L97:    iconst_0
L98:    goto L102
L101:   iconst_1
L102:   putstatic Field RKAYAFDQ v Z
L105:   return
L106:   
    .end code
.end method

.method private static final a : (LMBMGIXGO;LMBMGIXGO;LMBMGIXGO;LMBMGIXGO;)V
    .code stack 2 locals 4
L0:     sipush 9121
L3:     aload_1
L4:     invokestatic Method RKAYAFDQ a (ILMBMGIXGO;)V
L7:     aload_2
L8:     bipush -28
L10:    invokestatic Method RKAYAFDQ a (LMBMGIXGO;B)V
L13:    aload_0
L14:    iconst_1
L15:    invokestatic Method RKAYAFDQ a (LMBMGIXGO;Z)V
L18:    iconst_2
L19:    aload_3
L20:    invokestatic Method RKAYAFDQ a (BLMBMGIXGO;)V
L23:    return
L24:    
    .end code
.end method

.method private static final a : (BLMBMGIXGO;)V
    .code stack 4 locals 7
L0:     getstatic Field RKAYAFDQ v Z
L3:     istore 6
        .catch java/lang/RuntimeException from L5 to L98 using L99
L5:     aload_1
L6:     invokevirtual Method MBMGIXGO h ()I
L9:     istore_2
L10:    iload_2
L11:    multianewarray [[C 1
L15:    putstatic Field RKAYAFDQ s [[C
L18:    iload_2
L19:    newarray int
L21:    putstatic Field RKAYAFDQ t [I
L24:    iload_0
L25:    iconst_2
L26:    if_icmpeq L30
L29:    return
L30:    iconst_0
L31:    istore_3
L32:    iload 6
L34:    ifeq L93
L37:    getstatic Field RKAYAFDQ t [I
L40:    iload_3
L41:    aload_1
L42:    invokevirtual Method MBMGIXGO c ()I
L45:    iastore
L46:    aload_1
L47:    invokevirtual Method MBMGIXGO c ()I
L50:    newarray char
L52:    astore 4
L54:    iconst_0
L55:    istore 5
L57:    iload 6
L59:    ifeq L75
L62:    aload 4
L64:    iload 5
L66:    aload_1
L67:    invokevirtual Method MBMGIXGO c ()I
L70:    i2c
L71:    castore
L72:    iinc 5 1
L75:    iload 5
L77:    aload 4
L79:    arraylength
L80:    if_icmplt L62
L83:    getstatic Field RKAYAFDQ s [[C
L86:    iload_3
L87:    aload 4
L89:    aastore
L90:    iinc 3 1
L93:    iload_3
L94:    iload_2
L95:    if_icmplt L37
L98:    return
L99:    astore_2
L100:   new java/lang/StringBuffer
L103:   dup
L104:   ldc "65552, "
L106:   invokespecial Method java/lang/StringBuffer <init> (Ljava/lang/String;)V
L109:   iload_0
L110:   invokevirtual Method java/lang/StringBuffer append (I)Ljava/lang/StringBuffer;
L113:   ldc ", "
L115:   invokevirtual Method java/lang/StringBuffer append (Ljava/lang/String;)Ljava/lang/StringBuffer;
L118:   aload_1
L119:   invokevirtual Method java/lang/StringBuffer append (Ljava/lang/Object;)Ljava/lang/StringBuffer;
L122:   ldc ", "
L124:   invokevirtual Method java/lang/StringBuffer append (Ljava/lang/String;)Ljava/lang/StringBuffer;
L127:   aload_2
L128:   invokevirtual Method java/lang/Throwable toString ()Ljava/lang/String;
L131:   invokevirtual Method java/lang/StringBuffer append (Ljava/lang/String;)Ljava/lang/StringBuffer;
L134:   invokevirtual Method java/lang/StringBuffer toString ()Ljava/lang/String;
L137:   invokestatic Method sign/signlink reporterror (Ljava/lang/String;)V
L140:   new java/lang/RuntimeException
L143:   dup
L144:   invokespecial Method java/lang/RuntimeException <init> ()V
L147:   athrow
L148:   
    .end code
.end method

.method private static final a : (ILMBMGIXGO;)V
    .code stack 4 locals 3
        .catch java/lang/RuntimeException from L0 to L53 using L54
L0:     iload_0
L1:     sipush 9121
L4:     if_icmpeq L21
L7:     getstatic Field RKAYAFDQ n Z
L10:    ifeq L17
L13:    iconst_0
L14:    goto L18
L17:    iconst_1
L18:    putstatic Field RKAYAFDQ n Z
L21:    aload_1
L22:    invokevirtual Method MBMGIXGO h ()I
L25:    istore_2
L26:    iload_2
L27:    multianewarray [[C 1
L31:    putstatic Field RKAYAFDQ p [[C
L34:    iload_2
L35:    multianewarray [[[B 1
L39:    putstatic Field RKAYAFDQ q [[[B
L42:    aload_1
L43:    getstatic Field RKAYAFDQ p [[C
L46:    iconst_1
L47:    getstatic Field RKAYAFDQ q [[[B
L50:    invokestatic Method RKAYAFDQ a (LMBMGIXGO;[[CZ[[[B)V
L53:    return
L54:    astore_2
L55:    new java/lang/StringBuffer
L58:    dup
L59:    ldc "10223, "
L61:    invokespecial Method java/lang/StringBuffer <init> (Ljava/lang/String;)V
L64:    iload_0
L65:    invokevirtual Method java/lang/StringBuffer append (I)Ljava/lang/StringBuffer;
L68:    ldc ", "
L70:    invokevirtual Method java/lang/StringBuffer append (Ljava/lang/String;)Ljava/lang/StringBuffer;
L73:    aload_1
L74:    invokevirtual Method java/lang/StringBuffer append (Ljava/lang/Object;)Ljava/lang/StringBuffer;
L77:    ldc ", "
L79:    invokevirtual Method java/lang/StringBuffer append (Ljava/lang/String;)Ljava/lang/StringBuffer;
L82:    aload_2
L83:    invokevirtual Method java/lang/Throwable toString ()Ljava/lang/String;
L86:    invokevirtual Method java/lang/StringBuffer append (Ljava/lang/String;)Ljava/lang/StringBuffer;
L89:    invokevirtual Method java/lang/StringBuffer toString ()Ljava/lang/String;
L92:    invokestatic Method sign/signlink reporterror (Ljava/lang/String;)V
L95:    new java/lang/RuntimeException
L98:    dup
L99:    invokespecial Method java/lang/RuntimeException <init> ()V
L102:   athrow
L103:   
    .end code
.end method

.method private static final a : (LMBMGIXGO;B)V
    .code stack 3 locals 3
        .catch java/lang/RuntimeException from L0 to L30 using L31
L0:     aload_0
L1:     invokevirtual Method MBMGIXGO h ()I
L4:     istore_2
L5:     iload_2
L6:     multianewarray [[C 1
L10:    putstatic Field RKAYAFDQ r [[C
L13:    iload_1
L14:    bipush -28
L16:    if_icmpeq L20
L19:    return
L20:    getstatic Field RKAYAFDQ r [[C
L23:    aload_0
L24:    sipush -490
L27:    invokestatic Method RKAYAFDQ a ([[CLMBMGIXGO;I)V
L30:    return
L31:    astore_2
L32:    new java/lang/StringBuffer
L35:    dup
L36:    ldc "41706, "
L38:    invokespecial Method java/lang/StringBuffer <init> (Ljava/lang/String;)V
L41:    aload_0
L42:    invokevirtual Method java/lang/StringBuffer append (Ljava/lang/Object;)Ljava/lang/StringBuffer;
L45:    ldc ", "
L47:    invokevirtual Method java/lang/StringBuffer append (Ljava/lang/String;)Ljava/lang/StringBuffer;
L50:    iload_1
L51:    invokevirtual Method java/lang/StringBuffer append (I)Ljava/lang/StringBuffer;
L54:    ldc ", "
L56:    invokevirtual Method java/lang/StringBuffer append (Ljava/lang/String;)Ljava/lang/StringBuffer;
L59:    aload_2
L60:    invokevirtual Method java/lang/Throwable toString ()Ljava/lang/String;
L63:    invokevirtual Method java/lang/StringBuffer append (Ljava/lang/String;)Ljava/lang/StringBuffer;
L66:    invokevirtual Method java/lang/StringBuffer toString ()Ljava/lang/String;
L69:    invokestatic Method sign/signlink reporterror (Ljava/lang/String;)V
L72:    new java/lang/RuntimeException
L75:    dup
L76:    invokespecial Method java/lang/RuntimeException <init> ()V
L79:    athrow
L80:    
    .end code
.end method

.method private static final a : (LMBMGIXGO;Z)V
    .code stack 4 locals 3
        .catch java/lang/RuntimeException from L0 to L47 using L48
L0:     aload_0
L1:     invokevirtual Method MBMGIXGO h ()I
L4:     newarray int
L6:     putstatic Field RKAYAFDQ o [I
L9:     iconst_0
L10:    istore_2
L11:    getstatic Field RKAYAFDQ v Z
L14:    ifeq L29
L17:    getstatic Field RKAYAFDQ o [I
L20:    iload_2
L21:    aload_0
L22:    invokevirtual Method MBMGIXGO e ()I
L25:    iastore
L26:    iinc 2 1
L29:    iload_2
L30:    getstatic Field RKAYAFDQ o [I
L33:    arraylength
L34:    if_icmplt L17
L37:    iload_1
L38:    ifne L97
L41:    sipush 167
L44:    putstatic Field RKAYAFDQ d I
L47:    return
L48:    astore_2
L49:    new java/lang/StringBuffer
L52:    dup
L53:    ldc "99878, "
L55:    invokespecial Method java/lang/StringBuffer <init> (Ljava/lang/String;)V
L58:    aload_0
L59:    invokevirtual Method java/lang/StringBuffer append (Ljava/lang/Object;)Ljava/lang/StringBuffer;
L62:    ldc ", "
L64:    invokevirtual Method java/lang/StringBuffer append (Ljava/lang/String;)Ljava/lang/StringBuffer;
L67:    iload_1
L68:    invokevirtual Method java/lang/StringBuffer append (Z)Ljava/lang/StringBuffer;
L71:    ldc ", "
L73:    invokevirtual Method java/lang/StringBuffer append (Ljava/lang/String;)Ljava/lang/StringBuffer;
L76:    aload_2
L77:    invokevirtual Method java/lang/Throwable toString ()Ljava/lang/String;
L80:    invokevirtual Method java/lang/StringBuffer append (Ljava/lang/String;)Ljava/lang/StringBuffer;
L83:    invokevirtual Method java/lang/StringBuffer toString ()Ljava/lang/String;
L86:    invokestatic Method sign/signlink reporterror (Ljava/lang/String;)V
L89:    new java/lang/RuntimeException
L92:    dup
L93:    invokespecial Method java/lang/RuntimeException <init> ()V
L96:    athrow
L97:    return
L98:    
    .end code
.end method

.method private static final a : (LMBMGIXGO;[[CZ[[[B)V
    .code stack 4 locals 10
L0:     getstatic Field RKAYAFDQ v Z
L3:     istore 9
        .catch java/lang/RuntimeException from L5 to L152 using L153
L5:     iload_2
L6:     ifne L25
L9:     iconst_1
L10:    istore 4
L12:    iload 9
L14:    ifeq L20
L17:    iinc 4 1
L20:    iload 4
L22:    ifgt L17
L25:    iconst_0
L26:    istore 4
L28:    iload 9
L30:    ifeq L145
L33:    aload_0
L34:    invokevirtual Method MBMGIXGO c ()I
L37:    newarray char
L39:    astore 5
L41:    iconst_0
L42:    istore 6
L44:    iload 9
L46:    ifeq L62
L49:    aload 5
L51:    iload 6
L53:    aload_0
L54:    invokevirtual Method MBMGIXGO c ()I
L57:    i2c
L58:    castore
L59:    iinc 6 1
L62:    iload 6
L64:    aload 5
L66:    arraylength
L67:    if_icmplt L49
L70:    aload_1
L71:    iload 4
L73:    aload 5
L75:    aastore
L76:    aload_0
L77:    invokevirtual Method MBMGIXGO c ()I
L80:    iconst_2
L81:    multianewarray [[B 2
L85:    astore 7
L87:    iconst_0
L88:    istore 8
L90:    iload 9
L92:    ifeq L122
L95:    aload 7
L97:    iload 8
L99:    aaload
L100:   iconst_0
L101:   aload_0
L102:   invokevirtual Method MBMGIXGO c ()I
L105:   i2b
L106:   bastore
L107:   aload 7
L109:   iload 8
L111:   aaload
L112:   iconst_1
L113:   aload_0
L114:   invokevirtual Method MBMGIXGO c ()I
L117:   i2b
L118:   bastore
L119:   iinc 8 1
L122:   iload 8
L124:   aload 7
L126:   arraylength
L127:   if_icmplt L95
L130:   aload 7
L132:   arraylength
L133:   ifle L142
L136:   aload_3
L137:   iload 4
L139:   aload 7
L141:   aastore
L142:   iinc 4 1
L145:   iload 4
L147:   aload_1
L148:   arraylength
L149:   if_icmplt L33
L152:   return
L153:   astore 4
L155:   new java/lang/StringBuffer
L158:   dup
L159:   ldc "31244, "
L161:   invokespecial Method java/lang/StringBuffer <init> (Ljava/lang/String;)V
L164:   aload_0
L165:   invokevirtual Method java/lang/StringBuffer append (Ljava/lang/Object;)Ljava/lang/StringBuffer;
L168:   ldc ", "
L170:   invokevirtual Method java/lang/StringBuffer append (Ljava/lang/String;)Ljava/lang/StringBuffer;
L173:   aload_1
L174:   invokevirtual Method java/lang/StringBuffer append (Ljava/lang/Object;)Ljava/lang/StringBuffer;
L177:   ldc ", "
L179:   invokevirtual Method java/lang/StringBuffer append (Ljava/lang/String;)Ljava/lang/StringBuffer;
L182:   iload_2
L183:   invokevirtual Method java/lang/StringBuffer append (Z)Ljava/lang/StringBuffer;
L186:   ldc ", "
L188:   invokevirtual Method java/lang/StringBuffer append (Ljava/lang/String;)Ljava/lang/StringBuffer;
L191:   aload_3
L192:   invokevirtual Method java/lang/StringBuffer append (Ljava/lang/Object;)Ljava/lang/StringBuffer;
L195:   ldc ", "
L197:   invokevirtual Method java/lang/StringBuffer append (Ljava/lang/String;)Ljava/lang/StringBuffer;
L200:   aload 4
L202:   invokevirtual Method java/lang/Throwable toString ()Ljava/lang/String;
L205:   invokevirtual Method java/lang/StringBuffer append (Ljava/lang/String;)Ljava/lang/StringBuffer;
L208:   invokevirtual Method java/lang/StringBuffer toString ()Ljava/lang/String;
L211:   invokestatic Method sign/signlink reporterror (Ljava/lang/String;)V
L214:   new java/lang/RuntimeException
L217:   dup
L218:   invokespecial Method java/lang/RuntimeException <init> ()V
L221:   athrow
L222:   
    .end code
.end method

.method private static final a : ([[CLMBMGIXGO;I)V
    .code stack 4 locals 7
L0:     getstatic Field RKAYAFDQ v Z
L3:     istore 6
        .catch java/lang/RuntimeException from L5 to L68 using L69
L5:     iload_2
L6:     iflt L10
L9:     return
L10:    iconst_0
L11:    istore_3
L12:    iload 6
L14:    ifeq L62
L17:    aload_1
L18:    invokevirtual Method MBMGIXGO c ()I
L21:    newarray char
L23:    astore 4
L25:    iconst_0
L26:    istore 5
L28:    iload 6
L30:    ifeq L46
L33:    aload 4
L35:    iload 5
L37:    aload_1
L38:    invokevirtual Method MBMGIXGO c ()I
L41:    i2c
L42:    castore
L43:    iinc 5 1
L46:    iload 5
L48:    aload 4
L50:    arraylength
L51:    if_icmplt L33
L54:    aload_0
L55:    iload_3
L56:    aload 4
L58:    aastore
L59:    iinc 3 1
L62:    iload_3
L63:    aload_0
L64:    arraylength
L65:    if_icmplt L17
L68:    return
L69:    astore_3
L70:    new java/lang/StringBuffer
L73:    dup
L74:    ldc "79837, "
L76:    invokespecial Method java/lang/StringBuffer <init> (Ljava/lang/String;)V
L79:    aload_0
L80:    invokevirtual Method java/lang/StringBuffer append (Ljava/lang/Object;)Ljava/lang/StringBuffer;
L83:    ldc ", "
L85:    invokevirtual Method java/lang/StringBuffer append (Ljava/lang/String;)Ljava/lang/StringBuffer;
L88:    aload_1
L89:    invokevirtual Method java/lang/StringBuffer append (Ljava/lang/Object;)Ljava/lang/StringBuffer;
L92:    ldc ", "
L94:    invokevirtual Method java/lang/StringBuffer append (Ljava/lang/String;)Ljava/lang/StringBuffer;
L97:    iload_2
L98:    invokevirtual Method java/lang/StringBuffer append (I)Ljava/lang/StringBuffer;
L101:   ldc ", "
L103:   invokevirtual Method java/lang/StringBuffer append (Ljava/lang/String;)Ljava/lang/StringBuffer;
L106:   aload_3
L107:   invokevirtual Method java/lang/Throwable toString ()Ljava/lang/String;
L110:   invokevirtual Method java/lang/StringBuffer append (Ljava/lang/String;)Ljava/lang/StringBuffer;
L113:   invokevirtual Method java/lang/StringBuffer toString ()Ljava/lang/String;
L116:   invokestatic Method sign/signlink reporterror (Ljava/lang/String;)V
L119:   new java/lang/RuntimeException
L122:   dup
L123:   invokespecial Method java/lang/RuntimeException <init> ()V
L126:   athrow
L127:   
    .end code
.end method

.method private static final a : (Z[C)V
    .code stack 5 locals 6
L0:     getstatic Field RKAYAFDQ v Z
L3:     istore 5
        .catch java/lang/RuntimeException from L5 to L105 using L106
L5:     iconst_0
L6:     istore_2
L7:     iconst_0
L8:     istore_3
L9:     iload 5
L11:    ifeq L70
L14:    aload_1
L15:    iload_3
L16:    caload
L17:    getstatic Field RKAYAFDQ f I
L20:    invokestatic Method RKAYAFDQ a (CI)Z
L23:    ifeq L37
L26:    aload_1
L27:    iload_2
L28:    aload_1
L29:    iload_3
L30:    caload
L31:    castore
L32:    iload 5
L34:    ifeq L42
L37:    aload_1
L38:    iload_2
L39:    bipush 32
L41:    castore
L42:    iload_2
L43:    ifeq L64
L46:    aload_1
L47:    iload_2
L48:    caload
L49:    bipush 32
L51:    if_icmpne L64
L54:    aload_1
L55:    iload_2
L56:    iconst_1
L57:    isub
L58:    caload
L59:    bipush 32
L61:    if_icmpeq L67
L64:    iinc 2 1
L67:    iinc 3 1
L70:    iload_3
L71:    aload_1
L72:    arraylength
L73:    if_icmplt L14
L76:    iload_0
L77:    ifeq L81
L80:    return
L81:    iload_2
L82:    istore 4
L84:    iload 5
L86:    ifeq L98
L89:    aload_1
L90:    iload 4
L92:    bipush 32
L94:    castore
L95:    iinc 4 1
L98:    iload 4
L100:   aload_1
L101:   arraylength
L102:   if_icmplt L89
L105:   return
L106:   astore_2
L107:   new java/lang/StringBuffer
L110:   dup
L111:   ldc "14393, "
L113:   invokespecial Method java/lang/StringBuffer <init> (Ljava/lang/String;)V
L116:   iload_0
L117:   invokevirtual Method java/lang/StringBuffer append (Z)Ljava/lang/StringBuffer;
L120:   ldc ", "
L122:   invokevirtual Method java/lang/StringBuffer append (Ljava/lang/String;)Ljava/lang/StringBuffer;
L125:   aload_1
L126:   invokevirtual Method java/lang/StringBuffer append ([C)Ljava/lang/StringBuffer;
L129:   ldc ", "
L131:   invokevirtual Method java/lang/StringBuffer append (Ljava/lang/String;)Ljava/lang/StringBuffer;
L134:   aload_2
L135:   invokevirtual Method java/lang/Throwable toString ()Ljava/lang/String;
L138:   invokevirtual Method java/lang/StringBuffer append (Ljava/lang/String;)Ljava/lang/StringBuffer;
L141:   invokevirtual Method java/lang/StringBuffer toString ()Ljava/lang/String;
L144:   invokestatic Method sign/signlink reporterror (Ljava/lang/String;)V
L147:   new java/lang/RuntimeException
L150:   dup
L151:   invokespecial Method java/lang/RuntimeException <init> ()V
L154:   athrow
L155:   
    .end code
.end method

.method private static final a : (CI)Z
    .code stack 3 locals 3
        .catch java/lang/RuntimeException from L0 to L60 using L60
L0:     iload_1
L1:     ifeq L12
L4:     new java/lang/NullPointerException
L7:     dup
L8:     invokespecial Method java/lang/NullPointerException <init> ()V
L11:    athrow
L12:    iload_0
L13:    bipush 32
L15:    if_icmplt L24
L18:    iload_0
L19:    bipush 127
L21:    if_icmple L58
L24:    iload_0
L25:    bipush 32
L27:    if_icmpeq L58
L30:    iload_0
L31:    bipush 10
L33:    if_icmpeq L58
L36:    iload_0
L37:    bipush 9
L39:    if_icmpeq L58
L42:    iload_0
L43:    sipush 163
L46:    if_icmpeq L58
L49:    iload_0
L50:    sipush 8364
L53:    if_icmpeq L58
L56:    iconst_0
L57:    ireturn
L58:    iconst_1
L59:    ireturn
L60:    astore_2
L61:    new java/lang/StringBuffer
L64:    dup
L65:    ldc "65557, "
L67:    invokespecial Method java/lang/StringBuffer <init> (Ljava/lang/String;)V
L70:    iload_0
L71:    invokevirtual Method java/lang/StringBuffer append (C)Ljava/lang/StringBuffer;
L74:    ldc ", "
L76:    invokevirtual Method java/lang/StringBuffer append (Ljava/lang/String;)Ljava/lang/StringBuffer;
L79:    iload_1
L80:    invokevirtual Method java/lang/StringBuffer append (I)Ljava/lang/StringBuffer;
L83:    ldc ", "
L85:    invokevirtual Method java/lang/StringBuffer append (Ljava/lang/String;)Ljava/lang/StringBuffer;
L88:    aload_2
L89:    invokevirtual Method java/lang/Throwable toString ()Ljava/lang/String;
L92:    invokevirtual Method java/lang/StringBuffer append (Ljava/lang/String;)Ljava/lang/StringBuffer;
L95:    invokevirtual Method java/lang/StringBuffer toString ()Ljava/lang/String;
L98:    invokestatic Method sign/signlink reporterror (Ljava/lang/String;)V
L101:   new java/lang/RuntimeException
L104:   dup
L105:   invokespecial Method java/lang/RuntimeException <init> ()V
L108:   athrow
L109:   
    .end code
.end method

.method public static final a : (Ljava/lang/String;I)Ljava/lang/String;
    .code stack 5 locals 12
L0:     getstatic Field RKAYAFDQ v Z
L3:     istore 11
        .catch java/lang/RuntimeException from L5 to L232 using L232
L5:     invokestatic Method java/lang/System currentTimeMillis ()J
L8:     lstore_2
L9:     aload_0
L10:    invokevirtual Method java/lang/String toCharArray ()[C
L13:    astore 4
L15:    iconst_0
L16:    aload 4
L18:    invokestatic Method RKAYAFDQ a (Z[C)V
L21:    new java/lang/String
L24:    dup
L25:    aload 4
L27:    invokespecial Method java/lang/String <init> ([C)V
L30:    invokevirtual Method java/lang/String trim ()Ljava/lang/String;
L33:    astore 5
L35:    aload 5
L37:    invokevirtual Method java/lang/String toLowerCase ()Ljava/lang/String;
L40:    invokevirtual Method java/lang/String toCharArray ()[C
L43:    astore 4
L45:    aload 5
L47:    invokevirtual Method java/lang/String toLowerCase ()Ljava/lang/String;
L50:    astore 6
L52:    iconst_0
L53:    aload 4
L55:    invokestatic Method RKAYAFDQ b (Z[C)V
L58:    aload 4
L60:    iconst_1
L61:    invokestatic Method RKAYAFDQ a ([CZ)V
L64:    iload_1
L65:    ifeq L76
L68:    new java/lang/NullPointerException
L71:    dup
L72:    invokespecial Method java/lang/NullPointerException <init> ()V
L75:    athrow
L76:    iconst_0
L77:    aload 4
L79:    invokestatic Method RKAYAFDQ a (B[C)V
L82:    aload 4
L84:    sipush -511
L87:    invokestatic Method RKAYAFDQ a ([CI)V
L90:    iconst_0
L91:    istore 7
L93:    iload 11
L95:    ifeq L188
L98:    getstatic Field PKVMXVTO e Z
L101:   ifeq L108
L104:   iconst_0
L105:   goto L109
L108:   iconst_1
L109:   putstatic Field PKVMXVTO e Z
L112:   iconst_m1
L113:   istore 8
L115:   iload 11
L117:   ifeq L163
L120:   getstatic Field RKAYAFDQ u [Ljava/lang/String;
L123:   iload 7
L125:   aaload
L126:   invokevirtual Method java/lang/String toCharArray ()[C
L129:   astore 9
L131:   iconst_0
L132:   istore 10
L134:   iload 11
L136:   ifeq L155
L139:   aload 4
L141:   iload 10
L143:   iload 8
L145:   iadd
L146:   aload 9
L148:   iload 10
L150:   caload
L151:   castore
L152:   iinc 10 1
L155:   iload 10
L157:   aload 9
L159:   arraylength
L160:   if_icmplt L139
L163:   aload 6
L165:   getstatic Field RKAYAFDQ u [Ljava/lang/String;
L168:   iload 7
L170:   aaload
L171:   iload 8
L173:   iconst_1
L174:   iadd
L175:   invokevirtual Method java/lang/String indexOf (Ljava/lang/String;I)I
L178:   dup
L179:   istore 8
L181:   iconst_m1
L182:   if_icmpne L120
L185:   iinc 7 1
L188:   iload 7
L190:   getstatic Field RKAYAFDQ u [Ljava/lang/String;
L193:   arraylength
L194:   if_icmplt L112
L197:   aload 5
L199:   invokevirtual Method java/lang/String toCharArray ()[C
L202:   iconst_2
L203:   aload 4
L205:   invokestatic Method RKAYAFDQ a ([CI[C)V
L208:   iconst_0
L209:   aload 4
L211:   invokestatic Method RKAYAFDQ a (I[C)V
L214:   invokestatic Method java/lang/System currentTimeMillis ()J
L217:   lstore 8
L219:   new java/lang/String
L222:   dup
L223:   aload 4
L225:   invokespecial Method java/lang/String <init> ([C)V
L228:   invokevirtual Method java/lang/String trim ()Ljava/lang/String;
L231:   areturn
L232:   astore_2
L233:   new java/lang/StringBuffer
L236:   dup
L237:   ldc "44439, "
L239:   invokespecial Method java/lang/StringBuffer <init> (Ljava/lang/String;)V
L242:   aload_0
L243:   invokevirtual Method java/lang/StringBuffer append (Ljava/lang/String;)Ljava/lang/StringBuffer;
L246:   ldc ", "
L248:   invokevirtual Method java/lang/StringBuffer append (Ljava/lang/String;)Ljava/lang/StringBuffer;
L251:   iload_1
L252:   invokevirtual Method java/lang/StringBuffer append (I)Ljava/lang/StringBuffer;
L255:   ldc ", "
L257:   invokevirtual Method java/lang/StringBuffer append (Ljava/lang/String;)Ljava/lang/StringBuffer;
L260:   aload_2
L261:   invokevirtual Method java/lang/Throwable toString ()Ljava/lang/String;
L264:   invokevirtual Method java/lang/StringBuffer append (Ljava/lang/String;)Ljava/lang/StringBuffer;
L267:   invokevirtual Method java/lang/StringBuffer toString ()Ljava/lang/String;
L270:   invokestatic Method sign/signlink reporterror (Ljava/lang/String;)V
L273:   new java/lang/RuntimeException
L276:   dup
L277:   invokespecial Method java/lang/RuntimeException <init> ()V
L280:   athrow
L281:   
    .end code
.end method

.method private static final a : ([CI[C)V
    .code stack 5 locals 4
        .catch java/lang/RuntimeException from L0 to L47 using L47
L0:     iconst_0
L1:     istore_3
L2:     getstatic Field RKAYAFDQ v Z
L5:     ifeq L35
L8:     aload_2
L9:     iload_3
L10:    caload
L11:    bipush 42
L13:    if_icmpeq L32
L16:    iconst_1
L17:    aload_0
L18:    iload_3
L19:    caload
L20:    invokestatic Method RKAYAFDQ b (ZC)Z
L23:    ifeq L32
L26:    aload_2
L27:    iload_3
L28:    aload_0
L29:    iload_3
L30:    caload
L31:    castore
L32:    iinc 3 1
L35:    iload_3
L36:    aload_0
L37:    arraylength
L38:    if_icmplt L8
L41:    iload_1
L42:    iconst_2
L43:    if_icmpeq L105
L46:    return
L47:    astore_3
L48:    new java/lang/StringBuffer
L51:    dup
L52:    ldc "66493, "
L54:    invokespecial Method java/lang/StringBuffer <init> (Ljava/lang/String;)V
L57:    aload_0
L58:    invokevirtual Method java/lang/StringBuffer append ([C)Ljava/lang/StringBuffer;
L61:    ldc ", "
L63:    invokevirtual Method java/lang/StringBuffer append (Ljava/lang/String;)Ljava/lang/StringBuffer;
L66:    iload_1
L67:    invokevirtual Method java/lang/StringBuffer append (I)Ljava/lang/StringBuffer;
L70:    ldc ", "
L72:    invokevirtual Method java/lang/StringBuffer append (Ljava/lang/String;)Ljava/lang/StringBuffer;
L75:    aload_2
L76:    invokevirtual Method java/lang/StringBuffer append ([C)Ljava/lang/StringBuffer;
L79:    ldc ", "
L81:    invokevirtual Method java/lang/StringBuffer append (Ljava/lang/String;)Ljava/lang/StringBuffer;
L84:    aload_3
L85:    invokevirtual Method java/lang/Throwable toString ()Ljava/lang/String;
L88:    invokevirtual Method java/lang/StringBuffer append (Ljava/lang/String;)Ljava/lang/StringBuffer;
L91:    invokevirtual Method java/lang/StringBuffer toString ()Ljava/lang/String;
L94:    invokestatic Method sign/signlink reporterror (Ljava/lang/String;)V
L97:    new java/lang/RuntimeException
L100:   dup
L101:   invokespecial Method java/lang/RuntimeException <init> ()V
L104:   athrow
L105:   return
L106:   
    .end code
.end method

.method private static final a : (I[C)V
    .code stack 5 locals 6
L0:     getstatic Field RKAYAFDQ v Z
L3:     istore 5
        .catch java/lang/RuntimeException from L5 to L91 using L91
L5:     iconst_1
L6:     istore_2
L7:     iconst_0
L8:     istore_3
L9:     iload 5
L11:    ifeq L80
L14:    aload_1
L15:    iload_3
L16:    caload
L17:    istore 4
L19:    iload 4
L21:    ldc -46837
L23:    invokestatic Method RKAYAFDQ c (CI)Z
L26:    ifeq L75
L29:    iload_2
L30:    ifeq L49
L33:    iload 4
L35:    iconst_1
L36:    invokestatic Method RKAYAFDQ e (CI)Z
L39:    ifeq L77
L42:    iconst_0
L43:    istore_2
L44:    iload 5
L46:    ifeq L77
L49:    iconst_1
L50:    iload 4
L52:    invokestatic Method RKAYAFDQ b (ZC)Z
L55:    ifeq L77
L58:    aload_1
L59:    iload_3
L60:    iload 4
L62:    bipush 97
L64:    iadd
L65:    bipush 65
L67:    isub
L68:    i2c
L69:    castore
L70:    iload 5
L72:    ifeq L77
L75:    iconst_1
L76:    istore_2
L77:    iinc 3 1
L80:    iload_3
L81:    aload_1
L82:    arraylength
L83:    if_icmplt L14
L86:    iload_0
L87:    ifeq L140
L90:    return
L91:    astore_2
L92:    new java/lang/StringBuffer
L95:    dup
L96:    ldc "29891, "
L98:    invokespecial Method java/lang/StringBuffer <init> (Ljava/lang/String;)V
L101:   iload_0
L102:   invokevirtual Method java/lang/StringBuffer append (I)Ljava/lang/StringBuffer;
L105:   ldc ", "
L107:   invokevirtual Method java/lang/StringBuffer append (Ljava/lang/String;)Ljava/lang/StringBuffer;
L110:   aload_1
L111:   invokevirtual Method java/lang/StringBuffer append ([C)Ljava/lang/StringBuffer;
L114:   ldc ", "
L116:   invokevirtual Method java/lang/StringBuffer append (Ljava/lang/String;)Ljava/lang/StringBuffer;
L119:   aload_2
L120:   invokevirtual Method java/lang/Throwable toString ()Ljava/lang/String;
L123:   invokevirtual Method java/lang/StringBuffer append (Ljava/lang/String;)Ljava/lang/StringBuffer;
L126:   invokevirtual Method java/lang/StringBuffer toString ()Ljava/lang/String;
L129:   invokestatic Method sign/signlink reporterror (Ljava/lang/String;)V
L132:   new java/lang/RuntimeException
L135:   dup
L136:   invokespecial Method java/lang/RuntimeException <init> ()V
L139:   athrow
L140:   return
L141:   
    .end code
.end method

.method private static final a : ([CZ)V
    .code stack 6 locals 5
L0:     getstatic Field RKAYAFDQ v Z
L3:     istore 4
        .catch java/lang/RuntimeException from L5 to L61 using L62
L5:     iload_1
L6:     ifne L10
L9:     return
L10:    iconst_0
L11:    istore_2
L12:    iload 4
L14:    ifeq L56
L17:    getstatic Field RKAYAFDQ p [[C
L20:    arraylength
L21:    iconst_1
L22:    isub
L23:    istore_3
L24:    iload 4
L26:    ifeq L49
L29:    getstatic Field RKAYAFDQ q [[[B
L32:    iload_3
L33:    aaload
L34:    aload_0
L35:    getstatic Field RKAYAFDQ h I
L38:    getstatic Field RKAYAFDQ p [[C
L41:    iload_3
L42:    aaload
L43:    invokestatic Method RKAYAFDQ a ([[B[CI[C)V
L46:    iinc 3 -1
L49:    iload_3
L50:    ifge L29
L53:    iinc 2 1
L56:    iload_2
L57:    iconst_2
L58:    if_icmplt L17
L61:    return
L62:    astore_2
L63:    new java/lang/StringBuffer
L66:    dup
L67:    ldc "1109, "
L69:    invokespecial Method java/lang/StringBuffer <init> (Ljava/lang/String;)V
L72:    aload_0
L73:    invokevirtual Method java/lang/StringBuffer append ([C)Ljava/lang/StringBuffer;
L76:    ldc ", "
L78:    invokevirtual Method java/lang/StringBuffer append (Ljava/lang/String;)Ljava/lang/StringBuffer;
L81:    iload_1
L82:    invokevirtual Method java/lang/StringBuffer append (Z)Ljava/lang/StringBuffer;
L85:    ldc ", "
L87:    invokevirtual Method java/lang/StringBuffer append (Ljava/lang/String;)Ljava/lang/StringBuffer;
L90:    aload_2
L91:    invokevirtual Method java/lang/Throwable toString ()Ljava/lang/String;
L94:    invokevirtual Method java/lang/StringBuffer append (Ljava/lang/String;)Ljava/lang/StringBuffer;
L97:    invokevirtual Method java/lang/StringBuffer toString ()Ljava/lang/String;
L100:   invokestatic Method sign/signlink reporterror (Ljava/lang/String;)V
L103:   new java/lang/RuntimeException
L106:   dup
L107:   invokespecial Method java/lang/RuntimeException <init> ()V
L110:   athrow
L111:   
    .end code
.end method

.method private static final a : (B[C)V
    .code stack 6 locals 7
        .catch java/lang/RuntimeException from L0 to L119 using L119
L0:     aload_1
L1:     invokevirtual Method java/lang/Object clone ()Ljava/lang/Object;
L4:     checkcast [C
L7:     astore_2
L8:     iconst_3
L9:     newarray char
L11:    dup
L12:    iconst_0
L13:    bipush 40
L15:    castore
L16:    dup
L17:    iconst_1
L18:    bipush 97
L20:    castore
L21:    dup
L22:    iconst_2
L23:    bipush 41
L25:    castore
L26:    astore_3
L27:    aconst_null
L28:    aload_2
L29:    getstatic Field RKAYAFDQ h I
L32:    aload_3
L33:    invokestatic Method RKAYAFDQ a ([[B[CI[C)V
L36:    aload_1
L37:    invokevirtual Method java/lang/Object clone ()Ljava/lang/Object;
L40:    checkcast [C
L43:    astore 4
L45:    iconst_3
L46:    newarray char
L48:    dup
L49:    iconst_0
L50:    bipush 100
L52:    castore
L53:    dup
L54:    iconst_1
L55:    bipush 111
L57:    castore
L58:    dup
L59:    iconst_2
L60:    bipush 116
L62:    castore
L63:    astore 5
L65:    aconst_null
L66:    aload 4
L68:    getstatic Field RKAYAFDQ h I
L71:    aload 5
L73:    invokestatic Method RKAYAFDQ a ([[B[CI[C)V
L76:    getstatic Field RKAYAFDQ r [[C
L79:    arraylength
L80:    iconst_1
L81:    isub
L82:    istore 6
L84:    getstatic Field RKAYAFDQ v Z
L87:    ifeq L109
L90:    sipush 29200
L93:    aload_1
L94:    getstatic Field RKAYAFDQ r [[C
L97:    iload 6
L99:    aaload
L100:   aload 4
L102:   aload_2
L103:   invokestatic Method RKAYAFDQ a (I[C[C[C[C)V
L106:   iinc 6 -1
L109:   iload 6
L111:   ifge L90
L114:   iload_0
L115:   ifeq L168
L118:   return
L119:   astore_2
L120:   new java/lang/StringBuffer
L123:   dup
L124:   ldc "73832, "
L126:   invokespecial Method java/lang/StringBuffer <init> (Ljava/lang/String;)V
L129:   iload_0
L130:   invokevirtual Method java/lang/StringBuffer append (I)Ljava/lang/StringBuffer;
L133:   ldc ", "
L135:   invokevirtual Method java/lang/StringBuffer append (Ljava/lang/String;)Ljava/lang/StringBuffer;
L138:   aload_1
L139:   invokevirtual Method java/lang/StringBuffer append ([C)Ljava/lang/StringBuffer;
L142:   ldc ", "
L144:   invokevirtual Method java/lang/StringBuffer append (Ljava/lang/String;)Ljava/lang/StringBuffer;
L147:   aload_2
L148:   invokevirtual Method java/lang/Throwable toString ()Ljava/lang/String;
L151:   invokevirtual Method java/lang/StringBuffer append (Ljava/lang/String;)Ljava/lang/StringBuffer;
L154:   invokevirtual Method java/lang/StringBuffer toString ()Ljava/lang/String;
L157:   invokestatic Method sign/signlink reporterror (Ljava/lang/String;)V
L160:   new java/lang/RuntimeException
L163:   dup
L164:   invokespecial Method java/lang/RuntimeException <init> ()V
L167:   athrow
L168:   return
L169:   
    .end code
.end method

.method private static final a : (I[C[C[C[C)V
    .code stack 6 locals 14
L0:     getstatic Field RKAYAFDQ v Z
L3:     istore 13
        .catch java/lang/RuntimeException from L5 to L292 using L293
L5:     iload_0
L6:     sipush 29200
L9:     if_icmpeq L13
L12:    return
L13:    aload_2
L14:    arraylength
L15:    aload_1
L16:    arraylength
L17:    if_icmple L21
L20:    return
L21:    iconst_1
L22:    istore 5
L24:    iconst_0
L25:    istore 6
L27:    iload 13
L29:    ifeq L282
L32:    iload 6
L34:    istore 7
L36:    iconst_0
L37:    istore 8
L39:    iconst_1
L40:    istore 5
L42:    iload 13
L44:    ifeq L188
L47:    iconst_0
L48:    istore 9
L50:    aload_1
L51:    iload 7
L53:    caload
L54:    istore 10
L56:    iconst_0
L57:    istore 11
L59:    iload 7
L61:    iconst_1
L62:    iadd
L63:    aload_1
L64:    arraylength
L65:    if_icmpge L76
L68:    aload_1
L69:    iload 7
L71:    iconst_1
L72:    iadd
L73:    caload
L74:    istore 11
L76:    iload 8
L78:    aload_2
L79:    arraylength
L80:    if_icmpge L117
L83:    bipush 43
L85:    iload 10
L87:    aload_2
L88:    iload 8
L90:    caload
L91:    iload 11
L93:    invokestatic Method RKAYAFDQ a (ICCC)I
L96:    dup
L97:    istore 9
L99:    ifle L117
L102:   iload 7
L104:   iload 9
L106:   iadd
L107:   istore 7
L109:   iinc 8 1
L112:   iload 13
L114:   ifeq L188
L117:   iload 8
L119:   ifeq L195
L122:   bipush 43
L124:   iload 10
L126:   aload_2
L127:   iload 8
L129:   iconst_1
L130:   isub
L131:   caload
L132:   iload 11
L134:   invokestatic Method RKAYAFDQ a (ICCC)I
L137:   dup
L138:   istore 9
L140:   ifle L164
L143:   iload 7
L145:   iload 9
L147:   iadd
L148:   istore 7
L150:   iload 8
L152:   iconst_1
L153:   if_icmpne L188
L156:   iinc 5 1
L159:   iload 13
L161:   ifeq L188
L164:   iload 8
L166:   aload_2
L167:   arraylength
L168:   if_icmpge L195
L171:   sipush -12789
L174:   iload 10
L176:   invokestatic Method RKAYAFDQ a (IC)Z
L179:   ifeq L195
L182:   iinc 7 1
L185:   goto L188
L188:   iload 7
L190:   aload_1
L191:   arraylength
L192:   if_icmplt L47
L195:   iload 8
L197:   aload_2
L198:   arraylength
L199:   if_icmplt L275
L202:   iconst_0
L203:   istore 9
L205:   aload_1
L206:   iconst_4
L207:   aload 4
L209:   iload 6
L211:   invokestatic Method RKAYAFDQ a ([CI[CI)I
L214:   istore 10
L216:   getstatic Field RKAYAFDQ g B
L219:   aload_3
L220:   iload 7
L222:   iconst_1
L223:   isub
L224:   aload_1
L225:   invokestatic Method RKAYAFDQ a (B[CI[C)I
L228:   istore 11
L230:   iload 10
L232:   iconst_2
L233:   if_icmpgt L242
L236:   iload 11
L238:   iconst_2
L239:   if_icmple L245
L242:   iconst_1
L243:   istore 9
L245:   iload 9
L247:   ifeq L275
L250:   iload 6
L252:   istore 12
L254:   iload 13
L256:   ifeq L268
L259:   aload_1
L260:   iload 12
L262:   bipush 42
L264:   castore
L265:   iinc 12 1
L268:   iload 12
L270:   iload 7
L272:   if_icmplt L259
L275:   iload 6
L277:   iload 5
L279:   iadd
L280:   istore 6
L282:   iload 6
L284:   aload_1
L285:   arraylength
L286:   aload_2
L287:   arraylength
L288:   isub
L289:   if_icmple L32
L292:   return
L293:   astore 5
L295:   new java/lang/StringBuffer
L298:   dup
L299:   ldc "48695, "
L301:   invokespecial Method java/lang/StringBuffer <init> (Ljava/lang/String;)V
L304:   iload_0
L305:   invokevirtual Method java/lang/StringBuffer append (I)Ljava/lang/StringBuffer;
L308:   ldc ", "
L310:   invokevirtual Method java/lang/StringBuffer append (Ljava/lang/String;)Ljava/lang/StringBuffer;
L313:   aload_1
L314:   invokevirtual Method java/lang/StringBuffer append ([C)Ljava/lang/StringBuffer;
L317:   ldc ", "
L319:   invokevirtual Method java/lang/StringBuffer append (Ljava/lang/String;)Ljava/lang/StringBuffer;
L322:   aload_2
L323:   invokevirtual Method java/lang/StringBuffer append ([C)Ljava/lang/StringBuffer;
L326:   ldc ", "
L328:   invokevirtual Method java/lang/StringBuffer append (Ljava/lang/String;)Ljava/lang/StringBuffer;
L331:   aload_3
L332:   invokevirtual Method java/lang/StringBuffer append ([C)Ljava/lang/StringBuffer;
L335:   ldc ", "
L337:   invokevirtual Method java/lang/StringBuffer append (Ljava/lang/String;)Ljava/lang/StringBuffer;
L340:   aload 4
L342:   invokevirtual Method java/lang/StringBuffer append ([C)Ljava/lang/StringBuffer;
L345:   ldc ", "
L347:   invokevirtual Method java/lang/StringBuffer append (Ljava/lang/String;)Ljava/lang/StringBuffer;
L350:   aload 5
L352:   invokevirtual Method java/lang/Throwable toString ()Ljava/lang/String;
L355:   invokevirtual Method java/lang/StringBuffer append (Ljava/lang/String;)Ljava/lang/StringBuffer;
L358:   invokevirtual Method java/lang/StringBuffer toString ()Ljava/lang/String;
L361:   invokestatic Method sign/signlink reporterror (Ljava/lang/String;)V
L364:   new java/lang/RuntimeException
L367:   dup
L368:   invokespecial Method java/lang/RuntimeException <init> ()V
L371:   athrow
L372:   
    .end code
.end method

.method private static final a : ([CI[CI)I
    .code stack 5 locals 8
L0:     getstatic Field RKAYAFDQ v Z
L3:     istore 7
        .catch java/lang/RuntimeException from L5 to L140 using L140
L5:     iload_1
L6:     iconst_4
L7:     if_icmplt L15
L10:    iload_1
L11:    iconst_4
L12:    if_icmple L17
L15:    iconst_2
L16:    ireturn
L17:    iload_3
L18:    ifne L23
L21:    iconst_2
L22:    ireturn
L23:    iload_3
L24:    iconst_1
L25:    isub
L26:    istore 4
L28:    iload 7
L30:    ifeq L60
L33:    sipush -12789
L36:    aload_0
L37:    iload 4
L39:    caload
L40:    invokestatic Method RKAYAFDQ a (IC)Z
L43:    ifeq L65
L46:    aload_0
L47:    iload 4
L49:    caload
L50:    bipush 64
L52:    if_icmpne L57
L55:    iconst_3
L56:    ireturn
L57:    iinc 4 -1
L60:    iload 4
L62:    ifge L33
L65:    iconst_0
L66:    istore 5
L68:    iload_3
L69:    iconst_1
L70:    isub
L71:    istore 6
L73:    iload 7
L75:    ifeq L109
L78:    sipush -12789
L81:    aload_2
L82:    iload 6
L84:    caload
L85:    invokestatic Method RKAYAFDQ a (IC)Z
L88:    ifeq L114
L91:    aload_2
L92:    iload 6
L94:    caload
L95:    bipush 42
L97:    if_icmpne L106
L100:   iinc 5 1
L103:   goto L106
L106:   iinc 6 -1
L109:   iload 6
L111:   ifge L78
L114:   iload 5
L116:   iconst_3
L117:   if_icmplt L122
L120:   iconst_4
L121:   ireturn
L122:   sipush -12789
L125:   aload_0
L126:   iload_3
L127:   iconst_1
L128:   isub
L129:   caload
L130:   invokestatic Method RKAYAFDQ a (IC)Z
L133:   ifeq L138
L136:   iconst_1
L137:   ireturn
L138:   iconst_0
L139:   ireturn
L140:   astore 4
L142:   new java/lang/StringBuffer
L145:   dup
L146:   ldc "87152, "
L148:   invokespecial Method java/lang/StringBuffer <init> (Ljava/lang/String;)V
L151:   aload_0
L152:   invokevirtual Method java/lang/StringBuffer append ([C)Ljava/lang/StringBuffer;
L155:   ldc ", "
L157:   invokevirtual Method java/lang/StringBuffer append (Ljava/lang/String;)Ljava/lang/StringBuffer;
L160:   iload_1
L161:   invokevirtual Method java/lang/StringBuffer append (I)Ljava/lang/StringBuffer;
L164:   ldc ", "
L166:   invokevirtual Method java/lang/StringBuffer append (Ljava/lang/String;)Ljava/lang/StringBuffer;
L169:   aload_2
L170:   invokevirtual Method java/lang/StringBuffer append ([C)Ljava/lang/StringBuffer;
L173:   ldc ", "
L175:   invokevirtual Method java/lang/StringBuffer append (Ljava/lang/String;)Ljava/lang/StringBuffer;
L178:   iload_3
L179:   invokevirtual Method java/lang/StringBuffer append (I)Ljava/lang/StringBuffer;
L182:   ldc ", "
L184:   invokevirtual Method java/lang/StringBuffer append (Ljava/lang/String;)Ljava/lang/StringBuffer;
L187:   aload 4
L189:   invokevirtual Method java/lang/Throwable toString ()Ljava/lang/String;
L192:   invokevirtual Method java/lang/StringBuffer append (Ljava/lang/String;)Ljava/lang/StringBuffer;
L195:   invokevirtual Method java/lang/StringBuffer toString ()Ljava/lang/String;
L198:   invokestatic Method sign/signlink reporterror (Ljava/lang/String;)V
L201:   new java/lang/RuntimeException
L204:   dup
L205:   invokespecial Method java/lang/RuntimeException <init> ()V
L208:   athrow
L209:   
    .end code
.end method

.method private static final a : (B[CI[C)I
    .code stack 5 locals 8
L0:     getstatic Field RKAYAFDQ v Z
L3:     istore 7
        .catch java/lang/RuntimeException from L5 to L155 using L155
L5:     iload_2
L6:     iconst_1
L7:     iadd
L8:     aload_3
L9:     arraylength
L10:    if_icmpne L15
L13:    iconst_2
L14:    ireturn
L15:    iload_2
L16:    iconst_1
L17:    iadd
L18:    istore 4
L20:    iload 7
L22:    ifeq L61
L25:    sipush -12789
L28:    aload_3
L29:    iload 4
L31:    caload
L32:    invokestatic Method RKAYAFDQ a (IC)Z
L35:    ifeq L68
L38:    aload_3
L39:    iload 4
L41:    caload
L42:    bipush 46
L44:    if_icmpeq L56
L47:    aload_3
L48:    iload 4
L50:    caload
L51:    bipush 44
L53:    if_icmpne L58
L56:    iconst_3
L57:    ireturn
L58:    iinc 4 1
L61:    iload 4
L63:    aload_3
L64:    arraylength
L65:    if_icmplt L25
L68:    iload_0
L69:    bipush -117
L71:    if_icmpeq L78
L74:    getstatic Field RKAYAFDQ h I
L77:    ireturn
L78:    iconst_0
L79:    istore 5
L81:    iload_2
L82:    iconst_1
L83:    iadd
L84:    istore 6
L86:    iload 7
L88:    ifeq L122
L91:    sipush -12789
L94:    aload_1
L95:    iload 6
L97:    caload
L98:    invokestatic Method RKAYAFDQ a (IC)Z
L101:   ifeq L129
L104:   aload_1
L105:   iload 6
L107:   caload
L108:   bipush 42
L110:   if_icmpne L119
L113:   iinc 5 1
L116:   goto L119
L119:   iinc 6 1
L122:   iload 6
L124:   aload_3
L125:   arraylength
L126:   if_icmplt L91
L129:   iload 5
L131:   iconst_3
L132:   if_icmplt L137
L135:   iconst_4
L136:   ireturn
L137:   sipush -12789
L140:   aload_3
L141:   iload_2
L142:   iconst_1
L143:   iadd
L144:   caload
L145:   invokestatic Method RKAYAFDQ a (IC)Z
L148:   ifeq L153
L151:   iconst_1
L152:   ireturn
L153:   iconst_0
L154:   ireturn
L155:   astore 4
L157:   new java/lang/StringBuffer
L160:   dup
L161:   ldc "50081, "
L163:   invokespecial Method java/lang/StringBuffer <init> (Ljava/lang/String;)V
L166:   iload_0
L167:   invokevirtual Method java/lang/StringBuffer append (I)Ljava/lang/StringBuffer;
L170:   ldc ", "
L172:   invokevirtual Method java/lang/StringBuffer append (Ljava/lang/String;)Ljava/lang/StringBuffer;
L175:   aload_1
L176:   invokevirtual Method java/lang/StringBuffer append ([C)Ljava/lang/StringBuffer;
L179:   ldc ", "
L181:   invokevirtual Method java/lang/StringBuffer append (Ljava/lang/String;)Ljava/lang/StringBuffer;
L184:   iload_2
L185:   invokevirtual Method java/lang/StringBuffer append (I)Ljava/lang/StringBuffer;
L188:   ldc ", "
L190:   invokevirtual Method java/lang/StringBuffer append (Ljava/lang/String;)Ljava/lang/StringBuffer;
L193:   aload_3
L194:   invokevirtual Method java/lang/StringBuffer append ([C)Ljava/lang/StringBuffer;
L197:   ldc ", "
L199:   invokevirtual Method java/lang/StringBuffer append (Ljava/lang/String;)Ljava/lang/StringBuffer;
L202:   aload 4
L204:   invokevirtual Method java/lang/Throwable toString ()Ljava/lang/String;
L207:   invokevirtual Method java/lang/StringBuffer append (Ljava/lang/String;)Ljava/lang/StringBuffer;
L210:   invokevirtual Method java/lang/StringBuffer toString ()Ljava/lang/String;
L213:   invokestatic Method sign/signlink reporterror (Ljava/lang/String;)V
L216:   new java/lang/RuntimeException
L219:   dup
L220:   invokespecial Method java/lang/RuntimeException <init> ()V
L223:   athrow
L224:   
    .end code
.end method

.method private static final b : (Z[C)V
    .code stack 7 locals 7
        .catch java/lang/RuntimeException from L0 to L133 using L134
L0:     aload_1
L1:     invokevirtual Method java/lang/Object clone ()Ljava/lang/Object;
L4:     checkcast [C
L7:     astore_2
L8:     iconst_3
L9:     newarray char
L11:    dup
L12:    iconst_0
L13:    bipush 100
L15:    castore
L16:    dup
L17:    iconst_1
L18:    bipush 111
L20:    castore
L21:    dup
L22:    iconst_2
L23:    bipush 116
L25:    castore
L26:    astore_3
L27:    iload_0
L28:    ifeq L32
L31:    return
L32:    aconst_null
L33:    aload_2
L34:    getstatic Field RKAYAFDQ h I
L37:    aload_3
L38:    invokestatic Method RKAYAFDQ a ([[B[CI[C)V
L41:    aload_1
L42:    invokevirtual Method java/lang/Object clone ()Ljava/lang/Object;
L45:    checkcast [C
L48:    astore 4
L50:    iconst_5
L51:    newarray char
L53:    dup
L54:    iconst_0
L55:    bipush 115
L57:    castore
L58:    dup
L59:    iconst_1
L60:    bipush 108
L62:    castore
L63:    dup
L64:    iconst_2
L65:    bipush 97
L67:    castore
L68:    dup
L69:    iconst_3
L70:    bipush 115
L72:    castore
L73:    dup
L74:    iconst_4
L75:    bipush 104
L77:    castore
L78:    astore 5
L80:    aconst_null
L81:    aload 4
L83:    getstatic Field RKAYAFDQ h I
L86:    aload 5
L88:    invokestatic Method RKAYAFDQ a ([[B[CI[C)V
L91:    iconst_0
L92:    istore 6
L94:    getstatic Field RKAYAFDQ v Z
L97:    ifeq L124
L100:   aload 4
L102:   getstatic Field RKAYAFDQ s [[C
L105:   iload 6
L107:   aaload
L108:   getstatic Field RKAYAFDQ t [I
L111:   iload 6
L113:   iaload
L114:   bipush 51
L116:   aload_2
L117:   aload_1
L118:   invokestatic Method RKAYAFDQ a ([C[CIB[C[C)V
L121:   iinc 6 1
L124:   iload 6
L126:   getstatic Field RKAYAFDQ s [[C
L129:   arraylength
L130:   if_icmplt L100
L133:   return
L134:   astore_2
L135:   new java/lang/StringBuffer
L138:   dup
L139:   ldc "41909, "
L141:   invokespecial Method java/lang/StringBuffer <init> (Ljava/lang/String;)V
L144:   iload_0
L145:   invokevirtual Method java/lang/StringBuffer append (Z)Ljava/lang/StringBuffer;
L148:   ldc ", "
L150:   invokevirtual Method java/lang/StringBuffer append (Ljava/lang/String;)Ljava/lang/StringBuffer;
L153:   aload_1
L154:   invokevirtual Method java/lang/StringBuffer append ([C)Ljava/lang/StringBuffer;
L157:   ldc ", "
L159:   invokevirtual Method java/lang/StringBuffer append (Ljava/lang/String;)Ljava/lang/StringBuffer;
L162:   aload_2
L163:   invokevirtual Method java/lang/Throwable toString ()Ljava/lang/String;
L166:   invokevirtual Method java/lang/StringBuffer append (Ljava/lang/String;)Ljava/lang/StringBuffer;
L169:   invokevirtual Method java/lang/StringBuffer toString ()Ljava/lang/String;
L172:   invokestatic Method sign/signlink reporterror (Ljava/lang/String;)V
L175:   new java/lang/RuntimeException
L178:   dup
L179:   invokespecial Method java/lang/RuntimeException <init> ()V
L182:   athrow
L183:   
    .end code
.end method

.method private static final a : ([C[CIB[C[C)V
    .code stack 6 locals 18
L0:     getstatic Field RKAYAFDQ v Z
L3:     istore 17
        .catch java/lang/RuntimeException from L5 to L692 using L693
L5:     aload_1
L6:     arraylength
L7:     aload 5
L9:     arraylength
L10:    if_icmple L14
L13:    return
L14:    iconst_1
L15:    istore 6
L17:    iconst_0
L18:    istore 7
L20:    iload 17
L22:    ifeq L661
L25:    iload 7
L27:    istore 8
L29:    iconst_0
L30:    istore 9
L32:    iconst_1
L33:    istore 6
L35:    iload 17
L37:    ifeq L184
L40:    iconst_0
L41:    istore 10
L43:    aload 5
L45:    iload 8
L47:    caload
L48:    istore 11
L50:    iconst_0
L51:    istore 12
L53:    iload 8
L55:    iconst_1
L56:    iadd
L57:    aload 5
L59:    arraylength
L60:    if_icmpge L72
L63:    aload 5
L65:    iload 8
L67:    iconst_1
L68:    iadd
L69:    caload
L70:    istore 12
L72:    iload 9
L74:    aload_1
L75:    arraylength
L76:    if_icmpge L113
L79:    bipush 43
L81:    iload 11
L83:    aload_1
L84:    iload 9
L86:    caload
L87:    iload 12
L89:    invokestatic Method RKAYAFDQ a (ICCC)I
L92:    dup
L93:    istore 10
L95:    ifle L113
L98:    iload 8
L100:   iload 10
L102:   iadd
L103:   istore 8
L105:   iinc 9 1
L108:   iload 17
L110:   ifeq L184
L113:   iload 9
L115:   ifeq L192
L118:   bipush 43
L120:   iload 11
L122:   aload_1
L123:   iload 9
L125:   iconst_1
L126:   isub
L127:   caload
L128:   iload 12
L130:   invokestatic Method RKAYAFDQ a (ICCC)I
L133:   dup
L134:   istore 10
L136:   ifle L160
L139:   iload 8
L141:   iload 10
L143:   iadd
L144:   istore 8
L146:   iload 9
L148:   iconst_1
L149:   if_icmpne L184
L152:   iinc 6 1
L155:   iload 17
L157:   ifeq L184
L160:   iload 9
L162:   aload_1
L163:   arraylength
L164:   if_icmpge L192
L167:   sipush -12789
L170:   iload 11
L172:   invokestatic Method RKAYAFDQ a (IC)Z
L175:   ifeq L192
L178:   iinc 8 1
L181:   goto L184
L184:   iload 8
L186:   aload 5
L188:   arraylength
L189:   if_icmplt L40
L192:   iload 9
L194:   aload_1
L195:   arraylength
L196:   if_icmplt L654
L199:   iconst_0
L200:   istore 10
L202:   ldc 36209
L204:   aload 5
L206:   iload 7
L208:   aload 4
L210:   invokestatic Method RKAYAFDQ a (I[CI[C)I
L213:   istore 11
L215:   iconst_0
L216:   aload 5
L218:   aload_0
L219:   iload 8
L221:   iconst_1
L222:   isub
L223:   invokestatic Method RKAYAFDQ a (Z[C[CI)I
L226:   istore 12
L228:   iload_2
L229:   iconst_1
L230:   if_icmpne L246
L233:   iload 11
L235:   ifle L246
L238:   iload 12
L240:   ifle L246
L243:   iconst_1
L244:   istore 10
L246:   iload_2
L247:   iconst_2
L248:   if_icmpne L276
L251:   iload 11
L253:   iconst_2
L254:   if_icmple L262
L257:   iload 12
L259:   ifgt L273
L262:   iload 11
L264:   ifle L276
L267:   iload 12
L269:   iconst_2
L270:   if_icmple L276
L273:   iconst_1
L274:   istore 10
L276:   iload_2
L277:   iconst_3
L278:   if_icmpne L295
L281:   iload 11
L283:   ifle L295
L286:   iload 12
L288:   iconst_2
L289:   if_icmple L295
L292:   iconst_1
L293:   istore 10
L295:   iload_2
L296:   iconst_3
L297:   if_icmpne L311
L300:   iload 11
L302:   iconst_2
L303:   if_icmple L311
L306:   iload 12
L308:   ifgt L315
L311:   iconst_0
L312:   goto L316
L315:   iconst_1
L316:   pop
L317:   iload 10
L319:   ifeq L654
L322:   iload 7
L324:   istore 13
L326:   iload 8
L328:   iconst_1
L329:   isub
L330:   istore 14
L332:   iload 11
L334:   iconst_2
L335:   if_icmple L478
L338:   iload 11
L340:   iconst_4
L341:   if_icmpne L407
L344:   iconst_0
L345:   istore 15
L347:   iload 13
L349:   iconst_1
L350:   isub
L351:   istore 16
L353:   iload 17
L355:   ifeq L402
L358:   iload 15
L360:   ifeq L382
L363:   aload 4
L365:   iload 16
L367:   caload
L368:   bipush 42
L370:   if_icmpne L407
L373:   iload 16
L375:   istore 13
L377:   iload 17
L379:   ifeq L399
L382:   aload 4
L384:   iload 16
L386:   caload
L387:   bipush 42
L389:   if_icmpne L399
L392:   iload 16
L394:   istore 13
L396:   iconst_1
L397:   istore 15
L399:   iinc 16 -1
L402:   iload 16
L404:   ifge L358
L407:   iconst_0
L408:   istore 15
L410:   iload 13
L412:   iconst_1
L413:   isub
L414:   istore 16
L416:   iload 17
L418:   ifeq L473
L421:   iload 15
L423:   ifeq L449
L426:   sipush -12789
L429:   aload 5
L431:   iload 16
L433:   caload
L434:   invokestatic Method RKAYAFDQ a (IC)Z
L437:   ifne L478
L440:   iload 16
L442:   istore 13
L444:   iload 17
L446:   ifeq L470
L449:   sipush -12789
L452:   aload 5
L454:   iload 16
L456:   caload
L457:   invokestatic Method RKAYAFDQ a (IC)Z
L460:   ifne L470
L463:   iconst_1
L464:   istore 15
L466:   iload 16
L468:   istore 13
L470:   iinc 16 -1
L473:   iload 16
L475:   ifge L421
L478:   iload 12
L480:   iconst_2
L481:   if_icmple L628
L484:   iload 12
L486:   iconst_4
L487:   if_icmpne L554
L490:   iconst_0
L491:   istore 15
L493:   iload 14
L495:   iconst_1
L496:   iadd
L497:   istore 16
L499:   iload 17
L501:   ifeq L546
L504:   iload 15
L506:   ifeq L527
L509:   aload_0
L510:   iload 16
L512:   caload
L513:   bipush 42
L515:   if_icmpne L554
L518:   iload 16
L520:   istore 14
L522:   iload 17
L524:   ifeq L543
L527:   aload_0
L528:   iload 16
L530:   caload
L531:   bipush 42
L533:   if_icmpne L543
L536:   iload 16
L538:   istore 14
L540:   iconst_1
L541:   istore 15
L543:   iinc 16 1
L546:   iload 16
L548:   aload 5
L550:   arraylength
L551:   if_icmplt L504
L554:   iconst_0
L555:   istore 15
L557:   iload 14
L559:   iconst_1
L560:   iadd
L561:   istore 16
L563:   iload 17
L565:   ifeq L620
L568:   iload 15
L570:   ifeq L596
L573:   sipush -12789
L576:   aload 5
L578:   iload 16
L580:   caload
L581:   invokestatic Method RKAYAFDQ a (IC)Z
L584:   ifne L628
L587:   iload 16
L589:   istore 14
L591:   iload 17
L593:   ifeq L617
L596:   sipush -12789
L599:   aload 5
L601:   iload 16
L603:   caload
L604:   invokestatic Method RKAYAFDQ a (IC)Z
L607:   ifne L617
L610:   iconst_1
L611:   istore 15
L613:   iload 16
L615:   istore 14
L617:   iinc 16 1
L620:   iload 16
L622:   aload 5
L624:   arraylength
L625:   if_icmplt L568
L628:   iload 13
L630:   istore 15
L632:   iload 17
L634:   ifeq L647
L637:   aload 5
L639:   iload 15
L641:   bipush 42
L643:   castore
L644:   iinc 15 1
L647:   iload 15
L649:   iload 14
L651:   if_icmple L637
L654:   iload 7
L656:   iload 6
L658:   iadd
L659:   istore 7
L661:   iload 7
L663:   aload 5
L665:   arraylength
L666:   aload_1
L667:   arraylength
L668:   isub
L669:   if_icmple L25
L672:   iload_3
L673:   bipush 51
L675:   if_icmpeq L782
L678:   getstatic Field RKAYAFDQ n Z
L681:   ifeq L688
L684:   iconst_0
L685:   goto L689
L688:   iconst_1
L689:   putstatic Field RKAYAFDQ n Z
L692:   return
L693:   astore 6
L695:   new java/lang/StringBuffer
L698:   dup
L699:   ldc "17314, "
L701:   invokespecial Method java/lang/StringBuffer <init> (Ljava/lang/String;)V
L704:   aload_0
L705:   invokevirtual Method java/lang/StringBuffer append ([C)Ljava/lang/StringBuffer;
L708:   ldc ", "
L710:   invokevirtual Method java/lang/StringBuffer append (Ljava/lang/String;)Ljava/lang/StringBuffer;
L713:   aload_1
L714:   invokevirtual Method java/lang/StringBuffer append ([C)Ljava/lang/StringBuffer;
L717:   ldc ", "
L719:   invokevirtual Method java/lang/StringBuffer append (Ljava/lang/String;)Ljava/lang/StringBuffer;
L722:   iload_2
L723:   invokevirtual Method java/lang/StringBuffer append (I)Ljava/lang/StringBuffer;
L726:   ldc ", "
L728:   invokevirtual Method java/lang/StringBuffer append (Ljava/lang/String;)Ljava/lang/StringBuffer;
L731:   iload_3
L732:   invokevirtual Method java/lang/StringBuffer append (I)Ljava/lang/StringBuffer;
L735:   ldc ", "
L737:   invokevirtual Method java/lang/StringBuffer append (Ljava/lang/String;)Ljava/lang/StringBuffer;
L740:   aload 4
L742:   invokevirtual Method java/lang/StringBuffer append ([C)Ljava/lang/StringBuffer;
L745:   ldc ", "
L747:   invokevirtual Method java/lang/StringBuffer append (Ljava/lang/String;)Ljava/lang/StringBuffer;
L750:   aload 5
L752:   invokevirtual Method java/lang/StringBuffer append ([C)Ljava/lang/StringBuffer;
L755:   ldc ", "
L757:   invokevirtual Method java/lang/StringBuffer append (Ljava/lang/String;)Ljava/lang/StringBuffer;
L760:   aload 6
L762:   invokevirtual Method java/lang/Throwable toString ()Ljava/lang/String;
L765:   invokevirtual Method java/lang/StringBuffer append (Ljava/lang/String;)Ljava/lang/StringBuffer;
L768:   invokevirtual Method java/lang/StringBuffer toString ()Ljava/lang/String;
L771:   invokestatic Method sign/signlink reporterror (Ljava/lang/String;)V
L774:   new java/lang/RuntimeException
L777:   dup
L778:   invokespecial Method java/lang/RuntimeException <init> ()V
L781:   athrow
L782:   return
L783:   
    .end code
.end method

.method private static final a : (I[CI[C)I
    .code stack 5 locals 8
L0:     getstatic Field RKAYAFDQ v Z
L3:     istore 7
        .catch java/lang/RuntimeException from L5 to L157 using L157
L5:     iload_2
L6:     ifne L11
L9:     iconst_2
L10:    ireturn
L11:    iload_2
L12:    iconst_1
L13:    isub
L14:    istore 4
L16:    iload 7
L18:    ifeq L57
L21:    sipush -12789
L24:    aload_1
L25:    iload 4
L27:    caload
L28:    invokestatic Method RKAYAFDQ a (IC)Z
L31:    ifeq L62
L34:    aload_1
L35:    iload 4
L37:    caload
L38:    bipush 44
L40:    if_icmpeq L52
L43:    aload_1
L44:    iload 4
L46:    caload
L47:    bipush 46
L49:    if_icmpne L54
L52:    iconst_3
L53:    ireturn
L54:    iinc 4 -1
L57:    iload 4
L59:    ifge L21
L62:    iconst_0
L63:    istore 5
L65:    iload_2
L66:    iconst_1
L67:    isub
L68:    istore 6
L70:    iload 7
L72:    ifeq L106
L75:    sipush -12789
L78:    aload_3
L79:    iload 6
L81:    caload
L82:    invokestatic Method RKAYAFDQ a (IC)Z
L85:    ifeq L111
L88:    aload_3
L89:    iload 6
L91:    caload
L92:    bipush 42
L94:    if_icmpne L103
L97:    iinc 5 1
L100:   goto L103
L103:   iinc 6 -1
L106:   iload 6
L108:   ifge L75
L111:   iload_0
L112:   ldc 36209
L114:   if_icmpeq L131
L117:   getstatic Field RKAYAFDQ n Z
L120:   ifeq L127
L123:   iconst_0
L124:   goto L128
L127:   iconst_1
L128:   putstatic Field RKAYAFDQ n Z
L131:   iload 5
L133:   iconst_3
L134:   if_icmplt L139
L137:   iconst_4
L138:   ireturn
L139:   sipush -12789
L142:   aload_1
L143:   iload_2
L144:   iconst_1
L145:   isub
L146:   caload
L147:   invokestatic Method RKAYAFDQ a (IC)Z
L150:   ifeq L155
L153:   iconst_1
L154:   ireturn
L155:   iconst_0
L156:   ireturn
L157:   astore 4
L159:   new java/lang/StringBuffer
L162:   dup
L163:   ldc "50325, "
L165:   invokespecial Method java/lang/StringBuffer <init> (Ljava/lang/String;)V
L168:   iload_0
L169:   invokevirtual Method java/lang/StringBuffer append (I)Ljava/lang/StringBuffer;
L172:   ldc ", "
L174:   invokevirtual Method java/lang/StringBuffer append (Ljava/lang/String;)Ljava/lang/StringBuffer;
L177:   aload_1
L178:   invokevirtual Method java/lang/StringBuffer append ([C)Ljava/lang/StringBuffer;
L181:   ldc ", "
L183:   invokevirtual Method java/lang/StringBuffer append (Ljava/lang/String;)Ljava/lang/StringBuffer;
L186:   iload_2
L187:   invokevirtual Method java/lang/StringBuffer append (I)Ljava/lang/StringBuffer;
L190:   ldc ", "
L192:   invokevirtual Method java/lang/StringBuffer append (Ljava/lang/String;)Ljava/lang/StringBuffer;
L195:   aload_3
L196:   invokevirtual Method java/lang/StringBuffer append ([C)Ljava/lang/StringBuffer;
L199:   ldc ", "
L201:   invokevirtual Method java/lang/StringBuffer append (Ljava/lang/String;)Ljava/lang/StringBuffer;
L204:   aload 4
L206:   invokevirtual Method java/lang/Throwable toString ()Ljava/lang/String;
L209:   invokevirtual Method java/lang/StringBuffer append (Ljava/lang/String;)Ljava/lang/StringBuffer;
L212:   invokevirtual Method java/lang/StringBuffer toString ()Ljava/lang/String;
L215:   invokestatic Method sign/signlink reporterror (Ljava/lang/String;)V
L218:   new java/lang/RuntimeException
L221:   dup
L222:   invokespecial Method java/lang/RuntimeException <init> ()V
L225:   athrow
L226:   
    .end code
.end method

.method private static final a : (Z[C[CI)I
    .code stack 5 locals 8
L0:     getstatic Field RKAYAFDQ v Z
L3:     istore 7
        .catch java/lang/RuntimeException from L5 to L155 using L155
L5:     iload_0
L6:     ifeq L15
L9:     sipush 391
L12:    putstatic Field RKAYAFDQ c I
L15:    iload_3
L16:    iconst_1
L17:    iadd
L18:    aload_1
L19:    arraylength
L20:    if_icmpne L25
L23:    iconst_2
L24:    ireturn
L25:    iload_3
L26:    iconst_1
L27:    iadd
L28:    istore 4
L30:    iload 7
L32:    ifeq L71
L35:    sipush -12789
L38:    aload_1
L39:    iload 4
L41:    caload
L42:    invokestatic Method RKAYAFDQ a (IC)Z
L45:    ifeq L78
L48:    aload_1
L49:    iload 4
L51:    caload
L52:    bipush 92
L54:    if_icmpeq L66
L57:    aload_1
L58:    iload 4
L60:    caload
L61:    bipush 47
L63:    if_icmpne L68
L66:    iconst_3
L67:    ireturn
L68:    iinc 4 1
L71:    iload 4
L73:    aload_1
L74:    arraylength
L75:    if_icmplt L35
L78:    iconst_0
L79:    istore 5
L81:    iload_3
L82:    iconst_1
L83:    iadd
L84:    istore 6
L86:    iload 7
L88:    ifeq L122
L91:    sipush -12789
L94:    aload_2
L95:    iload 6
L97:    caload
L98:    invokestatic Method RKAYAFDQ a (IC)Z
L101:   ifeq L129
L104:   aload_2
L105:   iload 6
L107:   caload
L108:   bipush 42
L110:   if_icmpne L119
L113:   iinc 5 1
L116:   goto L119
L119:   iinc 6 1
L122:   iload 6
L124:   aload_1
L125:   arraylength
L126:   if_icmplt L91
L129:   iload 5
L131:   iconst_5
L132:   if_icmplt L137
L135:   iconst_4
L136:   ireturn
L137:   sipush -12789
L140:   aload_1
L141:   iload_3
L142:   iconst_1
L143:   iadd
L144:   caload
L145:   invokestatic Method RKAYAFDQ a (IC)Z
L148:   ifeq L153
L151:   iconst_1
L152:   ireturn
L153:   iconst_0
L154:   ireturn
L155:   astore 4
L157:   new java/lang/StringBuffer
L160:   dup
L161:   ldc "27208, "
L163:   invokespecial Method java/lang/StringBuffer <init> (Ljava/lang/String;)V
L166:   iload_0
L167:   invokevirtual Method java/lang/StringBuffer append (Z)Ljava/lang/StringBuffer;
L170:   ldc ", "
L172:   invokevirtual Method java/lang/StringBuffer append (Ljava/lang/String;)Ljava/lang/StringBuffer;
L175:   aload_1
L176:   invokevirtual Method java/lang/StringBuffer append ([C)Ljava/lang/StringBuffer;
L179:   ldc ", "
L181:   invokevirtual Method java/lang/StringBuffer append (Ljava/lang/String;)Ljava/lang/StringBuffer;
L184:   aload_2
L185:   invokevirtual Method java/lang/StringBuffer append ([C)Ljava/lang/StringBuffer;
L188:   ldc ", "
L190:   invokevirtual Method java/lang/StringBuffer append (Ljava/lang/String;)Ljava/lang/StringBuffer;
L193:   iload_3
L194:   invokevirtual Method java/lang/StringBuffer append (I)Ljava/lang/StringBuffer;
L197:   ldc ", "
L199:   invokevirtual Method java/lang/StringBuffer append (Ljava/lang/String;)Ljava/lang/StringBuffer;
L202:   aload 4
L204:   invokevirtual Method java/lang/Throwable toString ()Ljava/lang/String;
L207:   invokevirtual Method java/lang/StringBuffer append (Ljava/lang/String;)Ljava/lang/StringBuffer;
L210:   invokevirtual Method java/lang/StringBuffer toString ()Ljava/lang/String;
L213:   invokestatic Method sign/signlink reporterror (Ljava/lang/String;)V
L216:   new java/lang/RuntimeException
L219:   dup
L220:   invokespecial Method java/lang/RuntimeException <init> ()V
L223:   athrow
L224:   
    .end code
.end method

.method public static final a : ([[B[CI[C)V
    .code stack 7 locals 21
L0:     getstatic Field RKAYAFDQ v Z
L3:     istore 20
        .catch java/lang/RuntimeException from L5 to L882 using L883
L5:     iload 20
L7:     ifeq L11
L10:    return
L11:    iload_2
L12:    ifge L10
L15:    aload_3
L16:    arraylength
L17:    aload_1
L18:    arraylength
L19:    if_icmple L23
L22:    return
L23:    iconst_1
L24:    istore 4
L26:    iconst_0
L27:    istore 5
L29:    iload 20
L31:    ifeq L872
L34:    iload 5
L36:    istore 6
L38:    iconst_0
L39:    istore 7
L41:    iconst_0
L42:    istore 8
L44:    iconst_1
L45:    istore 4
L47:    iconst_0
L48:    istore 9
L50:    iconst_0
L51:    istore 10
L53:    iconst_0
L54:    istore 11
L56:    iload 20
L58:    ifeq L309
L61:    iconst_0
L62:    istore 12
L64:    aload_1
L65:    iload 6
L67:    caload
L68:    istore 13
L70:    iconst_0
L71:    istore 14
L73:    iload 6
L75:    iconst_1
L76:    iadd
L77:    aload_1
L78:    arraylength
L79:    if_icmpge L90
L82:    aload_1
L83:    iload 6
L85:    iconst_1
L86:    iadd
L87:    caload
L88:    istore 14
L90:    iload 7
L92:    aload_3
L93:    arraylength
L94:    if_icmpge L183
L97:    iload 14
L99:    iload 13
L101:   getstatic Field RKAYAFDQ i Z
L104:   aload_3
L105:   iload 7
L107:   caload
L108:   invokestatic Method RKAYAFDQ a (CCZC)I
L111:   dup
L112:   istore 12
L114:   ifle L183
L117:   iload 12
L119:   iconst_1
L120:   if_icmpne L137
L123:   iload 13
L125:   sipush -976
L128:   invokestatic Method RKAYAFDQ d (CI)Z
L131:   ifeq L137
L134:   iconst_1
L135:   istore 10
L137:   iload 12
L139:   iconst_2
L140:   if_icmpne L168
L143:   iload 13
L145:   sipush -976
L148:   invokestatic Method RKAYAFDQ d (CI)Z
L151:   ifne L165
L154:   iload 14
L156:   sipush -976
L159:   invokestatic Method RKAYAFDQ d (CI)Z
L162:   ifeq L168
L165:   iconst_1
L166:   istore 10
L168:   iload 6
L170:   iload 12
L172:   iadd
L173:   istore 6
L175:   iinc 7 1
L178:   iload 20
L180:   ifeq L309
L183:   iload 7
L185:   ifeq L326
L188:   iload 14
L190:   iload 13
L192:   getstatic Field RKAYAFDQ i Z
L195:   aload_3
L196:   iload 7
L198:   iconst_1
L199:   isub
L200:   caload
L201:   invokestatic Method RKAYAFDQ a (CCZC)I
L204:   dup
L205:   istore 12
L207:   ifle L231
L210:   iload 6
L212:   iload 12
L214:   iadd
L215:   istore 6
L217:   iload 7
L219:   iconst_1
L220:   if_icmpne L309
L223:   iinc 4 1
L226:   iload 20
L228:   ifeq L309
L231:   iload 7
L233:   aload_3
L234:   arraylength
L235:   if_icmpge L326
L238:   iconst_0
L239:   iload 13
L241:   invokestatic Method RKAYAFDQ a (ZC)Z
L244:   ifeq L326
L247:   sipush -12789
L250:   iload 13
L252:   invokestatic Method RKAYAFDQ a (IC)Z
L255:   ifeq L268
L258:   iload 13
L260:   bipush 39
L262:   if_icmpeq L268
L265:   iconst_1
L266:   istore 9
L268:   iload 13
L270:   sipush -976
L273:   invokestatic Method RKAYAFDQ d (CI)Z
L276:   ifeq L282
L279:   iconst_1
L280:   istore 11
L282:   iinc 6 1
L285:   iinc 8 1
L288:   iload 8
L290:   bipush 100
L292:   imul
L293:   iload 6
L295:   iload 5
L297:   isub
L298:   idiv
L299:   bipush 90
L301:   if_icmple L309
L304:   iload 20
L306:   ifeq L326
L309:   iload 6
L311:   aload_1
L312:   arraylength
L313:   if_icmpge L326
L316:   iload 10
L318:   ifeq L61
L321:   iload 11
L323:   ifeq L61
L326:   iload 7
L328:   aload_3
L329:   arraylength
L330:   if_icmplt L865
L333:   iload 10
L335:   ifeq L343
L338:   iload 11
L340:   ifne L865
L343:   iconst_1
L344:   istore 12
L346:   iload 9
L348:   ifne L432
L351:   bipush 32
L353:   istore 13
L355:   iload 5
L357:   iconst_1
L358:   isub
L359:   iflt L370
L362:   aload_1
L363:   iload 5
L365:   iconst_1
L366:   isub
L367:   caload
L368:   istore 13
L370:   bipush 32
L372:   istore 14
L374:   iload 6
L376:   aload_1
L377:   arraylength
L378:   if_icmpge L387
L381:   aload_1
L382:   iload 6
L384:   caload
L385:   istore 14
L387:   iload 13
L389:   getstatic Field RKAYAFDQ j I
L392:   invokestatic Method RKAYAFDQ b (CI)B
L395:   istore 15
L397:   iload 14
L399:   getstatic Field RKAYAFDQ j I
L402:   invokestatic Method RKAYAFDQ b (CI)B
L405:   istore 16
L407:   aload_0
L408:   ifnull L734
L411:   iload 15
L413:   bipush 8
L415:   aload_0
L416:   iload 16
L418:   invokestatic Method RKAYAFDQ a (BB[[BB)Z
L421:   ifeq L734
L424:   iconst_0
L425:   istore 12
L427:   iload 20
L429:   ifeq L734
L432:   iconst_0
L433:   istore 13
L435:   iconst_0
L436:   istore 14
L438:   iload 5
L440:   iconst_1
L441:   isub
L442:   iflt L471
L445:   sipush -12789
L448:   aload_1
L449:   iload 5
L451:   iconst_1
L452:   isub
L453:   caload
L454:   invokestatic Method RKAYAFDQ a (IC)Z
L457:   ifeq L474
L460:   aload_1
L461:   iload 5
L463:   iconst_1
L464:   isub
L465:   caload
L466:   bipush 39
L468:   if_icmpeq L474
L471:   iconst_1
L472:   istore 13
L474:   iload 6
L476:   aload_1
L477:   arraylength
L478:   if_icmpge L503
L481:   sipush -12789
L484:   aload_1
L485:   iload 6
L487:   caload
L488:   invokestatic Method RKAYAFDQ a (IC)Z
L491:   ifeq L506
L494:   aload_1
L495:   iload 6
L497:   caload
L498:   bipush 39
L500:   if_icmpeq L506
L503:   iconst_1
L504:   istore 14
L506:   iload 13
L508:   ifeq L516
L511:   iload 14
L513:   ifne L734
L516:   iconst_0
L517:   istore 15
L519:   iload 5
L521:   iconst_2
L522:   isub
L523:   istore 16
L525:   iload 13
L527:   ifeq L714
L530:   iload 5
L532:   istore 16
L534:   iload 20
L536:   ifeq L714
L539:   iload 16
L541:   iflt L711
L544:   sipush -12789
L547:   aload_1
L548:   iload 16
L550:   caload
L551:   invokestatic Method RKAYAFDQ a (IC)Z
L554:   ifeq L566
L557:   aload_1
L558:   iload 16
L560:   caload
L561:   bipush 39
L563:   if_icmpne L711
L566:   iconst_3
L567:   newarray char
L569:   astore 17
L571:   iconst_0
L572:   istore 18
L574:   iload 20
L576:   ifeq L635
L579:   iload 16
L581:   iload 18
L583:   iadd
L584:   aload_1
L585:   arraylength
L586:   if_icmpge L641
L589:   sipush -12789
L592:   aload_1
L593:   iload 16
L595:   iload 18
L597:   iadd
L598:   caload
L599:   invokestatic Method RKAYAFDQ a (IC)Z
L602:   ifeq L617
L605:   aload_1
L606:   iload 16
L608:   iload 18
L610:   iadd
L611:   caload
L612:   bipush 39
L614:   if_icmpne L641
L617:   aload 17
L619:   iload 18
L621:   aload_1
L622:   iload 16
L624:   iload 18
L626:   iadd
L627:   caload
L628:   castore
L629:   goto L632
L632:   iinc 18 1
L635:   iload 18
L637:   iconst_3
L638:   if_icmplt L579
L641:   iconst_1
L642:   istore 19
L644:   iload 18
L646:   ifne L652
L649:   iconst_0
L650:   istore 19
L652:   iload 18
L654:   iconst_3
L655:   if_icmpge L694
L658:   iload 16
L660:   iconst_1
L661:   isub
L662:   iflt L694
L665:   sipush -12789
L668:   aload_1
L669:   iload 16
L671:   iconst_1
L672:   isub
L673:   caload
L674:   invokestatic Method RKAYAFDQ a (IC)Z
L677:   ifeq L691
L680:   aload_1
L681:   iload 16
L683:   iconst_1
L684:   isub
L685:   caload
L686:   bipush 39
L688:   if_icmpne L694
L691:   iconst_0
L692:   istore 19
L694:   iload 19
L696:   ifeq L711
L699:   aload 17
L701:   iconst_4
L702:   invokestatic Method RKAYAFDQ a ([CB)Z
L705:   ifne L711
L708:   iconst_1
L709:   istore 15
L711:   iinc 16 1
L714:   iload 15
L716:   ifne L726
L719:   iload 16
L721:   iload 6
L723:   if_icmplt L539
L726:   iload 15
L728:   ifne L734
L731:   iconst_0
L732:   istore 12
L734:   iload 12
L736:   ifeq L865
L739:   iconst_0
L740:   istore 13
L742:   iconst_0
L743:   istore 14
L745:   iconst_m1
L746:   istore 15
L748:   iload 5
L750:   istore 16
L752:   iload 20
L754:   ifeq L800
L757:   aload_1
L758:   iload 16
L760:   caload
L761:   sipush -976
L764:   invokestatic Method RKAYAFDQ d (CI)Z
L767:   ifeq L778
L770:   iinc 13 1
L773:   iload 20
L775:   ifeq L797
L778:   aload_1
L779:   iload 16
L781:   caload
L782:   ldc -46837
L784:   invokestatic Method RKAYAFDQ c (CI)Z
L787:   ifeq L797
L790:   iinc 14 1
L793:   iload 16
L795:   istore 15
L797:   iinc 16 1
L800:   iload 16
L802:   iload 6
L804:   if_icmplt L757
L807:   iload 15
L809:   iconst_m1
L810:   if_icmple L825
L813:   iload 13
L815:   iload 6
L817:   iconst_1
L818:   isub
L819:   iload 15
L821:   isub
L822:   isub
L823:   istore 13
L825:   iload 13
L827:   iload 14
L829:   if_icmpgt L862
L832:   iload 5
L834:   istore 17
L836:   iload 20
L838:   ifeq L850
L841:   aload_1
L842:   iload 17
L844:   bipush 42
L846:   castore
L847:   iinc 17 1
L850:   iload 17
L852:   iload 6
L854:   if_icmplt L841
L857:   iload 20
L859:   ifeq L865
L862:   iconst_1
L863:   istore 4
L865:   iload 5
L867:   iload 4
L869:   iadd
L870:   istore 5
L872:   iload 5
L874:   aload_1
L875:   arraylength
L876:   aload_3
L877:   arraylength
L878:   isub
L879:   if_icmple L34
L882:   return
L883:   astore 4
L885:   new java/lang/StringBuffer
L888:   dup
L889:   ldc "25459, "
L891:   invokespecial Method java/lang/StringBuffer <init> (Ljava/lang/String;)V
L894:   aload_0
L895:   invokevirtual Method java/lang/StringBuffer append (Ljava/lang/Object;)Ljava/lang/StringBuffer;
L898:   ldc ", "
L900:   invokevirtual Method java/lang/StringBuffer append (Ljava/lang/String;)Ljava/lang/StringBuffer;
L903:   aload_1
L904:   invokevirtual Method java/lang/StringBuffer append ([C)Ljava/lang/StringBuffer;
L907:   ldc ", "
L909:   invokevirtual Method java/lang/StringBuffer append (Ljava/lang/String;)Ljava/lang/StringBuffer;
L912:   iload_2
L913:   invokevirtual Method java/lang/StringBuffer append (I)Ljava/lang/StringBuffer;
L916:   ldc ", "
L918:   invokevirtual Method java/lang/StringBuffer append (Ljava/lang/String;)Ljava/lang/StringBuffer;
L921:   aload_3
L922:   invokevirtual Method java/lang/StringBuffer append ([C)Ljava/lang/StringBuffer;
L925:   ldc ", "
L927:   invokevirtual Method java/lang/StringBuffer append (Ljava/lang/String;)Ljava/lang/StringBuffer;
L930:   aload 4
L932:   invokevirtual Method java/lang/Throwable toString ()Ljava/lang/String;
L935:   invokevirtual Method java/lang/StringBuffer append (Ljava/lang/String;)Ljava/lang/StringBuffer;
L938:   invokevirtual Method java/lang/StringBuffer toString ()Ljava/lang/String;
L941:   invokestatic Method sign/signlink reporterror (Ljava/lang/String;)V
L944:   new java/lang/RuntimeException
L947:   dup
L948:   invokespecial Method java/lang/RuntimeException <init> ()V
L951:   athrow
L952:   
    .end code
.end method

.method private static final a : (BB[[BB)Z
    .code stack 4 locals 7
        .catch java/lang/RuntimeException from L0 to L158 using L158
L0:     iconst_0
L1:     istore 4
L3:     iload_1
L4:     bipush 8
L6:     if_icmpeq L15
L9:     sipush 308
L12:    putstatic Field RKAYAFDQ h I
L15:    aload_2
L16:    iload 4
L18:    aaload
L19:    iconst_0
L20:    baload
L21:    iload_0
L22:    if_icmpne L37
L25:    aload_2
L26:    iload 4
L28:    aaload
L29:    iconst_1
L30:    baload
L31:    iload_3
L32:    if_icmpne L37
L35:    iconst_1
L36:    ireturn
L37:    aload_2
L38:    arraylength
L39:    iconst_1
L40:    isub
L41:    istore 5
L43:    aload_2
L44:    iload 5
L46:    aaload
L47:    iconst_0
L48:    baload
L49:    iload_0
L50:    if_icmpne L65
L53:    aload_2
L54:    iload 5
L56:    aaload
L57:    iconst_1
L58:    baload
L59:    iload_3
L60:    if_icmpne L65
L63:    iconst_1
L64:    ireturn
L65:    iload 4
L67:    iload 5
L69:    iadd
L70:    iconst_2
L71:    idiv
L72:    istore 6
L74:    aload_2
L75:    iload 6
L77:    aaload
L78:    iconst_0
L79:    baload
L80:    iload_0
L81:    if_icmpne L96
L84:    aload_2
L85:    iload 6
L87:    aaload
L88:    iconst_1
L89:    baload
L90:    iload_3
L91:    if_icmpne L96
L94:    iconst_1
L95:    ireturn
L96:    iload_0
L97:    aload_2
L98:    iload 6
L100:   aaload
L101:   iconst_0
L102:   baload
L103:   if_icmplt L126
L106:   iload_0
L107:   aload_2
L108:   iload 6
L110:   aaload
L111:   iconst_0
L112:   baload
L113:   if_icmpne L136
L116:   iload_3
L117:   aload_2
L118:   iload 6
L120:   aaload
L121:   iconst_1
L122:   baload
L123:   if_icmpge L136
L126:   iload 6
L128:   istore 5
L130:   getstatic Field RKAYAFDQ v Z
L133:   ifeq L140
L136:   iload 6
L138:   istore 4
L140:   iload 4
L142:   iload 5
L144:   if_icmpeq L156
L147:   iload 4
L149:   iconst_1
L150:   iadd
L151:   iload 5
L153:   if_icmpne L65
L156:   iconst_0
L157:   ireturn
L158:   astore 4
L160:   new java/lang/StringBuffer
L163:   dup
L164:   ldc "67276, "
L166:   invokespecial Method java/lang/StringBuffer <init> (Ljava/lang/String;)V
L169:   iload_0
L170:   invokevirtual Method java/lang/StringBuffer append (I)Ljava/lang/StringBuffer;
L173:   ldc ", "
L175:   invokevirtual Method java/lang/StringBuffer append (Ljava/lang/String;)Ljava/lang/StringBuffer;
L178:   iload_1
L179:   invokevirtual Method java/lang/StringBuffer append (I)Ljava/lang/StringBuffer;
L182:   ldc ", "
L184:   invokevirtual Method java/lang/StringBuffer append (Ljava/lang/String;)Ljava/lang/StringBuffer;
L187:   aload_2
L188:   invokevirtual Method java/lang/StringBuffer append (Ljava/lang/Object;)Ljava/lang/StringBuffer;
L191:   ldc ", "
L193:   invokevirtual Method java/lang/StringBuffer append (Ljava/lang/String;)Ljava/lang/StringBuffer;
L196:   iload_3
L197:   invokevirtual Method java/lang/StringBuffer append (I)Ljava/lang/StringBuffer;
L200:   ldc ", "
L202:   invokevirtual Method java/lang/StringBuffer append (Ljava/lang/String;)Ljava/lang/StringBuffer;
L205:   aload 4
L207:   invokevirtual Method java/lang/Throwable toString ()Ljava/lang/String;
L210:   invokevirtual Method java/lang/StringBuffer append (Ljava/lang/String;)Ljava/lang/StringBuffer;
L213:   invokevirtual Method java/lang/StringBuffer toString ()Ljava/lang/String;
L216:   invokestatic Method sign/signlink reporterror (Ljava/lang/String;)V
L219:   new java/lang/RuntimeException
L222:   dup
L223:   invokespecial Method java/lang/RuntimeException <init> ()V
L226:   athrow
L227:   
    .end code
.end method

.method private static final a : (ICCC)I
    .code stack 3 locals 5
        .catch java/lang/RuntimeException from L0 to L120 using L120
L0:     iload_0
L1:     ifgt L8
L4:     getstatic Field RKAYAFDQ c I
L7:     ireturn
L8:     iload_2
L9:     iload_1
L10:    if_icmpne L15
L13:    iconst_1
L14:    ireturn
L15:    iload_2
L16:    bipush 111
L18:    if_icmpne L29
L21:    iload_1
L22:    bipush 48
L24:    if_icmpne L29
L27:    iconst_1
L28:    ireturn
L29:    iload_2
L30:    bipush 111
L32:    if_icmpne L49
L35:    iload_1
L36:    bipush 40
L38:    if_icmpne L49
L41:    iload_3
L42:    bipush 41
L44:    if_icmpne L49
L47:    iconst_2
L48:    ireturn
L49:    iload_2
L50:    bipush 99
L52:    if_icmpne L75
L55:    iload_1
L56:    bipush 40
L58:    if_icmpeq L73
L61:    iload_1
L62:    bipush 60
L64:    if_icmpeq L73
L67:    iload_1
L68:    bipush 91
L70:    if_icmpne L75
L73:    iconst_1
L74:    ireturn
L75:    iload_2
L76:    bipush 101
L78:    if_icmpne L90
L81:    iload_1
L82:    sipush 8364
L85:    if_icmpne L90
L88:    iconst_1
L89:    ireturn
L90:    iload_2
L91:    bipush 115
L93:    if_icmpne L104
L96:    iload_1
L97:    bipush 36
L99:    if_icmpne L104
L102:   iconst_1
L103:   ireturn
L104:   iload_2
L105:   bipush 108
L107:   if_icmpne L118
L110:   iload_1
L111:   bipush 105
L113:   if_icmpne L118
L116:   iconst_1
L117:   ireturn
L118:   iconst_0
L119:   ireturn
L120:   astore 4
L122:   new java/lang/StringBuffer
L125:   dup
L126:   ldc "60577, "
L128:   invokespecial Method java/lang/StringBuffer <init> (Ljava/lang/String;)V
L131:   iload_0
L132:   invokevirtual Method java/lang/StringBuffer append (I)Ljava/lang/StringBuffer;
L135:   ldc ", "
L137:   invokevirtual Method java/lang/StringBuffer append (Ljava/lang/String;)Ljava/lang/StringBuffer;
L140:   iload_1
L141:   invokevirtual Method java/lang/StringBuffer append (C)Ljava/lang/StringBuffer;
L144:   ldc ", "
L146:   invokevirtual Method java/lang/StringBuffer append (Ljava/lang/String;)Ljava/lang/StringBuffer;
L149:   iload_2
L150:   invokevirtual Method java/lang/StringBuffer append (C)Ljava/lang/StringBuffer;
L153:   ldc ", "
L155:   invokevirtual Method java/lang/StringBuffer append (Ljava/lang/String;)Ljava/lang/StringBuffer;
L158:   iload_3
L159:   invokevirtual Method java/lang/StringBuffer append (C)Ljava/lang/StringBuffer;
L162:   ldc ", "
L164:   invokevirtual Method java/lang/StringBuffer append (Ljava/lang/String;)Ljava/lang/StringBuffer;
L167:   aload 4
L169:   invokevirtual Method java/lang/Throwable toString ()Ljava/lang/String;
L172:   invokevirtual Method java/lang/StringBuffer append (Ljava/lang/String;)Ljava/lang/StringBuffer;
L175:   invokevirtual Method java/lang/StringBuffer toString ()Ljava/lang/String;
L178:   invokestatic Method sign/signlink reporterror (Ljava/lang/String;)V
L181:   new java/lang/RuntimeException
L184:   dup
L185:   invokespecial Method java/lang/RuntimeException <init> ()V
L188:   athrow
L189:   
    .end code
.end method

.method private static final a : (CCZC)I
    .code stack 3 locals 5
        .catch java/lang/RuntimeException from L0 to L903 using L903
L0:     iload_2
L1:     ifne L10
L4:     sipush -260
L7:     putstatic Field RKAYAFDQ h I
L10:    iload_3
L11:    iload_1
L12:    if_icmpne L17
L15:    iconst_1
L16:    ireturn
L17:    iload_3
L18:    bipush 97
L20:    if_icmplt L395
L23:    iload_3
L24:    bipush 109
L26:    if_icmpgt L395
L29:    iload_3
L30:    bipush 97
L32:    if_icmpne L71
L35:    iload_1
L36:    bipush 52
L38:    if_icmpeq L53
L41:    iload_1
L42:    bipush 64
L44:    if_icmpeq L53
L47:    iload_1
L48:    bipush 94
L50:    if_icmpne L55
L53:    iconst_1
L54:    ireturn
L55:    iload_1
L56:    bipush 47
L58:    if_icmpne L69
L61:    iload_0
L62:    bipush 92
L64:    if_icmpne L69
L67:    iconst_2
L68:    ireturn
L69:    iconst_0
L70:    ireturn
L71:    iload_3
L72:    bipush 98
L74:    if_icmpne L119
L77:    iload_1
L78:    bipush 54
L80:    if_icmpeq L89
L83:    iload_1
L84:    bipush 56
L86:    if_icmpne L91
L89:    iconst_1
L90:    ireturn
L91:    iload_1
L92:    bipush 49
L94:    if_icmpne L103
L97:    iload_0
L98:    bipush 51
L100:   if_icmpeq L115
L103:   iload_1
L104:   bipush 105
L106:   if_icmpne L117
L109:   iload_0
L110:   bipush 51
L112:   if_icmpne L117
L115:   iconst_2
L116:   ireturn
L117:   iconst_0
L118:   ireturn
L119:   iload_3
L120:   bipush 99
L122:   if_icmpne L153
L125:   iload_1
L126:   bipush 40
L128:   if_icmpeq L149
L131:   iload_1
L132:   bipush 60
L134:   if_icmpeq L149
L137:   iload_1
L138:   bipush 123
L140:   if_icmpeq L149
L143:   iload_1
L144:   bipush 91
L146:   if_icmpne L151
L149:   iconst_1
L150:   ireturn
L151:   iconst_0
L152:   ireturn
L153:   iload_3
L154:   bipush 100
L156:   if_icmpne L187
L159:   iload_1
L160:   bipush 91
L162:   if_icmpne L171
L165:   iload_0
L166:   bipush 41
L168:   if_icmpeq L183
L171:   iload_1
L172:   bipush 105
L174:   if_icmpne L185
L177:   iload_0
L178:   bipush 41
L180:   if_icmpne L185
L183:   iconst_2
L184:   ireturn
L185:   iconst_0
L186:   ireturn
L187:   iload_3
L188:   bipush 101
L190:   if_icmpne L210
L193:   iload_1
L194:   bipush 51
L196:   if_icmpeq L206
L199:   iload_1
L200:   sipush 8364
L203:   if_icmpne L208
L206:   iconst_1
L207:   ireturn
L208:   iconst_0
L209:   ireturn
L210:   iload_3
L211:   bipush 102
L213:   if_icmpne L241
L216:   iload_1
L217:   bipush 112
L219:   if_icmpne L230
L222:   iload_0
L223:   bipush 104
L225:   if_icmpne L230
L228:   iconst_2
L229:   ireturn
L230:   iload_1
L231:   sipush 163
L234:   if_icmpne L239
L237:   iconst_1
L238:   ireturn
L239:   iconst_0
L240:   ireturn
L241:   iload_3
L242:   bipush 103
L244:   if_icmpne L269
L247:   iload_1
L248:   bipush 57
L250:   if_icmpeq L265
L253:   iload_1
L254:   bipush 54
L256:   if_icmpeq L265
L259:   iload_1
L260:   bipush 113
L262:   if_icmpne L267
L265:   iconst_1
L266:   ireturn
L267:   iconst_0
L268:   ireturn
L269:   iload_3
L270:   bipush 104
L272:   if_icmpne L285
L275:   iload_1
L276:   bipush 35
L278:   if_icmpne L283
L281:   iconst_1
L282:   ireturn
L283:   iconst_0
L284:   ireturn
L285:   iload_3
L286:   bipush 105
L288:   if_icmpne L343
L291:   iload_1
L292:   bipush 121
L294:   if_icmpeq L339
L297:   iload_1
L298:   bipush 108
L300:   if_icmpeq L339
L303:   iload_1
L304:   bipush 106
L306:   if_icmpeq L339
L309:   iload_1
L310:   bipush 49
L312:   if_icmpeq L339
L315:   iload_1
L316:   bipush 33
L318:   if_icmpeq L339
L321:   iload_1
L322:   bipush 58
L324:   if_icmpeq L339
L327:   iload_1
L328:   bipush 59
L330:   if_icmpeq L339
L333:   iload_1
L334:   bipush 124
L336:   if_icmpne L341
L339:   iconst_1
L340:   ireturn
L341:   iconst_0
L342:   ireturn
L343:   iload_3
L344:   bipush 106
L346:   if_icmpne L351
L349:   iconst_0
L350:   ireturn
L351:   iload_3
L352:   bipush 107
L354:   if_icmpne L359
L357:   iconst_0
L358:   ireturn
L359:   iload_3
L360:   bipush 108
L362:   if_icmpne L387
L365:   iload_1
L366:   bipush 49
L368:   if_icmpeq L383
L371:   iload_1
L372:   bipush 124
L374:   if_icmpeq L383
L377:   iload_1
L378:   bipush 105
L380:   if_icmpne L385
L383:   iconst_1
L384:   ireturn
L385:   iconst_0
L386:   ireturn
L387:   iload_3
L388:   bipush 109
L390:   if_icmpne L395
L393:   iconst_0
L394:   ireturn
L395:   iload_3
L396:   bipush 110
L398:   if_icmplt L763
L401:   iload_3
L402:   bipush 122
L404:   if_icmpgt L763
L407:   iload_3
L408:   bipush 110
L410:   if_icmpne L415
L413:   iconst_0
L414:   ireturn
L415:   iload_3
L416:   bipush 111
L418:   if_icmpne L487
L421:   iload_1
L422:   bipush 48
L424:   if_icmpeq L433
L427:   iload_1
L428:   bipush 42
L430:   if_icmpne L435
L433:   iconst_1
L434:   ireturn
L435:   iload_1
L436:   bipush 40
L438:   if_icmpne L447
L441:   iload_0
L442:   bipush 41
L444:   if_icmpeq L483
L447:   iload_1
L448:   bipush 91
L450:   if_icmpne L459
L453:   iload_0
L454:   bipush 93
L456:   if_icmpeq L483
L459:   iload_1
L460:   bipush 123
L462:   if_icmpne L471
L465:   iload_0
L466:   bipush 125
L468:   if_icmpeq L483
L471:   iload_1
L472:   bipush 60
L474:   if_icmpne L485
L477:   iload_0
L478:   bipush 62
L480:   if_icmpne L485
L483:   iconst_2
L484:   ireturn
L485:   iconst_0
L486:   ireturn
L487:   iload_3
L488:   bipush 112
L490:   if_icmpne L495
L493:   iconst_0
L494:   ireturn
L495:   iload_3
L496:   bipush 113
L498:   if_icmpne L503
L501:   iconst_0
L502:   ireturn
L503:   iload_3
L504:   bipush 114
L506:   if_icmpne L511
L509:   iconst_0
L510:   ireturn
L511:   iload_3
L512:   bipush 115
L514:   if_icmpne L545
L517:   iload_1
L518:   bipush 53
L520:   if_icmpeq L541
L523:   iload_1
L524:   bipush 122
L526:   if_icmpeq L541
L529:   iload_1
L530:   bipush 36
L532:   if_icmpeq L541
L535:   iload_1
L536:   bipush 50
L538:   if_icmpne L543
L541:   iconst_1
L542:   ireturn
L543:   iconst_0
L544:   ireturn
L545:   iload_3
L546:   bipush 116
L548:   if_icmpne L567
L551:   iload_1
L552:   bipush 55
L554:   if_icmpeq L563
L557:   iload_1
L558:   bipush 43
L560:   if_icmpne L565
L563:   iconst_1
L564:   ireturn
L565:   iconst_0
L566:   ireturn
L567:   iload_3
L568:   bipush 117
L570:   if_icmpne L621
L573:   iload_1
L574:   bipush 118
L576:   if_icmpne L581
L579:   iconst_1
L580:   ireturn
L581:   iload_1
L582:   bipush 92
L584:   if_icmpne L593
L587:   iload_0
L588:   bipush 47
L590:   if_icmpeq L617
L593:   iload_1
L594:   bipush 92
L596:   if_icmpne L605
L599:   iload_0
L600:   bipush 124
L602:   if_icmpeq L617
L605:   iload_1
L606:   bipush 124
L608:   if_icmpne L619
L611:   iload_0
L612:   bipush 47
L614:   if_icmpne L619
L617:   iconst_2
L618:   ireturn
L619:   iconst_0
L620:   ireturn
L621:   iload_3
L622:   bipush 118
L624:   if_icmpne L667
L627:   iload_1
L628:   bipush 92
L630:   if_icmpne L639
L633:   iload_0
L634:   bipush 47
L636:   if_icmpeq L663
L639:   iload_1
L640:   bipush 92
L642:   if_icmpne L651
L645:   iload_0
L646:   bipush 124
L648:   if_icmpeq L663
L651:   iload_1
L652:   bipush 124
L654:   if_icmpne L665
L657:   iload_0
L658:   bipush 47
L660:   if_icmpne L665
L663:   iconst_2
L664:   ireturn
L665:   iconst_0
L666:   ireturn
L667:   iload_3
L668:   bipush 119
L670:   if_icmpne L689
L673:   iload_1
L674:   bipush 118
L676:   if_icmpne L687
L679:   iload_0
L680:   bipush 118
L682:   if_icmpne L687
L685:   iconst_2
L686:   ireturn
L687:   iconst_0
L688:   ireturn
L689:   iload_3
L690:   bipush 120
L692:   if_icmpne L747
L695:   iload_1
L696:   bipush 41
L698:   if_icmpne L707
L701:   iload_0
L702:   bipush 40
L704:   if_icmpeq L743
L707:   iload_1
L708:   bipush 125
L710:   if_icmpne L719
L713:   iload_0
L714:   bipush 123
L716:   if_icmpeq L743
L719:   iload_1
L720:   bipush 93
L722:   if_icmpne L731
L725:   iload_0
L726:   bipush 91
L728:   if_icmpeq L743
L731:   iload_1
L732:   bipush 62
L734:   if_icmpne L745
L737:   iload_0
L738:   bipush 60
L740:   if_icmpne L745
L743:   iconst_2
L744:   ireturn
L745:   iconst_0
L746:   ireturn
L747:   iload_3
L748:   bipush 121
L750:   if_icmpne L755
L753:   iconst_0
L754:   ireturn
L755:   iload_3
L756:   bipush 122
L758:   if_icmpne L763
L761:   iconst_0
L762:   ireturn
L763:   iload_3
L764:   bipush 48
L766:   if_icmplt L853
L769:   iload_3
L770:   bipush 57
L772:   if_icmpgt L853
L775:   iload_3
L776:   bipush 48
L778:   if_icmpne L835
L781:   iload_1
L782:   bipush 111
L784:   if_icmpeq L793
L787:   iload_1
L788:   bipush 79
L790:   if_icmpne L795
L793:   iconst_1
L794:   ireturn
L795:   iload_1
L796:   bipush 40
L798:   if_icmpne L807
L801:   iload_0
L802:   bipush 41
L804:   if_icmpeq L831
L807:   iload_1
L808:   bipush 123
L810:   if_icmpne L819
L813:   iload_0
L814:   bipush 125
L816:   if_icmpeq L831
L819:   iload_1
L820:   bipush 91
L822:   if_icmpne L833
L825:   iload_0
L826:   bipush 93
L828:   if_icmpne L833
L831:   iconst_2
L832:   ireturn
L833:   iconst_0
L834:   ireturn
L835:   iload_3
L836:   bipush 49
L838:   if_icmpne L851
L841:   iload_1
L842:   bipush 108
L844:   if_icmpne L849
L847:   iconst_1
L848:   ireturn
L849:   iconst_0
L850:   ireturn
L851:   iconst_0
L852:   ireturn
L853:   iload_3
L854:   bipush 44
L856:   if_icmpne L869
L859:   iload_1
L860:   bipush 46
L862:   if_icmpne L867
L865:   iconst_1
L866:   ireturn
L867:   iconst_0
L868:   ireturn
L869:   iload_3
L870:   bipush 46
L872:   if_icmpne L885
L875:   iload_1
L876:   bipush 44
L878:   if_icmpne L883
L881:   iconst_1
L882:   ireturn
L883:   iconst_0
L884:   ireturn
L885:   iload_3
L886:   bipush 33
L888:   if_icmpne L901
L891:   iload_1
L892:   bipush 105
L894:   if_icmpne L899
L897:   iconst_1
L898:   ireturn
L899:   iconst_0
L900:   ireturn
L901:   iconst_0
L902:   ireturn
L903:   astore 4
L905:   new java/lang/StringBuffer
L908:   dup
L909:   ldc "9538, "
L911:   invokespecial Method java/lang/StringBuffer <init> (Ljava/lang/String;)V
L914:   iload_0
L915:   invokevirtual Method java/lang/StringBuffer append (C)Ljava/lang/StringBuffer;
L918:   ldc ", "
L920:   invokevirtual Method java/lang/StringBuffer append (Ljava/lang/String;)Ljava/lang/StringBuffer;
L923:   iload_1
L924:   invokevirtual Method java/lang/StringBuffer append (C)Ljava/lang/StringBuffer;
L927:   ldc ", "
L929:   invokevirtual Method java/lang/StringBuffer append (Ljava/lang/String;)Ljava/lang/StringBuffer;
L932:   iload_2
L933:   invokevirtual Method java/lang/StringBuffer append (Z)Ljava/lang/StringBuffer;
L936:   ldc ", "
L938:   invokevirtual Method java/lang/StringBuffer append (Ljava/lang/String;)Ljava/lang/StringBuffer;
L941:   iload_3
L942:   invokevirtual Method java/lang/StringBuffer append (C)Ljava/lang/StringBuffer;
L945:   ldc ", "
L947:   invokevirtual Method java/lang/StringBuffer append (Ljava/lang/String;)Ljava/lang/StringBuffer;
L950:   aload 4
L952:   invokevirtual Method java/lang/Throwable toString ()Ljava/lang/String;
L955:   invokevirtual Method java/lang/StringBuffer append (Ljava/lang/String;)Ljava/lang/StringBuffer;
L958:   invokevirtual Method java/lang/StringBuffer toString ()Ljava/lang/String;
L961:   invokestatic Method sign/signlink reporterror (Ljava/lang/String;)V
L964:   new java/lang/RuntimeException
L967:   dup
L968:   invokespecial Method java/lang/RuntimeException <init> ()V
L971:   athrow
L972:   
    .end code
.end method

.method private static final b : (CI)B
    .code stack 4 locals 3
        .catch java/lang/RuntimeException from L0 to L68 using L68
L0:     getstatic Field RKAYAFDQ v Z
L3:     ifeq L11
L6:     bipush -93
L8:     putstatic Field RKAYAFDQ a I
L11:    iload_1
L12:    ifge L6
L15:    iload_0
L16:    bipush 97
L18:    if_icmplt L35
L21:    iload_0
L22:    bipush 122
L24:    if_icmpgt L35
L27:    iload_0
L28:    bipush 97
L30:    isub
L31:    iconst_1
L32:    iadd
L33:    i2b
L34:    ireturn
L35:    iload_0
L36:    bipush 39
L38:    if_icmpne L44
L41:    bipush 28
L43:    ireturn
L44:    iload_0
L45:    bipush 48
L47:    if_icmplt L65
L50:    iload_0
L51:    bipush 57
L53:    if_icmpgt L65
L56:    iload_0
L57:    bipush 48
L59:    isub
L60:    bipush 29
L62:    iadd
L63:    i2b
L64:    ireturn
L65:    bipush 27
L67:    ireturn
L68:    astore_2
L69:    new java/lang/StringBuffer
L72:    dup
L73:    ldc "52349, "
L75:    invokespecial Method java/lang/StringBuffer <init> (Ljava/lang/String;)V
L78:    iload_0
L79:    invokevirtual Method java/lang/StringBuffer append (C)Ljava/lang/StringBuffer;
L82:    ldc ", "
L84:    invokevirtual Method java/lang/StringBuffer append (Ljava/lang/String;)Ljava/lang/StringBuffer;
L87:    iload_1
L88:    invokevirtual Method java/lang/StringBuffer append (I)Ljava/lang/StringBuffer;
L91:    ldc ", "
L93:    invokevirtual Method java/lang/StringBuffer append (Ljava/lang/String;)Ljava/lang/StringBuffer;
L96:    aload_2
L97:    invokevirtual Method java/lang/Throwable toString ()Ljava/lang/String;
L100:   invokevirtual Method java/lang/StringBuffer append (Ljava/lang/String;)Ljava/lang/StringBuffer;
L103:   invokevirtual Method java/lang/StringBuffer toString ()Ljava/lang/String;
L106:   invokestatic Method sign/signlink reporterror (Ljava/lang/String;)V
L109:   new java/lang/RuntimeException
L112:   dup
L113:   invokespecial Method java/lang/RuntimeException <init> ()V
L116:   athrow
L117:   
    .end code
.end method

.method private static final a : ([CI)V
    .code stack 4 locals 12
L0:     getstatic Field RKAYAFDQ v Z
L3:     istore 11
        .catch java/lang/RuntimeException from L5 to L227 using L228
L5:     iconst_0
L6:     istore_2
L7:     iconst_0
L8:     istore_3
L9:     iconst_0
L10:    istore 4
L12:    iconst_0
L13:    istore 5
L15:    iload_1
L16:    iflt L213
L19:    getstatic Field RKAYAFDQ b Z
L22:    ifeq L29
L25:    iconst_0
L26:    goto L30
L29:    iconst_1
L30:    putstatic Field RKAYAFDQ b Z
L33:    iload 11
L35:    ifeq L213
L38:    iconst_0
L39:    istore 6
L41:    iload_3
L42:    istore 7
L44:    iload 11
L46:    ifeq L79
L49:    sipush -12789
L52:    aload_0
L53:    iload 7
L55:    caload
L56:    invokestatic Method RKAYAFDQ a (IC)Z
L59:    ifne L76
L62:    iconst_0
L63:    aload_0
L64:    iload 7
L66:    caload
L67:    invokestatic Method RKAYAFDQ a (ZC)Z
L70:    ifne L76
L73:    iconst_1
L74:    istore 6
L76:    iinc 7 1
L79:    iload 7
L81:    iflt L95
L84:    iload 7
L86:    iload_2
L87:    if_icmpge L95
L90:    iload 6
L92:    ifeq L49
L95:    iload 6
L97:    ifeq L103
L100:   iconst_0
L101:   istore 4
L103:   iload 4
L105:   ifne L111
L108:   iload_2
L109:   istore 5
L111:   aload_0
L112:   iconst_0
L113:   iload_2
L114:   invokestatic Method RKAYAFDQ b ([CII)I
L117:   istore_3
L118:   iconst_0
L119:   istore 8
L121:   iload_2
L122:   istore 9
L124:   iload 11
L126:   ifeq L147
L129:   iload 8
L131:   bipush 10
L133:   imul
L134:   aload_0
L135:   iload 9
L137:   caload
L138:   iadd
L139:   bipush 48
L141:   isub
L142:   istore 8
L144:   iinc 9 1
L147:   iload 9
L149:   iload_3
L150:   if_icmplt L129
L153:   iload 8
L155:   sipush 255
L158:   if_icmpgt L169
L161:   iload_3
L162:   iload_2
L163:   isub
L164:   bipush 8
L166:   if_icmple L177
L169:   iconst_0
L170:   istore 4
L172:   iload 11
L174:   ifeq L180
L177:   iinc 4 1
L180:   iload 4
L182:   iconst_4
L183:   if_icmpne L213
L186:   iload 5
L188:   istore 10
L190:   iload 11
L192:   ifeq L204
L195:   aload_0
L196:   iload 10
L198:   bipush 42
L200:   castore
L201:   iinc 10 1
L204:   iload 10
L206:   iload_3
L207:   if_icmplt L195
L210:   iconst_0
L211:   istore 4
L213:   aload_0
L214:   iload_3
L215:   sipush 319
L218:   invokestatic Method RKAYAFDQ a ([CII)I
L221:   dup
L222:   istore_2
L223:   iconst_m1
L224:   if_icmpne L38
L227:   return
L228:   astore_2
L229:   new java/lang/StringBuffer
L232:   dup
L233:   ldc "38921, "
L235:   invokespecial Method java/lang/StringBuffer <init> (Ljava/lang/String;)V
L238:   aload_0
L239:   invokevirtual Method java/lang/StringBuffer append ([C)Ljava/lang/StringBuffer;
L242:   ldc ", "
L244:   invokevirtual Method java/lang/StringBuffer append (Ljava/lang/String;)Ljava/lang/StringBuffer;
L247:   iload_1
L248:   invokevirtual Method java/lang/StringBuffer append (I)Ljava/lang/StringBuffer;
L251:   ldc ", "
L253:   invokevirtual Method java/lang/StringBuffer append (Ljava/lang/String;)Ljava/lang/StringBuffer;
L256:   aload_2
L257:   invokevirtual Method java/lang/Throwable toString ()Ljava/lang/String;
L260:   invokevirtual Method java/lang/StringBuffer append (Ljava/lang/String;)Ljava/lang/StringBuffer;
L263:   invokevirtual Method java/lang/StringBuffer toString ()Ljava/lang/String;
L266:   invokestatic Method sign/signlink reporterror (Ljava/lang/String;)V
L269:   new java/lang/RuntimeException
L272:   dup
L273:   invokespecial Method java/lang/RuntimeException <init> ()V
L276:   athrow
L277:   
    .end code
.end method

.method private static final a : ([CII)I
    .code stack 4 locals 4
        .catch java/lang/RuntimeException from L0 to L46 using L46
L0:     bipush 23
L2:     iload_2
L3:     idiv
L4:     istore_2
L5:     iload_1
L6:     istore_3
L7:     getstatic Field RKAYAFDQ v Z
L10:    ifeq L34
L13:    aload_0
L14:    iload_3
L15:    caload
L16:    bipush 48
L18:    if_icmplt L31
L21:    aload_0
L22:    iload_3
L23:    caload
L24:    bipush 57
L26:    if_icmpgt L31
L29:    iload_3
L30:    ireturn
L31:    iinc 3 1
L34:    iload_3
L35:    aload_0
L36:    arraylength
L37:    if_icmpge L44
L40:    iload_3
L41:    ifge L13
L44:    iconst_m1
L45:    ireturn
L46:    astore_3
L47:    new java/lang/StringBuffer
L50:    dup
L51:    ldc "27983, "
L53:    invokespecial Method java/lang/StringBuffer <init> (Ljava/lang/String;)V
L56:    aload_0
L57:    invokevirtual Method java/lang/StringBuffer append ([C)Ljava/lang/StringBuffer;
L60:    ldc ", "
L62:    invokevirtual Method java/lang/StringBuffer append (Ljava/lang/String;)Ljava/lang/StringBuffer;
L65:    iload_1
L66:    invokevirtual Method java/lang/StringBuffer append (I)Ljava/lang/StringBuffer;
L69:    ldc ", "
L71:    invokevirtual Method java/lang/StringBuffer append (Ljava/lang/String;)Ljava/lang/StringBuffer;
L74:    iload_2
L75:    invokevirtual Method java/lang/StringBuffer append (I)Ljava/lang/StringBuffer;
L78:    ldc ", "
L80:    invokevirtual Method java/lang/StringBuffer append (Ljava/lang/String;)Ljava/lang/StringBuffer;
L83:    aload_3
L84:    invokevirtual Method java/lang/Throwable toString ()Ljava/lang/String;
L87:    invokevirtual Method java/lang/StringBuffer append (Ljava/lang/String;)Ljava/lang/StringBuffer;
L90:    invokevirtual Method java/lang/StringBuffer toString ()Ljava/lang/String;
L93:    invokestatic Method sign/signlink reporterror (Ljava/lang/String;)V
L96:    new java/lang/RuntimeException
L99:    dup
L100:   invokespecial Method java/lang/RuntimeException <init> ()V
L103:   athrow
L104:   
    .end code
.end method

.method private static final b : ([CII)I
    .code stack 4 locals 4
        .catch java/lang/RuntimeException from L0 to L48 using L48
L0:     iload_2
L1:     istore_3
L2:     getstatic Field RKAYAFDQ v Z
L5:     ifeq L29
L8:     aload_0
L9:     iload_3
L10:    caload
L11:    bipush 48
L13:    if_icmplt L24
L16:    aload_0
L17:    iload_3
L18:    caload
L19:    bipush 57
L21:    if_icmple L26
L24:    iload_3
L25:    ireturn
L26:    iinc 3 1
L29:    iload_3
L30:    aload_0
L31:    arraylength
L32:    if_icmpge L39
L35:    iload_3
L36:    ifge L8
L39:    iload_1
L40:    ifeq L45
L43:    iconst_3
L44:    ireturn
L45:    aload_0
L46:    arraylength
L47:    ireturn
L48:    astore_3
L49:    new java/lang/StringBuffer
L52:    dup
L53:    ldc "1466, "
L55:    invokespecial Method java/lang/StringBuffer <init> (Ljava/lang/String;)V
L58:    aload_0
L59:    invokevirtual Method java/lang/StringBuffer append ([C)Ljava/lang/StringBuffer;
L62:    ldc ", "
L64:    invokevirtual Method java/lang/StringBuffer append (Ljava/lang/String;)Ljava/lang/StringBuffer;
L67:    iload_1
L68:    invokevirtual Method java/lang/StringBuffer append (I)Ljava/lang/StringBuffer;
L71:    ldc ", "
L73:    invokevirtual Method java/lang/StringBuffer append (Ljava/lang/String;)Ljava/lang/StringBuffer;
L76:    iload_2
L77:    invokevirtual Method java/lang/StringBuffer append (I)Ljava/lang/StringBuffer;
L80:    ldc ", "
L82:    invokevirtual Method java/lang/StringBuffer append (Ljava/lang/String;)Ljava/lang/StringBuffer;
L85:    aload_3
L86:    invokevirtual Method java/lang/Throwable toString ()Ljava/lang/String;
L89:    invokevirtual Method java/lang/StringBuffer append (Ljava/lang/String;)Ljava/lang/StringBuffer;
L92:    invokevirtual Method java/lang/StringBuffer toString ()Ljava/lang/String;
L95:    invokestatic Method sign/signlink reporterror (Ljava/lang/String;)V
L98:    new java/lang/RuntimeException
L101:   dup
L102:   invokespecial Method java/lang/RuntimeException <init> ()V
L105:   athrow
L106:   
    .end code
.end method

.method private static final a : (IC)Z
    .code stack 3 locals 3
        .catch java/lang/RuntimeException from L0 to L38 using L38
L0:     iload_0
L1:     sipush -12789
L4:     if_icmpeq L15
L7:     new java/lang/NullPointerException
L10:    dup
L11:    invokespecial Method java/lang/NullPointerException <init> ()V
L14:    athrow
L15:    iload_1
L16:    ldc -46837
L18:    invokestatic Method RKAYAFDQ c (CI)Z
L21:    ifne L34
L24:    iload_1
L25:    sipush -976
L28:    invokestatic Method RKAYAFDQ d (CI)Z
L31:    ifeq L36
L34:    iconst_0
L35:    ireturn
L36:    iconst_1
L37:    ireturn
L38:    astore_2
L39:    new java/lang/StringBuffer
L42:    dup
L43:    ldc "18641, "
L45:    invokespecial Method java/lang/StringBuffer <init> (Ljava/lang/String;)V
L48:    iload_0
L49:    invokevirtual Method java/lang/StringBuffer append (I)Ljava/lang/StringBuffer;
L52:    ldc ", "
L54:    invokevirtual Method java/lang/StringBuffer append (Ljava/lang/String;)Ljava/lang/StringBuffer;
L57:    iload_1
L58:    invokevirtual Method java/lang/StringBuffer append (C)Ljava/lang/StringBuffer;
L61:    ldc ", "
L63:    invokevirtual Method java/lang/StringBuffer append (Ljava/lang/String;)Ljava/lang/StringBuffer;
L66:    aload_2
L67:    invokevirtual Method java/lang/Throwable toString ()Ljava/lang/String;
L70:    invokevirtual Method java/lang/StringBuffer append (Ljava/lang/String;)Ljava/lang/StringBuffer;
L73:    invokevirtual Method java/lang/StringBuffer toString ()Ljava/lang/String;
L76:    invokestatic Method sign/signlink reporterror (Ljava/lang/String;)V
L79:    new java/lang/RuntimeException
L82:    dup
L83:    invokespecial Method java/lang/RuntimeException <init> ()V
L86:    athrow
L87:    
    .end code
.end method

.method private static final a : (ZC)Z
    .code stack 3 locals 3
        .catch java/lang/RuntimeException from L0 to L58 using L58
L0:     iload_0
L1:     ifeq L10
L4:     sipush -233
L7:     putstatic Field RKAYAFDQ j I
L10:    iload_1
L11:    bipush 97
L13:    if_icmplt L22
L16:    iload_1
L17:    bipush 122
L19:    if_icmple L24
L22:    iconst_1
L23:    ireturn
L24:    iload_1
L25:    bipush 118
L27:    if_icmpeq L54
L30:    iload_1
L31:    bipush 120
L33:    if_icmpeq L54
L36:    iload_1
L37:    bipush 106
L39:    if_icmpeq L54
L42:    iload_1
L43:    bipush 113
L45:    if_icmpeq L54
L48:    iload_1
L49:    bipush 122
L51:    if_icmpne L56
L54:    iconst_1
L55:    ireturn
L56:    iconst_0
L57:    ireturn
L58:    astore_2
L59:    new java/lang/StringBuffer
L62:    dup
L63:    ldc "32846, "
L65:    invokespecial Method java/lang/StringBuffer <init> (Ljava/lang/String;)V
L68:    iload_0
L69:    invokevirtual Method java/lang/StringBuffer append (Z)Ljava/lang/StringBuffer;
L72:    ldc ", "
L74:    invokevirtual Method java/lang/StringBuffer append (Ljava/lang/String;)Ljava/lang/StringBuffer;
L77:    iload_1
L78:    invokevirtual Method java/lang/StringBuffer append (C)Ljava/lang/StringBuffer;
L81:    ldc ", "
L83:    invokevirtual Method java/lang/StringBuffer append (Ljava/lang/String;)Ljava/lang/StringBuffer;
L86:    aload_2
L87:    invokevirtual Method java/lang/Throwable toString ()Ljava/lang/String;
L90:    invokevirtual Method java/lang/StringBuffer append (Ljava/lang/String;)Ljava/lang/StringBuffer;
L93:    invokevirtual Method java/lang/StringBuffer toString ()Ljava/lang/String;
L96:    invokestatic Method sign/signlink reporterror (Ljava/lang/String;)V
L99:    new java/lang/RuntimeException
L102:   dup
L103:   invokespecial Method java/lang/RuntimeException <init> ()V
L106:   athrow
L107:   
    .end code
.end method

.method private static final c : (CI)Z
    .code stack 4 locals 3
        .catch java/lang/RuntimeException from L0 to L49 using L49
L0:     iload_1
L1:     ldc -46837
L3:     if_icmpeq L21
L6:     iconst_1
L7:     istore_2
L8:     getstatic Field RKAYAFDQ v Z
L11:    ifeq L17
L14:    iinc 2 1
L17:    iload_2
L18:    ifgt L14
L21:    iload_0
L22:    bipush 97
L24:    if_icmplt L33
L27:    iload_0
L28:    bipush 122
L30:    if_icmple L47
L33:    iload_0
L34:    bipush 65
L36:    if_icmplt L45
L39:    iload_0
L40:    bipush 90
L42:    if_icmple L47
L45:    iconst_0
L46:    ireturn
L47:    iconst_1
L48:    ireturn
L49:    astore_2
L50:    new java/lang/StringBuffer
L53:    dup
L54:    ldc "61160, "
L56:    invokespecial Method java/lang/StringBuffer <init> (Ljava/lang/String;)V
L59:    iload_0
L60:    invokevirtual Method java/lang/StringBuffer append (C)Ljava/lang/StringBuffer;
L63:    ldc ", "
L65:    invokevirtual Method java/lang/StringBuffer append (Ljava/lang/String;)Ljava/lang/StringBuffer;
L68:    iload_1
L69:    invokevirtual Method java/lang/StringBuffer append (I)Ljava/lang/StringBuffer;
L72:    ldc ", "
L74:    invokevirtual Method java/lang/StringBuffer append (Ljava/lang/String;)Ljava/lang/StringBuffer;
L77:    aload_2
L78:    invokevirtual Method java/lang/Throwable toString ()Ljava/lang/String;
L81:    invokevirtual Method java/lang/StringBuffer append (Ljava/lang/String;)Ljava/lang/StringBuffer;
L84:    invokevirtual Method java/lang/StringBuffer toString ()Ljava/lang/String;
L87:    invokestatic Method sign/signlink reporterror (Ljava/lang/String;)V
L90:    new java/lang/RuntimeException
L93:    dup
L94:    invokespecial Method java/lang/RuntimeException <init> ()V
L97:    athrow
L98:    
    .end code
.end method

.method private static final d : (CI)Z
    .code stack 3 locals 3
        .catch java/lang/RuntimeException from L0 to L26 using L26
L0:     iload_1
L1:     iflt L10
L4:     sipush 254
L7:     putstatic Field RKAYAFDQ j I
L10:    iload_0
L11:    bipush 48
L13:    if_icmplt L22
L16:    iload_0
L17:    bipush 57
L19:    if_icmple L24
L22:    iconst_0
L23:    ireturn
L24:    iconst_1
L25:    ireturn
L26:    astore_2
L27:    new java/lang/StringBuffer
L30:    dup
L31:    ldc "30488, "
L33:    invokespecial Method java/lang/StringBuffer <init> (Ljava/lang/String;)V
L36:    iload_0
L37:    invokevirtual Method java/lang/StringBuffer append (C)Ljava/lang/StringBuffer;
L40:    ldc ", "
L42:    invokevirtual Method java/lang/StringBuffer append (Ljava/lang/String;)Ljava/lang/StringBuffer;
L45:    iload_1
L46:    invokevirtual Method java/lang/StringBuffer append (I)Ljava/lang/StringBuffer;
L49:    ldc ", "
L51:    invokevirtual Method java/lang/StringBuffer append (Ljava/lang/String;)Ljava/lang/StringBuffer;
L54:    aload_2
L55:    invokevirtual Method java/lang/Throwable toString ()Ljava/lang/String;
L58:    invokevirtual Method java/lang/StringBuffer append (Ljava/lang/String;)Ljava/lang/StringBuffer;
L61:    invokevirtual Method java/lang/StringBuffer toString ()Ljava/lang/String;
L64:    invokestatic Method sign/signlink reporterror (Ljava/lang/String;)V
L67:    new java/lang/RuntimeException
L70:    dup
L71:    invokespecial Method java/lang/RuntimeException <init> ()V
L74:    athrow
L75:    
    .end code
.end method

.method private static final e : (CI)Z
    .code stack 4 locals 3
        .catch java/lang/RuntimeException from L0 to L36 using L36
L0:     iload_1
L1:     iconst_1
L2:     if_icmpeq L20
L5:     iconst_1
L6:     istore_2
L7:     getstatic Field RKAYAFDQ v Z
L10:    ifeq L16
L13:    iinc 2 1
L16:    iload_2
L17:    ifgt L13
L20:    iload_0
L21:    bipush 97
L23:    if_icmplt L32
L26:    iload_0
L27:    bipush 122
L29:    if_icmple L34
L32:    iconst_0
L33:    ireturn
L34:    iconst_1
L35:    ireturn
L36:    astore_2
L37:    new java/lang/StringBuffer
L40:    dup
L41:    ldc "25533, "
L43:    invokespecial Method java/lang/StringBuffer <init> (Ljava/lang/String;)V
L46:    iload_0
L47:    invokevirtual Method java/lang/StringBuffer append (C)Ljava/lang/StringBuffer;
L50:    ldc ", "
L52:    invokevirtual Method java/lang/StringBuffer append (Ljava/lang/String;)Ljava/lang/StringBuffer;
L55:    iload_1
L56:    invokevirtual Method java/lang/StringBuffer append (I)Ljava/lang/StringBuffer;
L59:    ldc ", "
L61:    invokevirtual Method java/lang/StringBuffer append (Ljava/lang/String;)Ljava/lang/StringBuffer;
L64:    aload_2
L65:    invokevirtual Method java/lang/Throwable toString ()Ljava/lang/String;
L68:    invokevirtual Method java/lang/StringBuffer append (Ljava/lang/String;)Ljava/lang/StringBuffer;
L71:    invokevirtual Method java/lang/StringBuffer toString ()Ljava/lang/String;
L74:    invokestatic Method sign/signlink reporterror (Ljava/lang/String;)V
L77:    new java/lang/RuntimeException
L80:    dup
L81:    invokespecial Method java/lang/RuntimeException <init> ()V
L84:    athrow
L85:    
    .end code
.end method

.method private static final b : (ZC)Z
    .code stack 3 locals 3
        .catch java/lang/RuntimeException from L0 to L28 using L28
L0:     iload_0
L1:     ifne L12
L4:     new java/lang/NullPointerException
L7:     dup
L8:     invokespecial Method java/lang/NullPointerException <init> ()V
L11:    athrow
L12:    iload_1
L13:    bipush 65
L15:    if_icmplt L24
L18:    iload_1
L19:    bipush 90
L21:    if_icmple L26
L24:    iconst_0
L25:    ireturn
L26:    iconst_1
L27:    ireturn
L28:    astore_2
L29:    new java/lang/StringBuffer
L32:    dup
L33:    ldc "1272, "
L35:    invokespecial Method java/lang/StringBuffer <init> (Ljava/lang/String;)V
L38:    iload_0
L39:    invokevirtual Method java/lang/StringBuffer append (Z)Ljava/lang/StringBuffer;
L42:    ldc ", "
L44:    invokevirtual Method java/lang/StringBuffer append (Ljava/lang/String;)Ljava/lang/StringBuffer;
L47:    iload_1
L48:    invokevirtual Method java/lang/StringBuffer append (C)Ljava/lang/StringBuffer;
L51:    ldc ", "
L53:    invokevirtual Method java/lang/StringBuffer append (Ljava/lang/String;)Ljava/lang/StringBuffer;
L56:    aload_2
L57:    invokevirtual Method java/lang/Throwable toString ()Ljava/lang/String;
L60:    invokevirtual Method java/lang/StringBuffer append (Ljava/lang/String;)Ljava/lang/StringBuffer;
L63:    invokevirtual Method java/lang/StringBuffer toString ()Ljava/lang/String;
L66:    invokestatic Method sign/signlink reporterror (Ljava/lang/String;)V
L69:    new java/lang/RuntimeException
L72:    dup
L73:    invokespecial Method java/lang/RuntimeException <init> ()V
L76:    athrow
L77:    
    .end code
.end method

.method private static final a : ([CB)Z
    .code stack 4 locals 9
L0:     getstatic Field RKAYAFDQ v Z
L3:     istore 8
        .catch java/lang/RuntimeException from L5 to L179 using L179
L5:     iload_1
L6:     getstatic Field RKAYAFDQ l B
L9:     if_icmpne L19
L12:    iconst_0
L13:    istore_1
L14:    iload 8
L16:    ifeq L27
L19:    new java/lang/NullPointerException
L22:    dup
L23:    invokespecial Method java/lang/NullPointerException <init> ()V
L26:    athrow
L27:    iconst_1
L28:    istore_2
L29:    iconst_0
L30:    istore_3
L31:    iload 8
L33:    ifeq L59
L36:    aload_0
L37:    iload_3
L38:    caload
L39:    sipush -976
L42:    invokestatic Method RKAYAFDQ d (CI)Z
L45:    ifne L56
L48:    aload_0
L49:    iload_3
L50:    caload
L51:    ifeq L56
L54:    iconst_0
L55:    istore_2
L56:    iinc 3 1
L59:    iload_3
L60:    aload_0
L61:    arraylength
L62:    if_icmplt L36
L65:    iload_2
L66:    ifeq L71
L69:    iconst_1
L70:    ireturn
L71:    aload_0
L72:    sipush 8801
L75:    invokestatic Method RKAYAFDQ b ([CI)I
L78:    istore 4
L80:    iconst_0
L81:    istore 5
L83:    getstatic Field RKAYAFDQ o [I
L86:    arraylength
L87:    iconst_1
L88:    isub
L89:    istore 6
L91:    iload 4
L93:    getstatic Field RKAYAFDQ o [I
L96:    iload 5
L98:    iaload
L99:    if_icmpeq L113
L102:   iload 4
L104:   getstatic Field RKAYAFDQ o [I
L107:   iload 6
L109:   iaload
L110:   if_icmpne L115
L113:   iconst_1
L114:   ireturn
L115:   iload 5
L117:   iload 6
L119:   iadd
L120:   iconst_2
L121:   idiv
L122:   istore 7
L124:   iload 4
L126:   getstatic Field RKAYAFDQ o [I
L129:   iload 7
L131:   iaload
L132:   if_icmpne L137
L135:   iconst_1
L136:   ireturn
L137:   iload 4
L139:   getstatic Field RKAYAFDQ o [I
L142:   iload 7
L144:   iaload
L145:   if_icmpge L157
L148:   iload 7
L150:   istore 6
L152:   iload 8
L154:   ifeq L161
L157:   iload 7
L159:   istore 5
L161:   iload 5
L163:   iload 6
L165:   if_icmpeq L177
L168:   iload 5
L170:   iconst_1
L171:   iadd
L172:   iload 6
L174:   if_icmpne L115
L177:   iconst_0
L178:   ireturn
L179:   astore_2
L180:   new java/lang/StringBuffer
L183:   dup
L184:   ldc "62482, "
L186:   invokespecial Method java/lang/StringBuffer <init> (Ljava/lang/String;)V
L189:   aload_0
L190:   invokevirtual Method java/lang/StringBuffer append ([C)Ljava/lang/StringBuffer;
L193:   ldc ", "
L195:   invokevirtual Method java/lang/StringBuffer append (Ljava/lang/String;)Ljava/lang/StringBuffer;
L198:   iload_1
L199:   invokevirtual Method java/lang/StringBuffer append (I)Ljava/lang/StringBuffer;
L202:   ldc ", "
L204:   invokevirtual Method java/lang/StringBuffer append (Ljava/lang/String;)Ljava/lang/StringBuffer;
L207:   aload_2
L208:   invokevirtual Method java/lang/Throwable toString ()Ljava/lang/String;
L211:   invokevirtual Method java/lang/StringBuffer append (Ljava/lang/String;)Ljava/lang/StringBuffer;
L214:   invokevirtual Method java/lang/StringBuffer toString ()Ljava/lang/String;
L217:   invokestatic Method sign/signlink reporterror (Ljava/lang/String;)V
L220:   new java/lang/RuntimeException
L223:   dup
L224:   invokespecial Method java/lang/RuntimeException <init> ()V
L227:   athrow
L228:   
    .end code
.end method

.method public static final b : ([CI)I
    .code stack 4 locals 6
L0:     getstatic Field RKAYAFDQ v Z
L3:     istore 5
        .catch java/lang/RuntimeException from L5 to L157 using L157
L5:     iload_1
L6:     getstatic Field RKAYAFDQ m I
L9:     if_icmpeq L26
L12:    iconst_1
L13:    istore_2
L14:    iload 5
L16:    ifeq L22
L19:    iinc 2 1
L22:    iload_2
L23:    ifgt L19
L26:    aload_0
L27:    arraylength
L28:    bipush 6
L30:    if_icmple L35
L33:    iconst_0
L34:    ireturn
L35:    iconst_0
L36:    istore_2
L37:    iconst_0
L38:    istore_3
L39:    iload 5
L41:    ifeq L149
L44:    aload_0
L45:    aload_0
L46:    arraylength
L47:    iload_3
L48:    isub
L49:    iconst_1
L50:    isub
L51:    caload
L52:    istore 4
L54:    iload 4
L56:    bipush 97
L58:    if_icmplt L86
L61:    iload 4
L63:    bipush 122
L65:    if_icmpgt L86
L68:    iload_2
L69:    bipush 38
L71:    imul
L72:    iload 4
L74:    bipush 97
L76:    isub
L77:    iconst_1
L78:    iadd
L79:    iadd
L80:    istore_2
L81:    iload 5
L83:    ifeq L146
L86:    iload 4
L88:    bipush 39
L90:    if_icmpne L106
L93:    iload_2
L94:    bipush 38
L96:    imul
L97:    bipush 27
L99:    iadd
L100:   istore_2
L101:   iload 5
L103:   ifeq L146
L106:   iload 4
L108:   bipush 48
L110:   if_icmplt L139
L113:   iload 4
L115:   bipush 57
L117:   if_icmpgt L139
L120:   iload_2
L121:   bipush 38
L123:   imul
L124:   iload 4
L126:   bipush 48
L128:   isub
L129:   bipush 28
L131:   iadd
L132:   iadd
L133:   istore_2
L134:   iload 5
L136:   ifeq L146
L139:   iload 4
L141:   ifeq L146
L144:   iconst_0
L145:   ireturn
L146:   iinc 3 1
L149:   iload_3
L150:   aload_0
L151:   arraylength
L152:   if_icmplt L44
L155:   iload_2
L156:   ireturn
L157:   astore_2
L158:   new java/lang/StringBuffer
L161:   dup
L162:   ldc "67682, "
L164:   invokespecial Method java/lang/StringBuffer <init> (Ljava/lang/String;)V
L167:   aload_0
L168:   invokevirtual Method java/lang/StringBuffer append ([C)Ljava/lang/StringBuffer;
L171:   ldc ", "
L173:   invokevirtual Method java/lang/StringBuffer append (Ljava/lang/String;)Ljava/lang/StringBuffer;
L176:   iload_1
L177:   invokevirtual Method java/lang/StringBuffer append (I)Ljava/lang/StringBuffer;
L180:   ldc ", "
L182:   invokevirtual Method java/lang/StringBuffer append (Ljava/lang/String;)Ljava/lang/StringBuffer;
L185:   aload_2
L186:   invokevirtual Method java/lang/Throwable toString ()Ljava/lang/String;
L189:   invokevirtual Method java/lang/StringBuffer append (Ljava/lang/String;)Ljava/lang/StringBuffer;
L192:   invokevirtual Method java/lang/StringBuffer toString ()Ljava/lang/String;
L195:   invokestatic Method sign/signlink reporterror (Ljava/lang/String;)V
L198:   new java/lang/RuntimeException
L201:   dup
L202:   invokespecial Method java/lang/RuntimeException <init> ()V
L205:   athrow
L206:   
    .end code
.end method

.method static <clinit> : ()V
    .code stack 4 locals 0
L0:     bipush 9
L2:     putstatic Field RKAYAFDQ a I
L5:     sipush 748
L8:     putstatic Field RKAYAFDQ c I
L11:    sipush 201
L14:    putstatic Field RKAYAFDQ d I
L17:    iconst_1
L18:    putstatic Field RKAYAFDQ e Z
L21:    bipush -117
L23:    putstatic Field RKAYAFDQ g B
L26:    sipush -575
L29:    putstatic Field RKAYAFDQ h I
L32:    iconst_1
L33:    putstatic Field RKAYAFDQ i Z
L36:    sipush -720
L39:    putstatic Field RKAYAFDQ j I
L42:    sipush -511
L45:    putstatic Field RKAYAFDQ k I
L48:    iconst_4
L49:    putstatic Field RKAYAFDQ l B
L52:    sipush 8801
L55:    putstatic Field RKAYAFDQ m I
L58:    iconst_1
L59:    putstatic Field RKAYAFDQ n Z
L62:    bipush 10
L64:    anewarray java/lang/String
L67:    dup
L68:    iconst_0
L69:    ldc "cook"
L71:    aastore
L72:    dup
L73:    iconst_1
L74:    ldc "cook's"
L76:    aastore
L77:    dup
L78:    iconst_2
L79:    ldc "cooks"
L81:    aastore
L82:    dup
L83:    iconst_3
L84:    ldc "seeks"
L86:    aastore
L87:    dup
L88:    iconst_4
L89:    ldc "sheet"
L91:    aastore
L92:    dup
L93:    iconst_5
L94:    ldc "woop"
L96:    aastore
L97:    dup
L98:    bipush 6
L100:   ldc "woops"
L102:   aastore
L103:   dup
L104:   bipush 7
L106:   ldc "faq"
L108:   aastore
L109:   dup
L110:   bipush 8
L112:   ldc "noob"
L114:   aastore
L115:   dup
L116:   bipush 9
L118:   ldc "noobs"
L120:   aastore
L121:   putstatic Field RKAYAFDQ u [Ljava/lang/String;
L124:   return
L125:   
    .end code
.end method
.end class
