.version 45 3
.class public super ZKARKDQW
.super XHHRODPC
.field private m I
.field private n Z
.field private o I
.field private p I
.field private q Z
.field private static r I
.field public static s I
.field public static t LZKARKDQW;
.field private static u [I
.field private static v [I
.field private static w [I
.field private static x [I
.field public y I
.field public z [I
.field public A [I
.field public B [I
.field public C I
.field public D [I
.field public E [I
.field public F [I
.field public G [I
.field public H [I
.field public I [I
.field public J [I
.field public K [I
.field public L [I
.field public M [I
.field public N I
.field public O I
.field public P [I
.field public Q [I
.field public R [I
.field public S I
.field public T I
.field public U I
.field public V I
.field public W I
.field public X I
.field public Y I
.field public Z I
.field public ab I
.field public bb [I
.field public cb [I
.field public db [[I
.field public eb [[I
.field public fb Z
.field gb [LRJXWGZGD;
.field static hb [LLLORVYLP;
.field static ib LVJKFYAWG;
.field static jb [Z
.field static kb [Z
.field static lb [I
.field static mb [I
.field static nb [I
.field static ob [I
.field static pb [I
.field static qb [I
.field static rb [I
.field static sb [[I
.field static tb [I
.field static ub [[I
.field static vb [I
.field static wb [I
.field static xb [I
.field static yb [I
.field static zb [I
.field static Ab [I
.field static Bb I
.field static Cb I
.field static Db I
.field public static Eb Z
.field public static Fb I
.field public static Gb I
.field public static Hb I
.field public static Ib [I
.field public static Jb [I
.field public static Kb [I
.field static Lb [I
.field static Mb [I

.method public static b : (I)V
    .code stack 4 locals 2
        .catch java/lang/RuntimeException from L0 to L91 using L92
L0:     aconst_null
L1:     putstatic Field ZKARKDQW hb [LLLORVYLP;
L4:     aconst_null
L5:     putstatic Field ZKARKDQW jb [Z
L8:     aconst_null
L9:     putstatic Field ZKARKDQW kb [Z
L12:    aconst_null
L13:    putstatic Field ZKARKDQW lb [I
L16:    getstatic Field XHHRODPC l Z
L19:    ifeq L23
L22:    return
L23:    iload_0
L24:    ifge L22
L27:    aconst_null
L28:    putstatic Field ZKARKDQW mb [I
L31:    aconst_null
L32:    putstatic Field ZKARKDQW nb [I
L35:    aconst_null
L36:    putstatic Field ZKARKDQW ob [I
L39:    aconst_null
L40:    putstatic Field ZKARKDQW pb [I
L43:    aconst_null
L44:    putstatic Field ZKARKDQW qb [I
L47:    aconst_null
L48:    putstatic Field ZKARKDQW rb [I
L51:    aconst_null
L52:    putstatic Field ZKARKDQW sb [[I
L55:    aconst_null
L56:    putstatic Field ZKARKDQW tb [I
L59:    aconst_null
L60:    putstatic Field ZKARKDQW ub [[I
L63:    aconst_null
L64:    putstatic Field ZKARKDQW vb [I
L67:    aconst_null
L68:    putstatic Field ZKARKDQW wb [I
L71:    aconst_null
L72:    putstatic Field ZKARKDQW xb [I
L75:    aconst_null
L76:    putstatic Field ZKARKDQW Jb [I
L79:    aconst_null
L80:    putstatic Field ZKARKDQW Kb [I
L83:    aconst_null
L84:    putstatic Field ZKARKDQW Lb [I
L87:    aconst_null
L88:    putstatic Field ZKARKDQW Mb [I
L91:    return
L92:    astore_1
L93:    new java/lang/StringBuffer
L96:    dup
L97:    ldc "30970, "
L99:    invokespecial Method java/lang/StringBuffer <init> (Ljava/lang/String;)V
L102:   iload_0
L103:   invokevirtual Method java/lang/StringBuffer append (I)Ljava/lang/StringBuffer;
L106:   ldc ", "
L108:   invokevirtual Method java/lang/StringBuffer append (Ljava/lang/String;)Ljava/lang/StringBuffer;
L111:   aload_1
L112:   invokevirtual Method java/lang/Throwable toString ()Ljava/lang/String;
L115:   invokevirtual Method java/lang/StringBuffer append (Ljava/lang/String;)Ljava/lang/StringBuffer;
L118:   invokevirtual Method java/lang/StringBuffer toString ()Ljava/lang/String;
L121:   invokestatic Method sign/signlink reporterror (Ljava/lang/String;)V
L124:   new java/lang/RuntimeException
L127:   dup
L128:   invokespecial Method java/lang/RuntimeException <init> ()V
L131:   athrow
L132:   
    .end code
.end method

.method public static a : (ILVJKFYAWG;)V
    .code stack 1 locals 2
L0:     iload_0
L1:     anewarray LLORVYLP
L4:     putstatic Field ZKARKDQW hb [LLLORVYLP;
L7:     aload_1
L8:     putstatic Field ZKARKDQW ib LVJKFYAWG;
L11:    return
L12:    
    .end code
.end method

.method public static a : ([BII)V
    .code stack 5 locals 16
L0:     getstatic Field XHHRODPC l Z
L3:     istore 15
        .catch java/lang/RuntimeException from L5 to L478 using L479
L5:     aload_0
L6:     ifnonnull L39
L9:     getstatic Field ZKARKDQW hb [LLLORVYLP;
L12:    iload_2
L13:    new LLORVYLP
L16:    dup
L17:    invokespecial Method LLORVYLP <init> ()V
L20:    dup_x2
L21:    aastore
L22:    astore_3
L23:    aload_3
L24:    iconst_0
L25:    putfield Field LLORVYLP b I
L28:    aload_3
L29:    iconst_0
L30:    putfield Field LLORVYLP c I
L33:    aload_3
L34:    iconst_0
L35:    putfield Field LLORVYLP d I
L38:    return
L39:    new MBMGIXGO
L42:    dup
L43:    aload_0
L44:    sipush 891
L47:    invokespecial Method MBMGIXGO <init> ([BI)V
L50:    astore_3
L51:    aload_3
L52:    aload_0
L53:    arraylength
L54:    bipush 18
L56:    isub
L57:    putfield Field MBMGIXGO z I
L60:    getstatic Field ZKARKDQW hb [LLLORVYLP;
L63:    iload_2
L64:    new LLORVYLP
L67:    dup
L68:    invokespecial Method LLORVYLP <init> ()V
L71:    dup_x2
L72:    aastore
L73:    astore 4
L75:    aload 4
L77:    aload_0
L78:    putfield Field LLORVYLP a [B
L81:    aload 4
L83:    aload_3
L84:    invokevirtual Method MBMGIXGO e ()I
L87:    putfield Field LLORVYLP b I
L90:    aload 4
L92:    aload_3
L93:    invokevirtual Method MBMGIXGO e ()I
L96:    putfield Field LLORVYLP c I
L99:    aload 4
L101:   aload_3
L102:   invokevirtual Method MBMGIXGO c ()I
L105:   putfield Field LLORVYLP d I
L108:   aload_3
L109:   invokevirtual Method MBMGIXGO c ()I
L112:   istore 5
L114:   aload_3
L115:   invokevirtual Method MBMGIXGO c ()I
L118:   istore 6
L120:   iload_1
L121:   sipush -4036
L124:   if_icmpeq L128
L127:   return
L128:   aload_3
L129:   invokevirtual Method MBMGIXGO c ()I
L132:   istore 7
L134:   aload_3
L135:   invokevirtual Method MBMGIXGO c ()I
L138:   istore 8
L140:   aload_3
L141:   invokevirtual Method MBMGIXGO c ()I
L144:   istore 9
L146:   aload_3
L147:   invokevirtual Method MBMGIXGO e ()I
L150:   istore 10
L152:   aload_3
L153:   invokevirtual Method MBMGIXGO e ()I
L156:   istore 11
L158:   aload_3
L159:   invokevirtual Method MBMGIXGO e ()I
L162:   istore 12
L164:   aload_3
L165:   invokevirtual Method MBMGIXGO e ()I
L168:   istore 13
L170:   iconst_0
L171:   istore 14
L173:   aload 4
L175:   iload 14
L177:   putfield Field LLORVYLP e I
L180:   iload 14
L182:   aload 4
L184:   getfield Field LLORVYLP b I
L187:   iadd
L188:   istore 14
L190:   aload 4
L192:   iload 14
L194:   putfield Field LLORVYLP k I
L197:   iload 14
L199:   aload 4
L201:   getfield Field LLORVYLP c I
L204:   iadd
L205:   istore 14
L207:   aload 4
L209:   iload 14
L211:   putfield Field LLORVYLP n I
L214:   iload 6
L216:   sipush 255
L219:   if_icmpne L237
L222:   iload 14
L224:   aload 4
L226:   getfield Field LLORVYLP c I
L229:   iadd
L230:   istore 14
L232:   iload 15
L234:   ifeq L247
L237:   aload 4
L239:   iload 6
L241:   ineg
L242:   iconst_1
L243:   isub
L244:   putfield Field LLORVYLP n I
L247:   aload 4
L249:   iload 14
L251:   putfield Field LLORVYLP p I
L254:   iload 8
L256:   iconst_1
L257:   if_icmpne L275
L260:   iload 14
L262:   aload 4
L264:   getfield Field LLORVYLP c I
L267:   iadd
L268:   istore 14
L270:   iload 15
L272:   ifeq L281
L275:   aload 4
L277:   iconst_m1
L278:   putfield Field LLORVYLP p I
L281:   aload 4
L283:   iload 14
L285:   putfield Field LLORVYLP m I
L288:   iload 5
L290:   iconst_1
L291:   if_icmpne L309
L294:   iload 14
L296:   aload 4
L298:   getfield Field LLORVYLP c I
L301:   iadd
L302:   istore 14
L304:   iload 15
L306:   ifeq L315
L309:   aload 4
L311:   iconst_m1
L312:   putfield Field LLORVYLP m I
L315:   aload 4
L317:   iload 14
L319:   putfield Field LLORVYLP i I
L322:   iload 9
L324:   iconst_1
L325:   if_icmpne L343
L328:   iload 14
L330:   aload 4
L332:   getfield Field LLORVYLP b I
L335:   iadd
L336:   istore 14
L338:   iload 15
L340:   ifeq L349
L343:   aload 4
L345:   iconst_m1
L346:   putfield Field LLORVYLP i I
L349:   aload 4
L351:   iload 14
L353:   putfield Field LLORVYLP o I
L356:   iload 7
L358:   iconst_1
L359:   if_icmpne L377
L362:   iload 14
L364:   aload 4
L366:   getfield Field LLORVYLP c I
L369:   iadd
L370:   istore 14
L372:   iload 15
L374:   ifeq L383
L377:   aload 4
L379:   iconst_m1
L380:   putfield Field LLORVYLP o I
L383:   aload 4
L385:   iload 14
L387:   putfield Field LLORVYLP j I
L390:   iload 14
L392:   iload 13
L394:   iadd
L395:   istore 14
L397:   aload 4
L399:   iload 14
L401:   putfield Field LLORVYLP l I
L404:   iload 14
L406:   aload 4
L408:   getfield Field LLORVYLP c I
L411:   iconst_2
L412:   imul
L413:   iadd
L414:   istore 14
L416:   aload 4
L418:   iload 14
L420:   putfield Field LLORVYLP q I
L423:   iload 14
L425:   aload 4
L427:   getfield Field LLORVYLP d I
L430:   bipush 6
L432:   imul
L433:   iadd
L434:   istore 14
L436:   aload 4
L438:   iload 14
L440:   putfield Field LLORVYLP f I
L443:   iload 14
L445:   iload 10
L447:   iadd
L448:   istore 14
L450:   aload 4
L452:   iload 14
L454:   putfield Field LLORVYLP g I
L457:   iload 14
L459:   iload 11
L461:   iadd
L462:   istore 14
L464:   aload 4
L466:   iload 14
L468:   putfield Field LLORVYLP h I
L471:   iload 14
L473:   iload 12
L475:   iadd
L476:   istore 14
L478:   return
L479:   astore_3
L480:   new java/lang/StringBuffer
L483:   dup
L484:   ldc "43492, "
L486:   invokespecial Method java/lang/StringBuffer <init> (Ljava/lang/String;)V
L489:   aload_0
L490:   invokevirtual Method java/lang/StringBuffer append (Ljava/lang/Object;)Ljava/lang/StringBuffer;
L493:   ldc ", "
L495:   invokevirtual Method java/lang/StringBuffer append (Ljava/lang/String;)Ljava/lang/StringBuffer;
L498:   iload_1
L499:   invokevirtual Method java/lang/StringBuffer append (I)Ljava/lang/StringBuffer;
L502:   ldc ", "
L504:   invokevirtual Method java/lang/StringBuffer append (Ljava/lang/String;)Ljava/lang/StringBuffer;
L507:   iload_2
L508:   invokevirtual Method java/lang/StringBuffer append (I)Ljava/lang/StringBuffer;
L511:   ldc ", "
L513:   invokevirtual Method java/lang/StringBuffer append (Ljava/lang/String;)Ljava/lang/StringBuffer;
L516:   aload_3
L517:   invokevirtual Method java/lang/Throwable toString ()Ljava/lang/String;
L520:   invokevirtual Method java/lang/StringBuffer append (Ljava/lang/String;)Ljava/lang/StringBuffer;
L523:   invokevirtual Method java/lang/StringBuffer toString ()Ljava/lang/String;
L526:   invokestatic Method sign/signlink reporterror (Ljava/lang/String;)V
L529:   new java/lang/RuntimeException
L532:   dup
L533:   invokespecial Method java/lang/RuntimeException <init> ()V
L536:   athrow
L537:   
    .end code
.end method

.method public static a : (II)V
    .code stack 3 locals 3
        .catch java/lang/RuntimeException from L0 to L16 using L17
L0:     getstatic Field ZKARKDQW hb [LLLORVYLP;
L3:     iload_1
L4:     aconst_null
L5:     aastore
L6:     iload_0
L7:     ifgt L66
L10:    sipush -219
L13:    putstatic Field ZKARKDQW r I
L16:    return
L17:    astore_2
L18:    new java/lang/StringBuffer
L21:    dup
L22:    ldc "72035, "
L24:    invokespecial Method java/lang/StringBuffer <init> (Ljava/lang/String;)V
L27:    iload_0
L28:    invokevirtual Method java/lang/StringBuffer append (I)Ljava/lang/StringBuffer;
L31:    ldc ", "
L33:    invokevirtual Method java/lang/StringBuffer append (Ljava/lang/String;)Ljava/lang/StringBuffer;
L36:    iload_1
L37:    invokevirtual Method java/lang/StringBuffer append (I)Ljava/lang/StringBuffer;
L40:    ldc ", "
L42:    invokevirtual Method java/lang/StringBuffer append (Ljava/lang/String;)Ljava/lang/StringBuffer;
L45:    aload_2
L46:    invokevirtual Method java/lang/Throwable toString ()Ljava/lang/String;
L49:    invokevirtual Method java/lang/StringBuffer append (Ljava/lang/String;)Ljava/lang/StringBuffer;
L52:    invokevirtual Method java/lang/StringBuffer toString ()Ljava/lang/String;
L55:    invokestatic Method sign/signlink reporterror (Ljava/lang/String;)V
L58:    new java/lang/RuntimeException
L61:    dup
L62:    invokespecial Method java/lang/RuntimeException <init> ()V
L65:    athrow
L66:    return
L67:    
    .end code
.end method

.method public static b : (II)LZKARKDQW;
    .code stack 5 locals 4
        .catch java/lang/RuntimeException from L0 to L60 using L60
L0:     getstatic Field ZKARKDQW hb [LLLORVYLP;
L3:     ifnonnull L8
L6:     aconst_null
L7:     areturn
L8:     getstatic Field ZKARKDQW hb [LLLORVYLP;
L11:    iload_1
L12:    aaload
L13:    astore_2
L14:    iload_0
L15:    bipush 9
L17:    if_icmpeq L35
L20:    iconst_1
L21:    istore_3
L22:    getstatic Field XHHRODPC l Z
L25:    ifeq L31
L28:    iinc 3 1
L31:    iload_3
L32:    ifgt L28
L35:    aload_2
L36:    ifnonnull L48
L39:    getstatic Field ZKARKDQW ib LVJKFYAWG;
L42:    iload_1
L43:    invokevirtual Method VJKFYAWG a (I)V
L46:    aconst_null
L47:    areturn
L48:    new ZKARKDQW
L51:    dup
L52:    iload_1
L53:    sipush -870
L56:    invokespecial Method ZKARKDQW <init> (II)V
L59:    areturn
L60:    astore_2
L61:    new java/lang/StringBuffer
L64:    dup
L65:    ldc "30916, "
L67:    invokespecial Method java/lang/StringBuffer <init> (Ljava/lang/String;)V
L70:    iload_0
L71:    invokevirtual Method java/lang/StringBuffer append (I)Ljava/lang/StringBuffer;
L74:    ldc ", "
L76:    invokevirtual Method java/lang/StringBuffer append (Ljava/lang/String;)Ljava/lang/StringBuffer;
L79:    iload_1
L80:    invokevirtual Method java/lang/StringBuffer append (I)Ljava/lang/StringBuffer;
L83:    ldc ", "
L85:    invokevirtual Method java/lang/StringBuffer append (Ljava/lang/String;)Ljava/lang/StringBuffer;
L88:    aload_2
L89:    invokevirtual Method java/lang/Throwable toString ()Ljava/lang/String;
L92:    invokevirtual Method java/lang/StringBuffer append (Ljava/lang/String;)Ljava/lang/StringBuffer;
L95:    invokevirtual Method java/lang/StringBuffer toString ()Ljava/lang/String;
L98:    invokestatic Method sign/signlink reporterror (Ljava/lang/String;)V
L101:   new java/lang/RuntimeException
L104:   dup
L105:   invokespecial Method java/lang/RuntimeException <init> ()V
L108:   athrow
L109:   
    .end code
.end method

.method public static c : (I)Z
    .code stack 2 locals 2
L0:     getstatic Field ZKARKDQW hb [LLLORVYLP;
L3:     ifnonnull L8
L6:     iconst_0
L7:     ireturn
L8:     getstatic Field ZKARKDQW hb [LLLORVYLP;
L11:    iload_0
L12:    aaload
L13:    astore_1
L14:    aload_1
L15:    ifnonnull L27
L18:    getstatic Field ZKARKDQW ib LVJKFYAWG;
L21:    iload_0
L22:    invokevirtual Method VJKFYAWG a (I)V
L25:    iconst_0
L26:    ireturn
L27:    iconst_1
L28:    ireturn
L29:    
    .end code
.end method

.method private <init> : (Z)V
    .code stack 3 locals 3
L0:     aload_0
L1:     invokespecial Method XHHRODPC <init> ()V
L4:     aload_0
L5:     bipush 9
L7:     putfield Field ZKARKDQW m I
L10:    aload_0
L11:    iconst_0
L12:    putfield Field ZKARKDQW n Z
L15:    aload_0
L16:    sipush 360
L19:    putfield Field ZKARKDQW o I
L22:    aload_0
L23:    iconst_1
L24:    putfield Field ZKARKDQW p I
L27:    aload_0
L28:    iconst_1
L29:    putfield Field ZKARKDQW q Z
L32:    aload_0
L33:    iconst_0
L34:    putfield Field ZKARKDQW fb Z
        .catch java/lang/RuntimeException from L37 to L57 using L58
L37:    iload_1
L38:    ifne L98
L41:    aload_0
L42:    aload_0
L43:    getfield Field ZKARKDQW q Z
L46:    ifeq L53
L49:    iconst_0
L50:    goto L54
L53:    iconst_1
L54:    putfield Field ZKARKDQW q Z
L57:    return
L58:    astore_2
L59:    new java/lang/StringBuffer
L62:    dup
L63:    ldc "59290, "
L65:    invokespecial Method java/lang/StringBuffer <init> (Ljava/lang/String;)V
L68:    iload_1
L69:    invokevirtual Method java/lang/StringBuffer append (Z)Ljava/lang/StringBuffer;
L72:    ldc ", "
L74:    invokevirtual Method java/lang/StringBuffer append (Ljava/lang/String;)Ljava/lang/StringBuffer;
L77:    aload_2
L78:    invokevirtual Method java/lang/Throwable toString ()Ljava/lang/String;
L81:    invokevirtual Method java/lang/StringBuffer append (Ljava/lang/String;)Ljava/lang/StringBuffer;
L84:    invokevirtual Method java/lang/StringBuffer toString ()Ljava/lang/String;
L87:    invokestatic Method sign/signlink reporterror (Ljava/lang/String;)V
L90:    new java/lang/RuntimeException
L93:    dup
L94:    invokespecial Method java/lang/RuntimeException <init> ()V
L97:    athrow
L98:    return
L99:    
    .end code
.end method

.method private <init> : (II)V
    .code stack 5 locals 22
L0:     getstatic Field XHHRODPC l Z
L3:     istore 21
L5:     aload_0
L6:     invokespecial Method XHHRODPC <init> ()V
L9:     aload_0
L10:    bipush 9
L12:    putfield Field ZKARKDQW m I
L15:    aload_0
L16:    iconst_0
L17:    putfield Field ZKARKDQW n Z
L20:    aload_0
L21:    sipush 360
L24:    putfield Field ZKARKDQW o I
L27:    aload_0
L28:    iconst_1
L29:    putfield Field ZKARKDQW p I
L32:    aload_0
L33:    iconst_1
L34:    putfield Field ZKARKDQW q Z
L37:    aload_0
L38:    iconst_0
L39:    putfield Field ZKARKDQW fb Z
        .catch java/lang/RuntimeException from L42 to L1119 using L1120
L42:    getstatic Field ZKARKDQW s I
L45:    iconst_1
L46:    iadd
L47:    putstatic Field ZKARKDQW s I
L50:    getstatic Field ZKARKDQW hb [LLLORVYLP;
L53:    iload_1
L54:    aaload
L55:    astore_3
L56:    aload_0
L57:    aload_3
L58:    getfield Field LLORVYLP b I
L61:    putfield Field ZKARKDQW y I
L64:    aload_0
L65:    aload_3
L66:    getfield Field LLORVYLP c I
L69:    putfield Field ZKARKDQW C I
L72:    aload_0
L73:    aload_3
L74:    getfield Field LLORVYLP d I
L77:    putfield Field ZKARKDQW O I
L80:    aload_0
L81:    aload_0
L82:    getfield Field ZKARKDQW y I
L85:    newarray int
L87:    putfield Field ZKARKDQW z [I
L90:    aload_0
L91:    aload_0
L92:    getfield Field ZKARKDQW y I
L95:    newarray int
L97:    putfield Field ZKARKDQW A [I
L100:   aload_0
L101:   aload_0
L102:   getfield Field ZKARKDQW y I
L105:   newarray int
L107:   putfield Field ZKARKDQW B [I
L110:   aload_0
L111:   aload_0
L112:   getfield Field ZKARKDQW C I
L115:   newarray int
L117:   putfield Field ZKARKDQW D [I
L120:   aload_0
L121:   aload_0
L122:   getfield Field ZKARKDQW C I
L125:   newarray int
L127:   putfield Field ZKARKDQW E [I
L130:   iload 21
L132:   ifeq L151
L135:   aload_0
L136:   aload_0
L137:   getfield Field ZKARKDQW q Z
L140:   ifeq L147
L143:   iconst_0
L144:   goto L148
L147:   iconst_1
L148:   putfield Field ZKARKDQW q Z
L151:   iload_2
L152:   ifge L135
L155:   aload_0
L156:   aload_0
L157:   getfield Field ZKARKDQW C I
L160:   newarray int
L162:   putfield Field ZKARKDQW F [I
L165:   aload_0
L166:   aload_0
L167:   getfield Field ZKARKDQW O I
L170:   newarray int
L172:   putfield Field ZKARKDQW P [I
L175:   aload_0
L176:   aload_0
L177:   getfield Field ZKARKDQW O I
L180:   newarray int
L182:   putfield Field ZKARKDQW Q [I
L185:   aload_0
L186:   aload_0
L187:   getfield Field ZKARKDQW O I
L190:   newarray int
L192:   putfield Field ZKARKDQW R [I
L195:   aload_3
L196:   getfield Field LLORVYLP i I
L199:   iflt L212
L202:   aload_0
L203:   aload_0
L204:   getfield Field ZKARKDQW y I
L207:   newarray int
L209:   putfield Field ZKARKDQW bb [I
L212:   aload_3
L213:   getfield Field LLORVYLP m I
L216:   iflt L229
L219:   aload_0
L220:   aload_0
L221:   getfield Field ZKARKDQW C I
L224:   newarray int
L226:   putfield Field ZKARKDQW J [I
L229:   aload_3
L230:   getfield Field LLORVYLP n I
L233:   iflt L251
L236:   aload_0
L237:   aload_0
L238:   getfield Field ZKARKDQW C I
L241:   newarray int
L243:   putfield Field ZKARKDQW K [I
L246:   iload 21
L248:   ifeq L262
L251:   aload_0
L252:   aload_3
L253:   getfield Field LLORVYLP n I
L256:   ineg
L257:   iconst_1
L258:   isub
L259:   putfield Field ZKARKDQW N I
L262:   aload_3
L263:   getfield Field LLORVYLP o I
L266:   iflt L279
L269:   aload_0
L270:   aload_0
L271:   getfield Field ZKARKDQW C I
L274:   newarray int
L276:   putfield Field ZKARKDQW L [I
L279:   aload_3
L280:   getfield Field LLORVYLP p I
L283:   iflt L296
L286:   aload_0
L287:   aload_0
L288:   getfield Field ZKARKDQW C I
L291:   newarray int
L293:   putfield Field ZKARKDQW cb [I
L296:   aload_0
L297:   aload_0
L298:   getfield Field ZKARKDQW C I
L301:   newarray int
L303:   putfield Field ZKARKDQW M [I
L306:   new MBMGIXGO
L309:   dup
L310:   aload_3
L311:   getfield Field LLORVYLP a [B
L314:   sipush 891
L317:   invokespecial Method MBMGIXGO <init> ([BI)V
L320:   astore 4
L322:   aload 4
L324:   aload_3
L325:   getfield Field LLORVYLP e I
L328:   putfield Field MBMGIXGO z I
L331:   new MBMGIXGO
L334:   dup
L335:   aload_3
L336:   getfield Field LLORVYLP a [B
L339:   sipush 891
L342:   invokespecial Method MBMGIXGO <init> ([BI)V
L345:   astore 5
L347:   aload 5
L349:   aload_3
L350:   getfield Field LLORVYLP f I
L353:   putfield Field MBMGIXGO z I
L356:   new MBMGIXGO
L359:   dup
L360:   aload_3
L361:   getfield Field LLORVYLP a [B
L364:   sipush 891
L367:   invokespecial Method MBMGIXGO <init> ([BI)V
L370:   astore 6
L372:   aload 6
L374:   aload_3
L375:   getfield Field LLORVYLP g I
L378:   putfield Field MBMGIXGO z I
L381:   new MBMGIXGO
L384:   dup
L385:   aload_3
L386:   getfield Field LLORVYLP a [B
L389:   sipush 891
L392:   invokespecial Method MBMGIXGO <init> ([BI)V
L395:   astore 7
L397:   aload 7
L399:   aload_3
L400:   getfield Field LLORVYLP h I
L403:   putfield Field MBMGIXGO z I
L406:   new MBMGIXGO
L409:   dup
L410:   aload_3
L411:   getfield Field LLORVYLP a [B
L414:   sipush 891
L417:   invokespecial Method MBMGIXGO <init> ([BI)V
L420:   astore 8
L422:   aload 8
L424:   aload_3
L425:   getfield Field LLORVYLP i I
L428:   putfield Field MBMGIXGO z I
L431:   iconst_0
L432:   istore 9
L434:   iconst_0
L435:   istore 10
L437:   iconst_0
L438:   istore 11
L440:   iconst_0
L441:   istore 12
L443:   iload 21
L445:   ifeq L591
L448:   aload 4
L450:   invokevirtual Method MBMGIXGO c ()I
L453:   istore 13
L455:   iconst_0
L456:   istore 14
L458:   iload 13
L460:   iconst_1
L461:   iand
L462:   ifeq L472
L465:   aload 5
L467:   invokevirtual Method MBMGIXGO j ()I
L470:   istore 14
L472:   iconst_0
L473:   istore 15
L475:   iload 13
L477:   iconst_2
L478:   iand
L479:   ifeq L489
L482:   aload 6
L484:   invokevirtual Method MBMGIXGO j ()I
L487:   istore 15
L489:   iconst_0
L490:   istore 16
L492:   iload 13
L494:   iconst_4
L495:   iand
L496:   ifeq L506
L499:   aload 7
L501:   invokevirtual Method MBMGIXGO j ()I
L504:   istore 16
L506:   aload_0
L507:   getfield Field ZKARKDQW z [I
L510:   iload 12
L512:   iload 9
L514:   iload 14
L516:   iadd
L517:   iastore
L518:   aload_0
L519:   getfield Field ZKARKDQW A [I
L522:   iload 12
L524:   iload 10
L526:   iload 15
L528:   iadd
L529:   iastore
L530:   aload_0
L531:   getfield Field ZKARKDQW B [I
L534:   iload 12
L536:   iload 11
L538:   iload 16
L540:   iadd
L541:   iastore
L542:   aload_0
L543:   getfield Field ZKARKDQW z [I
L546:   iload 12
L548:   iaload
L549:   istore 9
L551:   aload_0
L552:   getfield Field ZKARKDQW A [I
L555:   iload 12
L557:   iaload
L558:   istore 10
L560:   aload_0
L561:   getfield Field ZKARKDQW B [I
L564:   iload 12
L566:   iaload
L567:   istore 11
L569:   aload_0
L570:   getfield Field ZKARKDQW bb [I
L573:   ifnull L588
L576:   aload_0
L577:   getfield Field ZKARKDQW bb [I
L580:   iload 12
L582:   aload 8
L584:   invokevirtual Method MBMGIXGO c ()I
L587:   iastore
L588:   iinc 12 1
L591:   iload 12
L593:   aload_0
L594:   getfield Field ZKARKDQW y I
L597:   if_icmplt L448
L600:   aload 4
L602:   aload_3
L603:   getfield Field LLORVYLP l I
L606:   putfield Field MBMGIXGO z I
L609:   aload 5
L611:   aload_3
L612:   getfield Field LLORVYLP m I
L615:   putfield Field MBMGIXGO z I
L618:   aload 6
L620:   aload_3
L621:   getfield Field LLORVYLP n I
L624:   putfield Field MBMGIXGO z I
L627:   aload 7
L629:   aload_3
L630:   getfield Field LLORVYLP o I
L633:   putfield Field MBMGIXGO z I
L636:   aload 8
L638:   aload_3
L639:   getfield Field LLORVYLP p I
L642:   putfield Field MBMGIXGO z I
L645:   iconst_0
L646:   istore 13
L648:   iload 21
L650:   ifeq L744
L653:   aload_0
L654:   getfield Field ZKARKDQW M [I
L657:   iload 13
L659:   aload 4
L661:   invokevirtual Method MBMGIXGO e ()I
L664:   iastore
L665:   aload_0
L666:   getfield Field ZKARKDQW J [I
L669:   ifnull L684
L672:   aload_0
L673:   getfield Field ZKARKDQW J [I
L676:   iload 13
L678:   aload 5
L680:   invokevirtual Method MBMGIXGO c ()I
L683:   iastore
L684:   aload_0
L685:   getfield Field ZKARKDQW K [I
L688:   ifnull L703
L691:   aload_0
L692:   getfield Field ZKARKDQW K [I
L695:   iload 13
L697:   aload 6
L699:   invokevirtual Method MBMGIXGO c ()I
L702:   iastore
L703:   aload_0
L704:   getfield Field ZKARKDQW L [I
L707:   ifnull L722
L710:   aload_0
L711:   getfield Field ZKARKDQW L [I
L714:   iload 13
L716:   aload 7
L718:   invokevirtual Method MBMGIXGO c ()I
L721:   iastore
L722:   aload_0
L723:   getfield Field ZKARKDQW cb [I
L726:   ifnull L741
L729:   aload_0
L730:   getfield Field ZKARKDQW cb [I
L733:   iload 13
L735:   aload 8
L737:   invokevirtual Method MBMGIXGO c ()I
L740:   iastore
L741:   iinc 13 1
L744:   iload 13
L746:   aload_0
L747:   getfield Field ZKARKDQW C I
L750:   if_icmplt L653
L753:   aload 4
L755:   aload_3
L756:   getfield Field LLORVYLP j I
L759:   putfield Field MBMGIXGO z I
L762:   aload 5
L764:   aload_3
L765:   getfield Field LLORVYLP k I
L768:   putfield Field MBMGIXGO z I
L771:   iconst_0
L772:   istore 14
L774:   iconst_0
L775:   istore 15
L777:   iconst_0
L778:   istore 16
L780:   iconst_0
L781:   istore 17
L783:   iconst_0
L784:   istore 18
L786:   iload 21
L788:   ifeq L1045
L791:   aload 5
L793:   invokevirtual Method MBMGIXGO c ()I
L796:   istore 19
L798:   iload 19
L800:   iconst_1
L801:   if_icmpne L873
L804:   aload 4
L806:   invokevirtual Method MBMGIXGO j ()I
L809:   iload 17
L811:   iadd
L812:   istore 14
L814:   iload 14
L816:   istore 17
L818:   aload 4
L820:   invokevirtual Method MBMGIXGO j ()I
L823:   iload 17
L825:   iadd
L826:   istore 15
L828:   iload 15
L830:   istore 17
L832:   aload 4
L834:   invokevirtual Method MBMGIXGO j ()I
L837:   iload 17
L839:   iadd
L840:   istore 16
L842:   iload 16
L844:   istore 17
L846:   aload_0
L847:   getfield Field ZKARKDQW D [I
L850:   iload 18
L852:   iload 14
L854:   iastore
L855:   aload_0
L856:   getfield Field ZKARKDQW E [I
L859:   iload 18
L861:   iload 15
L863:   iastore
L864:   aload_0
L865:   getfield Field ZKARKDQW F [I
L868:   iload 18
L870:   iload 16
L872:   iastore
L873:   iload 19
L875:   iconst_2
L876:   if_icmpne L928
L879:   iload 14
L881:   istore 14
L883:   iload 16
L885:   istore 15
L887:   aload 4
L889:   invokevirtual Method MBMGIXGO j ()I
L892:   iload 17
L894:   iadd
L895:   istore 16
L897:   iload 16
L899:   istore 17
L901:   aload_0
L902:   getfield Field ZKARKDQW D [I
L905:   iload 18
L907:   iload 14
L909:   iastore
L910:   aload_0
L911:   getfield Field ZKARKDQW E [I
L914:   iload 18
L916:   iload 15
L918:   iastore
L919:   aload_0
L920:   getfield Field ZKARKDQW F [I
L923:   iload 18
L925:   iload 16
L927:   iastore
L928:   iload 19
L930:   iconst_3
L931:   if_icmpne L983
L934:   iload 16
L936:   istore 14
L938:   iload 15
L940:   istore 15
L942:   aload 4
L944:   invokevirtual Method MBMGIXGO j ()I
L947:   iload 17
L949:   iadd
L950:   istore 16
L952:   iload 16
L954:   istore 17
L956:   aload_0
L957:   getfield Field ZKARKDQW D [I
L960:   iload 18
L962:   iload 14
L964:   iastore
L965:   aload_0
L966:   getfield Field ZKARKDQW E [I
L969:   iload 18
L971:   iload 15
L973:   iastore
L974:   aload_0
L975:   getfield Field ZKARKDQW F [I
L978:   iload 18
L980:   iload 16
L982:   iastore
L983:   iload 19
L985:   iconst_4
L986:   if_icmpne L1042
L989:   iload 14
L991:   istore 20
L993:   iload 15
L995:   istore 14
L997:   iload 20
L999:   istore 15
L1001:  aload 4
L1003:  invokevirtual Method MBMGIXGO j ()I
L1006:  iload 17
L1008:  iadd
L1009:  istore 16
L1011:  iload 16
L1013:  istore 17
L1015:  aload_0
L1016:  getfield Field ZKARKDQW D [I
L1019:  iload 18
L1021:  iload 14
L1023:  iastore
L1024:  aload_0
L1025:  getfield Field ZKARKDQW E [I
L1028:  iload 18
L1030:  iload 15
L1032:  iastore
L1033:  aload_0
L1034:  getfield Field ZKARKDQW F [I
L1037:  iload 18
L1039:  iload 16
L1041:  iastore
L1042:  iinc 18 1
L1045:  iload 18
L1047:  aload_0
L1048:  getfield Field ZKARKDQW C I
L1051:  if_icmplt L791
L1054:  aload 4
L1056:  aload_3
L1057:  getfield Field LLORVYLP q I
L1060:  putfield Field MBMGIXGO z I
L1063:  iconst_0
L1064:  istore 19
L1066:  iload 21
L1068:  ifeq L1110
L1071:  aload_0
L1072:  getfield Field ZKARKDQW P [I
L1075:  iload 19
L1077:  aload 4
L1079:  invokevirtual Method MBMGIXGO e ()I
L1082:  iastore
L1083:  aload_0
L1084:  getfield Field ZKARKDQW Q [I
L1087:  iload 19
L1089:  aload 4
L1091:  invokevirtual Method MBMGIXGO e ()I
L1094:  iastore
L1095:  aload_0
L1096:  getfield Field ZKARKDQW R [I
L1099:  iload 19
L1101:  aload 4
L1103:  invokevirtual Method MBMGIXGO e ()I
L1106:  iastore
L1107:  iinc 19 1
L1110:  iload 19
L1112:  aload_0
L1113:  getfield Field ZKARKDQW O I
L1116:  if_icmplt L1071
L1119:  return
L1120:  astore_3
L1121:  new java/lang/StringBuffer
L1124:  dup
L1125:  ldc "51145, "
L1127:  invokespecial Method java/lang/StringBuffer <init> (Ljava/lang/String;)V
L1130:  iload_1
L1131:  invokevirtual Method java/lang/StringBuffer append (I)Ljava/lang/StringBuffer;
L1134:  ldc ", "
L1136:  invokevirtual Method java/lang/StringBuffer append (Ljava/lang/String;)Ljava/lang/StringBuffer;
L1139:  iload_2
L1140:  invokevirtual Method java/lang/StringBuffer append (I)Ljava/lang/StringBuffer;
L1143:  ldc ", "
L1145:  invokevirtual Method java/lang/StringBuffer append (Ljava/lang/String;)Ljava/lang/StringBuffer;
L1148:  aload_3
L1149:  invokevirtual Method java/lang/Throwable toString ()Ljava/lang/String;
L1152:  invokevirtual Method java/lang/StringBuffer append (Ljava/lang/String;)Ljava/lang/StringBuffer;
L1155:  invokevirtual Method java/lang/StringBuffer toString ()Ljava/lang/String;
L1158:  invokestatic Method sign/signlink reporterror (Ljava/lang/String;)V
L1161:  new java/lang/RuntimeException
L1164:  dup
L1165:  invokespecial Method java/lang/RuntimeException <init> ()V
L1168:  athrow
L1169:  
    .end code
.end method

.method public <init> : (I[LZKARKDQW;I)V
    .code stack 7 locals 15
L0:     getstatic Field XHHRODPC l Z
L3:     istore 14
L5:     aload_0
L6:     invokespecial Method XHHRODPC <init> ()V
L9:     aload_0
L10:    bipush 9
L12:    putfield Field ZKARKDQW m I
L15:    aload_0
L16:    iconst_0
L17:    putfield Field ZKARKDQW n Z
L20:    aload_0
L21:    sipush 360
L24:    putfield Field ZKARKDQW o I
L27:    aload_0
L28:    iconst_1
L29:    putfield Field ZKARKDQW p I
L32:    aload_0
L33:    iconst_1
L34:    putfield Field ZKARKDQW q Z
L37:    aload_0
L38:    iconst_0
L39:    putfield Field ZKARKDQW fb Z
        .catch java/lang/RuntimeException from L42 to L896 using L897
L42:    getstatic Field ZKARKDQW s I
L45:    iconst_1
L46:    iadd
L47:    putstatic Field ZKARKDQW s I
L50:    iconst_0
L51:    istore 4
L53:    iconst_0
L54:    istore 5
L56:    iconst_0
L57:    istore 6
L59:    iconst_0
L60:    istore 7
L62:    aload_0
L63:    iconst_0
L64:    putfield Field ZKARKDQW y I
L67:    aload_0
L68:    iconst_0
L69:    putfield Field ZKARKDQW C I
L72:    aload_0
L73:    iconst_0
L74:    putfield Field ZKARKDQW O I
L77:    aload_0
L78:    iconst_m1
L79:    putfield Field ZKARKDQW N I
L82:    iconst_0
L83:    istore 8
L85:    iload 14
L87:    ifeq L248
L90:    aload_2
L91:    iload 8
L93:    aaload
L94:    astore 9
L96:    aload 9
L98:    ifnull L245
L101:   aload_0
L102:   dup
L103:   getfield Field ZKARKDQW y I
L106:   aload 9
L108:   getfield Field ZKARKDQW y I
L111:   iadd
L112:   putfield Field ZKARKDQW y I
L115:   aload_0
L116:   dup
L117:   getfield Field ZKARKDQW C I
L120:   aload 9
L122:   getfield Field ZKARKDQW C I
L125:   iadd
L126:   putfield Field ZKARKDQW C I
L129:   aload_0
L130:   dup
L131:   getfield Field ZKARKDQW O I
L134:   aload 9
L136:   getfield Field ZKARKDQW O I
L139:   iadd
L140:   putfield Field ZKARKDQW O I
L143:   iload 4
L145:   aload 9
L147:   getfield Field ZKARKDQW J [I
L150:   ifnonnull L157
L153:   iconst_0
L154:   goto L158
L157:   iconst_1
L158:   ior
L159:   istore 4
L161:   aload 9
L163:   getfield Field ZKARKDQW K [I
L166:   ifnull L177
L169:   iconst_1
L170:   istore 5
L172:   iload 14
L174:   ifeq L209
L177:   aload_0
L178:   getfield Field ZKARKDQW N I
L181:   iconst_m1
L182:   if_icmpne L194
L185:   aload_0
L186:   aload 9
L188:   getfield Field ZKARKDQW N I
L191:   putfield Field ZKARKDQW N I
L194:   aload_0
L195:   getfield Field ZKARKDQW N I
L198:   aload 9
L200:   getfield Field ZKARKDQW N I
L203:   if_icmpeq L209
L206:   iconst_1
L207:   istore 5
L209:   iload 6
L211:   aload 9
L213:   getfield Field ZKARKDQW L [I
L216:   ifnonnull L223
L219:   iconst_0
L220:   goto L224
L223:   iconst_1
L224:   ior
L225:   istore 6
L227:   iload 7
L229:   aload 9
L231:   getfield Field ZKARKDQW cb [I
L234:   ifnonnull L241
L237:   iconst_0
L238:   goto L242
L241:   iconst_1
L242:   ior
L243:   istore 7
L245:   iinc 8 1
L248:   iload 8
L250:   iload_1
L251:   if_icmplt L90
L254:   aload_0
L255:   aload_0
L256:   getfield Field ZKARKDQW y I
L259:   newarray int
L261:   putfield Field ZKARKDQW z [I
L264:   aload_0
L265:   aload_0
L266:   getfield Field ZKARKDQW y I
L269:   newarray int
L271:   putfield Field ZKARKDQW A [I
L274:   aload_0
L275:   aload_0
L276:   getfield Field ZKARKDQW y I
L279:   newarray int
L281:   putfield Field ZKARKDQW B [I
L284:   aload_0
L285:   aload_0
L286:   getfield Field ZKARKDQW y I
L289:   newarray int
L291:   putfield Field ZKARKDQW bb [I
L294:   aload_0
L295:   aload_0
L296:   getfield Field ZKARKDQW C I
L299:   newarray int
L301:   putfield Field ZKARKDQW D [I
L304:   aload_0
L305:   aload_0
L306:   getfield Field ZKARKDQW C I
L309:   newarray int
L311:   putfield Field ZKARKDQW E [I
L314:   aload_0
L315:   aload_0
L316:   getfield Field ZKARKDQW C I
L319:   newarray int
L321:   putfield Field ZKARKDQW F [I
L324:   aload_0
L325:   aload_0
L326:   getfield Field ZKARKDQW O I
L329:   newarray int
L331:   putfield Field ZKARKDQW P [I
L334:   aload_0
L335:   aload_0
L336:   getfield Field ZKARKDQW O I
L339:   newarray int
L341:   putfield Field ZKARKDQW Q [I
L344:   aload_0
L345:   aload_0
L346:   getfield Field ZKARKDQW O I
L349:   newarray int
L351:   putfield Field ZKARKDQW R [I
L354:   iload 4
L356:   ifeq L369
L359:   aload_0
L360:   aload_0
L361:   getfield Field ZKARKDQW C I
L364:   newarray int
L366:   putfield Field ZKARKDQW J [I
L369:   iload 5
L371:   ifeq L384
L374:   aload_0
L375:   aload_0
L376:   getfield Field ZKARKDQW C I
L379:   newarray int
L381:   putfield Field ZKARKDQW K [I
L384:   iload 6
L386:   ifeq L399
L389:   aload_0
L390:   aload_0
L391:   getfield Field ZKARKDQW C I
L394:   newarray int
L396:   putfield Field ZKARKDQW L [I
L399:   iload 7
L401:   ifeq L414
L404:   aload_0
L405:   aload_0
L406:   getfield Field ZKARKDQW C I
L409:   newarray int
L411:   putfield Field ZKARKDQW cb [I
L414:   aload_0
L415:   aload_0
L416:   getfield Field ZKARKDQW C I
L419:   newarray int
L421:   putfield Field ZKARKDQW M [I
L424:   aload_0
L425:   iconst_0
L426:   putfield Field ZKARKDQW y I
L429:   aload_0
L430:   iconst_0
L431:   putfield Field ZKARKDQW C I
L434:   aload_0
L435:   iconst_0
L436:   putfield Field ZKARKDQW O I
L439:   iload_3
L440:   iflt L448
L443:   bipush 23
L445:   putstatic Field ZKARKDQW r I
L448:   iconst_0
L449:   istore 9
L451:   iconst_0
L452:   istore 10
L454:   iload 14
L456:   ifeq L890
L459:   aload_2
L460:   iload 10
L462:   aaload
L463:   astore 11
L465:   aload 11
L467:   ifnull L887
L470:   iconst_0
L471:   istore 12
L473:   iload 14
L475:   ifeq L767
L478:   iload 4
L480:   ifeq L544
L483:   aload 11
L485:   getfield Field ZKARKDQW J [I
L488:   ifnonnull L506
L491:   aload_0
L492:   getfield Field ZKARKDQW J [I
L495:   aload_0
L496:   getfield Field ZKARKDQW C I
L499:   iconst_0
L500:   iastore
L501:   iload 14
L503:   ifeq L544
L506:   aload 11
L508:   getfield Field ZKARKDQW J [I
L511:   iload 12
L513:   iaload
L514:   istore 13
L516:   iload 13
L518:   iconst_2
L519:   iand
L520:   iconst_2
L521:   if_icmpne L533
L524:   iload 13
L526:   iload 9
L528:   iconst_2
L529:   ishl
L530:   iadd
L531:   istore 13
L533:   aload_0
L534:   getfield Field ZKARKDQW J [I
L537:   aload_0
L538:   getfield Field ZKARKDQW C I
L541:   iload 13
L543:   iastore
L544:   iload 5
L546:   ifeq L593
L549:   aload 11
L551:   getfield Field ZKARKDQW K [I
L554:   ifnonnull L576
L557:   aload_0
L558:   getfield Field ZKARKDQW K [I
L561:   aload_0
L562:   getfield Field ZKARKDQW C I
L565:   aload 11
L567:   getfield Field ZKARKDQW N I
L570:   iastore
L571:   iload 14
L573:   ifeq L593
L576:   aload_0
L577:   getfield Field ZKARKDQW K [I
L580:   aload_0
L581:   getfield Field ZKARKDQW C I
L584:   aload 11
L586:   getfield Field ZKARKDQW K [I
L589:   iload 12
L591:   iaload
L592:   iastore
L593:   iload 6
L595:   ifeq L638
L598:   aload 11
L600:   getfield Field ZKARKDQW L [I
L603:   ifnonnull L621
L606:   aload_0
L607:   getfield Field ZKARKDQW L [I
L610:   aload_0
L611:   getfield Field ZKARKDQW C I
L614:   iconst_0
L615:   iastore
L616:   iload 14
L618:   ifeq L638
L621:   aload_0
L622:   getfield Field ZKARKDQW L [I
L625:   aload_0
L626:   getfield Field ZKARKDQW C I
L629:   aload 11
L631:   getfield Field ZKARKDQW L [I
L634:   iload 12
L636:   iaload
L637:   iastore
L638:   iload 7
L640:   ifeq L668
L643:   aload 11
L645:   getfield Field ZKARKDQW cb [I
L648:   ifnull L668
L651:   aload_0
L652:   getfield Field ZKARKDQW cb [I
L655:   aload_0
L656:   getfield Field ZKARKDQW C I
L659:   aload 11
L661:   getfield Field ZKARKDQW cb [I
L664:   iload 12
L666:   iaload
L667:   iastore
L668:   aload_0
L669:   getfield Field ZKARKDQW M [I
L672:   aload_0
L673:   getfield Field ZKARKDQW C I
L676:   aload 11
L678:   getfield Field ZKARKDQW M [I
L681:   iload 12
L683:   iaload
L684:   iastore
L685:   aload_0
L686:   getfield Field ZKARKDQW D [I
L689:   aload_0
L690:   getfield Field ZKARKDQW C I
L693:   aload_0
L694:   aload 11
L696:   aload 11
L698:   getfield Field ZKARKDQW D [I
L701:   iload 12
L703:   iaload
L704:   invokespecial Method ZKARKDQW a (LZKARKDQW;I)I
L707:   iastore
L708:   aload_0
L709:   getfield Field ZKARKDQW E [I
L712:   aload_0
L713:   getfield Field ZKARKDQW C I
L716:   aload_0
L717:   aload 11
L719:   aload 11
L721:   getfield Field ZKARKDQW E [I
L724:   iload 12
L726:   iaload
L727:   invokespecial Method ZKARKDQW a (LZKARKDQW;I)I
L730:   iastore
L731:   aload_0
L732:   getfield Field ZKARKDQW F [I
L735:   aload_0
L736:   getfield Field ZKARKDQW C I
L739:   aload_0
L740:   aload 11
L742:   aload 11
L744:   getfield Field ZKARKDQW F [I
L747:   iload 12
L749:   iaload
L750:   invokespecial Method ZKARKDQW a (LZKARKDQW;I)I
L753:   iastore
L754:   aload_0
L755:   dup
L756:   getfield Field ZKARKDQW C I
L759:   iconst_1
L760:   iadd
L761:   putfield Field ZKARKDQW C I
L764:   iinc 12 1
L767:   iload 12
L769:   aload 11
L771:   getfield Field ZKARKDQW C I
L774:   if_icmplt L478
L777:   iconst_0
L778:   istore 13
L780:   iload 14
L782:   ifeq L867
L785:   aload_0
L786:   getfield Field ZKARKDQW P [I
L789:   aload_0
L790:   getfield Field ZKARKDQW O I
L793:   aload_0
L794:   aload 11
L796:   aload 11
L798:   getfield Field ZKARKDQW P [I
L801:   iload 13
L803:   iaload
L804:   invokespecial Method ZKARKDQW a (LZKARKDQW;I)I
L807:   iastore
L808:   aload_0
L809:   getfield Field ZKARKDQW Q [I
L812:   aload_0
L813:   getfield Field ZKARKDQW O I
L816:   aload_0
L817:   aload 11
L819:   aload 11
L821:   getfield Field ZKARKDQW Q [I
L824:   iload 13
L826:   iaload
L827:   invokespecial Method ZKARKDQW a (LZKARKDQW;I)I
L830:   iastore
L831:   aload_0
L832:   getfield Field ZKARKDQW R [I
L835:   aload_0
L836:   getfield Field ZKARKDQW O I
L839:   aload_0
L840:   aload 11
L842:   aload 11
L844:   getfield Field ZKARKDQW R [I
L847:   iload 13
L849:   iaload
L850:   invokespecial Method ZKARKDQW a (LZKARKDQW;I)I
L853:   iastore
L854:   aload_0
L855:   dup
L856:   getfield Field ZKARKDQW O I
L859:   iconst_1
L860:   iadd
L861:   putfield Field ZKARKDQW O I
L864:   iinc 13 1
L867:   iload 13
L869:   aload 11
L871:   getfield Field ZKARKDQW O I
L874:   if_icmplt L785
L877:   iload 9
L879:   aload 11
L881:   getfield Field ZKARKDQW O I
L884:   iadd
L885:   istore 9
L887:   iinc 10 1
L890:   iload 10
L892:   iload_1
L893:   if_icmplt L459
L896:   return
L897:   astore 4
L899:   new java/lang/StringBuffer
L902:   dup
L903:   ldc "84140, "
L905:   invokespecial Method java/lang/StringBuffer <init> (Ljava/lang/String;)V
L908:   iload_1
L909:   invokevirtual Method java/lang/StringBuffer append (I)Ljava/lang/StringBuffer;
L912:   ldc ", "
L914:   invokevirtual Method java/lang/StringBuffer append (Ljava/lang/String;)Ljava/lang/StringBuffer;
L917:   aload_2
L918:   invokevirtual Method java/lang/StringBuffer append (Ljava/lang/Object;)Ljava/lang/StringBuffer;
L921:   ldc ", "
L923:   invokevirtual Method java/lang/StringBuffer append (Ljava/lang/String;)Ljava/lang/StringBuffer;
L926:   iload_3
L927:   invokevirtual Method java/lang/StringBuffer append (I)Ljava/lang/StringBuffer;
L930:   ldc ", "
L932:   invokevirtual Method java/lang/StringBuffer append (Ljava/lang/String;)Ljava/lang/StringBuffer;
L935:   aload 4
L937:   invokevirtual Method java/lang/Throwable toString ()Ljava/lang/String;
L940:   invokevirtual Method java/lang/StringBuffer append (Ljava/lang/String;)Ljava/lang/StringBuffer;
L943:   invokevirtual Method java/lang/StringBuffer toString ()Ljava/lang/String;
L946:   invokestatic Method sign/signlink reporterror (Ljava/lang/String;)V
L949:   new java/lang/RuntimeException
L952:   dup
L953:   invokespecial Method java/lang/RuntimeException <init> ()V
L956:   athrow
L957:   
    .end code
.end method

.method public <init> : (IIZ[LZKARKDQW;)V
    .code stack 5 locals 18
L0:     getstatic Field XHHRODPC l Z
L3:     istore 17
L5:     aload_0
L6:     invokespecial Method XHHRODPC <init> ()V
L9:     aload_0
L10:    bipush 9
L12:    putfield Field ZKARKDQW m I
L15:    aload_0
L16:    iconst_0
L17:    putfield Field ZKARKDQW n Z
L20:    aload_0
L21:    sipush 360
L24:    putfield Field ZKARKDQW o I
L27:    aload_0
L28:    iconst_1
L29:    putfield Field ZKARKDQW p I
L32:    aload_0
L33:    iconst_1
L34:    putfield Field ZKARKDQW q Z
L37:    aload_0
L38:    iconst_0
L39:    putfield Field ZKARKDQW fb Z
        .catch java/lang/RuntimeException from L42 to L1028 using L1029
L42:    getstatic Field ZKARKDQW s I
L45:    iconst_1
L46:    iadd
L47:    putstatic Field ZKARKDQW s I
L50:    iconst_0
L51:    istore 5
L53:    iconst_0
L54:    istore 6
L56:    iconst_0
L57:    istore 7
L59:    iconst_0
L60:    istore 8
L62:    aload_0
L63:    iconst_0
L64:    putfield Field ZKARKDQW y I
L67:    aload_0
L68:    iconst_0
L69:    putfield Field ZKARKDQW C I
L72:    aload_0
L73:    iconst_0
L74:    putfield Field ZKARKDQW O I
L77:    aload_0
L78:    iconst_m1
L79:    putfield Field ZKARKDQW N I
L82:    iconst_0
L83:    istore 9
L85:    iload 17
L87:    ifeq L249
L90:    aload 4
L92:    iload 9
L94:    aaload
L95:    astore 10
L97:    aload 10
L99:    ifnull L246
L102:   aload_0
L103:   dup
L104:   getfield Field ZKARKDQW y I
L107:   aload 10
L109:   getfield Field ZKARKDQW y I
L112:   iadd
L113:   putfield Field ZKARKDQW y I
L116:   aload_0
L117:   dup
L118:   getfield Field ZKARKDQW C I
L121:   aload 10
L123:   getfield Field ZKARKDQW C I
L126:   iadd
L127:   putfield Field ZKARKDQW C I
L130:   aload_0
L131:   dup
L132:   getfield Field ZKARKDQW O I
L135:   aload 10
L137:   getfield Field ZKARKDQW O I
L140:   iadd
L141:   putfield Field ZKARKDQW O I
L144:   iload 5
L146:   aload 10
L148:   getfield Field ZKARKDQW J [I
L151:   ifnonnull L158
L154:   iconst_0
L155:   goto L159
L158:   iconst_1
L159:   ior
L160:   istore 5
L162:   aload 10
L164:   getfield Field ZKARKDQW K [I
L167:   ifnull L178
L170:   iconst_1
L171:   istore 6
L173:   iload 17
L175:   ifeq L210
L178:   aload_0
L179:   getfield Field ZKARKDQW N I
L182:   iconst_m1
L183:   if_icmpne L195
L186:   aload_0
L187:   aload 10
L189:   getfield Field ZKARKDQW N I
L192:   putfield Field ZKARKDQW N I
L195:   aload_0
L196:   getfield Field ZKARKDQW N I
L199:   aload 10
L201:   getfield Field ZKARKDQW N I
L204:   if_icmpeq L210
L207:   iconst_1
L208:   istore 6
L210:   iload 7
L212:   aload 10
L214:   getfield Field ZKARKDQW L [I
L217:   ifnonnull L224
L220:   iconst_0
L221:   goto L225
L224:   iconst_1
L225:   ior
L226:   istore 7
L228:   iload 8
L230:   aload 10
L232:   getfield Field ZKARKDQW M [I
L235:   ifnonnull L242
L238:   iconst_0
L239:   goto L243
L242:   iconst_1
L243:   ior
L244:   istore 8
L246:   iinc 9 1
L249:   iload 9
L251:   iload_1
L252:   if_icmplt L90
L255:   aload_0
L256:   aload_0
L257:   getfield Field ZKARKDQW y I
L260:   newarray int
L262:   putfield Field ZKARKDQW z [I
L265:   aload_0
L266:   aload_0
L267:   getfield Field ZKARKDQW y I
L270:   newarray int
L272:   putfield Field ZKARKDQW A [I
L275:   aload_0
L276:   aload_0
L277:   getfield Field ZKARKDQW y I
L280:   newarray int
L282:   putfield Field ZKARKDQW B [I
L285:   aload_0
L286:   aload_0
L287:   getfield Field ZKARKDQW C I
L290:   newarray int
L292:   putfield Field ZKARKDQW D [I
L295:   aload_0
L296:   aload_0
L297:   getfield Field ZKARKDQW C I
L300:   newarray int
L302:   putfield Field ZKARKDQW E [I
L305:   aload_0
L306:   aload_0
L307:   getfield Field ZKARKDQW C I
L310:   newarray int
L312:   putfield Field ZKARKDQW F [I
L315:   aload_0
L316:   aload_0
L317:   getfield Field ZKARKDQW C I
L320:   newarray int
L322:   putfield Field ZKARKDQW G [I
L325:   aload_0
L326:   aload_0
L327:   getfield Field ZKARKDQW C I
L330:   newarray int
L332:   putfield Field ZKARKDQW H [I
L335:   aload_0
L336:   aload_0
L337:   getfield Field ZKARKDQW C I
L340:   newarray int
L342:   putfield Field ZKARKDQW I [I
L345:   aload_0
L346:   aload_0
L347:   getfield Field ZKARKDQW O I
L350:   newarray int
L352:   putfield Field ZKARKDQW P [I
L355:   aload_0
L356:   aload_0
L357:   getfield Field ZKARKDQW O I
L360:   newarray int
L362:   putfield Field ZKARKDQW Q [I
L365:   aload_0
L366:   aload_0
L367:   getfield Field ZKARKDQW O I
L370:   newarray int
L372:   putfield Field ZKARKDQW R [I
L375:   iload_2
L376:   iflt L395
L379:   iconst_1
L380:   istore 10
L382:   iload 17
L384:   ifeq L390
L387:   iinc 10 1
L390:   iload 10
L392:   ifgt L387
L395:   iload 5
L397:   ifeq L410
L400:   aload_0
L401:   aload_0
L402:   getfield Field ZKARKDQW C I
L405:   newarray int
L407:   putfield Field ZKARKDQW J [I
L410:   iload 6
L412:   ifeq L425
L415:   aload_0
L416:   aload_0
L417:   getfield Field ZKARKDQW C I
L420:   newarray int
L422:   putfield Field ZKARKDQW K [I
L425:   iload 7
L427:   ifeq L440
L430:   aload_0
L431:   aload_0
L432:   getfield Field ZKARKDQW C I
L435:   newarray int
L437:   putfield Field ZKARKDQW L [I
L440:   iload 8
L442:   ifeq L455
L445:   aload_0
L446:   aload_0
L447:   getfield Field ZKARKDQW C I
L450:   newarray int
L452:   putfield Field ZKARKDQW M [I
L455:   aload_0
L456:   iconst_0
L457:   putfield Field ZKARKDQW y I
L460:   aload_0
L461:   iconst_0
L462:   putfield Field ZKARKDQW C I
L465:   aload_0
L466:   iconst_0
L467:   putfield Field ZKARKDQW O I
L470:   iconst_0
L471:   istore 10
L473:   iconst_0
L474:   istore 11
L476:   iload 17
L478:   ifeq L1017
L481:   aload 4
L483:   iload 11
L485:   aaload
L486:   astore 12
L488:   aload 12
L490:   ifnull L1014
L493:   aload_0
L494:   getfield Field ZKARKDQW y I
L497:   istore 13
L499:   iconst_0
L500:   istore 14
L502:   iload 17
L504:   ifeq L571
L507:   aload_0
L508:   getfield Field ZKARKDQW z [I
L511:   aload_0
L512:   getfield Field ZKARKDQW y I
L515:   aload 12
L517:   getfield Field ZKARKDQW z [I
L520:   iload 14
L522:   iaload
L523:   iastore
L524:   aload_0
L525:   getfield Field ZKARKDQW A [I
L528:   aload_0
L529:   getfield Field ZKARKDQW y I
L532:   aload 12
L534:   getfield Field ZKARKDQW A [I
L537:   iload 14
L539:   iaload
L540:   iastore
L541:   aload_0
L542:   getfield Field ZKARKDQW B [I
L545:   aload_0
L546:   getfield Field ZKARKDQW y I
L549:   aload 12
L551:   getfield Field ZKARKDQW B [I
L554:   iload 14
L556:   iaload
L557:   iastore
L558:   aload_0
L559:   dup
L560:   getfield Field ZKARKDQW y I
L563:   iconst_1
L564:   iadd
L565:   putfield Field ZKARKDQW y I
L568:   iinc 14 1
L571:   iload 14
L573:   aload 12
L575:   getfield Field ZKARKDQW y I
L578:   if_icmplt L507
L581:   iconst_0
L582:   istore 15
L584:   iload 17
L586:   ifeq L903
L589:   aload_0
L590:   getfield Field ZKARKDQW D [I
L593:   aload_0
L594:   getfield Field ZKARKDQW C I
L597:   aload 12
L599:   getfield Field ZKARKDQW D [I
L602:   iload 15
L604:   iaload
L605:   iload 13
L607:   iadd
L608:   iastore
L609:   aload_0
L610:   getfield Field ZKARKDQW E [I
L613:   aload_0
L614:   getfield Field ZKARKDQW C I
L617:   aload 12
L619:   getfield Field ZKARKDQW E [I
L622:   iload 15
L624:   iaload
L625:   iload 13
L627:   iadd
L628:   iastore
L629:   aload_0
L630:   getfield Field ZKARKDQW F [I
L633:   aload_0
L634:   getfield Field ZKARKDQW C I
L637:   aload 12
L639:   getfield Field ZKARKDQW F [I
L642:   iload 15
L644:   iaload
L645:   iload 13
L647:   iadd
L648:   iastore
L649:   aload_0
L650:   getfield Field ZKARKDQW G [I
L653:   aload_0
L654:   getfield Field ZKARKDQW C I
L657:   aload 12
L659:   getfield Field ZKARKDQW G [I
L662:   iload 15
L664:   iaload
L665:   iastore
L666:   aload_0
L667:   getfield Field ZKARKDQW H [I
L670:   aload_0
L671:   getfield Field ZKARKDQW C I
L674:   aload 12
L676:   getfield Field ZKARKDQW H [I
L679:   iload 15
L681:   iaload
L682:   iastore
L683:   aload_0
L684:   getfield Field ZKARKDQW I [I
L687:   aload_0
L688:   getfield Field ZKARKDQW C I
L691:   aload 12
L693:   getfield Field ZKARKDQW I [I
L696:   iload 15
L698:   iaload
L699:   iastore
L700:   iload 5
L702:   ifeq L766
L705:   aload 12
L707:   getfield Field ZKARKDQW J [I
L710:   ifnonnull L728
L713:   aload_0
L714:   getfield Field ZKARKDQW J [I
L717:   aload_0
L718:   getfield Field ZKARKDQW C I
L721:   iconst_0
L722:   iastore
L723:   iload 17
L725:   ifeq L766
L728:   aload 12
L730:   getfield Field ZKARKDQW J [I
L733:   iload 15
L735:   iaload
L736:   istore 16
L738:   iload 16
L740:   iconst_2
L741:   iand
L742:   iconst_2
L743:   if_icmpne L755
L746:   iload 16
L748:   iload 10
L750:   iconst_2
L751:   ishl
L752:   iadd
L753:   istore 16
L755:   aload_0
L756:   getfield Field ZKARKDQW J [I
L759:   aload_0
L760:   getfield Field ZKARKDQW C I
L763:   iload 16
L765:   iastore
L766:   iload 6
L768:   ifeq L815
L771:   aload 12
L773:   getfield Field ZKARKDQW K [I
L776:   ifnonnull L798
L779:   aload_0
L780:   getfield Field ZKARKDQW K [I
L783:   aload_0
L784:   getfield Field ZKARKDQW C I
L787:   aload 12
L789:   getfield Field ZKARKDQW N I
L792:   iastore
L793:   iload 17
L795:   ifeq L815
L798:   aload_0
L799:   getfield Field ZKARKDQW K [I
L802:   aload_0
L803:   getfield Field ZKARKDQW C I
L806:   aload 12
L808:   getfield Field ZKARKDQW K [I
L811:   iload 15
L813:   iaload
L814:   iastore
L815:   iload 7
L817:   ifeq L860
L820:   aload 12
L822:   getfield Field ZKARKDQW L [I
L825:   ifnonnull L843
L828:   aload_0
L829:   getfield Field ZKARKDQW L [I
L832:   aload_0
L833:   getfield Field ZKARKDQW C I
L836:   iconst_0
L837:   iastore
L838:   iload 17
L840:   ifeq L860
L843:   aload_0
L844:   getfield Field ZKARKDQW L [I
L847:   aload_0
L848:   getfield Field ZKARKDQW C I
L851:   aload 12
L853:   getfield Field ZKARKDQW L [I
L856:   iload 15
L858:   iaload
L859:   iastore
L860:   iload 8
L862:   ifeq L890
L865:   aload 12
L867:   getfield Field ZKARKDQW M [I
L870:   ifnull L890
L873:   aload_0
L874:   getfield Field ZKARKDQW M [I
L877:   aload_0
L878:   getfield Field ZKARKDQW C I
L881:   aload 12
L883:   getfield Field ZKARKDQW M [I
L886:   iload 15
L888:   iaload
L889:   iastore
L890:   aload_0
L891:   dup
L892:   getfield Field ZKARKDQW C I
L895:   iconst_1
L896:   iadd
L897:   putfield Field ZKARKDQW C I
L900:   iinc 15 1
L903:   iload 15
L905:   aload 12
L907:   getfield Field ZKARKDQW C I
L910:   if_icmplt L589
L913:   iconst_0
L914:   istore 16
L916:   iload 17
L918:   ifeq L994
L921:   aload_0
L922:   getfield Field ZKARKDQW P [I
L925:   aload_0
L926:   getfield Field ZKARKDQW O I
L929:   aload 12
L931:   getfield Field ZKARKDQW P [I
L934:   iload 16
L936:   iaload
L937:   iload 13
L939:   iadd
L940:   iastore
L941:   aload_0
L942:   getfield Field ZKARKDQW Q [I
L945:   aload_0
L946:   getfield Field ZKARKDQW O I
L949:   aload 12
L951:   getfield Field ZKARKDQW Q [I
L954:   iload 16
L956:   iaload
L957:   iload 13
L959:   iadd
L960:   iastore
L961:   aload_0
L962:   getfield Field ZKARKDQW R [I
L965:   aload_0
L966:   getfield Field ZKARKDQW O I
L969:   aload 12
L971:   getfield Field ZKARKDQW R [I
L974:   iload 16
L976:   iaload
L977:   iload 13
L979:   iadd
L980:   iastore
L981:   aload_0
L982:   dup
L983:   getfield Field ZKARKDQW O I
L986:   iconst_1
L987:   iadd
L988:   putfield Field ZKARKDQW O I
L991:   iinc 16 1
L994:   iload 16
L996:   aload 12
L998:   getfield Field ZKARKDQW O I
L1001:  if_icmplt L921
L1004:  iload 10
L1006:  aload 12
L1008:  getfield Field ZKARKDQW O I
L1011:  iadd
L1012:  istore 10
L1014:  iinc 11 1
L1017:  iload 11
L1019:  iload_1
L1020:  if_icmplt L481
L1023:  aload_0
L1024:  iconst_0
L1025:  invokevirtual Method ZKARKDQW a (Z)V
L1028:  return
L1029:  astore 5
L1031:  new java/lang/StringBuffer
L1034:  dup
L1035:  ldc "65900, "
L1037:  invokespecial Method java/lang/StringBuffer <init> (Ljava/lang/String;)V
L1040:  iload_1
L1041:  invokevirtual Method java/lang/StringBuffer append (I)Ljava/lang/StringBuffer;
L1044:  ldc ", "
L1046:  invokevirtual Method java/lang/StringBuffer append (Ljava/lang/String;)Ljava/lang/StringBuffer;
L1049:  iload_2
L1050:  invokevirtual Method java/lang/StringBuffer append (I)Ljava/lang/StringBuffer;
L1053:  ldc ", "
L1055:  invokevirtual Method java/lang/StringBuffer append (Ljava/lang/String;)Ljava/lang/StringBuffer;
L1058:  iload_3
L1059:  invokevirtual Method java/lang/StringBuffer append (Z)Ljava/lang/StringBuffer;
L1062:  ldc ", "
L1064:  invokevirtual Method java/lang/StringBuffer append (Ljava/lang/String;)Ljava/lang/StringBuffer;
L1067:  aload 4
L1069:  invokevirtual Method java/lang/StringBuffer append (Ljava/lang/Object;)Ljava/lang/StringBuffer;
L1072:  ldc ", "
L1074:  invokevirtual Method java/lang/StringBuffer append (Ljava/lang/String;)Ljava/lang/StringBuffer;
L1077:  aload 5
L1079:  invokevirtual Method java/lang/Throwable toString ()Ljava/lang/String;
L1082:  invokevirtual Method java/lang/StringBuffer append (Ljava/lang/String;)Ljava/lang/StringBuffer;
L1085:  invokevirtual Method java/lang/StringBuffer toString ()Ljava/lang/String;
L1088:  invokestatic Method sign/signlink reporterror (Ljava/lang/String;)V
L1091:  new java/lang/RuntimeException
L1094:  dup
L1095:  invokespecial Method java/lang/RuntimeException <init> ()V
L1098:  athrow
L1099:  
    .end code
.end method

.method public <init> : (IZZZLZKARKDQW;)V
    .code stack 5 locals 8
L0:     getstatic Field XHHRODPC l Z
L3:     istore 7
L5:     aload_0
L6:     invokespecial Method XHHRODPC <init> ()V
L9:     aload_0
L10:    bipush 9
L12:    putfield Field ZKARKDQW m I
L15:    aload_0
L16:    iconst_0
L17:    putfield Field ZKARKDQW n Z
L20:    aload_0
L21:    sipush 360
L24:    putfield Field ZKARKDQW o I
L27:    aload_0
L28:    iconst_1
L29:    putfield Field ZKARKDQW p I
L32:    aload_0
L33:    iconst_1
L34:    putfield Field ZKARKDQW q Z
L37:    aload_0
L38:    iconst_0
L39:    putfield Field ZKARKDQW fb Z
        .catch java/lang/RuntimeException from L42 to L501 using L502
L42:    getstatic Field ZKARKDQW s I
L45:    iconst_1
L46:    iadd
L47:    putstatic Field ZKARKDQW s I
L50:    aload_0
L51:    aload 5
L53:    getfield Field ZKARKDQW y I
L56:    putfield Field ZKARKDQW y I
L59:    aload_0
L60:    aload 5
L62:    getfield Field ZKARKDQW C I
L65:    putfield Field ZKARKDQW C I
L68:    aload_0
L69:    aload 5
L71:    getfield Field ZKARKDQW O I
L74:    putfield Field ZKARKDQW O I
L77:    iload 4
L79:    ifeq L114
L82:    aload_0
L83:    aload 5
L85:    getfield Field ZKARKDQW z [I
L88:    putfield Field ZKARKDQW z [I
L91:    aload_0
L92:    aload 5
L94:    getfield Field ZKARKDQW A [I
L97:    putfield Field ZKARKDQW A [I
L100:   aload_0
L101:   aload 5
L103:   getfield Field ZKARKDQW B [I
L106:   putfield Field ZKARKDQW B [I
L109:   iload 7
L111:   ifeq L209
L114:   aload_0
L115:   aload_0
L116:   getfield Field ZKARKDQW y I
L119:   newarray int
L121:   putfield Field ZKARKDQW z [I
L124:   aload_0
L125:   aload_0
L126:   getfield Field ZKARKDQW y I
L129:   newarray int
L131:   putfield Field ZKARKDQW A [I
L134:   aload_0
L135:   aload_0
L136:   getfield Field ZKARKDQW y I
L139:   newarray int
L141:   putfield Field ZKARKDQW B [I
L144:   iconst_0
L145:   istore 6
L147:   iload 7
L149:   ifeq L200
L152:   aload_0
L153:   getfield Field ZKARKDQW z [I
L156:   iload 6
L158:   aload 5
L160:   getfield Field ZKARKDQW z [I
L163:   iload 6
L165:   iaload
L166:   iastore
L167:   aload_0
L168:   getfield Field ZKARKDQW A [I
L171:   iload 6
L173:   aload 5
L175:   getfield Field ZKARKDQW A [I
L178:   iload 6
L180:   iaload
L181:   iastore
L182:   aload_0
L183:   getfield Field ZKARKDQW B [I
L186:   iload 6
L188:   aload 5
L190:   getfield Field ZKARKDQW B [I
L193:   iload 6
L195:   iaload
L196:   iastore
L197:   iinc 6 1
L200:   iload 6
L202:   aload_0
L203:   getfield Field ZKARKDQW y I
L206:   if_icmplt L152
L209:   iload_2
L210:   ifeq L227
L213:   aload_0
L214:   aload 5
L216:   getfield Field ZKARKDQW M [I
L219:   putfield Field ZKARKDQW M [I
L222:   iload 7
L224:   ifeq L272
L227:   aload_0
L228:   aload_0
L229:   getfield Field ZKARKDQW C I
L232:   newarray int
L234:   putfield Field ZKARKDQW M [I
L237:   iconst_0
L238:   istore 6
L240:   iload 7
L242:   ifeq L263
L245:   aload_0
L246:   getfield Field ZKARKDQW M [I
L249:   iload 6
L251:   aload 5
L253:   getfield Field ZKARKDQW M [I
L256:   iload 6
L258:   iaload
L259:   iastore
L260:   iinc 6 1
L263:   iload 6
L265:   aload_0
L266:   getfield Field ZKARKDQW C I
L269:   if_icmplt L245
L272:   iload_3
L273:   ifeq L290
L276:   aload_0
L277:   aload 5
L279:   getfield Field ZKARKDQW L [I
L282:   putfield Field ZKARKDQW L [I
L285:   iload 7
L287:   ifeq L374
L290:   aload_0
L291:   aload_0
L292:   getfield Field ZKARKDQW C I
L295:   newarray int
L297:   putfield Field ZKARKDQW L [I
L300:   aload 5
L302:   getfield Field ZKARKDQW L [I
L305:   ifnonnull L339
L308:   iconst_0
L309:   istore 6
L311:   iload 7
L313:   ifeq L327
L316:   aload_0
L317:   getfield Field ZKARKDQW L [I
L320:   iload 6
L322:   iconst_0
L323:   iastore
L324:   iinc 6 1
L327:   iload 6
L329:   aload_0
L330:   getfield Field ZKARKDQW C I
L333:   if_icmplt L316
L336:   goto L374
L339:   iconst_0
L340:   istore 6
L342:   iload 7
L344:   ifeq L365
L347:   aload_0
L348:   getfield Field ZKARKDQW L [I
L351:   iload 6
L353:   aload 5
L355:   getfield Field ZKARKDQW L [I
L358:   iload 6
L360:   iaload
L361:   iastore
L362:   iinc 6 1
L365:   iload 6
L367:   aload_0
L368:   getfield Field ZKARKDQW C I
L371:   if_icmplt L347
L374:   aload_0
L375:   aload 5
L377:   getfield Field ZKARKDQW bb [I
L380:   putfield Field ZKARKDQW bb [I
L383:   aload_0
L384:   aload 5
L386:   getfield Field ZKARKDQW cb [I
L389:   putfield Field ZKARKDQW cb [I
L392:   aload_0
L393:   aload 5
L395:   getfield Field ZKARKDQW J [I
L398:   putfield Field ZKARKDQW J [I
L401:   aload_0
L402:   aload 5
L404:   getfield Field ZKARKDQW D [I
L407:   putfield Field ZKARKDQW D [I
L410:   aload_0
L411:   aload 5
L413:   getfield Field ZKARKDQW E [I
L416:   putfield Field ZKARKDQW E [I
L419:   aload_0
L420:   aload 5
L422:   getfield Field ZKARKDQW F [I
L425:   putfield Field ZKARKDQW F [I
L428:   aload_0
L429:   aload 5
L431:   getfield Field ZKARKDQW K [I
L434:   putfield Field ZKARKDQW K [I
L437:   aload_0
L438:   aload 5
L440:   getfield Field ZKARKDQW N I
L443:   putfield Field ZKARKDQW N I
L446:   aload_0
L447:   aload 5
L449:   getfield Field ZKARKDQW P [I
L452:   putfield Field ZKARKDQW P [I
L455:   iload_1
L456:   bipush 9
L458:   if_icmplt L467
L461:   iload_1
L462:   bipush 9
L464:   if_icmple L483
L467:   iconst_1
L468:   istore 6
L470:   iload 7
L472:   ifeq L478
L475:   iinc 6 1
L478:   iload 6
L480:   ifgt L475
L483:   aload_0
L484:   aload 5
L486:   getfield Field ZKARKDQW Q [I
L489:   putfield Field ZKARKDQW Q [I
L492:   aload_0
L493:   aload 5
L495:   getfield Field ZKARKDQW R [I
L498:   putfield Field ZKARKDQW R [I
L501:   return
L502:   astore 6
L504:   new java/lang/StringBuffer
L507:   dup
L508:   ldc "76077, "
L510:   invokespecial Method java/lang/StringBuffer <init> (Ljava/lang/String;)V
L513:   iload_1
L514:   invokevirtual Method java/lang/StringBuffer append (I)Ljava/lang/StringBuffer;
L517:   ldc ", "
L519:   invokevirtual Method java/lang/StringBuffer append (Ljava/lang/String;)Ljava/lang/StringBuffer;
L522:   iload_2
L523:   invokevirtual Method java/lang/StringBuffer append (Z)Ljava/lang/StringBuffer;
L526:   ldc ", "
L528:   invokevirtual Method java/lang/StringBuffer append (Ljava/lang/String;)Ljava/lang/StringBuffer;
L531:   iload_3
L532:   invokevirtual Method java/lang/StringBuffer append (Z)Ljava/lang/StringBuffer;
L535:   ldc ", "
L537:   invokevirtual Method java/lang/StringBuffer append (Ljava/lang/String;)Ljava/lang/StringBuffer;
L540:   iload 4
L542:   invokevirtual Method java/lang/StringBuffer append (Z)Ljava/lang/StringBuffer;
L545:   ldc ", "
L547:   invokevirtual Method java/lang/StringBuffer append (Ljava/lang/String;)Ljava/lang/StringBuffer;
L550:   aload 5
L552:   invokevirtual Method java/lang/StringBuffer append (Ljava/lang/Object;)Ljava/lang/StringBuffer;
L555:   ldc ", "
L557:   invokevirtual Method java/lang/StringBuffer append (Ljava/lang/String;)Ljava/lang/StringBuffer;
L560:   aload 6
L562:   invokevirtual Method java/lang/Throwable toString ()Ljava/lang/String;
L565:   invokevirtual Method java/lang/StringBuffer append (Ljava/lang/String;)Ljava/lang/StringBuffer;
L568:   invokevirtual Method java/lang/StringBuffer toString ()Ljava/lang/String;
L571:   invokestatic Method sign/signlink reporterror (Ljava/lang/String;)V
L574:   new java/lang/RuntimeException
L577:   dup
L578:   invokespecial Method java/lang/RuntimeException <init> ()V
L581:   athrow
L582:   
    .end code
.end method

.method public <init> : (ZIZLZKARKDQW;)V
    .code stack 5 locals 10
L0:     getstatic Field XHHRODPC l Z
L3:     istore 9
L5:     aload_0
L6:     invokespecial Method XHHRODPC <init> ()V
L9:     aload_0
L10:    bipush 9
L12:    putfield Field ZKARKDQW m I
L15:    aload_0
L16:    iconst_0
L17:    putfield Field ZKARKDQW n Z
L20:    aload_0
L21:    sipush 360
L24:    putfield Field ZKARKDQW o I
L27:    aload_0
L28:    iconst_1
L29:    putfield Field ZKARKDQW p I
L32:    aload_0
L33:    iconst_1
L34:    putfield Field ZKARKDQW q Z
L37:    aload_0
L38:    iconst_0
L39:    putfield Field ZKARKDQW fb Z
        .catch java/lang/RuntimeException from L42 to L675 using L676
L42:    getstatic Field ZKARKDQW s I
L45:    iconst_1
L46:    iadd
L47:    putstatic Field ZKARKDQW s I
L50:    aload_0
L51:    aload 4
L53:    getfield Field ZKARKDQW y I
L56:    putfield Field ZKARKDQW y I
L59:    aload_0
L60:    aload 4
L62:    getfield Field ZKARKDQW C I
L65:    putfield Field ZKARKDQW C I
L68:    aload_0
L69:    aload 4
L71:    getfield Field ZKARKDQW O I
L74:    putfield Field ZKARKDQW O I
L77:    iload_1
L78:    ifeq L129
L81:    aload_0
L82:    aload_0
L83:    getfield Field ZKARKDQW y I
L86:    newarray int
L88:    putfield Field ZKARKDQW A [I
L91:    iconst_0
L92:    istore 5
L94:    iload 9
L96:    ifeq L117
L99:    aload_0
L100:   getfield Field ZKARKDQW A [I
L103:   iload 5
L105:   aload 4
L107:   getfield Field ZKARKDQW A [I
L110:   iload 5
L112:   iaload
L113:   iastore
L114:   iinc 5 1
L117:   iload 5
L119:   aload_0
L120:   getfield Field ZKARKDQW y I
L123:   if_icmplt L99
L126:   goto L138
L129:   aload_0
L130:   aload 4
L132:   getfield Field ZKARKDQW A [I
L135:   putfield Field ZKARKDQW A [I
L138:   iload_3
L139:   ifeq L433
L142:   aload_0
L143:   aload_0
L144:   getfield Field ZKARKDQW C I
L147:   newarray int
L149:   putfield Field ZKARKDQW G [I
L152:   aload_0
L153:   aload_0
L154:   getfield Field ZKARKDQW C I
L157:   newarray int
L159:   putfield Field ZKARKDQW H [I
L162:   aload_0
L163:   aload_0
L164:   getfield Field ZKARKDQW C I
L167:   newarray int
L169:   putfield Field ZKARKDQW I [I
L172:   iconst_0
L173:   istore 5
L175:   iload 9
L177:   ifeq L228
L180:   aload_0
L181:   getfield Field ZKARKDQW G [I
L184:   iload 5
L186:   aload 4
L188:   getfield Field ZKARKDQW G [I
L191:   iload 5
L193:   iaload
L194:   iastore
L195:   aload_0
L196:   getfield Field ZKARKDQW H [I
L199:   iload 5
L201:   aload 4
L203:   getfield Field ZKARKDQW H [I
L206:   iload 5
L208:   iaload
L209:   iastore
L210:   aload_0
L211:   getfield Field ZKARKDQW I [I
L214:   iload 5
L216:   aload 4
L218:   getfield Field ZKARKDQW I [I
L221:   iload 5
L223:   iaload
L224:   iastore
L225:   iinc 5 1
L228:   iload 5
L230:   aload_0
L231:   getfield Field ZKARKDQW C I
L234:   if_icmplt L180
L237:   aload_0
L238:   aload_0
L239:   getfield Field ZKARKDQW C I
L242:   newarray int
L244:   putfield Field ZKARKDQW J [I
L247:   aload 4
L249:   getfield Field ZKARKDQW J [I
L252:   ifnonnull L286
L255:   iconst_0
L256:   istore 6
L258:   iload 9
L260:   ifeq L274
L263:   aload_0
L264:   getfield Field ZKARKDQW J [I
L267:   iload 6
L269:   iconst_0
L270:   iastore
L271:   iinc 6 1
L274:   iload 6
L276:   aload_0
L277:   getfield Field ZKARKDQW C I
L280:   if_icmplt L263
L283:   goto L321
L286:   iconst_0
L287:   istore 6
L289:   iload 9
L291:   ifeq L312
L294:   aload_0
L295:   getfield Field ZKARKDQW J [I
L298:   iload 6
L300:   aload 4
L302:   getfield Field ZKARKDQW J [I
L305:   iload 6
L307:   iaload
L308:   iastore
L309:   iinc 6 1
L312:   iload 6
L314:   aload_0
L315:   getfield Field ZKARKDQW C I
L318:   if_icmplt L294
L321:   aload_0
L322:   aload_0
L323:   getfield Field ZKARKDQW y I
L326:   anewarray RJXWGZGD
L329:   putfield Field XHHRODPC j [LRJXWGZGD;
L332:   iconst_0
L333:   istore 6
L335:   iload 9
L337:   ifeq L410
L340:   aload_0
L341:   getfield Field XHHRODPC j [LRJXWGZGD;
L344:   iload 6
L346:   new RJXWGZGD
L349:   dup
L350:   invokespecial Method RJXWGZGD <init> ()V
L353:   dup_x2
L354:   aastore
L355:   astore 7
L357:   aload 4
L359:   getfield Field XHHRODPC j [LRJXWGZGD;
L362:   iload 6
L364:   aaload
L365:   astore 8
L367:   aload 7
L369:   aload 8
L371:   getfield Field RJXWGZGD a I
L374:   putfield Field RJXWGZGD a I
L377:   aload 7
L379:   aload 8
L381:   getfield Field RJXWGZGD b I
L384:   putfield Field RJXWGZGD b I
L387:   aload 7
L389:   aload 8
L391:   getfield Field RJXWGZGD c I
L394:   putfield Field RJXWGZGD c I
L397:   aload 7
L399:   aload 8
L401:   getfield Field RJXWGZGD d I
L404:   putfield Field RJXWGZGD d I
L407:   iinc 6 1
L410:   iload 6
L412:   aload_0
L413:   getfield Field ZKARKDQW y I
L416:   if_icmplt L340
L419:   aload_0
L420:   aload 4
L422:   getfield Field ZKARKDQW gb [LRJXWGZGD;
L425:   putfield Field ZKARKDQW gb [LRJXWGZGD;
L428:   iload 9
L430:   ifeq L469
L433:   aload_0
L434:   aload 4
L436:   getfield Field ZKARKDQW G [I
L439:   putfield Field ZKARKDQW G [I
L442:   aload_0
L443:   aload 4
L445:   getfield Field ZKARKDQW H [I
L448:   putfield Field ZKARKDQW H [I
L451:   aload_0
L452:   aload 4
L454:   getfield Field ZKARKDQW I [I
L457:   putfield Field ZKARKDQW I [I
L460:   aload_0
L461:   aload 4
L463:   getfield Field ZKARKDQW J [I
L466:   putfield Field ZKARKDQW J [I
L469:   aload_0
L470:   aload 4
L472:   getfield Field ZKARKDQW z [I
L475:   putfield Field ZKARKDQW z [I
L478:   aload_0
L479:   aload 4
L481:   getfield Field ZKARKDQW B [I
L484:   putfield Field ZKARKDQW B [I
L487:   aload_0
L488:   aload 4
L490:   getfield Field ZKARKDQW M [I
L493:   putfield Field ZKARKDQW M [I
L496:   aload_0
L497:   aload 4
L499:   getfield Field ZKARKDQW L [I
L502:   putfield Field ZKARKDQW L [I
L505:   aload_0
L506:   aload 4
L508:   getfield Field ZKARKDQW K [I
L511:   putfield Field ZKARKDQW K [I
L514:   aload_0
L515:   aload 4
L517:   getfield Field ZKARKDQW N I
L520:   putfield Field ZKARKDQW N I
L523:   aload_0
L524:   aload 4
L526:   getfield Field ZKARKDQW D [I
L529:   putfield Field ZKARKDQW D [I
L532:   aload_0
L533:   aload 4
L535:   getfield Field ZKARKDQW E [I
L538:   putfield Field ZKARKDQW E [I
L541:   aload_0
L542:   aload 4
L544:   getfield Field ZKARKDQW F [I
L547:   putfield Field ZKARKDQW F [I
L550:   aload_0
L551:   aload 4
L553:   getfield Field ZKARKDQW P [I
L556:   putfield Field ZKARKDQW P [I
L559:   aload_0
L560:   aload 4
L562:   getfield Field ZKARKDQW Q [I
L565:   putfield Field ZKARKDQW Q [I
L568:   aload_0
L569:   aload 4
L571:   getfield Field ZKARKDQW R [I
L574:   putfield Field ZKARKDQW R [I
L577:   aload_0
L578:   aload 4
L580:   getfield Field XHHRODPC k I
L583:   putfield Field XHHRODPC k I
L586:   aload_0
L587:   aload 4
L589:   getfield Field ZKARKDQW X I
L592:   putfield Field ZKARKDQW X I
L595:   iload 9
L597:   ifeq L608
L600:   new java/lang/NullPointerException
L603:   dup
L604:   invokespecial Method java/lang/NullPointerException <init> ()V
L607:   athrow
L608:   iload_2
L609:   ifge L600
L612:   aload_0
L613:   aload 4
L615:   getfield Field ZKARKDQW W I
L618:   putfield Field ZKARKDQW W I
L621:   aload_0
L622:   aload 4
L624:   getfield Field ZKARKDQW Z I
L627:   putfield Field ZKARKDQW Z I
L630:   aload_0
L631:   aload 4
L633:   getfield Field ZKARKDQW Y I
L636:   putfield Field ZKARKDQW Y I
L639:   aload_0
L640:   aload 4
L642:   getfield Field ZKARKDQW S I
L645:   putfield Field ZKARKDQW S I
L648:   aload_0
L649:   aload 4
L651:   getfield Field ZKARKDQW U I
L654:   putfield Field ZKARKDQW U I
L657:   aload_0
L658:   aload 4
L660:   getfield Field ZKARKDQW V I
L663:   putfield Field ZKARKDQW V I
L666:   aload_0
L667:   aload 4
L669:   getfield Field ZKARKDQW T I
L672:   putfield Field ZKARKDQW T I
L675:   return
L676:   astore 5
L678:   new java/lang/StringBuffer
L681:   dup
L682:   ldc "16425, "
L684:   invokespecial Method java/lang/StringBuffer <init> (Ljava/lang/String;)V
L687:   iload_1
L688:   invokevirtual Method java/lang/StringBuffer append (Z)Ljava/lang/StringBuffer;
L691:   ldc ", "
L693:   invokevirtual Method java/lang/StringBuffer append (Ljava/lang/String;)Ljava/lang/StringBuffer;
L696:   iload_2
L697:   invokevirtual Method java/lang/StringBuffer append (I)Ljava/lang/StringBuffer;
L700:   ldc ", "
L702:   invokevirtual Method java/lang/StringBuffer append (Ljava/lang/String;)Ljava/lang/StringBuffer;
L705:   iload_3
L706:   invokevirtual Method java/lang/StringBuffer append (Z)Ljava/lang/StringBuffer;
L709:   ldc ", "
L711:   invokevirtual Method java/lang/StringBuffer append (Ljava/lang/String;)Ljava/lang/StringBuffer;
L714:   aload 4
L716:   invokevirtual Method java/lang/StringBuffer append (Ljava/lang/Object;)Ljava/lang/StringBuffer;
L719:   ldc ", "
L721:   invokevirtual Method java/lang/StringBuffer append (Ljava/lang/String;)Ljava/lang/StringBuffer;
L724:   aload 5
L726:   invokevirtual Method java/lang/Throwable toString ()Ljava/lang/String;
L729:   invokevirtual Method java/lang/StringBuffer append (Ljava/lang/String;)Ljava/lang/StringBuffer;
L732:   invokevirtual Method java/lang/StringBuffer toString ()Ljava/lang/String;
L735:   invokestatic Method sign/signlink reporterror (Ljava/lang/String;)V
L738:   new java/lang/RuntimeException
L741:   dup
L742:   invokespecial Method java/lang/RuntimeException <init> ()V
L745:   athrow
L746:   
    .end code
.end method

.method public a : (ILZKARKDQW;Z)V
    .code stack 5 locals 7
L0:     getstatic Field XHHRODPC l Z
L3:     istore 6
        .catch java/lang/RuntimeException from L5 to L420 using L421
L5:     aload_0
L6:     aload_2
L7:     getfield Field ZKARKDQW y I
L10:    putfield Field ZKARKDQW y I
L13:    iload_1
L14:    bipush 7
L16:    if_icmpeq L35
L19:    iconst_1
L20:    istore 4
L22:    iload 6
L24:    ifeq L30
L27:    iinc 4 1
L30:    iload 4
L32:    ifgt L27
L35:    aload_0
L36:    aload_2
L37:    getfield Field ZKARKDQW C I
L40:    putfield Field ZKARKDQW C I
L43:    aload_0
L44:    aload_2
L45:    getfield Field ZKARKDQW O I
L48:    putfield Field ZKARKDQW O I
L51:    getstatic Field ZKARKDQW u [I
L54:    arraylength
L55:    aload_0
L56:    getfield Field ZKARKDQW y I
L59:    if_icmpge L98
L62:    aload_0
L63:    getfield Field ZKARKDQW y I
L66:    bipush 100
L68:    iadd
L69:    newarray int
L71:    putstatic Field ZKARKDQW u [I
L74:    aload_0
L75:    getfield Field ZKARKDQW y I
L78:    bipush 100
L80:    iadd
L81:    newarray int
L83:    putstatic Field ZKARKDQW v [I
L86:    aload_0
L87:    getfield Field ZKARKDQW y I
L90:    bipush 100
L92:    iadd
L93:    newarray int
L95:    putstatic Field ZKARKDQW w [I
L98:    aload_0
L99:    getstatic Field ZKARKDQW u [I
L102:   putfield Field ZKARKDQW z [I
L105:   aload_0
L106:   getstatic Field ZKARKDQW v [I
L109:   putfield Field ZKARKDQW A [I
L112:   aload_0
L113:   getstatic Field ZKARKDQW w [I
L116:   putfield Field ZKARKDQW B [I
L119:   iconst_0
L120:   istore 4
L122:   iload 6
L124:   ifeq L172
L127:   aload_0
L128:   getfield Field ZKARKDQW z [I
L131:   iload 4
L133:   aload_2
L134:   getfield Field ZKARKDQW z [I
L137:   iload 4
L139:   iaload
L140:   iastore
L141:   aload_0
L142:   getfield Field ZKARKDQW A [I
L145:   iload 4
L147:   aload_2
L148:   getfield Field ZKARKDQW A [I
L151:   iload 4
L153:   iaload
L154:   iastore
L155:   aload_0
L156:   getfield Field ZKARKDQW B [I
L159:   iload 4
L161:   aload_2
L162:   getfield Field ZKARKDQW B [I
L165:   iload 4
L167:   iaload
L168:   iastore
L169:   iinc 4 1
L172:   iload 4
L174:   aload_0
L175:   getfield Field ZKARKDQW y I
L178:   if_icmplt L127
L181:   iload_3
L182:   ifeq L198
L185:   aload_0
L186:   aload_2
L187:   getfield Field ZKARKDQW L [I
L190:   putfield Field ZKARKDQW L [I
L193:   iload 6
L195:   ifeq L300
L198:   getstatic Field ZKARKDQW x [I
L201:   arraylength
L202:   aload_0
L203:   getfield Field ZKARKDQW C I
L206:   if_icmpge L221
L209:   aload_0
L210:   getfield Field ZKARKDQW C I
L213:   bipush 100
L215:   iadd
L216:   newarray int
L218:   putstatic Field ZKARKDQW x [I
L221:   aload_0
L222:   getstatic Field ZKARKDQW x [I
L225:   putfield Field ZKARKDQW L [I
L228:   aload_2
L229:   getfield Field ZKARKDQW L [I
L232:   ifnonnull L266
L235:   iconst_0
L236:   istore 5
L238:   iload 6
L240:   ifeq L254
L243:   aload_0
L244:   getfield Field ZKARKDQW L [I
L247:   iload 5
L249:   iconst_0
L250:   iastore
L251:   iinc 5 1
L254:   iload 5
L256:   aload_0
L257:   getfield Field ZKARKDQW C I
L260:   if_icmplt L243
L263:   goto L300
L266:   iconst_0
L267:   istore 5
L269:   iload 6
L271:   ifeq L291
L274:   aload_0
L275:   getfield Field ZKARKDQW L [I
L278:   iload 5
L280:   aload_2
L281:   getfield Field ZKARKDQW L [I
L284:   iload 5
L286:   iaload
L287:   iastore
L288:   iinc 5 1
L291:   iload 5
L293:   aload_0
L294:   getfield Field ZKARKDQW C I
L297:   if_icmplt L274
L300:   aload_0
L301:   aload_2
L302:   getfield Field ZKARKDQW J [I
L305:   putfield Field ZKARKDQW J [I
L308:   aload_0
L309:   aload_2
L310:   getfield Field ZKARKDQW M [I
L313:   putfield Field ZKARKDQW M [I
L316:   aload_0
L317:   aload_2
L318:   getfield Field ZKARKDQW K [I
L321:   putfield Field ZKARKDQW K [I
L324:   aload_0
L325:   aload_2
L326:   getfield Field ZKARKDQW N I
L329:   putfield Field ZKARKDQW N I
L332:   aload_0
L333:   aload_2
L334:   getfield Field ZKARKDQW eb [[I
L337:   putfield Field ZKARKDQW eb [[I
L340:   aload_0
L341:   aload_2
L342:   getfield Field ZKARKDQW db [[I
L345:   putfield Field ZKARKDQW db [[I
L348:   aload_0
L349:   aload_2
L350:   getfield Field ZKARKDQW D [I
L353:   putfield Field ZKARKDQW D [I
L356:   aload_0
L357:   aload_2
L358:   getfield Field ZKARKDQW E [I
L361:   putfield Field ZKARKDQW E [I
L364:   aload_0
L365:   aload_2
L366:   getfield Field ZKARKDQW F [I
L369:   putfield Field ZKARKDQW F [I
L372:   aload_0
L373:   aload_2
L374:   getfield Field ZKARKDQW G [I
L377:   putfield Field ZKARKDQW G [I
L380:   aload_0
L381:   aload_2
L382:   getfield Field ZKARKDQW H [I
L385:   putfield Field ZKARKDQW H [I
L388:   aload_0
L389:   aload_2
L390:   getfield Field ZKARKDQW I [I
L393:   putfield Field ZKARKDQW I [I
L396:   aload_0
L397:   aload_2
L398:   getfield Field ZKARKDQW P [I
L401:   putfield Field ZKARKDQW P [I
L404:   aload_0
L405:   aload_2
L406:   getfield Field ZKARKDQW Q [I
L409:   putfield Field ZKARKDQW Q [I
L412:   aload_0
L413:   aload_2
L414:   getfield Field ZKARKDQW R [I
L417:   putfield Field ZKARKDQW R [I
L420:   return
L421:   astore 4
L423:   new java/lang/StringBuffer
L426:   dup
L427:   ldc "18331, "
L429:   invokespecial Method java/lang/StringBuffer <init> (Ljava/lang/String;)V
L432:   iload_1
L433:   invokevirtual Method java/lang/StringBuffer append (I)Ljava/lang/StringBuffer;
L436:   ldc ", "
L438:   invokevirtual Method java/lang/StringBuffer append (Ljava/lang/String;)Ljava/lang/StringBuffer;
L441:   aload_2
L442:   invokevirtual Method java/lang/StringBuffer append (Ljava/lang/Object;)Ljava/lang/StringBuffer;
L445:   ldc ", "
L447:   invokevirtual Method java/lang/StringBuffer append (Ljava/lang/String;)Ljava/lang/StringBuffer;
L450:   iload_3
L451:   invokevirtual Method java/lang/StringBuffer append (Z)Ljava/lang/StringBuffer;
L454:   ldc ", "
L456:   invokevirtual Method java/lang/StringBuffer append (Ljava/lang/String;)Ljava/lang/StringBuffer;
L459:   aload 4
L461:   invokevirtual Method java/lang/Throwable toString ()Ljava/lang/String;
L464:   invokevirtual Method java/lang/StringBuffer append (Ljava/lang/String;)Ljava/lang/StringBuffer;
L467:   invokevirtual Method java/lang/StringBuffer toString ()Ljava/lang/String;
L470:   invokestatic Method sign/signlink reporterror (Ljava/lang/String;)V
L473:   new java/lang/RuntimeException
L476:   dup
L477:   invokespecial Method java/lang/RuntimeException <init> ()V
L480:   athrow
L481:   
    .end code
.end method

.method private final a : (LZKARKDQW;I)I
    .code stack 5 locals 9
L0:     getstatic Field XHHRODPC l Z
L3:     istore 8
L5:     iconst_m1
L6:     istore_3
L7:     aload_1
L8:     getfield Field ZKARKDQW z [I
L11:    iload_2
L12:    iaload
L13:    istore 4
L15:    aload_1
L16:    getfield Field ZKARKDQW A [I
L19:    iload_2
L20:    iaload
L21:    istore 5
L23:    aload_1
L24:    getfield Field ZKARKDQW B [I
L27:    iload_2
L28:    iaload
L29:    istore 6
L31:    iconst_0
L32:    istore 7
L34:    iload 8
L36:    ifeq L86
L39:    iload 4
L41:    aload_0
L42:    getfield Field ZKARKDQW z [I
L45:    iload 7
L47:    iaload
L48:    if_icmpne L83
L51:    iload 5
L53:    aload_0
L54:    getfield Field ZKARKDQW A [I
L57:    iload 7
L59:    iaload
L60:    if_icmpne L83
L63:    iload 6
L65:    aload_0
L66:    getfield Field ZKARKDQW B [I
L69:    iload 7
L71:    iaload
L72:    if_icmpne L83
L75:    iload 7
L77:    istore_3
L78:    iload 8
L80:    ifeq L95
L83:    iinc 7 1
L86:    iload 7
L88:    aload_0
L89:    getfield Field ZKARKDQW y I
L92:    if_icmplt L39
L95:    iload_3
L96:    iconst_m1
L97:    if_icmpne L167
L100:   aload_0
L101:   getfield Field ZKARKDQW z [I
L104:   aload_0
L105:   getfield Field ZKARKDQW y I
L108:   iload 4
L110:   iastore
L111:   aload_0
L112:   getfield Field ZKARKDQW A [I
L115:   aload_0
L116:   getfield Field ZKARKDQW y I
L119:   iload 5
L121:   iastore
L122:   aload_0
L123:   getfield Field ZKARKDQW B [I
L126:   aload_0
L127:   getfield Field ZKARKDQW y I
L130:   iload 6
L132:   iastore
L133:   aload_1
L134:   getfield Field ZKARKDQW bb [I
L137:   ifnull L155
L140:   aload_0
L141:   getfield Field ZKARKDQW bb [I
L144:   aload_0
L145:   getfield Field ZKARKDQW y I
L148:   aload_1
L149:   getfield Field ZKARKDQW bb [I
L152:   iload_2
L153:   iaload
L154:   iastore
L155:   aload_0
L156:   dup
L157:   getfield Field ZKARKDQW y I
L160:   dup_x1
L161:   iconst_1
L162:   iadd
L163:   putfield Field ZKARKDQW y I
L166:   istore_3
L167:   iload_3
L168:   ireturn
L169:   
    .end code
.end method

.method public a : (Z)V
    .code stack 7 locals 7
        .catch java/lang/RuntimeException from L0 to L211 using L212
L0:     aload_0
L1:     iconst_0
L2:     putfield Field XHHRODPC k I
L5:     aload_0
L6:     iconst_0
L7:     putfield Field ZKARKDQW W I
L10:    aload_0
L11:    iconst_0
L12:    putfield Field ZKARKDQW X I
L15:    iconst_0
L16:    istore_2
L17:    getstatic Field XHHRODPC l Z
L20:    ifeq L107
L23:    aload_0
L24:    getfield Field ZKARKDQW z [I
L27:    iload_2
L28:    iaload
L29:    istore_3
L30:    aload_0
L31:    getfield Field ZKARKDQW A [I
L34:    iload_2
L35:    iaload
L36:    istore 4
L38:    aload_0
L39:    getfield Field ZKARKDQW B [I
L42:    iload_2
L43:    iaload
L44:    istore 5
L46:    iload 4
L48:    ineg
L49:    aload_0
L50:    getfield Field XHHRODPC k I
L53:    if_icmple L63
L56:    aload_0
L57:    iload 4
L59:    ineg
L60:    putfield Field XHHRODPC k I
L63:    iload 4
L65:    aload_0
L66:    getfield Field ZKARKDQW X I
L69:    if_icmple L78
L72:    aload_0
L73:    iload 4
L75:    putfield Field ZKARKDQW X I
L78:    iload_3
L79:    iload_3
L80:    imul
L81:    iload 5
L83:    iload 5
L85:    imul
L86:    iadd
L87:    istore 6
L89:    iload 6
L91:    aload_0
L92:    getfield Field ZKARKDQW W I
L95:    if_icmple L104
L98:    aload_0
L99:    iload 6
L101:   putfield Field ZKARKDQW W I
L104:   iinc 2 1
L107:   iload_2
L108:   aload_0
L109:   getfield Field ZKARKDQW y I
L112:   if_icmplt L23
L115:   iload_1
L116:   ifeq L125
L119:   sipush 455
L122:   putstatic Field ZKARKDQW r I
L125:   aload_0
L126:   aload_0
L127:   getfield Field ZKARKDQW W I
L130:   i2d
L131:   invokestatic Method java/lang/Math sqrt (D)D
L134:   ldc2_w 9.9e-1
L137:   dadd
L138:   d2i
L139:   putfield Field ZKARKDQW W I
L142:   aload_0
L143:   aload_0
L144:   getfield Field ZKARKDQW W I
L147:   aload_0
L148:   getfield Field ZKARKDQW W I
L151:   imul
L152:   aload_0
L153:   getfield Field XHHRODPC k I
L156:   aload_0
L157:   getfield Field XHHRODPC k I
L160:   imul
L161:   iadd
L162:   i2d
L163:   invokestatic Method java/lang/Math sqrt (D)D
L166:   ldc2_w 9.9e-1
L169:   dadd
L170:   d2i
L171:   putfield Field ZKARKDQW Z I
L174:   aload_0
L175:   aload_0
L176:   getfield Field ZKARKDQW Z I
L179:   aload_0
L180:   getfield Field ZKARKDQW W I
L183:   aload_0
L184:   getfield Field ZKARKDQW W I
L187:   imul
L188:   aload_0
L189:   getfield Field ZKARKDQW X I
L192:   aload_0
L193:   getfield Field ZKARKDQW X I
L196:   imul
L197:   iadd
L198:   i2d
L199:   invokestatic Method java/lang/Math sqrt (D)D
L202:   ldc2_w 9.9e-1
L205:   dadd
L206:   d2i
L207:   iadd
L208:   putfield Field ZKARKDQW Y I
L211:   return
L212:   astore_2
L213:   new java/lang/StringBuffer
L216:   dup
L217:   ldc "41353, "
L219:   invokespecial Method java/lang/StringBuffer <init> (Ljava/lang/String;)V
L222:   iload_1
L223:   invokevirtual Method java/lang/StringBuffer append (Z)Ljava/lang/StringBuffer;
L226:   ldc ", "
L228:   invokevirtual Method java/lang/StringBuffer append (Ljava/lang/String;)Ljava/lang/StringBuffer;
L231:   aload_2
L232:   invokevirtual Method java/lang/Throwable toString ()Ljava/lang/String;
L235:   invokevirtual Method java/lang/StringBuffer append (Ljava/lang/String;)Ljava/lang/StringBuffer;
L238:   invokevirtual Method java/lang/StringBuffer toString ()Ljava/lang/String;
L241:   invokestatic Method sign/signlink reporterror (Ljava/lang/String;)V
L244:   new java/lang/RuntimeException
L247:   dup
L248:   invokespecial Method java/lang/RuntimeException <init> ()V
L251:   athrow
L252:   
    .end code
.end method

.method public b : (Z)V
    .code stack 7 locals 4
        .catch java/lang/RuntimeException from L0 to L153 using L154
L0:     aload_0
L1:     iconst_0
L2:     putfield Field XHHRODPC k I
L5:     aload_0
L6:     iconst_0
L7:     putfield Field ZKARKDQW X I
L10:    iload_1
L11:    ifeq L30
L14:    aload_0
L15:    aload_0
L16:    getfield Field ZKARKDQW n Z
L19:    ifeq L26
L22:    iconst_0
L23:    goto L27
L26:    iconst_1
L27:    putfield Field ZKARKDQW n Z
L30:    iconst_0
L31:    istore_2
L32:    getstatic Field XHHRODPC l Z
L35:    ifeq L76
L38:    aload_0
L39:    getfield Field ZKARKDQW A [I
L42:    iload_2
L43:    iaload
L44:    istore_3
L45:    iload_3
L46:    ineg
L47:    aload_0
L48:    getfield Field XHHRODPC k I
L51:    if_icmple L60
L54:    aload_0
L55:    iload_3
L56:    ineg
L57:    putfield Field XHHRODPC k I
L60:    iload_3
L61:    aload_0
L62:    getfield Field ZKARKDQW X I
L65:    if_icmple L73
L68:    aload_0
L69:    iload_3
L70:    putfield Field ZKARKDQW X I
L73:    iinc 2 1
L76:    iload_2
L77:    aload_0
L78:    getfield Field ZKARKDQW y I
L81:    if_icmplt L38
L84:    aload_0
L85:    aload_0
L86:    getfield Field ZKARKDQW W I
L89:    aload_0
L90:    getfield Field ZKARKDQW W I
L93:    imul
L94:    aload_0
L95:    getfield Field XHHRODPC k I
L98:    aload_0
L99:    getfield Field XHHRODPC k I
L102:   imul
L103:   iadd
L104:   i2d
L105:   invokestatic Method java/lang/Math sqrt (D)D
L108:   ldc2_w 9.9e-1
L111:   dadd
L112:   d2i
L113:   putfield Field ZKARKDQW Z I
L116:   aload_0
L117:   aload_0
L118:   getfield Field ZKARKDQW Z I
L121:   aload_0
L122:   getfield Field ZKARKDQW W I
L125:   aload_0
L126:   getfield Field ZKARKDQW W I
L129:   imul
L130:   aload_0
L131:   getfield Field ZKARKDQW X I
L134:   aload_0
L135:   getfield Field ZKARKDQW X I
L138:   imul
L139:   iadd
L140:   i2d
L141:   invokestatic Method java/lang/Math sqrt (D)D
L144:   ldc2_w 9.9e-1
L147:   dadd
L148:   d2i
L149:   iadd
L150:   putfield Field ZKARKDQW Y I
L153:   return
L154:   astore_2
L155:   new java/lang/StringBuffer
L158:   dup
L159:   ldc "87212, "
L161:   invokespecial Method java/lang/StringBuffer <init> (Ljava/lang/String;)V
L164:   iload_1
L165:   invokevirtual Method java/lang/StringBuffer append (Z)Ljava/lang/StringBuffer;
L168:   ldc ", "
L170:   invokevirtual Method java/lang/StringBuffer append (Ljava/lang/String;)Ljava/lang/StringBuffer;
L173:   aload_2
L174:   invokevirtual Method java/lang/Throwable toString ()Ljava/lang/String;
L177:   invokevirtual Method java/lang/StringBuffer append (Ljava/lang/String;)Ljava/lang/StringBuffer;
L180:   invokevirtual Method java/lang/StringBuffer toString ()Ljava/lang/String;
L183:   invokestatic Method sign/signlink reporterror (Ljava/lang/String;)V
L186:   new java/lang/RuntimeException
L189:   dup
L190:   invokespecial Method java/lang/RuntimeException <init> ()V
L193:   athrow
L194:   
    .end code
.end method

.method public d : (I)V
    .code stack 6 locals 7
        .catch java/lang/RuntimeException from L0 to L277 using L278
L0:     aload_0
L1:     iconst_0
L2:     putfield Field XHHRODPC k I
L5:     aload_0
L6:     iconst_0
L7:     putfield Field ZKARKDQW W I
L10:    aload_0
L11:    iconst_0
L12:    putfield Field ZKARKDQW X I
L15:    aload_0
L16:    ldc 999999
L18:    putfield Field ZKARKDQW S I
L21:    aload_0
L22:    ldc -999999
L24:    putfield Field ZKARKDQW T I
L27:    aload_0
L28:    ldc -99999
L30:    putfield Field ZKARKDQW U I
L33:    aload_0
L34:    ldc 99999
L36:    putfield Field ZKARKDQW V I
L39:    iconst_0
L40:    istore_2
L41:    getstatic Field XHHRODPC l Z
L44:    ifeq L187
L47:    aload_0
L48:    getfield Field ZKARKDQW z [I
L51:    iload_2
L52:    iaload
L53:    istore_3
L54:    aload_0
L55:    getfield Field ZKARKDQW A [I
L58:    iload_2
L59:    iaload
L60:    istore 4
L62:    aload_0
L63:    getfield Field ZKARKDQW B [I
L66:    iload_2
L67:    iaload
L68:    istore 5
L70:    iload_3
L71:    aload_0
L72:    getfield Field ZKARKDQW S I
L75:    if_icmpge L83
L78:    aload_0
L79:    iload_3
L80:    putfield Field ZKARKDQW S I
L83:    iload_3
L84:    aload_0
L85:    getfield Field ZKARKDQW T I
L88:    if_icmple L96
L91:    aload_0
L92:    iload_3
L93:    putfield Field ZKARKDQW T I
L96:    iload 5
L98:    aload_0
L99:    getfield Field ZKARKDQW V I
L102:   if_icmpge L111
L105:   aload_0
L106:   iload 5
L108:   putfield Field ZKARKDQW V I
L111:   iload 5
L113:   aload_0
L114:   getfield Field ZKARKDQW U I
L117:   if_icmple L126
L120:   aload_0
L121:   iload 5
L123:   putfield Field ZKARKDQW U I
L126:   iload 4
L128:   ineg
L129:   aload_0
L130:   getfield Field XHHRODPC k I
L133:   if_icmple L143
L136:   aload_0
L137:   iload 4
L139:   ineg
L140:   putfield Field XHHRODPC k I
L143:   iload 4
L145:   aload_0
L146:   getfield Field ZKARKDQW X I
L149:   if_icmple L158
L152:   aload_0
L153:   iload 4
L155:   putfield Field ZKARKDQW X I
L158:   iload_3
L159:   iload_3
L160:   imul
L161:   iload 5
L163:   iload 5
L165:   imul
L166:   iadd
L167:   istore 6
L169:   iload 6
L171:   aload_0
L172:   getfield Field ZKARKDQW W I
L175:   if_icmple L184
L178:   aload_0
L179:   iload 6
L181:   putfield Field ZKARKDQW W I
L184:   iinc 2 1
L187:   iload_2
L188:   aload_0
L189:   getfield Field ZKARKDQW y I
L192:   if_icmplt L47
L195:   aload_0
L196:   aload_0
L197:   getfield Field ZKARKDQW W I
L200:   i2d
L201:   invokestatic Method java/lang/Math sqrt (D)D
L204:   d2i
L205:   putfield Field ZKARKDQW W I
L208:   aload_0
L209:   aload_0
L210:   getfield Field ZKARKDQW W I
L213:   aload_0
L214:   getfield Field ZKARKDQW W I
L217:   imul
L218:   aload_0
L219:   getfield Field XHHRODPC k I
L222:   aload_0
L223:   getfield Field XHHRODPC k I
L226:   imul
L227:   iadd
L228:   i2d
L229:   invokestatic Method java/lang/Math sqrt (D)D
L232:   d2i
L233:   putfield Field ZKARKDQW Z I
L236:   iload_1
L237:   sipush 21073
L240:   if_icmpeq L244
L243:   return
L244:   aload_0
L245:   aload_0
L246:   getfield Field ZKARKDQW Z I
L249:   aload_0
L250:   getfield Field ZKARKDQW W I
L253:   aload_0
L254:   getfield Field ZKARKDQW W I
L257:   imul
L258:   aload_0
L259:   getfield Field ZKARKDQW X I
L262:   aload_0
L263:   getfield Field ZKARKDQW X I
L266:   imul
L267:   iadd
L268:   i2d
L269:   invokestatic Method java/lang/Math sqrt (D)D
L272:   d2i
L273:   iadd
L274:   putfield Field ZKARKDQW Y I
L277:   return
L278:   astore_2
L279:   new java/lang/StringBuffer
L282:   dup
L283:   ldc "2042, "
L285:   invokespecial Method java/lang/StringBuffer <init> (Ljava/lang/String;)V
L288:   iload_1
L289:   invokevirtual Method java/lang/StringBuffer append (I)Ljava/lang/StringBuffer;
L292:   ldc ", "
L294:   invokevirtual Method java/lang/StringBuffer append (Ljava/lang/String;)Ljava/lang/StringBuffer;
L297:   aload_2
L298:   invokevirtual Method java/lang/Throwable toString ()Ljava/lang/String;
L301:   invokevirtual Method java/lang/StringBuffer append (Ljava/lang/String;)Ljava/lang/StringBuffer;
L304:   invokevirtual Method java/lang/StringBuffer toString ()Ljava/lang/String;
L307:   invokestatic Method sign/signlink reporterror (Ljava/lang/String;)V
L310:   new java/lang/RuntimeException
L313:   dup
L314:   invokespecial Method java/lang/RuntimeException <init> ()V
L317:   athrow
L318:   
    .end code
.end method

.method public a : (B)V
    .code stack 7 locals 9
L0:     getstatic Field XHHRODPC l Z
L3:     istore 8
        .catch java/lang/RuntimeException from L5 to L345 using L346
L5:     iload_1
L6:     bipush -71
L8:     if_icmpeq L25
L11:    iconst_1
L12:    istore_2
L13:    iload 8
L15:    ifeq L21
L18:    iinc 2 1
L21:    iload_2
L22:    ifgt L18
L25:    aload_0
L26:    getfield Field ZKARKDQW bb [I
L29:    ifnull L185
L32:    sipush 256
L35:    newarray int
L37:    astore_2
L38:    iconst_0
L39:    istore_3
L40:    iconst_0
L41:    istore 4
L43:    iload 8
L45:    ifeq L77
L48:    aload_0
L49:    getfield Field ZKARKDQW bb [I
L52:    iload 4
L54:    iaload
L55:    istore 5
L57:    aload_2
L58:    iload 5
L60:    dup2
L61:    iaload
L62:    iconst_1
L63:    iadd
L64:    iastore
L65:    iload 5
L67:    iload_3
L68:    if_icmple L74
L71:    iload 5
L73:    istore_3
L74:    iinc 4 1
L77:    iload 4
L79:    aload_0
L80:    getfield Field ZKARKDQW y I
L83:    if_icmplt L48
L86:    aload_0
L87:    iload_3
L88:    iconst_1
L89:    iadd
L90:    multianewarray [[I 1
L94:    putfield Field ZKARKDQW db [[I
L97:    iconst_0
L98:    istore 5
L100:   iload 8
L102:   ifeq L126
L105:   aload_0
L106:   getfield Field ZKARKDQW db [[I
L109:   iload 5
L111:   aload_2
L112:   iload 5
L114:   iaload
L115:   newarray int
L117:   aastore
L118:   aload_2
L119:   iload 5
L121:   iconst_0
L122:   iastore
L123:   iinc 5 1
L126:   iload 5
L128:   iload_3
L129:   if_icmple L105
L132:   iconst_0
L133:   istore 6
L135:   iload 8
L137:   ifeq L171
L140:   aload_0
L141:   getfield Field ZKARKDQW bb [I
L144:   iload 6
L146:   iaload
L147:   istore 7
L149:   aload_0
L150:   getfield Field ZKARKDQW db [[I
L153:   iload 7
L155:   aaload
L156:   aload_2
L157:   iload 7
L159:   dup2
L160:   iaload
L161:   dup_x2
L162:   iconst_1
L163:   iadd
L164:   iastore
L165:   iload 6
L167:   iastore
L168:   iinc 6 1
L171:   iload 6
L173:   aload_0
L174:   getfield Field ZKARKDQW y I
L177:   if_icmplt L140
L180:   aload_0
L181:   aconst_null
L182:   putfield Field ZKARKDQW bb [I
L185:   aload_0
L186:   getfield Field ZKARKDQW cb [I
L189:   ifnull L386
L192:   sipush 256
L195:   newarray int
L197:   astore_2
L198:   iconst_0
L199:   istore_3
L200:   iconst_0
L201:   istore 4
L203:   iload 8
L205:   ifeq L237
L208:   aload_0
L209:   getfield Field ZKARKDQW cb [I
L212:   iload 4
L214:   iaload
L215:   istore 5
L217:   aload_2
L218:   iload 5
L220:   dup2
L221:   iaload
L222:   iconst_1
L223:   iadd
L224:   iastore
L225:   iload 5
L227:   iload_3
L228:   if_icmple L234
L231:   iload 5
L233:   istore_3
L234:   iinc 4 1
L237:   iload 4
L239:   aload_0
L240:   getfield Field ZKARKDQW C I
L243:   if_icmplt L208
L246:   aload_0
L247:   iload_3
L248:   iconst_1
L249:   iadd
L250:   multianewarray [[I 1
L254:   putfield Field ZKARKDQW eb [[I
L257:   iconst_0
L258:   istore 5
L260:   iload 8
L262:   ifeq L286
L265:   aload_0
L266:   getfield Field ZKARKDQW eb [[I
L269:   iload 5
L271:   aload_2
L272:   iload 5
L274:   iaload
L275:   newarray int
L277:   aastore
L278:   aload_2
L279:   iload 5
L281:   iconst_0
L282:   iastore
L283:   iinc 5 1
L286:   iload 5
L288:   iload_3
L289:   if_icmple L265
L292:   iconst_0
L293:   istore 6
L295:   iload 8
L297:   ifeq L331
L300:   aload_0
L301:   getfield Field ZKARKDQW cb [I
L304:   iload 6
L306:   iaload
L307:   istore 7
L309:   aload_0
L310:   getfield Field ZKARKDQW eb [[I
L313:   iload 7
L315:   aaload
L316:   aload_2
L317:   iload 7
L319:   dup2
L320:   iaload
L321:   dup_x2
L322:   iconst_1
L323:   iadd
L324:   iastore
L325:   iload 6
L327:   iastore
L328:   iinc 6 1
L331:   iload 6
L333:   aload_0
L334:   getfield Field ZKARKDQW C I
L337:   if_icmplt L300
L340:   aload_0
L341:   aconst_null
L342:   putfield Field ZKARKDQW cb [I
L345:   return
L346:   astore_2
L347:   new java/lang/StringBuffer
L350:   dup
L351:   ldc "96395, "
L353:   invokespecial Method java/lang/StringBuffer <init> (Ljava/lang/String;)V
L356:   iload_1
L357:   invokevirtual Method java/lang/StringBuffer append (I)Ljava/lang/StringBuffer;
L360:   ldc ", "
L362:   invokevirtual Method java/lang/StringBuffer append (Ljava/lang/String;)Ljava/lang/StringBuffer;
L365:   aload_2
L366:   invokevirtual Method java/lang/Throwable toString ()Ljava/lang/String;
L369:   invokevirtual Method java/lang/StringBuffer append (Ljava/lang/String;)Ljava/lang/StringBuffer;
L372:   invokevirtual Method java/lang/StringBuffer toString ()Ljava/lang/String;
L375:   invokestatic Method sign/signlink reporterror (Ljava/lang/String;)V
L378:   new java/lang/RuntimeException
L381:   dup
L382:   invokespecial Method java/lang/RuntimeException <init> ()V
L385:   athrow
L386:   return
L387:   
    .end code
.end method

.method public c : (II)V
    .code stack 8 locals 7
        .catch java/lang/RuntimeException from L0 to L124 using L125
L0:     aload_0
L1:     getfield Field ZKARKDQW db [[I
L4:     ifnonnull L8
L7:     return
L8:     iload_1
L9:     iconst_m1
L10:    if_icmpne L14
L13:    return
L14:    aload_0
L15:    getfield Field ZKARKDQW m I
L18:    iload_1
L19:    invokestatic Method SQHJOGRT a (II)LSQHJOGRT;
L22:    astore_3
L23:    aload_3
L24:    ifnonnull L28
L27:    return
L28:    aload_3
L29:    getfield Field SQHJOGRT d LKVCQPLIW;
L32:    astore 4
L34:    iload_2
L35:    ldc 40542
L37:    if_icmpeq L41
L40:    return
L41:    iconst_0
L42:    putstatic Field ZKARKDQW Bb I
L45:    iconst_0
L46:    putstatic Field ZKARKDQW Cb I
L49:    iconst_0
L50:    putstatic Field ZKARKDQW Db I
L53:    iconst_0
L54:    istore 5
L56:    getstatic Field XHHRODPC l Z
L59:    ifeq L115
L62:    aload_3
L63:    getfield Field SQHJOGRT f [I
L66:    iload 5
L68:    iaload
L69:    istore 6
L71:    aload_0
L72:    aload 4
L74:    getfield Field KVCQPLIW c [I
L77:    iload 6
L79:    iaload
L80:    aload 4
L82:    getfield Field KVCQPLIW d [[I
L85:    iload 6
L87:    aaload
L88:    aload_3
L89:    getfield Field SQHJOGRT g [I
L92:    iload 5
L94:    iaload
L95:    aload_3
L96:    getfield Field SQHJOGRT h [I
L99:    iload 5
L101:   iaload
L102:   aload_3
L103:   getfield Field SQHJOGRT i [I
L106:   iload 5
L108:   iaload
L109:   invokespecial Method ZKARKDQW a (I[IIII)V
L112:   iinc 5 1
L115:   iload 5
L117:   aload_3
L118:   getfield Field SQHJOGRT e I
L121:   if_icmplt L62
L124:   return
L125:   astore_3
L126:   new java/lang/StringBuffer
L129:   dup
L130:   ldc "77052, "
L132:   invokespecial Method java/lang/StringBuffer <init> (Ljava/lang/String;)V
L135:   iload_1
L136:   invokevirtual Method java/lang/StringBuffer append (I)Ljava/lang/StringBuffer;
L139:   ldc ", "
L141:   invokevirtual Method java/lang/StringBuffer append (Ljava/lang/String;)Ljava/lang/StringBuffer;
L144:   iload_2
L145:   invokevirtual Method java/lang/StringBuffer append (I)Ljava/lang/StringBuffer;
L148:   ldc ", "
L150:   invokevirtual Method java/lang/StringBuffer append (Ljava/lang/String;)Ljava/lang/StringBuffer;
L153:   aload_3
L154:   invokevirtual Method java/lang/Throwable toString ()Ljava/lang/String;
L157:   invokevirtual Method java/lang/StringBuffer append (Ljava/lang/String;)Ljava/lang/StringBuffer;
L160:   invokevirtual Method java/lang/StringBuffer toString ()Ljava/lang/String;
L163:   invokestatic Method sign/signlink reporterror (Ljava/lang/String;)V
L166:   new java/lang/RuntimeException
L169:   dup
L170:   invokespecial Method java/lang/RuntimeException <init> ()V
L173:   athrow
L174:   
    .end code
.end method

.method public a : (I[III)V
    .code stack 8 locals 14
L0:     getstatic Field XHHRODPC l Z
L3:     istore 13
        .catch java/lang/RuntimeException from L5 to L362 using L363
L5:     iload 4
L7:     iconst_m1
L8:     if_icmpne L12
L11:    return
L12:    aload_2
L13:    ifnull L21
L16:    iload_3
L17:    iconst_m1
L18:    if_icmpne L30
L21:    aload_0
L22:    iload 4
L24:    ldc 40542
L26:    invokevirtual Method ZKARKDQW c (II)V
L29:    return
L30:    aload_0
L31:    getfield Field ZKARKDQW m I
L34:    iload 4
L36:    invokestatic Method SQHJOGRT a (II)LSQHJOGRT;
L39:    astore 5
L41:    aload 5
L43:    ifnonnull L47
L46:    return
L47:    aload_0
L48:    getfield Field ZKARKDQW m I
L51:    iload_3
L52:    invokestatic Method SQHJOGRT a (II)LSQHJOGRT;
L55:    astore 6
L57:    iload_1
L58:    sipush -20491
L61:    if_icmpeq L65
L64:    return
L65:    aload 6
L67:    ifnonnull L79
L70:    aload_0
L71:    iload 4
L73:    ldc 40542
L75:    invokevirtual Method ZKARKDQW c (II)V
L78:    return
L79:    aload 5
L81:    getfield Field SQHJOGRT d LKVCQPLIW;
L84:    astore 7
L86:    iconst_0
L87:    putstatic Field ZKARKDQW Bb I
L90:    iconst_0
L91:    putstatic Field ZKARKDQW Cb I
L94:    iconst_0
L95:    putstatic Field ZKARKDQW Db I
L98:    iconst_0
L99:    istore 8
L101:   aload_2
L102:   iload 8
L104:   iinc 8 1
L107:   iaload
L108:   istore 9
L110:   iconst_0
L111:   istore 10
L113:   iload 13
L115:   ifeq L214
L118:   aload 5
L120:   getfield Field SQHJOGRT f [I
L123:   iload 10
L125:   iaload
L126:   istore 11
L128:   iload 13
L130:   ifeq L142
L133:   aload_2
L134:   iload 8
L136:   iinc 8 1
L139:   iaload
L140:   istore 9
L142:   iload 11
L144:   iload 9
L146:   if_icmpgt L133
L149:   iload 11
L151:   iload 9
L153:   if_icmpne L167
L156:   aload 7
L158:   getfield Field KVCQPLIW c [I
L161:   iload 11
L163:   iaload
L164:   ifne L211
L167:   aload_0
L168:   aload 7
L170:   getfield Field KVCQPLIW c [I
L173:   iload 11
L175:   iaload
L176:   aload 7
L178:   getfield Field KVCQPLIW d [[I
L181:   iload 11
L183:   aaload
L184:   aload 5
L186:   getfield Field SQHJOGRT g [I
L189:   iload 10
L191:   iaload
L192:   aload 5
L194:   getfield Field SQHJOGRT h [I
L197:   iload 10
L199:   iaload
L200:   aload 5
L202:   getfield Field SQHJOGRT i [I
L205:   iload 10
L207:   iaload
L208:   invokespecial Method ZKARKDQW a (I[IIII)V
L211:   iinc 10 1
L214:   iload 10
L216:   aload 5
L218:   getfield Field SQHJOGRT e I
L221:   if_icmplt L118
L224:   iconst_0
L225:   putstatic Field ZKARKDQW Bb I
L228:   iconst_0
L229:   putstatic Field ZKARKDQW Cb I
L232:   iconst_0
L233:   putstatic Field ZKARKDQW Db I
L236:   iconst_0
L237:   istore 8
L239:   aload_2
L240:   iload 8
L242:   iinc 8 1
L245:   iaload
L246:   istore 9
L248:   iconst_0
L249:   istore 11
L251:   iload 13
L253:   ifeq L352
L256:   aload 6
L258:   getfield Field SQHJOGRT f [I
L261:   iload 11
L263:   iaload
L264:   istore 12
L266:   iload 13
L268:   ifeq L280
L271:   aload_2
L272:   iload 8
L274:   iinc 8 1
L277:   iaload
L278:   istore 9
L280:   iload 12
L282:   iload 9
L284:   if_icmpgt L271
L287:   iload 12
L289:   iload 9
L291:   if_icmpeq L305
L294:   aload 7
L296:   getfield Field KVCQPLIW c [I
L299:   iload 12
L301:   iaload
L302:   ifne L349
L305:   aload_0
L306:   aload 7
L308:   getfield Field KVCQPLIW c [I
L311:   iload 12
L313:   iaload
L314:   aload 7
L316:   getfield Field KVCQPLIW d [[I
L319:   iload 12
L321:   aaload
L322:   aload 6
L324:   getfield Field SQHJOGRT g [I
L327:   iload 11
L329:   iaload
L330:   aload 6
L332:   getfield Field SQHJOGRT h [I
L335:   iload 11
L337:   iaload
L338:   aload 6
L340:   getfield Field SQHJOGRT i [I
L343:   iload 11
L345:   iaload
L346:   invokespecial Method ZKARKDQW a (I[IIII)V
L349:   iinc 11 1
L352:   iload 11
L354:   aload 6
L356:   getfield Field SQHJOGRT e I
L359:   if_icmplt L256
L362:   return
L363:   astore 5
L365:   new java/lang/StringBuffer
L368:   dup
L369:   ldc "63853, "
L371:   invokespecial Method java/lang/StringBuffer <init> (Ljava/lang/String;)V
L374:   iload_1
L375:   invokevirtual Method java/lang/StringBuffer append (I)Ljava/lang/StringBuffer;
L378:   ldc ", "
L380:   invokevirtual Method java/lang/StringBuffer append (Ljava/lang/String;)Ljava/lang/StringBuffer;
L383:   aload_2
L384:   invokevirtual Method java/lang/StringBuffer append (Ljava/lang/Object;)Ljava/lang/StringBuffer;
L387:   ldc ", "
L389:   invokevirtual Method java/lang/StringBuffer append (Ljava/lang/String;)Ljava/lang/StringBuffer;
L392:   iload_3
L393:   invokevirtual Method java/lang/StringBuffer append (I)Ljava/lang/StringBuffer;
L396:   ldc ", "
L398:   invokevirtual Method java/lang/StringBuffer append (Ljava/lang/String;)Ljava/lang/StringBuffer;
L401:   iload 4
L403:   invokevirtual Method java/lang/StringBuffer append (I)Ljava/lang/StringBuffer;
L406:   ldc ", "
L408:   invokevirtual Method java/lang/StringBuffer append (Ljava/lang/String;)Ljava/lang/StringBuffer;
L411:   aload 5
L413:   invokevirtual Method java/lang/Throwable toString ()Ljava/lang/String;
L416:   invokevirtual Method java/lang/StringBuffer append (Ljava/lang/String;)Ljava/lang/StringBuffer;
L419:   invokevirtual Method java/lang/StringBuffer toString ()Ljava/lang/String;
L422:   invokestatic Method sign/signlink reporterror (Ljava/lang/String;)V
L425:   new java/lang/RuntimeException
L428:   dup
L429:   invokespecial Method java/lang/RuntimeException <init> ()V
L432:   athrow
L433:   
    .end code
.end method

.method private a : (I[IIII)V
    .code stack 6 locals 19
L0:     getstatic Field XHHRODPC l Z
L3:     istore 18
L5:     aload_2
L6:     arraylength
L7:     istore 6
L9:     iload_1
L10:    ifne L198
L13:    iconst_0
L14:    istore 7
L16:    iconst_0
L17:    putstatic Field ZKARKDQW Bb I
L20:    iconst_0
L21:    putstatic Field ZKARKDQW Cb I
L24:    iconst_0
L25:    putstatic Field ZKARKDQW Db I
L28:    iconst_0
L29:    istore 8
L31:    iload 18
L33:    ifeq L135
L36:    aload_2
L37:    iload 8
L39:    iaload
L40:    istore 9
L42:    iload 9
L44:    aload_0
L45:    getfield Field ZKARKDQW db [[I
L48:    arraylength
L49:    if_icmpge L132
L52:    aload_0
L53:    getfield Field ZKARKDQW db [[I
L56:    iload 9
L58:    aaload
L59:    astore 10
L61:    iconst_0
L62:    istore 11
L64:    iload 18
L66:    ifeq L124
L69:    aload 10
L71:    iload 11
L73:    iaload
L74:    istore 12
L76:    getstatic Field ZKARKDQW Bb I
L79:    aload_0
L80:    getfield Field ZKARKDQW z [I
L83:    iload 12
L85:    iaload
L86:    iadd
L87:    putstatic Field ZKARKDQW Bb I
L90:    getstatic Field ZKARKDQW Cb I
L93:    aload_0
L94:    getfield Field ZKARKDQW A [I
L97:    iload 12
L99:    iaload
L100:   iadd
L101:   putstatic Field ZKARKDQW Cb I
L104:   getstatic Field ZKARKDQW Db I
L107:   aload_0
L108:   getfield Field ZKARKDQW B [I
L111:   iload 12
L113:   iaload
L114:   iadd
L115:   putstatic Field ZKARKDQW Db I
L118:   iinc 7 1
L121:   iinc 11 1
L124:   iload 11
L126:   aload 10
L128:   arraylength
L129:   if_icmplt L69
L132:   iinc 8 1
L135:   iload 8
L137:   iload 6
L139:   if_icmplt L36
L142:   iload 7
L144:   ifle L183
L147:   getstatic Field ZKARKDQW Bb I
L150:   iload 7
L152:   idiv
L153:   iload_3
L154:   iadd
L155:   putstatic Field ZKARKDQW Bb I
L158:   getstatic Field ZKARKDQW Cb I
L161:   iload 7
L163:   idiv
L164:   iload 4
L166:   iadd
L167:   putstatic Field ZKARKDQW Cb I
L170:   getstatic Field ZKARKDQW Db I
L173:   iload 7
L175:   idiv
L176:   iload 5
L178:   iadd
L179:   putstatic Field ZKARKDQW Db I
L182:   return
L183:   iload_3
L184:   putstatic Field ZKARKDQW Bb I
L187:   iload 4
L189:   putstatic Field ZKARKDQW Cb I
L192:   iload 5
L194:   putstatic Field ZKARKDQW Db I
L197:   return
L198:   iload_1
L199:   iconst_1
L200:   if_icmpne L308
L203:   iconst_0
L204:   istore 7
L206:   iload 18
L208:   ifeq L300
L211:   aload_2
L212:   iload 7
L214:   iaload
L215:   istore 8
L217:   iload 8
L219:   aload_0
L220:   getfield Field ZKARKDQW db [[I
L223:   arraylength
L224:   if_icmpge L297
L227:   aload_0
L228:   getfield Field ZKARKDQW db [[I
L231:   iload 8
L233:   aaload
L234:   astore 9
L236:   iconst_0
L237:   istore 10
L239:   iload 18
L241:   ifeq L289
L244:   aload 9
L246:   iload 10
L248:   iaload
L249:   istore 11
L251:   aload_0
L252:   getfield Field ZKARKDQW z [I
L255:   iload 11
L257:   dup2
L258:   iaload
L259:   iload_3
L260:   iadd
L261:   iastore
L262:   aload_0
L263:   getfield Field ZKARKDQW A [I
L266:   iload 11
L268:   dup2
L269:   iaload
L270:   iload 4
L272:   iadd
L273:   iastore
L274:   aload_0
L275:   getfield Field ZKARKDQW B [I
L278:   iload 11
L280:   dup2
L281:   iaload
L282:   iload 5
L284:   iadd
L285:   iastore
L286:   iinc 10 1
L289:   iload 10
L291:   aload 9
L293:   arraylength
L294:   if_icmplt L244
L297:   iinc 7 1
L300:   iload 7
L302:   iload 6
L304:   if_icmplt L211
L307:   return
L308:   iload_1
L309:   iconst_2
L310:   if_icmpne L754
L313:   iconst_0
L314:   istore 7
L316:   iload 18
L318:   ifeq L746
L321:   aload_2
L322:   iload 7
L324:   iaload
L325:   istore 8
L327:   iload 8
L329:   aload_0
L330:   getfield Field ZKARKDQW db [[I
L333:   arraylength
L334:   if_icmpge L743
L337:   aload_0
L338:   getfield Field ZKARKDQW db [[I
L341:   iload 8
L343:   aaload
L344:   astore 9
L346:   iconst_0
L347:   istore 10
L349:   iload 18
L351:   ifeq L735
L354:   aload 9
L356:   iload 10
L358:   iaload
L359:   istore 11
L361:   aload_0
L362:   getfield Field ZKARKDQW z [I
L365:   iload 11
L367:   dup2
L368:   iaload
L369:   getstatic Field ZKARKDQW Bb I
L372:   isub
L373:   iastore
L374:   aload_0
L375:   getfield Field ZKARKDQW A [I
L378:   iload 11
L380:   dup2
L381:   iaload
L382:   getstatic Field ZKARKDQW Cb I
L385:   isub
L386:   iastore
L387:   aload_0
L388:   getfield Field ZKARKDQW B [I
L391:   iload 11
L393:   dup2
L394:   iaload
L395:   getstatic Field ZKARKDQW Db I
L398:   isub
L399:   iastore
L400:   iload_3
L401:   sipush 255
L404:   iand
L405:   bipush 8
L407:   imul
L408:   istore 12
L410:   iload 4
L412:   sipush 255
L415:   iand
L416:   bipush 8
L418:   imul
L419:   istore 13
L421:   iload 5
L423:   sipush 255
L426:   iand
L427:   bipush 8
L429:   imul
L430:   istore 14
L432:   iload 14
L434:   ifeq L519
L437:   getstatic Field ZKARKDQW Jb [I
L440:   iload 14
L442:   iaload
L443:   istore 15
L445:   getstatic Field ZKARKDQW Kb [I
L448:   iload 14
L450:   iaload
L451:   istore 16
L453:   aload_0
L454:   getfield Field ZKARKDQW A [I
L457:   iload 11
L459:   iaload
L460:   iload 15
L462:   imul
L463:   aload_0
L464:   getfield Field ZKARKDQW z [I
L467:   iload 11
L469:   iaload
L470:   iload 16
L472:   imul
L473:   iadd
L474:   bipush 16
L476:   ishr
L477:   istore 17
L479:   aload_0
L480:   getfield Field ZKARKDQW A [I
L483:   iload 11
L485:   aload_0
L486:   getfield Field ZKARKDQW A [I
L489:   iload 11
L491:   iaload
L492:   iload 16
L494:   imul
L495:   aload_0
L496:   getfield Field ZKARKDQW z [I
L499:   iload 11
L501:   iaload
L502:   iload 15
L504:   imul
L505:   isub
L506:   bipush 16
L508:   ishr
L509:   iastore
L510:   aload_0
L511:   getfield Field ZKARKDQW z [I
L514:   iload 11
L516:   iload 17
L518:   iastore
L519:   iload 12
L521:   ifeq L606
L524:   getstatic Field ZKARKDQW Jb [I
L527:   iload 12
L529:   iaload
L530:   istore 15
L532:   getstatic Field ZKARKDQW Kb [I
L535:   iload 12
L537:   iaload
L538:   istore 16
L540:   aload_0
L541:   getfield Field ZKARKDQW A [I
L544:   iload 11
L546:   iaload
L547:   iload 16
L549:   imul
L550:   aload_0
L551:   getfield Field ZKARKDQW B [I
L554:   iload 11
L556:   iaload
L557:   iload 15
L559:   imul
L560:   isub
L561:   bipush 16
L563:   ishr
L564:   istore 17
L566:   aload_0
L567:   getfield Field ZKARKDQW B [I
L570:   iload 11
L572:   aload_0
L573:   getfield Field ZKARKDQW A [I
L576:   iload 11
L578:   iaload
L579:   iload 15
L581:   imul
L582:   aload_0
L583:   getfield Field ZKARKDQW B [I
L586:   iload 11
L588:   iaload
L589:   iload 16
L591:   imul
L592:   iadd
L593:   bipush 16
L595:   ishr
L596:   iastore
L597:   aload_0
L598:   getfield Field ZKARKDQW A [I
L601:   iload 11
L603:   iload 17
L605:   iastore
L606:   iload 13
L608:   ifeq L693
L611:   getstatic Field ZKARKDQW Jb [I
L614:   iload 13
L616:   iaload
L617:   istore 15
L619:   getstatic Field ZKARKDQW Kb [I
L622:   iload 13
L624:   iaload
L625:   istore 16
L627:   aload_0
L628:   getfield Field ZKARKDQW B [I
L631:   iload 11
L633:   iaload
L634:   iload 15
L636:   imul
L637:   aload_0
L638:   getfield Field ZKARKDQW z [I
L641:   iload 11
L643:   iaload
L644:   iload 16
L646:   imul
L647:   iadd
L648:   bipush 16
L650:   ishr
L651:   istore 17
L653:   aload_0
L654:   getfield Field ZKARKDQW B [I
L657:   iload 11
L659:   aload_0
L660:   getfield Field ZKARKDQW B [I
L663:   iload 11
L665:   iaload
L666:   iload 16
L668:   imul
L669:   aload_0
L670:   getfield Field ZKARKDQW z [I
L673:   iload 11
L675:   iaload
L676:   iload 15
L678:   imul
L679:   isub
L680:   bipush 16
L682:   ishr
L683:   iastore
L684:   aload_0
L685:   getfield Field ZKARKDQW z [I
L688:   iload 11
L690:   iload 17
L692:   iastore
L693:   aload_0
L694:   getfield Field ZKARKDQW z [I
L697:   iload 11
L699:   dup2
L700:   iaload
L701:   getstatic Field ZKARKDQW Bb I
L704:   iadd
L705:   iastore
L706:   aload_0
L707:   getfield Field ZKARKDQW A [I
L710:   iload 11
L712:   dup2
L713:   iaload
L714:   getstatic Field ZKARKDQW Cb I
L717:   iadd
L718:   iastore
L719:   aload_0
L720:   getfield Field ZKARKDQW B [I
L723:   iload 11
L725:   dup2
L726:   iaload
L727:   getstatic Field ZKARKDQW Db I
L730:   iadd
L731:   iastore
L732:   iinc 10 1
L735:   iload 10
L737:   aload 9
L739:   arraylength
L740:   if_icmplt L354
L743:   iinc 7 1
L746:   iload 7
L748:   iload 6
L750:   if_icmplt L321
L753:   return
L754:   iload_1
L755:   iconst_3
L756:   if_icmpne L969
L759:   iconst_0
L760:   istore 7
L762:   iload 18
L764:   ifeq L961
L767:   aload_2
L768:   iload 7
L770:   iaload
L771:   istore 8
L773:   iload 8
L775:   aload_0
L776:   getfield Field ZKARKDQW db [[I
L779:   arraylength
L780:   if_icmpge L958
L783:   aload_0
L784:   getfield Field ZKARKDQW db [[I
L787:   iload 8
L789:   aaload
L790:   astore 9
L792:   iconst_0
L793:   istore 10
L795:   iload 18
L797:   ifeq L950
L800:   aload 9
L802:   iload 10
L804:   iaload
L805:   istore 11
L807:   aload_0
L808:   getfield Field ZKARKDQW z [I
L811:   iload 11
L813:   dup2
L814:   iaload
L815:   getstatic Field ZKARKDQW Bb I
L818:   isub
L819:   iastore
L820:   aload_0
L821:   getfield Field ZKARKDQW A [I
L824:   iload 11
L826:   dup2
L827:   iaload
L828:   getstatic Field ZKARKDQW Cb I
L831:   isub
L832:   iastore
L833:   aload_0
L834:   getfield Field ZKARKDQW B [I
L837:   iload 11
L839:   dup2
L840:   iaload
L841:   getstatic Field ZKARKDQW Db I
L844:   isub
L845:   iastore
L846:   aload_0
L847:   getfield Field ZKARKDQW z [I
L850:   iload 11
L852:   aload_0
L853:   getfield Field ZKARKDQW z [I
L856:   iload 11
L858:   iaload
L859:   iload_3
L860:   imul
L861:   sipush 128
L864:   idiv
L865:   iastore
L866:   aload_0
L867:   getfield Field ZKARKDQW A [I
L870:   iload 11
L872:   aload_0
L873:   getfield Field ZKARKDQW A [I
L876:   iload 11
L878:   iaload
L879:   iload 4
L881:   imul
L882:   sipush 128
L885:   idiv
L886:   iastore
L887:   aload_0
L888:   getfield Field ZKARKDQW B [I
L891:   iload 11
L893:   aload_0
L894:   getfield Field ZKARKDQW B [I
L897:   iload 11
L899:   iaload
L900:   iload 5
L902:   imul
L903:   sipush 128
L906:   idiv
L907:   iastore
L908:   aload_0
L909:   getfield Field ZKARKDQW z [I
L912:   iload 11
L914:   dup2
L915:   iaload
L916:   getstatic Field ZKARKDQW Bb I
L919:   iadd
L920:   iastore
L921:   aload_0
L922:   getfield Field ZKARKDQW A [I
L925:   iload 11
L927:   dup2
L928:   iaload
L929:   getstatic Field ZKARKDQW Cb I
L932:   iadd
L933:   iastore
L934:   aload_0
L935:   getfield Field ZKARKDQW B [I
L938:   iload 11
L940:   dup2
L941:   iaload
L942:   getstatic Field ZKARKDQW Db I
L945:   iadd
L946:   iastore
L947:   iinc 10 1
L950:   iload 10
L952:   aload 9
L954:   arraylength
L955:   if_icmplt L800
L958:   iinc 7 1
L961:   iload 7
L963:   iload 6
L965:   if_icmplt L767
L968:   return
L969:   iload_1
L970:   iconst_5
L971:   if_icmpne L1113
L974:   aload_0
L975:   getfield Field ZKARKDQW eb [[I
L978:   ifnull L1112
L981:   aload_0
L982:   getfield Field ZKARKDQW L [I
L985:   ifnull L1112
L988:   iconst_0
L989:   istore 7
L991:   iload 18
L993:   ifeq L1105
L996:   aload_2
L997:   iload 7
L999:   iaload
L1000:  istore 8
L1002:  iload 8
L1004:  aload_0
L1005:  getfield Field ZKARKDQW eb [[I
L1008:  arraylength
L1009:  if_icmpge L1102
L1012:  aload_0
L1013:  getfield Field ZKARKDQW eb [[I
L1016:  iload 8
L1018:  aaload
L1019:  astore 9
L1021:  iconst_0
L1022:  istore 10
L1024:  iload 18
L1026:  ifeq L1094
L1029:  aload 9
L1031:  iload 10
L1033:  iaload
L1034:  istore 11
L1036:  aload_0
L1037:  getfield Field ZKARKDQW L [I
L1040:  iload 11
L1042:  dup2
L1043:  iaload
L1044:  iload_3
L1045:  bipush 8
L1047:  imul
L1048:  iadd
L1049:  iastore
L1050:  aload_0
L1051:  getfield Field ZKARKDQW L [I
L1054:  iload 11
L1056:  iaload
L1057:  ifge L1068
L1060:  aload_0
L1061:  getfield Field ZKARKDQW L [I
L1064:  iload 11
L1066:  iconst_0
L1067:  iastore
L1068:  aload_0
L1069:  getfield Field ZKARKDQW L [I
L1072:  iload 11
L1074:  iaload
L1075:  sipush 255
L1078:  if_icmple L1091
L1081:  aload_0
L1082:  getfield Field ZKARKDQW L [I
L1085:  iload 11
L1087:  sipush 255
L1090:  iastore
L1091:  iinc 10 1
L1094:  iload 10
L1096:  aload 9
L1098:  arraylength
L1099:  if_icmplt L1029
L1102:  iinc 7 1
L1105:  iload 7
L1107:  iload 6
L1109:  if_icmplt L996
L1112:  return
L1113:  return
L1114:  
    .end code
.end method

.method public e : (I)V
    .code stack 5 locals 4
        .catch java/lang/RuntimeException from L0 to L51 using L52
L0:     iload_1
L1:     ifgt L5
L4:     return
L5:     iconst_0
L6:     istore_2
L7:     getstatic Field XHHRODPC l Z
L10:    ifeq L43
L13:    aload_0
L14:    getfield Field ZKARKDQW z [I
L17:    iload_2
L18:    iaload
L19:    istore_3
L20:    aload_0
L21:    getfield Field ZKARKDQW z [I
L24:    iload_2
L25:    aload_0
L26:    getfield Field ZKARKDQW B [I
L29:    iload_2
L30:    iaload
L31:    iastore
L32:    aload_0
L33:    getfield Field ZKARKDQW B [I
L36:    iload_2
L37:    iload_3
L38:    ineg
L39:    iastore
L40:    iinc 2 1
L43:    iload_2
L44:    aload_0
L45:    getfield Field ZKARKDQW y I
L48:    if_icmplt L13
L51:    return
L52:    astore_2
L53:    new java/lang/StringBuffer
L56:    dup
L57:    ldc "59385, "
L59:    invokespecial Method java/lang/StringBuffer <init> (Ljava/lang/String;)V
L62:    iload_1
L63:    invokevirtual Method java/lang/StringBuffer append (I)Ljava/lang/StringBuffer;
L66:    ldc ", "
L68:    invokevirtual Method java/lang/StringBuffer append (Ljava/lang/String;)Ljava/lang/StringBuffer;
L71:    aload_2
L72:    invokevirtual Method java/lang/Throwable toString ()Ljava/lang/String;
L75:    invokevirtual Method java/lang/StringBuffer append (Ljava/lang/String;)Ljava/lang/StringBuffer;
L78:    invokevirtual Method java/lang/StringBuffer toString ()Ljava/lang/String;
L81:    invokestatic Method sign/signlink reporterror (Ljava/lang/String;)V
L84:    new java/lang/RuntimeException
L87:    dup
L88:    invokespecial Method java/lang/RuntimeException <init> ()V
L91:    athrow
L92:    
    .end code
.end method

.method public d : (II)V
    .code stack 6 locals 7
        .catch java/lang/RuntimeException from L0 to L121 using L122
L0:     getstatic Field ZKARKDQW Jb [I
L3:     iload_1
L4:     iaload
L5:     istore_3
L6:     getstatic Field ZKARKDQW Kb [I
L9:     iload_1
L10:    iaload
L11:    istore 4
L13:    iconst_0
L14:    istore 5
L16:    getstatic Field XHHRODPC l Z
L19:    ifeq L89
L22:    aload_0
L23:    getfield Field ZKARKDQW A [I
L26:    iload 5
L28:    iaload
L29:    iload 4
L31:    imul
L32:    aload_0
L33:    getfield Field ZKARKDQW B [I
L36:    iload 5
L38:    iaload
L39:    iload_3
L40:    imul
L41:    isub
L42:    bipush 16
L44:    ishr
L45:    istore 6
L47:    aload_0
L48:    getfield Field ZKARKDQW B [I
L51:    iload 5
L53:    aload_0
L54:    getfield Field ZKARKDQW A [I
L57:    iload 5
L59:    iaload
L60:    iload_3
L61:    imul
L62:    aload_0
L63:    getfield Field ZKARKDQW B [I
L66:    iload 5
L68:    iaload
L69:    iload 4
L71:    imul
L72:    iadd
L73:    bipush 16
L75:    ishr
L76:    iastore
L77:    aload_0
L78:    getfield Field ZKARKDQW A [I
L81:    iload 5
L83:    iload 6
L85:    iastore
L86:    iinc 5 1
L89:    iload 5
L91:    aload_0
L92:    getfield Field ZKARKDQW y I
L95:    if_icmplt L22
L98:    iload_2
L99:    aload_0
L100:   getfield Field ZKARKDQW p I
L103:   if_icmplt L114
L106:   iload_2
L107:   aload_0
L108:   getfield Field ZKARKDQW p I
L111:   if_icmple L121
L114:   aload_0
L115:   sipush 324
L118:   putfield Field ZKARKDQW p I
L121:   return
L122:   astore_3
L123:   new java/lang/StringBuffer
L126:   dup
L127:   ldc "13317, "
L129:   invokespecial Method java/lang/StringBuffer <init> (Ljava/lang/String;)V
L132:   iload_1
L133:   invokevirtual Method java/lang/StringBuffer append (I)Ljava/lang/StringBuffer;
L136:   ldc ", "
L138:   invokevirtual Method java/lang/StringBuffer append (Ljava/lang/String;)Ljava/lang/StringBuffer;
L141:   iload_2
L142:   invokevirtual Method java/lang/StringBuffer append (I)Ljava/lang/StringBuffer;
L145:   ldc ", "
L147:   invokevirtual Method java/lang/StringBuffer append (Ljava/lang/String;)Ljava/lang/StringBuffer;
L150:   aload_3
L151:   invokevirtual Method java/lang/Throwable toString ()Ljava/lang/String;
L154:   invokevirtual Method java/lang/StringBuffer append (Ljava/lang/String;)Ljava/lang/StringBuffer;
L157:   invokevirtual Method java/lang/StringBuffer toString ()Ljava/lang/String;
L160:   invokestatic Method sign/signlink reporterror (Ljava/lang/String;)V
L163:   new java/lang/RuntimeException
L166:   dup
L167:   invokespecial Method java/lang/RuntimeException <init> ()V
L170:   athrow
L171:   
    .end code
.end method

.method public a : (IIII)V
    .code stack 5 locals 6
        .catch java/lang/RuntimeException from L0 to L69 using L70
L0:     iload_3
L1:     sipush 16384
L4:     if_icmpeq L14
L7:     aload_0
L8:     sipush -132
L11:    putfield Field ZKARKDQW m I
L14:    iconst_0
L15:    istore 5
L17:    getstatic Field XHHRODPC l Z
L20:    ifeq L60
L23:    aload_0
L24:    getfield Field ZKARKDQW z [I
L27:    iload 5
L29:    dup2
L30:    iaload
L31:    iload_1
L32:    iadd
L33:    iastore
L34:    aload_0
L35:    getfield Field ZKARKDQW A [I
L38:    iload 5
L40:    dup2
L41:    iaload
L42:    iload_2
L43:    iadd
L44:    iastore
L45:    aload_0
L46:    getfield Field ZKARKDQW B [I
L49:    iload 5
L51:    dup2
L52:    iaload
L53:    iload 4
L55:    iadd
L56:    iastore
L57:    iinc 5 1
L60:    iload 5
L62:    aload_0
L63:    getfield Field ZKARKDQW y I
L66:    if_icmplt L23
L69:    return
L70:    astore 5
L72:    new java/lang/StringBuffer
L75:    dup
L76:    ldc "1706, "
L78:    invokespecial Method java/lang/StringBuffer <init> (Ljava/lang/String;)V
L81:    iload_1
L82:    invokevirtual Method java/lang/StringBuffer append (I)Ljava/lang/StringBuffer;
L85:    ldc ", "
L87:    invokevirtual Method java/lang/StringBuffer append (Ljava/lang/String;)Ljava/lang/StringBuffer;
L90:    iload_2
L91:    invokevirtual Method java/lang/StringBuffer append (I)Ljava/lang/StringBuffer;
L94:    ldc ", "
L96:    invokevirtual Method java/lang/StringBuffer append (Ljava/lang/String;)Ljava/lang/StringBuffer;
L99:    iload_3
L100:   invokevirtual Method java/lang/StringBuffer append (I)Ljava/lang/StringBuffer;
L103:   ldc ", "
L105:   invokevirtual Method java/lang/StringBuffer append (Ljava/lang/String;)Ljava/lang/StringBuffer;
L108:   iload 4
L110:   invokevirtual Method java/lang/StringBuffer append (I)Ljava/lang/StringBuffer;
L113:   ldc ", "
L115:   invokevirtual Method java/lang/StringBuffer append (Ljava/lang/String;)Ljava/lang/StringBuffer;
L118:   aload 5
L120:   invokevirtual Method java/lang/Throwable toString ()Ljava/lang/String;
L123:   invokevirtual Method java/lang/StringBuffer append (Ljava/lang/String;)Ljava/lang/StringBuffer;
L126:   invokevirtual Method java/lang/StringBuffer toString ()Ljava/lang/String;
L129:   invokestatic Method sign/signlink reporterror (Ljava/lang/String;)V
L132:   new java/lang/RuntimeException
L135:   dup
L136:   invokespecial Method java/lang/RuntimeException <init> ()V
L139:   athrow
L140:   
    .end code
.end method

.method public e : (II)V
    .code stack 4 locals 4
L0:     iconst_0
L1:     istore_3
L2:     getstatic Field XHHRODPC l Z
L5:     ifeq L28
L8:     aload_0
L9:     getfield Field ZKARKDQW M [I
L12:    iload_3
L13:    iaload
L14:    iload_1
L15:    if_icmpne L25
L18:    aload_0
L19:    getfield Field ZKARKDQW M [I
L22:    iload_3
L23:    iload_2
L24:    iastore
L25:    iinc 3 1
L28:    iload_3
L29:    aload_0
L30:    getfield Field ZKARKDQW C I
L33:    if_icmplt L8
L36:    return
L37:    
    .end code
.end method

.method public f : (I)V
    .code stack 5 locals 6
L0:     getstatic Field XHHRODPC l Z
L3:     istore 5
        .catch java/lang/RuntimeException from L5 to L91 using L92
L5:     iconst_0
L6:     istore_2
L7:     iload 5
L9:     ifeq L28
L12:    aload_0
L13:    getfield Field ZKARKDQW B [I
L16:    iload_2
L17:    aload_0
L18:    getfield Field ZKARKDQW B [I
L21:    iload_2
L22:    iaload
L23:    ineg
L24:    iastore
L25:    iinc 2 1
L28:    iload_2
L29:    aload_0
L30:    getfield Field ZKARKDQW y I
L33:    if_icmplt L12
L36:    iconst_0
L37:    istore_3
L38:    iload 5
L40:    ifeq L74
L43:    aload_0
L44:    getfield Field ZKARKDQW D [I
L47:    iload_3
L48:    iaload
L49:    istore 4
L51:    aload_0
L52:    getfield Field ZKARKDQW D [I
L55:    iload_3
L56:    aload_0
L57:    getfield Field ZKARKDQW F [I
L60:    iload_3
L61:    iaload
L62:    iastore
L63:    aload_0
L64:    getfield Field ZKARKDQW F [I
L67:    iload_3
L68:    iload 4
L70:    iastore
L71:    iinc 3 1
L74:    iload_3
L75:    aload_0
L76:    getfield Field ZKARKDQW C I
L79:    if_icmplt L43
L82:    iload_1
L83:    ifeq L132
L86:    bipush 107
L88:    putstatic Field ZKARKDQW r I
L91:    return
L92:    astore_2
L93:    new java/lang/StringBuffer
L96:    dup
L97:    ldc "2772, "
L99:    invokespecial Method java/lang/StringBuffer <init> (Ljava/lang/String;)V
L102:   iload_1
L103:   invokevirtual Method java/lang/StringBuffer append (I)Ljava/lang/StringBuffer;
L106:   ldc ", "
L108:   invokevirtual Method java/lang/StringBuffer append (Ljava/lang/String;)Ljava/lang/StringBuffer;
L111:   aload_2
L112:   invokevirtual Method java/lang/Throwable toString ()Ljava/lang/String;
L115:   invokevirtual Method java/lang/StringBuffer append (Ljava/lang/String;)Ljava/lang/StringBuffer;
L118:   invokevirtual Method java/lang/StringBuffer toString ()Ljava/lang/String;
L121:   invokestatic Method sign/signlink reporterror (Ljava/lang/String;)V
L124:   new java/lang/RuntimeException
L127:   dup
L128:   invokespecial Method java/lang/RuntimeException <init> ()V
L131:   athrow
L132:   return
L133:   
    .end code
.end method

.method public b : (IIII)V
    .code stack 5 locals 6
        .catch java/lang/RuntimeException from L0 to L95 using L96
L0:     iload_3
L1:     bipush 9
L3:     if_icmpeq L13
L6:     aload_0
L7:     sipush -383
L10:    putfield Field ZKARKDQW p I
L13:    iconst_0
L14:    istore 5
L16:    getstatic Field XHHRODPC l Z
L19:    ifeq L86
L22:    aload_0
L23:    getfield Field ZKARKDQW z [I
L26:    iload 5
L28:    aload_0
L29:    getfield Field ZKARKDQW z [I
L32:    iload 5
L34:    iaload
L35:    iload_1
L36:    imul
L37:    sipush 128
L40:    idiv
L41:    iastore
L42:    aload_0
L43:    getfield Field ZKARKDQW A [I
L46:    iload 5
L48:    aload_0
L49:    getfield Field ZKARKDQW A [I
L52:    iload 5
L54:    iaload
L55:    iload 4
L57:    imul
L58:    sipush 128
L61:    idiv
L62:    iastore
L63:    aload_0
L64:    getfield Field ZKARKDQW B [I
L67:    iload 5
L69:    aload_0
L70:    getfield Field ZKARKDQW B [I
L73:    iload 5
L75:    iaload
L76:    iload_2
L77:    imul
L78:    sipush 128
L81:    idiv
L82:    iastore
L83:    iinc 5 1
L86:    iload 5
L88:    aload_0
L89:    getfield Field ZKARKDQW y I
L92:    if_icmplt L22
L95:    return
L96:    astore 5
L98:    new java/lang/StringBuffer
L101:   dup
L102:   ldc "64795, "
L104:   invokespecial Method java/lang/StringBuffer <init> (Ljava/lang/String;)V
L107:   iload_1
L108:   invokevirtual Method java/lang/StringBuffer append (I)Ljava/lang/StringBuffer;
L111:   ldc ", "
L113:   invokevirtual Method java/lang/StringBuffer append (Ljava/lang/String;)Ljava/lang/StringBuffer;
L116:   iload_2
L117:   invokevirtual Method java/lang/StringBuffer append (I)Ljava/lang/StringBuffer;
L120:   ldc ", "
L122:   invokevirtual Method java/lang/StringBuffer append (Ljava/lang/String;)Ljava/lang/StringBuffer;
L125:   iload_3
L126:   invokevirtual Method java/lang/StringBuffer append (I)Ljava/lang/StringBuffer;
L129:   ldc ", "
L131:   invokevirtual Method java/lang/StringBuffer append (Ljava/lang/String;)Ljava/lang/StringBuffer;
L134:   iload 4
L136:   invokevirtual Method java/lang/StringBuffer append (I)Ljava/lang/StringBuffer;
L139:   ldc ", "
L141:   invokevirtual Method java/lang/StringBuffer append (Ljava/lang/String;)Ljava/lang/StringBuffer;
L144:   aload 5
L146:   invokevirtual Method java/lang/Throwable toString ()Ljava/lang/String;
L149:   invokevirtual Method java/lang/StringBuffer append (Ljava/lang/String;)Ljava/lang/StringBuffer;
L152:   invokevirtual Method java/lang/StringBuffer toString ()Ljava/lang/String;
L155:   invokestatic Method sign/signlink reporterror (Ljava/lang/String;)V
L158:   new java/lang/RuntimeException
L161:   dup
L162:   invokespecial Method java/lang/RuntimeException <init> ()V
L165:   athrow
L166:   
    .end code
.end method

.method public final a : (IIIIIZ)V
    .code stack 7 locals 25
L0:     getstatic Field XHHRODPC l Z
L3:     istore 24
L5:     iload_3
L6:     iload_3
L7:     imul
L8:     iload 4
L10:    iload 4
L12:    imul
L13:    iadd
L14:    iload 5
L16:    iload 5
L18:    imul
L19:    iadd
L20:    i2d
L21:    invokestatic Method java/lang/Math sqrt (D)D
L24:    d2i
L25:    istore 7
L27:    iload_2
L28:    iload 7
L30:    imul
L31:    bipush 8
L33:    ishr
L34:    istore 8
L36:    aload_0
L37:    getfield Field ZKARKDQW G [I
L40:    ifnonnull L73
L43:    aload_0
L44:    aload_0
L45:    getfield Field ZKARKDQW C I
L48:    newarray int
L50:    putfield Field ZKARKDQW G [I
L53:    aload_0
L54:    aload_0
L55:    getfield Field ZKARKDQW C I
L58:    newarray int
L60:    putfield Field ZKARKDQW H [I
L63:    aload_0
L64:    aload_0
L65:    getfield Field ZKARKDQW C I
L68:    newarray int
L70:    putfield Field ZKARKDQW I [I
L73:    aload_0
L74:    getfield Field XHHRODPC j [LRJXWGZGD;
L77:    ifnonnull L125
L80:    aload_0
L81:    aload_0
L82:    getfield Field ZKARKDQW y I
L85:    anewarray RJXWGZGD
L88:    putfield Field XHHRODPC j [LRJXWGZGD;
L91:    iconst_0
L92:    istore 9
L94:    iload 24
L96:    ifeq L116
L99:    aload_0
L100:   getfield Field XHHRODPC j [LRJXWGZGD;
L103:   iload 9
L105:   new RJXWGZGD
L108:   dup
L109:   invokespecial Method RJXWGZGD <init> ()V
L112:   aastore
L113:   iinc 9 1
L116:   iload 9
L118:   aload_0
L119:   getfield Field ZKARKDQW y I
L122:   if_icmplt L99
L125:   iconst_0
L126:   istore 9
L128:   iload 24
L130:   ifeq L686
L133:   aload_0
L134:   getfield Field ZKARKDQW D [I
L137:   iload 9
L139:   iaload
L140:   istore 10
L142:   aload_0
L143:   getfield Field ZKARKDQW E [I
L146:   iload 9
L148:   iaload
L149:   istore 11
L151:   aload_0
L152:   getfield Field ZKARKDQW F [I
L155:   iload 9
L157:   iaload
L158:   istore 12
L160:   aload_0
L161:   getfield Field ZKARKDQW z [I
L164:   iload 11
L166:   iaload
L167:   aload_0
L168:   getfield Field ZKARKDQW z [I
L171:   iload 10
L173:   iaload
L174:   isub
L175:   istore 13
L177:   aload_0
L178:   getfield Field ZKARKDQW A [I
L181:   iload 11
L183:   iaload
L184:   aload_0
L185:   getfield Field ZKARKDQW A [I
L188:   iload 10
L190:   iaload
L191:   isub
L192:   istore 14
L194:   aload_0
L195:   getfield Field ZKARKDQW B [I
L198:   iload 11
L200:   iaload
L201:   aload_0
L202:   getfield Field ZKARKDQW B [I
L205:   iload 10
L207:   iaload
L208:   isub
L209:   istore 15
L211:   aload_0
L212:   getfield Field ZKARKDQW z [I
L215:   iload 12
L217:   iaload
L218:   aload_0
L219:   getfield Field ZKARKDQW z [I
L222:   iload 10
L224:   iaload
L225:   isub
L226:   istore 16
L228:   aload_0
L229:   getfield Field ZKARKDQW A [I
L232:   iload 12
L234:   iaload
L235:   aload_0
L236:   getfield Field ZKARKDQW A [I
L239:   iload 10
L241:   iaload
L242:   isub
L243:   istore 17
L245:   aload_0
L246:   getfield Field ZKARKDQW B [I
L249:   iload 12
L251:   iaload
L252:   aload_0
L253:   getfield Field ZKARKDQW B [I
L256:   iload 10
L258:   iaload
L259:   isub
L260:   istore 18
L262:   iload 14
L264:   iload 18
L266:   imul
L267:   iload 17
L269:   iload 15
L271:   imul
L272:   isub
L273:   istore 19
L275:   iload 15
L277:   iload 16
L279:   imul
L280:   iload 18
L282:   iload 13
L284:   imul
L285:   isub
L286:   istore 20
L288:   iload 13
L290:   iload 17
L292:   imul
L293:   iload 16
L295:   iload 14
L297:   imul
L298:   isub
L299:   istore 21
L301:   iload 24
L303:   ifeq L324
L306:   iload 19
L308:   iconst_1
L309:   ishr
L310:   istore 19
L312:   iload 20
L314:   iconst_1
L315:   ishr
L316:   istore 20
L318:   iload 21
L320:   iconst_1
L321:   ishr
L322:   istore 21
L324:   iload 19
L326:   sipush 8192
L329:   if_icmpgt L306
L332:   iload 20
L334:   sipush 8192
L337:   if_icmpgt L306
L340:   iload 21
L342:   sipush 8192
L345:   if_icmpgt L306
L348:   iload 19
L350:   sipush -8192
L353:   if_icmplt L306
L356:   iload 20
L358:   sipush -8192
L361:   if_icmplt L306
L364:   iload 21
L366:   sipush -8192
L369:   if_icmplt L306
L372:   iload 19
L374:   iload 19
L376:   imul
L377:   iload 20
L379:   iload 20
L381:   imul
L382:   iadd
L383:   iload 21
L385:   iload 21
L387:   imul
L388:   iadd
L389:   i2d
L390:   invokestatic Method java/lang/Math sqrt (D)D
L393:   d2i
L394:   istore 22
L396:   iload 22
L398:   ifgt L404
L401:   iconst_1
L402:   istore 22
L404:   iload 19
L406:   sipush 256
L409:   imul
L410:   iload 22
L412:   idiv
L413:   istore 19
L415:   iload 20
L417:   sipush 256
L420:   imul
L421:   iload 22
L423:   idiv
L424:   istore 20
L426:   iload 21
L428:   sipush 256
L431:   imul
L432:   iload 22
L434:   idiv
L435:   istore 21
L437:   aload_0
L438:   getfield Field ZKARKDQW J [I
L441:   ifnull L456
L444:   aload_0
L445:   getfield Field ZKARKDQW J [I
L448:   iload 9
L450:   iaload
L451:   iconst_1
L452:   iand
L453:   ifne L629
L456:   aload_0
L457:   getfield Field XHHRODPC j [LRJXWGZGD;
L460:   iload 10
L462:   aaload
L463:   astore 23
L465:   aload 23
L467:   dup
L468:   getfield Field RJXWGZGD a I
L471:   iload 19
L473:   iadd
L474:   putfield Field RJXWGZGD a I
L477:   aload 23
L479:   dup
L480:   getfield Field RJXWGZGD b I
L483:   iload 20
L485:   iadd
L486:   putfield Field RJXWGZGD b I
L489:   aload 23
L491:   dup
L492:   getfield Field RJXWGZGD c I
L495:   iload 21
L497:   iadd
L498:   putfield Field RJXWGZGD c I
L501:   aload 23
L503:   dup
L504:   getfield Field RJXWGZGD d I
L507:   iconst_1
L508:   iadd
L509:   putfield Field RJXWGZGD d I
L512:   aload_0
L513:   getfield Field XHHRODPC j [LRJXWGZGD;
L516:   iload 11
L518:   aaload
L519:   astore 23
L521:   aload 23
L523:   dup
L524:   getfield Field RJXWGZGD a I
L527:   iload 19
L529:   iadd
L530:   putfield Field RJXWGZGD a I
L533:   aload 23
L535:   dup
L536:   getfield Field RJXWGZGD b I
L539:   iload 20
L541:   iadd
L542:   putfield Field RJXWGZGD b I
L545:   aload 23
L547:   dup
L548:   getfield Field RJXWGZGD c I
L551:   iload 21
L553:   iadd
L554:   putfield Field RJXWGZGD c I
L557:   aload 23
L559:   dup
L560:   getfield Field RJXWGZGD d I
L563:   iconst_1
L564:   iadd
L565:   putfield Field RJXWGZGD d I
L568:   aload_0
L569:   getfield Field XHHRODPC j [LRJXWGZGD;
L572:   iload 12
L574:   aaload
L575:   astore 23
L577:   aload 23
L579:   dup
L580:   getfield Field RJXWGZGD a I
L583:   iload 19
L585:   iadd
L586:   putfield Field RJXWGZGD a I
L589:   aload 23
L591:   dup
L592:   getfield Field RJXWGZGD b I
L595:   iload 20
L597:   iadd
L598:   putfield Field RJXWGZGD b I
L601:   aload 23
L603:   dup
L604:   getfield Field RJXWGZGD c I
L607:   iload 21
L609:   iadd
L610:   putfield Field RJXWGZGD c I
L613:   aload 23
L615:   dup
L616:   getfield Field RJXWGZGD d I
L619:   iconst_1
L620:   iadd
L621:   putfield Field RJXWGZGD d I
L624:   iload 24
L626:   ifeq L683
L629:   iload_1
L630:   iload_3
L631:   iload 19
L633:   imul
L634:   iload 4
L636:   iload 20
L638:   imul
L639:   iadd
L640:   iload 5
L642:   iload 21
L644:   imul
L645:   iadd
L646:   iload 8
L648:   iload 8
L650:   iconst_2
L651:   idiv
L652:   iadd
L653:   idiv
L654:   iadd
L655:   istore 23
L657:   aload_0
L658:   getfield Field ZKARKDQW G [I
L661:   iload 9
L663:   aload_0
L664:   getfield Field ZKARKDQW M [I
L667:   iload 9
L669:   iaload
L670:   iload 23
L672:   aload_0
L673:   getfield Field ZKARKDQW J [I
L676:   iload 9
L678:   iaload
L679:   invokestatic Method ZKARKDQW a (III)I
L682:   iastore
L683:   iinc 9 1
L686:   iload 9
L688:   aload_0
L689:   getfield Field ZKARKDQW C I
L692:   if_icmplt L133
L695:   iload 6
L697:   ifeq L717
L700:   aload_0
L701:   iload_1
L702:   iload 8
L704:   iload_3
L705:   iload 4
L707:   iload 5
L709:   invokevirtual Method ZKARKDQW a (IIIII)V
L712:   iload 24
L714:   ifeq L814
L717:   aload_0
L718:   aload_0
L719:   getfield Field ZKARKDQW y I
L722:   anewarray RJXWGZGD
L725:   putfield Field ZKARKDQW gb [LRJXWGZGD;
L728:   iconst_0
L729:   istore 10
L731:   iload 24
L733:   ifeq L805
L736:   aload_0
L737:   getfield Field XHHRODPC j [LRJXWGZGD;
L740:   iload 10
L742:   aaload
L743:   astore 11
L745:   aload_0
L746:   getfield Field ZKARKDQW gb [LRJXWGZGD;
L749:   iload 10
L751:   new RJXWGZGD
L754:   dup
L755:   invokespecial Method RJXWGZGD <init> ()V
L758:   dup_x2
L759:   aastore
L760:   astore 12
L762:   aload 12
L764:   aload 11
L766:   getfield Field RJXWGZGD a I
L769:   putfield Field RJXWGZGD a I
L772:   aload 12
L774:   aload 11
L776:   getfield Field RJXWGZGD b I
L779:   putfield Field RJXWGZGD b I
L782:   aload 12
L784:   aload 11
L786:   getfield Field RJXWGZGD c I
L789:   putfield Field RJXWGZGD c I
L792:   aload 12
L794:   aload 11
L796:   getfield Field RJXWGZGD d I
L799:   putfield Field RJXWGZGD d I
L802:   iinc 10 1
L805:   iload 10
L807:   aload_0
L808:   getfield Field ZKARKDQW y I
L811:   if_icmplt L736
L814:   iload 6
L816:   ifeq L825
L819:   aload_0
L820:   iconst_0
L821:   invokevirtual Method ZKARKDQW a (Z)V
L824:   return
L825:   aload_0
L826:   sipush 21073
L829:   invokevirtual Method ZKARKDQW d (I)V
L832:   return
L833:   
    .end code
.end method

.method public final a : (IIIII)V
    .code stack 6 locals 15
L0:     getstatic Field XHHRODPC l Z
L3:     istore 14
L5:     iconst_0
L6:     istore 6
L8:     iload 14
L10:    ifeq L463
L13:    aload_0
L14:    getfield Field ZKARKDQW D [I
L17:    iload 6
L19:    iaload
L20:    istore 7
L22:    aload_0
L23:    getfield Field ZKARKDQW E [I
L26:    iload 6
L28:    iaload
L29:    istore 8
L31:    aload_0
L32:    getfield Field ZKARKDQW F [I
L35:    iload 6
L37:    iaload
L38:    istore 9
L40:    aload_0
L41:    getfield Field ZKARKDQW J [I
L44:    ifnonnull L244
L47:    aload_0
L48:    getfield Field ZKARKDQW M [I
L51:    iload 6
L53:    iaload
L54:    istore 12
L56:    aload_0
L57:    getfield Field XHHRODPC j [LRJXWGZGD;
L60:    iload 7
L62:    aaload
L63:    astore 10
L65:    iload_1
L66:    iload_3
L67:    aload 10
L69:    getfield Field RJXWGZGD a I
L72:    imul
L73:    iload 4
L75:    aload 10
L77:    getfield Field RJXWGZGD b I
L80:    imul
L81:    iadd
L82:    iload 5
L84:    aload 10
L86:    getfield Field RJXWGZGD c I
L89:    imul
L90:    iadd
L91:    iload_2
L92:    aload 10
L94:    getfield Field RJXWGZGD d I
L97:    imul
L98:    idiv
L99:    iadd
L100:   istore 11
L102:   aload_0
L103:   getfield Field ZKARKDQW G [I
L106:   iload 6
L108:   iload 12
L110:   iload 11
L112:   iconst_0
L113:   invokestatic Method ZKARKDQW a (III)I
L116:   iastore
L117:   aload_0
L118:   getfield Field XHHRODPC j [LRJXWGZGD;
L121:   iload 8
L123:   aaload
L124:   astore 10
L126:   iload_1
L127:   iload_3
L128:   aload 10
L130:   getfield Field RJXWGZGD a I
L133:   imul
L134:   iload 4
L136:   aload 10
L138:   getfield Field RJXWGZGD b I
L141:   imul
L142:   iadd
L143:   iload 5
L145:   aload 10
L147:   getfield Field RJXWGZGD c I
L150:   imul
L151:   iadd
L152:   iload_2
L153:   aload 10
L155:   getfield Field RJXWGZGD d I
L158:   imul
L159:   idiv
L160:   iadd
L161:   istore 11
L163:   aload_0
L164:   getfield Field ZKARKDQW H [I
L167:   iload 6
L169:   iload 12
L171:   iload 11
L173:   iconst_0
L174:   invokestatic Method ZKARKDQW a (III)I
L177:   iastore
L178:   aload_0
L179:   getfield Field XHHRODPC j [LRJXWGZGD;
L182:   iload 9
L184:   aaload
L185:   astore 10
L187:   iload_1
L188:   iload_3
L189:   aload 10
L191:   getfield Field RJXWGZGD a I
L194:   imul
L195:   iload 4
L197:   aload 10
L199:   getfield Field RJXWGZGD b I
L202:   imul
L203:   iadd
L204:   iload 5
L206:   aload 10
L208:   getfield Field RJXWGZGD c I
L211:   imul
L212:   iadd
L213:   iload_2
L214:   aload 10
L216:   getfield Field RJXWGZGD d I
L219:   imul
L220:   idiv
L221:   iadd
L222:   istore 11
L224:   aload_0
L225:   getfield Field ZKARKDQW I [I
L228:   iload 6
L230:   iload 12
L232:   iload 11
L234:   iconst_0
L235:   invokestatic Method ZKARKDQW a (III)I
L238:   iastore
L239:   iload 14
L241:   ifeq L460
L244:   aload_0
L245:   getfield Field ZKARKDQW J [I
L248:   iload 6
L250:   iaload
L251:   iconst_1
L252:   iand
L253:   ifne L460
L256:   aload_0
L257:   getfield Field ZKARKDQW M [I
L260:   iload 6
L262:   iaload
L263:   istore 12
L265:   aload_0
L266:   getfield Field ZKARKDQW J [I
L269:   iload 6
L271:   iaload
L272:   istore 13
L274:   aload_0
L275:   getfield Field XHHRODPC j [LRJXWGZGD;
L278:   iload 7
L280:   aaload
L281:   astore 10
L283:   iload_1
L284:   iload_3
L285:   aload 10
L287:   getfield Field RJXWGZGD a I
L290:   imul
L291:   iload 4
L293:   aload 10
L295:   getfield Field RJXWGZGD b I
L298:   imul
L299:   iadd
L300:   iload 5
L302:   aload 10
L304:   getfield Field RJXWGZGD c I
L307:   imul
L308:   iadd
L309:   iload_2
L310:   aload 10
L312:   getfield Field RJXWGZGD d I
L315:   imul
L316:   idiv
L317:   iadd
L318:   istore 11
L320:   aload_0
L321:   getfield Field ZKARKDQW G [I
L324:   iload 6
L326:   iload 12
L328:   iload 11
L330:   iload 13
L332:   invokestatic Method ZKARKDQW a (III)I
L335:   iastore
L336:   aload_0
L337:   getfield Field XHHRODPC j [LRJXWGZGD;
L340:   iload 8
L342:   aaload
L343:   astore 10
L345:   iload_1
L346:   iload_3
L347:   aload 10
L349:   getfield Field RJXWGZGD a I
L352:   imul
L353:   iload 4
L355:   aload 10
L357:   getfield Field RJXWGZGD b I
L360:   imul
L361:   iadd
L362:   iload 5
L364:   aload 10
L366:   getfield Field RJXWGZGD c I
L369:   imul
L370:   iadd
L371:   iload_2
L372:   aload 10
L374:   getfield Field RJXWGZGD d I
L377:   imul
L378:   idiv
L379:   iadd
L380:   istore 11
L382:   aload_0
L383:   getfield Field ZKARKDQW H [I
L386:   iload 6
L388:   iload 12
L390:   iload 11
L392:   iload 13
L394:   invokestatic Method ZKARKDQW a (III)I
L397:   iastore
L398:   aload_0
L399:   getfield Field XHHRODPC j [LRJXWGZGD;
L402:   iload 9
L404:   aaload
L405:   astore 10
L407:   iload_1
L408:   iload_3
L409:   aload 10
L411:   getfield Field RJXWGZGD a I
L414:   imul
L415:   iload 4
L417:   aload 10
L419:   getfield Field RJXWGZGD b I
L422:   imul
L423:   iadd
L424:   iload 5
L426:   aload 10
L428:   getfield Field RJXWGZGD c I
L431:   imul
L432:   iadd
L433:   iload_2
L434:   aload 10
L436:   getfield Field RJXWGZGD d I
L439:   imul
L440:   idiv
L441:   iadd
L442:   istore 11
L444:   aload_0
L445:   getfield Field ZKARKDQW I [I
L448:   iload 6
L450:   iload 12
L452:   iload 11
L454:   iload 13
L456:   invokestatic Method ZKARKDQW a (III)I
L459:   iastore
L460:   iinc 6 1
L463:   iload 6
L465:   aload_0
L466:   getfield Field ZKARKDQW C I
L469:   if_icmplt L13
L472:   aload_0
L473:   aconst_null
L474:   putfield Field XHHRODPC j [LRJXWGZGD;
L477:   aload_0
L478:   aconst_null
L479:   putfield Field ZKARKDQW gb [LRJXWGZGD;
L482:   aload_0
L483:   aconst_null
L484:   putfield Field ZKARKDQW bb [I
L487:   aload_0
L488:   aconst_null
L489:   putfield Field ZKARKDQW cb [I
L492:   aload_0
L493:   getfield Field ZKARKDQW J [I
L496:   ifnull L533
L499:   iconst_0
L500:   istore 7
L502:   iload 14
L504:   ifeq L524
L507:   aload_0
L508:   getfield Field ZKARKDQW J [I
L511:   iload 7
L513:   iaload
L514:   iconst_2
L515:   iand
L516:   iconst_2
L517:   if_icmpne L521
L520:   return
L521:   iinc 7 1
L524:   iload 7
L526:   aload_0
L527:   getfield Field ZKARKDQW C I
L530:   if_icmplt L507
L533:   aload_0
L534:   aconst_null
L535:   putfield Field ZKARKDQW M [I
L538:   return
L539:   
    .end code
.end method

.method public static final a : (III)I
    .code stack 4 locals 4
L0:     getstatic Field XHHRODPC l Z
L3:     istore_3
L4:     iload_2
L5:     iconst_2
L6:     iand
L7:     iconst_2
L8:     if_icmpne L37
L11:    iload_1
L12:    ifge L21
L15:    iconst_0
L16:    istore_1
L17:    iload_3
L18:    ifeq L30
L21:    iload_1
L22:    bipush 127
L24:    if_icmple L30
L27:    bipush 127
L29:    istore_1
L30:    bipush 127
L32:    iload_1
L33:    isub
L34:    istore_1
L35:    iload_1
L36:    ireturn
L37:    iload_1
L38:    iload_0
L39:    bipush 127
L41:    iand
L42:    imul
L43:    bipush 7
L45:    ishr
L46:    istore_1
L47:    iload_1
L48:    iconst_2
L49:    if_icmpge L58
L52:    iconst_2
L53:    istore_1
L54:    iload_3
L55:    ifeq L67
L58:    iload_1
L59:    bipush 126
L61:    if_icmple L67
L64:    bipush 126
L66:    istore_1
L67:    iload_0
L68:    ldc 65408
L70:    iand
L71:    iload_1
L72:    iadd
L73:    ireturn
L74:    
    .end code
.end method

.method public final a : (IIIIIII)V
    .code stack 6 locals 24
L0:     getstatic Field OPPOFIOL F I
L3:     istore 8
L5:     getstatic Field OPPOFIOL G I
L8:     istore 9
L10:    getstatic Field ZKARKDQW Jb [I
L13:    iload_1
L14:    iaload
L15:    istore 10
L17:    getstatic Field ZKARKDQW Kb [I
L20:    iload_1
L21:    iaload
L22:    istore 11
L24:    getstatic Field ZKARKDQW Jb [I
L27:    iload_2
L28:    iaload
L29:    istore 12
L31:    getstatic Field ZKARKDQW Kb [I
L34:    iload_2
L35:    iaload
L36:    istore 13
L38:    getstatic Field ZKARKDQW Jb [I
L41:    iload_3
L42:    iaload
L43:    istore 14
L45:    getstatic Field ZKARKDQW Kb [I
L48:    iload_3
L49:    iaload
L50:    istore 15
L52:    getstatic Field ZKARKDQW Jb [I
L55:    iload 4
L57:    iaload
L58:    istore 16
L60:    getstatic Field ZKARKDQW Kb [I
L63:    iload 4
L65:    iaload
L66:    istore 17
L68:    iload 6
L70:    iload 16
L72:    imul
L73:    iload 7
L75:    iload 17
L77:    imul
L78:    iadd
L79:    bipush 16
L81:    ishr
L82:    istore 18
L84:    iconst_0
L85:    istore 19
L87:    getstatic Field XHHRODPC l Z
L90:    ifeq L376
L93:    aload_0
L94:    getfield Field ZKARKDQW z [I
L97:    iload 19
L99:    iaload
L100:   istore 20
L102:   aload_0
L103:   getfield Field ZKARKDQW A [I
L106:   iload 19
L108:   iaload
L109:   istore 21
L111:   aload_0
L112:   getfield Field ZKARKDQW B [I
L115:   iload 19
L117:   iaload
L118:   istore 22
L120:   iload_3
L121:   ifeq L160
L124:   iload 21
L126:   iload 14
L128:   imul
L129:   iload 20
L131:   iload 15
L133:   imul
L134:   iadd
L135:   bipush 16
L137:   ishr
L138:   istore 23
L140:   iload 21
L142:   iload 15
L144:   imul
L145:   iload 20
L147:   iload 14
L149:   imul
L150:   isub
L151:   bipush 16
L153:   ishr
L154:   istore 21
L156:   iload 23
L158:   istore 20
L160:   iload_1
L161:   ifeq L200
L164:   iload 21
L166:   iload 11
L168:   imul
L169:   iload 22
L171:   iload 10
L173:   imul
L174:   isub
L175:   bipush 16
L177:   ishr
L178:   istore 23
L180:   iload 21
L182:   iload 10
L184:   imul
L185:   iload 22
L187:   iload 11
L189:   imul
L190:   iadd
L191:   bipush 16
L193:   ishr
L194:   istore 22
L196:   iload 23
L198:   istore 21
L200:   iload_2
L201:   ifeq L240
L204:   iload 22
L206:   iload 12
L208:   imul
L209:   iload 20
L211:   iload 13
L213:   imul
L214:   iadd
L215:   bipush 16
L217:   ishr
L218:   istore 23
L220:   iload 22
L222:   iload 13
L224:   imul
L225:   iload 20
L227:   iload 12
L229:   imul
L230:   isub
L231:   bipush 16
L233:   ishr
L234:   istore 22
L236:   iload 23
L238:   istore 20
L240:   iload 20
L242:   iload 5
L244:   iadd
L245:   istore 20
L247:   iload 21
L249:   iload 6
L251:   iadd
L252:   istore 21
L254:   iload 22
L256:   iload 7
L258:   iadd
L259:   istore 22
L261:   iload 21
L263:   iload 17
L265:   imul
L266:   iload 22
L268:   iload 16
L270:   imul
L271:   isub
L272:   bipush 16
L274:   ishr
L275:   istore 23
L277:   iload 21
L279:   iload 16
L281:   imul
L282:   iload 22
L284:   iload 17
L286:   imul
L287:   iadd
L288:   bipush 16
L290:   ishr
L291:   istore 22
L293:   iload 23
L295:   istore 21
L297:   getstatic Field ZKARKDQW nb [I
L300:   iload 19
L302:   iload 22
L304:   iload 18
L306:   isub
L307:   iastore
L308:   getstatic Field ZKARKDQW lb [I
L311:   iload 19
L313:   iload 8
L315:   iload 20
L317:   bipush 9
L319:   ishl
L320:   iload 22
L322:   idiv
L323:   iadd
L324:   iastore
L325:   getstatic Field ZKARKDQW mb [I
L328:   iload 19
L330:   iload 9
L332:   iload 21
L334:   bipush 9
L336:   ishl
L337:   iload 22
L339:   idiv
L340:   iadd
L341:   iastore
L342:   aload_0
L343:   getfield Field ZKARKDQW O I
L346:   ifle L373
L349:   getstatic Field ZKARKDQW ob [I
L352:   iload 19
L354:   iload 20
L356:   iastore
L357:   getstatic Field ZKARKDQW pb [I
L360:   iload 19
L362:   iload 21
L364:   iastore
L365:   getstatic Field ZKARKDQW qb [I
L368:   iload 19
L370:   iload 22
L372:   iastore
L373:   iinc 19 1
L376:   iload 19
L378:   aload_0
L379:   getfield Field ZKARKDQW y I
L382:   if_icmplt L93
        .catch java/lang/Exception from L385 to L392 using L393
L385:   aload_0
L386:   iconst_0
L387:   iconst_0
L388:   iconst_0
L389:   invokespecial Method ZKARKDQW a (ZZI)V
L392:   return
L393:   pop
L394:   return
L395:   
    .end code
.end method

.method public final a : (IIIIIIIII)V
    .code stack 6 locals 35
L0:     getstatic Field XHHRODPC l Z
L3:     istore 34
L5:     iload 8
L7:     iload 5
L9:     imul
L10:    iload 6
L12:    iload 4
L14:    imul
L15:    isub
L16:    bipush 16
L18:    ishr
L19:    istore 10
L21:    iload 7
L23:    iload_2
L24:    imul
L25:    iload 10
L27:    iload_3
L28:    imul
L29:    iadd
L30:    bipush 16
L32:    ishr
L33:    istore 11
L35:    aload_0
L36:    getfield Field ZKARKDQW W I
L39:    iload_3
L40:    imul
L41:    bipush 16
L43:    ishr
L44:    istore 12
L46:    iload 11
L48:    iload 12
L50:    iadd
L51:    istore 13
L53:    iload 13
L55:    bipush 50
L57:    if_icmple L68
L60:    iload 11
L62:    sipush 3500
L65:    if_icmplt L69
L68:    return
L69:    iload 8
L71:    iload 4
L73:    imul
L74:    iload 6
L76:    iload 5
L78:    imul
L79:    iadd
L80:    bipush 16
L82:    ishr
L83:    istore 14
L85:    iload 14
L87:    aload_0
L88:    getfield Field ZKARKDQW W I
L91:    isub
L92:    bipush 9
L94:    ishl
L95:    istore 15
L97:    iload 15
L99:    iload 13
L101:   idiv
L102:   getstatic Field AFCKELYG u I
L105:   if_icmplt L109
L108:   return
L109:   iload 14
L111:   aload_0
L112:   getfield Field ZKARKDQW W I
L115:   iadd
L116:   bipush 9
L118:   ishl
L119:   istore 16
L121:   iload 16
L123:   iload 13
L125:   idiv
L126:   getstatic Field AFCKELYG u I
L129:   ineg
L130:   if_icmpgt L134
L133:   return
L134:   iload 7
L136:   iload_3
L137:   imul
L138:   iload 10
L140:   iload_2
L141:   imul
L142:   isub
L143:   bipush 16
L145:   ishr
L146:   istore 17
L148:   aload_0
L149:   getfield Field ZKARKDQW W I
L152:   iload_2
L153:   imul
L154:   bipush 16
L156:   ishr
L157:   istore 18
L159:   iload 17
L161:   iload 18
L163:   iadd
L164:   bipush 9
L166:   ishl
L167:   istore 19
L169:   iload 19
L171:   iload 13
L173:   idiv
L174:   getstatic Field AFCKELYG v I
L177:   ineg
L178:   if_icmpgt L182
L181:   return
L182:   iload 18
L184:   aload_0
L185:   getfield Field XHHRODPC k I
L188:   iload_3
L189:   imul
L190:   bipush 16
L192:   ishr
L193:   iadd
L194:   istore 20
L196:   iload 17
L198:   iload 20
L200:   isub
L201:   bipush 9
L203:   ishl
L204:   istore 21
L206:   iload 21
L208:   iload 13
L210:   idiv
L211:   getstatic Field AFCKELYG v I
L214:   if_icmplt L218
L217:   return
L218:   iload 12
L220:   aload_0
L221:   getfield Field XHHRODPC k I
L224:   iload_2
L225:   imul
L226:   bipush 16
L228:   ishr
L229:   iadd
L230:   istore 22
L232:   iconst_0
L233:   istore 23
L235:   iload 11
L237:   iload 22
L239:   isub
L240:   bipush 50
L242:   if_icmpgt L248
L245:   iconst_1
L246:   istore 23
L248:   iconst_0
L249:   istore 24
L251:   iload 9
L253:   ifle L432
L256:   getstatic Field ZKARKDQW Eb Z
L259:   ifeq L432
L262:   iload 11
L264:   iload 12
L266:   isub
L267:   istore 25
L269:   iload 25
L271:   bipush 50
L273:   if_icmpgt L280
L276:   bipush 50
L278:   istore 25
L280:   iload 14
L282:   ifle L304
L285:   iload 15
L287:   iload 13
L289:   idiv
L290:   istore 15
L292:   iload 16
L294:   iload 25
L296:   idiv
L297:   istore 16
L299:   iload 34
L301:   ifeq L318
L304:   iload 16
L306:   iload 13
L308:   idiv
L309:   istore 16
L311:   iload 15
L313:   iload 25
L315:   idiv
L316:   istore 15
L318:   iload 17
L320:   ifle L342
L323:   iload 21
L325:   iload 13
L327:   idiv
L328:   istore 21
L330:   iload 19
L332:   iload 25
L334:   idiv
L335:   istore 19
L337:   iload 34
L339:   ifeq L356
L342:   iload 19
L344:   iload 13
L346:   idiv
L347:   istore 19
L349:   iload 21
L351:   iload 25
L353:   idiv
L354:   istore 21
L356:   getstatic Field ZKARKDQW Fb I
L359:   getstatic Field OPPOFIOL F I
L362:   isub
L363:   istore 26
L365:   getstatic Field ZKARKDQW Gb I
L368:   getstatic Field OPPOFIOL G I
L371:   isub
L372:   istore 27
L374:   iload 26
L376:   iload 15
L378:   if_icmple L432
L381:   iload 26
L383:   iload 16
L385:   if_icmpge L432
L388:   iload 27
L390:   iload 21
L392:   if_icmple L432
L395:   iload 27
L397:   iload 19
L399:   if_icmpge L432
L402:   aload_0
L403:   getfield Field ZKARKDQW fb Z
L406:   ifeq L429
L409:   getstatic Field ZKARKDQW Ib [I
L412:   getstatic Field ZKARKDQW Hb I
L415:   dup
L416:   iconst_1
L417:   iadd
L418:   putstatic Field ZKARKDQW Hb I
L421:   iload 9
L423:   iastore
L424:   iload 34
L426:   ifeq L432
L429:   iconst_1
L430:   istore 24
L432:   getstatic Field OPPOFIOL F I
L435:   istore 25
L437:   getstatic Field OPPOFIOL G I
L440:   istore 26
L442:   iconst_0
L443:   istore 27
L445:   iconst_0
L446:   istore 28
L448:   iload_1
L449:   ifeq L466
L452:   getstatic Field ZKARKDQW Jb [I
L455:   iload_1
L456:   iaload
L457:   istore 27
L459:   getstatic Field ZKARKDQW Kb [I
L462:   iload_1
L463:   iaload
L464:   istore 28
L466:   iconst_0
L467:   istore 29
L469:   iload 34
L471:   ifeq L738
L474:   aload_0
L475:   getfield Field ZKARKDQW z [I
L478:   iload 29
L480:   iaload
L481:   istore 30
L483:   aload_0
L484:   getfield Field ZKARKDQW A [I
L487:   iload 29
L489:   iaload
L490:   istore 31
L492:   aload_0
L493:   getfield Field ZKARKDQW B [I
L496:   iload 29
L498:   iaload
L499:   istore 32
L501:   iload_1
L502:   ifeq L541
L505:   iload 32
L507:   iload 27
L509:   imul
L510:   iload 30
L512:   iload 28
L514:   imul
L515:   iadd
L516:   bipush 16
L518:   ishr
L519:   istore 33
L521:   iload 32
L523:   iload 28
L525:   imul
L526:   iload 30
L528:   iload 27
L530:   imul
L531:   isub
L532:   bipush 16
L534:   ishr
L535:   istore 32
L537:   iload 33
L539:   istore 30
L541:   iload 30
L543:   iload 6
L545:   iadd
L546:   istore 30
L548:   iload 31
L550:   iload 7
L552:   iadd
L553:   istore 31
L555:   iload 32
L557:   iload 8
L559:   iadd
L560:   istore 32
L562:   iload 32
L564:   iload 4
L566:   imul
L567:   iload 30
L569:   iload 5
L571:   imul
L572:   iadd
L573:   bipush 16
L575:   ishr
L576:   istore 33
L578:   iload 32
L580:   iload 5
L582:   imul
L583:   iload 30
L585:   iload 4
L587:   imul
L588:   isub
L589:   bipush 16
L591:   ishr
L592:   istore 32
L594:   iload 33
L596:   istore 30
L598:   iload 31
L600:   iload_3
L601:   imul
L602:   iload 32
L604:   iload_2
L605:   imul
L606:   isub
L607:   bipush 16
L609:   ishr
L610:   istore 33
L612:   iload 31
L614:   iload_2
L615:   imul
L616:   iload 32
L618:   iload_3
L619:   imul
L620:   iadd
L621:   bipush 16
L623:   ishr
L624:   istore 32
L626:   iload 33
L628:   istore 31
L630:   getstatic Field ZKARKDQW nb [I
L633:   iload 29
L635:   iload 32
L637:   iload 11
L639:   isub
L640:   iastore
L641:   iload 32
L643:   bipush 50
L645:   if_icmplt L687
L648:   getstatic Field ZKARKDQW lb [I
L651:   iload 29
L653:   iload 25
L655:   iload 30
L657:   bipush 9
L659:   ishl
L660:   iload 32
L662:   idiv
L663:   iadd
L664:   iastore
L665:   getstatic Field ZKARKDQW mb [I
L668:   iload 29
L670:   iload 26
L672:   iload 31
L674:   bipush 9
L676:   ishl
L677:   iload 32
L679:   idiv
L680:   iadd
L681:   iastore
L682:   iload 34
L684:   ifeq L699
L687:   getstatic Field ZKARKDQW lb [I
L690:   iload 29
L692:   sipush -5000
L695:   iastore
L696:   iconst_1
L697:   istore 23
L699:   iload 23
L701:   ifne L711
L704:   aload_0
L705:   getfield Field ZKARKDQW O I
L708:   ifle L735
L711:   getstatic Field ZKARKDQW ob [I
L714:   iload 29
L716:   iload 30
L718:   iastore
L719:   getstatic Field ZKARKDQW pb [I
L722:   iload 29
L724:   iload 31
L726:   iastore
L727:   getstatic Field ZKARKDQW qb [I
L730:   iload 29
L732:   iload 32
L734:   iastore
L735:   iinc 29 1
L738:   iload 29
L740:   aload_0
L741:   getfield Field ZKARKDQW y I
L744:   if_icmplt L474
        .catch java/lang/Exception from L747 to L757 using L758
L747:   aload_0
L748:   iload 23
L750:   iload 24
L752:   iload 9
L754:   invokespecial Method ZKARKDQW a (ZZI)V
L757:   return
L758:   pop
L759:   return
L760:   
    .end code
.end method

.method private final a : (ZZI)V
    .code stack 10 locals 21
L0:     getstatic Field XHHRODPC l Z
L3:     istore 20
L5:     iconst_0
L6:     istore 4
L8:     iload 20
L10:    ifeq L23
L13:    getstatic Field ZKARKDQW rb [I
L16:    iload 4
L18:    iconst_0
L19:    iastore
L20:    iinc 4 1
L23:    iload 4
L25:    aload_0
L26:    getfield Field ZKARKDQW Y I
L29:    if_icmplt L13
L32:    iconst_0
L33:    istore 5
L35:    iload 20
L37:    ifeq L414
L40:    aload_0
L41:    getfield Field ZKARKDQW J [I
L44:    ifnull L58
L47:    aload_0
L48:    getfield Field ZKARKDQW J [I
L51:    iload 5
L53:    iaload
L54:    iconst_m1
L55:    if_icmpeq L411
L58:    aload_0
L59:    getfield Field ZKARKDQW D [I
L62:    iload 5
L64:    iaload
L65:    istore 6
L67:    aload_0
L68:    getfield Field ZKARKDQW E [I
L71:    iload 5
L73:    iaload
L74:    istore 7
L76:    aload_0
L77:    getfield Field ZKARKDQW F [I
L80:    iload 5
L82:    iaload
L83:    istore 8
L85:    getstatic Field ZKARKDQW lb [I
L88:    iload 6
L90:    iaload
L91:    istore 9
L93:    getstatic Field ZKARKDQW lb [I
L96:    iload 7
L98:    iaload
L99:    istore 10
L101:   getstatic Field ZKARKDQW lb [I
L104:   iload 8
L106:   iaload
L107:   istore 11
L109:   iload_1
L110:   ifeq L198
L113:   iload 9
L115:   sipush -5000
L118:   if_icmpeq L137
L121:   iload 10
L123:   sipush -5000
L126:   if_icmpeq L137
L129:   iload 11
L131:   sipush -5000
L134:   if_icmpne L198
L137:   getstatic Field ZKARKDQW kb [Z
L140:   iload 5
L142:   iconst_1
L143:   bastore
L144:   getstatic Field ZKARKDQW nb [I
L147:   iload 6
L149:   iaload
L150:   getstatic Field ZKARKDQW nb [I
L153:   iload 7
L155:   iaload
L156:   iadd
L157:   getstatic Field ZKARKDQW nb [I
L160:   iload 8
L162:   iaload
L163:   iadd
L164:   iconst_3
L165:   idiv
L166:   aload_0
L167:   getfield Field ZKARKDQW Z I
L170:   iadd
L171:   istore 12
L173:   getstatic Field ZKARKDQW sb [[I
L176:   iload 12
L178:   aaload
L179:   getstatic Field ZKARKDQW rb [I
L182:   iload 12
L184:   dup2
L185:   iaload
L186:   dup_x2
L187:   iconst_1
L188:   iadd
L189:   iastore
L190:   iload 5
L192:   iastore
L193:   iload 20
L195:   ifeq L411
L198:   iload_2
L199:   ifeq L255
L202:   aload_0
L203:   getstatic Field ZKARKDQW Fb I
L206:   getstatic Field ZKARKDQW Gb I
L209:   getstatic Field ZKARKDQW mb [I
L212:   iload 6
L214:   iaload
L215:   getstatic Field ZKARKDQW mb [I
L218:   iload 7
L220:   iaload
L221:   getstatic Field ZKARKDQW mb [I
L224:   iload 8
L226:   iaload
L227:   iload 9
L229:   iload 10
L231:   iload 11
L233:   invokespecial Method ZKARKDQW a (IIIIIIII)Z
L236:   ifeq L255
L239:   getstatic Field ZKARKDQW Ib [I
L242:   getstatic Field ZKARKDQW Hb I
L245:   dup
L246:   iconst_1
L247:   iadd
L248:   putstatic Field ZKARKDQW Hb I
L251:   iload_3
L252:   iastore
L253:   iconst_0
L254:   istore_2
L255:   iload 9
L257:   iload 10
L259:   isub
L260:   getstatic Field ZKARKDQW mb [I
L263:   iload 8
L265:   iaload
L266:   getstatic Field ZKARKDQW mb [I
L269:   iload 7
L271:   iaload
L272:   isub
L273:   imul
L274:   getstatic Field ZKARKDQW mb [I
L277:   iload 6
L279:   iaload
L280:   getstatic Field ZKARKDQW mb [I
L283:   iload 7
L285:   iaload
L286:   isub
L287:   iload 11
L289:   iload 10
L291:   isub
L292:   imul
L293:   isub
L294:   ifle L411
L297:   getstatic Field ZKARKDQW kb [Z
L300:   iload 5
L302:   iconst_0
L303:   bastore
L304:   iload 9
L306:   iflt L343
L309:   iload 10
L311:   iflt L343
L314:   iload 11
L316:   iflt L343
L319:   iload 9
L321:   getstatic Field AFCKELYG t I
L324:   if_icmpgt L343
L327:   iload 10
L329:   getstatic Field AFCKELYG t I
L332:   if_icmpgt L343
L335:   iload 11
L337:   getstatic Field AFCKELYG t I
L340:   if_icmple L355
L343:   getstatic Field ZKARKDQW jb [Z
L346:   iload 5
L348:   iconst_1
L349:   bastore
L350:   iload 20
L352:   ifeq L362
L355:   getstatic Field ZKARKDQW jb [Z
L358:   iload 5
L360:   iconst_0
L361:   bastore
L362:   getstatic Field ZKARKDQW nb [I
L365:   iload 6
L367:   iaload
L368:   getstatic Field ZKARKDQW nb [I
L371:   iload 7
L373:   iaload
L374:   iadd
L375:   getstatic Field ZKARKDQW nb [I
L378:   iload 8
L380:   iaload
L381:   iadd
L382:   iconst_3
L383:   idiv
L384:   aload_0
L385:   getfield Field ZKARKDQW Z I
L388:   iadd
L389:   istore 12
L391:   getstatic Field ZKARKDQW sb [[I
L394:   iload 12
L396:   aaload
L397:   getstatic Field ZKARKDQW rb [I
L400:   iload 12
L402:   dup2
L403:   iaload
L404:   dup_x2
L405:   iconst_1
L406:   iadd
L407:   iastore
L408:   iload 5
L410:   iastore
L411:   iinc 5 1
L414:   iload 5
L416:   aload_0
L417:   getfield Field ZKARKDQW C I
L420:   if_icmplt L40
L423:   aload_0
L424:   getfield Field ZKARKDQW K [I
L427:   ifnonnull L500
L430:   aload_0
L431:   getfield Field ZKARKDQW Y I
L434:   iconst_1
L435:   isub
L436:   istore 6
L438:   iload 20
L440:   ifeq L494
L443:   getstatic Field ZKARKDQW rb [I
L446:   iload 6
L448:   iaload
L449:   istore 7
L451:   iload 7
L453:   ifle L491
L456:   getstatic Field ZKARKDQW sb [[I
L459:   iload 6
L461:   aaload
L462:   astore 8
L464:   iconst_0
L465:   istore 9
L467:   iload 20
L469:   ifeq L484
L472:   aload_0
L473:   aload 8
L475:   iload 9
L477:   iaload
L478:   invokespecial Method ZKARKDQW g (I)V
L481:   iinc 9 1
L484:   iload 9
L486:   iload 7
L488:   if_icmplt L472
L491:   iinc 6 -1
L494:   iload 6
L496:   ifge L443
L499:   return
L500:   iconst_0
L501:   istore 6
L503:   iload 20
L505:   ifeq L525
L508:   getstatic Field ZKARKDQW tb [I
L511:   iload 6
L513:   iconst_0
L514:   iastore
L515:   getstatic Field ZKARKDQW xb [I
L518:   iload 6
L520:   iconst_0
L521:   iastore
L522:   iinc 6 1
L525:   iload 6
L527:   bipush 12
L529:   if_icmplt L508
L532:   aload_0
L533:   getfield Field ZKARKDQW Y I
L536:   iconst_1
L537:   isub
L538:   istore 7
L540:   iload 20
L542:   ifeq L678
L545:   getstatic Field ZKARKDQW rb [I
L548:   iload 7
L550:   iaload
L551:   istore 8
L553:   iload 8
L555:   ifle L675
L558:   getstatic Field ZKARKDQW sb [[I
L561:   iload 7
L563:   aaload
L564:   astore 9
L566:   iconst_0
L567:   istore 10
L569:   iload 20
L571:   ifeq L668
L574:   aload 9
L576:   iload 10
L578:   iaload
L579:   istore 11
L581:   aload_0
L582:   getfield Field ZKARKDQW K [I
L585:   iload 11
L587:   iaload
L588:   istore 12
L590:   getstatic Field ZKARKDQW tb [I
L593:   iload 12
L595:   dup2
L596:   iaload
L597:   dup_x2
L598:   iconst_1
L599:   iadd
L600:   iastore
L601:   istore 13
L603:   getstatic Field ZKARKDQW ub [[I
L606:   iload 12
L608:   aaload
L609:   iload 13
L611:   iload 11
L613:   iastore
L614:   iload 12
L616:   bipush 10
L618:   if_icmpge L637
L621:   getstatic Field ZKARKDQW xb [I
L624:   iload 12
L626:   dup2
L627:   iaload
L628:   iload 7
L630:   iadd
L631:   iastore
L632:   iload 20
L634:   ifeq L665
L637:   iload 12
L639:   bipush 10
L641:   if_icmpne L657
L644:   getstatic Field ZKARKDQW vb [I
L647:   iload 13
L649:   iload 7
L651:   iastore
L652:   iload 20
L654:   ifeq L665
L657:   getstatic Field ZKARKDQW wb [I
L660:   iload 13
L662:   iload 7
L664:   iastore
L665:   iinc 10 1
L668:   iload 10
L670:   iload 8
L672:   if_icmplt L574
L675:   iinc 7 -1
L678:   iload 7
L680:   ifge L545
L683:   iconst_0
L684:   istore 8
L686:   getstatic Field ZKARKDQW tb [I
L689:   iconst_1
L690:   iaload
L691:   ifgt L702
L694:   getstatic Field ZKARKDQW tb [I
L697:   iconst_2
L698:   iaload
L699:   ifle L727
L702:   getstatic Field ZKARKDQW xb [I
L705:   iconst_1
L706:   iaload
L707:   getstatic Field ZKARKDQW xb [I
L710:   iconst_2
L711:   iaload
L712:   iadd
L713:   getstatic Field ZKARKDQW tb [I
L716:   iconst_1
L717:   iaload
L718:   getstatic Field ZKARKDQW tb [I
L721:   iconst_2
L722:   iaload
L723:   iadd
L724:   idiv
L725:   istore 8
L727:   iconst_0
L728:   istore 9
L730:   getstatic Field ZKARKDQW tb [I
L733:   iconst_3
L734:   iaload
L735:   ifgt L746
L738:   getstatic Field ZKARKDQW tb [I
L741:   iconst_4
L742:   iaload
L743:   ifle L771
L746:   getstatic Field ZKARKDQW xb [I
L749:   iconst_3
L750:   iaload
L751:   getstatic Field ZKARKDQW xb [I
L754:   iconst_4
L755:   iaload
L756:   iadd
L757:   getstatic Field ZKARKDQW tb [I
L760:   iconst_3
L761:   iaload
L762:   getstatic Field ZKARKDQW tb [I
L765:   iconst_4
L766:   iaload
L767:   iadd
L768:   idiv
L769:   istore 9
L771:   iconst_0
L772:   istore 10
L774:   getstatic Field ZKARKDQW tb [I
L777:   bipush 6
L779:   iaload
L780:   ifgt L792
L783:   getstatic Field ZKARKDQW tb [I
L786:   bipush 8
L788:   iaload
L789:   ifle L821
L792:   getstatic Field ZKARKDQW xb [I
L795:   bipush 6
L797:   iaload
L798:   getstatic Field ZKARKDQW xb [I
L801:   bipush 8
L803:   iaload
L804:   iadd
L805:   getstatic Field ZKARKDQW tb [I
L808:   bipush 6
L810:   iaload
L811:   getstatic Field ZKARKDQW tb [I
L814:   bipush 8
L816:   iaload
L817:   iadd
L818:   idiv
L819:   istore 10
L821:   iconst_0
L822:   istore 12
L824:   getstatic Field ZKARKDQW tb [I
L827:   bipush 10
L829:   iaload
L830:   istore 13
L832:   getstatic Field ZKARKDQW ub [[I
L835:   bipush 10
L837:   aaload
L838:   astore 14
L840:   getstatic Field ZKARKDQW vb [I
L843:   astore 15
L845:   iload 12
L847:   iload 13
L849:   if_icmpne L876
L852:   iconst_0
L853:   istore 12
L855:   getstatic Field ZKARKDQW tb [I
L858:   bipush 11
L860:   iaload
L861:   istore 13
L863:   getstatic Field ZKARKDQW ub [[I
L866:   bipush 11
L868:   aaload
L869:   astore 14
L871:   getstatic Field ZKARKDQW wb [I
L874:   astore 15
L876:   iload 12
L878:   iload 13
L880:   if_icmpge L895
L883:   aload 15
L885:   iload 12
L887:   iaload
L888:   istore 11
L890:   iload 20
L892:   ifeq L900
L895:   sipush -1000
L898:   istore 11
L900:   iconst_0
L901:   istore 16
L903:   iload 20
L905:   ifeq L1236
L908:   aload_0
L909:   aload 14
L911:   iload 12
L913:   iinc 12 1
L916:   iaload
L917:   invokespecial Method ZKARKDQW g (I)V
L920:   iload 12
L922:   iload 13
L924:   if_icmpne L962
L927:   aload 14
L929:   getstatic Field ZKARKDQW ub [[I
L932:   bipush 11
L934:   aaload
L935:   if_acmpeq L962
L938:   iconst_0
L939:   istore 12
L941:   getstatic Field ZKARKDQW tb [I
L944:   bipush 11
L946:   iaload
L947:   istore 13
L949:   getstatic Field ZKARKDQW ub [[I
L952:   bipush 11
L954:   aaload
L955:   astore 14
L957:   getstatic Field ZKARKDQW wb [I
L960:   astore 15
L962:   iload 12
L964:   iload 13
L966:   if_icmpge L981
L969:   aload 15
L971:   iload 12
L973:   iaload
L974:   istore 11
L976:   iload 20
L978:   ifeq L986
L981:   sipush -1000
L984:   istore 11
L986:   iload 16
L988:   ifne L1081
L991:   iload 11
L993:   iload 8
L995:   if_icmpgt L908
L998:   iload 20
L1000:  ifeq L1081
L1003:  aload_0
L1004:  aload 14
L1006:  iload 12
L1008:  iinc 12 1
L1011:  iaload
L1012:  invokespecial Method ZKARKDQW g (I)V
L1015:  iload 12
L1017:  iload 13
L1019:  if_icmpne L1057
L1022:  aload 14
L1024:  getstatic Field ZKARKDQW ub [[I
L1027:  bipush 11
L1029:  aaload
L1030:  if_acmpeq L1057
L1033:  iconst_0
L1034:  istore 12
L1036:  getstatic Field ZKARKDQW tb [I
L1039:  bipush 11
L1041:  iaload
L1042:  istore 13
L1044:  getstatic Field ZKARKDQW ub [[I
L1047:  bipush 11
L1049:  aaload
L1050:  astore 14
L1052:  getstatic Field ZKARKDQW wb [I
L1055:  astore 15
L1057:  iload 12
L1059:  iload 13
L1061:  if_icmpge L1076
L1064:  aload 15
L1066:  iload 12
L1068:  iaload
L1069:  istore 11
L1071:  iload 20
L1073:  ifeq L1081
L1076:  sipush -1000
L1079:  istore 11
L1081:  iload 16
L1083:  iconst_3
L1084:  if_icmpne L1177
L1087:  iload 11
L1089:  iload 9
L1091:  if_icmpgt L1003
L1094:  iload 20
L1096:  ifeq L1177
L1099:  aload_0
L1100:  aload 14
L1102:  iload 12
L1104:  iinc 12 1
L1107:  iaload
L1108:  invokespecial Method ZKARKDQW g (I)V
L1111:  iload 12
L1113:  iload 13
L1115:  if_icmpne L1153
L1118:  aload 14
L1120:  getstatic Field ZKARKDQW ub [[I
L1123:  bipush 11
L1125:  aaload
L1126:  if_acmpeq L1153
L1129:  iconst_0
L1130:  istore 12
L1132:  getstatic Field ZKARKDQW tb [I
L1135:  bipush 11
L1137:  iaload
L1138:  istore 13
L1140:  getstatic Field ZKARKDQW ub [[I
L1143:  bipush 11
L1145:  aaload
L1146:  astore 14
L1148:  getstatic Field ZKARKDQW wb [I
L1151:  astore 15
L1153:  iload 12
L1155:  iload 13
L1157:  if_icmpge L1172
L1160:  aload 15
L1162:  iload 12
L1164:  iaload
L1165:  istore 11
L1167:  iload 20
L1169:  ifeq L1177
L1172:  sipush -1000
L1175:  istore 11
L1177:  iload 16
L1179:  iconst_5
L1180:  if_icmpne L1190
L1183:  iload 11
L1185:  iload 10
L1187:  if_icmpgt L1099
L1190:  getstatic Field ZKARKDQW tb [I
L1193:  iload 16
L1195:  iaload
L1196:  istore 17
L1198:  getstatic Field ZKARKDQW ub [[I
L1201:  iload 16
L1203:  aaload
L1204:  astore 18
L1206:  iconst_0
L1207:  istore 19
L1209:  iload 20
L1211:  ifeq L1226
L1214:  aload_0
L1215:  aload 18
L1217:  iload 19
L1219:  iaload
L1220:  invokespecial Method ZKARKDQW g (I)V
L1223:  iinc 19 1
L1226:  iload 19
L1228:  iload 17
L1230:  if_icmplt L1214
L1233:  iinc 16 1
L1236:  iload 16
L1238:  bipush 10
L1240:  if_icmplt L986
L1243:  iload 20
L1245:  ifeq L1326
L1248:  aload_0
L1249:  aload 14
L1251:  iload 12
L1253:  iinc 12 1
L1256:  iaload
L1257:  invokespecial Method ZKARKDQW g (I)V
L1260:  iload 12
L1262:  iload 13
L1264:  if_icmpne L1302
L1267:  aload 14
L1269:  getstatic Field ZKARKDQW ub [[I
L1272:  bipush 11
L1274:  aaload
L1275:  if_acmpeq L1302
L1278:  iconst_0
L1279:  istore 12
L1281:  getstatic Field ZKARKDQW ub [[I
L1284:  bipush 11
L1286:  aaload
L1287:  astore 14
L1289:  getstatic Field ZKARKDQW tb [I
L1292:  bipush 11
L1294:  iaload
L1295:  istore 13
L1297:  getstatic Field ZKARKDQW wb [I
L1300:  astore 15
L1302:  iload 12
L1304:  iload 13
L1306:  if_icmpge L1321
L1309:  aload 15
L1311:  iload 12
L1313:  iaload
L1314:  istore 11
L1316:  iload 20
L1318:  ifeq L1326
L1321:  sipush -1000
L1324:  istore 11
L1326:  iload 11
L1328:  sipush -1000
L1331:  if_icmpne L1248
L1334:  return
L1335:  
    .end code
.end method

.method private final g : (I)V
    .code stack 21 locals 11
L0:     getstatic Field XHHRODPC l Z
L3:     istore 10
L5:     getstatic Field ZKARKDQW kb [Z
L8:     iload_1
L9:     baload
L10:    ifeq L19
L13:    aload_0
L14:    iload_1
L15:    invokespecial Method ZKARKDQW h (I)V
L18:    return
L19:    aload_0
L20:    getfield Field ZKARKDQW D [I
L23:    iload_1
L24:    iaload
L25:    istore_2
L26:    aload_0
L27:    getfield Field ZKARKDQW E [I
L30:    iload_1
L31:    iaload
L32:    istore_3
L33:    aload_0
L34:    getfield Field ZKARKDQW F [I
L37:    iload_1
L38:    iaload
L39:    istore 4
L41:    getstatic Field ZKARKDQW jb [Z
L44:    iload_1
L45:    baload
L46:    putstatic Field OPPOFIOL B Z
L49:    aload_0
L50:    getfield Field ZKARKDQW L [I
L53:    ifnonnull L65
L56:    iconst_0
L57:    putstatic Field OPPOFIOL E I
L60:    iload 10
L62:    ifeq L74
L65:    aload_0
L66:    getfield Field ZKARKDQW L [I
L69:    iload_1
L70:    iaload
L71:    putstatic Field OPPOFIOL E I
L74:    aload_0
L75:    getfield Field ZKARKDQW J [I
L78:    ifnonnull L89
L81:    iconst_0
L82:    istore 5
L84:    iload 10
L86:    ifeq L99
L89:    aload_0
L90:    getfield Field ZKARKDQW J [I
L93:    iload_1
L94:    iaload
L95:    iconst_3
L96:    iand
L97:    istore 5
L99:    iload 5
L101:   ifne L158
L104:   getstatic Field ZKARKDQW mb [I
L107:   iload_2
L108:   iaload
L109:   getstatic Field ZKARKDQW mb [I
L112:   iload_3
L113:   iaload
L114:   getstatic Field ZKARKDQW mb [I
L117:   iload 4
L119:   iaload
L120:   getstatic Field ZKARKDQW lb [I
L123:   iload_2
L124:   iaload
L125:   getstatic Field ZKARKDQW lb [I
L128:   iload_3
L129:   iaload
L130:   getstatic Field ZKARKDQW lb [I
L133:   iload 4
L135:   iaload
L136:   aload_0
L137:   getfield Field ZKARKDQW G [I
L140:   iload_1
L141:   iaload
L142:   aload_0
L143:   getfield Field ZKARKDQW H [I
L146:   iload_1
L147:   iaload
L148:   aload_0
L149:   getfield Field ZKARKDQW I [I
L152:   iload_1
L153:   iaload
L154:   invokestatic Method OPPOFIOL a (IIIIIIIII)V
L157:   return
L158:   iload 5
L160:   iconst_1
L161:   if_icmpne L210
L164:   getstatic Field ZKARKDQW mb [I
L167:   iload_2
L168:   iaload
L169:   getstatic Field ZKARKDQW mb [I
L172:   iload_3
L173:   iaload
L174:   getstatic Field ZKARKDQW mb [I
L177:   iload 4
L179:   iaload
L180:   getstatic Field ZKARKDQW lb [I
L183:   iload_2
L184:   iaload
L185:   getstatic Field ZKARKDQW lb [I
L188:   iload_3
L189:   iaload
L190:   getstatic Field ZKARKDQW lb [I
L193:   iload 4
L195:   iaload
L196:   getstatic Field ZKARKDQW Lb [I
L199:   aload_0
L200:   getfield Field ZKARKDQW G [I
L203:   iload_1
L204:   iaload
L205:   iaload
L206:   invokestatic Method OPPOFIOL c (IIIIIII)V
L209:   return
L210:   iload 5
L212:   iconst_2
L213:   if_icmpne L367
L216:   aload_0
L217:   getfield Field ZKARKDQW J [I
L220:   iload_1
L221:   iaload
L222:   iconst_2
L223:   ishr
L224:   istore 6
L226:   aload_0
L227:   getfield Field ZKARKDQW P [I
L230:   iload 6
L232:   iaload
L233:   istore 7
L235:   aload_0
L236:   getfield Field ZKARKDQW Q [I
L239:   iload 6
L241:   iaload
L242:   istore 8
L244:   aload_0
L245:   getfield Field ZKARKDQW R [I
L248:   iload 6
L250:   iaload
L251:   istore 9
L253:   getstatic Field ZKARKDQW mb [I
L256:   iload_2
L257:   iaload
L258:   getstatic Field ZKARKDQW mb [I
L261:   iload_3
L262:   iaload
L263:   getstatic Field ZKARKDQW mb [I
L266:   iload 4
L268:   iaload
L269:   getstatic Field ZKARKDQW lb [I
L272:   iload_2
L273:   iaload
L274:   getstatic Field ZKARKDQW lb [I
L277:   iload_3
L278:   iaload
L279:   getstatic Field ZKARKDQW lb [I
L282:   iload 4
L284:   iaload
L285:   aload_0
L286:   getfield Field ZKARKDQW G [I
L289:   iload_1
L290:   iaload
L291:   aload_0
L292:   getfield Field ZKARKDQW H [I
L295:   iload_1
L296:   iaload
L297:   aload_0
L298:   getfield Field ZKARKDQW I [I
L301:   iload_1
L302:   iaload
L303:   getstatic Field ZKARKDQW ob [I
L306:   iload 7
L308:   iaload
L309:   getstatic Field ZKARKDQW ob [I
L312:   iload 8
L314:   iaload
L315:   getstatic Field ZKARKDQW ob [I
L318:   iload 9
L320:   iaload
L321:   getstatic Field ZKARKDQW pb [I
L324:   iload 7
L326:   iaload
L327:   getstatic Field ZKARKDQW pb [I
L330:   iload 8
L332:   iaload
L333:   getstatic Field ZKARKDQW pb [I
L336:   iload 9
L338:   iaload
L339:   getstatic Field ZKARKDQW qb [I
L342:   iload 7
L344:   iaload
L345:   getstatic Field ZKARKDQW qb [I
L348:   iload 8
L350:   iaload
L351:   getstatic Field ZKARKDQW qb [I
L354:   iload 9
L356:   iaload
L357:   aload_0
L358:   getfield Field ZKARKDQW M [I
L361:   iload_1
L362:   iaload
L363:   invokestatic Method OPPOFIOL a (IIIIIIIIIIIIIIIIIII)V
L366:   return
L367:   iload 5
L369:   iconst_3
L370:   if_icmpne L523
L373:   aload_0
L374:   getfield Field ZKARKDQW J [I
L377:   iload_1
L378:   iaload
L379:   iconst_2
L380:   ishr
L381:   istore 6
L383:   aload_0
L384:   getfield Field ZKARKDQW P [I
L387:   iload 6
L389:   iaload
L390:   istore 7
L392:   aload_0
L393:   getfield Field ZKARKDQW Q [I
L396:   iload 6
L398:   iaload
L399:   istore 8
L401:   aload_0
L402:   getfield Field ZKARKDQW R [I
L405:   iload 6
L407:   iaload
L408:   istore 9
L410:   getstatic Field ZKARKDQW mb [I
L413:   iload_2
L414:   iaload
L415:   getstatic Field ZKARKDQW mb [I
L418:   iload_3
L419:   iaload
L420:   getstatic Field ZKARKDQW mb [I
L423:   iload 4
L425:   iaload
L426:   getstatic Field ZKARKDQW lb [I
L429:   iload_2
L430:   iaload
L431:   getstatic Field ZKARKDQW lb [I
L434:   iload_3
L435:   iaload
L436:   getstatic Field ZKARKDQW lb [I
L439:   iload 4
L441:   iaload
L442:   aload_0
L443:   getfield Field ZKARKDQW G [I
L446:   iload_1
L447:   iaload
L448:   aload_0
L449:   getfield Field ZKARKDQW G [I
L452:   iload_1
L453:   iaload
L454:   aload_0
L455:   getfield Field ZKARKDQW G [I
L458:   iload_1
L459:   iaload
L460:   getstatic Field ZKARKDQW ob [I
L463:   iload 7
L465:   iaload
L466:   getstatic Field ZKARKDQW ob [I
L469:   iload 8
L471:   iaload
L472:   getstatic Field ZKARKDQW ob [I
L475:   iload 9
L477:   iaload
L478:   getstatic Field ZKARKDQW pb [I
L481:   iload 7
L483:   iaload
L484:   getstatic Field ZKARKDQW pb [I
L487:   iload 8
L489:   iaload
L490:   getstatic Field ZKARKDQW pb [I
L493:   iload 9
L495:   iaload
L496:   getstatic Field ZKARKDQW qb [I
L499:   iload 7
L501:   iaload
L502:   getstatic Field ZKARKDQW qb [I
L505:   iload 8
L507:   iaload
L508:   getstatic Field ZKARKDQW qb [I
L511:   iload 9
L513:   iaload
L514:   aload_0
L515:   getfield Field ZKARKDQW M [I
L518:   iload_1
L519:   iaload
L520:   invokestatic Method OPPOFIOL a (IIIIIIIIIIIIIIIIIII)V
L523:   return
L524:   
    .end code
.end method

.method private final h : (I)V
    .code stack 21 locals 23
L0:     getstatic Field XHHRODPC l Z
L3:     istore 22
L5:     getstatic Field OPPOFIOL F I
L8:     istore_2
L9:     getstatic Field OPPOFIOL G I
L12:    istore_3
L13:    iconst_0
L14:    istore 4
L16:    aload_0
L17:    getfield Field ZKARKDQW D [I
L20:    iload_1
L21:    iaload
L22:    istore 5
L24:    aload_0
L25:    getfield Field ZKARKDQW E [I
L28:    iload_1
L29:    iaload
L30:    istore 6
L32:    aload_0
L33:    getfield Field ZKARKDQW F [I
L36:    iload_1
L37:    iaload
L38:    istore 7
L40:    getstatic Field ZKARKDQW qb [I
L43:    iload 5
L45:    iaload
L46:    istore 8
L48:    getstatic Field ZKARKDQW qb [I
L51:    iload 6
L53:    iaload
L54:    istore 9
L56:    getstatic Field ZKARKDQW qb [I
L59:    iload 7
L61:    iaload
L62:    istore 10
L64:    iload 8
L66:    bipush 50
L68:    if_icmplt L115
L71:    getstatic Field ZKARKDQW yb [I
L74:    iload 4
L76:    getstatic Field ZKARKDQW lb [I
L79:    iload 5
L81:    iaload
L82:    iastore
L83:    getstatic Field ZKARKDQW zb [I
L86:    iload 4
L88:    getstatic Field ZKARKDQW mb [I
L91:    iload 5
L93:    iaload
L94:    iastore
L95:    getstatic Field ZKARKDQW Ab [I
L98:    iload 4
L100:   iinc 4 1
L103:   aload_0
L104:   getfield Field ZKARKDQW G [I
L107:   iload_1
L108:   iaload
L109:   iastore
L110:   iload 22
L112:   ifeq L369
L115:   getstatic Field ZKARKDQW ob [I
L118:   iload 5
L120:   iaload
L121:   istore 11
L123:   getstatic Field ZKARKDQW pb [I
L126:   iload 5
L128:   iaload
L129:   istore 12
L131:   aload_0
L132:   getfield Field ZKARKDQW G [I
L135:   iload_1
L136:   iaload
L137:   istore 13
L139:   iload 10
L141:   bipush 50
L143:   if_icmplt L254
L146:   bipush 50
L148:   iload 8
L150:   isub
L151:   getstatic Field ZKARKDQW Mb [I
L154:   iload 10
L156:   iload 8
L158:   isub
L159:   iaload
L160:   imul
L161:   istore 14
L163:   getstatic Field ZKARKDQW yb [I
L166:   iload 4
L168:   iload_2
L169:   iload 11
L171:   getstatic Field ZKARKDQW ob [I
L174:   iload 7
L176:   iaload
L177:   iload 11
L179:   isub
L180:   iload 14
L182:   imul
L183:   bipush 16
L185:   ishr
L186:   iadd
L187:   bipush 9
L189:   ishl
L190:   bipush 50
L192:   idiv
L193:   iadd
L194:   iastore
L195:   getstatic Field ZKARKDQW zb [I
L198:   iload 4
L200:   iload_3
L201:   iload 12
L203:   getstatic Field ZKARKDQW pb [I
L206:   iload 7
L208:   iaload
L209:   iload 12
L211:   isub
L212:   iload 14
L214:   imul
L215:   bipush 16
L217:   ishr
L218:   iadd
L219:   bipush 9
L221:   ishl
L222:   bipush 50
L224:   idiv
L225:   iadd
L226:   iastore
L227:   getstatic Field ZKARKDQW Ab [I
L230:   iload 4
L232:   iinc 4 1
L235:   iload 13
L237:   aload_0
L238:   getfield Field ZKARKDQW I [I
L241:   iload_1
L242:   iaload
L243:   iload 13
L245:   isub
L246:   iload 14
L248:   imul
L249:   bipush 16
L251:   ishr
L252:   iadd
L253:   iastore
L254:   iload 9
L256:   bipush 50
L258:   if_icmplt L369
L261:   bipush 50
L263:   iload 8
L265:   isub
L266:   getstatic Field ZKARKDQW Mb [I
L269:   iload 9
L271:   iload 8
L273:   isub
L274:   iaload
L275:   imul
L276:   istore 14
L278:   getstatic Field ZKARKDQW yb [I
L281:   iload 4
L283:   iload_2
L284:   iload 11
L286:   getstatic Field ZKARKDQW ob [I
L289:   iload 6
L291:   iaload
L292:   iload 11
L294:   isub
L295:   iload 14
L297:   imul
L298:   bipush 16
L300:   ishr
L301:   iadd
L302:   bipush 9
L304:   ishl
L305:   bipush 50
L307:   idiv
L308:   iadd
L309:   iastore
L310:   getstatic Field ZKARKDQW zb [I
L313:   iload 4
L315:   iload_3
L316:   iload 12
L318:   getstatic Field ZKARKDQW pb [I
L321:   iload 6
L323:   iaload
L324:   iload 12
L326:   isub
L327:   iload 14
L329:   imul
L330:   bipush 16
L332:   ishr
L333:   iadd
L334:   bipush 9
L336:   ishl
L337:   bipush 50
L339:   idiv
L340:   iadd
L341:   iastore
L342:   getstatic Field ZKARKDQW Ab [I
L345:   iload 4
L347:   iinc 4 1
L350:   iload 13
L352:   aload_0
L353:   getfield Field ZKARKDQW H [I
L356:   iload_1
L357:   iaload
L358:   iload 13
L360:   isub
L361:   iload 14
L363:   imul
L364:   bipush 16
L366:   ishr
L367:   iadd
L368:   iastore
L369:   iload 9
L371:   bipush 50
L373:   if_icmplt L420
L376:   getstatic Field ZKARKDQW yb [I
L379:   iload 4
L381:   getstatic Field ZKARKDQW lb [I
L384:   iload 6
L386:   iaload
L387:   iastore
L388:   getstatic Field ZKARKDQW zb [I
L391:   iload 4
L393:   getstatic Field ZKARKDQW mb [I
L396:   iload 6
L398:   iaload
L399:   iastore
L400:   getstatic Field ZKARKDQW Ab [I
L403:   iload 4
L405:   iinc 4 1
L408:   aload_0
L409:   getfield Field ZKARKDQW H [I
L412:   iload_1
L413:   iaload
L414:   iastore
L415:   iload 22
L417:   ifeq L674
L420:   getstatic Field ZKARKDQW ob [I
L423:   iload 6
L425:   iaload
L426:   istore 11
L428:   getstatic Field ZKARKDQW pb [I
L431:   iload 6
L433:   iaload
L434:   istore 12
L436:   aload_0
L437:   getfield Field ZKARKDQW H [I
L440:   iload_1
L441:   iaload
L442:   istore 13
L444:   iload 8
L446:   bipush 50
L448:   if_icmplt L559
L451:   bipush 50
L453:   iload 9
L455:   isub
L456:   getstatic Field ZKARKDQW Mb [I
L459:   iload 8
L461:   iload 9
L463:   isub
L464:   iaload
L465:   imul
L466:   istore 14
L468:   getstatic Field ZKARKDQW yb [I
L471:   iload 4
L473:   iload_2
L474:   iload 11
L476:   getstatic Field ZKARKDQW ob [I
L479:   iload 5
L481:   iaload
L482:   iload 11
L484:   isub
L485:   iload 14
L487:   imul
L488:   bipush 16
L490:   ishr
L491:   iadd
L492:   bipush 9
L494:   ishl
L495:   bipush 50
L497:   idiv
L498:   iadd
L499:   iastore
L500:   getstatic Field ZKARKDQW zb [I
L503:   iload 4
L505:   iload_3
L506:   iload 12
L508:   getstatic Field ZKARKDQW pb [I
L511:   iload 5
L513:   iaload
L514:   iload 12
L516:   isub
L517:   iload 14
L519:   imul
L520:   bipush 16
L522:   ishr
L523:   iadd
L524:   bipush 9
L526:   ishl
L527:   bipush 50
L529:   idiv
L530:   iadd
L531:   iastore
L532:   getstatic Field ZKARKDQW Ab [I
L535:   iload 4
L537:   iinc 4 1
L540:   iload 13
L542:   aload_0
L543:   getfield Field ZKARKDQW G [I
L546:   iload_1
L547:   iaload
L548:   iload 13
L550:   isub
L551:   iload 14
L553:   imul
L554:   bipush 16
L556:   ishr
L557:   iadd
L558:   iastore
L559:   iload 10
L561:   bipush 50
L563:   if_icmplt L674
L566:   bipush 50
L568:   iload 9
L570:   isub
L571:   getstatic Field ZKARKDQW Mb [I
L574:   iload 10
L576:   iload 9
L578:   isub
L579:   iaload
L580:   imul
L581:   istore 14
L583:   getstatic Field ZKARKDQW yb [I
L586:   iload 4
L588:   iload_2
L589:   iload 11
L591:   getstatic Field ZKARKDQW ob [I
L594:   iload 7
L596:   iaload
L597:   iload 11
L599:   isub
L600:   iload 14
L602:   imul
L603:   bipush 16
L605:   ishr
L606:   iadd
L607:   bipush 9
L609:   ishl
L610:   bipush 50
L612:   idiv
L613:   iadd
L614:   iastore
L615:   getstatic Field ZKARKDQW zb [I
L618:   iload 4
L620:   iload_3
L621:   iload 12
L623:   getstatic Field ZKARKDQW pb [I
L626:   iload 7
L628:   iaload
L629:   iload 12
L631:   isub
L632:   iload 14
L634:   imul
L635:   bipush 16
L637:   ishr
L638:   iadd
L639:   bipush 9
L641:   ishl
L642:   bipush 50
L644:   idiv
L645:   iadd
L646:   iastore
L647:   getstatic Field ZKARKDQW Ab [I
L650:   iload 4
L652:   iinc 4 1
L655:   iload 13
L657:   aload_0
L658:   getfield Field ZKARKDQW I [I
L661:   iload_1
L662:   iaload
L663:   iload 13
L665:   isub
L666:   iload 14
L668:   imul
L669:   bipush 16
L671:   ishr
L672:   iadd
L673:   iastore
L674:   iload 10
L676:   bipush 50
L678:   if_icmplt L725
L681:   getstatic Field ZKARKDQW yb [I
L684:   iload 4
L686:   getstatic Field ZKARKDQW lb [I
L689:   iload 7
L691:   iaload
L692:   iastore
L693:   getstatic Field ZKARKDQW zb [I
L696:   iload 4
L698:   getstatic Field ZKARKDQW mb [I
L701:   iload 7
L703:   iaload
L704:   iastore
L705:   getstatic Field ZKARKDQW Ab [I
L708:   iload 4
L710:   iinc 4 1
L713:   aload_0
L714:   getfield Field ZKARKDQW I [I
L717:   iload_1
L718:   iaload
L719:   iastore
L720:   iload 22
L722:   ifeq L979
L725:   getstatic Field ZKARKDQW ob [I
L728:   iload 7
L730:   iaload
L731:   istore 11
L733:   getstatic Field ZKARKDQW pb [I
L736:   iload 7
L738:   iaload
L739:   istore 12
L741:   aload_0
L742:   getfield Field ZKARKDQW I [I
L745:   iload_1
L746:   iaload
L747:   istore 13
L749:   iload 9
L751:   bipush 50
L753:   if_icmplt L864
L756:   bipush 50
L758:   iload 10
L760:   isub
L761:   getstatic Field ZKARKDQW Mb [I
L764:   iload 9
L766:   iload 10
L768:   isub
L769:   iaload
L770:   imul
L771:   istore 14
L773:   getstatic Field ZKARKDQW yb [I
L776:   iload 4
L778:   iload_2
L779:   iload 11
L781:   getstatic Field ZKARKDQW ob [I
L784:   iload 6
L786:   iaload
L787:   iload 11
L789:   isub
L790:   iload 14
L792:   imul
L793:   bipush 16
L795:   ishr
L796:   iadd
L797:   bipush 9
L799:   ishl
L800:   bipush 50
L802:   idiv
L803:   iadd
L804:   iastore
L805:   getstatic Field ZKARKDQW zb [I
L808:   iload 4
L810:   iload_3
L811:   iload 12
L813:   getstatic Field ZKARKDQW pb [I
L816:   iload 6
L818:   iaload
L819:   iload 12
L821:   isub
L822:   iload 14
L824:   imul
L825:   bipush 16
L827:   ishr
L828:   iadd
L829:   bipush 9
L831:   ishl
L832:   bipush 50
L834:   idiv
L835:   iadd
L836:   iastore
L837:   getstatic Field ZKARKDQW Ab [I
L840:   iload 4
L842:   iinc 4 1
L845:   iload 13
L847:   aload_0
L848:   getfield Field ZKARKDQW H [I
L851:   iload_1
L852:   iaload
L853:   iload 13
L855:   isub
L856:   iload 14
L858:   imul
L859:   bipush 16
L861:   ishr
L862:   iadd
L863:   iastore
L864:   iload 8
L866:   bipush 50
L868:   if_icmplt L979
L871:   bipush 50
L873:   iload 10
L875:   isub
L876:   getstatic Field ZKARKDQW Mb [I
L879:   iload 8
L881:   iload 10
L883:   isub
L884:   iaload
L885:   imul
L886:   istore 14
L888:   getstatic Field ZKARKDQW yb [I
L891:   iload 4
L893:   iload_2
L894:   iload 11
L896:   getstatic Field ZKARKDQW ob [I
L899:   iload 5
L901:   iaload
L902:   iload 11
L904:   isub
L905:   iload 14
L907:   imul
L908:   bipush 16
L910:   ishr
L911:   iadd
L912:   bipush 9
L914:   ishl
L915:   bipush 50
L917:   idiv
L918:   iadd
L919:   iastore
L920:   getstatic Field ZKARKDQW zb [I
L923:   iload 4
L925:   iload_3
L926:   iload 12
L928:   getstatic Field ZKARKDQW pb [I
L931:   iload 5
L933:   iaload
L934:   iload 12
L936:   isub
L937:   iload 14
L939:   imul
L940:   bipush 16
L942:   ishr
L943:   iadd
L944:   bipush 9
L946:   ishl
L947:   bipush 50
L949:   idiv
L950:   iadd
L951:   iastore
L952:   getstatic Field ZKARKDQW Ab [I
L955:   iload 4
L957:   iinc 4 1
L960:   iload 13
L962:   aload_0
L963:   getfield Field ZKARKDQW G [I
L966:   iload_1
L967:   iaload
L968:   iload 13
L970:   isub
L971:   iload 14
L973:   imul
L974:   bipush 16
L976:   ishr
L977:   iadd
L978:   iastore
L979:   getstatic Field ZKARKDQW yb [I
L982:   iconst_0
L983:   iaload
L984:   istore 11
L986:   getstatic Field ZKARKDQW yb [I
L989:   iconst_1
L990:   iaload
L991:   istore 12
L993:   getstatic Field ZKARKDQW yb [I
L996:   iconst_2
L997:   iaload
L998:   istore 13
L1000:  getstatic Field ZKARKDQW zb [I
L1003:  iconst_0
L1004:  iaload
L1005:  istore 14
L1007:  getstatic Field ZKARKDQW zb [I
L1010:  iconst_1
L1011:  iaload
L1012:  istore 15
L1014:  getstatic Field ZKARKDQW zb [I
L1017:  iconst_2
L1018:  iaload
L1019:  istore 16
L1021:  iload 11
L1023:  iload 12
L1025:  isub
L1026:  iload 16
L1028:  iload 15
L1030:  isub
L1031:  imul
L1032:  iload 14
L1034:  iload 15
L1036:  isub
L1037:  iload 13
L1039:  iload 12
L1041:  isub
L1042:  imul
L1043:  isub
L1044:  ifle L2164
L1047:  iconst_0
L1048:  putstatic Field OPPOFIOL B Z
L1051:  iload 4
L1053:  iconst_3
L1054:  if_icmpne L1475
L1057:  iload 11
L1059:  iflt L1096
L1062:  iload 12
L1064:  iflt L1096
L1067:  iload 13
L1069:  iflt L1096
L1072:  iload 11
L1074:  getstatic Field AFCKELYG t I
L1077:  if_icmpgt L1096
L1080:  iload 12
L1082:  getstatic Field AFCKELYG t I
L1085:  if_icmpgt L1096
L1088:  iload 13
L1090:  getstatic Field AFCKELYG t I
L1093:  if_icmple L1100
L1096:  iconst_1
L1097:  putstatic Field OPPOFIOL B Z
L1100:  aload_0
L1101:  getfield Field ZKARKDQW J [I
L1104:  ifnonnull L1115
L1107:  iconst_0
L1108:  istore 17
L1110:  iload 22
L1112:  ifeq L1125
L1115:  aload_0
L1116:  getfield Field ZKARKDQW J [I
L1119:  iload_1
L1120:  iaload
L1121:  iconst_3
L1122:  iand
L1123:  istore 17
L1125:  iload 17
L1127:  ifne L1165
L1130:  iload 14
L1132:  iload 15
L1134:  iload 16
L1136:  iload 11
L1138:  iload 12
L1140:  iload 13
L1142:  getstatic Field ZKARKDQW Ab [I
L1145:  iconst_0
L1146:  iaload
L1147:  getstatic Field ZKARKDQW Ab [I
L1150:  iconst_1
L1151:  iaload
L1152:  getstatic Field ZKARKDQW Ab [I
L1155:  iconst_2
L1156:  iaload
L1157:  invokestatic Method OPPOFIOL a (IIIIIIIII)V
L1160:  iload 22
L1162:  ifeq L1475
L1165:  iload 17
L1167:  iconst_1
L1168:  if_icmpne L1201
L1171:  iload 14
L1173:  iload 15
L1175:  iload 16
L1177:  iload 11
L1179:  iload 12
L1181:  iload 13
L1183:  getstatic Field ZKARKDQW Lb [I
L1186:  aload_0
L1187:  getfield Field ZKARKDQW G [I
L1190:  iload_1
L1191:  iaload
L1192:  iaload
L1193:  invokestatic Method OPPOFIOL c (IIIIIII)V
L1196:  iload 22
L1198:  ifeq L1475
L1201:  iload 17
L1203:  iconst_2
L1204:  if_icmpne L1339
L1207:  aload_0
L1208:  getfield Field ZKARKDQW J [I
L1211:  iload_1
L1212:  iaload
L1213:  iconst_2
L1214:  ishr
L1215:  istore 18
L1217:  aload_0
L1218:  getfield Field ZKARKDQW P [I
L1221:  iload 18
L1223:  iaload
L1224:  istore 19
L1226:  aload_0
L1227:  getfield Field ZKARKDQW Q [I
L1230:  iload 18
L1232:  iaload
L1233:  istore 20
L1235:  aload_0
L1236:  getfield Field ZKARKDQW R [I
L1239:  iload 18
L1241:  iaload
L1242:  istore 21
L1244:  iload 14
L1246:  iload 15
L1248:  iload 16
L1250:  iload 11
L1252:  iload 12
L1254:  iload 13
L1256:  getstatic Field ZKARKDQW Ab [I
L1259:  iconst_0
L1260:  iaload
L1261:  getstatic Field ZKARKDQW Ab [I
L1264:  iconst_1
L1265:  iaload
L1266:  getstatic Field ZKARKDQW Ab [I
L1269:  iconst_2
L1270:  iaload
L1271:  getstatic Field ZKARKDQW ob [I
L1274:  iload 19
L1276:  iaload
L1277:  getstatic Field ZKARKDQW ob [I
L1280:  iload 20
L1282:  iaload
L1283:  getstatic Field ZKARKDQW ob [I
L1286:  iload 21
L1288:  iaload
L1289:  getstatic Field ZKARKDQW pb [I
L1292:  iload 19
L1294:  iaload
L1295:  getstatic Field ZKARKDQW pb [I
L1298:  iload 20
L1300:  iaload
L1301:  getstatic Field ZKARKDQW pb [I
L1304:  iload 21
L1306:  iaload
L1307:  getstatic Field ZKARKDQW qb [I
L1310:  iload 19
L1312:  iaload
L1313:  getstatic Field ZKARKDQW qb [I
L1316:  iload 20
L1318:  iaload
L1319:  getstatic Field ZKARKDQW qb [I
L1322:  iload 21
L1324:  iaload
L1325:  aload_0
L1326:  getfield Field ZKARKDQW M [I
L1329:  iload_1
L1330:  iaload
L1331:  invokestatic Method OPPOFIOL a (IIIIIIIIIIIIIIIIIII)V
L1334:  iload 22
L1336:  ifeq L1475
L1339:  iload 17
L1341:  iconst_3
L1342:  if_icmpne L1475
L1345:  aload_0
L1346:  getfield Field ZKARKDQW J [I
L1349:  iload_1
L1350:  iaload
L1351:  iconst_2
L1352:  ishr
L1353:  istore 18
L1355:  aload_0
L1356:  getfield Field ZKARKDQW P [I
L1359:  iload 18
L1361:  iaload
L1362:  istore 19
L1364:  aload_0
L1365:  getfield Field ZKARKDQW Q [I
L1368:  iload 18
L1370:  iaload
L1371:  istore 20
L1373:  aload_0
L1374:  getfield Field ZKARKDQW R [I
L1377:  iload 18
L1379:  iaload
L1380:  istore 21
L1382:  iload 14
L1384:  iload 15
L1386:  iload 16
L1388:  iload 11
L1390:  iload 12
L1392:  iload 13
L1394:  aload_0
L1395:  getfield Field ZKARKDQW G [I
L1398:  iload_1
L1399:  iaload
L1400:  aload_0
L1401:  getfield Field ZKARKDQW G [I
L1404:  iload_1
L1405:  iaload
L1406:  aload_0
L1407:  getfield Field ZKARKDQW G [I
L1410:  iload_1
L1411:  iaload
L1412:  getstatic Field ZKARKDQW ob [I
L1415:  iload 19
L1417:  iaload
L1418:  getstatic Field ZKARKDQW ob [I
L1421:  iload 20
L1423:  iaload
L1424:  getstatic Field ZKARKDQW ob [I
L1427:  iload 21
L1429:  iaload
L1430:  getstatic Field ZKARKDQW pb [I
L1433:  iload 19
L1435:  iaload
L1436:  getstatic Field ZKARKDQW pb [I
L1439:  iload 20
L1441:  iaload
L1442:  getstatic Field ZKARKDQW pb [I
L1445:  iload 21
L1447:  iaload
L1448:  getstatic Field ZKARKDQW qb [I
L1451:  iload 19
L1453:  iaload
L1454:  getstatic Field ZKARKDQW qb [I
L1457:  iload 20
L1459:  iaload
L1460:  getstatic Field ZKARKDQW qb [I
L1463:  iload 21
L1465:  iaload
L1466:  aload_0
L1467:  getfield Field ZKARKDQW M [I
L1470:  iload_1
L1471:  iaload
L1472:  invokestatic Method OPPOFIOL a (IIIIIIIIIIIIIIIIIII)V
L1475:  iload 4
L1477:  iconst_4
L1478:  if_icmpne L2164
L1481:  iload 11
L1483:  iflt L1539
L1486:  iload 12
L1488:  iflt L1539
L1491:  iload 13
L1493:  iflt L1539
L1496:  iload 11
L1498:  getstatic Field AFCKELYG t I
L1501:  if_icmpgt L1539
L1504:  iload 12
L1506:  getstatic Field AFCKELYG t I
L1509:  if_icmpgt L1539
L1512:  iload 13
L1514:  getstatic Field AFCKELYG t I
L1517:  if_icmpgt L1539
L1520:  getstatic Field ZKARKDQW yb [I
L1523:  iconst_3
L1524:  iaload
L1525:  iflt L1539
L1528:  getstatic Field ZKARKDQW yb [I
L1531:  iconst_3
L1532:  iaload
L1533:  getstatic Field AFCKELYG t I
L1536:  if_icmple L1543
L1539:  iconst_1
L1540:  putstatic Field OPPOFIOL B Z
L1543:  aload_0
L1544:  getfield Field ZKARKDQW J [I
L1547:  ifnonnull L1558
L1550:  iconst_0
L1551:  istore 17
L1553:  iload 22
L1555:  ifeq L1568
L1558:  aload_0
L1559:  getfield Field ZKARKDQW J [I
L1562:  iload_1
L1563:  iaload
L1564:  iconst_3
L1565:  iand
L1566:  istore 17
L1568:  iload 17
L1570:  ifne L1640
L1573:  iload 14
L1575:  iload 15
L1577:  iload 16
L1579:  iload 11
L1581:  iload 12
L1583:  iload 13
L1585:  getstatic Field ZKARKDQW Ab [I
L1588:  iconst_0
L1589:  iaload
L1590:  getstatic Field ZKARKDQW Ab [I
L1593:  iconst_1
L1594:  iaload
L1595:  getstatic Field ZKARKDQW Ab [I
L1598:  iconst_2
L1599:  iaload
L1600:  invokestatic Method OPPOFIOL a (IIIIIIIII)V
L1603:  iload 14
L1605:  iload 16
L1607:  getstatic Field ZKARKDQW zb [I
L1610:  iconst_3
L1611:  iaload
L1612:  iload 11
L1614:  iload 13
L1616:  getstatic Field ZKARKDQW yb [I
L1619:  iconst_3
L1620:  iaload
L1621:  getstatic Field ZKARKDQW Ab [I
L1624:  iconst_0
L1625:  iaload
L1626:  getstatic Field ZKARKDQW Ab [I
L1629:  iconst_2
L1630:  iaload
L1631:  getstatic Field ZKARKDQW Ab [I
L1634:  iconst_3
L1635:  iaload
L1636:  invokestatic Method OPPOFIOL a (IIIIIIIII)V
L1639:  return
L1640:  iload 17
L1642:  iconst_1
L1643:  if_icmpne L1699
L1646:  getstatic Field ZKARKDQW Lb [I
L1649:  aload_0
L1650:  getfield Field ZKARKDQW G [I
L1653:  iload_1
L1654:  iaload
L1655:  iaload
L1656:  istore 18
L1658:  iload 14
L1660:  iload 15
L1662:  iload 16
L1664:  iload 11
L1666:  iload 12
L1668:  iload 13
L1670:  iload 18
L1672:  invokestatic Method OPPOFIOL c (IIIIIII)V
L1675:  iload 14
L1677:  iload 16
L1679:  getstatic Field ZKARKDQW zb [I
L1682:  iconst_3
L1683:  iaload
L1684:  iload 11
L1686:  iload 13
L1688:  getstatic Field ZKARKDQW yb [I
L1691:  iconst_3
L1692:  iaload
L1693:  iload 18
L1695:  invokestatic Method OPPOFIOL c (IIIIIII)V
L1698:  return
L1699:  iload 17
L1701:  iconst_2
L1702:  if_icmpne L1929
L1705:  aload_0
L1706:  getfield Field ZKARKDQW J [I
L1709:  iload_1
L1710:  iaload
L1711:  iconst_2
L1712:  ishr
L1713:  istore 18
L1715:  aload_0
L1716:  getfield Field ZKARKDQW P [I
L1719:  iload 18
L1721:  iaload
L1722:  istore 19
L1724:  aload_0
L1725:  getfield Field ZKARKDQW Q [I
L1728:  iload 18
L1730:  iaload
L1731:  istore 20
L1733:  aload_0
L1734:  getfield Field ZKARKDQW R [I
L1737:  iload 18
L1739:  iaload
L1740:  istore 21
L1742:  iload 14
L1744:  iload 15
L1746:  iload 16
L1748:  iload 11
L1750:  iload 12
L1752:  iload 13
L1754:  getstatic Field ZKARKDQW Ab [I
L1757:  iconst_0
L1758:  iaload
L1759:  getstatic Field ZKARKDQW Ab [I
L1762:  iconst_1
L1763:  iaload
L1764:  getstatic Field ZKARKDQW Ab [I
L1767:  iconst_2
L1768:  iaload
L1769:  getstatic Field ZKARKDQW ob [I
L1772:  iload 19
L1774:  iaload
L1775:  getstatic Field ZKARKDQW ob [I
L1778:  iload 20
L1780:  iaload
L1781:  getstatic Field ZKARKDQW ob [I
L1784:  iload 21
L1786:  iaload
L1787:  getstatic Field ZKARKDQW pb [I
L1790:  iload 19
L1792:  iaload
L1793:  getstatic Field ZKARKDQW pb [I
L1796:  iload 20
L1798:  iaload
L1799:  getstatic Field ZKARKDQW pb [I
L1802:  iload 21
L1804:  iaload
L1805:  getstatic Field ZKARKDQW qb [I
L1808:  iload 19
L1810:  iaload
L1811:  getstatic Field ZKARKDQW qb [I
L1814:  iload 20
L1816:  iaload
L1817:  getstatic Field ZKARKDQW qb [I
L1820:  iload 21
L1822:  iaload
L1823:  aload_0
L1824:  getfield Field ZKARKDQW M [I
L1827:  iload_1
L1828:  iaload
L1829:  invokestatic Method OPPOFIOL a (IIIIIIIIIIIIIIIIIII)V
L1832:  iload 14
L1834:  iload 16
L1836:  getstatic Field ZKARKDQW zb [I
L1839:  iconst_3
L1840:  iaload
L1841:  iload 11
L1843:  iload 13
L1845:  getstatic Field ZKARKDQW yb [I
L1848:  iconst_3
L1849:  iaload
L1850:  getstatic Field ZKARKDQW Ab [I
L1853:  iconst_0
L1854:  iaload
L1855:  getstatic Field ZKARKDQW Ab [I
L1858:  iconst_2
L1859:  iaload
L1860:  getstatic Field ZKARKDQW Ab [I
L1863:  iconst_3
L1864:  iaload
L1865:  getstatic Field ZKARKDQW ob [I
L1868:  iload 19
L1870:  iaload
L1871:  getstatic Field ZKARKDQW ob [I
L1874:  iload 20
L1876:  iaload
L1877:  getstatic Field ZKARKDQW ob [I
L1880:  iload 21
L1882:  iaload
L1883:  getstatic Field ZKARKDQW pb [I
L1886:  iload 19
L1888:  iaload
L1889:  getstatic Field ZKARKDQW pb [I
L1892:  iload 20
L1894:  iaload
L1895:  getstatic Field ZKARKDQW pb [I
L1898:  iload 21
L1900:  iaload
L1901:  getstatic Field ZKARKDQW qb [I
L1904:  iload 19
L1906:  iaload
L1907:  getstatic Field ZKARKDQW qb [I
L1910:  iload 20
L1912:  iaload
L1913:  getstatic Field ZKARKDQW qb [I
L1916:  iload 21
L1918:  iaload
L1919:  aload_0
L1920:  getfield Field ZKARKDQW M [I
L1923:  iload_1
L1924:  iaload
L1925:  invokestatic Method OPPOFIOL a (IIIIIIIIIIIIIIIIIII)V
L1928:  return
L1929:  iload 17
L1931:  iconst_3
L1932:  if_icmpne L2164
L1935:  aload_0
L1936:  getfield Field ZKARKDQW J [I
L1939:  iload_1
L1940:  iaload
L1941:  iconst_2
L1942:  ishr
L1943:  istore 18
L1945:  aload_0
L1946:  getfield Field ZKARKDQW P [I
L1949:  iload 18
L1951:  iaload
L1952:  istore 19
L1954:  aload_0
L1955:  getfield Field ZKARKDQW Q [I
L1958:  iload 18
L1960:  iaload
L1961:  istore 20
L1963:  aload_0
L1964:  getfield Field ZKARKDQW R [I
L1967:  iload 18
L1969:  iaload
L1970:  istore 21
L1972:  iload 14
L1974:  iload 15
L1976:  iload 16
L1978:  iload 11
L1980:  iload 12
L1982:  iload 13
L1984:  aload_0
L1985:  getfield Field ZKARKDQW G [I
L1988:  iload_1
L1989:  iaload
L1990:  aload_0
L1991:  getfield Field ZKARKDQW G [I
L1994:  iload_1
L1995:  iaload
L1996:  aload_0
L1997:  getfield Field ZKARKDQW G [I
L2000:  iload_1
L2001:  iaload
L2002:  getstatic Field ZKARKDQW ob [I
L2005:  iload 19
L2007:  iaload
L2008:  getstatic Field ZKARKDQW ob [I
L2011:  iload 20
L2013:  iaload
L2014:  getstatic Field ZKARKDQW ob [I
L2017:  iload 21
L2019:  iaload
L2020:  getstatic Field ZKARKDQW pb [I
L2023:  iload 19
L2025:  iaload
L2026:  getstatic Field ZKARKDQW pb [I
L2029:  iload 20
L2031:  iaload
L2032:  getstatic Field ZKARKDQW pb [I
L2035:  iload 21
L2037:  iaload
L2038:  getstatic Field ZKARKDQW qb [I
L2041:  iload 19
L2043:  iaload
L2044:  getstatic Field ZKARKDQW qb [I
L2047:  iload 20
L2049:  iaload
L2050:  getstatic Field ZKARKDQW qb [I
L2053:  iload 21
L2055:  iaload
L2056:  aload_0
L2057:  getfield Field ZKARKDQW M [I
L2060:  iload_1
L2061:  iaload
L2062:  invokestatic Method OPPOFIOL a (IIIIIIIIIIIIIIIIIII)V
L2065:  iload 14
L2067:  iload 16
L2069:  getstatic Field ZKARKDQW zb [I
L2072:  iconst_3
L2073:  iaload
L2074:  iload 11
L2076:  iload 13
L2078:  getstatic Field ZKARKDQW yb [I
L2081:  iconst_3
L2082:  iaload
L2083:  aload_0
L2084:  getfield Field ZKARKDQW G [I
L2087:  iload_1
L2088:  iaload
L2089:  aload_0
L2090:  getfield Field ZKARKDQW G [I
L2093:  iload_1
L2094:  iaload
L2095:  aload_0
L2096:  getfield Field ZKARKDQW G [I
L2099:  iload_1
L2100:  iaload
L2101:  getstatic Field ZKARKDQW ob [I
L2104:  iload 19
L2106:  iaload
L2107:  getstatic Field ZKARKDQW ob [I
L2110:  iload 20
L2112:  iaload
L2113:  getstatic Field ZKARKDQW ob [I
L2116:  iload 21
L2118:  iaload
L2119:  getstatic Field ZKARKDQW pb [I
L2122:  iload 19
L2124:  iaload
L2125:  getstatic Field ZKARKDQW pb [I
L2128:  iload 20
L2130:  iaload
L2131:  getstatic Field ZKARKDQW pb [I
L2134:  iload 21
L2136:  iaload
L2137:  getstatic Field ZKARKDQW qb [I
L2140:  iload 19
L2142:  iaload
L2143:  getstatic Field ZKARKDQW qb [I
L2146:  iload 20
L2148:  iaload
L2149:  getstatic Field ZKARKDQW qb [I
L2152:  iload 21
L2154:  iaload
L2155:  aload_0
L2156:  getfield Field ZKARKDQW M [I
L2159:  iload_1
L2160:  iaload
L2161:  invokestatic Method OPPOFIOL a (IIIIIIIIIIIIIIIIIII)V
L2164:  return
L2165:  
    .end code
.end method

.method private final a : (IIIIIIII)Z
    .code stack 2 locals 9
L0:     iload_2
L1:     iload_3
L2:     if_icmpge L19
L5:     iload_2
L6:     iload 4
L8:     if_icmpge L19
L11:    iload_2
L12:    iload 5
L14:    if_icmpge L19
L17:    iconst_0
L18:    ireturn
L19:    iload_2
L20:    iload_3
L21:    if_icmple L38
L24:    iload_2
L25:    iload 4
L27:    if_icmple L38
L30:    iload_2
L31:    iload 5
L33:    if_icmple L38
L36:    iconst_0
L37:    ireturn
L38:    iload_1
L39:    iload 6
L41:    if_icmpge L58
L44:    iload_1
L45:    iload 7
L47:    if_icmpge L58
L50:    iload_1
L51:    iload 8
L53:    if_icmpge L58
L56:    iconst_0
L57:    ireturn
L58:    iload_1
L59:    iload 6
L61:    if_icmple L78
L64:    iload_1
L65:    iload 7
L67:    if_icmple L78
L70:    iload_1
L71:    iload 8
L73:    if_icmple L78
L76:    iconst_0
L77:    ireturn
L78:    iconst_1
L79:    ireturn
L80:    
    .end code
.end method

.method static <clinit> : ()V
    .code stack 3 locals 0
L0:     sipush -192
L3:     putstatic Field ZKARKDQW r I
L6:     new ZKARKDQW
L9:     dup
L10:    iconst_1
L11:    invokespecial Method ZKARKDQW <init> (Z)V
L14:    putstatic Field ZKARKDQW t LZKARKDQW;
L17:    sipush 2000
L20:    newarray int
L22:    putstatic Field ZKARKDQW u [I
L25:    sipush 2000
L28:    newarray int
L30:    putstatic Field ZKARKDQW v [I
L33:    sipush 2000
L36:    newarray int
L38:    putstatic Field ZKARKDQW w [I
L41:    sipush 2000
L44:    newarray int
L46:    putstatic Field ZKARKDQW x [I
L49:    sipush 4096
L52:    newarray boolean
L54:    putstatic Field ZKARKDQW jb [Z
L57:    sipush 4096
L60:    newarray boolean
L62:    putstatic Field ZKARKDQW kb [Z
L65:    sipush 4096
L68:    newarray int
L70:    putstatic Field ZKARKDQW lb [I
L73:    sipush 4096
L76:    newarray int
L78:    putstatic Field ZKARKDQW mb [I
L81:    sipush 4096
L84:    newarray int
L86:    putstatic Field ZKARKDQW nb [I
L89:    sipush 4096
L92:    newarray int
L94:    putstatic Field ZKARKDQW ob [I
L97:    sipush 4096
L100:   newarray int
L102:   putstatic Field ZKARKDQW pb [I
L105:   sipush 4096
L108:   newarray int
L110:   putstatic Field ZKARKDQW qb [I
L113:   sipush 1500
L116:   newarray int
L118:   putstatic Field ZKARKDQW rb [I
L121:   sipush 1500
L124:   sipush 512
L127:   multianewarray [[I 2
L131:   putstatic Field ZKARKDQW sb [[I
L134:   bipush 12
L136:   newarray int
L138:   putstatic Field ZKARKDQW tb [I
L141:   bipush 12
L143:   sipush 2000
L146:   multianewarray [[I 2
L150:   putstatic Field ZKARKDQW ub [[I
L153:   sipush 2000
L156:   newarray int
L158:   putstatic Field ZKARKDQW vb [I
L161:   sipush 2000
L164:   newarray int
L166:   putstatic Field ZKARKDQW wb [I
L169:   bipush 12
L171:   newarray int
L173:   putstatic Field ZKARKDQW xb [I
L176:   bipush 10
L178:   newarray int
L180:   putstatic Field ZKARKDQW yb [I
L183:   bipush 10
L185:   newarray int
L187:   putstatic Field ZKARKDQW zb [I
L190:   bipush 10
L192:   newarray int
L194:   putstatic Field ZKARKDQW Ab [I
L197:   sipush 1000
L200:   newarray int
L202:   putstatic Field ZKARKDQW Ib [I
L205:   getstatic Field OPPOFIOL J [I
L208:   putstatic Field ZKARKDQW Jb [I
L211:   getstatic Field OPPOFIOL K [I
L214:   putstatic Field ZKARKDQW Kb [I
L217:   getstatic Field OPPOFIOL V [I
L220:   putstatic Field ZKARKDQW Lb [I
L223:   getstatic Field OPPOFIOL I [I
L226:   putstatic Field ZKARKDQW Mb [I
L229:   return
L230:   
    .end code
.end method
.end class
